Workbook

Sheet Credit Card Charge
A1: Reference number | B1: CC account | C1: Line: Amount | D1: Name | E1: Type | F1: Line: Account | G1: Credit | H1: Currency | I1: Location | J1: Exchange Rate | K1: Global tax calculation | L1: Update Credit Card Charge | M1: Line: Billable status | N1: Line: Class | O1: Line: Customer | P1: Line: Tax code | Q1: Line: Description | R1: Line: Tax amount | S1: Line: Markup percent | T1: Item: Product | U1: Item: Quantity | V1: Item: Unit price | W1: Payment method | X1: Memo | Y1: Txn date | Z1: Txn source | AA1: Total tax | AB1: Transaction Location Type | AC1: Attachment: File Link | AD1: Attachment: Id | AE1: Attachment: Attach to email
B2: ='QBO Transactions'!$U4 | C2: ='QBO Transactions'!$S4 | D2: ='QBO Transactions'!$R4 | F2: ='QBO Transactions'!$X4 | N2: ='QBO Transactions'!$Y4 | Q2: ='QBO Transactions'!$T4 | X2: =Q2 | Y2: ='QBO Transactions'!$Q4
B3: ='QBO Transactions'!$U5 | C3: ='QBO Transactions'!$S5 | D3: ='QBO Transactions'!$R5 | F3: ='QBO Transactions'!$X5 | N3: ='QBO Transactions'!$Y5 | Q3: ='QBO Transactions'!$T5 | X3: =Q3 | Y3: ='QBO Transactions'!$Q5
B4: ='QBO Transactions'!$U6 | C4: ='QBO Transactions'!$S6 | D4: ='QBO Transactions'!$R6 | F4: ='QBO Transactions'!$X6 | N4: ='QBO Transactions'!$Y6 | Q4: ='QBO Transactions'!$T6 | X4: =Q4 | Y4: ='QBO Transactions'!$Q6
B5: ='QBO Transactions'!$U7 | C5: ='QBO Transactions'!$S7 | D5: ='QBO Transactions'!$R7 | F5: ='QBO Transactions'!$X7 | N5: ='QBO Transactions'!$Y7 | Q5: ='QBO Transactions'!$T7 | X5: =Q5 | Y5: ='QBO Transactions'!$Q7
B6: ='QBO Transactions'!$U8 | C6: ='QBO Transactions'!$S8 | D6: ='QBO Transactions'!$R8 | F6: ='QBO Transactions'!$X8 | N6: ='QBO Transactions'!$Y8 | Q6: ='QBO Transactions'!$T8 | X6: =Q6 | Y6: ='QBO Transactions'!$Q8
B7: ='QBO Transactions'!$U9 | C7: ='QBO Transactions'!$S9 | D7: ='QBO Transactions'!$R9 | F7: ='QBO Transactions'!$X9 | N7: ='QBO Transactions'!$Y9 | Q7: ='QBO Transactions'!$T9 | X7: =Q7 | Y7: ='QBO Transactions'!$Q9
B8: ='QBO Transactions'!$U10 | C8: ='QBO Transactions'!$S10 | D8: ='QBO Transactions'!$R10 | F8: ='QBO Transactions'!$X10 | N8: ='QBO Transactions'!$Y10 | Q8: ='QBO Transactions'!$T10 | X8: =Q8 | Y8: ='QBO Transactions'!$Q10
B9: ='QBO Transactions'!$U11 | C9: ='QBO Transactions'!$S11 | D9: ='QBO Transactions'!$R11 | F9: ='QBO Transactions'!$X11 | N9: ='QBO Transactions'!$Y11 | Q9: ='QBO Transactions'!$T11 | X9: =Q9 | Y9: ='QBO Transactions'!$Q11
B10: ='QBO Transactions'!$U12 | C10: ='QBO Transactions'!$S12 | D10: ='QBO Transactions'!$R12 | F10: ='QBO Transactions'!$X12 | N10: ='QBO Transactions'!$Y12 | Q10: ='QBO Transactions'!$T12 | X10: =Q10 | Y10: ='QBO Transactions'!$Q12
B11: ='QBO Transactions'!$U13 | C11: ='QBO Transactions'!$S13 | D11: ='QBO Transactions'!$R13 | F11: ='QBO Transactions'!$X13 | N11: ='QBO Transactions'!$Y13 | Q11: ='QBO Transactions'!$T13 | X11: =Q11 | Y11: ='QBO Transactions'!$Q13
B12: ='QBO Transactions'!$U14 | C12: ='QBO Transactions'!$S14 | D12: ='QBO Transactions'!$R14 | F12: ='QBO Transactions'!$X14 | N12: ='QBO Transactions'!$Y14 | Q12: ='QBO Transactions'!$T14 | X12: =Q12 | Y12: ='QBO Transactions'!$Q14
B13: ='QBO Transactions'!$U15 | C13: ='QBO Transactions'!$S15 | D13: ='QBO Transactions'!$R15 | F13: ='QBO Transactions'!$X15 | N13: ='QBO Transactions'!$Y15 | Q13: ='QBO Transactions'!$T15 | X13: =Q13 | Y13: ='QBO Transactions'!$Q15
... B657: ='QBO Transactions'!$U659 | C657: ='QBO Transactions'!$S659 | D657: ='QBO Transactions'!$R659 | F657: ='QBO Transactions'!$X659 | N657: ='QBO Transactions'!$Y659 | Q657: ='QBO Transactions'!$T659 | X657: =Q657 | Y657: ='QBO Transactions'!$Q659

Sheet QBO Transactions
C1: Credit Card Account: | D1: Brex Credit Card | I1: Travel Vendor | K1: Taxi Vendor
B2: QBO Credit Card Transaction Data | I2: Food Vendor | K2: Office Vendor
B3: DATE | C3: DESCRIPTION | D3: Payee | E3: Category or Match | F3: SPENT | G3: RECEIVED | H3: xxx | I3: Payee Override | J3: Full Acct Override | K3: Parent Category Override | L3: Sub Category Override | M3: Dept Override | N3: Card # | O3: Card Name | P3: EE ID | Q3: Date | R3: Vendor | S3: Amount | T3: Updated Description | U3: Card Acct | V3: Parent Category | W3: Sub Category | X3: Line Acct | Y3: Department | Z3: Acct Check
B4: 46164 | C4: QANTASXXXXXXXX41055 MASTERCARD-544015XXXXXX7759-Mickenzi Krpec | E4: 61210 Sales & Marketing:Sales & Marketing- Travel Expenses:Airfare | F4: 8368.3 | I4: Travel Vendor | L4: Airfare | O4: =IF(C4="", "", TRIM(RIGHT(C4, LEN(C4) - FIND("@@", SUBSTITUTE(C4, "-", "@@", LEN(C4) - LEN(SUBSTITUTE(C4, "-", ""))))))) | P4: {=IFERROR(XLOOKUP(O4,'Department Listing'!$O$1:$O$395,'Department Listing'!$A$1:$A$395),IFERROR(XLOOKUP(O4,'Name Aliases'!$A$2:$A$1000,'Name Aliases'!$B$2:$B$1000),""))} | Q4: =IF(ISBLANK($C4),"",$B4) | R4: =IF(ISBLANK($C4),"",IF(ISBLANK($I4),$D4,$I4)) | S4: =IF(ISBLANK($C4),"",$F4 - $G4) | T4: =IF(ISBLANK($C4),"",C4) | U4: =IF(ISBLANK($C4),"",$D$1) | V4: {=IF(ISBLANK($B4),"",IF(ISBLANK($K4),IF(XLOOKUP($W4,'Category Mapping'!$C:$C,'Category Mapping'!$B:$B)="Travel",XLOOKUP($P4,'Department Listing'!$A:$A,'Department Listing'!$M:$M),XLOOKUP($W4,'Category Mapping'!$C:$C,'Category Mapping'!$D:$D)),$K4))} | W4: =IF(ISBLANK($B4),"",IF(ISBLANK($L4),RIGHT($E4,LEN($E4) - FIND("^",SUBSTITUTE($E4,":","^",LEN($E4) - LEN(SUBSTITUTE($E4,":",""))))),$L4)) | X4: =IF(ISBLANK($J4),$V4&$W4,$J4) | Y4: {=IF(ISBLANK($M4),IFERROR(XLOOKUP($P4,'Department Listing'!$A:$A,'Department Listing'!$L:$L),""),$M4)} | Z4: =IF(ISBLANK($B4),"",MATCH($X4,COA!$B:$B,0))
B5: 46170 | C5: Monument Charlestown Restaurant & Tavern MASTERCARD-544015XXXXXX7759-Mickenzi Krpec | E5: 61290 Sales & Marketing:Sales & Marketing- Travel Expenses:Other Travel Expenses | F5: 2764.88 | I5: Food Vendor | L5: Meals & Entertainment | O5: =IF(C5="", "", TRIM(RIGHT(C5, LEN(C5) - FIND("@@", SUBSTITUTE(C5, "-", "@@", LEN(C5) - LEN(SUBSTITUTE(C5, "-", ""))))))) | P5: {=IFERROR(XLOOKUP(O5,'Department Listing'!$O$1:$O$395,'Department Listing'!$A$1:$A$395),IFERROR(XLOOKUP(O5,'Name Aliases'!$A$2:$A$1000,'Name Aliases'!$B$2:$B$1000),""))} | Q5: =IF(ISBLANK($C5),"",$B5) | R5: =IF(ISBLANK($C5),"",IF(ISBLANK($I5),$D5,$I5)) | S5: =IF(ISBLANK($C5),"",$F5 - $G5) | T5: =IF(ISBLANK($C5),"",C5) | U5: =IF(ISBLANK($C5),"",$D$1) | V5: {=IF(ISBLANK($B5),"",IF(ISBLANK($K5),IF(XLOOKUP($W5,'Category Mapping'!$C:$C,'Category Mapping'!$B:$B)="Travel",XLOOKUP($P5,'Department Listing'!$A:$A,'Department Listing'!$M:$M),XLOOKUP($W5,'Category Mapping'!$C:$C,'Category Mapping'!$D:$D)),$K5))} | W5: =IF(ISBLANK($B5),"",IF(ISBLANK($L5),RIGHT($E5,LEN($E5) - FIND("^",SUBSTITUTE($E5,":","^",LEN($E5) - LEN(SUBSTITUTE($E5,":",""))))),$L5)) | X5: =IF(ISBLANK($J5),$V5&$W5,$J5) | Y5: {=IF(ISBLANK($M5),IFERROR(XLOOKUP($P5,'Department Listing'!$A:$A,'Department Listing'!$L:$L),""),$M5)} | Z5: =IF(ISBLANK($B5),"",MATCH($X5,COA!$B:$B,0))
B6: 46169 | C6: Bar Primi Penn District MASTERCARD-555671XXXXXX5731-Nikita Ashok | E6: 61240 Sales & Marketing:Sales & Marketing- Travel Expenses:Meals & Entertainment | F6: 2366.4 | I6: Food Vendor | O6: =IF(C6="", "", TRIM(RIGHT(C6, LEN(C6) - FIND("@@", SUBSTITUTE(C6, "-", "@@", LEN(C6) - LEN(SUBSTITUTE(C6, "-", ""))))))) | P6: {=IFERROR(XLOOKUP(O6,'Department Listing'!$O$1:$O$395,'Department Listing'!$A$1:$A$395),IFERROR(XLOOKUP(O6,'Name Aliases'!$A$2:$A$1000,'Name Aliases'!$B$2:$B$1000),""))} | Q6: =IF(ISBLANK($C6),"",$B6) | R6: =IF(ISBLANK($C6),"",IF(ISBLANK($I6),$D6,$I6)) | S6: =IF(ISBLANK($C6),"",$F6 - $G6) | T6: =IF(ISBLANK($C6),"",C6) | U6: =IF(ISBLANK($C6),"",$D$1) | V6: {=IF(ISBLANK($B6),"",IF(ISBLANK($K6),IF(XLOOKUP($W6,'Category Mapping'!$C:$C,'Category Mapping'!$B:$B)="Travel",XLOOKUP($P6,'Department Listing'!$A:$A,'Department Listing'!$M:$M),XLOOKUP($W6,'Category Mapping'!$C:$C,'Category Mapping'!$D:$D)),$K6))} | W6: =IF(ISBLANK($B6),"",IF(ISBLANK($L6),RIGHT($E6,LEN($E6) - FIND("^",SUBSTITUTE($E6,":","^",LEN($E6) - LEN(SUBSTITUTE($E6,":",""))))),$L6)) | X6: =IF(ISBLANK($J6),$V6&$W6,$J6) | Y6: {=IF(ISBLANK($M6),IFERROR(XLOOKUP($P6,'Department Listing'!$A:$A,'Department Listing'!$L:$L),""),$M6)} | Z6: =IF(ISBLANK($B6),"",MATCH($X6,COA!$B:$B,0))
B7: 46168 | C7: Bamboo HR MASTERCARD-544015XXXXXX0151-Eric Rabkin | D7: Bamboo HR | E7: 63310 General & Administrative:Software Licenses | F7: 1783.48 | O7: =IF(C7="", "", TRIM(RIGHT(C7, LEN(C7) - FIND("@@", SUBSTITUTE(C7, "-", "@@", LEN(C7) - LEN(SUBSTITUTE(C7, "-", ""))))))) | P7: {=IFERROR(XLOOKUP(O7,'Department Listing'!$O$1:$O$395,'Department Listing'!$A$1:$A$395),IFERROR(XLOOKUP(O7,'Name Aliases'!$A$2:$A$1000,'Name Aliases'!$B$2:$B$1000),""))} | Q7: =IF(ISBLANK($C7),"",$B7) | R7: =IF(ISBLANK($C7),"",IF(ISBLANK($I7),$D7,$I7)) | S7: =IF(ISBLANK($C7),"",$F7 - $G7) | T7: =IF(ISBLANK($C7),"",C7) | U7: =IF(ISBLANK($C7),"",$D$1) | V7: {=IF(ISBLANK($B7),"",IF(ISBLANK($K7),IF(XLOOKUP($W7,'Category Mapping'!$C:$C,'Category Mapping'!$B:$B)="Travel",XLOOKUP($P7,'Department Listing'!$A:$A,'Department Listing'!$M:$M),XLOOKUP($W7,'Category Mapping'!$C:$C,'Category Mapping'!$D:$D)),$K7))} | W7: =IF(ISBLANK($B7),"",IF(ISBLANK($L7),RIGHT($E7,LEN($E7) - FIND("^",SUBSTITUTE($E7,":","^",LEN($E7) - LEN(SUBSTITUTE($E7,":",""))))),$L7)) | X7: =IF(ISBLANK($J7),$V7&$W7,$J7) | Y7: {=IF(ISBLANK($M7),IFERROR(XLOOKUP($P7,'Department Listing'!$A:$A,'Department Listing'!$L:$L),""),$M7)} | Z7: =IF(ISBLANK($B7),"",MATCH($X7,COA!$B:$B,0))
B8: 46165 | C8: Back Bay Garage MASTERCARD-544015XXXXXX4926-Alta Abel | D8: Back Bay Garage | E8: 61220 Sales & Marketing:Sales & Marketing- Travel Expenses:Ground Transportation | F8: 1685 | O8: =IF(C8="", "", TRIM(RIGHT(C8, LEN(C8) - FIND("@@", SUBSTITUTE(C8, "-", "@@", LEN(C8) - LEN(SUBSTITUTE(C8, "-", ""))))))) | P8: {=IFERROR(XLOOKUP(O8,'Department Listing'!$O$1:$O$395,'Department Listing'!$A$1:$A$395),IFERROR(XLOOKUP(O8,'Name Aliases'!$A$2:$A$1000,'Name Aliases'!$B$2:$B$1000),""))} | Q8: =IF(ISBLANK($C8),"",$B8) | R8: =IF(ISBLANK($C8),"",IF(ISBLANK($I8),$D8,$I8)) | S8: =IF(ISBLANK($C8),"",$F8 - $G8) | T8: =IF(ISBLANK($C8),"",C8) | U8: =IF(ISBLANK($C8),"",$D$1) | V8: {=IF(ISBLANK($B8),"",IF(ISBLANK($K8),IF(XLOOKUP($W8,'Category Mapping'!$C:$C,'Category Mapping'!$B:$B)="Travel",XLOOKUP($P8,'Department Listing'!$A:$A,'Department Listing'!$M:$M),XLOOKUP($W8,'Category Mapping'!$C:$C,'Category Mapping'!$D:$D)),$K8))} | W8: =IF(ISBLANK($B8),"",IF(ISBLANK($L8),RIGHT($E8,LEN($E8) - FIND("^",SUBSTITUTE($E8,":","^",LEN($E8) - LEN(SUBSTITUTE($E8,":",""))))),$L8)) | X8: =IF(ISBLANK($J8),$V8&$W8,$J8) | Y8: {=IF(ISBLANK($M8),IFERROR(XLOOKUP($P8,'Department Listing'!$A:$A,'Department Listing'!$L:$L),""),$M8)} | Z8: =IF(ISBLANK($B8),"",MATCH($X8,COA!$B:$B,0))
B9: 46168 | C9: CustomCookies.com MASTERCARD-544015XXXXXX8091-Brooke Berg | E9: 63410 General & Administrative:Office Expenses:Office Supplies | F9: 1355 | I9: Customcookies.com | O9: =IF(C9="", "", TRIM(RIGHT(C9, LEN(C9) - FIND("@@", SUBSTITUTE(C9, "-", "@@", LEN(C9) - LEN(SUBSTITUTE(C9, "-", ""))))))) | P9: {=IFERROR(XLOOKUP(O9,'Department Listing'!$O$1:$O$395,'Department Listing'!$A$1:$A$395),IFERROR(XLOOKUP(O9,'Name Aliases'!$A$2:$A$1000,'Name Aliases'!$B$2:$B$1000),""))} | Q9: =IF(ISBLANK($C9),"",$B9) | R9: =IF(ISBLANK($C9),"",IF(ISBLANK($I9),$D9,$I9)) | S9: =IF(ISBLANK($C9),"",$F9 - $G9) | T9: =IF(ISBLANK($C9),"",C9) | U9: =IF(ISBLANK($C9),"",$D$1) | V9: {=IF(ISBLANK($B9),"",IF(ISBLANK($K9),IF(XLOOKUP($W9,'Category Mapping'!$C:$C,'Category Mapping'!$B:$B)="Travel",XLOOKUP($P9,'Department Listing'!$A:$A,'Department Listing'!$M:$M),XLOOKUP($W9,'Category Mapping'!$C:$C,'Category Mapping'!$D:$D)),$K9))} | W9: =IF(ISBLANK($B9),"",IF(ISBLANK($L9),RIGHT($E9,LEN($E9) - FIND("^",SUBSTITUTE($E9,":","^",LEN($E9) - LEN(SUBSTITUTE($E9,":",""))))),$L9)) | X9: =IF(ISBLANK($J9),$V9&$W9,$J9) | Y9: {=IF(ISBLANK($M9),IFERROR(XLOOKUP($P9,'Department Listing'!$A:$A,'Department Listing'!$L:$L),""),$M9)} | Z9: =IF(ISBLANK($B9),"",MATCH($X9,COA!$B:$B,0))
B10: 46165 | C10: Claude MASTERCARD-544015XXXXXX0151-Eric Rabkin | D10: Claude.AI | E10: 63310 General & Administrative:Software Licenses | F10: 1038.46 | O10: =IF(C10="", "", TRIM(RIGHT(C10, LEN(C10) - FIND("@@", SUBSTITUTE(C10, "-", "@@", LEN(C10) - LEN(SUBSTITUTE(C10, "-", ""))))))) | P10: {=IFERROR(XLOOKUP(O10,'Department Listing'!$O$1:$O$395,'Department Listing'!$A$1:$A$395),IFERROR(XLOOKUP(O10,'Name Aliases'!$A$2:$A$1000,'Name Aliases'!$B$2:$B$1000),""))} | Q10: =IF(ISBLANK($C10),"",$B10) | R10: =IF(ISBLANK($C10),"",IF(ISBLANK($I10),$D10,$I10)) | S10: =IF(ISBLANK($C10),"",$F10 - $G10) | T10: =IF(ISBLANK($C10),"",C10) | U10: =IF(ISBLANK($C10),"",$D$1) | V10: {=IF(ISBLANK($B10),"",IF(ISBLANK($K10),IF(XLOOKUP($W10,'Category Mapping'!$C:$C,'Category Mapping'!$B:$B)="Travel",XLOOKUP($P10,'Department Listing'!$A:$A,'Department Listing'!$M:$M),XLOOKUP($W10,'Category Mapping'!$C:$C,'Category Mapping'!$D:$D)),$K10))} | W10: =IF(ISBLANK($B10),"",IF(ISBLANK($L10),RIGHT($E10,LEN($E10) - FIND("^",SUBSTITUTE($E10,":","^",LEN($E10) - LEN(SUBSTITUTE($E10,":",""))))),$L10)) | X10: =IF(ISBLANK($J10),$V10&$W10,$J10) | Y10: {=IF(ISBLANK($M10),IFERROR(XLOOKUP($P10,'Department Listing'!$A:$A,'Department Listing'!$L:$L),""),$M10)} | Z10: =IF(ISBLANK($B10),"",MATCH($X10,COA!$B:$B,0))
B11: 46166 | C11: Claude MASTERCARD-544015XXXXXX0151-Eric Rabkin | D11: Claude.AI | E11: 63310 General & Administrative:Software Licenses | F11: 1037.63 | O11: =IF(C11="", "", TRIM(RIGHT(C11, LEN(C11) - FIND("@@", SUBSTITUTE(C11, "-", "@@", LEN(C11) - LEN(SUBSTITUTE(C11, "-", ""))))))) | P11: {=IFERROR(XLOOKUP(O11,'Department Listing'!$O$1:$O$395,'Department Listing'!$A$1:$A$395),IFERROR(XLOOKUP(O11,'Name Aliases'!$A$2:$A$1000,'Name Aliases'!$B$2:$B$1000),""))} | Q11: =IF(ISBLANK($C11),"",$B11) | R11: =IF(ISBLANK($C11),"",IF(ISBLANK($I11),$D11,$I11)) | S11: =IF(ISBLANK($C11),"",$F11 - $G11) | T11: =IF(ISBLANK($C11),"",C11) | U11: =IF(ISBLANK($C11),"",$D$1) | V11: {=IF(ISBLANK($B11),"",IF(ISBLANK($K11),IF(XLOOKUP($W11,'Category Mapping'!$C:$C,'Category Mapping'!$B:$B)="Travel",XLOOKUP($P11,'Department Listing'!$A:$A,'Department Listing'!$M:$M),XLOOKUP($W11,'Category Mapping'!$C:$C,'Category Mapping'!$D:$D)),$K11))} | W11: =IF(ISBLANK($B11),"",IF(ISBLANK($L11),RIGHT($E11,LEN($E11) - FIND("^",SUBSTITUTE($E11,":","^",LEN($E11) - LEN(SUBSTITUTE($E11,":",""))))),$L11)) | X11: =IF(ISBLANK($J11),$V11&$W11,$J11) | Y11: {=IF(ISBLANK($M11),IFERROR(XLOOKUP($P11,'Department Listing'!$A:$A,'Department Listing'!$L:$L),""),$M11)} | Z11: =IF(ISBLANK($B11),"",MATCH($X11,COA!$B:$B,0))
B12: 46165 | C12: Claude MASTERCARD-544015XXXXXX0151-Eric Rabkin | D12: Claude.AI | E12: 63310 General & Administrative:Software Licenses | F12: 1036.29 | O12: =IF(C12="", "", TRIM(RIGHT(C12, LEN(C12) - FIND("@@", SUBSTITUTE(C12, "-", "@@", LEN(C12) - LEN(SUBSTITUTE(C12, "-", ""))))))) | P12: {=IFERROR(XLOOKUP(O12,'Department Listing'!$O$1:$O$395,'Department Listing'!$A$1:$A$395),IFERROR(XLOOKUP(O12,'Name Aliases'!$A$2:$A$1000,'Name Aliases'!$B$2:$B$1000),""))} | Q12: =IF(ISBLANK($C12),"",$B12) | R12: =IF(ISBLANK($C12),"",IF(ISBLANK($I12),$D12,$I12)) | S12: =IF(ISBLANK($C12),"",$F12 - $G12) | T12: =IF(ISBLANK($C12),"",C12) | U12: =IF(ISBLANK($C12),"",$D$1) | V12: {=IF(ISBLANK($B12),"",IF(ISBLANK($K12),IF(XLOOKUP($W12,'Category Mapping'!$C:$C,'Category Mapping'!$B:$B)="Travel",XLOOKUP($P12,'Department Listing'!$A:$A,'Department Listing'!$M:$M),XLOOKUP($W12,'Category Mapping'!$C:$C,'Category Mapping'!$D:$D)),$K12))} | W12: =IF(ISBLANK($B12),"",IF(ISBLANK($L12),RIGHT($E12,LEN($E12) - FIND("^",SUBSTITUTE($E12,":","^",LEN($E12) - LEN(SUBSTITUTE($E12,":",""))))),$L12)) | X12: =IF(ISBLANK($J12),$V12&$W12,$J12) | Y12: {=IF(ISBLANK($M12),IFERROR(XLOOKUP($P12,'Department Listing'!$A:$A,'Department Listing'!$L:$L),""),$M12)} | Z12: =IF(ISBLANK($B12),"",MATCH($X12,COA!$B:$B,0))
B13: 46166 | C13: Claude MASTERCARD-544015XXXXXX0151-Eric Rabkin | D13: Claude.AI | E13: 63310 General & Administrative:Software Licenses | F13: 1036.22 | O13: =IF(C13="", "", TRIM(RIGHT(C13, LEN(C13) - FIND("@@", SUBSTITUTE(C13, "-", "@@", LEN(C13) - LEN(SUBSTITUTE(C13, "-", ""))))))) | P13: {=IFERROR(XLOOKUP(O13,'Department Listing'!$O$1:$O$395,'Department Listing'!$A$1:$A$395),IFERROR(XLOOKUP(O13,'Name Aliases'!$A$2:$A$1000,'Name Aliases'!$B$2:$B$1000),""))} | Q13: =IF(ISBLANK($C13),"",$B13) | R13: =IF(ISBLANK($C13),"",IF(ISBLANK($I13),$D13,$I13)) | S13: =IF(ISBLANK($C13),"",$F13 - $G13) | T13: =IF(ISBLANK($C13),"",C13) | U13: =IF(ISBLANK($C13),"",$D$1) | V13: {=IF(ISBLANK($B13),"",IF(ISBLANK($K13),IF(XLOOKUP($W13,'Category Mapping'!$C:$C,'Category Mapping'!$B:$B)="Travel",XLOOKUP($P13,'Department Listing'!$A:$A,'Department Listing'!$M:$M),XLOOKUP($W13,'Category Mapping'!$C:$C,'Category Mapping'!$D:$D)),$K13))} | W13: =IF(ISBLANK($B13),"",IF(ISBLANK($L13),RIGHT($E13,LEN($E13) - FIND("^",SUBSTITUTE($E13,":","^",LEN($E13) - LEN(SUBSTITUTE($E13,":",""))))),$L13)) | X13: =IF(ISBLANK($J13),$V13&$W13,$J13) | Y13: {=IF(ISBLANK($M13),IFERROR(XLOOKUP($P13,'Department Listing'!$A:$A,'Department Listing'!$L:$L),""),$M13)} | Z13: =IF(ISBLANK($B13),"",MATCH($X13,COA!$B:$B,0))
B14: 46165 | C14: Claude MASTERCARD-544015XXXXXX0151-Eric Rabkin | D14: Claude.AI | E14: 63310 General & Administrative:Software Licenses | F14: 1029.53 | O14: =IF(C14="", "", TRIM(RIGHT(C14, LEN(C14) - FIND("@@", SUBSTITUTE(C14, "-", "@@", LEN(C14) - LEN(SUBSTITUTE(C14, "-", ""))))))) | P14: {=IFERROR(XLOOKUP(O14,'Department Listing'!$O$1:$O$395,'Department Listing'!$A$1:$A$395),IFERROR(XLOOKUP(O14,'Name Aliases'!$A$2:$A$1000,'Name Aliases'!$B$2:$B$1000),""))} | Q14: =IF(ISBLANK($C14),"",$B14) | R14: =IF(ISBLANK($C14),"",IF(ISBLANK($I14),$D14,$I14)) | S14: =IF(ISBLANK($C14),"",$F14 - $G14) | T14: =IF(ISBLANK($C14),"",C14) | U14: =IF(ISBLANK($C14),"",$D$1) | V14: {=IF(ISBLANK($B14),"",IF(ISBLANK($K14),IF(XLOOKUP($W14,'Category Mapping'!$C:$C,'Category Mapping'!$B:$B)="Travel",XLOOKUP($P14,'Department Listing'!$A:$A,'Department Listing'!$M:$M),XLOOKUP($W14,'Category Mapping'!$C:$C,'Category Mapping'!$D:$D)),$K14))} | W14: =IF(ISBLANK($B14),"",IF(ISBLANK($L14),RIGHT($E14,LEN($E14) - FIND("^",SUBSTITUTE($E14,":","^",LEN($E14) - LEN(SUBSTITUTE($E14,":",""))))),$L14)) | X14: =IF(ISBLANK($J14),$V14&$W14,$J14) | Y14: {=IF(ISBLANK($M14),IFERROR(XLOOKUP($P14,'Department Listing'!$A:$A,'Department Listing'!$L:$L),""),$M14)} | Z14: =IF(ISBLANK($B14),"",MATCH($X14,COA!$B:$B,0))
B15: 46169 | C15: Csi Worldwide MASTERCARD-555671XXXXXX8308-Toni Manning | E15: 61290 Sales & Marketing:Sales & Marketing- Travel Expenses:Other Travel Expenses | F15: 1029.42 | I15: Office Vendor | L15: Dues & Subscriptions | O15: =IF(C15="", "", TRIM(RIGHT(C15, LEN(C15) - FIND("@@", SUBSTITUTE(C15, "-", "@@", LEN(C15) - LEN(SUBSTITUTE(C15, "-", ""))))))) | P15: {=IFERROR(XLOOKUP(O15,'Department Listing'!$O$1:$O$395,'Department Listing'!$A$1:$A$395),IFERROR(XLOOKUP(O15,'Name Aliases'!$A$2:$A$1000,'Name Aliases'!$B$2:$B$1000),""))} | Q15: =IF(ISBLANK($C15),"",$B15) | R15: =IF(ISBLANK($C15),"",IF(ISBLANK($I15),$D15,$I15)) | S15: =IF(ISBLANK($C15),"",$F15 - $G15) | T15: =IF(ISBLANK($C15),"",C15) | U15: =IF(ISBLANK($C15),"",$D$1) | V15: {=IF(ISBLANK($B15),"",IF(ISBLANK($K15),IF(XLOOKUP($W15,'Category Mapping'!$C:$C,'Category Mapping'!$B:$B)="Travel",XLOOKUP($P15,'Department Listing'!$A:$A,'Department Listing'!$M:$M),XLOOKUP($W15,'Category Mapping'!$C:$C,'Category Mapping'!$D:$D)),$K15))} | W15: =IF(ISBLANK($B15),"",IF(ISBLANK($L15),RIGHT($E15,LEN($E15) - FIND("^",SUBSTITUTE($E15,":","^",LEN($E15) - LEN(SUBSTITUTE($E15,":",""))))),$L15)) | X15: =IF(ISBLANK($J15),$V15&$W15,$J15) | Y15: {=IF(ISBLANK($M15),IFERROR(XLOOKUP($P15,'Department Listing'!$A:$A,'Department Listing'!$L:$L),""),$M15)} | Z15: =IF(ISBLANK($B15),"",MATCH($X15,COA!$B:$B,0))
B16: 46166 | C16: Claude MASTERCARD-544015XXXXXX0151-Eric Rabkin | D16: Claude.AI | E16: 63310 General & Administrative:Software Licenses | F16: 1029.01 | O16: =IF(C16="", "", TRIM(RIGHT(C16, LEN(C16) - FIND("@@", SUBSTITUTE(C16, "-", "@@", LEN(C16) - LEN(SUBSTITUTE(C16, "-", ""))))))) | P16: {=IFERROR(XLOOKUP(O16,'Department Listing'!$O$1:$O$395,'Department Listing'!$A$1:$A$395),IFERROR(XLOOKUP(O16,'Name Aliases'!$A$2:$A$1000,'Name Aliases'!$B$2:$B$1000),""))} | Q16: =IF(ISBLANK($C16),"",$B16) | R16: =IF(ISBLANK($C16),"",IF(ISBLANK($I16),$D16,$I16)) | S16: =IF(ISBLANK($C16),"",$F16 - $G16) | T16: =IF(ISBLANK($C16),"",C16) | U16: =IF(ISBLANK($C16),"",$D$1) | V16: {=IF(ISBLANK($B16),"",IF(ISBLANK($K16),IF(XLOOKUP($W16,'Category Mapping'!$C:$C,'Category Mapping'!$B:$B)="Travel",XLOOKUP($P16,'Department Listing'!$A:$A,'Department Listing'!$M:$M),XLOOKUP($W16,'Category Mapping'!$C:$C,'Category Mapping'!$D:$D)),$K16))} | W16: =IF(ISBLANK($B16),"",IF(ISBLANK($L16),RIGHT($E16,LEN($E16) - FIND("^",SUBSTITUTE($E16,":","^",LEN($E16) - LEN(SUBSTITUTE($E16,":",""))))),$L16)) | X16: =IF(ISBLANK($J16),$V16&$W16,$J16) | Y16: {=IF(ISBLANK($M16),IFERROR(XLOOKUP($P16,'Department Listing'!$A:$A,'Department Listing'!$L:$L),""),$M16)} | Z16: =IF(ISBLANK($B16),"",MATCH($X16,COA!$B:$B,0))
B17: 46165 | C17: Claude MASTERCARD-544015XXXXXX0151-Eric Rabkin | D17: Claude.AI | E17: 63310 General & Administrative:Software Licenses | F17: 1024.09 | O17: =IF(C17="", "", TRIM(RIGHT(C17, LEN(C17) - FIND("@@", SUBSTITUTE(C17, "-", "@@", LEN(C17) - LEN(SUBSTITUTE(C17, "-", ""))))))) | P17: {=IFERROR(XLOOKUP(O17,'Department Listing'!$O$1:$O$395,'Department Listing'!$A$1:$A$395),IFERROR(XLOOKUP(O17,'Name Aliases'!$A$2:$A$1000,'Name Aliases'!$B$2:$B$1000),""))} | Q17: =IF(ISBLANK($C17),"",$B17) | R17: =IF(ISBLANK($C17),"",IF(ISBLANK($I17),$D17,$I17)) | S17: =IF(ISBLANK($C17),"",$F17 - $G17) | T17: =IF(ISBLANK($C17),"",C17) | U17: =IF(ISBLANK($C17),"",$D$1) | V17: {=IF(ISBLANK($B17),"",IF(ISBLANK($K17),IF(XLOOKUP($W17,'Category Mapping'!$C:$C,'Category Mapping'!$B:$B)="Travel",XLOOKUP($P17,'Department Listing'!$A:$A,'Department Listing'!$M:$M),XLOOKUP($W17,'Category Mapping'!$C:$C,'Category Mapping'!$D:$D)),$K17))} | W17: =IF(ISBLANK($B17),"",IF(ISBLANK($L17),RIGHT($E17,LEN($E17) - FIND("^",SUBSTITUTE($E17,":","^",LEN($E17) - LEN(SUBSTITUTE($E17,":",""))))),$L17)) | X17: =IF(ISBLANK($J17),$V17&$W17,$J17) | Y17: {=IF(ISBLANK($M17),IFERROR(XLOOKUP($P17,'Department Listing'!$A:$A,'Department Listing'!$L:$L),""),$M17)} | Z17: =IF(ISBLANK($B17),"",MATCH($X17,COA!$B:$B,0))
B18: 46166 | C18: Claude MASTERCARD-544015XXXXXX0151-Eric Rabkin | D18: Claude.AI | E18: 63310 General & Administrative:Software Licenses | F18: 1023.44 | O18: =IF(C18="", "", TRIM(RIGHT(C18, LEN(C18) - FIND("@@", SUBSTITUTE(C18, "-", "@@", LEN(C18) - LEN(SUBSTITUTE(C18, "-", ""))))))) | P18: {=IFERROR(XLOOKUP(O18,'Department Listing'!$O$1:$O$395,'Department Listing'!$A$1:$A$395),IFERROR(XLOOKUP(O18,'Name Aliases'!$A$2:$A$1000,'Name Aliases'!$B$2:$B$1000),""))} | Q18: =IF(ISBLANK($C18),"",$B18) | R18: =IF(ISBLANK($C18),"",IF(ISBLANK($I18),$D18,$I18)) | S18: =IF(ISBLANK($C18),"",$F18 - $G18) | T18: =IF(ISBLANK($C18),"",C18) | U18: =IF(ISBLANK($C18),"",$D$1) | V18: {=IF(ISBLANK($B18),"",IF(ISBLANK($K18),IF(XLOOKUP($W18,'Category Mapping'!$C:$C,'Category Mapping'!$B:$B)="Travel",XLOOKUP($P18,'Department Listing'!$A:$A,'Department Listing'!$M:$M),XLOOKUP($W18,'Category Mapping'!$C:$C,'Category Mapping'!$D:$D)),$K18))} | W18: =IF(ISBLANK($B18),"",IF(ISBLANK($L18),RIGHT($E18,LEN($E18) - FIND("^",SUBSTITUTE($E18,":","^",LEN($E18) - LEN(SUBSTITUTE($E18,":",""))))),$L18)) | X18: =IF(ISBLANK($J18),$V18&$W18,$J18) | Y18: {=IF(ISBLANK($M18),IFERROR(XLOOKUP($P18,'Department Listing'!$A:$A,'Department Listing'!$L:$L),""),$M18)} | Z18: =IF(ISBLANK($B18),"",MATCH($X18,COA!$B:$B,0))
B19: 46166 | C19: Claude MASTERCARD-544015XXXXXX0151-Eric Rabkin | D19: Claude.AI | E19: 63310 General & Administrative:Software Licenses | F19: 1022.16 | O19: =IF(C19="", "", TRIM(RIGHT(C19, LEN(C19) - FIND("@@", SUBSTITUTE(C19, "-", "@@", LEN(C19) - LEN(SUBSTITUTE(C19, "-", ""))))))) | P19: {=IFERROR(XLOOKUP(O19,'Department Listing'!$O$1:$O$395,'Department Listing'!$A$1:$A$395),IFERROR(XLOOKUP(O19,'Name Aliases'!$A$2:$A$1000,'Name Aliases'!$B$2:$B$1000),""))} | Q19: =IF(ISBLANK($C19),"",$B19) | R19: =IF(ISBLANK($C19),"",IF(ISBLANK($I19),$D19,$I19)) | S19: =IF(ISBLANK($C19),"",$F19 - $G19) | T19: =IF(ISBLANK($C19),"",C19) | U19: =IF(ISBLANK($C19),"",$D$1) | V19: {=IF(ISBLANK($B19),"",IF(ISBLANK($K19),IF(XLOOKUP($W19,'Category Mapping'!$C:$C,'Category Mapping'!$B:$B)="Travel",XLOOKUP($P19,'Department Listing'!$A:$A,'Department Listing'!$M:$M),XLOOKUP($W19,'Category Mapping'!$C:$C,'Category Mapping'!$D:$D)),$K19))} | W19: =IF(ISBLANK($B19),"",IF(ISBLANK($L19),RIGHT($E19,LEN($E19) - FIND("^",SUBSTITUTE($E19,":","^",LEN($E19) - LEN(SUBSTITUTE($E19,":",""))))),$L19)) | X19: =IF(ISBLANK($J19),$V19&$W19,$J19) | Y19: {=IF(ISBLANK($M19),IFERROR(XLOOKUP($P19,'Department Listing'!$A:$A,'Department Listing'!$L:$L),""),$M19)} | Z19: =IF(ISBLANK($B19),"",MATCH($X19,COA!$B:$B,0))
B20: 46166 | C20: Claude MASTERCARD-544015XXXXXX0151-Eric Rabkin | D20: Claude.AI | E20: 63310 General & Administrative:Software Licenses | F20: 1020.56 | O20: =IF(C20="", "", TRIM(RIGHT(C20, LEN(C20) - FIND("@@", SUBSTITUTE(C20, "-", "@@", LEN(C20) - LEN(SUBSTITUTE(C20, "-", ""))))))) | P20: {=IFERROR(XLOOKUP(O20,'Department Listing'!$O$1:$O$395,'Department Listing'!$A$1:$A$395),IFERROR(XLOOKUP(O20,'Name Aliases'!$A$2:$A$1000,'Name Aliases'!$B$2:$B$1000),""))} | Q20: =IF(ISBLANK($C20),"",$B20) | R20: =IF(ISBLANK($C20),"",IF(ISBLANK($I20),$D20,$I20)) | S20: =IF(ISBLANK($C20),"",$F20 - $G20) | T20: =IF(ISBLANK($C20),"",C20) | U20: =IF(ISBLANK($C20),"",$D$1) | V20: {=IF(ISBLANK($B20),"",IF(ISBLANK($K20),IF(XLOOKUP($W20,'Category Mapping'!$C:$C,'Category Mapping'!$B:$B)="Travel",XLOOKUP($P20,'Department Listing'!$A:$A,'Department Listing'!$M:$M),XLOOKUP($W20,'Category Mapping'!$C:$C,'Category Mapping'!$D:$D)),$K20))} | W20: =IF(ISBLANK($B20),"",IF(ISBLANK($L20),RIGHT($E20,LEN($E20) - FIND("^",SUBSTITUTE($E20,":","^",LEN($E20) - LEN(SUBSTITUTE($E20,":",""))))),$L20)) | X20: =IF(ISBLANK($J20),$V20&$W20,$J20) | Y20: {=IF(ISBLANK($M20),IFERROR(XLOOKUP($P20,'Department Listing'!$A:$A,'Department Listing'!$L:$L),""),$M20)} | Z20: =IF(ISBLANK($B20),"",MATCH($X20,COA!$B:$B,0))
B21: 46165 | C21: Claude MASTERCARD-544015XXXXXX0151-Eric Rabkin | D21: Claude.AI | E21: 63310 General & Administrative:Software Licenses | F21: 1019.16 | O21: =IF(C21="", "", TRIM(RIGHT(C21, LEN(C21) - FIND("@@", SUBSTITUTE(C21, "-", "@@", LEN(C21) - LEN(SUBSTITUTE(C21, "-", ""))))))) | P21: {=IFERROR(XLOOKUP(O21,'Department Listing'!$O$1:$O$395,'Department Listing'!$A$1:$A$395),IFERROR(XLOOKUP(O21,'Name Aliases'!$A$2:$A$1000,'Name Aliases'!$B$2:$B$1000),""))} | Q21: =IF(ISBLANK($C21),"",$B21) | R21: =IF(ISBLANK($C21),"",IF(ISBLANK($I21),$D21,$I21)) | S21: =IF(ISBLANK($C21),"",$F21 - $G21) | T21: =IF(ISBLANK($C21),"",C21) | U21: =IF(ISBLANK($C21),"",$D$1) | V21: {=IF(ISBLANK($B21),"",IF(ISBLANK($K21),IF(XLOOKUP($W21,'Category Mapping'!$C:$C,'Category Mapping'!$B:$B)="Travel",XLOOKUP($P21,'Department Listing'!$A:$A,'Department Listing'!$M:$M),XLOOKUP($W21,'Category Mapping'!$C:$C,'Category Mapping'!$D:$D)),$K21))} | W21: =IF(ISBLANK($B21),"",IF(ISBLANK($L21),RIGHT($E21,LEN($E21) - FIND("^",SUBSTITUTE($E21,":","^",LEN($E21) - LEN(SUBSTITUTE($E21,":",""))))),$L21)) | X21: =IF(ISBLANK($J21),$V21&$W21,$J21) | Y21: {=IF(ISBLANK($M21),IFERROR(XLOOKUP($P21,'Department Listing'!$A:$A,'Department Listing'!$L:$L),""),$M21)} | Z21: =IF(ISBLANK($B21),"",MATCH($X21,COA!$B:$B,0))
B22: 46165 | C22: Claude MASTERCARD-544015XXXXXX0151-Eric Rabkin | D22: Claude.AI | E22: 63310 General & Administrative:Software Licenses | F22: 1018.67 | O22: =IF(C22="", "", TRIM(RIGHT(C22, LEN(C22) - FIND("@@", SUBSTITUTE(C22, "-", "@@", LEN(C22) - LEN(SUBSTITUTE(C22, "-", ""))))))) | P22: {=IFERROR(XLOOKUP(O22,'Department Listing'!$O$1:$O$395,'Department Listing'!$A$1:$A$395),IFERROR(XLOOKUP(O22,'Name Aliases'!$A$2:$A$1000,'Name Aliases'!$B$2:$B$1000),""))} | Q22: =IF(ISBLANK($C22),"",$B22) | R22: =IF(ISBLANK($C22),"",IF(ISBLANK($I22),$D22,$I22)) | S22: =IF(ISBLANK($C22),"",$F22 - $G22) | T22: =IF(ISBLANK($C22),"",C22) | U22: =IF(ISBLANK($C22),"",$D$1) | V22: {=IF(ISBLANK($B22),"",IF(ISBLANK($K22),IF(XLOOKUP($W22,'Category Mapping'!$C:$C,'Category Mapping'!$B:$B)="Travel",XLOOKUP($P22,'Department Listing'!$A:$A,'Department Listing'!$M:$M),XLOOKUP($W22,'Category Mapping'!$C:$C,'Category Mapping'!$D:$D)),$K22))} | W22: =IF(ISBLANK($B22),"",IF(ISBLANK($L22),RIGHT($E22,LEN($E22) - FIND("^",SUBSTITUTE($E22,":","^",LEN($E22) - LEN(SUBSTITUTE($E22,":",""))))),$L22)) | X22: =IF(ISBLANK($J22),$V22&$W22,$J22) | Y22: {=IF(ISBLANK($M22),IFERROR(XLOOKUP($P22,'Department Listing'!$A:$A,'Department Listing'!$L:$L),""),$M22)} | Z22: =IF(ISBLANK($B22),"",MATCH($X22,COA!$B:$B,0))
B23: 46165 | C23: Claude MASTERCARD-544015XXXXXX0151-Eric Rabkin | D23: Claude.AI | E23: 63310 General & Administrative:Software Licenses | F23: 1018.34 | O23: =IF(C23="", "", TRIM(RIGHT(C23, LEN(C23) - FIND("@@", SUBSTITUTE(C23, "-", "@@", LEN(C23) - LEN(SUBSTITUTE(C23, "-", ""))))))) | P23: {=IFERROR(XLOOKUP(O23,'Department Listing'!$O$1:$O$395,'Department Listing'!$A$1:$A$395),IFERROR(XLOOKUP(O23,'Name Aliases'!$A$2:$A$1000,'Name Aliases'!$B$2:$B$1000),""))} | Q23: =IF(ISBLANK($C23),"",$B23) | R23: =IF(ISBLANK($C23),"",IF(ISBLANK($I23),$D23,$I23)) | S23: =IF(ISBLANK($C23),"",$F23 - $G23) | T23: =IF(ISBLANK($C23),"",C23) | U23: =IF(ISBLANK($C23),"",$D$1) | V23: {=IF(ISBLANK($B23),"",IF(ISBLANK($K23),IF(XLOOKUP($W23,'Category Mapping'!$C:$C,'Category Mapping'!$B:$B)="Travel",XLOOKUP($P23,'Department Listing'!$A:$A,'Department Listing'!$M:$M),XLOOKUP($W23,'Category Mapping'!$C:$C,'Category Mapping'!$D:$D)),$K23))} | W23: =IF(ISBLANK($B23),"",IF(ISBLANK($L23),RIGHT($E23,LEN($E23) - FIND("^",SUBSTITUTE($E23,":","^",LEN($E23) - LEN(SUBSTITUTE($E23,":",""))))),$L23)) | X23: =IF(ISBLANK($J23),$V23&$W23,$J23) | Y23: {=IF(ISBLANK($M23),IFERROR(XLOOKUP($P23,'Department Listing'!$A:$A,'Department Listing'!$L:$L),""),$M23)} | Z23: =IF(ISBLANK($B23),"",MATCH($X23,COA!$B:$B,0))
B24: 46166 | C24: Claude MASTERCARD-544015XXXXXX0151-Eric Rabkin | D24: Claude.AI | E24: 63310 General & Administrative:Software Licenses | F24: 1017.01 | O24: =IF(C24="", "", TRIM(RIGHT(C24, LEN(C24) - FIND("@@", SUBSTITUTE(C24, "-", "@@", LEN(C24) - LEN(SUBSTITUTE(C24, "-", ""))))))) | P24: {=IFERROR(XLOOKUP(O24,'Department Listing'!$O$1:$O$395,'Department Listing'!$A$1:$A$395),IFERROR(XLOOKUP(O24,'Name Aliases'!$A$2:$A$1000,'Name Aliases'!$B$2:$B$1000),""))} | Q24: =IF(ISBLANK($C24),"",$B24) | R24: =IF(ISBLANK($C24),"",IF(ISBLANK($I24),$D24,$I24)) | S24: =IF(ISBLANK($C24),"",$F24 - $G24) | T24: =IF(ISBLANK($C24),"",C24) | U24: =IF(ISBLANK($C24),"",$D$1) | V24: {=IF(ISBLANK($B24),"",IF(ISBLANK($K24),IF(XLOOKUP($W24,'Category Mapping'!$C:$C,'Category Mapping'!$B:$B)="Travel",XLOOKUP($P24,'Department Listing'!$A:$A,'Department Listing'!$M:$M),XLOOKUP($W24,'Category Mapping'!$C:$C,'Category Mapping'!$D:$D)),$K24))} | W24: =IF(ISBLANK($B24),"",IF(ISBLANK($L24),RIGHT($E24,LEN($E24) - FIND("^",SUBSTITUTE($E24,":","^",LEN($E24) - LEN(SUBSTITUTE($E24,":",""))))),$L24)) | X24: =IF(ISBLANK($J24),$V24&$W24,$J24) | Y24: {=IF(ISBLANK($M24),IFERROR(XLOOKUP($P24,'Department Listing'!$A:$A,'Department Listing'!$L:$L),""),$M24)} | Z24: =IF(ISBLANK($B24),"",MATCH($X24,COA!$B:$B,0))
B25: 46169 | C25: Claude MASTERCARD-544015XXXXXX0151-Eric Rabkin | D25: Claude.AI | E25: 63310 General & Administrative:Software Licenses | F25: 1015.91 | O25: =IF(C25="", "", TRIM(RIGHT(C25, LEN(C25) - FIND("@@", SUBSTITUTE(C25, "-", "@@", LEN(C25) - LEN(SUBSTITUTE(C25, "-", ""))))))) | P25: {=IFERROR(XLOOKUP(O25,'Department Listing'!$O$1:$O$395,'Department Listing'!$A$1:$A$395),IFERROR(XLOOKUP(O25,'Name Aliases'!$A$2:$A$1000,'Name Aliases'!$B$2:$B$1000),""))} | Q25: =IF(ISBLANK($C25),"",$B25) | R25: =IF(ISBLANK($C25),"",IF(ISBLANK($I25),$D25,$I25)) | S25: =IF(ISBLANK($C25),"",$F25 - $G25) | T25: =IF(ISBLANK($C25),"",C25) | U25: =IF(ISBLANK($C25),"",$D$1) | V25: {=IF(ISBLANK($B25),"",IF(ISBLANK($K25),IF(XLOOKUP($W25,'Category Mapping'!$C:$C,'Category Mapping'!$B:$B)="Travel",XLOOKUP($P25,'Department Listing'!$A:$A,'Department Listing'!$M:$M),XLOOKUP($W25,'Category Mapping'!$C:$C,'Category Mapping'!$D:$D)),$K25))} | W25: =IF(ISBLANK($B25),"",IF(ISBLANK($L25),RIGHT($E25,LEN($E25) - FIND("^",SUBSTITUTE($E25,":","^",LEN($E25) - LEN(SUBSTITUTE($E25,":",""))))),$L25)) | X25: =IF(ISBLANK($J25),$V25&$W25,$J25) | Y25: {=IF(ISBLANK($M25),IFERROR(XLOOKUP($P25,'Department Listing'!$A:$A,'Department Listing'!$L:$L),""),$M25)} | Z25: =IF(ISBLANK($B25),"",MATCH($X25,COA!$B:$B,0))
B26: 46166 | C26: Claude MASTERCARD-544015XXXXXX0151-Eric Rabkin | D26: Claude.AI | E26: 63310 General & Administrative:Software Licenses | F26: 1015.56 | O26: =IF(C26="", "", TRIM(RIGHT(C26, LEN(C26) - FIND("@@", SUBSTITUTE(C26, "-", "@@", LEN(C26) - LEN(SUBSTITUTE(C26, "-", ""))))))) | P26: {=IFERROR(XLOOKUP(O26,'Department Listing'!$O$1:$O$395,'Department Listing'!$A$1:$A$395),IFERROR(XLOOKUP(O26,'Name Aliases'!$A$2:$A$1000,'Name Aliases'!$B$2:$B$1000),""))} | Q26: =IF(ISBLANK($C26),"",$B26) | R26: =IF(ISBLANK($C26),"",IF(ISBLANK($I26),$D26,$I26)) | S26: =IF(ISBLANK($C26),"",$F26 - $G26) | T26: =IF(ISBLANK($C26),"",C26) | U26: =IF(ISBLANK($C26),"",$D$1) | V26: {=IF(ISBLANK($B26),"",IF(ISBLANK($K26),IF(XLOOKUP($W26,'Category Mapping'!$C:$C,'Category Mapping'!$B:$B)="Travel",XLOOKUP($P26,'Department Listing'!$A:$A,'Department Listing'!$M:$M),XLOOKUP($W26,'Category Mapping'!$C:$C,'Category Mapping'!$D:$D)),$K26))} | W26: =IF(ISBLANK($B26),"",IF(ISBLANK($L26),RIGHT($E26,LEN($E26) - FIND("^",SUBSTITUTE($E26,":","^",LEN($E26) - LEN(SUBSTITUTE($E26,":",""))))),$L26)) | X26: =IF(ISBLANK($J26),$V26&$W26,$J26) | Y26: {=IF(ISBLANK($M26),IFERROR(XLOOKUP($P26,'Department Listing'!$A:$A,'Department Listing'!$L:$L),""),$M26)} | Z26: =IF(ISBLANK($B26),"",MATCH($X26,COA!$B:$B,0))
B27: 46164 | C27: Claude MASTERCARD-544015XXXXXX0151-Eric Rabkin | D27: Claude.AI | E27: 63310 General & Administrative:Software Licenses | F27: 1015.12 | O27: =IF(C27="", "", TRIM(RIGHT(C27, LEN(C27) - FIND("@@", SUBSTITUTE(C27, "-", "@@", LEN(C27) - LEN(SUBSTITUTE(C27, "-", ""))))))) | P27: {=IFERROR(XLOOKUP(O27,'Department Listing'!$O$1:$O$395,'Department Listing'!$A$1:$A$395),IFERROR(XLOOKUP(O27,'Name Aliases'!$A$2:$A$1000,'Name Aliases'!$B$2:$B$1000),""))} | Q27: =IF(ISBLANK($C27),"",$B27) | R27: =IF(ISBLANK($C27),"",IF(ISBLANK($I27),$D27,$I27)) | S27: =IF(ISBLANK($C27),"",$F27 - $G27) | T27: =IF(ISBLANK($C27),"",C27) | U27: =IF(ISBLANK($C27),"",$D$1) | V27: {=IF(ISBLANK($B27),"",IF(ISBLANK($K27),IF(XLOOKUP($W27,'Category Mapping'!$C:$C,'Category Mapping'!$B:$B)="Travel",XLOOKUP($P27,'Department Listing'!$A:$A,'Department Listing'!$M:$M),XLOOKUP($W27,'Category Mapping'!$C:$C,'Category Mapping'!$D:$D)),$K27))} | W27: =IF(ISBLANK($B27),"",IF(ISBLANK($L27),RIGHT($E27,LEN($E27) - FIND("^",SUBSTITUTE($E27,":","^",LEN($E27) - LEN(SUBSTITUTE($E27,":",""))))),$L27)) | X27: =IF(ISBLANK($J27),$V27&$W27,$J27) | Y27: {=IF(ISBLANK($M27),IFERROR(XLOOKUP($P27,'Department Listing'!$A:$A,'Department Listing'!$L:$L),""),$M27)} | Z27: =IF(ISBLANK($B27),"",MATCH($X27,COA!$B:$B,0))
... B39: 46170 | C39: Claude MASTERCARD-544015XXXXXX0151-Eric Rabkin | D39: Claude.AI | E39: 63310 General & Administrative:Software Licenses | F39: 1009.49 | O39: =IF(C39="", "", TRIM(RIGHT(C39, LEN(C39) - FIND("@@", SUBSTITUTE(C39, "-", "@@", LEN(C39) - LEN(SUBSTITUTE(C39, "-", ""))))))) | P39: {=IFERROR(XLOOKUP(O39,'Department Listing'!$O$1:$O$395,'Department Listing'!$A$1:$A$395),IFERROR(XLOOKUP(O39,'Name Aliases'!$A$2:$A$1000,'Name Aliases'!$B$2:$B$1000),""))} | Q39: =IF(ISBLANK($C39),"",$B39) | R39: =IF(ISBLANK($C39),"",IF(ISBLANK($I39),$D39,$I39)) | S39: =IF(ISBLANK($C39),"",$F39 - $G39) | T39: =IF(ISBLANK($C39),"",C39) | U39: =IF(ISBLANK($C39),"",$D$1) | V39: {=IF(ISBLANK($B39),"",IF(ISBLANK($K39),IF(XLOOKUP($W39,'Category Mapping'!$C:$C,'Category Mapping'!$B:$B)="Travel",XLOOKUP($P39,'Department Listing'!$A:$A,'Department Listing'!$M:$M),XLOOKUP($W39,'Category Mapping'!$C:$C,'Category Mapping'!$D:$D)),$K39))} | W39: =IF(ISBLANK($B39),"",IF(ISBLANK($L39),RIGHT($E39,LEN($E39) - FIND("^",SUBSTITUTE($E39,":","^",LEN($E39) - LEN(SUBSTITUTE($E39,":",""))))),$L39)) | X39: =IF(ISBLANK($J39),$V39&$W39,$J39) | Y39: {=IF(ISBLANK($M39),IFERROR(XLOOKUP($P39,'Department Listing'!$A:$A,'Department Listing'!$L:$L),""),$M39)} | Z39: =IF(ISBLANK($B39),"",MATCH($X39,COA!$B:$B,0))
B40: 46165 | C40: MakeStickers.com MASTERCARD-544015XXXXXX8091-Brooke Berg | E40: 63410 General & Administrative:Office Expenses:Office Supplies | F40: 958.31 | I40: Makestickers.com | O40: =IF(C40="", "", TRIM(RIGHT(C40, LEN(C40) - FIND("@@", SUBSTITUTE(C40, "-", "@@", LEN(C40) - LEN(SUBSTITUTE(C40, "-", ""))))))) | P40: {=IFERROR(XLOOKUP(O40,'Department Listing'!$O$1:$O$395,'Department Listing'!$A$1:$A$395),IFERROR(XLOOKUP(O40,'Name Aliases'!$A$2:$A$1000,'Name Aliases'!$B$2:$B$1000),""))} | Q40: =IF(ISBLANK($C40),"",$B40) | R40: =IF(ISBLANK($C40),"",IF(ISBLANK($I40),$D40,$I40)) | S40: =IF(ISBLANK($C40),"",$F40 - $G40) | T40: =IF(ISBLANK($C40),"",C40) | U40: =IF(ISBLANK($C40),"",$D$1) | V40: {=IF(ISBLANK($B40),"",IF(ISBLANK($K40),IF(XLOOKUP($W40,'Category Mapping'!$C:$C,'Category Mapping'!$B:$B)="Travel",XLOOKUP($P40,'Department Listing'!$A:$A,'Department Listing'!$M:$M),XLOOKUP($W40,'Category Mapping'!$C:$C,'Category Mapping'!$D:$D)),$K40))} | W40: =IF(ISBLANK($B40),"",IF(ISBLANK($L40),RIGHT($E40,LEN($E40) - FIND("^",SUBSTITUTE($E40,":","^",LEN($E40) - LEN(SUBSTITUTE($E40,":",""))))),$L40)) | X40: =IF(ISBLANK($J40),$V40&$W40,$J40) | Y40: {=IF(ISBLANK($M40),IFERROR(XLOOKUP($P40,'Department Listing'!$A:$A,'Department Listing'!$L:$L),""),$M40)} | Z40: =IF(ISBLANK($B40),"",MATCH($X40,COA!$B:$B,0))
B41: 46165 | C41: Southwest Airlines MASTERCARD-544015XXXXXX8678-John Taylor | D41: Southwest Air | E41: 61210 Sales & Marketing:Sales & Marketing- Travel Expenses:Airfare | F41: 882.8 | O41: =IF(C41="", "", TRIM(RIGHT(C41, LEN(C41) - FIND("@@", SUBSTITUTE(C41, "-", "@@", LEN(C41) - LEN(SUBSTITUTE(C41, "-", ""))))))) | P41: {=IFERROR(XLOOKUP(O41,'Department Listing'!$O$1:$O$395,'Department Listing'!$A$1:$A$395),IFERROR(XLOOKUP(O41,'Name Aliases'!$A$2:$A$1000,'Name Aliases'!$B$2:$B$1000),""))} | Q41: =IF(ISBLANK($C41),"",$B41) | R41: =IF(ISBLANK($C41),"",IF(ISBLANK($I41),$D41,$I41)) | S41: =IF(ISBLANK($C41),"",$F41 - $G41) | T41: =IF(ISBLANK($C41),"",C41) | U41: =IF(ISBLANK($C41),"",$D$1) | V41: {=IF(ISBLANK($B41),"",IF(ISBLANK($K41),IF(XLOOKUP($W41,'Category Mapping'!$C:$C,'Category Mapping'!$B:$B)="Travel",XLOOKUP($P41,'Department Listing'!$A:$A,'Department Listing'!$M:$M),XLOOKUP($W41,'Category Mapping'!$C:$C,'Category Mapping'!$D:$D)),$K41))} | W41: =IF(ISBLANK($B41),"",IF(ISBLANK($L41),RIGHT($E41,LEN($E41) - FIND("^",SUBSTITUTE($E41,":","^",LEN($E41) - LEN(SUBSTITUTE($E41,":",""))))),$L41)) | X41: =IF(ISBLANK($J41),$V41&$W41,$J41) | Y41: {=IF(ISBLANK($M41),IFERROR(XLOOKUP($P41,'Department Listing'!$A:$A,'Department Listing'!$L:$L),""),$M41)} | Z41: =IF(ISBLANK($B41),"",MATCH($X41,COA!$B:$B,0))
B42: 46165 | C42: Jamie Cosgrove MASTERCARD-544015XXXXXX6112-Elyse Neumeier | E42: 63310 General & Administrative:Software Licenses | F42: 750 | I42: Office Vendor | L42: Dues & Subscriptions | O42: =IF(C42="", "", TRIM(RIGHT(C42, LEN(C42) - FIND("@@", SUBSTITUTE(C42, "-", "@@", LEN(C42) - LEN(SUBSTITUTE(C42, "-", ""))))))) | P42: {=IFERROR(XLOOKUP(O42,'Department Listing'!$O$1:$O$395,'Department Listing'!$A$1:$A$395),IFERROR(XLOOKUP(O42,'Name Aliases'!$A$2:$A$1000,'Name Aliases'!$B$2:$B$1000),""))} | Q42: =IF(ISBLANK($C42),"",$B42) | R42: =IF(ISBLANK($C42),"",IF(ISBLANK($I42),$D42,$I42)) | S42: =IF(ISBLANK($C42),"",$F42 - $G42) | T42: =IF(ISBLANK($C42),"",C42) | U42: =IF(ISBLANK($C42),"",$D$1) | V42: {=IF(ISBLANK($B42),"",IF(ISBLANK($K42),IF(XLOOKUP($W42,'Category Mapping'!$C:$C,'Category Mapping'!$B:$B)="Travel",XLOOKUP($P42,'Department Listing'!$A:$A,'Department Listing'!$M:$M),XLOOKUP($W42,'Category Mapping'!$C:$C,'Category Mapping'!$D:$D)),$K42))} | W42: =IF(ISBLANK($B42),"",IF(ISBLANK($L42),RIGHT($E42,LEN($E42) - FIND("^",SUBSTITUTE($E42,":","^",LEN($E42) - LEN(SUBSTITUTE($E42,":",""))))),$L42)) | X42: =IF(ISBLANK($J42),$V42&$W42,$J42) | Y42: {=IF(ISBLANK($M42),IFERROR(XLOOKUP($P42,'Department Listing'!$A:$A,'Department Listing'!$L:$L),""),$M42)} | Z42: =IF(ISBLANK($B42),"",MATCH($X42,COA!$B:$B,0))
B43: 46168 | C43: GUESTRS*PUROWARSZA MASTERCARD-544015XXXXXX5191-Samantha Purpura | E43: 61220 Sales & Marketing:Sales & Marketing- Travel Expenses:Ground Transportation | F43: 739.92 | I43: Hotel Vendor | L43: Lodging | O43: =IF(C43="", "", TRIM(RIGHT(C43, LEN(C43) - FIND("@@", SUBSTITUTE(C43, "-", "@@", LEN(C43) - LEN(SUBSTITUTE(C43, "-", ""))))))) | P43: {=IFERROR(XLOOKUP(O43,'Department Listing'!$O$1:$O$395,'Department Listing'!$A$1:$A$395),IFERROR(XLOOKUP(O43,'Name Aliases'!$A$2:$A$1000,'Name Aliases'!$B$2:$B$1000),""))} | Q43: =IF(ISBLANK($C43),"",$B43) | R43: =IF(ISBLANK($C43),"",IF(ISBLANK($I43),$D43,$I43)) | S43: =IF(ISBLANK($C43),"",$F43 - $G43) | T43: =IF(ISBLANK($C43),"",C43) | U43: =IF(ISBLANK($C43),"",$D$1) | V43: {=IF(ISBLANK($B43),"",IF(ISBLANK($K43),IF(XLOOKUP($W43,'Category Mapping'!$C:$C,'Category Mapping'!$B:$B)="Travel",XLOOKUP($P43,'Department Listing'!$A:$A,'Department Listing'!$M:$M),XLOOKUP($W43,'Category Mapping'!$C:$C,'Category Mapping'!$D:$D)),$K43))} | W43: =IF(ISBLANK($B43),"",IF(ISBLANK($L43),RIGHT($E43,LEN($E43) - FIND("^",SUBSTITUTE($E43,":","^",LEN($E43) - LEN(SUBSTITUTE($E43,":",""))))),$L43)) | X43: =IF(ISBLANK($J43),$V43&$W43,$J43) | Y43: {=IF(ISBLANK($M43),IFERROR(XLOOKUP($P43,'Department Listing'!$A:$A,'Department Listing'!$L:$L),""),$M43)} | Z43: =IF(ISBLANK($B43),"",MATCH($X43,COA!$B:$B,0))
B44: 46164 | C44: Marriott Union Square MASTERCARD-544015XXXXXX2445-Tyler Grimshaw | D44: Marriott | E44: 61230 Sales & Marketing:Sales & Marketing- Travel Expenses:Lodging | F44: 699.46 | O44: =IF(C44="", "", TRIM(RIGHT(C44, LEN(C44) - FIND("@@", SUBSTITUTE(C44, "-", "@@", LEN(C44) - LEN(SUBSTITUTE(C44, "-", ""))))))) | P44: {=IFERROR(XLOOKUP(O44,'Department Listing'!$O$1:$O$395,'Department Listing'!$A$1:$A$395),IFERROR(XLOOKUP(O44,'Name Aliases'!$A$2:$A$1000,'Name Aliases'!$B$2:$B$1000),""))} | Q44: =IF(ISBLANK($C44),"",$B44) | R44: =IF(ISBLANK($C44),"",IF(ISBLANK($I44),$D44,$I44)) | S44: =IF(ISBLANK($C44),"",$F44 - $G44) | T44: =IF(ISBLANK($C44),"",C44) | U44: =IF(ISBLANK($C44),"",$D$1) | V44: {=IF(ISBLANK($B44),"",IF(ISBLANK($K44),IF(XLOOKUP($W44,'Category Mapping'!$C:$C,'Category Mapping'!$B:$B)="Travel",XLOOKUP($P44,'Department Listing'!$A:$A,'Department Listing'!$M:$M),XLOOKUP($W44,'Category Mapping'!$C:$C,'Category Mapping'!$D:$D)),$K44))} | W44: =IF(ISBLANK($B44),"",IF(ISBLANK($L44),RIGHT($E44,LEN($E44) - FIND("^",SUBSTITUTE($E44,":","^",LEN($E44) - LEN(SUBSTITUTE($E44,":",""))))),$L44)) | X44: =IF(ISBLANK($J44),$V44&$W44,$J44) | Y44: {=IF(ISBLANK($M44),IFERROR(XLOOKUP($P44,'Department Listing'!$A:$A,'Department Listing'!$L:$L),""),$M44)} | Z44: =IF(ISBLANK($B44),"",MATCH($X44,COA!$B:$B,0))
B45: 46167 | C45: Air Canada MASTERCARD-555671XXXXXX3587-Pooja Manjeshwar | D45: Air Canada | E45: 61210 Sales & Marketing:Sales & Marketing- Travel Expenses:Airfare | F45: 646.62 | O45: =IF(C45="", "", TRIM(RIGHT(C45, LEN(C45) - FIND("@@", SUBSTITUTE(C45, "-", "@@", LEN(C45) - LEN(SUBSTITUTE(C45, "-", ""))))))) | P45: {=IFERROR(XLOOKUP(O45,'Department Listing'!$O$1:$O$395,'Department Listing'!$A$1:$A$395),IFERROR(XLOOKUP(O45,'Name Aliases'!$A$2:$A$1000,'Name Aliases'!$B$2:$B$1000),""))} | Q45: =IF(ISBLANK($C45),"",$B45) | R45: =IF(ISBLANK($C45),"",IF(ISBLANK($I45),$D45,$I45)) | S45: =IF(ISBLANK($C45),"",$F45 - $G45) | T45: =IF(ISBLANK($C45),"",C45) | U45: =IF(ISBLANK($C45),"",$D$1) | V45: {=IF(ISBLANK($B45),"",IF(ISBLANK($K45),IF(XLOOKUP($W45,'Category Mapping'!$C:$C,'Category Mapping'!$B:$B)="Travel",XLOOKUP($P45,'Department Listing'!$A:$A,'Department Listing'!$M:$M),XLOOKUP($W45,'Category Mapping'!$C:$C,'Category Mapping'!$D:$D)),$K45))} | W45: =IF(ISBLANK($B45),"",IF(ISBLANK($L45),RIGHT($E45,LEN($E45) - FIND("^",SUBSTITUTE($E45,":","^",LEN($E45) - LEN(SUBSTITUTE($E45,":",""))))),$L45)) | X45: =IF(ISBLANK($J45),$V45&$W45,$J45) | Y45: {=IF(ISBLANK($M45),IFERROR(XLOOKUP($P45,'Department Listing'!$A:$A,'Department Listing'!$L:$L),""),$M45)} | Z45: =IF(ISBLANK($B45),"",MATCH($X45,COA!$B:$B,0))
B46: 46168 | C46: FedEx MASTERCARD-544015XXXXXX0151-Eric Rabkin | D46: FedEx | E46: 63430 General & Administrative:Office Expenses:Shipping Expense | F46: 637.7 | O46: =IF(C46="", "", TRIM(RIGHT(C46, LEN(C46) - FIND("@@", SUBSTITUTE(C46, "-", "@@", LEN(C46) - LEN(SUBSTITUTE(C46, "-", ""))))))) | P46: {=IFERROR(XLOOKUP(O46,'Department Listing'!$O$1:$O$395,'Department Listing'!$A$1:$A$395),IFERROR(XLOOKUP(O46,'Name Aliases'!$A$2:$A$1000,'Name Aliases'!$B$2:$B$1000),""))} | Q46: =IF(ISBLANK($C46),"",$B46) | R46: =IF(ISBLANK($C46),"",IF(ISBLANK($I46),$D46,$I46)) | S46: =IF(ISBLANK($C46),"",$F46 - $G46) | T46: =IF(ISBLANK($C46),"",C46) | U46: =IF(ISBLANK($C46),"",$D$1) | V46: {=IF(ISBLANK($B46),"",IF(ISBLANK($K46),IF(XLOOKUP($W46,'Category Mapping'!$C:$C,'Category Mapping'!$B:$B)="Travel",XLOOKUP($P46,'Department Listing'!$A:$A,'Department Listing'!$M:$M),XLOOKUP($W46,'Category Mapping'!$C:$C,'Category Mapping'!$D:$D)),$K46))} | W46: =IF(ISBLANK($B46),"",IF(ISBLANK($L46),RIGHT($E46,LEN($E46) - FIND("^",SUBSTITUTE($E46,":","^",LEN($E46) - LEN(SUBSTITUTE($E46,":",""))))),$L46)) | X46: =IF(ISBLANK($J46),$V46&$W46,$J46) | Y46: {=IF(ISBLANK($M46),IFERROR(XLOOKUP($P46,'Department Listing'!$A:$A,'Department Listing'!$L:$L),""),$M46)} | Z46: =IF(ISBLANK($B46),"",MATCH($X46,COA!$B:$B,0))
B47: 46167 | C47: American Airlines MASTERCARD-544015XXXXXX5029-Austin Nadler | D47: American Airlines | E47: 61210 Sales & Marketing:Sales & Marketing- Travel Expenses:Airfare | F47: 594.8 | O47: =IF(C47="", "", TRIM(RIGHT(C47, LEN(C47) - FIND("@@", SUBSTITUTE(C47, "-", "@@", LEN(C47) - LEN(SUBSTITUTE(C47, "-", ""))))))) | P47: {=IFERROR(XLOOKUP(O47,'Department Listing'!$O$1:$O$395,'Department Listing'!$A$1:$A$395),IFERROR(XLOOKUP(O47,'Name Aliases'!$A$2:$A$1000,'Name Aliases'!$B$2:$B$1000),""))} | Q47: =IF(ISBLANK($C47),"",$B47) | R47: =IF(ISBLANK($C47),"",IF(ISBLANK($I47),$D47,$I47)) | S47: =IF(ISBLANK($C47),"",$F47 - $G47) | T47: =IF(ISBLANK($C47),"",C47) | U47: =IF(ISBLANK($C47),"",$D$1) | V47: {=IF(ISBLANK($B47),"",IF(ISBLANK($K47),IF(XLOOKUP($W47,'Category Mapping'!$C:$C,'Category Mapping'!$B:$B)="Travel",XLOOKUP($P47,'Department Listing'!$A:$A,'Department Listing'!$M:$M),XLOOKUP($W47,'Category Mapping'!$C:$C,'Category Mapping'!$D:$D)),$K47))} | W47: =IF(ISBLANK($B47),"",IF(ISBLANK($L47),RIGHT($E47,LEN($E47) - FIND("^",SUBSTITUTE($E47,":","^",LEN($E47) - LEN(SUBSTITUTE($E47,":",""))))),$L47)) | X47: =IF(ISBLANK($J47),$V47&$W47,$J47) | Y47: {=IF(ISBLANK($M47),IFERROR(XLOOKUP($P47,'Department Listing'!$A:$A,'Department Listing'!$L:$L),""),$M47)} | Z47: =IF(ISBLANK($B47),"",MATCH($X47,COA!$B:$B,0))
B48: 46168 | C48: Wegmans MASTERCARD-544015XXXXXX7759-Mickenzi Krpec | E48: 61240 Sales & Marketing:Sales & Marketing- Travel Expenses:Meals & Entertainment | F48: 507.74 | I48: Food Vendor | O48: =IF(C48="", "", TRIM(RIGHT(C48, LEN(C48) - FIND("@@", SUBSTITUTE(C48, "-", "@@", LEN(C48) - LEN(SUBSTITUTE(C48, "-", ""))))))) | P48: {=IFERROR(XLOOKUP(O48,'Department Listing'!$O$1:$O$395,'Department Listing'!$A$1:$A$395),IFERROR(XLOOKUP(O48,'Name Aliases'!$A$2:$A$1000,'Name Aliases'!$B$2:$B$1000),""))} | Q48: =IF(ISBLANK($C48),"",$B48) | R48: =IF(ISBLANK($C48),"",IF(ISBLANK($I48),$D48,$I48)) | S48: =IF(ISBLANK($C48),"",$F48 - $G48) | T48: =IF(ISBLANK($C48),"",C48) | U48: =IF(ISBLANK($C48),"",$D$1) | V48: {=IF(ISBLANK($B48),"",IF(ISBLANK($K48),IF(XLOOKUP($W48,'Category Mapping'!$C:$C,'Category Mapping'!$B:$B)="Travel",XLOOKUP($P48,'Department Listing'!$A:$A,'Department Listing'!$M:$M),XLOOKUP($W48,'Category Mapping'!$C:$C,'Category Mapping'!$D:$D)),$K48))} | W48: =IF(ISBLANK($B48),"",IF(ISBLANK($L48),RIGHT($E48,LEN($E48) - FIND("^",SUBSTITUTE($E48,":","^",LEN($E48) - LEN(SUBSTITUTE($E48,":",""))))),$L48)) | X48: =IF(ISBLANK($J48),$V48&$W48,$J48) | Y48: {=IF(ISBLANK($M48),IFERROR(XLOOKUP($P48,'Department Listing'!$A:$A,'Department Listing'!$L:$L),""),$M48)} | Z48: =IF(ISBLANK($B48),"",MATCH($X48,COA!$B:$B,0))
B49: 46164 | C49: Presidio Golf Course MASTERCARD-544015XXXXXX2445-Tyler Grimshaw | E49: 61240 Sales & Marketing:Sales & Marketing- Travel Expenses:Meals & Entertainment | F49: 501.28 | I49: Food Vendor | O49: =IF(C49="", "", TRIM(RIGHT(C49, LEN(C49) - FIND("@@", SUBSTITUTE(C49, "-", "@@", LEN(C49) - LEN(SUBSTITUTE(C49, "-", ""))))))) | P49: {=IFERROR(XLOOKUP(O49,'Department Listing'!$O$1:$O$395,'Department Listing'!$A$1:$A$395),IFERROR(XLOOKUP(O49,'Name Aliases'!$A$2:$A$1000,'Name Aliases'!$B$2:$B$1000),""))} | Q49: =IF(ISBLANK($C49),"",$B49) | R49: =IF(ISBLANK($C49),"",IF(ISBLANK($I49),$D49,$I49)) | S49: =IF(ISBLANK($C49),"",$F49 - $G49) | T49: =IF(ISBLANK($C49),"",C49) | U49: =IF(ISBLANK($C49),"",$D$1) | V49: {=IF(ISBLANK($B49),"",IF(ISBLANK($K49),IF(XLOOKUP($W49,'Category Mapping'!$C:$C,'Category Mapping'!$B:$B)="Travel",XLOOKUP($P49,'Department Listing'!$A:$A,'Department Listing'!$M:$M),XLOOKUP($W49,'Category Mapping'!$C:$C,'Category Mapping'!$D:$D)),$K49))} | W49: =IF(ISBLANK($B49),"",IF(ISBLANK($L49),RIGHT($E49,LEN($E49) - FIND("^",SUBSTITUTE($E49,":","^",LEN($E49) - LEN(SUBSTITUTE($E49,":",""))))),$L49)) | X49: =IF(ISBLANK($J49),$V49&$W49,$J49) | Y49: {=IF(ISBLANK($M49),IFERROR(XLOOKUP($P49,'Department Listing'!$A:$A,'Department Listing'!$L:$L),""),$M49)} | Z49: =IF(ISBLANK($B49),"",MATCH($X49,COA!$B:$B,0))
B50: 46168 | C50: Uber Eats MASTERCARD-544015XXXXXX7759-Mickenzi Krpec | D50: Uber Eats | E50: 61240 Sales & Marketing:Sales & Marketing- Travel Expenses:Meals & Entertainment | F50: 480.39 | O50: =IF(C50="", "", TRIM(RIGHT(C50, LEN(C50) - FIND("@@", SUBSTITUTE(C50, "-", "@@", LEN(C50) - LEN(SUBSTITUTE(C50, "-", ""))))))) | P50: {=IFERROR(XLOOKUP(O50,'Department Listing'!$O$1:$O$395,'Department Listing'!$A$1:$A$395),IFERROR(XLOOKUP(O50,'Name Aliases'!$A$2:$A$1000,'Name Aliases'!$B$2:$B$1000),""))} | Q50: =IF(ISBLANK($C50),"",$B50) | R50: =IF(ISBLANK($C50),"",IF(ISBLANK($I50),$D50,$I50)) | S50: =IF(ISBLANK($C50),"",$F50 - $G50) | T50: =IF(ISBLANK($C50),"",C50) | U50: =IF(ISBLANK($C50),"",$D$1) | V50: {=IF(ISBLANK($B50),"",IF(ISBLANK($K50),IF(XLOOKUP($W50,'Category Mapping'!$C:$C,'Category Mapping'!$B:$B)="Travel",XLOOKUP($P50,'Department Listing'!$A:$A,'Department Listing'!$M:$M),XLOOKUP($W50,'Category Mapping'!$C:$C,'Category Mapping'!$D:$D)),$K50))} | W50: =IF(ISBLANK($B50),"",IF(ISBLANK($L50),RIGHT($E50,LEN($E50) - FIND("^",SUBSTITUTE($E50,":","^",LEN($E50) - LEN(SUBSTITUTE($E50,":",""))))),$L50)) | X50: =IF(ISBLANK($J50),$V50&$W50,$J50) | Y50: {=IF(ISBLANK($M50),IFERROR(XLOOKUP($P50,'Department Listing'!$A:$A,'Department Listing'!$L:$L),""),$M50)} | Z50: =IF(ISBLANK($B50),"",MATCH($X50,COA!$B:$B,0))
B51: 46168 | C51: Uber Eats MASTERCARD-544015XXXXXX7759-Mickenzi Krpec | D51: Uber Eats | E51: 61240 Sales & Marketing:Sales & Marketing- Travel Expenses:Meals & Entertainment | F51: 469.84 | O51: =IF(C51="", "", TRIM(RIGHT(C51, LEN(C51) - FIND("@@", SUBSTITUTE(C51, "-", "@@", LEN(C51) - LEN(SUBSTITUTE(C51, "-", ""))))))) | P51: {=IFERROR(XLOOKUP(O51,'Department Listing'!$O$1:$O$395,'Department Listing'!$A$1:$A$395),IFERROR(XLOOKUP(O51,'Name Aliases'!$A$2:$A$1000,'Name Aliases'!$B$2:$B$1000),""))} | Q51: =IF(ISBLANK($C51),"",$B51) | R51: =IF(ISBLANK($C51),"",IF(ISBLANK($I51),$D51,$I51)) | S51: =IF(ISBLANK($C51),"",$F51 - $G51) | T51: =IF(ISBLANK($C51),"",C51) | U51: =IF(ISBLANK($C51),"",$D$1) | V51: {=IF(ISBLANK($B51),"",IF(ISBLANK($K51),IF(XLOOKUP($W51,'Category Mapping'!$C:$C,'Category Mapping'!$B:$B)="Travel",XLOOKUP($P51,'Department Listing'!$A:$A,'Department Listing'!$M:$M),XLOOKUP($W51,'Category Mapping'!$C:$C,'Category Mapping'!$D:$D)),$K51))} | W51: =IF(ISBLANK($B51),"",IF(ISBLANK($L51),RIGHT($E51,LEN($E51) - FIND("^",SUBSTITUTE($E51,":","^",LEN($E51) - LEN(SUBSTITUTE($E51,":",""))))),$L51)) | X51: =IF(ISBLANK($J51),$V51&$W51,$J51) | Y51: {=IF(ISBLANK($M51),IFERROR(XLOOKUP($P51,'Department Listing'!$A:$A,'Department Listing'!$L:$L),""),$M51)} | Z51: =IF(ISBLANK($B51),"",MATCH($X51,COA!$B:$B,0))
B52: 46165 | C52: National Car Rental MASTERCARD-544015XXXXXX8678-John Taylor | D52: National Car | E52: 61220 Sales & Marketing:Sales & Marketing- Travel Expenses:Ground Transportation | F52: 454.77 | O52: =IF(C52="", "", TRIM(RIGHT(C52, LEN(C52) - FIND("@@", SUBSTITUTE(C52, "-", "@@", LEN(C52) - LEN(SUBSTITUTE(C52, "-", ""))))))) | P52: {=IFERROR(XLOOKUP(O52,'Department Listing'!$O$1:$O$395,'Department Listing'!$A$1:$A$395),IFERROR(XLOOKUP(O52,'Name Aliases'!$A$2:$A$1000,'Name Aliases'!$B$2:$B$1000),""))} | Q52: =IF(ISBLANK($C52),"",$B52) | R52: =IF(ISBLANK($C52),"",IF(ISBLANK($I52),$D52,$I52)) | S52: =IF(ISBLANK($C52),"",$F52 - $G52) | T52: =IF(ISBLANK($C52),"",C52) | U52: =IF(ISBLANK($C52),"",$D$1) | V52: {=IF(ISBLANK($B52),"",IF(ISBLANK($K52),IF(XLOOKUP($W52,'Category Mapping'!$C:$C,'Category Mapping'!$B:$B)="Travel",XLOOKUP($P52,'Department Listing'!$A:$A,'Department Listing'!$M:$M),XLOOKUP($W52,'Category Mapping'!$C:$C,'Category Mapping'!$D:$D)),$K52))} | W52: =IF(ISBLANK($B52),"",IF(ISBLANK($L52),RIGHT($E52,LEN($E52) - FIND("^",SUBSTITUTE($E52,":","^",LEN($E52) - LEN(SUBSTITUTE($E52,":",""))))),$L52)) | X52: =IF(ISBLANK($J52),$V52&$W52,$J52) | Y52: {=IF(ISBLANK($M52),IFERROR(XLOOKUP($P52,'Department Listing'!$A:$A,'Department Listing'!$L:$L),""),$M52)} | Z52: =IF(ISBLANK($B52),"",MATCH($X52,COA!$B:$B,0))
B53: 46169 | C53: Southwest Airlines MASTERCARD-555671XXXXXX6688-Matt Hyman | D53: Southwest Air | E53: 61210 Sales & Marketing:Sales & Marketing- Travel Expenses:Airfare | F53: 400.4 | O53: =IF(C53="", "", TRIM(RIGHT(C53, LEN(C53) - FIND("@@", SUBSTITUTE(C53, "-", "@@", LEN(C53) - LEN(SUBSTITUTE(C53, "-", ""))))))) | P53: {=IFERROR(XLOOKUP(O53,'Department Listing'!$O$1:$O$395,'Department Listing'!$A$1:$A$395),IFERROR(XLOOKUP(O53,'Name Aliases'!$A$2:$A$1000,'Name Aliases'!$B$2:$B$1000),""))} | Q53: =IF(ISBLANK($C53),"",$B53) | R53: =IF(ISBLANK($C53),"",IF(ISBLANK($I53),$D53,$I53)) | S53: =IF(ISBLANK($C53),"",$F53 - $G53) | T53: =IF(ISBLANK($C53),"",C53) | U53: =IF(ISBLANK($C53),"",$D$1) | V53: {=IF(ISBLANK($B53),"",IF(ISBLANK($K53),IF(XLOOKUP($W53,'Category Mapping'!$C:$C,'Category Mapping'!$B:$B)="Travel",XLOOKUP($P53,'Department Listing'!$A:$A,'Department Listing'!$M:$M),XLOOKUP($W53,'Category Mapping'!$C:$C,'Category Mapping'!$D:$D)),$K53))} | W53: =IF(ISBLANK($B53),"",IF(ISBLANK($L53),RIGHT($E53,LEN($E53) - FIND("^",SUBSTITUTE($E53,":","^",LEN($E53) - LEN(SUBSTITUTE($E53,":",""))))),$L53)) | X53: =IF(ISBLANK($J53),$V53&$W53,$J53) | Y53: {=IF(ISBLANK($M53),IFERROR(XLOOKUP($P53,'Department Listing'!$A:$A,'Department Listing'!$L:$L),""),$M53)} | Z53: =IF(ISBLANK($B53),"",MATCH($X53,COA!$B:$B,0))
B54: 46164 | C54: WEISSGERBER S GOLDEN M MASTERCARD-544015XXXXXX8678-John Taylor | E54: 61240 Sales & Marketing:Sales & Marketing- Travel Expenses:Meals & Entertainment | F54: 385 | I54: Food Vendor | O54: =IF(C54="", "", TRIM(RIGHT(C54, LEN(C54) - FIND("@@", SUBSTITUTE(C54, "-", "@@", LEN(C54) - LEN(SUBSTITUTE(C54, "-", ""))))))) | P54: {=IFERROR(XLOOKUP(O54,'Department Listing'!$O$1:$O$395,'Department Listing'!$A$1:$A$395),IFERROR(XLOOKUP(O54,'Name Aliases'!$A$2:$A$1000,'Name Aliases'!$B$2:$B$1000),""))} | Q54: =IF(ISBLANK($C54),"",$B54) | R54: =IF(ISBLANK($C54),"",IF(ISBLANK($I54),$D54,$I54)) | S54: =IF(ISBLANK($C54),"",$F54 - $G54) | T54: =IF(ISBLANK($C54),"",C54) | U54: =IF(ISBLANK($C54),"",$D$1) | V54: {=IF(ISBLANK($B54),"",IF(ISBLANK($K54),IF(XLOOKUP($W54,'Category Mapping'!$C:$C,'Category Mapping'!$B:$B)="Travel",XLOOKUP($P54,'Department Listing'!$A:$A,'Department Listing'!$M:$M),XLOOKUP($W54,'Category Mapping'!$C:$C,'Category Mapping'!$D:$D)),$K54))} | W54: =IF(ISBLANK($B54),"",IF(ISBLANK($L54),RIGHT($E54,LEN($E54) - FIND("^",SUBSTITUTE($E54,":","^",LEN($E54) - LEN(SUBSTITUTE($E54,":",""))))),$L54)) | X54: =IF(ISBLANK($J54),$V54&$W54,$J54) | Y54: {=IF(ISBLANK($M54),IFERROR(XLOOKUP($P54,'Department Listing'!$A:$A,'Department Listing'!$L:$L),""),$M54)} | Z54: =IF(ISBLANK($B54),"",MATCH($X54,COA!$B:$B,0))
B55: 46169 | C55: British Airways MASTERCARD-555671XXXXXX4106-Daniel Mooney | D55: British Airways | E55: 61210 Sales & Marketing:Sales & Marketing- Travel Expenses:Airfare | F55: 375.23 | O55: =IF(C55="", "", TRIM(RIGHT(C55, LEN(C55) - FIND("@@", SUBSTITUTE(C55, "-", "@@", LEN(C55) - LEN(SUBSTITUTE(C55, "-", ""))))))) | P55: {=IFERROR(XLOOKUP(O55,'Department Listing'!$O$1:$O$395,'Department Listing'!$A$1:$A$395),IFERROR(XLOOKUP(O55,'Name Aliases'!$A$2:$A$1000,'Name Aliases'!$B$2:$B$1000),""))} | Q55: =IF(ISBLANK($C55),"",$B55) | R55: =IF(ISBLANK($C55),"",IF(ISBLANK($I55),$D55,$I55)) | S55: =IF(ISBLANK($C55),"",$F55 - $G55) | T55: =IF(ISBLANK($C55),"",C55) | U55: =IF(ISBLANK($C55),"",$D$1) | V55: {=IF(ISBLANK($B55),"",IF(ISBLANK($K55),IF(XLOOKUP($W55,'Category Mapping'!$C:$C,'Category Mapping'!$B:$B)="Travel",XLOOKUP($P55,'Department Listing'!$A:$A,'Department Listing'!$M:$M),XLOOKUP($W55,'Category Mapping'!$C:$C,'Category Mapping'!$D:$D)),$K55))} | W55: =IF(ISBLANK($B55),"",IF(ISBLANK($L55),RIGHT($E55,LEN($E55) - FIND("^",SUBSTITUTE($E55,":","^",LEN($E55) - LEN(SUBSTITUTE($E55,":",""))))),$L55)) | X55: =IF(ISBLANK($J55),$V55&$W55,$J55) | Y55: {=IF(ISBLANK($M55),IFERROR(XLOOKUP($P55,'Department Listing'!$A:$A,'Department Listing'!$L:$L),""),$M55)} | Z55: =IF(ISBLANK($B55),"",MATCH($X55,COA!$B:$B,0))
B56: 46169 | C56: Uber Eats MASTERCARD-544015XXXXXX7759-Mickenzi Krpec | D56: Uber Eats | E56: 61240 Sales & Marketing:Sales & Marketing- Travel Expenses:Meals & Entertainment | F56: 362.59 | O56: =IF(C56="", "", TRIM(RIGHT(C56, LEN(C56) - FIND("@@", SUBSTITUTE(C56, "-", "@@", LEN(C56) - LEN(SUBSTITUTE(C56, "-", ""))))))) | P56: {=IFERROR(XLOOKUP(O56,'Department Listing'!$O$1:$O$395,'Department Listing'!$A$1:$A$395),IFERROR(XLOOKUP(O56,'Name Aliases'!$A$2:$A$1000,'Name Aliases'!$B$2:$B$1000),""))} | Q56: =IF(ISBLANK($C56),"",$B56) | R56: =IF(ISBLANK($C56),"",IF(ISBLANK($I56),$D56,$I56)) | S56: =IF(ISBLANK($C56),"",$F56 - $G56) | T56: =IF(ISBLANK($C56),"",C56) | U56: =IF(ISBLANK($C56),"",$D$1) | V56: {=IF(ISBLANK($B56),"",IF(ISBLANK($K56),IF(XLOOKUP($W56,'Category Mapping'!$C:$C,'Category Mapping'!$B:$B)="Travel",XLOOKUP($P56,'Department Listing'!$A:$A,'Department Listing'!$M:$M),XLOOKUP($W56,'Category Mapping'!$C:$C,'Category Mapping'!$D:$D)),$K56))} | W56: =IF(ISBLANK($B56),"",IF(ISBLANK($L56),RIGHT($E56,LEN($E56) - FIND("^",SUBSTITUTE($E56,":","^",LEN($E56) - LEN(SUBSTITUTE($E56,":",""))))),$L56)) | X56: =IF(ISBLANK($J56),$V56&$W56,$J56) | Y56: {=IF(ISBLANK($M56),IFERROR(XLOOKUP($P56,'Department Listing'!$A:$A,'Department Listing'!$L:$L),""),$M56)} | Z56: =IF(ISBLANK($B56),"",MATCH($X56,COA!$B:$B,0))
B57: 46168 | C57: GUESTRS*PUROWARSZA MASTERCARD-544015XXXXXX5191-Samantha Purpura | E57: 61220 Sales & Marketing:Sales & Marketing- Travel Expenses:Ground Transportation | F57: 312.71 | I57: Hotel Vendor | L57: Lodging | O57: =IF(C57="", "", TRIM(RIGHT(C57, LEN(C57) - FIND("@@", SUBSTITUTE(C57, "-", "@@", LEN(C57) - LEN(SUBSTITUTE(C57, "-", ""))))))) | P57: {=IFERROR(XLOOKUP(O57,'Department Listing'!$O$1:$O$395,'Department Listing'!$A$1:$A$395),IFERROR(XLOOKUP(O57,'Name Aliases'!$A$2:$A$1000,'Name Aliases'!$B$2:$B$1000),""))} | Q57: =IF(ISBLANK($C57),"",$B57) | R57: =IF(ISBLANK($C57),"",IF(ISBLANK($I57),$D57,$I57)) | S57: =IF(ISBLANK($C57),"",$F57 - $G57) | T57: =IF(ISBLANK($C57),"",C57) | U57: =IF(ISBLANK($C57),"",$D$1) | V57: {=IF(ISBLANK($B57),"",IF(ISBLANK($K57),IF(XLOOKUP($W57,'Category Mapping'!$C:$C,'Category Mapping'!$B:$B)="Travel",XLOOKUP($P57,'Department Listing'!$A:$A,'Department Listing'!$M:$M),XLOOKUP($W57,'Category Mapping'!$C:$C,'Category Mapping'!$D:$D)),$K57))} | W57: =IF(ISBLANK($B57),"",IF(ISBLANK($L57),RIGHT($E57,LEN($E57) - FIND("^",SUBSTITUTE($E57,":","^",LEN($E57) - LEN(SUBSTITUTE($E57,":",""))))),$L57)) | X57: =IF(ISBLANK($J57),$V57&$W57,$J57) | Y57: {=IF(ISBLANK($M57),IFERROR(XLOOKUP($P57,'Department Listing'!$A:$A,'Department Listing'!$L:$L),""),$M57)} | Z57: =IF(ISBLANK($B57),"",MATCH($X57,COA!$B:$B,0))
B58: 46168 | C58: Booking.com MASTERCARD-555671XXXXXX4106-Daniel Mooney | D58: Booking.com | E58: 61290 Sales & Marketing:Sales & Marketing- Travel Expenses:Other Travel Expenses | F58: 304.99 | O58: =IF(C58="", "", TRIM(RIGHT(C58, LEN(C58) - FIND("@@", SUBSTITUTE(C58, "-", "@@", LEN(C58) - LEN(SUBSTITUTE(C58, "-", ""))))))) | P58: {=IFERROR(XLOOKUP(O58,'Department Listing'!$O$1:$O$395,'Department Listing'!$A$1:$A$395),IFERROR(XLOOKUP(O58,'Name Aliases'!$A$2:$A$1000,'Name Aliases'!$B$2:$B$1000),""))} | Q58: =IF(ISBLANK($C58),"",$B58) | R58: =IF(ISBLANK($C58),"",IF(ISBLANK($I58),$D58,$I58)) | S58: =IF(ISBLANK($C58),"",$F58 - $G58) | T58: =IF(ISBLANK($C58),"",C58) | U58: =IF(ISBLANK($C58),"",$D$1) | V58: {=IF(ISBLANK($B58),"",IF(ISBLANK($K58),IF(XLOOKUP($W58,'Category Mapping'!$C:$C,'Category Mapping'!$B:$B)="Travel",XLOOKUP($P58,'Department Listing'!$A:$A,'Department Listing'!$M:$M),XLOOKUP($W58,'Category Mapping'!$C:$C,'Category Mapping'!$D:$D)),$K58))} | W58: =IF(ISBLANK($B58),"",IF(ISBLANK($L58),RIGHT($E58,LEN($E58) - FIND("^",SUBSTITUTE($E58,":","^",LEN($E58) - LEN(SUBSTITUTE($E58,":",""))))),$L58)) | X58: =IF(ISBLANK($J58),$V58&$W58,$J58) | Y58: {=IF(ISBLANK($M58),IFERROR(XLOOKUP($P58,'Department Listing'!$A:$A,'Department Listing'!$L:$L),""),$M58)} | Z58: =IF(ISBLANK($B58),"",MATCH($X58,COA!$B:$B,0))
B59: 46167 | C59: Microsoft MASTERCARD-555671XXXXXX5364-Erik Williams | D59: Microsoft | E59: 63310 General & Administrative:Software Licenses | F59: 285.2 | O59: =IF(C59="", "", TRIM(RIGHT(C59, LEN(C59) - FIND("@@", SUBSTITUTE(C59, "-", "@@", LEN(C59) - LEN(SUBSTITUTE(C59, "-", ""))))))) | P59: {=IFERROR(XLOOKUP(O59,'Department Listing'!$O$1:$O$395,'Department Listing'!$A$1:$A$395),IFERROR(XLOOKUP(O59,'Name Aliases'!$A$2:$A$1000,'Name Aliases'!$B$2:$B$1000),""))} | Q59: =IF(ISBLANK($C59),"",$B59) | R59: =IF(ISBLANK($C59),"",IF(ISBLANK($I59),$D59,$I59)) | S59: =IF(ISBLANK($C59),"",$F59 - $G59) | T59: =IF(ISBLANK($C59),"",C59) | U59: =IF(ISBLANK($C59),"",$D$1) | V59: {=IF(ISBLANK($B59),"",IF(ISBLANK($K59),IF(XLOOKUP($W59,'Category Mapping'!$C:$C,'Category Mapping'!$B:$B)="Travel",XLOOKUP($P59,'Department Listing'!$A:$A,'Department Listing'!$M:$M),XLOOKUP($W59,'Category Mapping'!$C:$C,'Category Mapping'!$D:$D)),$K59))} | W59: =IF(ISBLANK($B59),"",IF(ISBLANK($L59),RIGHT($E59,LEN($E59) - FIND("^",SUBSTITUTE($E59,":","^",LEN($E59) - LEN(SUBSTITUTE($E59,":",""))))),$L59)) | X59: =IF(ISBLANK($J59),$V59&$W59,$J59) | Y59: {=IF(ISBLANK($M59),IFERROR(XLOOKUP($P59,'Department Listing'!$A:$A,'Department Listing'!$L:$L),""),$M59)} | Z59: =IF(ISBLANK($B59),"",MATCH($X59,COA!$B:$B,0))
B60: 46165 | C60: American MASTERCARD-544015XXXXXX2900-Chloe Brant | D60: American Airlines | E60: 61210 Sales & Marketing:Sales & Marketing- Travel Expenses:Airfare | F60: 268.4 | O60: =IF(C60="", "", TRIM(RIGHT(C60, LEN(C60) - FIND("@@", SUBSTITUTE(C60, "-", "@@", LEN(C60) - LEN(SUBSTITUTE(C60, "-", ""))))))) | P60: {=IFERROR(XLOOKUP(O60,'Department Listing'!$O$1:$O$395,'Department Listing'!$A$1:$A$395),IFERROR(XLOOKUP(O60,'Name Aliases'!$A$2:$A$1000,'Name Aliases'!$B$2:$B$1000),""))} | Q60: =IF(ISBLANK($C60),"",$B60) | R60: =IF(ISBLANK($C60),"",IF(ISBLANK($I60),$D60,$I60)) | S60: =IF(ISBLANK($C60),"",$F60 - $G60) | T60: =IF(ISBLANK($C60),"",C60) | U60: =IF(ISBLANK($C60),"",$D$1) | V60: {=IF(ISBLANK($B60),"",IF(ISBLANK($K60),IF(XLOOKUP($W60,'Category Mapping'!$C:$C,'Category Mapping'!$B:$B)="Travel",XLOOKUP($P60,'Department Listing'!$A:$A,'Department Listing'!$M:$M),XLOOKUP($W60,'Category Mapping'!$C:$C,'Category Mapping'!$D:$D)),$K60))} | W60: =IF(ISBLANK($B60),"",IF(ISBLANK($L60),RIGHT($E60,LEN($E60) - FIND("^",SUBSTITUTE($E60,":","^",LEN($E60) - LEN(SUBSTITUTE($E60,":",""))))),$L60)) | X60: =IF(ISBLANK($J60),$V60&$W60,$J60) | Y60: {=IF(ISBLANK($M60),IFERROR(XLOOKUP($P60,'Department Listing'!$A:$A,'Department Listing'!$L:$L),""),$M60)} | Z60: =IF(ISBLANK($B60),"",MATCH($X60,COA!$B:$B,0))
B61: 46170 | C61: Expedia MASTERCARD-555671XXXXXX8870-Kyle Brueckner | D61: Expedia.com | E61: 61290 Sales & Marketing:Sales & Marketing- Travel Expenses:Other Travel Expenses | F61: 264.71 | O61: =IF(C61="", "", TRIM(RIGHT(C61, LEN(C61) - FIND("@@", SUBSTITUTE(C61, "-", "@@", LEN(C61) - LEN(SUBSTITUTE(C61, "-", ""))))))) | P61: {=IFERROR(XLOOKUP(O61,'Department Listing'!$O$1:$O$395,'Department Listing'!$A$1:$A$395),IFERROR(XLOOKUP(O61,'Name Aliases'!$A$2:$A$1000,'Name Aliases'!$B$2:$B$1000),""))} | Q61: =IF(ISBLANK($C61),"",$B61) | R61: =IF(ISBLANK($C61),"",IF(ISBLANK($I61),$D61,$I61)) | S61: =IF(ISBLANK($C61),"",$F61 - $G61) | T61: =IF(ISBLANK($C61),"",C61) | U61: =IF(ISBLANK($C61),"",$D$1) | V61: {=IF(ISBLANK($B61),"",IF(ISBLANK($K61),IF(XLOOKUP($W61,'Category Mapping'!$C:$C,'Category Mapping'!$B:$B)="Travel",XLOOKUP($P61,'Department Listing'!$A:$A,'Department Listing'!$M:$M),XLOOKUP($W61,'Category Mapping'!$C:$C,'Category Mapping'!$D:$D)),$K61))} | W61: =IF(ISBLANK($B61),"",IF(ISBLANK($L61),RIGHT($E61,LEN($E61) - FIND("^",SUBSTITUTE($E61,":","^",LEN($E61) - LEN(SUBSTITUTE($E61,":",""))))),$L61)) | X61: =IF(ISBLANK($J61),$V61&$W61,$J61) | Y61: {=IF(ISBLANK($M61),IFERROR(XLOOKUP($P61,'Department Listing'!$A:$A,'Department Listing'!$L:$L),""),$M61)} | Z61: =IF(ISBLANK($B61),"",MATCH($X61,COA!$B:$B,0))
B62: 46169 | C62: United Airlines MASTERCARD-544015XXXXXX4359-Jason Speet | D62: United Airlines | E62: 61210 Sales & Marketing:Sales & Marketing- Travel Expenses:Airfare | F62: 263.32 | O62: =IF(C62="", "", TRIM(RIGHT(C62, LEN(C62) - FIND("@@", SUBSTITUTE(C62, "-", "@@", LEN(C62) - LEN(SUBSTITUTE(C62, "-", ""))))))) | P62: {=IFERROR(XLOOKUP(O62,'Department Listing'!$O$1:$O$395,'Department Listing'!$A$1:$A$395),IFERROR(XLOOKUP(O62,'Name Aliases'!$A$2:$A$1000,'Name Aliases'!$B$2:$B$1000),""))} | Q62: =IF(ISBLANK($C62),"",$B62) | R62: =IF(ISBLANK($C62),"",IF(ISBLANK($I62),$D62,$I62)) | S62: =IF(ISBLANK($C62),"",$F62 - $G62) | T62: =IF(ISBLANK($C62),"",C62) | U62: =IF(ISBLANK($C62),"",$D$1) | V62: {=IF(ISBLANK($B62),"",IF(ISBLANK($K62),IF(XLOOKUP($W62,'Category Mapping'!$C:$C,'Category Mapping'!$B:$B)="Travel",XLOOKUP($P62,'Department Listing'!$A:$A,'Department Listing'!$M:$M),XLOOKUP($W62,'Category Mapping'!$C:$C,'Category Mapping'!$D:$D)),$K62))} | W62: =IF(ISBLANK($B62),"",IF(ISBLANK($L62),RIGHT($E62,LEN($E62) - FIND("^",SUBSTITUTE($E62,":","^",LEN($E62) - LEN(SUBSTITUTE($E62,":",""))))),$L62)) | X62: =IF(ISBLANK($J62),$V62&$W62,$J62) | Y62: {=IF(ISBLANK($M62),IFERROR(XLOOKUP($P62,'Department Listing'!$A:$A,'Department Listing'!$L:$L),""),$M62)} | Z62: =IF(ISBLANK($B62),"",MATCH($X62,COA!$B:$B,0))
B63: 46169 | C63: Allegiant Travel Co MASTERCARD-544015XXXXXX4359-Jason Speet | D63: Allianz | E63: 61290 Sales & Marketing:Sales & Marketing- Travel Expenses:Other Travel Expenses | F63: 258 | O63: =IF(C63="", "", TRIM(RIGHT(C63, LEN(C63) - FIND("@@", SUBSTITUTE(C63, "-", "@@", LEN(C63) - LEN(SUBSTITUTE(C63, "-", ""))))))) | P63: {=IFERROR(XLOOKUP(O63,'Department Listing'!$O$1:$O$395,'Department Listing'!$A$1:$A$395),IFERROR(XLOOKUP(O63,'Name Aliases'!$A$2:$A$1000,'Name Aliases'!$B$2:$B$1000),""))} | Q63: =IF(ISBLANK($C63),"",$B63) | R63: =IF(ISBLANK($C63),"",IF(ISBLANK($I63),$D63,$I63)) | S63: =IF(ISBLANK($C63),"",$F63 - $G63) | T63: =IF(ISBLANK($C63),"",C63) | U63: =IF(ISBLANK($C63),"",$D$1) | V63: {=IF(ISBLANK($B63),"",IF(ISBLANK($K63),IF(XLOOKUP($W63,'Category Mapping'!$C:$C,'Category Mapping'!$B:$B)="Travel",XLOOKUP($P63,'Department Listing'!$A:$A,'Department Listing'!$M:$M),XLOOKUP($W63,'Category Mapping'!$C:$C,'Category Mapping'!$D:$D)),$K63))} | W63: =IF(ISBLANK($B63),"",IF(ISBLANK($L63),RIGHT($E63,LEN($E63) - FIND("^",SUBSTITUTE($E63,":","^",LEN($E63) - LEN(SUBSTITUTE($E63,":",""))))),$L63)) | X63: =IF(ISBLANK($J63),$V63&$W63,$J63) | Y63: {=IF(ISBLANK($M63),IFERROR(XLOOKUP($P63,'Department Listing'!$A:$A,'Department Listing'!$L:$L),""),$M63)} | Z63: =IF(ISBLANK($B63),"",MATCH($X63,COA!$B:$B,0))
B64: 46165 | C64: JetBlue Airways MASTERCARD-544015XXXXXX7263-Brendan Nolan | D64: JetBlue | E64: 61210 Sales & Marketing:Sales & Marketing- Travel Expenses:Airfare | F64: 236.8 | O64: =IF(C64="", "", TRIM(RIGHT(C64, LEN(C64) - FIND("@@", SUBSTITUTE(C64, "-", "@@", LEN(C64) - LEN(SUBSTITUTE(C64, "-", ""))))))) | P64: {=IFERROR(XLOOKUP(O64,'Department Listing'!$O$1:$O$395,'Department Listing'!$A$1:$A$395),IFERROR(XLOOKUP(O64,'Name Aliases'!$A$2:$A$1000,'Name Aliases'!$B$2:$B$1000),""))} | Q64: =IF(ISBLANK($C64),"",$B64) | R64: =IF(ISBLANK($C64),"",IF(ISBLANK($I64),$D64,$I64)) | S64: =IF(ISBLANK($C64),"",$F64 - $G64) | T64: =IF(ISBLANK($C64),"",C64) | U64: =IF(ISBLANK($C64),"",$D$1) | V64: {=IF(ISBLANK($B64),"",IF(ISBLANK($K64),IF(XLOOKUP($W64,'Category Mapping'!$C:$C,'Category Mapping'!$B:$B)="Travel",XLOOKUP($P64,'Department Listing'!$A:$A,'Department Listing'!$M:$M),XLOOKUP($W64,'Category Mapping'!$C:$C,'Category Mapping'!$D:$D)),$K64))} | W64: =IF(ISBLANK($B64),"",IF(ISBLANK($L64),RIGHT($E64,LEN($E64) - FIND("^",SUBSTITUTE($E64,":","^",LEN($E64) - LEN(SUBSTITUTE($E64,":",""))))),$L64)) | X64: =IF(ISBLANK($J64),$V64&$W64,$J64) | Y64: {=IF(ISBLANK($M64),IFERROR(XLOOKUP($P64,'Department Listing'!$A:$A,'Department Listing'!$L:$L),""),$M64)} | Z64: =IF(ISBLANK($B64),"",MATCH($X64,COA!$B:$B,0))
B65: 46165 | C65: American MASTERCARD-544015XXXXXX2900-Chloe Brant | D65: American Airlines | E65: 61210 Sales & Marketing:Sales & Marketing- Travel Expenses:Airfare | F65: 235.4 | O65: =IF(C65="", "", TRIM(RIGHT(C65, LEN(C65) - FIND("@@", SUBSTITUTE(C65, "-", "@@", LEN(C65) - LEN(SUBSTITUTE(C65, "-", ""))))))) | P65: {=IFERROR(XLOOKUP(O65,'Department Listing'!$O$1:$O$395,'Department Listing'!$A$1:$A$395),IFERROR(XLOOKUP(O65,'Name Aliases'!$A$2:$A$1000,'Name Aliases'!$B$2:$B$1000),""))} | Q65: =IF(ISBLANK($C65),"",$B65) | R65: =IF(ISBLANK($C65),"",IF(ISBLANK($I65),$D65,$I65)) | S65: =IF(ISBLANK($C65),"",$F65 - $G65) | T65: =IF(ISBLANK($C65),"",C65) | U65: =IF(ISBLANK($C65),"",$D$1) | V65: {=IF(ISBLANK($B65),"",IF(ISBLANK($K65),IF(XLOOKUP($W65,'Category Mapping'!$C:$C,'Category Mapping'!$B:$B)="Travel",XLOOKUP($P65,'Department Listing'!$A:$A,'Department Listing'!$M:$M),XLOOKUP($W65,'Category Mapping'!$C:$C,'Category Mapping'!$D:$D)),$K65))} | W65: =IF(ISBLANK($B65),"",IF(ISBLANK($L65),RIGHT($E65,LEN($E65) - FIND("^",SUBSTITUTE($E65,":","^",LEN($E65) - LEN(SUBSTITUTE($E65,":",""))))),$L65)) | X65: =IF(ISBLANK($J65),$V65&$W65,$J65) | Y65: {=IF(ISBLANK($M65),IFERROR(XLOOKUP($P65,'Department Listing'!$A:$A,'Department Listing'!$L:$L),""),$M65)} | Z65: =IF(ISBLANK($B65),"",MATCH($X65,COA!$B:$B,0))
B66: 46170 | C66: Amtrak MASTERCARD-544015XXXXXX2900-Chloe Brant | D66: Amtrak | E66: 61220 Sales & Marketing:Sales & Marketing- Travel Expenses:Ground Transportation | F66: 218 | O66: =IF(C66="", "", TRIM(RIGHT(C66, LEN(C66) - FIND("@@", SUBSTITUTE(C66, "-", "@@", LEN(C66) - LEN(SUBSTITUTE(C66, "-", ""))))))) | P66: {=IFERROR(XLOOKUP(O66,'Department Listing'!$O$1:$O$395,'Department Listing'!$A$1:$A$395),IFERROR(XLOOKUP(O66,'Name Aliases'!$A$2:$A$1000,'Name Aliases'!$B$2:$B$1000),""))} | Q66: =IF(ISBLANK($C66),"",$B66) | R66: =IF(ISBLANK($C66),"",IF(ISBLANK($I66),$D66,$I66)) | S66: =IF(ISBLANK($C66),"",$F66 - $G66) | T66: =IF(ISBLANK($C66),"",C66) | U66: =IF(ISBLANK($C66),"",$D$1) | V66: {=IF(ISBLANK($B66),"",IF(ISBLANK($K66),IF(XLOOKUP($W66,'Category Mapping'!$C:$C,'Category Mapping'!$B:$B)="Travel",XLOOKUP($P66,'Department Listing'!$A:$A,'Department Listing'!$M:$M),XLOOKUP($W66,'Category Mapping'!$C:$C,'Category Mapping'!$D:$D)),$K66))} | W66: =IF(ISBLANK($B66),"",IF(ISBLANK($L66),RIGHT($E66,LEN($E66) - FIND("^",SUBSTITUTE($E66,":","^",LEN($E66) - LEN(SUBSTITUTE($E66,":",""))))),$L66)) | X66: =IF(ISBLANK($J66),$V66&$W66,$J66) | Y66: {=IF(ISBLANK($M66),IFERROR(XLOOKUP($P66,'Department Listing'!$A:$A,'Department Listing'!$L:$L),""),$M66)} | Z66: =IF(ISBLANK($B66),"",MATCH($X66,COA!$B:$B,0))
B67: 46169 | C67: Amazon Marketplace US MASTERCARD-544015XXXXXX7759-Mickenzi Krpec | D67: Amazon | E67: 63410 General & Administrative:Office Expenses:Office Supplies | F67: 216.85 | O67: =IF(C67="", "", TRIM(RIGHT(C67, LEN(C67) - FIND("@@", SUBSTITUTE(C67, "-", "@@", LEN(C67) - LEN(SUBSTITUTE(C67, "-", ""))))))) | P67: {=IFERROR(XLOOKUP(O67,'Department Listing'!$O$1:$O$395,'Department Listing'!$A$1:$A$395),IFERROR(XLOOKUP(O67,'Name Aliases'!$A$2:$A$1000,'Name Aliases'!$B$2:$B$1000),""))} | Q67: =IF(ISBLANK($C67),"",$B67) | R67: =IF(ISBLANK($C67),"",IF(ISBLANK($I67),$D67,$I67)) | S67: =IF(ISBLANK($C67),"",$F67 - $G67) | T67: =IF(ISBLANK($C67),"",C67) | U67: =IF(ISBLANK($C67),"",$D$1) | V67: {=IF(ISBLANK($B67),"",IF(ISBLANK($K67),IF(XLOOKUP($W67,'Category Mapping'!$C:$C,'Category Mapping'!$B:$B)="Travel",XLOOKUP($P67,'Department Listing'!$A:$A,'Department Listing'!$M:$M),XLOOKUP($W67,'Category Mapping'!$C:$C,'Category Mapping'!$D:$D)),$K67))} | W67: =IF(ISBLANK($B67),"",IF(ISBLANK($L67),RIGHT($E67,LEN($E67) - FIND("^",SUBSTITUTE($E67,":","^",LEN($E67) - LEN(SUBSTITUTE($E67,":",""))))),$L67)) | X67: =IF(ISBLANK($J67),$V67&$W67,$J67) | Y67: {=IF(ISBLANK($M67),IFERROR(XLOOKUP($P67,'Department Listing'!$A:$A,'Department Listing'!$L:$L),""),$M67)} | Z67: =IF(ISBLANK($B67),"",MATCH($X67,COA!$B:$B,0))
B68: 46169 | C68: Amazon Marketplace US MASTERCARD-544015XXXXXX7759-Mickenzi Krpec | D68: Amazon | E68: 63410 General & Administrative:Office Expenses:Office Supplies | F68: 212.73 | O68: =IF(C68="", "", TRIM(RIGHT(C68, LEN(C68) - FIND("@@", SUBSTITUTE(C68, "-", "@@", LEN(C68) - LEN(SUBSTITUTE(C68, "-", ""))))))) | P68: {=IFERROR(XLOOKUP(O68,'Department Listing'!$O$1:$O$395,'Department Listing'!$A$1:$A$395),IFERROR(XLOOKUP(O68,'Name Aliases'!$A$2:$A$1000,'Name Aliases'!$B$2:$B$1000),""))} | Q68: =IF(ISBLANK($C68),"",$B68) | R68: =IF(ISBLANK($C68),"",IF(ISBLANK($I68),$D68,$I68)) | S68: =IF(ISBLANK($C68),"",$F68 - $G68) | T68: =IF(ISBLANK($C68),"",C68) | U68: =IF(ISBLANK($C68),"",$D$1) | V68: {=IF(ISBLANK($B68),"",IF(ISBLANK($K68),IF(XLOOKUP($W68,'Category Mapping'!$C:$C,'Category Mapping'!$B:$B)="Travel",XLOOKUP($P68,'Department Listing'!$A:$A,'Department Listing'!$M:$M),XLOOKUP($W68,'Category Mapping'!$C:$C,'Category Mapping'!$D:$D)),$K68))} | W68: =IF(ISBLANK($B68),"",IF(ISBLANK($L68),RIGHT($E68,LEN($E68) - FIND("^",SUBSTITUTE($E68,":","^",LEN($E68) - LEN(SUBSTITUTE($E68,":",""))))),$L68)) | X68: =IF(ISBLANK($J68),$V68&$W68,$J68) | Y68: {=IF(ISBLANK($M68),IFERROR(XLOOKUP($P68,'Department Listing'!$A:$A,'Department Listing'!$L:$L),""),$M68)} | Z68: =IF(ISBLANK($B68),"",MATCH($X68,COA!$B:$B,0))
B69: 46168 | C69: Wegmans MASTERCARD-544015XXXXXX7759-Mickenzi Krpec | E69: 61240 Sales & Marketing:Sales & Marketing- Travel Expenses:Meals & Entertainment | F69: 166.5 | I69: Food Vendor | O69: =IF(C69="", "", TRIM(RIGHT(C69, LEN(C69) - FIND("@@", SUBSTITUTE(C69, "-", "@@", LEN(C69) - LEN(SUBSTITUTE(C69, "-", ""))))))) | P69: {=IFERROR(XLOOKUP(O69,'Department Listing'!$O$1:$O$395,'Department Listing'!$A$1:$A$395),IFERROR(XLOOKUP(O69,'Name Aliases'!$A$2:$A$1000,'Name Aliases'!$B$2:$B$1000),""))} | Q69: =IF(ISBLANK($C69),"",$B69) | R69: =IF(ISBLANK($C69),"",IF(ISBLANK($I69),$D69,$I69)) | S69: =IF(ISBLANK($C69),"",$F69 - $G69) | T69: =IF(ISBLANK($C69),"",C69) | U69: =IF(ISBLANK($C69),"",$D$1) | V69: {=IF(ISBLANK($B69),"",IF(ISBLANK($K69),IF(XLOOKUP($W69,'Category Mapping'!$C:$C,'Category Mapping'!$B:$B)="Travel",XLOOKUP($P69,'Department Listing'!$A:$A,'Department Listing'!$M:$M),XLOOKUP($W69,'Category Mapping'!$C:$C,'Category Mapping'!$D:$D)),$K69))} | W69: =IF(ISBLANK($B69),"",IF(ISBLANK($L69),RIGHT($E69,LEN($E69) - FIND("^",SUBSTITUTE($E69,":","^",LEN($E69) - LEN(SUBSTITUTE($E69,":",""))))),$L69)) | X69: =IF(ISBLANK($J69),$V69&$W69,$J69) | Y69: {=IF(ISBLANK($M69),IFERROR(XLOOKUP($P69,'Department Listing'!$A:$A,'Department Listing'!$L:$L),""),$M69)} | Z69: =IF(ISBLANK($B69),"",MATCH($X69,COA!$B:$B,0))
B70: 46164 | C70: FedEx MASTERCARD-544015XXXXXX0151-Eric Rabkin | D70: FedEx | E70: 63430 General & Administrative:Office Expenses:Shipping Expense | F70: 149.07 | O70: =IF(C70="", "", TRIM(RIGHT(C70, LEN(C70) - FIND("@@", SUBSTITUTE(C70, "-", "@@", LEN(C70) - LEN(SUBSTITUTE(C70, "-", ""))))))) | P70: {=IFERROR(XLOOKUP(O70,'Department Listing'!$O$1:$O$395,'Department Listing'!$A$1:$A$395),IFERROR(XLOOKUP(O70,'Name Aliases'!$A$2:$A$1000,'Name Aliases'!$B$2:$B$1000),""))} | Q70: =IF(ISBLANK($C70),"",$B70) | R70: =IF(ISBLANK($C70),"",IF(ISBLANK($I70),$D70,$I70)) | S70: =IF(ISBLANK($C70),"",$F70 - $G70) | T70: =IF(ISBLANK($C70),"",C70) | U70: =IF(ISBLANK($C70),"",$D$1) | V70: {=IF(ISBLANK($B70),"",IF(ISBLANK($K70),IF(XLOOKUP($W70,'Category Mapping'!$C:$C,'Category Mapping'!$B:$B)="Travel",XLOOKUP($P70,'Department Listing'!$A:$A,'Department Listing'!$M:$M),XLOOKUP($W70,'Category Mapping'!$C:$C,'Category Mapping'!$D:$D)),$K70))} | W70: =IF(ISBLANK($B70),"",IF(ISBLANK($L70),RIGHT($E70,LEN($E70) - FIND("^",SUBSTITUTE($E70,":","^",LEN($E70) - LEN(SUBSTITUTE($E70,":",""))))),$L70)) | X70: =IF(ISBLANK($J70),$V70&$W70,$J70) | Y70: {=IF(ISBLANK($M70),IFERROR(XLOOKUP($P70,'Department Listing'!$A:$A,'Department Listing'!$L:$L),""),$M70)} | Z70: =IF(ISBLANK($B70),"",MATCH($X70,COA!$B:$B,0))
B71: 46164 | C71: Presidio Golf Course Cafe MASTERCARD-544015XXXXXX2445-Tyler Grimshaw | E71: 61240 Sales & Marketing:Sales & Marketing- Travel Expenses:Meals & Entertainment | F71: 147.23 | I71: Food Vendor | O71: =IF(C71="", "", TRIM(RIGHT(C71, LEN(C71) - FIND("@@", SUBSTITUTE(C71, "-", "@@", LEN(C71) - LEN(SUBSTITUTE(C71, "-", ""))))))) | P71: {=IFERROR(XLOOKUP(O71,'Department Listing'!$O$1:$O$395,'Department Listing'!$A$1:$A$395),IFERROR(XLOOKUP(O71,'Name Aliases'!$A$2:$A$1000,'Name Aliases'!$B$2:$B$1000),""))} | Q71: =IF(ISBLANK($C71),"",$B71) | R71: =IF(ISBLANK($C71),"",IF(ISBLANK($I71),$D71,$I71)) | S71: =IF(ISBLANK($C71),"",$F71 - $G71) | T71: =IF(ISBLANK($C71),"",C71) | U71: =IF(ISBLANK($C71),"",$D$1) | V71: {=IF(ISBLANK($B71),"",IF(ISBLANK($K71),IF(XLOOKUP($W71,'Category Mapping'!$C:$C,'Category Mapping'!$B:$B)="Travel",XLOOKUP($P71,'Department Listing'!$A:$A,'Department Listing'!$M:$M),XLOOKUP($W71,'Category Mapping'!$C:$C,'Category Mapping'!$D:$D)),$K71))} | W71: =IF(ISBLANK($B71),"",IF(ISBLANK($L71),RIGHT($E71,LEN($E71) - FIND("^",SUBSTITUTE($E71,":","^",LEN($E71) - LEN(SUBSTITUTE($E71,":",""))))),$L71)) | X71: =IF(ISBLANK($J71),$V71&$W71,$J71) | Y71: {=IF(ISBLANK($M71),IFERROR(XLOOKUP($P71,'Department Listing'!$A:$A,'Department Listing'!$L:$L),""),$M71)} | Z71: =IF(ISBLANK($B71),"",MATCH($X71,COA!$B:$B,0))
B72: 46169 | C72: Amazon MASTERCARD-544015XXXXXX7759-Mickenzi Krpec | D72: Amazon | E72: 63410 General & Administrative:Office Expenses:Office Supplies | F72: 144.04 | O72: =IF(C72="", "", TRIM(RIGHT(C72, LEN(C72) - FIND("@@", SUBSTITUTE(C72, "-", "@@", LEN(C72) - LEN(SUBSTITUTE(C72, "-", ""))))))) | P72: {=IFERROR(XLOOKUP(O72,'Department Listing'!$O$1:$O$395,'Department Listing'!$A$1:$A$395),IFERROR(XLOOKUP(O72,'Name Aliases'!$A$2:$A$1000,'Name Aliases'!$B$2:$B$1000),""))} | Q72: =IF(ISBLANK($C72),"",$B72) | R72: =IF(ISBLANK($C72),"",IF(ISBLANK($I72),$D72,$I72)) | S72: =IF(ISBLANK($C72),"",$F72 - $G72) | T72: =IF(ISBLANK($C72),"",C72) | U72: =IF(ISBLANK($C72),"",$D$1) | V72: {=IF(ISBLANK($B72),"",IF(ISBLANK($K72),IF(XLOOKUP($W72,'Category Mapping'!$C:$C,'Category Mapping'!$B:$B)="Travel",XLOOKUP($P72,'Department Listing'!$A:$A,'Department Listing'!$M:$M),XLOOKUP($W72,'Category Mapping'!$C:$C,'Category Mapping'!$D:$D)),$K72))} | W72: =IF(ISBLANK($B72),"",IF(ISBLANK($L72),RIGHT($E72,LEN($E72) - FIND("^",SUBSTITUTE($E72,":","^",LEN($E72) - LEN(SUBSTITUTE($E72,":",""))))),$L72)) | X72: =IF(ISBLANK($J72),$V72&$W72,$J72) | Y72: {=IF(ISBLANK($M72),IFERROR(XLOOKUP($P72,'Department Listing'!$A:$A,'Department Listing'!$L:$L),""),$M72)} | Z72: =IF(ISBLANK($B72),"",MATCH($X72,COA!$B:$B,0))
B73: 46169 | C73: Bca Ltd* Belfast City MASTERCARD-555671XXXXXX4106-Daniel Mooney | E73: 61220 Sales & Marketing:Sales & Marketing- Travel Expenses:Ground Transportation | F73: 139.27 | I73: Travel Vendor | L73: Other Travel Expenses | O73: =IF(C73="", "", TRIM(RIGHT(C73, LEN(C73) - FIND("@@", SUBSTITUTE(C73, "-", "@@", LEN(C73) - LEN(SUBSTITUTE(C73, "-", ""))))))) | P73: {=IFERROR(XLOOKUP(O73,'Department Listing'!$O$1:$O$395,'Department Listing'!$A$1:$A$395),IFERROR(XLOOKUP(O73,'Name Aliases'!$A$2:$A$1000,'Name Aliases'!$B$2:$B$1000),""))} | Q73: =IF(ISBLANK($C73),"",$B73) | R73: =IF(ISBLANK($C73),"",IF(ISBLANK($I73),$D73,$I73)) | S73: =IF(ISBLANK($C73),"",$F73 - $G73) | T73: =IF(ISBLANK($C73),"",C73) | U73: =IF(ISBLANK($C73),"",$D$1) | V73: {=IF(ISBLANK($B73),"",IF(ISBLANK($K73),IF(XLOOKUP($W73,'Category Mapping'!$C:$C,'Category Mapping'!$B:$B)="Travel",XLOOKUP($P73,'Department Listing'!$A:$A,'Department Listing'!$M:$M),XLOOKUP($W73,'Category Mapping'!$C:$C,'Category Mapping'!$D:$D)),$K73))} | W73: =IF(ISBLANK($B73),"",IF(ISBLANK($L73),RIGHT($E73,LEN($E73) - FIND("^",SUBSTITUTE($E73,":","^",LEN($E73) - LEN(SUBSTITUTE($E73,":",""))))),$L73)) | X73: =IF(ISBLANK($J73),$V73&$W73,$J73) | Y73: {=IF(ISBLANK($M73),IFERROR(XLOOKUP($P73,'Department Listing'!$A:$A,'Department Listing'!$L:$L),""),$M73)} | Z73: =IF(ISBLANK($B73),"",MATCH($X73,COA!$B:$B,0))
B74: 46168 | C74: Vistaprint MASTERCARD-544015XXXXXX0918-Brooke Berg | D74: VistaPrint | E74: 61190 Sales & Marketing:Marketing Expenses:Other Marketing Expenses | F74: 139.16 | O74: =IF(C74="", "", TRIM(RIGHT(C74, LEN(C74) - FIND("@@", SUBSTITUTE(C74, "-", "@@", LEN(C74) - LEN(SUBSTITUTE(C74, "-", ""))))))) | P74: {=IFERROR(XLOOKUP(O74,'Department Listing'!$O$1:$O$395,'Department Listing'!$A$1:$A$395),IFERROR(XLOOKUP(O74,'Name Aliases'!$A$2:$A$1000,'Name Aliases'!$B$2:$B$1000),""))} | Q74: =IF(ISBLANK($C74),"",$B74) | R74: =IF(ISBLANK($C74),"",IF(ISBLANK($I74),$D74,$I74)) | S74: =IF(ISBLANK($C74),"",$F74 - $G74) | T74: =IF(ISBLANK($C74),"",C74) | U74: =IF(ISBLANK($C74),"",$D$1) | V74: {=IF(ISBLANK($B74),"",IF(ISBLANK($K74),IF(XLOOKUP($W74,'Category Mapping'!$C:$C,'Category Mapping'!$B:$B)="Travel",XLOOKUP($P74,'Department Listing'!$A:$A,'Department Listing'!$M:$M),XLOOKUP($W74,'Category Mapping'!$C:$C,'Category Mapping'!$D:$D)),$K74))} | W74: =IF(ISBLANK($B74),"",IF(ISBLANK($L74),RIGHT($E74,LEN($E74) - FIND("^",SUBSTITUTE($E74,":","^",LEN($E74) - LEN(SUBSTITUTE($E74,":",""))))),$L74)) | X74: =IF(ISBLANK($J74),$V74&$W74,$J74) | Y74: {=IF(ISBLANK($M74),IFERROR(XLOOKUP($P74,'Department Listing'!$A:$A,'Department Listing'!$L:$L),""),$M74)} | Z74: =IF(ISBLANK($B74),"",MATCH($X74,COA!$B:$B,0))
B75: 46169 | C75: Uber HQ MASTERCARD-544015XXXXXX8678-John Taylor | D75: Uber | E75: 61220 Sales & Marketing:Sales & Marketing- Travel Expenses:Ground Transportation | F75: 105.93 | O75: =IF(C75="", "", TRIM(RIGHT(C75, LEN(C75) - FIND("@@", SUBSTITUTE(C75, "-", "@@", LEN(C75) - LEN(SUBSTITUTE(C75, "-", ""))))))) | P75: {=IFERROR(XLOOKUP(O75,'Department Listing'!$O$1:$O$395,'Department Listing'!$A$1:$A$395),IFERROR(XLOOKUP(O75,'Name Aliases'!$A$2:$A$1000,'Name Aliases'!$B$2:$B$1000),""))} | Q75: =IF(ISBLANK($C75),"",$B75) | R75: =IF(ISBLANK($C75),"",IF(ISBLANK($I75),$D75,$I75)) | S75: =IF(ISBLANK($C75),"",$F75 - $G75) | T75: =IF(ISBLANK($C75),"",C75) | U75: =IF(ISBLANK($C75),"",$D$1) | V75: {=IF(ISBLANK($B75),"",IF(ISBLANK($K75),IF(XLOOKUP($W75,'Category Mapping'!$C:$C,'Category Mapping'!$B:$B)="Travel",XLOOKUP($P75,'Department Listing'!$A:$A,'Department Listing'!$M:$M),XLOOKUP($W75,'Category Mapping'!$C:$C,'Category Mapping'!$D:$D)),$K75))} | W75: =IF(ISBLANK($B75),"",IF(ISBLANK($L75),RIGHT($E75,LEN($E75) - FIND("^",SUBSTITUTE($E75,":","^",LEN($E75) - LEN(SUBSTITUTE($E75,":",""))))),$L75)) | X75: =IF(ISBLANK($J75),$V75&$W75,$J75) | Y75: {=IF(ISBLANK($M75),IFERROR(XLOOKUP($P75,'Department Listing'!$A:$A,'Department Listing'!$L:$L),""),$M75)} | Z75: =IF(ISBLANK($B75),"",MATCH($X75,COA!$B:$B,0))
B76: 46170 | C76: Amazon Marketplace US MASTERCARD-544015XXXXXX8091-Brooke Berg | D76: Amazon | E76: 63410 General & Administrative:Office Expenses:Office Supplies | F76: 97.72 | O76: =IF(C76="", "", TRIM(RIGHT(C76, LEN(C76) - FIND("@@", SUBSTITUTE(C76, "-", "@@", LEN(C76) - LEN(SUBSTITUTE(C76, "-", ""))))))) | P76: {=IFERROR(XLOOKUP(O76,'Department Listing'!$O$1:$O$395,'Department Listing'!$A$1:$A$395),IFERROR(XLOOKUP(O76,'Name Aliases'!$A$2:$A$1000,'Name Aliases'!$B$2:$B$1000),""))} | Q76: =IF(ISBLANK($C76),"",$B76) | R76: =IF(ISBLANK($C76),"",IF(ISBLANK($I76),$D76,$I76)) | S76: =IF(ISBLANK($C76),"",$F76 - $G76) | T76: =IF(ISBLANK($C76),"",C76) | U76: =IF(ISBLANK($C76),"",$D$1) | V76: {=IF(ISBLANK($B76),"",IF(ISBLANK($K76),IF(XLOOKUP($W76,'Category Mapping'!$C:$C,'Category Mapping'!$B:$B)="Travel",XLOOKUP($P76,'Department Listing'!$A:$A,'Department Listing'!$M:$M),XLOOKUP($W76,'Category Mapping'!$C:$C,'Category Mapping'!$D:$D)),$K76))} | W76: =IF(ISBLANK($B76),"",IF(ISBLANK($L76),RIGHT($E76,LEN($E76) - FIND("^",SUBSTITUTE($E76,":","^",LEN($E76) - LEN(SUBSTITUTE($E76,":",""))))),$L76)) | X76: =IF(ISBLANK($J76),$V76&$W76,$J76) | Y76: {=IF(ISBLANK($M76),IFERROR(XLOOKUP($P76,'Department Listing'!$A:$A,'Department Listing'!$L:$L),""),$M76)} | Z76: =IF(ISBLANK($B76),"",MATCH($X76,COA!$B:$B,0))
B77: 46169 | C77: Uber HQ MASTERCARD-544015XXXXXX9350-Gary Passaglia | D77: Uber | E77: 61220 Sales & Marketing:Sales & Marketing- Travel Expenses:Ground Transportation | F77: 89.09 | O77: =IF(C77="", "", TRIM(RIGHT(C77, LEN(C77) - FIND("@@", SUBSTITUTE(C77, "-", "@@", LEN(C77) - LEN(SUBSTITUTE(C77, "-", ""))))))) | P77: {=IFERROR(XLOOKUP(O77,'Department Listing'!$O$1:$O$395,'Department Listing'!$A$1:$A$395),IFERROR(XLOOKUP(O77,'Name Aliases'!$A$2:$A$1000,'Name Aliases'!$B$2:$B$1000),""))} | Q77: =IF(ISBLANK($C77),"",$B77) | R77: =IF(ISBLANK($C77),"",IF(ISBLANK($I77),$D77,$I77)) | S77: =IF(ISBLANK($C77),"",$F77 - $G77) | T77: =IF(ISBLANK($C77),"",C77) | U77: =IF(ISBLANK($C77),"",$D$1) | V77: {=IF(ISBLANK($B77),"",IF(ISBLANK($K77),IF(XLOOKUP($W77,'Category Mapping'!$C:$C,'Category Mapping'!$B:$B)="Travel",XLOOKUP($P77,'Department Listing'!$A:$A,'Department Listing'!$M:$M),XLOOKUP($W77,'Category Mapping'!$C:$C,'Category Mapping'!$D:$D)),$K77))} | W77: =IF(ISBLANK($B77),"",IF(ISBLANK($L77),RIGHT($E77,LEN($E77) - FIND("^",SUBSTITUTE($E77,":","^",LEN($E77) - LEN(SUBSTITUTE($E77,":",""))))),$L77)) | X77: =IF(ISBLANK($J77),$V77&$W77,$J77) | Y77: {=IF(ISBLANK($M77),IFERROR(XLOOKUP($P77,'Department Listing'!$A:$A,'Department Listing'!$L:$L),""),$M77)} | Z77: =IF(ISBLANK($B77),"",MATCH($X77,COA!$B:$B,0))
B78: 46169 | C78: PKL Boston MASTERCARD-555671XXXXXX3587-Pooja Manjeshwar | D78: PKL Boston | E78: 61240 Sales & Marketing:Sales & Marketing- Travel Expenses:Meals & Entertainment | F78: 80 | O78: =IF(C78="", "", TRIM(RIGHT(C78, LEN(C78) - FIND("@@", SUBSTITUTE(C78, "-", "@@", LEN(C78) - LEN(SUBSTITUTE(C78, "-", ""))))))) | P78: {=IFERROR(XLOOKUP(O78,'Department Listing'!$O$1:$O$395,'Department Listing'!$A$1:$A$395),IFERROR(XLOOKUP(O78,'Name Aliases'!$A$2:$A$1000,'Name Aliases'!$B$2:$B$1000),""))} | Q78: =IF(ISBLANK($C78),"",$B78) | R78: =IF(ISBLANK($C78),"",IF(ISBLANK($I78),$D78,$I78)) | S78: =IF(ISBLANK($C78),"",$F78 - $G78) | T78: =IF(ISBLANK($C78),"",C78) | U78: =IF(ISBLANK($C78),"",$D$1) | V78: {=IF(ISBLANK($B78),"",IF(ISBLANK($K78),IF(XLOOKUP($W78,'Category Mapping'!$C:$C,'Category Mapping'!$B:$B)="Travel",XLOOKUP($P78,'Department Listing'!$A:$A,'Department Listing'!$M:$M),XLOOKUP($W78,'Category Mapping'!$C:$C,'Category Mapping'!$D:$D)),$K78))} | W78: =IF(ISBLANK($B78),"",IF(ISBLANK($L78),RIGHT($E78,LEN($E78) - FIND("^",SUBSTITUTE($E78,":","^",LEN($E78) - LEN(SUBSTITUTE($E78,":",""))))),$L78)) | X78: =IF(ISBLANK($J78),$V78&$W78,$J78) | Y78: {=IF(ISBLANK($M78),IFERROR(XLOOKUP($P78,'Department Listing'!$A:$A,'Department Listing'!$L:$L),""),$M78)} | Z78: =IF(ISBLANK($B78),"",MATCH($X78,COA!$B:$B,0))
B79: 46169 | C79: PKL Boston MASTERCARD-555671XXXXXX3587-Pooja Manjeshwar | D79: PKL Boston | E79: 61240 Sales & Marketing:Sales & Marketing- Travel Expenses:Meals & Entertainment | F79: 80 | O79: =IF(C79="", "", TRIM(RIGHT(C79, LEN(C79) - FIND("@@", SUBSTITUTE(C79, "-", "@@", LEN(C79) - LEN(SUBSTITUTE(C79, "-", ""))))))) | P79: {=IFERROR(XLOOKUP(O79,'Department Listing'!$O$1:$O$395,'Department Listing'!$A$1:$A$395),IFERROR(XLOOKUP(O79,'Name Aliases'!$A$2:$A$1000,'Name Aliases'!$B$2:$B$1000),""))} | Q79: =IF(ISBLANK($C79),"",$B79) | R79: =IF(ISBLANK($C79),"",IF(ISBLANK($I79),$D79,$I79)) | S79: =IF(ISBLANK($C79),"",$F79 - $G79) | T79: =IF(ISBLANK($C79),"",C79) | U79: =IF(ISBLANK($C79),"",$D$1) | V79: {=IF(ISBLANK($B79),"",IF(ISBLANK($K79),IF(XLOOKUP($W79,'Category Mapping'!$C:$C,'Category Mapping'!$B:$B)="Travel",XLOOKUP($P79,'Department Listing'!$A:$A,'Department Listing'!$M:$M),XLOOKUP($W79,'Category Mapping'!$C:$C,'Category Mapping'!$D:$D)),$K79))} | W79: =IF(ISBLANK($B79),"",IF(ISBLANK($L79),RIGHT($E79,LEN($E79) - FIND("^",SUBSTITUTE($E79,":","^",LEN($E79) - LEN(SUBSTITUTE($E79,":",""))))),$L79)) | X79: =IF(ISBLANK($J79),$V79&$W79,$J79) | Y79: {=IF(ISBLANK($M79),IFERROR(XLOOKUP($P79,'Department Listing'!$A:$A,'Department Listing'!$L:$L),""),$M79)} | Z79: =IF(ISBLANK($B79),"",MATCH($X79,COA!$B:$B,0))
B80: 46164 | C80: Presidio Golf Course Cafe MASTERCARD-544015XXXXXX2445-Tyler Grimshaw | E80: 61240 Sales & Marketing:Sales & Marketing- Travel Expenses:Meals & Entertainment | F80: 79.12 | I80: Food Vendor | O80: =IF(C80="", "", TRIM(RIGHT(C80, LEN(C80) - FIND("@@", SUBSTITUTE(C80, "-", "@@", LEN(C80) - LEN(SUBSTITUTE(C80, "-", ""))))))) | P80: {=IFERROR(XLOOKUP(O80,'Department Listing'!$O$1:$O$395,'Department Listing'!$A$1:$A$395),IFERROR(XLOOKUP(O80,'Name Aliases'!$A$2:$A$1000,'Name Aliases'!$B$2:$B$1000),""))} | Q80: =IF(ISBLANK($C80),"",$B80) | R80: =IF(ISBLANK($C80),"",IF(ISBLANK($I80),$D80,$I80)) | S80: =IF(ISBLANK($C80),"",$F80 - $G80) | T80: =IF(ISBLANK($C80),"",C80) | U80: =IF(ISBLANK($C80),"",$D$1) | V80: {=IF(ISBLANK($B80),"",IF(ISBLANK($K80),IF(XLOOKUP($W80,'Category Mapping'!$C:$C,'Category Mapping'!$B:$B)="Travel",XLOOKUP($P80,'Department Listing'!$A:$A,'Department Listing'!$M:$M),XLOOKUP($W80,'Category Mapping'!$C:$C,'Category Mapping'!$D:$D)),$K80))} | W80: =IF(ISBLANK($B80),"",IF(ISBLANK($L80),RIGHT($E80,LEN($E80) - FIND("^",SUBSTITUTE($E80,":","^",LEN($E80) - LEN(SUBSTITUTE($E80,":",""))))),$L80)) | X80: =IF(ISBLANK($J80),$V80&$W80,$J80) | Y80: {=IF(ISBLANK($M80),IFERROR(XLOOKUP($P80,'Department Listing'!$A:$A,'Department Listing'!$L:$L),""),$M80)} | Z80: =IF(ISBLANK($B80),"",MATCH($X80,COA!$B:$B,0))
B81: 46170 | C81: Grand Central Oyster Bar MASTERCARD-544015XXXXXX2900-Chloe Brant | E81: 61240 Sales & Marketing:Sales & Marketing- Travel Expenses:Meals & Entertainment | F81: 71.34 | I81: Food Vendor | O81: =IF(C81="", "", TRIM(RIGHT(C81, LEN(C81) - FIND("@@", SUBSTITUTE(C81, "-", "@@", LEN(C81) - LEN(SUBSTITUTE(C81, "-", ""))))))) | P81: {=IFERROR(XLOOKUP(O81,'Department Listing'!$O$1:$O$395,'Department Listing'!$A$1:$A$395),IFERROR(XLOOKUP(O81,'Name Aliases'!$A$2:$A$1000,'Name Aliases'!$B$2:$B$1000),""))} | Q81: =IF(ISBLANK($C81),"",$B81) | R81: =IF(ISBLANK($C81),"",IF(ISBLANK($I81),$D81,$I81)) | S81: =IF(ISBLANK($C81),"",$F81 - $G81) | T81: =IF(ISBLANK($C81),"",C81) | U81: =IF(ISBLANK($C81),"",$D$1) | V81: {=IF(ISBLANK($B81),"",IF(ISBLANK($K81),IF(XLOOKUP($W81,'Category Mapping'!$C:$C,'Category Mapping'!$B:$B)="Travel",XLOOKUP($P81,'Department Listing'!$A:$A,'Department Listing'!$M:$M),XLOOKUP($W81,'Category Mapping'!$C:$C,'Category Mapping'!$D:$D)),$K81))} | W81: =IF(ISBLANK($B81),"",IF(ISBLANK($L81),RIGHT($E81,LEN($E81) - FIND("^",SUBSTITUTE($E81,":","^",LEN($E81) - LEN(SUBSTITUTE($E81,":",""))))),$L81)) | X81: =IF(ISBLANK($J81),$V81&$W81,$J81) | Y81: {=IF(ISBLANK($M81),IFERROR(XLOOKUP($P81,'Department Listing'!$A:$A,'Department Listing'!$L:$L),""),$M81)} | Z81: =IF(ISBLANK($B81),"",MATCH($X81,COA!$B:$B,0))
B82: 46164 | C82: Lyft MASTERCARD-544015XXXXXX7759-Mickenzi Krpec | D82: Lyft | E82: 61220 Sales & Marketing:Sales & Marketing- Travel Expenses:Ground Transportation | F82: 68.28 | O82: =IF(C82="", "", TRIM(RIGHT(C82, LEN(C82) - FIND("@@", SUBSTITUTE(C82, "-", "@@", LEN(C82) - LEN(SUBSTITUTE(C82, "-", ""))))))) | P82: {=IFERROR(XLOOKUP(O82,'Department Listing'!$O$1:$O$395,'Department Listing'!$A$1:$A$395),IFERROR(XLOOKUP(O82,'Name Aliases'!$A$2:$A$1000,'Name Aliases'!$B$2:$B$1000),""))} | Q82: =IF(ISBLANK($C82),"",$B82) | R82: =IF(ISBLANK($C82),"",IF(ISBLANK($I82),$D82,$I82)) | S82: =IF(ISBLANK($C82),"",$F82 - $G82) | T82: =IF(ISBLANK($C82),"",C82) | U82: =IF(ISBLANK($C82),"",$D$1) | V82: {=IF(ISBLANK($B82),"",IF(ISBLANK($K82),IF(XLOOKUP($W82,'Category Mapping'!$C:$C,'Category Mapping'!$B:$B)="Travel",XLOOKUP($P82,'Department Listing'!$A:$A,'Department Listing'!$M:$M),XLOOKUP($W82,'Category Mapping'!$C:$C,'Category Mapping'!$D:$D)),$K82))} | W82: =IF(ISBLANK($B82),"",IF(ISBLANK($L82),RIGHT($E82,LEN($E82) - FIND("^",SUBSTITUTE($E82,":","^",LEN($E82) - LEN(SUBSTITUTE($E82,":",""))))),$L82)) | X82: =IF(ISBLANK($J82),$V82&$W82,$J82) | Y82: {=IF(ISBLANK($M82),IFERROR(XLOOKUP($P82,'Department Listing'!$A:$A,'Department Listing'!$L:$L),""),$M82)} | Z82: =IF(ISBLANK($B82),"",MATCH($X82,COA!$B:$B,0))
B83: 46168 | C83: Uber Eats MASTERCARD-544015XXXXXX2900-Chloe Brant | D83: Uber Eats | E83: 61240 Sales & Marketing:Sales & Marketing- Travel Expenses:Meals & Entertainment | F83: 63.41 | O83: =IF(C83="", "", TRIM(RIGHT(C83, LEN(C83) - FIND("@@", SUBSTITUTE(C83, "-", "@@", LEN(C83) - LEN(SUBSTITUTE(C83, "-", ""))))))) | P83: {=IFERROR(XLOOKUP(O83,'Department Listing'!$O$1:$O$395,'Department Listing'!$A$1:$A$395),IFERROR(XLOOKUP(O83,'Name Aliases'!$A$2:$A$1000,'Name Aliases'!$B$2:$B$1000),""))} | Q83: =IF(ISBLANK($C83),"",$B83) | R83: =IF(ISBLANK($C83),"",IF(ISBLANK($I83),$D83,$I83)) | S83: =IF(ISBLANK($C83),"",$F83 - $G83) | T83: =IF(ISBLANK($C83),"",C83) | U83: =IF(ISBLANK($C83),"",$D$1) | V83: {=IF(ISBLANK($B83),"",IF(ISBLANK($K83),IF(XLOOKUP($W83,'Category Mapping'!$C:$C,'Category Mapping'!$B:$B)="Travel",XLOOKUP($P83,'Department Listing'!$A:$A,'Department Listing'!$M:$M),XLOOKUP($W83,'Category Mapping'!$C:$C,'Category Mapping'!$D:$D)),$K83))} | W83: =IF(ISBLANK($B83),"",IF(ISBLANK($L83),RIGHT($E83,LEN($E83) - FIND("^",SUBSTITUTE($E83,":","^",LEN($E83) - LEN(SUBSTITUTE($E83,":",""))))),$L83)) | X83: =IF(ISBLANK($J83),$V83&$W83,$J83) | Y83: {=IF(ISBLANK($M83),IFERROR(XLOOKUP($P83,'Department Listing'!$A:$A,'Department Listing'!$L:$L),""),$M83)} | Z83: =IF(ISBLANK($B83),"",MATCH($X83,COA!$B:$B,0))
B84: 46169 | C84: Amazon MASTERCARD-544015XXXXXX8091-Brooke Berg | D84: Amazon | E84: 63410 General & Administrative:Office Expenses:Office Supplies | F84: 59.93 | O84: =IF(C84="", "", TRIM(RIGHT(C84, LEN(C84) - FIND("@@", SUBSTITUTE(C84, "-", "@@", LEN(C84) - LEN(SUBSTITUTE(C84, "-", ""))))))) | P84: {=IFERROR(XLOOKUP(O84,'Department Listing'!$O$1:$O$395,'Department Listing'!$A$1:$A$395),IFERROR(XLOOKUP(O84,'Name Aliases'!$A$2:$A$1000,'Name Aliases'!$B$2:$B$1000),""))} | Q84: =IF(ISBLANK($C84),"",$B84) | R84: =IF(ISBLANK($C84),"",IF(ISBLANK($I84),$D84,$I84)) | S84: =IF(ISBLANK($C84),"",$F84 - $G84) | T84: =IF(ISBLANK($C84),"",C84) | U84: =IF(ISBLANK($C84),"",$D$1) | V84: {=IF(ISBLANK($B84),"",IF(ISBLANK($K84),IF(XLOOKUP($W84,'Category Mapping'!$C:$C,'Category Mapping'!$B:$B)="Travel",XLOOKUP($P84,'Department Listing'!$A:$A,'Department Listing'!$M:$M),XLOOKUP($W84,'Category Mapping'!$C:$C,'Category Mapping'!$D:$D)),$K84))} | W84: =IF(ISBLANK($B84),"",IF(ISBLANK($L84),RIGHT($E84,LEN($E84) - FIND("^",SUBSTITUTE($E84,":","^",LEN($E84) - LEN(SUBSTITUTE($E84,":",""))))),$L84)) | X84: =IF(ISBLANK($J84),$V84&$W84,$J84) | Y84: {=IF(ISBLANK($M84),IFERROR(XLOOKUP($P84,'Department Listing'!$A:$A,'Department Listing'!$L:$L),""),$M84)} | Z84: =IF(ISBLANK($B84),"",MATCH($X84,COA!$B:$B,0))
B85: 46169 | C85: Taxi MASTERCARD-544015XXXXXX0424-Dwight Henderson | D85: Taxi Vendor | E85: 61220 Sales & Marketing:Sales & Marketing- Travel Expenses:Ground Transportation | F85: 59.86 | O85: =IF(C85="", "", TRIM(RIGHT(C85, LEN(C85) - FIND("@@", SUBSTITUTE(C85, "-", "@@", LEN(C85) - LEN(SUBSTITUTE(C85, "-", ""))))))) | P85: {=IFERROR(XLOOKUP(O85,'Department Listing'!$O$1:$O$395,'Department Listing'!$A$1:$A$395),IFERROR(XLOOKUP(O85,'Name Aliases'!$A$2:$A$1000,'Name Aliases'!$B$2:$B$1000),""))} | Q85: =IF(ISBLANK($C85),"",$B85) | R85: =IF(ISBLANK($C85),"",IF(ISBLANK($I85),$D85,$I85)) | S85: =IF(ISBLANK($C85),"",$F85 - $G85) | T85: =IF(ISBLANK($C85),"",C85) | U85: =IF(ISBLANK($C85),"",$D$1) | V85: {=IF(ISBLANK($B85),"",IF(ISBLANK($K85),IF(XLOOKUP($W85,'Category Mapping'!$C:$C,'Category Mapping'!$B:$B)="Travel",XLOOKUP($P85,'Department Listing'!$A:$A,'Department Listing'!$M:$M),XLOOKUP($W85,'Category Mapping'!$C:$C,'Category Mapping'!$D:$D)),$K85))} | W85: =IF(ISBLANK($B85),"",IF(ISBLANK($L85),RIGHT($E85,LEN($E85) - FIND("^",SUBSTITUTE($E85,":","^",LEN($E85) - LEN(SUBSTITUTE($E85,":",""))))),$L85)) | X85: =IF(ISBLANK($J85),$V85&$W85,$J85) | Y85: {=IF(ISBLANK($M85),IFERROR(XLOOKUP($P85,'Department Listing'!$A:$A,'Department Listing'!$L:$L),""),$M85)} | Z85: =IF(ISBLANK($B85),"",MATCH($X85,COA!$B:$B,0))
B86: 46170 | C86: Amazon Marketplace US MASTERCARD-544015XXXXXX8091-Brooke Berg | D86: Amazon | E86: 63410 General & Administrative:Office Expenses:Office Supplies | F86: 52.04 | O86: =IF(C86="", "", TRIM(RIGHT(C86, LEN(C86) - FIND("@@", SUBSTITUTE(C86, "-", "@@", LEN(C86) - LEN(SUBSTITUTE(C86, "-", ""))))))) | P86: {=IFERROR(XLOOKUP(O86,'Department Listing'!$O$1:$O$395,'Department Listing'!$A$1:$A$395),IFERROR(XLOOKUP(O86,'Name Aliases'!$A$2:$A$1000,'Name Aliases'!$B$2:$B$1000),""))} | Q86: =IF(ISBLANK($C86),"",$B86) | R86: =IF(ISBLANK($C86),"",IF(ISBLANK($I86),$D86,$I86)) | S86: =IF(ISBLANK($C86),"",$F86 - $G86) | T86: =IF(ISBLANK($C86),"",C86) | U86: =IF(ISBLANK($C86),"",$D$1) | V86: {=IF(ISBLANK($B86),"",IF(ISBLANK($K86),IF(XLOOKUP($W86,'Category Mapping'!$C:$C,'Category Mapping'!$B:$B)="Travel",XLOOKUP($P86,'Department Listing'!$A:$A,'Department Listing'!$M:$M),XLOOKUP($W86,'Category Mapping'!$C:$C,'Category Mapping'!$D:$D)),$K86))} | W86: =IF(ISBLANK($B86),"",IF(ISBLANK($L86),RIGHT($E86,LEN($E86) - FIND("^",SUBSTITUTE($E86,":","^",LEN($E86) - LEN(SUBSTITUTE($E86,":",""))))),$L86)) | X86: =IF(ISBLANK($J86),$V86&$W86,$J86) | Y86: {=IF(ISBLANK($M86),IFERROR(XLOOKUP($P86,'Department Listing'!$A:$A,'Department Listing'!$L:$L),""),$M86)} | Z86: =IF(ISBLANK($B86),"",MATCH($X86,COA!$B:$B,0))
B87: 46169 | C87: Amazon Marketplace US MASTERCARD-544015XXXXXX7759-Mickenzi Krpec | D87: Amazon | E87: 63410 General & Administrative:Office Expenses:Office Supplies | F87: 50.97 | O87: =IF(C87="", "", TRIM(RIGHT(C87, LEN(C87) - FIND("@@", SUBSTITUTE(C87, "-", "@@", LEN(C87) - LEN(SUBSTITUTE(C87, "-", ""))))))) | P87: {=IFERROR(XLOOKUP(O87,'Department Listing'!$O$1:$O$395,'Department Listing'!$A$1:$A$395),IFERROR(XLOOKUP(O87,'Name Aliases'!$A$2:$A$1000,'Name Aliases'!$B$2:$B$1000),""))} | Q87: =IF(ISBLANK($C87),"",$B87) | R87: =IF(ISBLANK($C87),"",IF(ISBLANK($I87),$D87,$I87)) | S87: =IF(ISBLANK($C87),"",$F87 - $G87) | T87: =IF(ISBLANK($C87),"",C87) | U87: =IF(ISBLANK($C87),"",$D$1) | V87: {=IF(ISBLANK($B87),"",IF(ISBLANK($K87),IF(XLOOKUP($W87,'Category Mapping'!$C:$C,'Category Mapping'!$B:$B)="Travel",XLOOKUP($P87,'Department Listing'!$A:$A,'Department Listing'!$M:$M),XLOOKUP($W87,'Category Mapping'!$C:$C,'Category Mapping'!$D:$D)),$K87))} | W87: =IF(ISBLANK($B87),"",IF(ISBLANK($L87),RIGHT($E87,LEN($E87) - FIND("^",SUBSTITUTE($E87,":","^",LEN($E87) - LEN(SUBSTITUTE($E87,":",""))))),$L87)) | X87: =IF(ISBLANK($J87),$V87&$W87,$J87) | Y87: {=IF(ISBLANK($M87),IFERROR(XLOOKUP($P87,'Department Listing'!$A:$A,'Department Listing'!$L:$L),""),$M87)} | Z87: =IF(ISBLANK($B87),"",MATCH($X87,COA!$B:$B,0))
B88: 46167 | C88: Lyft MASTERCARD-544015XXXXXX8601-Heidebritta Frank | D88: Lyft | E88: 61220 Sales & Marketing:Sales & Marketing- Travel Expenses:Ground Transportation | F88: 49.91 | O88: =IF(C88="", "", TRIM(RIGHT(C88, LEN(C88) - FIND("@@", SUBSTITUTE(C88, "-", "@@", LEN(C88) - LEN(SUBSTITUTE(C88, "-", ""))))))) | P88: {=IFERROR(XLOOKUP(O88,'Department Listing'!$O$1:$O$395,'Department Listing'!$A$1:$A$395),IFERROR(XLOOKUP(O88,'Name Aliases'!$A$2:$A$1000,'Name Aliases'!$B$2:$B$1000),""))} | Q88: =IF(ISBLANK($C88),"",$B88) | R88: =IF(ISBLANK($C88),"",IF(ISBLANK($I88),$D88,$I88)) | S88: =IF(ISBLANK($C88),"",$F88 - $G88) | T88: =IF(ISBLANK($C88),"",C88) | U88: =IF(ISBLANK($C88),"",$D$1) | V88: {=IF(ISBLANK($B88),"",IF(ISBLANK($K88),IF(XLOOKUP($W88,'Category Mapping'!$C:$C,'Category Mapping'!$B:$B)="Travel",XLOOKUP($P88,'Department Listing'!$A:$A,'Department Listing'!$M:$M),XLOOKUP($W88,'Category Mapping'!$C:$C,'Category Mapping'!$D:$D)),$K88))} | W88: =IF(ISBLANK($B88),"",IF(ISBLANK($L88),RIGHT($E88,LEN($E88) - FIND("^",SUBSTITUTE($E88,":","^",LEN($E88) - LEN(SUBSTITUTE($E88,":",""))))),$L88)) | X88: =IF(ISBLANK($J88),$V88&$W88,$J88) | Y88: {=IF(ISBLANK($M88),IFERROR(XLOOKUP($P88,'Department Listing'!$A:$A,'Department Listing'!$L:$L),""),$M88)} | Z88: =IF(ISBLANK($B88),"",MATCH($X88,COA!$B:$B,0))
B89: 46168 | C89: Amazon Marketplace US MASTERCARD-544015XXXXXX7759-Mickenzi Krpec | D89: Amazon | E89: 63410 General & Administrative:Office Expenses:Office Supplies | F89: 45.35 | O89: =IF(C89="", "", TRIM(RIGHT(C89, LEN(C89) - FIND("@@", SUBSTITUTE(C89, "-", "@@", LEN(C89) - LEN(SUBSTITUTE(C89, "-", ""))))))) | P89: {=IFERROR(XLOOKUP(O89,'Department Listing'!$O$1:$O$395,'Department Listing'!$A$1:$A$395),IFERROR(XLOOKUP(O89,'Name Aliases'!$A$2:$A$1000,'Name Aliases'!$B$2:$B$1000),""))} | Q89: =IF(ISBLANK($C89),"",$B89) | R89: =IF(ISBLANK($C89),"",IF(ISBLANK($I89),$D89,$I89)) | S89: =IF(ISBLANK($C89),"",$F89 - $G89) | T89: =IF(ISBLANK($C89),"",C89) | U89: =IF(ISBLANK($C89),"",$D$1) | V89: {=IF(ISBLANK($B89),"",IF(ISBLANK($K89),IF(XLOOKUP($W89,'Category Mapping'!$C:$C,'Category Mapping'!$B:$B)="Travel",XLOOKUP($P89,'Department Listing'!$A:$A,'Department Listing'!$M:$M),XLOOKUP($W89,'Category Mapping'!$C:$C,'Category Mapping'!$D:$D)),$K89))} | W89: =IF(ISBLANK($B89),"",IF(ISBLANK($L89),RIGHT($E89,LEN($E89) - FIND("^",SUBSTITUTE($E89,":","^",LEN($E89) - LEN(SUBSTITUTE($E89,":",""))))),$L89)) | X89: =IF(ISBLANK($J89),$V89&$W89,$J89) | Y89: {=IF(ISBLANK($M89),IFERROR(XLOOKUP($P89,'Department Listing'!$A:$A,'Department Listing'!$L:$L),""),$M89)} | Z89: =IF(ISBLANK($B89),"",MATCH($X89,COA!$B:$B,0))
B90: 46164 | C90: Presidio Golf Course Cafe MASTERCARD-544015XXXXXX2445-Tyler Grimshaw | E90: 61240 Sales & Marketing:Sales & Marketing- Travel Expenses:Meals & Entertainment | F90: 44.84 | I90: Food Vendor | O90: =IF(C90="", "", TRIM(RIGHT(C90, LEN(C90) - FIND("@@", SUBSTITUTE(C90, "-", "@@", LEN(C90) - LEN(SUBSTITUTE(C90, "-", ""))))))) | P90: {=IFERROR(XLOOKUP(O90,'Department Listing'!$O$1:$O$395,'Department Listing'!$A$1:$A$395),IFERROR(XLOOKUP(O90,'Name Aliases'!$A$2:$A$1000,'Name Aliases'!$B$2:$B$1000),""))} | Q90: =IF(ISBLANK($C90),"",$B90) | R90: =IF(ISBLANK($C90),"",IF(ISBLANK($I90),$D90,$I90)) | S90: =IF(ISBLANK($C90),"",$F90 - $G90) | T90: =IF(ISBLANK($C90),"",C90) | U90: =IF(ISBLANK($C90),"",$D$1) | V90: {=IF(ISBLANK($B90),"",IF(ISBLANK($K90),IF(XLOOKUP($W90,'Category Mapping'!$C:$C,'Category Mapping'!$B:$B)="Travel",XLOOKUP($P90,'Department Listing'!$A:$A,'Department Listing'!$M:$M),XLOOKUP($W90,'Category Mapping'!$C:$C,'Category Mapping'!$D:$D)),$K90))} | W90: =IF(ISBLANK($B90),"",IF(ISBLANK($L90),RIGHT($E90,LEN($E90) - FIND("^",SUBSTITUTE($E90,":","^",LEN($E90) - LEN(SUBSTITUTE($E90,":",""))))),$L90)) | X90: =IF(ISBLANK($J90),$V90&$W90,$J90) | Y90: {=IF(ISBLANK($M90),IFERROR(XLOOKUP($P90,'Department Listing'!$A:$A,'Department Listing'!$L:$L),""),$M90)} | Z90: =IF(ISBLANK($B90),"",MATCH($X90,COA!$B:$B,0))
B91: 46165 | C91: Raising Canes Chicken Fingers MASTERCARD-555671XXXXXX3281-Elias Kapetanopoulos | E91: 61240 Sales & Marketing:Sales & Marketing- Travel Expenses:Meals & Entertainment | F91: 43.83 | I91: Raising Canes | O91: =IF(C91="", "", TRIM(RIGHT(C91, LEN(C91) - FIND("@@", SUBSTITUTE(C91, "-", "@@", LEN(C91) - LEN(SUBSTITUTE(C91, "-", ""))))))) | P91: {=IFERROR(XLOOKUP(O91,'Department Listing'!$O$1:$O$395,'Department Listing'!$A$1:$A$395),IFERROR(XLOOKUP(O91,'Name Aliases'!$A$2:$A$1000,'Name Aliases'!$B$2:$B$1000),""))} | Q91: =IF(ISBLANK($C91),"",$B91) | R91: =IF(ISBLANK($C91),"",IF(ISBLANK($I91),$D91,$I91)) | S91: =IF(ISBLANK($C91),"",$F91 - $G91) | T91: =IF(ISBLANK($C91),"",C91) | U91: =IF(ISBLANK($C91),"",$D$1) | V91: {=IF(ISBLANK($B91),"",IF(ISBLANK($K91),IF(XLOOKUP($W91,'Category Mapping'!$C:$C,'Category Mapping'!$B:$B)="Travel",XLOOKUP($P91,'Department Listing'!$A:$A,'Department Listing'!$M:$M),XLOOKUP($W91,'Category Mapping'!$C:$C,'Category Mapping'!$D:$D)),$K91))} | W91: =IF(ISBLANK($B91),"",IF(ISBLANK($L91),RIGHT($E91,LEN($E91) - FIND("^",SUBSTITUTE($E91,":","^",LEN($E91) - LEN(SUBSTITUTE($E91,":",""))))),$L91)) | X91: =IF(ISBLANK($J91),$V91&$W91,$J91) | Y91: {=IF(ISBLANK($M91),IFERROR(XLOOKUP($P91,'Department Listing'!$A:$A,'Department Listing'!$L:$L),""),$M91)} | Z91: =IF(ISBLANK($B91),"",MATCH($X91,COA!$B:$B,0))
B92: 46168 | C92: Asana MASTERCARD-544015XXXXXX0374-Vincent Planz | D92: Asana | E92: 63310 General & Administrative:Software Licenses | F92: 43 | L92: Airfare | O92: =IF(C92="", "", TRIM(RIGHT(C92, LEN(C92) - FIND("@@", SUBSTITUTE(C92, "-", "@@", LEN(C92) - LEN(SUBSTITUTE(C92, "-", ""))))))) | P92: {=IFERROR(XLOOKUP(O92,'Department Listing'!$O$1:$O$395,'Department Listing'!$A$1:$A$395),IFERROR(XLOOKUP(O92,'Name Aliases'!$A$2:$A$1000,'Name Aliases'!$B$2:$B$1000),""))} | Q92: =IF(ISBLANK($C92),"",$B92) | R92: =IF(ISBLANK($C92),"",IF(ISBLANK($I92),$D92,$I92)) | S92: =IF(ISBLANK($C92),"",$F92 - $G92) | T92: =IF(ISBLANK($C92),"",C92) | U92: =IF(ISBLANK($C92),"",$D$1) | V92: {=IF(ISBLANK($B92),"",IF(ISBLANK($K92),IF(XLOOKUP($W92,'Category Mapping'!$C:$C,'Category Mapping'!$B:$B)="Travel",XLOOKUP($P92,'Department Listing'!$A:$A,'Department Listing'!$M:$M),XLOOKUP($W92,'Category Mapping'!$C:$C,'Category Mapping'!$D:$D)),$K92))} | W92: =IF(ISBLANK($B92),"",IF(ISBLANK($L92),RIGHT($E92,LEN($E92) - FIND("^",SUBSTITUTE($E92,":","^",LEN($E92) - LEN(SUBSTITUTE($E92,":",""))))),$L92)) | X92: =IF(ISBLANK($J92),$V92&$W92,$J92) | Y92: {=IF(ISBLANK($M92),IFERROR(XLOOKUP($P92,'Department Listing'!$A:$A,'Department Listing'!$L:$L),""),$M92)} | Z92: =IF(ISBLANK($B92),"",MATCH($X92,COA!$B:$B,0))
B93: 46169 | C93: Amazon Marketplace US MASTERCARD-544015XXXXXX8091-Brooke Berg | D93: Amazon | E93: 63410 General & Administrative:Office Expenses:Office Supplies | F93: 41.96 | O93: =IF(C93="", "", TRIM(RIGHT(C93, LEN(C93) - FIND("@@", SUBSTITUTE(C93, "-", "@@", LEN(C93) - LEN(SUBSTITUTE(C93, "-", ""))))))) | P93: {=IFERROR(XLOOKUP(O93,'Department Listing'!$O$1:$O$395,'Department Listing'!$A$1:$A$395),IFERROR(XLOOKUP(O93,'Name Aliases'!$A$2:$A$1000,'Name Aliases'!$B$2:$B$1000),""))} | Q93: =IF(ISBLANK($C93),"",$B93) | R93: =IF(ISBLANK($C93),"",IF(ISBLANK($I93),$D93,$I93)) | S93: =IF(ISBLANK($C93),"",$F93 - $G93) | T93: =IF(ISBLANK($C93),"",C93) | U93: =IF(ISBLANK($C93),"",$D$1) | V93: {=IF(ISBLANK($B93),"",IF(ISBLANK($K93),IF(XLOOKUP($W93,'Category Mapping'!$C:$C,'Category Mapping'!$B:$B)="Travel",XLOOKUP($P93,'Department Listing'!$A:$A,'Department Listing'!$M:$M),XLOOKUP($W93,'Category Mapping'!$C:$C,'Category Mapping'!$D:$D)),$K93))} | W93: =IF(ISBLANK($B93),"",IF(ISBLANK($L93),RIGHT($E93,LEN($E93) - FIND("^",SUBSTITUTE($E93,":","^",LEN($E93) - LEN(SUBSTITUTE($E93,":",""))))),$L93)) | X93: =IF(ISBLANK($J93),$V93&$W93,$J93) | Y93: {=IF(ISBLANK($M93),IFERROR(XLOOKUP($P93,'Department Listing'!$A:$A,'Department Listing'!$L:$L),""),$M93)} | Z93: =IF(ISBLANK($B93),"",MATCH($X93,COA!$B:$B,0))
B94: 46169 | C94: Uber HQ MASTERCARD-544015XXXXXX8678-John Taylor | D94: Uber | E94: 61220 Sales & Marketing:Sales & Marketing- Travel Expenses:Ground Transportation | F94: 39.96 | O94: =IF(C94="", "", TRIM(RIGHT(C94, LEN(C94) - FIND("@@", SUBSTITUTE(C94, "-", "@@", LEN(C94) - LEN(SUBSTITUTE(C94, "-", ""))))))) | P94: {=IFERROR(XLOOKUP(O94,'Department Listing'!$O$1:$O$395,'Department Listing'!$A$1:$A$395),IFERROR(XLOOKUP(O94,'Name Aliases'!$A$2:$A$1000,'Name Aliases'!$B$2:$B$1000),""))} | Q94: =IF(ISBLANK($C94),"",$B94) | R94: =IF(ISBLANK($C94),"",IF(ISBLANK($I94),$D94,$I94)) | S94: =IF(ISBLANK($C94),"",$F94 - $G94) | T94: =IF(ISBLANK($C94),"",C94) | U94: =IF(ISBLANK($C94),"",$D$1) | V94: {=IF(ISBLANK($B94),"",IF(ISBLANK($K94),IF(XLOOKUP($W94,'Category Mapping'!$C:$C,'Category Mapping'!$B:$B)="Travel",XLOOKUP($P94,'Department Listing'!$A:$A,'Department Listing'!$M:$M),XLOOKUP($W94,'Category Mapping'!$C:$C,'Category Mapping'!$D:$D)),$K94))} | W94: =IF(ISBLANK($B94),"",IF(ISBLANK($L94),RIGHT($E94,LEN($E94) - FIND("^",SUBSTITUTE($E94,":","^",LEN($E94) - LEN(SUBSTITUTE($E94,":",""))))),$L94)) | X94: =IF(ISBLANK($J94),$V94&$W94,$J94) | Y94: {=IF(ISBLANK($M94),IFERROR(XLOOKUP($P94,'Department Listing'!$A:$A,'Department Listing'!$L:$L),""),$M94)} | Z94: =IF(ISBLANK($B94),"",MATCH($X94,COA!$B:$B,0))
B95: 46167 | C95: Uber HQ MASTERCARD-555671XXXXXX5379-Ashley Karpel | D95: Uber | E95: 61220 Sales & Marketing:Sales & Marketing- Travel Expenses:Ground Transportation | F95: 39.7 | O95: =IF(C95="", "", TRIM(RIGHT(C95, LEN(C95) - FIND("@@", SUBSTITUTE(C95, "-", "@@", LEN(C95) - LEN(SUBSTITUTE(C95, "-", ""))))))) | P95: {=IFERROR(XLOOKUP(O95,'Department Listing'!$O$1:$O$395,'Department Listing'!$A$1:$A$395),IFERROR(XLOOKUP(O95,'Name Aliases'!$A$2:$A$1000,'Name Aliases'!$B$2:$B$1000),""))} | Q95: =IF(ISBLANK($C95),"",$B95) | R95: =IF(ISBLANK($C95),"",IF(ISBLANK($I95),$D95,$I95)) | S95: =IF(ISBLANK($C95),"",$F95 - $G95) | T95: =IF(ISBLANK($C95),"",C95) | U95: =IF(ISBLANK($C95),"",$D$1) | V95: {=IF(ISBLANK($B95),"",IF(ISBLANK($K95),IF(XLOOKUP($W95,'Category Mapping'!$C:$C,'Category Mapping'!$B:$B)="Travel",XLOOKUP($P95,'Department Listing'!$A:$A,'Department Listing'!$M:$M),XLOOKUP($W95,'Category Mapping'!$C:$C,'Category Mapping'!$D:$D)),$K95))} | W95: =IF(ISBLANK($B95),"",IF(ISBLANK($L95),RIGHT($E95,LEN($E95) - FIND("^",SUBSTITUTE($E95,":","^",LEN($E95) - LEN(SUBSTITUTE($E95,":",""))))),$L95)) | X95: =IF(ISBLANK($J95),$V95&$W95,$J95) | Y95: {=IF(ISBLANK($M95),IFERROR(XLOOKUP($P95,'Department Listing'!$A:$A,'Department Listing'!$L:$L),""),$M95)} | Z95: =IF(ISBLANK($B95),"",MATCH($X95,COA!$B:$B,0))
B96: 46164 | C96: Boston Common Garage MASTERCARD-544015XXXXXX9352-Ryan Kelly | D96: Boston Common Garage | E96: 61220 Sales & Marketing:Sales & Marketing- Travel Expenses:Ground Transportation | F96: 38 | O96: =IF(C96="", "", TRIM(RIGHT(C96, LEN(C96) - FIND("@@", SUBSTITUTE(C96, "-", "@@", LEN(C96) - LEN(SUBSTITUTE(C96, "-", ""))))))) | P96: {=IFERROR(XLOOKUP(O96,'Department Listing'!$O$1:$O$395,'Department Listing'!$A$1:$A$395),IFERROR(XLOOKUP(O96,'Name Aliases'!$A$2:$A$1000,'Name Aliases'!$B$2:$B$1000),""))} | Q96: =IF(ISBLANK($C96),"",$B96) | R96: =IF(ISBLANK($C96),"",IF(ISBLANK($I96),$D96,$I96)) | S96: =IF(ISBLANK($C96),"",$F96 - $G96) | T96: =IF(ISBLANK($C96),"",C96) | U96: =IF(ISBLANK($C96),"",$D$1) | V96: {=IF(ISBLANK($B96),"",IF(ISBLANK($K96),IF(XLOOKUP($W96,'Category Mapping'!$C:$C,'Category Mapping'!$B:$B)="Travel",XLOOKUP($P96,'Department Listing'!$A:$A,'Department Listing'!$M:$M),XLOOKUP($W96,'Category Mapping'!$C:$C,'Category Mapping'!$D:$D)),$K96))} | W96: =IF(ISBLANK($B96),"",IF(ISBLANK($L96),RIGHT($E96,LEN($E96) - FIND("^",SUBSTITUTE($E96,":","^",LEN($E96) - LEN(SUBSTITUTE($E96,":",""))))),$L96)) | X96: =IF(ISBLANK($J96),$V96&$W96,$J96) | Y96: {=IF(ISBLANK($M96),IFERROR(XLOOKUP($P96,'Department Listing'!$A:$A,'Department Listing'!$L:$L),""),$M96)} | Z96: =IF(ISBLANK($B96),"",MATCH($X96,COA!$B:$B,0))
B97: 46165 | C97: GoMoWorld MASTERCARD-544015XXXXXX2884-Ayla Hourani | E97: 61190 Sales & Marketing:Marketing Expenses:Other Marketing Expenses | F97: 35.93 | I97: Travel Vendor | L97: Other Travel Expenses | O97: =IF(C97="", "", TRIM(RIGHT(C97, LEN(C97) - FIND("@@", SUBSTITUTE(C97, "-", "@@", LEN(C97) - LEN(SUBSTITUTE(C97, "-", ""))))))) | P97: {=IFERROR(XLOOKUP(O97,'Department Listing'!$O$1:$O$395,'Department Listing'!$A$1:$A$395),IFERROR(XLOOKUP(O97,'Name Aliases'!$A$2:$A$1000,'Name Aliases'!$B$2:$B$1000),""))} | Q97: =IF(ISBLANK($C97),"",$B97) | R97: =IF(ISBLANK($C97),"",IF(ISBLANK($I97),$D97,$I97)) | S97: =IF(ISBLANK($C97),"",$F97 - $G97) | T97: =IF(ISBLANK($C97),"",C97) | U97: =IF(ISBLANK($C97),"",$D$1) | V97: {=IF(ISBLANK($B97),"",IF(ISBLANK($K97),IF(XLOOKUP($W97,'Category Mapping'!$C:$C,'Category Mapping'!$B:$B)="Travel",XLOOKUP($P97,'Department Listing'!$A:$A,'Department Listing'!$M:$M),XLOOKUP($W97,'Category Mapping'!$C:$C,'Category Mapping'!$D:$D)),$K97))} | W97: =IF(ISBLANK($B97),"",IF(ISBLANK($L97),RIGHT($E97,LEN($E97) - FIND("^",SUBSTITUTE($E97,":","^",LEN($E97) - LEN(SUBSTITUTE($E97,":",""))))),$L97)) | X97: =IF(ISBLANK($J97),$V97&$W97,$J97) | Y97: {=IF(ISBLANK($M97),IFERROR(XLOOKUP($P97,'Department Listing'!$A:$A,'Department Listing'!$L:$L),""),$M97)} | Z97: =IF(ISBLANK($B97),"",MATCH($X97,COA!$B:$B,0))
B98: 46170 | C98: Amazon Marketplace US MASTERCARD-544015XXXXXX8091-Brooke Berg | D98: Amazon | E98: 63410 General & Administrative:Office Expenses:Office Supplies | F98: 35.72 | O98: =IF(C98="", "", TRIM(RIGHT(C98, LEN(C98) - FIND("@@", SUBSTITUTE(C98, "-", "@@", LEN(C98) - LEN(SUBSTITUTE(C98, "-", ""))))))) | P98: {=IFERROR(XLOOKUP(O98,'Department Listing'!$O$1:$O$395,'Department Listing'!$A$1:$A$395),IFERROR(XLOOKUP(O98,'Name Aliases'!$A$2:$A$1000,'Name Aliases'!$B$2:$B$1000),""))} | Q98: =IF(ISBLANK($C98),"",$B98) | R98: =IF(ISBLANK($C98),"",IF(ISBLANK($I98),$D98,$I98)) | S98: =IF(ISBLANK($C98),"",$F98 - $G98) | T98: =IF(ISBLANK($C98),"",C98) | U98: =IF(ISBLANK($C98),"",$D$1) | V98: {=IF(ISBLANK($B98),"",IF(ISBLANK($K98),IF(XLOOKUP($W98,'Category Mapping'!$C:$C,'Category Mapping'!$B:$B)="Travel",XLOOKUP($P98,'Department Listing'!$A:$A,'Department Listing'!$M:$M),XLOOKUP($W98,'Category Mapping'!$C:$C,'Category Mapping'!$D:$D)),$K98))} | W98: =IF(ISBLANK($B98),"",IF(ISBLANK($L98),RIGHT($E98,LEN($E98) - FIND("^",SUBSTITUTE($E98,":","^",LEN($E98) - LEN(SUBSTITUTE($E98,":",""))))),$L98)) | X98: =IF(ISBLANK($J98),$V98&$W98,$J98) | Y98: {=IF(ISBLANK($M98),IFERROR(XLOOKUP($P98,'Department Listing'!$A:$A,'Department Listing'!$L:$L),""),$M98)} | Z98: =IF(ISBLANK($B98),"",MATCH($X98,COA!$B:$B,0))
B99: 46168 | C99: Amazon Marketplace US MASTERCARD-544015XXXXXX7759-Mickenzi Krpec | D99: Amazon | E99: 63410 General & Administrative:Office Expenses:Office Supplies | F99: 35.1 | O99: =IF(C99="", "", TRIM(RIGHT(C99, LEN(C99) - FIND("@@", SUBSTITUTE(C99, "-", "@@", LEN(C99) - LEN(SUBSTITUTE(C99, "-", ""))))))) | P99: {=IFERROR(XLOOKUP(O99,'Department Listing'!$O$1:$O$395,'Department Listing'!$A$1:$A$395),IFERROR(XLOOKUP(O99,'Name Aliases'!$A$2:$A$1000,'Name Aliases'!$B$2:$B$1000),""))} | Q99: =IF(ISBLANK($C99),"",$B99) | R99: =IF(ISBLANK($C99),"",IF(ISBLANK($I99),$D99,$I99)) | S99: =IF(ISBLANK($C99),"",$F99 - $G99) | T99: =IF(ISBLANK($C99),"",C99) | U99: =IF(ISBLANK($C99),"",$D$1) | V99: {=IF(ISBLANK($B99),"",IF(ISBLANK($K99),IF(XLOOKUP($W99,'Category Mapping'!$C:$C,'Category Mapping'!$B:$B)="Travel",XLOOKUP($P99,'Department Listing'!$A:$A,'Department Listing'!$M:$M),XLOOKUP($W99,'Category Mapping'!$C:$C,'Category Mapping'!$D:$D)),$K99))} | W99: =IF(ISBLANK($B99),"",IF(ISBLANK($L99),RIGHT($E99,LEN($E99) - FIND("^",SUBSTITUTE($E99,":","^",LEN($E99) - LEN(SUBSTITUTE($E99,":",""))))),$L99)) | X99: =IF(ISBLANK($J99),$V99&$W99,$J99) | Y99: {=IF(ISBLANK($M99),IFERROR(XLOOKUP($P99,'Department Listing'!$A:$A,'Department Listing'!$L:$L),""),$M99)} | Z99: =IF(ISBLANK($B99),"",MATCH($X99,COA!$B:$B,0))
B100: 46165 | C100: Uber HQ MASTERCARD-544015XXXXXX9350-Gary Passaglia | D100: Uber | E100: 61220 Sales & Marketing:Sales & Marketing- Travel Expenses:Ground Transportation | F100: 34.97 | O100: =IF(C100="", "", TRIM(RIGHT(C100, LEN(C100) - FIND("@@", SUBSTITUTE(C100, "-", "@@", LEN(C100) - LEN(SUBSTITUTE(C100, "-", ""))))))) | P100: {=IFERROR(XLOOKUP(O100,'Department Listing'!$O$1:$O$395,'Department Listing'!$A$1:$A$395),IFERROR(XLOOKUP(O100,'Name Aliases'!$A$2:$A$1000,'Name Aliases'!$B$2:$B$1000),""))} | Q100: =IF(ISBLANK($C100),"",$B100) | R100: =IF(ISBLANK($C100),"",IF(ISBLANK($I100),$D100,$I100)) | S100: =IF(ISBLANK($C100),"",$F100 - $G100) | T100: =IF(ISBLANK($C100),"",C100) | U100: =IF(ISBLANK($C100),"",$D$1) | V100: {=IF(ISBLANK($B100),"",IF(ISBLANK($K100),IF(XLOOKUP($W100,'Category Mapping'!$C:$C,'Category Mapping'!$B:$B)="Travel",XLOOKUP($P100,'Department Listing'!$A:$A,'Department Listing'!$M:$M),XLOOKUP($W100,'Category Mapping'!$C:$C,'Category Mapping'!$D:$D)),$K100))} | W100: =IF(ISBLANK($B100),"",IF(ISBLANK($L100),RIGHT($E100,LEN($E100) - FIND("^",SUBSTITUTE($E100,":","^",LEN($E100) - LEN(SUBSTITUTE($E100,":",""))))),$L100)) | X100: =IF(ISBLANK($J100),$V100&$W100,$J100) | Y100: {=IF(ISBLANK($M100),IFERROR(XLOOKUP($P100,'Department Listing'!$A:$A,'Department Listing'!$L:$L),""),$M100)} | Z100: =IF(ISBLANK($B100),"",MATCH($X100,COA!$B:$B,0))
B101: 46165 | C101: Certn (Formerly Credence) Background Screening MASTERCARD-544015XXXXXX6112-Elyse Neumeier | D101: Certn | E101: 63410 General & Administrative:Office Expenses:Office Supplies | F101: 34.65 | O101: =IF(C101="", "", TRIM(RIGHT(C101, LEN(C101) - FIND("@@", SUBSTITUTE(C101, "-", "@@", LEN(C101) - LEN(SUBSTITUTE(C101, "-", ""))))))) | P101: {=IFERROR(XLOOKUP(O101,'Department Listing'!$O$1:$O$395,'Department Listing'!$A$1:$A$395),IFERROR(XLOOKUP(O101,'Name Aliases'!$A$2:$A$1000,'Name Aliases'!$B$2:$B$1000),""))} | Q101: =IF(ISBLANK($C101),"",$B101) | R101: =IF(ISBLANK($C101),"",IF(ISBLANK($I101),$D101,$I101)) | S101: =IF(ISBLANK($C101),"",$F101 - $G101) | T101: =IF(ISBLANK($C101),"",C101) | U101: =IF(ISBLANK($C101),"",$D$1) | V101: {=IF(ISBLANK($B101),"",IF(ISBLANK($K101),IF(XLOOKUP($W101,'Category Mapping'!$C:$C,'Category Mapping'!$B:$B)="Travel",XLOOKUP($P101,'Department Listing'!$A:$A,'Department Listing'!$M:$M),XLOOKUP($W101,'Category Mapping'!$C:$C,'Category Mapping'!$D:$D)),$K101))} | W101: =IF(ISBLANK($B101),"",IF(ISBLANK($L101),RIGHT($E101,LEN($E101) - FIND("^",SUBSTITUTE($E101,":","^",LEN($E101) - LEN(SUBSTITUTE($E101,":",""))))),$L101)) | X101: =IF(ISBLANK($J101),$V101&$W101,$J101) | Y101: {=IF(ISBLANK($M101),IFERROR(XLOOKUP($P101,'Department Listing'!$A:$A,'Department Listing'!$L:$L),""),$M101)} | Z101: =IF(ISBLANK($B101),"",MATCH($X101,COA!$B:$B,0))
B102: 46168 | C102: Amazon Marketplace US MASTERCARD-544015XXXXXX7759-Mickenzi Krpec | D102: Amazon | E102: 63410 General & Administrative:Office Expenses:Office Supplies | F102: 34.4 | O102: =IF(C102="", "", TRIM(RIGHT(C102, LEN(C102) - FIND("@@", SUBSTITUTE(C102, "-", "@@", LEN(C102) - LEN(SUBSTITUTE(C102, "-", ""))))))) | P102: {=IFERROR(XLOOKUP(O102,'Department Listing'!$O$1:$O$395,'Department Listing'!$A$1:$A$395),IFERROR(XLOOKUP(O102,'Name Aliases'!$A$2:$A$1000,'Name Aliases'!$B$2:$B$1000),""))} | Q102: =IF(ISBLANK($C102),"",$B102) | R102: =IF(ISBLANK($C102),"",IF(ISBLANK($I102),$D102,$I102)) | S102: =IF(ISBLANK($C102),"",$F102 - $G102) | T102: =IF(ISBLANK($C102),"",C102) | U102: =IF(ISBLANK($C102),"",$D$1) | V102: {=IF(ISBLANK($B102),"",IF(ISBLANK($K102),IF(XLOOKUP($W102,'Category Mapping'!$C:$C,'Category Mapping'!$B:$B)="Travel",XLOOKUP($P102,'Department Listing'!$A:$A,'Department Listing'!$M:$M),XLOOKUP($W102,'Category Mapping'!$C:$C,'Category Mapping'!$D:$D)),$K102))} | W102: =IF(ISBLANK($B102),"",IF(ISBLANK($L102),RIGHT($E102,LEN($E102) - FIND("^",SUBSTITUTE($E102,":","^",LEN($E102) - LEN(SUBSTITUTE($E102,":",""))))),$L102)) | X102: =IF(ISBLANK($J102),$V102&$W102,$J102) | Y102: {=IF(ISBLANK($M102),IFERROR(XLOOKUP($P102,'Department Listing'!$A:$A,'Department Listing'!$L:$L),""),$M102)} | Z102: =IF(ISBLANK($B102),"",MATCH($X102,COA!$B:$B,0))
B103: 46168 | C103: Uber HQ MASTERCARD-544015XXXXXX9350-Gary Passaglia | D103: Uber | E103: 61220 Sales & Marketing:Sales & Marketing- Travel Expenses:Ground Transportation | F103: 33.93 | O103: =IF(C103="", "", TRIM(RIGHT(C103, LEN(C103) - FIND("@@", SUBSTITUTE(C103, "-", "@@", LEN(C103) - LEN(SUBSTITUTE(C103, "-", ""))))))) | P103: {=IFERROR(XLOOKUP(O103,'Department Listing'!$O$1:$O$395,'Department Listing'!$A$1:$A$395),IFERROR(XLOOKUP(O103,'Name Aliases'!$A$2:$A$1000,'Name Aliases'!$B$2:$B$1000),""))} | Q103: =IF(ISBLANK($C103),"",$B103) | R103: =IF(ISBLANK($C103),"",IF(ISBLANK($I103),$D103,$I103)) | S103: =IF(ISBLANK($C103),"",$F103 - $G103) | T103: =IF(ISBLANK($C103),"",C103) | U103: =IF(ISBLANK($C103),"",$D$1) | V103: {=IF(ISBLANK($B103),"",IF(ISBLANK($K103),IF(XLOOKUP($W103,'Category Mapping'!$C:$C,'Category Mapping'!$B:$B)="Travel",XLOOKUP($P103,'Department Listing'!$A:$A,'Department Listing'!$M:$M),XLOOKUP($W103,'Category Mapping'!$C:$C,'Category Mapping'!$D:$D)),$K103))} | W103: =IF(ISBLANK($B103),"",IF(ISBLANK($L103),RIGHT($E103,LEN($E103) - FIND("^",SUBSTITUTE($E103,":","^",LEN($E103) - LEN(SUBSTITUTE($E103,":",""))))),$L103)) | X103: =IF(ISBLANK($J103),$V103&$W103,$J103) | Y103: {=IF(ISBLANK($M103),IFERROR(XLOOKUP($P103,'Department Listing'!$A:$A,'Department Listing'!$L:$L),""),$M103)} | Z103: =IF(ISBLANK($B103),"",MATCH($X103,COA!$B:$B,0))
B104: 46170 | C104: Amazon Marketplace US MASTERCARD-544015XXXXXX8091-Brooke Berg | D104: Amazon | E104: 63410 General & Administrative:Office Expenses:Office Supplies | F104: 32.4 | O104: =IF(C104="", "", TRIM(RIGHT(C104, LEN(C104) - FIND("@@", SUBSTITUTE(C104, "-", "@@", LEN(C104) - LEN(SUBSTITUTE(C104, "-", ""))))))) | P104: {=IFERROR(XLOOKUP(O104,'Department Listing'!$O$1:$O$395,'Department Listing'!$A$1:$A$395),IFERROR(XLOOKUP(O104,'Name Aliases'!$A$2:$A$1000,'Name Aliases'!$B$2:$B$1000),""))} | Q104: =IF(ISBLANK($C104),"",$B104) | R104: =IF(ISBLANK($C104),"",IF(ISBLANK($I104),$D104,$I104)) | S104: =IF(ISBLANK($C104),"",$F104 - $G104) | T104: =IF(ISBLANK($C104),"",C104) | U104: =IF(ISBLANK($C104),"",$D$1) | V104: {=IF(ISBLANK($B104),"",IF(ISBLANK($K104),IF(XLOOKUP($W104,'Category Mapping'!$C:$C,'Category Mapping'!$B:$B)="Travel",XLOOKUP($P104,'Department Listing'!$A:$A,'Department Listing'!$M:$M),XLOOKUP($W104,'Category Mapping'!$C:$C,'Category Mapping'!$D:$D)),$K104))} | W104: =IF(ISBLANK($B104),"",IF(ISBLANK($L104),RIGHT($E104,LEN($E104) - FIND("^",SUBSTITUTE($E104,":","^",LEN($E104) - LEN(SUBSTITUTE($E104,":",""))))),$L104)) | X104: =IF(ISBLANK($J104),$V104&$W104,$J104) | Y104: {=IF(ISBLANK($M104),IFERROR(XLOOKUP($P104,'Department Listing'!$A:$A,'Department Listing'!$L:$L),""),$M104)} | Z104: =IF(ISBLANK($B104),"",MATCH($X104,COA!$B:$B,0))
B105: 46164 | C105: Taxi MASTERCARD-555671XXXXXX1123-Tomas Cespedes | E105: 61220 Sales & Marketing:Sales & Marketing- Travel Expenses:Ground Transportation | F105: 32.1 | I105: Taxi Vendor | O105: =IF(C105="", "", TRIM(RIGHT(C105, LEN(C105) - FIND("@@", SUBSTITUTE(C105, "-", "@@", LEN(C105) - LEN(SUBSTITUTE(C105, "-", ""))))))) | P105: {=IFERROR(XLOOKUP(O105,'Department Listing'!$O$1:$O$395,'Department Listing'!$A$1:$A$395),IFERROR(XLOOKUP(O105,'Name Aliases'!$A$2:$A$1000,'Name Aliases'!$B$2:$B$1000),""))} | Q105: =IF(ISBLANK($C105),"",$B105) | R105: =IF(ISBLANK($C105),"",IF(ISBLANK($I105),$D105,$I105)) | S105: =IF(ISBLANK($C105),"",$F105 - $G105) | T105: =IF(ISBLANK($C105),"",C105) | U105: =IF(ISBLANK($C105),"",$D$1) | V105: {=IF(ISBLANK($B105),"",IF(ISBLANK($K105),IF(XLOOKUP($W105,'Category Mapping'!$C:$C,'Category Mapping'!$B:$B)="Travel",XLOOKUP($P105,'Department Listing'!$A:$A,'Department Listing'!$M:$M),XLOOKUP($W105,'Category Mapping'!$C:$C,'Category Mapping'!$D:$D)),$K105))} | W105: =IF(ISBLANK($B105),"",IF(ISBLANK($L105),RIGHT($E105,LEN($E105) - FIND("^",SUBSTITUTE($E105,":","^",LEN($E105) - LEN(SUBSTITUTE($E105,":",""))))),$L105)) | X105: =IF(ISBLANK($J105),$V105&$W105,$J105) | Y105: {=IF(ISBLANK($M105),IFERROR(XLOOKUP($P105,'Department Listing'!$A:$A,'Department Listing'!$L:$L),""),$M105)} | Z105: =IF(ISBLANK($B105),"",MATCH($X105,COA!$B:$B,0))
B106: 46169 | C106: Amazon MASTERCARD-544015XXXXXX9692-Aaron Rhodes | D106: Amazon | E106: 63410 General & Administrative:Office Expenses:Office Supplies | F106: 31.33 | O106: =IF(C106="", "", TRIM(RIGHT(C106, LEN(C106) - FIND("@@", SUBSTITUTE(C106, "-", "@@", LEN(C106) - LEN(SUBSTITUTE(C106, "-", ""))))))) | P106: {=IFERROR(XLOOKUP(O106,'Department Listing'!$O$1:$O$395,'Department Listing'!$A$1:$A$395),IFERROR(XLOOKUP(O106,'Name Aliases'!$A$2:$A$1000,'Name Aliases'!$B$2:$B$1000),""))} | Q106: =IF(ISBLANK($C106),"",$B106) | R106: =IF(ISBLANK($C106),"",IF(ISBLANK($I106),$D106,$I106)) | S106: =IF(ISBLANK($C106),"",$F106 - $G106) | T106: =IF(ISBLANK($C106),"",C106) | U106: =IF(ISBLANK($C106),"",$D$1) | V106: {=IF(ISBLANK($B106),"",IF(ISBLANK($K106),IF(XLOOKUP($W106,'Category Mapping'!$C:$C,'Category Mapping'!$B:$B)="Travel",XLOOKUP($P106,'Department Listing'!$A:$A,'Department Listing'!$M:$M),XLOOKUP($W106,'Category Mapping'!$C:$C,'Category Mapping'!$D:$D)),$K106))} | W106: =IF(ISBLANK($B106),"",IF(ISBLANK($L106),RIGHT($E106,LEN($E106) - FIND("^",SUBSTITUTE($E106,":","^",LEN($E106) - LEN(SUBSTITUTE($E106,":",""))))),$L106)) | X106: =IF(ISBLANK($J106),$V106&$W106,$J106) | Y106: {=IF(ISBLANK($M106),IFERROR(XLOOKUP($P106,'Department Listing'!$A:$A,'Department Listing'!$L:$L),""),$M106)} | Z106: =IF(ISBLANK($B106),"",MATCH($X106,COA!$B:$B,0))
B107: 46168 | C107: Wegmans MASTERCARD-544015XXXXXX7759-Mickenzi Krpec | E107: 61240 Sales & Marketing:Sales & Marketing- Travel Expenses:Meals & Entertainment | F107: 30.46 | I107: Food Vendor | O107: =IF(C107="", "", TRIM(RIGHT(C107, LEN(C107) - FIND("@@", SUBSTITUTE(C107, "-", "@@", LEN(C107) - LEN(SUBSTITUTE(C107, "-", ""))))))) | P107: {=IFERROR(XLOOKUP(O107,'Department Listing'!$O$1:$O$395,'Department Listing'!$A$1:$A$395),IFERROR(XLOOKUP(O107,'Name Aliases'!$A$2:$A$1000,'Name Aliases'!$B$2:$B$1000),""))} | Q107: =IF(ISBLANK($C107),"",$B107) | R107: =IF(ISBLANK($C107),"",IF(ISBLANK($I107),$D107,$I107)) | S107: =IF(ISBLANK($C107),"",$F107 - $G107) | T107: =IF(ISBLANK($C107),"",C107) | U107: =IF(ISBLANK($C107),"",$D$1) | V107: {=IF(ISBLANK($B107),"",IF(ISBLANK($K107),IF(XLOOKUP($W107,'Category Mapping'!$C:$C,'Category Mapping'!$B:$B)="Travel",XLOOKUP($P107,'Department Listing'!$A:$A,'Department Listing'!$M:$M),XLOOKUP($W107,'Category Mapping'!$C:$C,'Category Mapping'!$D:$D)),$K107))} | W107: =IF(ISBLANK($B107),"",IF(ISBLANK($L107),RIGHT($E107,LEN($E107) - FIND("^",SUBSTITUTE($E107,":","^",LEN($E107) - LEN(SUBSTITUTE($E107,":",""))))),$L107)) | X107: =IF(ISBLANK($J107),$V107&$W107,$J107) | Y107: {=IF(ISBLANK($M107),IFERROR(XLOOKUP($P107,'Department Listing'!$A:$A,'Department Listing'!$L:$L),""),$M107)} | Z107: =IF(ISBLANK($B107),"",MATCH($X107,COA!$B:$B,0))
B108: 46167 | C108: Amazon Marketplace US MASTERCARD-544015XXXXXX9352-Ryan Kelly | D108: Amazon | E108: 63410 General & Administrative:Office Expenses:Office Supplies | F108: 29.99 | O108: =IF(C108="", "", TRIM(RIGHT(C108, LEN(C108) - FIND("@@", SUBSTITUTE(C108, "-", "@@", LEN(C108) - LEN(SUBSTITUTE(C108, "-", ""))))))) | P108: {=IFERROR(XLOOKUP(O108,'Department Listing'!$O$1:$O$395,'Department Listing'!$A$1:$A$395),IFERROR(XLOOKUP(O108,'Name Aliases'!$A$2:$A$1000,'Name Aliases'!$B$2:$B$1000),""))} | Q108: =IF(ISBLANK($C108),"",$B108) | R108: =IF(ISBLANK($C108),"",IF(ISBLANK($I108),$D108,$I108)) | S108: =IF(ISBLANK($C108),"",$F108 - $G108) | T108: =IF(ISBLANK($C108),"",C108) | U108: =IF(ISBLANK($C108),"",$D$1) | V108: {=IF(ISBLANK($B108),"",IF(ISBLANK($K108),IF(XLOOKUP($W108,'Category Mapping'!$C:$C,'Category Mapping'!$B:$B)="Travel",XLOOKUP($P108,'Department Listing'!$A:$A,'Department Listing'!$M:$M),XLOOKUP($W108,'Category Mapping'!$C:$C,'Category Mapping'!$D:$D)),$K108))} | W108: =IF(ISBLANK($B108),"",IF(ISBLANK($L108),RIGHT($E108,LEN($E108) - FIND("^",SUBSTITUTE($E108,":","^",LEN($E108) - LEN(SUBSTITUTE($E108,":",""))))),$L108)) | X108: =IF(ISBLANK($J108),$V108&$W108,$J108) | Y108: {=IF(ISBLANK($M108),IFERROR(XLOOKUP($P108,'Department Listing'!$A:$A,'Department Listing'!$L:$L),""),$M108)} | Z108: =IF(ISBLANK($B108),"",MATCH($X108,COA!$B:$B,0))
B109: 46166 | C109: Amazon MASTERCARD-544015XXXXXX2900-Chloe Brant | D109: Amazon | E109: 63410 General & Administrative:Office Expenses:Office Supplies | F109: 28.06 | O109: =IF(C109="", "", TRIM(RIGHT(C109, LEN(C109) - FIND("@@", SUBSTITUTE(C109, "-", "@@", LEN(C109) - LEN(SUBSTITUTE(C109, "-", ""))))))) | P109: {=IFERROR(XLOOKUP(O109,'Department Listing'!$O$1:$O$395,'Department Listing'!$A$1:$A$395),IFERROR(XLOOKUP(O109,'Name Aliases'!$A$2:$A$1000,'Name Aliases'!$B$2:$B$1000),""))} | Q109: =IF(ISBLANK($C109),"",$B109) | R109: =IF(ISBLANK($C109),"",IF(ISBLANK($I109),$D109,$I109)) | S109: =IF(ISBLANK($C109),"",$F109 - $G109) | T109: =IF(ISBLANK($C109),"",C109) | U109: =IF(ISBLANK($C109),"",$D$1) | V109: {=IF(ISBLANK($B109),"",IF(ISBLANK($K109),IF(XLOOKUP($W109,'Category Mapping'!$C:$C,'Category Mapping'!$B:$B)="Travel",XLOOKUP($P109,'Department Listing'!$A:$A,'Department Listing'!$M:$M),XLOOKUP($W109,'Category Mapping'!$C:$C,'Category Mapping'!$D:$D)),$K109))} | W109: =IF(ISBLANK($B109),"",IF(ISBLANK($L109),RIGHT($E109,LEN($E109) - FIND("^",SUBSTITUTE($E109,":","^",LEN($E109) - LEN(SUBSTITUTE($E109,":",""))))),$L109)) | X109: =IF(ISBLANK($J109),$V109&$W109,$J109) | Y109: {=IF(ISBLANK($M109),IFERROR(XLOOKUP($P109,'Department Listing'!$A:$A,'Department Listing'!$L:$L),""),$M109)} | Z109: =IF(ISBLANK($B109),"",MATCH($X109,COA!$B:$B,0))
B110: 46165 | C110: Chipotle Mexican Grill MASTERCARD-544015XXXXXX2505-Frederick Simpson | D110: Chipotle | E110: 61240 Sales & Marketing:Sales & Marketing- Travel Expenses:Meals & Entertainment | F110: 27.71 | O110: =IF(C110="", "", TRIM(RIGHT(C110, LEN(C110) - FIND("@@", SUBSTITUTE(C110, "-", "@@", LEN(C110) - LEN(SUBSTITUTE(C110, "-", ""))))))) | P110: {=IFERROR(XLOOKUP(O110,'Department Listing'!$O$1:$O$395,'Department Listing'!$A$1:$A$395),IFERROR(XLOOKUP(O110,'Name Aliases'!$A$2:$A$1000,'Name Aliases'!$B$2:$B$1000),""))} | Q110: =IF(ISBLANK($C110),"",$B110) | R110: =IF(ISBLANK($C110),"",IF(ISBLANK($I110),$D110,$I110)) | S110: =IF(ISBLANK($C110),"",$F110 - $G110) | T110: =IF(ISBLANK($C110),"",C110) | U110: =IF(ISBLANK($C110),"",$D$1) | V110: {=IF(ISBLANK($B110),"",IF(ISBLANK($K110),IF(XLOOKUP($W110,'Category Mapping'!$C:$C,'Category Mapping'!$B:$B)="Travel",XLOOKUP($P110,'Department Listing'!$A:$A,'Department Listing'!$M:$M),XLOOKUP($W110,'Category Mapping'!$C:$C,'Category Mapping'!$D:$D)),$K110))} | W110: =IF(ISBLANK($B110),"",IF(ISBLANK($L110),RIGHT($E110,LEN($E110) - FIND("^",SUBSTITUTE($E110,":","^",LEN($E110) - LEN(SUBSTITUTE($E110,":",""))))),$L110)) | X110: =IF(ISBLANK($J110),$V110&$W110,$J110) | Y110: {=IF(ISBLANK($M110),IFERROR(XLOOKUP($P110,'Department Listing'!$A:$A,'Department Listing'!$L:$L),""),$M110)} | Z110: =IF(ISBLANK($B110),"",MATCH($X110,COA!$B:$B,0))
B111: 46164 | C111: WEISSGERBER S GOLDEN M MASTERCARD-544015XXXXXX2553-Ryan Hale | E111: 61240 Sales & Marketing:Sales & Marketing- Travel Expenses:Meals & Entertainment | F111: 25.09 | I111: Food Vendor | O111: =IF(C111="", "", TRIM(RIGHT(C111, LEN(C111) - FIND("@@", SUBSTITUTE(C111, "-", "@@", LEN(C111) - LEN(SUBSTITUTE(C111, "-", ""))))))) | P111: {=IFERROR(XLOOKUP(O111,'Department Listing'!$O$1:$O$395,'Department Listing'!$A$1:$A$395),IFERROR(XLOOKUP(O111,'Name Aliases'!$A$2:$A$1000,'Name Aliases'!$B$2:$B$1000),""))} | Q111: =IF(ISBLANK($C111),"",$B111) | R111: =IF(ISBLANK($C111),"",IF(ISBLANK($I111),$D111,$I111)) | S111: =IF(ISBLANK($C111),"",$F111 - $G111) | T111: =IF(ISBLANK($C111),"",C111) | U111: =IF(ISBLANK($C111),"",$D$1) | V111: {=IF(ISBLANK($B111),"",IF(ISBLANK($K111),IF(XLOOKUP($W111,'Category Mapping'!$C:$C,'Category Mapping'!$B:$B)="Travel",XLOOKUP($P111,'Department Listing'!$A:$A,'Department Listing'!$M:$M),XLOOKUP($W111,'Category Mapping'!$C:$C,'Category Mapping'!$D:$D)),$K111))} | W111: =IF(ISBLANK($B111),"",IF(ISBLANK($L111),RIGHT($E111,LEN($E111) - FIND("^",SUBSTITUTE($E111,":","^",LEN($E111) - LEN(SUBSTITUTE($E111,":",""))))),$L111)) | X111: =IF(ISBLANK($J111),$V111&$W111,$J111) | Y111: {=IF(ISBLANK($M111),IFERROR(XLOOKUP($P111,'Department Listing'!$A:$A,'Department Listing'!$L:$L),""),$M111)} | Z111: =IF(ISBLANK($B111),"",MATCH($X111,COA!$B:$B,0))
...

Sheet Card Mapping
B2: Card Number (last 4 Digits) | C2: Card Name | D2: Department | E2: EE ID | H2: Amex Accounts
B3: 2011 | C3: Matt Keyes | D3: 200- Datadog:230- Sales | E3: 104 | H3: Amex Plat 2 *51005
B4: 2219 | C4: Toni Manning | D4: 100- Operations:120- Marketing | E4: 121 | H4: Amex Plat *12006
B5: 3159 | C5: John Taylor | D5: 300- ServiceNow:330- Sales | E5: 118 | H5: Amex Centurion *01008
H6: Brex Credit Card
B7: 2193 | C7: Jacob McKenna | D7: 300- ServiceNow:320- Engineering | E7: 120 | H7: Amex Delta *13003
B8: 1302 | C8: Andrew Bissel | D8: 200- Datadog:220- Engineering | E8: 135
B9: 2110 | C9: Chris Breiner | D9: 200- Datadog:230- Sales | E9: 115
B10: 2094 | C10: Jon Lawer | D10: 300- ServiceNow:330- Sales | E10: 113
B11: 2243 | C11: Scott Lane | D11: 300- ServiceNow:330- Sales | E11: 132
B12: 2169 | C12: R Faria De Oliveira | D12: 200- Datadog:220- Engineering | E12: 125
B13: 2086 | C13: Richard Upshall | D13: 200- Datadog:230- Sales | E13: 112
B14: 2201 | C14: Eric Ledyard | D14: 100- Operations:110- G&A | E14: 123
B15: 2006 | C15: Tameem Hourani | D15: 100- Operations:110- G&A | E15: 1
B16: 1933 | C16: Nikita Ashok | D16: 100- Operations:120- Marketing | E16: 111
B17: 3418 | C17: Alta Abel | D17: 100- Operations:110- G&A | E17: 69
B18: 2675 | C18: Chloe Brant | D18: 300- ServiceNow:330- Sales | E18: 77
B19: 2170 | C19: Josh Van Harn | D19: 300- ServiceNow:330- Sales | E19: 23
... B125: 1799 | C125: Jacob Woolf | D125: 300- ServiceNow:320- Engineering | E125: 194
B126: 1823 | C126: Teresa Bobst | E126: 188
B127: 1856 | C127: Tim Lee | E127: 213
B128: 2813 | C128: Ona Kolosky | D128: 300- ServiceNow:320- Engineering | E128: 198
B129: 1864 | C129: Timothy Lau | D129: 200- Datadog:220- Engineering | E129: 210
B130: 1872 | C130: Sakshi Sasalate | D130: 300- ServiceNow:320- Engineering | E130: 209
B131: 1724 | C131: Sarah Dwyer | D131: 200- Datadog:210- Delivery | E131: 183
B132: 0151 | C132: Eric Rabkin | D132: 100- Operations:110- G&A | E132: 246
C133: Kyle Bense | D133: 300- ServiceNow:320- Engineering | E133: 252
C134: James O'Shaughnessy | D134: 300- ServiceNow:310- Delivery | E134: 239
C135: Cody Sanderford | D135: 300- ServiceNow:320- Engineering | E135: 245
C136: Harry Tomczyk | D136: 300- ServiceNow:330- Sales | E136: 251

Sheet Category Mapping
B3: Account Type | C3: Sub Account | D3: Parent Category
B4: Travel | C4: Airfare
B5: G&A | C5: Contractors | D5: General & Administrative:
B6: G&A | C6: Dues & Subscriptions | D6: General & Administrative:Office Expenses:
B7: Travel | C7: Ground Transportation
B8: G&A | C8: Hardware & Peripherals | D8: General & Administrative:Office Expenses:
B9: Travel | C9: Lodging
B10: Travel | C10: Meals & Entertainment
B11: G&A | C11: Office Supplies | D11: General & Administrative:Office Expenses:
B12: S&M | C12: Other Marketing Expenses | D12: Sales & Marketing:Marketing Expenses:
B13: Travel | C13: Other Travel Expenses
B14: G&A | C14: Shipping Expense | D14: General & Administrative:Office Expenses:
B15: G&A | C15: Software Licenses | D15: General & Administrative:
B16: G&A | C16: Misc. Taxes & Licenses | D16: General & Administrative:
B17: G&A | C17: Utilities | D17: General & Administrative:Office Expenses:
B18: G&A | C18: Communication Expense | D18: General & Administrative:Office Expenses:
B19: G&A | C19: Charitable Contribution | D19: General & Administrative:
B20: G&A | C20: General & Administrative:Office Expenses:Rent & Lease | D20: General & Administrative:

Sheet COA
B1: All QBO Accounts
B2: 45904
B4: BOA Checking 4855
B5: Brex Checking
B6: Cash
B7: Checking (Citizens)
B8: Northern Bank Checking 3097
B9: Accounts Receivable
B10: Accounts Receivable (A/R)
B11: Accounts Receivable (A/R) - CAD
B12: Accounts Receivable (A/R) - EUR
B13: Accounts Receivable (A/R) - GBP
B14: Asset Clearing
B15: Credit Card Receivables (deleted)
... B223: Other Expenses:Reconciliation Discrepancies

Sheet Instructions
B2: Purpose: Import Amex transactions with accurate department, account and description into QuickBooks Online
B4: Instructions
B5: 1. Duplicate File and ensure file name has today's date and the Amex account being entered
B6: 2. Review credit card transactions in QuickBooks, and manually enter credit card credits using "Card Mapping" tab as a reference. Ensure Vendor Name, Account, Department fields are populated and you add " - " & the Employee name to the end of the Memo field
B7: 3. CTRL+H Find and Replace "-" for " - "
B8: 4. Sort the transactions in QuickBooks based on Date
B9: 5. Export transactions from QuickBooks
B10: 6. Copy exported transactions, paste values in cells B-F of the "QBO Transactions" tab
B11: 7. Review Columns K-F of "QBO transactions" to ensure all cells are populated.
B12: 8. Ensure Column Q of "QBO Transactions" is showing the correct card account. Update in Cell D1 if incorrect
B13: 9. Filter Column R, Line Acct by each individual account to ensure transactions are coded accurately
B14: 10. Ensure transactions on "Credit Card Charge" tab, the transaction importer, match what's on "QBO Transactions" tab (transaction count and amount match)

Sheet Name Aliases
A1: Brex Name | B1: EE ID | C1: BambooHR Name | D1: Confirmed | E1: Note

Sheet Department Listing
A1: Employee # | B1: First Name | C1: Last Name | D1: Last name, First name | E1: Hire Date | F1: Employment Status | G1: Employment Status: Date | H1: Division | I1: Department | J1: Location | K1: Billable Status | L1: QBO Department | M1: Prefix- Travel | N1: Prefix- Payroll
A2: 1 | B2: Tameem | C2: Hourani | D2: Hourani, Tameem | E2: 43651 | F2: Owner/Partner | G2: 43651 | H2: Operations | I2: Operations | J2: Boylston | K2: No | L2: 400- Synechron:410- Digital platforms G&A | M2: General & Administrative:G&A- Travel Expenses: | N2: General & Administrative:G&A- Personnel Expenses: | O2: =B2&" "&C2
A3: 2 | B3: Jonathan | C3: Giara | D3: Giara, Jonathan | E3: 43647 | F3: Full-Time | G3: 43773 | H3: ServiceNow | I3: Engineering | J3: Remote | K3: Yes | L3: 300- ServiceNow:320- Engineering | M3: Cost of Goods Sold:COGS- Travel Expenses: | N3: Cost of Goods Sold:COGS- Personnel Expense: | O3: =B3&" "&C3
A4: 3 | B4: Connor | C4: Brackett | D4: Brackett, Connor | E4: 43773 | F4: Full-Time | G4: 43773 | H4: ServiceNow | I4: Sales | J4: Boylston | K4: No | L4: 300- ServiceNow:330- Sales | M4: Sales & Marketing:Sales & Marketing- Travel Expenses: | N4: Sales & Marketing:Sales & Marketing- Personnel Expenses: | O4: =B4&" "&C4
A5: 4 | B5: Jeffrey | C5: Mu | D5: Mu, Jeffrey | E5: 43754 | F5: Full-Time | G5: 43754 | H5: ServiceNow | I5: Engineering | J5: Boylston | K5: Yes | L5: 300- ServiceNow:320- Engineering | M5: Cost of Goods Sold:COGS- Travel Expenses: | N5: Cost of Goods Sold:COGS- Personnel Expense: | O5: =B5&" "&C5
A6: 5 | B6: James | C6: Craveiro | D6: Craveiro, James | E6: 43871 | F6: Terminated | G6: 44835 | H6: Datadog | I6: Engineering | J6: Remote | K6: Yes | L6: 200- Datadog:220- Engineering | M6: Cost of Goods Sold:COGS- Travel Expenses: | N6: Cost of Goods Sold:COGS- Personnel Expense: | O6: =B6&" "&C6
A7: 6 | B7: Kristopher | C7: Borodiansky | D7: Borodiansky, Kristopher | E7: 43857 | F7: Terminated | G7: 43886 | H7: Datadog | I7: Engineering | J7: Remote | K7: Yes | L7: 200- Datadog:220- Engineering | M7: Cost of Goods Sold:COGS- Travel Expenses: | N7: Cost of Goods Sold:COGS- Personnel Expense: | O7: =B7&" "&C7
A8: 7 | B8: Erik | C8: Williams | D8: Williams, Erik | E8: 43885 | F8: Full-Time | G8: 43885 | H8: Operations | I8: Strategy | J8: Remote | K8: Yes | L8: 400- Synechron:410- Digital platforms G&A | M8: Cost of Goods Sold:COGS- Travel Expenses: | N8: Cost of Goods Sold:COGS- Personnel Expense: | O8: =B8&" "&C8
A9: 8 | B9: Logan | C9: Rohloff | D9: Rohloff, Logan | E9: 43906 | F9: Full-Time | G9: 43906 | H9: Datadog | I9: Engineering | J9: Remote | K9: Yes | L9: 200- Datadog:220- Engineering | M9: Cost of Goods Sold:COGS- Travel Expenses: | N9: Cost of Goods Sold:COGS- Personnel Expense: | O9: =B9&" "&C9
A10: 9 | B10: Reese | C10: Boisse | D10: Boisse, Reese | E10: 43927 | F10: Full-Time | G10: 43927 | H10: ServiceNow | I10: Sales | J10: Boylston | K10: No | L10: 300- ServiceNow:330- Sales | M10: Sales & Marketing:Sales & Marketing- Travel Expenses: | N10: Sales & Marketing:Sales & Marketing- Personnel Expenses: | O10: =B10&" "&C10
A11: 10 | B11: Reuben | C11: Stump | D11: Stump, Reuben | E11: 43985 | F11: Full-Time | G11: 43985 | H11: Datadog | I11: Engineering | J11: Remote | K11: Yes | L11: 200- Datadog:220- Engineering | M11: Cost of Goods Sold:COGS- Travel Expenses: | N11: Cost of Goods Sold:COGS- Personnel Expense: | O11: =B11&" "&C11
A12: 11 | B12: Victoria | C12: Quinn | D12: Quinn, Victoria | E12: 43990 | F12: Terminated | G12: 45003 | H12: Operations | I12: Admin | J12: Remote | K12: No | L12: 100- Operations:110- G&A | M12: General & Administrative:G&A- Travel Expenses: | N12: General & Administrative:G&A- Personnel Expenses: | O12: =B12&" "&C12
A13: 12 | B13: Elias | C13: Kapetanopoulos | D13: Kapetanopoulos, Elias | E13: 44060 | F13: Full-Time | G13: 44060 | H13: ServiceNow | I13: Engineering | J13: Boylston | K13: No | L13: 300- ServiceNow:320- Engineering | M13: General & Administrative:G&A- Travel Expenses: | N13: Sales & Marketing:Sales & Marketing- Personnel Expenses: | O13: =B13&" "&C13
... A252: 259 | B252: Brendan | C252: Nolan | D252: Nolan, Brendan | E252: 46084 | F252: Full-Time | G252: 46084 | H252: ServiceNow | I252: Engineering | J252: Remote | K252: Yes | L252: 300- ServiceNow:320- Engineering | M252: Cost of Goods Sold:COGS- Travel Expenses: | N252: Cost of Goods Sold:COGS- Personnel Expense: | O252: =B252&" "&C252
A253: 261 | B253: Dan | C253: Hennessy | D253: Hennessy, Dan | F253: Full-Time | G253: 46097 | H253: Datadog | I253: Engineering | J253: Remote | L253: 200- Datadog:220- Engineering | M253: Cost of Goods Sold:COGS- Travel Expenses: | N253: Cost of Goods Sold:COGS- Personnel Expense: | O253: =B253&" "&C253
A254: 260 | B254: Talon | C254: Walz | D254: Walz, Talon | F254: Full-Time | G254: 46091 | H254: ServiceNow | I254: Engineering | J254: Remote | K254: Yes | L254: 300- ServiceNow:320- Engineering | M254: Cost of Goods Sold:COGS- Travel Expenses: | N254: Cost of Goods Sold:COGS- Personnel Expense: | O254: =B254&" "&C254
A255: 262 | B255: Christopher | C255: Turner | D255: Turner, Christopher | F255: Full-Time | G255: 46076 | H255: Datadog | I255: Engineering | J255: Boylston | K255: Yes | L255: 200- Datadog:220- Engineering | M255: Cost of Goods Sold:COGS- Travel Expenses: | N255: Cost of Goods Sold:COGS- Personnel Expense: | O255: =B255&" "&C255
A256: 263 | B256: Evan | C256: Mitchell | D256: Mitchell, Evan | F256: Full-Time | G256: 46083 | H256: Datadog | I256: Engineering | J256: Boylston | K256: Yes | L256: 200- Datadog:220- Engineering | M256: Cost of Goods Sold:COGS- Travel Expenses: | N256: Cost of Goods Sold:COGS- Personnel Expense: | O256: =B256&" "&C256
A257: 264 | B257: Tyler | C257: Grimshaw | D257: Grimshaw, Tyler | F257: Full-Time | G257: 46132 | H257: Datadog | I257: Sales | J257: Remote | K257: No | L257: 200- Datadog:230- Sales | M257: Sales & Marketing:Sales & Marketing- Travel Expenses: | N257: Sales & Marketing:Sales & Marketing- Personnel Expenses: | O257: =B257&" "&C257
A258: 266 | B258: Samara | C258: McVey | D258: McVey, Samara | F258: Full-Time | G258: 46168 | H258: ServiceNow | I258: Project Management | J258: Boylston | K258: No | L258: 300- ServiceNow:310- Delivery | M258: General & Administrative:G&A- Travel Expenses: | N258: General & Administrative:G&A- Personnel Expenses: | O258: =B258&" "&C258
A259: 268 | B259: Jacy | C259: Hennawy | D259: Hennawy, Jacy | F259: Full-Time | G259: 46105 | H259: Operations | I259: People Operations | J259: Boylston | K259: No | L259: 100- Operations:110- G&A | M259: General & Administrative:G&A- Travel Expenses: | N259: General & Administrative:G&A- Personnel Expenses: | O259: =B259&" "&C259
A260: 269 | B260: Brian | C260: McGonigal | D260: McGonigal, Brian | F260: Full-Time | G260: 46118 | H260: ServiceNow | I260: Sales | J260: Remote | K260: No | L260: 300- ServiceNow:330- Sales | M260: Sales & Marketing:Sales & Marketing- Travel Expenses: | N260: Sales & Marketing:Sales & Marketing- Personnel Expenses: | O260: =B260&" "&C260
A261: 270 | B261: James | C261: Dean | D261: Dean, James | F261: Full-Time | G261: 46209 | H261: Datadog | I261: Sales | J261: Non-US | K261: No | L261: 200- Datadog:230- Sales | M261: Sales & Marketing:Sales & Marketing- Travel Expenses: | N261: Sales & Marketing:Sales & Marketing- Personnel Expenses: | O261: =B261&" "&C261
A262: 271 | B262: Marsha | C262: Whitman | D262: Whitman, Marsha | F262: Full-Time | G262: 46133 | H262: ServiceNow | I262: Project Management | J262: Boylston | K262: Yes | L262: 300- ServiceNow:310- Delivery | M262: Cost of Goods Sold:COGS- Travel Expenses: | N262: Cost of Goods Sold:COGS- Personnel Expense: | O262: =B262&" "&C262
A263: 273 | B263: Michael | C263: Button | D263: Button, Michael | F263: Full-Time | G263: 46153 | H263: Operations | I263: Operations | J263: Boylston | K263: No | L263: 100- Operations:110- G&A | M263: General & Administrative:G&A- Travel Expenses: | N263: General & Administrative:G&A- Personnel Expenses: | O263: =B263&" "&C263
A264: 274 | B264: Robin | C264: Wiggs | D264: Wiggs, Robin | F264: Full-Time | G264: 46132 | H264: Datadog | I264: Engineering | J264: Non-US | K264: Yes | L264: 200- Datadog:220- Engineering | M264: Cost of Goods Sold:COGS- Travel Expenses: | N264: Cost of Goods Sold:COGS- Personnel Expense: | O264: =B264&" "&C264
A265: 275 | B265: John | C265: Fennell | D265: Fennell, John | F265: Full-Time | G265: 46160 | H265: Operations | I265: Marketing | J265: Boylston | K265: No | L265: 100- Operations:120- Marketing | M265: Sales & Marketing:Sales & Marketing- Travel Expenses: | N265: Sales & Marketing:Sales & Marketing- Personnel Expenses: | O265: =B265&" "&C265
... A270: 284 | B270: Lenny | C270: Caraballo | D270: Caraballo, Lenny | F270: Full-Time | G270: 46181 | H270: Datadog | I270: Engineering | J270: Boylston | K270: No | L270: 200- Datadog:220- Engineering | M270: General & Administrative:G&A- Travel Expenses: | N270: General & Administrative:G&A- Personnel Expenses: | O270: =B270&" "&C270
A271: 285 | B271: Anthony | C271: Nguyen | D271: Nguyen, Anthony | F271: Full-Time | G271: 46209 | H271: Datadog | I271: Engineering | K271: Yes | L271: 200- Datadog:220- Engineering | M271: Cost of Goods Sold:COGS- Travel Expenses: | N271: Cost of Goods Sold:COGS- Personnel Expense: | O271: =B271&" "&C271
A272: 286 | B272: Paulina | C272: Mateo | D272: Mateo, Paulina | F272: Full-Time | H272: ServiceNow | I272: OCM Specialist | J272: Boylston | K272: Yes | L272: 300- ServiceNow:310- Delivery | M272: Cost of Goods Sold:COGS- Travel Expenses: | N272: Cost of Goods Sold:COGS- Personnel Expense: | O272: =B272&" "&C272
A273: 289 | B273: Jared | C273: Kennedy | D273: Kennedy, Jared | F273: Full-Time | H273: Datadog | I273: Sales | J273: Non-Us | K273: No | L273: 200- Datadog:230- Sales | M273: Sales & Marketing:Sales & Marketing- Travel Expenses: | N273: General & Administrative:G&A- Personnel Expenses: | O273: =B273&" "&C273
