Workbook

Sheet Credit Card Charge
A1: Reference number | B1: CC account | C1: Line: Amount | D1: Name | E1: Type | F1: Line: Account | G1: Credit | H1: Currency | I1: Location | J1: Exchange Rate | K1: Global tax calculation | L1: Update Credit Card Charge | M1: Line: Billable status | N1: Line: Class | O1: Line: Customer | P1: Line: Tax code | Q1: Line: Description | R1: Line: Tax amount | S1: Line: Markup percent | T1: Item: Product | U1: Item: Quantity | V1: Item: Unit price | W1: Payment method | X1: Memo | Y1: Txn date | Z1: Txn source | AA1: Total tax | AB1: Transaction Location Type | AC1: Attachment: File Link | AD1: Attachment: Id | AE1: Attachment: Attach to email
B2: ='QBO Transactions'!$U4 -> Brex Credit Card | C2: ='QBO Transactions'!$S4 -> 53 | D2: ='QBO Transactions'!$R4 -> SpotHero | F2: ='QBO Transactions'!$X4 -> Cost of Goods Sold:COGS- Travel Expenses:Ground Transportation | N2: ='QBO Transactions'!$Y4 -> 200- Datadog:220- Engineering | Q2: ='QBO Transactions'!$T4 -> SPOTHERO 844-356-8054 MASTERCARD-XXXXXXPJG2AN-Logan Rohloff | X2: =Q2 -> SPOTHERO 844-356-8054 MASTERCARD-XXXXXXPJG2AN-Logan Rohloff | Y2: ='QBO Transactions'!$Q4 -> 46233
B3: ='QBO Transactions'!$U5 -> Brex Credit Card | C3: ='QBO Transactions'!$S5 -> 5207.23 | D3: ='QBO Transactions'!$R5 -> Anthropic | F3: ='QBO Transactions'!$X5 -> General & Administrative:Software Licenses | N3: ='QBO Transactions'!$Y5 -> 100- Operations:110- G&A | Q3: ='QBO Transactions'!$T5 -> ANTHROPIC MASTERCARD-XXXXXXQYD6Y9-Eric Rabkin | X3: =Q3 -> ANTHROPIC MASTERCARD-XXXXXXQYD6Y9-Eric Rabkin | Y3: ='QBO Transactions'!$Q5 -> 46233
B4: ='QBO Transactions'!$U6 -> Brex Credit Card | C4: ='QBO Transactions'!$S6 -> 78.95 | D4: ='QBO Transactions'!$R6 -> Uber | F4: ='QBO Transactions'!$X6 -> General & Administrative:G&A- Travel Expenses:Ground Transportation | N4: ='QBO Transactions'!$Y6 -> 300- ServiceNow:320- Engineering | Q4: ='QBO Transactions'!$T6 -> UBER *TRIP MASTERCARD-XXXXXX9HTP2T-Daniel Blauvelt | X4: =Q4 -> UBER *TRIP MASTERCARD-XXXXXX9HTP2T-Daniel Blauvelt | Y4: ='QBO Transactions'!$Q6 -> 46233
B5: ='QBO Transactions'!$U7 -> Brex Credit Card | C5: ='QBO Transactions'!$S7 -> 37.03 | D5: ='QBO Transactions'!$R7 -> Sweeney's | F5: ='QBO Transactions'!$X7 -> Sales & Marketing:Sales & Marketing- Travel Expenses:Meals & Entertainment | N5: ='QBO Transactions'!$Y7 -> 300- ServiceNow:330- Sales | Q5: ='QBO Transactions'!$T7 -> TST*SWEENEYS MASTERCARD-XXXXXXNQXBCA-Ryan Hale | X5: =Q5 -> TST*SWEENEYS MASTERCARD-XXXXXXNQXBCA-Ryan Hale | Y5: ='QBO Transactions'!$Q7 -> 46233
B6: ='QBO Transactions'!$U8 -> Brex Credit Card | C6: ='QBO Transactions'!$S8 -> 41.38 | D6: ='QBO Transactions'!$R8 -> Uber | F6: ='QBO Transactions'!$X8 -> Sales & Marketing:Sales & Marketing- Travel Expenses:Ground Transportation | N6: ='QBO Transactions'!$Y8 -> 200- Datadog:230- Sales | Q6: ='QBO Transactions'!$T8 -> UBER *EATS HELP.UBER.C MASTERCARD-XXXXXXFXJBXL-Jackson Donahoe | X6: =Q6 -> UBER *EATS HELP.UBER.C MASTERCARD-XXXXXXFXJBXL-Jackson Donahoe | Y6: ='QBO Transactions'!$Q8 -> 46233
B7: ='QBO Transactions'!$U9 -> Brex Credit Card | C7: ='QBO Transactions'!$S9 -> 20.99 | D7: ='QBO Transactions'!$R9 -> Uber | F7: ='QBO Transactions'!$X9 -> General & Administrative:G&A- Travel Expenses:Ground Transportation | N7: ='QBO Transactions'!$Y9 -> 100- Operations:110- G&A | Q7: ='QBO Transactions'!$T9 -> UBER *TRIP MASTERCARD-XXXXXX113XV3-Michael Button | X7: =Q7 -> UBER *TRIP MASTERCARD-XXXXXX113XV3-Michael Button | Y7: ='QBO Transactions'!$Q9 -> 46233
B8: ='QBO Transactions'!$U10 -> Brex Credit Card | C8: ='QBO Transactions'!$S10 -> 8 | D8: ='QBO Transactions'!$R10 -> Uber | F8: ='QBO Transactions'!$X10 -> Sales & Marketing:Sales & Marketing- Travel Expenses:Ground Transportation | N8: ='QBO Transactions'!$Y10 -> 100- Operations:120- Marketing | Q8: ='QBO Transactions'!$T10 -> UBER *TRIP MASTERCARD-XXXXXXPLNGVU-Leslee Brady | X8: =Q8 -> UBER *TRIP MASTERCARD-XXXXXXPLNGVU-Leslee Brady | Y8: ='QBO Transactions'!$Q10 -> 46233
B9: ='QBO Transactions'!$U11 -> Brex Credit Card | C9: ='QBO Transactions'!$S11 -> 35.98 | D9: ='QBO Transactions'!$R11 -> Uber | F9: ='QBO Transactions'!$X11 -> Cost of Goods Sold:COGS- Travel Expenses:Ground Transportation | N9: ='QBO Transactions'!$Y11 -> 300- ServiceNow:320- Engineering | Q9: ='QBO Transactions'!$T11 -> UBER *TRIP MASTERCARD-XXXXXXDU86DC-William Watson | X9: =Q9 -> UBER *TRIP MASTERCARD-XXXXXXDU86DC-William Watson | Y9: ='QBO Transactions'!$Q11 -> 46233
B10: ='QBO Transactions'!$U12 -> Brex Credit Card | C10: ='QBO Transactions'!$S12 -> 5 | D10: ='QBO Transactions'!$R12 -> Uber | F10: ='QBO Transactions'!$X12 -> Cost of Goods Sold:COGS- Travel Expenses:Ground Transportation | N10: ='QBO Transactions'!$Y12 -> 300- ServiceNow:320- Engineering | Q10: ='QBO Transactions'!$T12 -> UBER *TRIP MASTERCARD-XXXXXXRH0ON1-Jonathan Stricklin | X10: =Q10 -> UBER *TRIP MASTERCARD-XXXXXXRH0ON1-Jonathan Stricklin | Y10: ='QBO Transactions'!$Q12 -> 46233
B11: ='QBO Transactions'!$U13 -> Brex Credit Card | C11: ='QBO Transactions'!$S13 -> 47.1 | D11: ='QBO Transactions'!$R13 -> Uber | F11: ='QBO Transactions'!$X13 -> General & Administrative:G&A- Travel Expenses:Ground Transportation | N11: ='QBO Transactions'!$Y13 -> 100- Operations:110- G&A | Q11: ='QBO Transactions'!$T13 -> UBER *TRIP MASTERCARD-XXXXXXBVS4W8-Frederick Simpson | X11: =Q11 -> UBER *TRIP MASTERCARD-XXXXXXBVS4W8-Frederick Simpson | Y11: ='QBO Transactions'!$Q13 -> 46233
B12: ='QBO Transactions'!$U14 -> Brex Credit Card | C12: ='QBO Transactions'!$S14 -> 83.96 | D12: ='QBO Transactions'!$R14 -> Uber | F12: ='QBO Transactions'!$X14 -> General & Administrative:G&A- Travel Expenses:Ground Transportation | N12: ='QBO Transactions'!$Y14 -> 100- Operations:110- G&A | Q12: ='QBO Transactions'!$T14 -> UBER *TRIP MASTERCARD-XXXXXXF6IXA9-Michael Button | X12: =Q12 -> UBER *TRIP MASTERCARD-XXXXXXF6IXA9-Michael Button | Y12: ='QBO Transactions'!$Q14 -> 46233
B13: ='QBO Transactions'!$U15 -> Brex Credit Card | C13: ='QBO Transactions'!$S15 -> 20.27 | D13: ='QBO Transactions'!$R15 -> Uber | F13: ='QBO Transactions'!$X15 -> Cost of Goods Sold:COGS- Travel Expenses:Ground Transportation | N13: ='QBO Transactions'!$Y15 -> 300- ServiceNow:320- Engineering | Q13: ='QBO Transactions'!$T15 -> UBER *TRIP MASTERCARD-XXXXXXO1EQ9C-Tokuya Takahashi | X13: =Q13 -> UBER *TRIP MASTERCARD-XXXXXXO1EQ9C-Tokuya Takahashi | Y13: ='QBO Transactions'!$Q15 -> 46233
... B657: ='QBO Transactions'!$U659 | C657: ='QBO Transactions'!$S659 | D657: ='QBO Transactions'!$R659 | F657: ='QBO Transactions'!$X659 | N657: ='QBO Transactions'!$Y659 | Q657: ='QBO Transactions'!$T659 | X657: =Q657 | Y657: ='QBO Transactions'!$Q659

Sheet QBO Transactions
C1: Credit Card Account: | D1: Brex Credit Card | I1: Travel Vendor | K1: Taxi Vendor
B2: QBO Credit Card Transaction Data | I2: Food Vendor | K2: Office Vendor
B3: DATE | C3: DESCRIPTION | D3: Payee | E3: Category or Match | F3: SPENT | G3: RECEIVED | H3: xxx | I3: Payee Override | J3: Full Acct Override | K3: Parent Category Override | L3: Sub Category Override | M3: Dept Override | N3: Card # | O3: Card Name | P3: EE ID | Q3: Date | R3: Vendor | S3: Amount | T3: Updated Description | U3: Card Acct | V3: Parent Category | W3: Sub Category | X3: Line Acct | Y3: Department | Z3: Acct Check
B4: 46233 | C4: SPOTHERO 844-356-8054 MASTERCARD-XXXXXXPJG2AN-Logan Rohloff | E4: Sales & Marketing:Sales & Marketing- Travel Expenses:Ground Transportation | F4: 53 | I4: SpotHero | L4: Ground Transportation | O4: =IF(C4="", "", TRIM(RIGHT(C4, LEN(C4) - FIND("@@", SUBSTITUTE(C4, "-", "@@", LEN(C4) - LEN(SUBSTITUTE(C4, "-", ""))))))) -> Logan Rohloff | P4: =IFERROR(_xlfn.XLOOKUP(O4,'Department Listing'!$O$1:$O$395,'Department Listing'!$A$1:$A$395),IFERROR(_xlfn.XLOOKUP(O4,'Name Aliases'!$A$2:$A$1000,'Name Aliases'!$B$2:$B$1000),"")) -> 8 | Q4: =IF(ISBLANK($C4),"",$B4) -> 46233 | R4: =IF(ISBLANK($C4),"",IF(ISBLANK($I4),$D4,$I4)) -> SpotHero | S4: =IF(ISBLANK($C4),"",$F4 - $G4) -> 53 | T4: =IF(ISBLANK($C4),"",C4) -> SPOTHERO 844-356-8054 MASTERCARD-XXXXXXPJG2AN-Logan Rohloff | U4: =IF(ISBLANK($C4),"",$D$1) -> Brex Credit Card | V4: =IF(ISBLANK($B4),"",IF(ISBLANK($K4),IF(_xlfn.XLOOKUP($W4,'Category Mapping'!$C:$C,'Category Mapping'!$B:$B)="Travel",_xlfn.XLOOKUP($P4,'Department Listing'!$A:$A,'Department Listing'!$M:$M),_xlfn.XLOOKUP($W4,'Category Mapping'!$C:$C,'Category Mapping'!$D:$D)),$K4)) -> Cost of Goods Sold:COGS- Travel Expenses: | W4: =IF(ISBLANK($B4),"",IF(ISBLANK($L4),RIGHT($E4,LEN($E4) - FIND("^",SUBSTITUTE($E4,":","^",LEN($E4) - LEN(SUBSTITUTE($E4,":",""))))),$L4)) -> Ground Transportation | X4: =IF(ISBLANK($J4),$V4&$W4,$J4) -> Cost of Goods Sold:COGS- Travel Expenses:Ground Transportation | Y4: =IF(ISBLANK($M4),IFERROR(_xlfn.XLOOKUP($P4,'Department Listing'!$A:$A,'Department Listing'!$L:$L),""),$M4) -> 200- Datadog:220- Engineering | Z4: =IF(ISBLANK($B4),"",MATCH($X4,COA!$B:$B,0)) -> 124
B5: 46233 | C5: ANTHROPIC MASTERCARD-XXXXXXQYD6Y9-Eric Rabkin | E5: General & Administrative:Software Licenses | F5: 5207.23 | I5: Anthropic | L5: Software Licenses | O5: =IF(C5="", "", TRIM(RIGHT(C5, LEN(C5) - FIND("@@", SUBSTITUTE(C5, "-", "@@", LEN(C5) - LEN(SUBSTITUTE(C5, "-", ""))))))) -> Eric Rabkin | P5: =IFERROR(_xlfn.XLOOKUP(O5,'Department Listing'!$O$1:$O$395,'Department Listing'!$A$1:$A$395),IFERROR(_xlfn.XLOOKUP(O5,'Name Aliases'!$A$2:$A$1000,'Name Aliases'!$B$2:$B$1000),"")) -> 246 | Q5: =IF(ISBLANK($C5),"",$B5) -> 46233 | R5: =IF(ISBLANK($C5),"",IF(ISBLANK($I5),$D5,$I5)) -> Anthropic | S5: =IF(ISBLANK($C5),"",$F5 - $G5) -> 5207.23 | T5: =IF(ISBLANK($C5),"",C5) -> ANTHROPIC MASTERCARD-XXXXXXQYD6Y9-Eric Rabkin | U5: =IF(ISBLANK($C5),"",$D$1) -> Brex Credit Card | V5: =IF(ISBLANK($B5),"",IF(ISBLANK($K5),IF(_xlfn.XLOOKUP($W5,'Category Mapping'!$C:$C,'Category Mapping'!$B:$B)="Travel",_xlfn.XLOOKUP($P5,'Department Listing'!$A:$A,'Department Listing'!$M:$M),_xlfn.XLOOKUP($W5,'Category Mapping'!$C:$C,'Category Mapping'!$D:$D)),$K5)) -> General & Administrative: | W5: =IF(ISBLANK($B5),"",IF(ISBLANK($L5),RIGHT($E5,LEN($E5) - FIND("^",SUBSTITUTE($E5,":","^",LEN($E5) - LEN(SUBSTITUTE($E5,":",""))))),$L5)) -> Software Licenses | X5: =IF(ISBLANK($J5),$V5&$W5,$J5) -> General & Administrative:Software Licenses | Y5: =IF(ISBLANK($M5),IFERROR(_xlfn.XLOOKUP($P5,'Department Listing'!$A:$A,'Department Listing'!$L:$L),""),$M5) -> 100- Operations:110- G&A | Z5: =IF(ISBLANK($B5),"",MATCH($X5,COA!$B:$B,0)) -> 170
B6: 46233 | C6: UBER *TRIP MASTERCARD-XXXXXX9HTP2T-Daniel Blauvelt | E6: Sales & Marketing:Sales & Marketing- Travel Expenses:Ground Transportation | F6: 78.95 | I6: Uber | L6: Ground Transportation | O6: =IF(C6="", "", TRIM(RIGHT(C6, LEN(C6) - FIND("@@", SUBSTITUTE(C6, "-", "@@", LEN(C6) - LEN(SUBSTITUTE(C6, "-", ""))))))) -> Daniel Blauvelt | P6: =IFERROR(_xlfn.XLOOKUP(O6,'Department Listing'!$O$1:$O$395,'Department Listing'!$A$1:$A$395),IFERROR(_xlfn.XLOOKUP(O6,'Name Aliases'!$A$2:$A$1000,'Name Aliases'!$B$2:$B$1000),"")) -> 207 | Q6: =IF(ISBLANK($C6),"",$B6) -> 46233 | R6: =IF(ISBLANK($C6),"",IF(ISBLANK($I6),$D6,$I6)) -> Uber | S6: =IF(ISBLANK($C6),"",$F6 - $G6) -> 78.95 | T6: =IF(ISBLANK($C6),"",C6) -> UBER *TRIP MASTERCARD-XXXXXX9HTP2T-Daniel Blauvelt | U6: =IF(ISBLANK($C6),"",$D$1) -> Brex Credit Card | V6: =IF(ISBLANK($B6),"",IF(ISBLANK($K6),IF(_xlfn.XLOOKUP($W6,'Category Mapping'!$C:$C,'Category Mapping'!$B:$B)="Travel",_xlfn.XLOOKUP($P6,'Department Listing'!$A:$A,'Department Listing'!$M:$M),_xlfn.XLOOKUP($W6,'Category Mapping'!$C:$C,'Category Mapping'!$D:$D)),$K6)) -> General & Administrative:G&A- Travel Expenses: | W6: =IF(ISBLANK($B6),"",IF(ISBLANK($L6),RIGHT($E6,LEN($E6) - FIND("^",SUBSTITUTE($E6,":","^",LEN($E6) - LEN(SUBSTITUTE($E6,":",""))))),$L6)) -> Ground Transportation | X6: =IF(ISBLANK($J6),$V6&$W6,$J6) -> General & Administrative:G&A- Travel Expenses:Ground Transportation | Y6: =IF(ISBLANK($M6),IFERROR(_xlfn.XLOOKUP($P6,'Department Listing'!$A:$A,'Department Listing'!$L:$L),""),$M6) -> 300- ServiceNow:320- Engineering | Z6: =IF(ISBLANK($B6),"",MATCH($X6,COA!$B:$B,0)) -> 149
B7: 46233 | C7: TST*SWEENEYS MASTERCARD-XXXXXXNQXBCA-Ryan Hale | E7: Sales & Marketing:Sales & Marketing- Travel Expenses:Meals & Entertainment | F7: 37.03 | I7: Sweeney's | L7: Meals & Entertainment | O7: =IF(C7="", "", TRIM(RIGHT(C7, LEN(C7) - FIND("@@", SUBSTITUTE(C7, "-", "@@", LEN(C7) - LEN(SUBSTITUTE(C7, "-", ""))))))) -> Ryan Hale | P7: =IFERROR(_xlfn.XLOOKUP(O7,'Department Listing'!$O$1:$O$395,'Department Listing'!$A$1:$A$395),IFERROR(_xlfn.XLOOKUP(O7,'Name Aliases'!$A$2:$A$1000,'Name Aliases'!$B$2:$B$1000),"")) -> 222 | Q7: =IF(ISBLANK($C7),"",$B7) -> 46233 | R7: =IF(ISBLANK($C7),"",IF(ISBLANK($I7),$D7,$I7)) -> Sweeney's | S7: =IF(ISBLANK($C7),"",$F7 - $G7) -> 37.03 | T7: =IF(ISBLANK($C7),"",C7) -> TST*SWEENEYS MASTERCARD-XXXXXXNQXBCA-Ryan Hale | U7: =IF(ISBLANK($C7),"",$D$1) -> Brex Credit Card | V7: =IF(ISBLANK($B7),"",IF(ISBLANK($K7),IF(_xlfn.XLOOKUP($W7,'Category Mapping'!$C:$C,'Category Mapping'!$B:$B)="Travel",_xlfn.XLOOKUP($P7,'Department Listing'!$A:$A,'Department Listing'!$M:$M),_xlfn.XLOOKUP($W7,'Category Mapping'!$C:$C,'Category Mapping'!$D:$D)),$K7)) -> Sales & Marketing:Sales & Marketing- Travel Expenses: | W7: =IF(ISBLANK($B7),"",IF(ISBLANK($L7),RIGHT($E7,LEN($E7) - FIND("^",SUBSTITUTE($E7,":","^",LEN($E7) - LEN(SUBSTITUTE($E7,":",""))))),$L7)) -> Meals & Entertainment | X7: =IF(ISBLANK($J7),$V7&$W7,$J7) -> Sales & Marketing:Sales & Marketing- Travel Expenses:Meals & Entertainment | Y7: =IF(ISBLANK($M7),IFERROR(_xlfn.XLOOKUP($P7,'Department Listing'!$A:$A,'Department Listing'!$L:$L),""),$M7) -> 300- ServiceNow:330- Sales | Z7: =IF(ISBLANK($B7),"",MATCH($X7,COA!$B:$B,0)) -> 202
B8: 46233 | C8: UBER *EATS HELP.UBER.C MASTERCARD-XXXXXXFXJBXL-Jackson Donahoe | E8: Sales & Marketing:Sales & Marketing- Travel Expenses:Ground Transportation | F8: 41.38 | I8: Uber | L8: Ground Transportation | O8: =IF(C8="", "", TRIM(RIGHT(C8, LEN(C8) - FIND("@@", SUBSTITUTE(C8, "-", "@@", LEN(C8) - LEN(SUBSTITUTE(C8, "-", ""))))))) -> Jackson Donahoe | P8: =IFERROR(_xlfn.XLOOKUP(O8,'Department Listing'!$O$1:$O$395,'Department Listing'!$A$1:$A$395),IFERROR(_xlfn.XLOOKUP(O8,'Name Aliases'!$A$2:$A$1000,'Name Aliases'!$B$2:$B$1000),"")) -> 143 | Q8: =IF(ISBLANK($C8),"",$B8) -> 46233 | R8: =IF(ISBLANK($C8),"",IF(ISBLANK($I8),$D8,$I8)) -> Uber | S8: =IF(ISBLANK($C8),"",$F8 - $G8) -> 41.38 | T8: =IF(ISBLANK($C8),"",C8) -> UBER *EATS HELP.UBER.C MASTERCARD-XXXXXXFXJBXL-Jackson Donahoe | U8: =IF(ISBLANK($C8),"",$D$1) -> Brex Credit Card | V8: =IF(ISBLANK($B8),"",IF(ISBLANK($K8),IF(_xlfn.XLOOKUP($W8,'Category Mapping'!$C:$C,'Category Mapping'!$B:$B)="Travel",_xlfn.XLOOKUP($P8,'Department Listing'!$A:$A,'Department Listing'!$M:$M),_xlfn.XLOOKUP($W8,'Category Mapping'!$C:$C,'Category Mapping'!$D:$D)),$K8)) -> Sales & Marketing:Sales & Marketing- Travel Expenses: | W8: =IF(ISBLANK($B8),"",IF(ISBLANK($L8),RIGHT($E8,LEN($E8) - FIND("^",SUBSTITUTE($E8,":","^",LEN($E8) - LEN(SUBSTITUTE($E8,":",""))))),$L8)) -> Ground Transportation | X8: =IF(ISBLANK($J8),$V8&$W8,$J8) -> Sales & Marketing:Sales & Marketing- Travel Expenses:Ground Transportation | Y8: =IF(ISBLANK($M8),IFERROR(_xlfn.XLOOKUP($P8,'Department Listing'!$A:$A,'Department Listing'!$L:$L),""),$M8) -> 200- Datadog:230- Sales | Z8: =IF(ISBLANK($B8),"",MATCH($X8,COA!$B:$B,0)) -> 200
B9: 46233 | C9: UBER *TRIP MASTERCARD-XXXXXX113XV3-Michael Button | E9: Sales & Marketing:Sales & Marketing- Travel Expenses:Ground Transportation | F9: 20.99 | I9: Uber | L9: Ground Transportation | O9: =IF(C9="", "", TRIM(RIGHT(C9, LEN(C9) - FIND("@@", SUBSTITUTE(C9, "-", "@@", LEN(C9) - LEN(SUBSTITUTE(C9, "-", ""))))))) -> Michael Button | P9: =IFERROR(_xlfn.XLOOKUP(O9,'Department Listing'!$O$1:$O$395,'Department Listing'!$A$1:$A$395),IFERROR(_xlfn.XLOOKUP(O9,'Name Aliases'!$A$2:$A$1000,'Name Aliases'!$B$2:$B$1000),"")) -> 273 | Q9: =IF(ISBLANK($C9),"",$B9) -> 46233 | R9: =IF(ISBLANK($C9),"",IF(ISBLANK($I9),$D9,$I9)) -> Uber | S9: =IF(ISBLANK($C9),"",$F9 - $G9) -> 20.99 | T9: =IF(ISBLANK($C9),"",C9) -> UBER *TRIP MASTERCARD-XXXXXX113XV3-Michael Button | U9: =IF(ISBLANK($C9),"",$D$1) -> Brex Credit Card | V9: =IF(ISBLANK($B9),"",IF(ISBLANK($K9),IF(_xlfn.XLOOKUP($W9,'Category Mapping'!$C:$C,'Category Mapping'!$B:$B)="Travel",_xlfn.XLOOKUP($P9,'Department Listing'!$A:$A,'Department Listing'!$M:$M),_xlfn.XLOOKUP($W9,'Category Mapping'!$C:$C,'Category Mapping'!$D:$D)),$K9)) -> General & Administrative:G&A- Travel Expenses: | W9: =IF(ISBLANK($B9),"",IF(ISBLANK($L9),RIGHT($E9,LEN($E9) - FIND("^",SUBSTITUTE($E9,":","^",LEN($E9) - LEN(SUBSTITUTE($E9,":",""))))),$L9)) -> Ground Transportation | X9: =IF(ISBLANK($J9),$V9&$W9,$J9) -> General & Administrative:G&A- Travel Expenses:Ground Transportation | Y9: =IF(ISBLANK($M9),IFERROR(_xlfn.XLOOKUP($P9,'Department Listing'!$A:$A,'Department Listing'!$L:$L),""),$M9) -> 100- Operations:110- G&A | Z9: =IF(ISBLANK($B9),"",MATCH($X9,COA!$B:$B,0)) -> 149
B10: 46233 | C10: UBER *TRIP MASTERCARD-XXXXXXPLNGVU-Leslee Brady | E10: Sales & Marketing:Sales & Marketing- Travel Expenses:Ground Transportation | F10: 8 | I10: Uber | L10: Ground Transportation | O10: =IF(C10="", "", TRIM(RIGHT(C10, LEN(C10) - FIND("@@", SUBSTITUTE(C10, "-", "@@", LEN(C10) - LEN(SUBSTITUTE(C10, "-", ""))))))) -> Leslee Brady | P10: =IFERROR(_xlfn.XLOOKUP(O10,'Department Listing'!$O$1:$O$395,'Department Listing'!$A$1:$A$395),IFERROR(_xlfn.XLOOKUP(O10,'Name Aliases'!$A$2:$A$1000,'Name Aliases'!$B$2:$B$1000),"")) -> 103 | Q10: =IF(ISBLANK($C10),"",$B10) -> 46233 | R10: =IF(ISBLANK($C10),"",IF(ISBLANK($I10),$D10,$I10)) -> Uber | S10: =IF(ISBLANK($C10),"",$F10 - $G10) -> 8 | T10: =IF(ISBLANK($C10),"",C10) -> UBER *TRIP MASTERCARD-XXXXXXPLNGVU-Leslee Brady | U10: =IF(ISBLANK($C10),"",$D$1) -> Brex Credit Card | V10: =IF(ISBLANK($B10),"",IF(ISBLANK($K10),IF(_xlfn.XLOOKUP($W10,'Category Mapping'!$C:$C,'Category Mapping'!$B:$B)="Travel",_xlfn.XLOOKUP($P10,'Department Listing'!$A:$A,'Department Listing'!$M:$M),_xlfn.XLOOKUP($W10,'Category Mapping'!$C:$C,'Category Mapping'!$D:$D)),$K10)) -> Sales & Marketing:Sales & Marketing- Travel Expenses: | W10: =IF(ISBLANK($B10),"",IF(ISBLANK($L10),RIGHT($E10,LEN($E10) - FIND("^",SUBSTITUTE($E10,":","^",LEN($E10) - LEN(SUBSTITUTE($E10,":",""))))),$L10)) -> Ground Transportation | X10: =IF(ISBLANK($J10),$V10&$W10,$J10) -> Sales & Marketing:Sales & Marketing- Travel Expenses:Ground Transportation | Y10: =IF(ISBLANK($M10),IFERROR(_xlfn.XLOOKUP($P10,'Department Listing'!$A:$A,'Department Listing'!$L:$L),""),$M10) -> 100- Operations:120- Marketing | Z10: =IF(ISBLANK($B10),"",MATCH($X10,COA!$B:$B,0)) -> 200
B11: 46233 | C11: UBER *TRIP MASTERCARD-XXXXXXDU86DC-William Watson | E11: Sales & Marketing:Sales & Marketing- Travel Expenses:Ground Transportation | F11: 35.98 | I11: Uber | L11: Ground Transportation | O11: =IF(C11="", "", TRIM(RIGHT(C11, LEN(C11) - FIND("@@", SUBSTITUTE(C11, "-", "@@", LEN(C11) - LEN(SUBSTITUTE(C11, "-", ""))))))) -> William Watson | P11: =IFERROR(_xlfn.XLOOKUP(O11,'Department Listing'!$O$1:$O$395,'Department Listing'!$A$1:$A$395),IFERROR(_xlfn.XLOOKUP(O11,'Name Aliases'!$A$2:$A$1000,'Name Aliases'!$B$2:$B$1000),"")) -> 116 | Q11: =IF(ISBLANK($C11),"",$B11) -> 46233 | R11: =IF(ISBLANK($C11),"",IF(ISBLANK($I11),$D11,$I11)) -> Uber | S11: =IF(ISBLANK($C11),"",$F11 - $G11) -> 35.98 | T11: =IF(ISBLANK($C11),"",C11) -> UBER *TRIP MASTERCARD-XXXXXXDU86DC-William Watson | U11: =IF(ISBLANK($C11),"",$D$1) -> Brex Credit Card | V11: =IF(ISBLANK($B11),"",IF(ISBLANK($K11),IF(_xlfn.XLOOKUP($W11,'Category Mapping'!$C:$C,'Category Mapping'!$B:$B)="Travel",_xlfn.XLOOKUP($P11,'Department Listing'!$A:$A,'Department Listing'!$M:$M),_xlfn.XLOOKUP($W11,'Category Mapping'!$C:$C,'Category Mapping'!$D:$D)),$K11)) -> Cost of Goods Sold:COGS- Travel Expenses: | W11: =IF(ISBLANK($B11),"",IF(ISBLANK($L11),RIGHT($E11,LEN($E11) - FIND("^",SUBSTITUTE($E11,":","^",LEN($E11) - LEN(SUBSTITUTE($E11,":",""))))),$L11)) -> Ground Transportation | X11: =IF(ISBLANK($J11),$V11&$W11,$J11) -> Cost of Goods Sold:COGS- Travel Expenses:Ground Transportation | Y11: =IF(ISBLANK($M11),IFERROR(_xlfn.XLOOKUP($P11,'Department Listing'!$A:$A,'Department Listing'!$L:$L),""),$M11) -> 300- ServiceNow:320- Engineering | Z11: =IF(ISBLANK($B11),"",MATCH($X11,COA!$B:$B,0)) -> 124
B12: 46233 | C12: UBER *TRIP MASTERCARD-XXXXXXRH0ON1-Jonathan Stricklin | E12: Sales & Marketing:Sales & Marketing- Travel Expenses:Ground Transportation | F12: 5 | I12: Uber | L12: Ground Transportation | O12: =IF(C12="", "", TRIM(RIGHT(C12, LEN(C12) - FIND("@@", SUBSTITUTE(C12, "-", "@@", LEN(C12) - LEN(SUBSTITUTE(C12, "-", ""))))))) -> Jonathan Stricklin | P12: =IFERROR(_xlfn.XLOOKUP(O12,'Department Listing'!$O$1:$O$395,'Department Listing'!$A$1:$A$395),IFERROR(_xlfn.XLOOKUP(O12,'Name Aliases'!$A$2:$A$1000,'Name Aliases'!$B$2:$B$1000),"")) -> 167 | Q12: =IF(ISBLANK($C12),"",$B12) -> 46233 | R12: =IF(ISBLANK($C12),"",IF(ISBLANK($I12),$D12,$I12)) -> Uber | S12: =IF(ISBLANK($C12),"",$F12 - $G12) -> 5 | T12: =IF(ISBLANK($C12),"",C12) -> UBER *TRIP MASTERCARD-XXXXXXRH0ON1-Jonathan Stricklin | U12: =IF(ISBLANK($C12),"",$D$1) -> Brex Credit Card | V12: =IF(ISBLANK($B12),"",IF(ISBLANK($K12),IF(_xlfn.XLOOKUP($W12,'Category Mapping'!$C:$C,'Category Mapping'!$B:$B)="Travel",_xlfn.XLOOKUP($P12,'Department Listing'!$A:$A,'Department Listing'!$M:$M),_xlfn.XLOOKUP($W12,'Category Mapping'!$C:$C,'Category Mapping'!$D:$D)),$K12)) -> Cost of Goods Sold:COGS- Travel Expenses: | W12: =IF(ISBLANK($B12),"",IF(ISBLANK($L12),RIGHT($E12,LEN($E12) - FIND("^",SUBSTITUTE($E12,":","^",LEN($E12) - LEN(SUBSTITUTE($E12,":",""))))),$L12)) -> Ground Transportation | X12: =IF(ISBLANK($J12),$V12&$W12,$J12) -> Cost of Goods Sold:COGS- Travel Expenses:Ground Transportation | Y12: =IF(ISBLANK($M12),IFERROR(_xlfn.XLOOKUP($P12,'Department Listing'!$A:$A,'Department Listing'!$L:$L),""),$M12) -> 300- ServiceNow:320- Engineering | Z12: =IF(ISBLANK($B12),"",MATCH($X12,COA!$B:$B,0)) -> 124
B13: 46233 | C13: UBER *TRIP MASTERCARD-XXXXXXBVS4W8-Frederick Simpson | E13: Sales & Marketing:Sales & Marketing- Travel Expenses:Ground Transportation | F13: 47.1 | I13: Uber | L13: Ground Transportation | O13: =IF(C13="", "", TRIM(RIGHT(C13, LEN(C13) - FIND("@@", SUBSTITUTE(C13, "-", "@@", LEN(C13) - LEN(SUBSTITUTE(C13, "-", ""))))))) -> Frederick Simpson | P13: =IFERROR(_xlfn.XLOOKUP(O13,'Department Listing'!$O$1:$O$395,'Department Listing'!$A$1:$A$395),IFERROR(_xlfn.XLOOKUP(O13,'Name Aliases'!$A$2:$A$1000,'Name Aliases'!$B$2:$B$1000),"")) -> 177 | Q13: =IF(ISBLANK($C13),"",$B13) -> 46233 | R13: =IF(ISBLANK($C13),"",IF(ISBLANK($I13),$D13,$I13)) -> Uber | S13: =IF(ISBLANK($C13),"",$F13 - $G13) -> 47.1 | T13: =IF(ISBLANK($C13),"",C13) -> UBER *TRIP MASTERCARD-XXXXXXBVS4W8-Frederick Simpson | U13: =IF(ISBLANK($C13),"",$D$1) -> Brex Credit Card | V13: =IF(ISBLANK($B13),"",IF(ISBLANK($K13),IF(_xlfn.XLOOKUP($W13,'Category Mapping'!$C:$C,'Category Mapping'!$B:$B)="Travel",_xlfn.XLOOKUP($P13,'Department Listing'!$A:$A,'Department Listing'!$M:$M),_xlfn.XLOOKUP($W13,'Category Mapping'!$C:$C,'Category Mapping'!$D:$D)),$K13)) -> General & Administrative:G&A- Travel Expenses: | W13: =IF(ISBLANK($B13),"",IF(ISBLANK($L13),RIGHT($E13,LEN($E13) - FIND("^",SUBSTITUTE($E13,":","^",LEN($E13) - LEN(SUBSTITUTE($E13,":",""))))),$L13)) -> Ground Transportation | X13: =IF(ISBLANK($J13),$V13&$W13,$J13) -> General & Administrative:G&A- Travel Expenses:Ground Transportation | Y13: =IF(ISBLANK($M13),IFERROR(_xlfn.XLOOKUP($P13,'Department Listing'!$A:$A,'Department Listing'!$L:$L),""),$M13) -> 100- Operations:110- G&A | Z13: =IF(ISBLANK($B13),"",MATCH($X13,COA!$B:$B,0)) -> 149
B14: 46233 | C14: UBER *TRIP MASTERCARD-XXXXXXF6IXA9-Michael Button | E14: Sales & Marketing:Sales & Marketing- Travel Expenses:Ground Transportation | F14: 83.96 | I14: Uber | L14: Ground Transportation | O14: =IF(C14="", "", TRIM(RIGHT(C14, LEN(C14) - FIND("@@", SUBSTITUTE(C14, "-", "@@", LEN(C14) - LEN(SUBSTITUTE(C14, "-", ""))))))) -> Michael Button | P14: =IFERROR(_xlfn.XLOOKUP(O14,'Department Listing'!$O$1:$O$395,'Department Listing'!$A$1:$A$395),IFERROR(_xlfn.XLOOKUP(O14,'Name Aliases'!$A$2:$A$1000,'Name Aliases'!$B$2:$B$1000),"")) -> 273 | Q14: =IF(ISBLANK($C14),"",$B14) -> 46233 | R14: =IF(ISBLANK($C14),"",IF(ISBLANK($I14),$D14,$I14)) -> Uber | S14: =IF(ISBLANK($C14),"",$F14 - $G14) -> 83.96 | T14: =IF(ISBLANK($C14),"",C14) -> UBER *TRIP MASTERCARD-XXXXXXF6IXA9-Michael Button | U14: =IF(ISBLANK($C14),"",$D$1) -> Brex Credit Card | V14: =IF(ISBLANK($B14),"",IF(ISBLANK($K14),IF(_xlfn.XLOOKUP($W14,'Category Mapping'!$C:$C,'Category Mapping'!$B:$B)="Travel",_xlfn.XLOOKUP($P14,'Department Listing'!$A:$A,'Department Listing'!$M:$M),_xlfn.XLOOKUP($W14,'Category Mapping'!$C:$C,'Category Mapping'!$D:$D)),$K14)) -> General & Administrative:G&A- Travel Expenses: | W14: =IF(ISBLANK($B14),"",IF(ISBLANK($L14),RIGHT($E14,LEN($E14) - FIND("^",SUBSTITUTE($E14,":","^",LEN($E14) - LEN(SUBSTITUTE($E14,":",""))))),$L14)) -> Ground Transportation | X14: =IF(ISBLANK($J14),$V14&$W14,$J14) -> General & Administrative:G&A- Travel Expenses:Ground Transportation | Y14: =IF(ISBLANK($M14),IFERROR(_xlfn.XLOOKUP($P14,'Department Listing'!$A:$A,'Department Listing'!$L:$L),""),$M14) -> 100- Operations:110- G&A | Z14: =IF(ISBLANK($B14),"",MATCH($X14,COA!$B:$B,0)) -> 149
B15: 46233 | C15: UBER *TRIP MASTERCARD-XXXXXXO1EQ9C-Tokuya Takahashi | E15: Sales & Marketing:Sales & Marketing- Travel Expenses:Ground Transportation | F15: 20.27 | I15: Uber | L15: Ground Transportation | O15: =IF(C15="", "", TRIM(RIGHT(C15, LEN(C15) - FIND("@@", SUBSTITUTE(C15, "-", "@@", LEN(C15) - LEN(SUBSTITUTE(C15, "-", ""))))))) -> Tokuya Takahashi | P15: =IFERROR(_xlfn.XLOOKUP(O15,'Department Listing'!$O$1:$O$395,'Department Listing'!$A$1:$A$395),IFERROR(_xlfn.XLOOKUP(O15,'Name Aliases'!$A$2:$A$1000,'Name Aliases'!$B$2:$B$1000),"")) -> 214 | Q15: =IF(ISBLANK($C15),"",$B15) -> 46233 | R15: =IF(ISBLANK($C15),"",IF(ISBLANK($I15),$D15,$I15)) -> Uber | S15: =IF(ISBLANK($C15),"",$F15 - $G15) -> 20.27 | T15: =IF(ISBLANK($C15),"",C15) -> UBER *TRIP MASTERCARD-XXXXXXO1EQ9C-Tokuya Takahashi | U15: =IF(ISBLANK($C15),"",$D$1) -> Brex Credit Card | V15: =IF(ISBLANK($B15),"",IF(ISBLANK($K15),IF(_xlfn.XLOOKUP($W15,'Category Mapping'!$C:$C,'Category Mapping'!$B:$B)="Travel",_xlfn.XLOOKUP($P15,'Department Listing'!$A:$A,'Department Listing'!$M:$M),_xlfn.XLOOKUP($W15,'Category Mapping'!$C:$C,'Category Mapping'!$D:$D)),$K15)) -> Cost of Goods Sold:COGS- Travel Expenses: | W15: =IF(ISBLANK($B15),"",IF(ISBLANK($L15),RIGHT($E15,LEN($E15) - FIND("^",SUBSTITUTE($E15,":","^",LEN($E15) - LEN(SUBSTITUTE($E15,":",""))))),$L15)) -> Ground Transportation | X15: =IF(ISBLANK($J15),$V15&$W15,$J15) -> Cost of Goods Sold:COGS- Travel Expenses:Ground Transportation | Y15: =IF(ISBLANK($M15),IFERROR(_xlfn.XLOOKUP($P15,'Department Listing'!$A:$A,'Department Listing'!$L:$L),""),$M15) -> 300- ServiceNow:320- Engineering | Z15: =IF(ISBLANK($B15),"",MATCH($X15,COA!$B:$B,0)) -> 124
... B17: 46233 | C17: LYFT *STANDARD 07-29 MASTERCARD-XXXXXXQ5WVA4-Darshilkumar Shah | E17: Sales & Marketing:Sales & Marketing- Travel Expenses:Ground Transportation | F17: 17.94 | I17: Lyft | L17: Ground Transportation | O17: =IF(C17="", "", TRIM(RIGHT(C17, LEN(C17) - FIND("@@", SUBSTITUTE(C17, "-", "@@", LEN(C17) - LEN(SUBSTITUTE(C17, "-", ""))))))) -> Darshilkumar Shah | P17: =IFERROR(_xlfn.XLOOKUP(O17,'Department Listing'!$O$1:$O$395,'Department Listing'!$A$1:$A$395),IFERROR(_xlfn.XLOOKUP(O17,'Name Aliases'!$A$2:$A$1000,'Name Aliases'!$B$2:$B$1000),"")) -> 225 | Q17: =IF(ISBLANK($C17),"",$B17) -> 46233 | R17: =IF(ISBLANK($C17),"",IF(ISBLANK($I17),$D17,$I17)) -> Lyft | S17: =IF(ISBLANK($C17),"",$F17 - $G17) -> 17.94 | T17: =IF(ISBLANK($C17),"",C17) -> LYFT *STANDARD 07-29 MASTERCARD-XXXXXXQ5WVA4-Darshilkumar Shah | U17: =IF(ISBLANK($C17),"",$D$1) -> Brex Credit Card | V17: =IF(ISBLANK($B17),"",IF(ISBLANK($K17),IF(_xlfn.XLOOKUP($W17,'Category Mapping'!$C:$C,'Category Mapping'!$B:$B)="Travel",_xlfn.XLOOKUP($P17,'Department Listing'!$A:$A,'Department Listing'!$M:$M),_xlfn.XLOOKUP($W17,'Category Mapping'!$C:$C,'Category Mapping'!$D:$D)),$K17)) -> General & Administrative:G&A- Travel Expenses: | W17: =IF(ISBLANK($B17),"",IF(ISBLANK($L17),RIGHT($E17,LEN($E17) - FIND("^",SUBSTITUTE($E17,":","^",LEN($E17) - LEN(SUBSTITUTE($E17,":",""))))),$L17)) -> Ground Transportation | X17: =IF(ISBLANK($J17),$V17&$W17,$J17) -> General & Administrative:G&A- Travel Expenses:Ground Transportation | Y17: =IF(ISBLANK($M17),IFERROR(_xlfn.XLOOKUP($P17,'Department Listing'!$A:$A,'Department Listing'!$L:$L),""),$M17) -> 300- ServiceNow:320- Engineering | Z17: =IF(ISBLANK($B17),"",MATCH($X17,COA!$B:$B,0)) -> 149
B18: 46233 | C18: Audible*M65CI3K63 MASTERCARD-XXXXXX0V96UI-Matt Hyman | F18: 16.03 | I18: Office Vendor | L18: Dues & Subscriptions | O18: =IF(C18="", "", TRIM(RIGHT(C18, LEN(C18) - FIND("@@", SUBSTITUTE(C18, "-", "@@", LEN(C18) - LEN(SUBSTITUTE(C18, "-", ""))))))) -> Matt Hyman | P18: =IFERROR(_xlfn.XLOOKUP(O18,'Department Listing'!$O$1:$O$395,'Department Listing'!$A$1:$A$395),IFERROR(_xlfn.XLOOKUP(O18,'Name Aliases'!$A$2:$A$1000,'Name Aliases'!$B$2:$B$1000),"")) -> 24 | Q18: =IF(ISBLANK($C18),"",$B18) -> 46233 | R18: =IF(ISBLANK($C18),"",IF(ISBLANK($I18),$D18,$I18)) -> Office Vendor | S18: =IF(ISBLANK($C18),"",$F18 - $G18) -> 16.03 | T18: =IF(ISBLANK($C18),"",C18) -> Audible*M65CI3K63 MASTERCARD-XXXXXX0V96UI-Matt Hyman | U18: =IF(ISBLANK($C18),"",$D$1) -> Brex Credit Card | V18: =IF(ISBLANK($B18),"",IF(ISBLANK($K18),IF(_xlfn.XLOOKUP($W18,'Category Mapping'!$C:$C,'Category Mapping'!$B:$B)="Travel",_xlfn.XLOOKUP($P18,'Department Listing'!$A:$A,'Department Listing'!$M:$M),_xlfn.XLOOKUP($W18,'Category Mapping'!$C:$C,'Category Mapping'!$D:$D)),$K18)) -> General & Administrative:Office Expenses: | W18: =IF(ISBLANK($B18),"",IF(ISBLANK($L18),RIGHT($E18,LEN($E18) - FIND("^",SUBSTITUTE($E18,":","^",LEN($E18) - LEN(SUBSTITUTE($E18,":",""))))),$L18)) -> Dues & Subscriptions | X18: =IF(ISBLANK($J18),$V18&$W18,$J18) -> General & Administrative:Office Expenses:Dues & Subscriptions | Y18: =IF(ISBLANK($M18),IFERROR(_xlfn.XLOOKUP($P18,'Department Listing'!$A:$A,'Department Listing'!$L:$L),""),$M18) -> 300- ServiceNow:330- Sales | Z18: =IF(ISBLANK($B18),"",MATCH($X18,COA!$B:$B,0)) -> 159
B19: 46233 | C19: UBER *TRIP MASTERCARD-XXXXXXUI2GZ4-Jonathan Stricklin | E19: Sales & Marketing:Sales & Marketing- Travel Expenses:Ground Transportation | F19: 16.98 | I19: Uber | L19: Ground Transportation | O19: =IF(C19="", "", TRIM(RIGHT(C19, LEN(C19) - FIND("@@", SUBSTITUTE(C19, "-", "@@", LEN(C19) - LEN(SUBSTITUTE(C19, "-", ""))))))) -> Jonathan Stricklin | P19: =IFERROR(_xlfn.XLOOKUP(O19,'Department Listing'!$O$1:$O$395,'Department Listing'!$A$1:$A$395),IFERROR(_xlfn.XLOOKUP(O19,'Name Aliases'!$A$2:$A$1000,'Name Aliases'!$B$2:$B$1000),"")) -> 167 | Q19: =IF(ISBLANK($C19),"",$B19) -> 46233 | R19: =IF(ISBLANK($C19),"",IF(ISBLANK($I19),$D19,$I19)) -> Uber | S19: =IF(ISBLANK($C19),"",$F19 - $G19) -> 16.98 | T19: =IF(ISBLANK($C19),"",C19) -> UBER *TRIP MASTERCARD-XXXXXXUI2GZ4-Jonathan Stricklin | U19: =IF(ISBLANK($C19),"",$D$1) -> Brex Credit Card | V19: =IF(ISBLANK($B19),"",IF(ISBLANK($K19),IF(_xlfn.XLOOKUP($W19,'Category Mapping'!$C:$C,'Category Mapping'!$B:$B)="Travel",_xlfn.XLOOKUP($P19,'Department Listing'!$A:$A,'Department Listing'!$M:$M),_xlfn.XLOOKUP($W19,'Category Mapping'!$C:$C,'Category Mapping'!$D:$D)),$K19)) -> Cost of Goods Sold:COGS- Travel Expenses: | W19: =IF(ISBLANK($B19),"",IF(ISBLANK($L19),RIGHT($E19,LEN($E19) - FIND("^",SUBSTITUTE($E19,":","^",LEN($E19) - LEN(SUBSTITUTE($E19,":",""))))),$L19)) -> Ground Transportation | X19: =IF(ISBLANK($J19),$V19&$W19,$J19) -> Cost of Goods Sold:COGS- Travel Expenses:Ground Transportation | Y19: =IF(ISBLANK($M19),IFERROR(_xlfn.XLOOKUP($P19,'Department Listing'!$A:$A,'Department Listing'!$L:$L),""),$M19) -> 300- ServiceNow:320- Engineering | Z19: =IF(ISBLANK($B19),"",MATCH($X19,COA!$B:$B,0)) -> 124
B20: 46233 | C20: TST*SRV - BOSTON MASTERCARD-XXXXXXNLBUC5-Mickenzi Krpec | E20: Sales & Marketing:Sales & Marketing- Travel Expenses:Meals & Entertainment | F20: 8049.24 | I20: Food Vendor | L20: Meals & Entertainment | O20: =IF(C20="", "", TRIM(RIGHT(C20, LEN(C20) - FIND("@@", SUBSTITUTE(C20, "-", "@@", LEN(C20) - LEN(SUBSTITUTE(C20, "-", ""))))))) -> Mickenzi Krpec | P20: =IFERROR(_xlfn.XLOOKUP(O20,'Department Listing'!$O$1:$O$395,'Department Listing'!$A$1:$A$395),IFERROR(_xlfn.XLOOKUP(O20,'Name Aliases'!$A$2:$A$1000,'Name Aliases'!$B$2:$B$1000),"")) -> 170 | Q20: =IF(ISBLANK($C20),"",$B20) -> 46233 | R20: =IF(ISBLANK($C20),"",IF(ISBLANK($I20),$D20,$I20)) -> Food Vendor | S20: =IF(ISBLANK($C20),"",$F20 - $G20) -> 8049.24 | T20: =IF(ISBLANK($C20),"",C20) -> TST*SRV - BOSTON MASTERCARD-XXXXXXNLBUC5-Mickenzi Krpec | U20: =IF(ISBLANK($C20),"",$D$1) -> Brex Credit Card | V20: =IF(ISBLANK($B20),"",IF(ISBLANK($K20),IF(_xlfn.XLOOKUP($W20,'Category Mapping'!$C:$C,'Category Mapping'!$B:$B)="Travel",_xlfn.XLOOKUP($P20,'Department Listing'!$A:$A,'Department Listing'!$M:$M),_xlfn.XLOOKUP($W20,'Category Mapping'!$C:$C,'Category Mapping'!$D:$D)),$K20)) -> General & Administrative:G&A- Travel Expenses: | W20: =IF(ISBLANK($B20),"",IF(ISBLANK($L20),RIGHT($E20,LEN($E20) - FIND("^",SUBSTITUTE($E20,":","^",LEN($E20) - LEN(SUBSTITUTE($E20,":",""))))),$L20)) -> Meals & Entertainment | X20: =IF(ISBLANK($J20),$V20&$W20,$J20) -> General & Administrative:G&A- Travel Expenses:Meals & Entertainment | Y20: =IF(ISBLANK($M20),IFERROR(_xlfn.XLOOKUP($P20,'Department Listing'!$A:$A,'Department Listing'!$L:$L),""),$M20) -> 100- Operations:110- G&A | Z20: =IF(ISBLANK($B20),"",MATCH($X20,COA!$B:$B,0)) -> 151
B21: 46233 | C21: TST*SWEENEYS MASTERCARD-XXXXXX282FVU-Matt Hyman | E21: Sales & Marketing:Sales & Marketing- Travel Expenses:Meals & Entertainment | F21: 37.82 | I21: Sweeney's | L21: Meals & Entertainment | O21: =IF(C21="", "", TRIM(RIGHT(C21, LEN(C21) - FIND("@@", SUBSTITUTE(C21, "-", "@@", LEN(C21) - LEN(SUBSTITUTE(C21, "-", ""))))))) -> Matt Hyman | P21: =IFERROR(_xlfn.XLOOKUP(O21,'Department Listing'!$O$1:$O$395,'Department Listing'!$A$1:$A$395),IFERROR(_xlfn.XLOOKUP(O21,'Name Aliases'!$A$2:$A$1000,'Name Aliases'!$B$2:$B$1000),"")) -> 24 | Q21: =IF(ISBLANK($C21),"",$B21) -> 46233 | R21: =IF(ISBLANK($C21),"",IF(ISBLANK($I21),$D21,$I21)) -> Sweeney's | S21: =IF(ISBLANK($C21),"",$F21 - $G21) -> 37.82 | T21: =IF(ISBLANK($C21),"",C21) -> TST*SWEENEYS MASTERCARD-XXXXXX282FVU-Matt Hyman | U21: =IF(ISBLANK($C21),"",$D$1) -> Brex Credit Card | V21: =IF(ISBLANK($B21),"",IF(ISBLANK($K21),IF(_xlfn.XLOOKUP($W21,'Category Mapping'!$C:$C,'Category Mapping'!$B:$B)="Travel",_xlfn.XLOOKUP($P21,'Department Listing'!$A:$A,'Department Listing'!$M:$M),_xlfn.XLOOKUP($W21,'Category Mapping'!$C:$C,'Category Mapping'!$D:$D)),$K21)) -> Sales & Marketing:Sales & Marketing- Travel Expenses: | W21: =IF(ISBLANK($B21),"",IF(ISBLANK($L21),RIGHT($E21,LEN($E21) - FIND("^",SUBSTITUTE($E21,":","^",LEN($E21) - LEN(SUBSTITUTE($E21,":",""))))),$L21)) -> Meals & Entertainment | X21: =IF(ISBLANK($J21),$V21&$W21,$J21) -> Sales & Marketing:Sales & Marketing- Travel Expenses:Meals & Entertainment | Y21: =IF(ISBLANK($M21),IFERROR(_xlfn.XLOOKUP($P21,'Department Listing'!$A:$A,'Department Listing'!$L:$L),""),$M21) -> 300- ServiceNow:330- Sales | Z21: =IF(ISBLANK($B21),"",MATCH($X21,COA!$B:$B,0)) -> 202
B22: 46233 | C22: UBER *TRIP MASTERCARD-XXXXXX7O5SL0-Saurabh Premraj | E22: Sales & Marketing:Sales & Marketing- Travel Expenses:Ground Transportation | F22: 35.96 | I22: Uber | L22: Ground Transportation | O22: =IF(C22="", "", TRIM(RIGHT(C22, LEN(C22) - FIND("@@", SUBSTITUTE(C22, "-", "@@", LEN(C22) - LEN(SUBSTITUTE(C22, "-", ""))))))) -> Saurabh Premraj | P22: =IFERROR(_xlfn.XLOOKUP(O22,'Department Listing'!$O$1:$O$395,'Department Listing'!$A$1:$A$395),IFERROR(_xlfn.XLOOKUP(O22,'Name Aliases'!$A$2:$A$1000,'Name Aliases'!$B$2:$B$1000),"")) -> 199 | Q22: =IF(ISBLANK($C22),"",$B22) -> 46233 | R22: =IF(ISBLANK($C22),"",IF(ISBLANK($I22),$D22,$I22)) -> Uber | S22: =IF(ISBLANK($C22),"",$F22 - $G22) -> 35.96 | T22: =IF(ISBLANK($C22),"",C22) -> UBER *TRIP MASTERCARD-XXXXXX7O5SL0-Saurabh Premraj | U22: =IF(ISBLANK($C22),"",$D$1) -> Brex Credit Card | V22: =IF(ISBLANK($B22),"",IF(ISBLANK($K22),IF(_xlfn.XLOOKUP($W22,'Category Mapping'!$C:$C,'Category Mapping'!$B:$B)="Travel",_xlfn.XLOOKUP($P22,'Department Listing'!$A:$A,'Department Listing'!$M:$M),_xlfn.XLOOKUP($W22,'Category Mapping'!$C:$C,'Category Mapping'!$D:$D)),$K22)) -> Cost of Goods Sold:COGS- Travel Expenses: | W22: =IF(ISBLANK($B22),"",IF(ISBLANK($L22),RIGHT($E22,LEN($E22) - FIND("^",SUBSTITUTE($E22,":","^",LEN($E22) - LEN(SUBSTITUTE($E22,":",""))))),$L22)) -> Ground Transportation | X22: =IF(ISBLANK($J22),$V22&$W22,$J22) -> Cost of Goods Sold:COGS- Travel Expenses:Ground Transportation | Y22: =IF(ISBLANK($M22),IFERROR(_xlfn.XLOOKUP($P22,'Department Listing'!$A:$A,'Department Listing'!$L:$L),""),$M22) -> 200- Datadog:220- Engineering | Z22: =IF(ISBLANK($B22),"",MATCH($X22,COA!$B:$B,0)) -> 124
B23: 46233 | C23: UBER *TRIP MASTERCARD-XXXXXXQ0RO6W-Zayn Moselhy | E23: Sales & Marketing:Sales & Marketing- Travel Expenses:Ground Transportation | F23: 28.99 | I23: Uber | L23: Ground Transportation | O23: =IF(C23="", "", TRIM(RIGHT(C23, LEN(C23) - FIND("@@", SUBSTITUTE(C23, "-", "@@", LEN(C23) - LEN(SUBSTITUTE(C23, "-", ""))))))) -> Zayn Moselhy | P23: =IFERROR(_xlfn.XLOOKUP(O23,'Department Listing'!$O$1:$O$395,'Department Listing'!$A$1:$A$395),IFERROR(_xlfn.XLOOKUP(O23,'Name Aliases'!$A$2:$A$1000,'Name Aliases'!$B$2:$B$1000),"")) -> 184 | Q23: =IF(ISBLANK($C23),"",$B23) -> 46233 | R23: =IF(ISBLANK($C23),"",IF(ISBLANK($I23),$D23,$I23)) -> Uber | S23: =IF(ISBLANK($C23),"",$F23 - $G23) -> 28.99 | T23: =IF(ISBLANK($C23),"",C23) -> UBER *TRIP MASTERCARD-XXXXXXQ0RO6W-Zayn Moselhy | U23: =IF(ISBLANK($C23),"",$D$1) -> Brex Credit Card | V23: =IF(ISBLANK($B23),"",IF(ISBLANK($K23),IF(_xlfn.XLOOKUP($W23,'Category Mapping'!$C:$C,'Category Mapping'!$B:$B)="Travel",_xlfn.XLOOKUP($P23,'Department Listing'!$A:$A,'Department Listing'!$M:$M),_xlfn.XLOOKUP($W23,'Category Mapping'!$C:$C,'Category Mapping'!$D:$D)),$K23)) -> General & Administrative:G&A- Travel Expenses: | W23: =IF(ISBLANK($B23),"",IF(ISBLANK($L23),RIGHT($E23,LEN($E23) - FIND("^",SUBSTITUTE($E23,":","^",LEN($E23) - LEN(SUBSTITUTE($E23,":",""))))),$L23)) -> Ground Transportation | X23: =IF(ISBLANK($J23),$V23&$W23,$J23) -> General & Administrative:G&A- Travel Expenses:Ground Transportation | Y23: =IF(ISBLANK($M23),IFERROR(_xlfn.XLOOKUP($P23,'Department Listing'!$A:$A,'Department Listing'!$L:$L),""),$M23) -> 100- Operations:110- G&A | Z23: =IF(ISBLANK($B23),"",MATCH($X23,COA!$B:$B,0)) -> 149
B24: 46233 | C24: LYFT *SCHD STD 07-29 MASTERCARD-XXXXXX1Y2IYE-Patrick Donovan | E24: Sales & Marketing:Sales & Marketing- Travel Expenses:Ground Transportation | F24: 55.91 | I24: Lyft | L24: Ground Transportation | O24: =IF(C24="", "", TRIM(RIGHT(C24, LEN(C24) - FIND("@@", SUBSTITUTE(C24, "-", "@@", LEN(C24) - LEN(SUBSTITUTE(C24, "-", ""))))))) -> Patrick Donovan | P24: =IFERROR(_xlfn.XLOOKUP(O24,'Department Listing'!$O$1:$O$395,'Department Listing'!$A$1:$A$395),IFERROR(_xlfn.XLOOKUP(O24,'Name Aliases'!$A$2:$A$1000,'Name Aliases'!$B$2:$B$1000),"")) -> 137 | Q24: =IF(ISBLANK($C24),"",$B24) -> 46233 | R24: =IF(ISBLANK($C24),"",IF(ISBLANK($I24),$D24,$I24)) -> Lyft | S24: =IF(ISBLANK($C24),"",$F24 - $G24) -> 55.91 | T24: =IF(ISBLANK($C24),"",C24) -> LYFT *SCHD STD 07-29 MASTERCARD-XXXXXX1Y2IYE-Patrick Donovan | U24: =IF(ISBLANK($C24),"",$D$1) -> Brex Credit Card | V24: =IF(ISBLANK($B24),"",IF(ISBLANK($K24),IF(_xlfn.XLOOKUP($W24,'Category Mapping'!$C:$C,'Category Mapping'!$B:$B)="Travel",_xlfn.XLOOKUP($P24,'Department Listing'!$A:$A,'Department Listing'!$M:$M),_xlfn.XLOOKUP($W24,'Category Mapping'!$C:$C,'Category Mapping'!$D:$D)),$K24)) -> Cost of Goods Sold:COGS- Travel Expenses: | W24: =IF(ISBLANK($B24),"",IF(ISBLANK($L24),RIGHT($E24,LEN($E24) - FIND("^",SUBSTITUTE($E24,":","^",LEN($E24) - LEN(SUBSTITUTE($E24,":",""))))),$L24)) -> Ground Transportation | X24: =IF(ISBLANK($J24),$V24&$W24,$J24) -> Cost of Goods Sold:COGS- Travel Expenses:Ground Transportation | Y24: =IF(ISBLANK($M24),IFERROR(_xlfn.XLOOKUP($P24,'Department Listing'!$A:$A,'Department Listing'!$L:$L),""),$M24) -> 200- Datadog:210- Delivery | Z24: =IF(ISBLANK($B24),"",MATCH($X24,COA!$B:$B,0)) -> 124
B25: 46233 | C25: UBER *TRIP MASTERCARD-XXXXXXG5H8YM-Frederick Simpson | E25: Sales & Marketing:Sales & Marketing- Travel Expenses:Ground Transportation | F25: 25.81 | I25: Uber | L25: Ground Transportation | O25: =IF(C25="", "", TRIM(RIGHT(C25, LEN(C25) - FIND("@@", SUBSTITUTE(C25, "-", "@@", LEN(C25) - LEN(SUBSTITUTE(C25, "-", ""))))))) -> Frederick Simpson | P25: =IFERROR(_xlfn.XLOOKUP(O25,'Department Listing'!$O$1:$O$395,'Department Listing'!$A$1:$A$395),IFERROR(_xlfn.XLOOKUP(O25,'Name Aliases'!$A$2:$A$1000,'Name Aliases'!$B$2:$B$1000),"")) -> 177 | Q25: =IF(ISBLANK($C25),"",$B25) -> 46233 | R25: =IF(ISBLANK($C25),"",IF(ISBLANK($I25),$D25,$I25)) -> Uber | S25: =IF(ISBLANK($C25),"",$F25 - $G25) -> 25.81 | T25: =IF(ISBLANK($C25),"",C25) -> UBER *TRIP MASTERCARD-XXXXXXG5H8YM-Frederick Simpson | U25: =IF(ISBLANK($C25),"",$D$1) -> Brex Credit Card | V25: =IF(ISBLANK($B25),"",IF(ISBLANK($K25),IF(_xlfn.XLOOKUP($W25,'Category Mapping'!$C:$C,'Category Mapping'!$B:$B)="Travel",_xlfn.XLOOKUP($P25,'Department Listing'!$A:$A,'Department Listing'!$M:$M),_xlfn.XLOOKUP($W25,'Category Mapping'!$C:$C,'Category Mapping'!$D:$D)),$K25)) -> General & Administrative:G&A- Travel Expenses: | W25: =IF(ISBLANK($B25),"",IF(ISBLANK($L25),RIGHT($E25,LEN($E25) - FIND("^",SUBSTITUTE($E25,":","^",LEN($E25) - LEN(SUBSTITUTE($E25,":",""))))),$L25)) -> Ground Transportation | X25: =IF(ISBLANK($J25),$V25&$W25,$J25) -> General & Administrative:G&A- Travel Expenses:Ground Transportation | Y25: =IF(ISBLANK($M25),IFERROR(_xlfn.XLOOKUP($P25,'Department Listing'!$A:$A,'Department Listing'!$L:$L),""),$M25) -> 100- Operations:110- G&A | Z25: =IF(ISBLANK($B25),"",MATCH($X25,COA!$B:$B,0)) -> 149
B26: 46233 | C26: UBER *TRIP MASTERCARD-XXXXXXEGMHWC-Tyler Grimshaw | E26: Sales & Marketing:Sales & Marketing- Travel Expenses:Ground Transportation | F26: 31.99 | I26: Uber | L26: Ground Transportation | O26: =IF(C26="", "", TRIM(RIGHT(C26, LEN(C26) - FIND("@@", SUBSTITUTE(C26, "-", "@@", LEN(C26) - LEN(SUBSTITUTE(C26, "-", ""))))))) -> Tyler Grimshaw | P26: =IFERROR(_xlfn.XLOOKUP(O26,'Department Listing'!$O$1:$O$395,'Department Listing'!$A$1:$A$395),IFERROR(_xlfn.XLOOKUP(O26,'Name Aliases'!$A$2:$A$1000,'Name Aliases'!$B$2:$B$1000),"")) -> 264 | Q26: =IF(ISBLANK($C26),"",$B26) -> 46233 | R26: =IF(ISBLANK($C26),"",IF(ISBLANK($I26),$D26,$I26)) -> Uber | S26: =IF(ISBLANK($C26),"",$F26 - $G26) -> 31.99 | T26: =IF(ISBLANK($C26),"",C26) -> UBER *TRIP MASTERCARD-XXXXXXEGMHWC-Tyler Grimshaw | U26: =IF(ISBLANK($C26),"",$D$1) -> Brex Credit Card | V26: =IF(ISBLANK($B26),"",IF(ISBLANK($K26),IF(_xlfn.XLOOKUP($W26,'Category Mapping'!$C:$C,'Category Mapping'!$B:$B)="Travel",_xlfn.XLOOKUP($P26,'Department Listing'!$A:$A,'Department Listing'!$M:$M),_xlfn.XLOOKUP($W26,'Category Mapping'!$C:$C,'Category Mapping'!$D:$D)),$K26)) -> Sales & Marketing:Sales & Marketing- Travel Expenses: | W26: =IF(ISBLANK($B26),"",IF(ISBLANK($L26),RIGHT($E26,LEN($E26) - FIND("^",SUBSTITUTE($E26,":","^",LEN($E26) - LEN(SUBSTITUTE($E26,":",""))))),$L26)) -> Ground Transportation | X26: =IF(ISBLANK($J26),$V26&$W26,$J26) -> Sales & Marketing:Sales & Marketing- Travel Expenses:Ground Transportation | Y26: =IF(ISBLANK($M26),IFERROR(_xlfn.XLOOKUP($P26,'Department Listing'!$A:$A,'Department Listing'!$L:$L),""),$M26) -> 200- Datadog:230- Sales | Z26: =IF(ISBLANK($B26),"",MATCH($X26,COA!$B:$B,0)) -> 200
B27: 46233 | C27: UBER *TRIP MASTERCARD-XXXXXXR1SOS6-Toni Manning | E27: Sales & Marketing:Sales & Marketing- Travel Expenses:Ground Transportation | F27: 3 | I27: Uber | L27: Ground Transportation | O27: =IF(C27="", "", TRIM(RIGHT(C27, LEN(C27) - FIND("@@", SUBSTITUTE(C27, "-", "@@", LEN(C27) - LEN(SUBSTITUTE(C27, "-", ""))))))) -> Toni Manning | P27: =IFERROR(_xlfn.XLOOKUP(O27,'Department Listing'!$O$1:$O$395,'Department Listing'!$A$1:$A$395),IFERROR(_xlfn.XLOOKUP(O27,'Name Aliases'!$A$2:$A$1000,'Name Aliases'!$B$2:$B$1000),"")) -> 121 | Q27: =IF(ISBLANK($C27),"",$B27) -> 46233 | R27: =IF(ISBLANK($C27),"",IF(ISBLANK($I27),$D27,$I27)) -> Uber | S27: =IF(ISBLANK($C27),"",$F27 - $G27) -> 3 | T27: =IF(ISBLANK($C27),"",C27) -> UBER *TRIP MASTERCARD-XXXXXXR1SOS6-Toni Manning | U27: =IF(ISBLANK($C27),"",$D$1) -> Brex Credit Card | V27: =IF(ISBLANK($B27),"",IF(ISBLANK($K27),IF(_xlfn.XLOOKUP($W27,'Category Mapping'!$C:$C,'Category Mapping'!$B:$B)="Travel",_xlfn.XLOOKUP($P27,'Department Listing'!$A:$A,'Department Listing'!$M:$M),_xlfn.XLOOKUP($W27,'Category Mapping'!$C:$C,'Category Mapping'!$D:$D)),$K27)) -> Sales & Marketing:Sales & Marketing- Travel Expenses: | W27: =IF(ISBLANK($B27),"",IF(ISBLANK($L27),RIGHT($E27,LEN($E27) - FIND("^",SUBSTITUTE($E27,":","^",LEN($E27) - LEN(SUBSTITUTE($E27,":",""))))),$L27)) -> Ground Transportation | X27: =IF(ISBLANK($J27),$V27&$W27,$J27) -> Sales & Marketing:Sales & Marketing- Travel Expenses:Ground Transportation | Y27: =IF(ISBLANK($M27),IFERROR(_xlfn.XLOOKUP($P27,'Department Listing'!$A:$A,'Department Listing'!$L:$L),""),$M27) -> 100- Operations:120- Marketing | Z27: =IF(ISBLANK($B27),"",MATCH($X27,COA!$B:$B,0)) -> 200
B28: 46233 | C28: UBER *TRIP MASTERCARD-XXXXXXXR4LXN-Jackson Donahoe | E28: Sales & Marketing:Sales & Marketing- Travel Expenses:Ground Transportation | F28: 12.99 | I28: Uber | L28: Ground Transportation | O28: =IF(C28="", "", TRIM(RIGHT(C28, LEN(C28) - FIND("@@", SUBSTITUTE(C28, "-", "@@", LEN(C28) - LEN(SUBSTITUTE(C28, "-", ""))))))) -> Jackson Donahoe | P28: =IFERROR(_xlfn.XLOOKUP(O28,'Department Listing'!$O$1:$O$395,'Department Listing'!$A$1:$A$395),IFERROR(_xlfn.XLOOKUP(O28,'Name Aliases'!$A$2:$A$1000,'Name Aliases'!$B$2:$B$1000),"")) -> 143 | Q28: =IF(ISBLANK($C28),"",$B28) -> 46233 | R28: =IF(ISBLANK($C28),"",IF(ISBLANK($I28),$D28,$I28)) -> Uber | S28: =IF(ISBLANK($C28),"",$F28 - $G28) -> 12.99 | T28: =IF(ISBLANK($C28),"",C28) -> UBER *TRIP MASTERCARD-XXXXXXXR4LXN-Jackson Donahoe | U28: =IF(ISBLANK($C28),"",$D$1) -> Brex Credit Card | V28: =IF(ISBLANK($B28),"",IF(ISBLANK($K28),IF(_xlfn.XLOOKUP($W28,'Category Mapping'!$C:$C,'Category Mapping'!$B:$B)="Travel",_xlfn.XLOOKUP($P28,'Department Listing'!$A:$A,'Department Listing'!$M:$M),_xlfn.XLOOKUP($W28,'Category Mapping'!$C:$C,'Category Mapping'!$D:$D)),$K28)) -> Sales & Marketing:Sales & Marketing- Travel Expenses: | W28: =IF(ISBLANK($B28),"",IF(ISBLANK($L28),RIGHT($E28,LEN($E28) - FIND("^",SUBSTITUTE($E28,":","^",LEN($E28) - LEN(SUBSTITUTE($E28,":",""))))),$L28)) -> Ground Transportation | X28: =IF(ISBLANK($J28),$V28&$W28,$J28) -> Sales & Marketing:Sales & Marketing- Travel Expenses:Ground Transportation | Y28: =IF(ISBLANK($M28),IFERROR(_xlfn.XLOOKUP($P28,'Department Listing'!$A:$A,'Department Listing'!$L:$L),""),$M28) -> 200- Datadog:230- Sales | Z28: =IF(ISBLANK($B28),"",MATCH($X28,COA!$B:$B,0)) -> 200
B29: 46233 | C29: UBER *TRIP MASTERCARD-XXXXXXWBKXK9-Robert Kolosky | E29: Sales & Marketing:Sales & Marketing- Travel Expenses:Ground Transportation | F29: 24.97 | I29: Uber | L29: Ground Transportation | O29: =IF(C29="", "", TRIM(RIGHT(C29, LEN(C29) - FIND("@@", SUBSTITUTE(C29, "-", "@@", LEN(C29) - LEN(SUBSTITUTE(C29, "-", ""))))))) -> Robert Kolosky | P29: =IFERROR(_xlfn.XLOOKUP(O29,'Department Listing'!$O$1:$O$395,'Department Listing'!$A$1:$A$395),IFERROR(_xlfn.XLOOKUP(O29,'Name Aliases'!$A$2:$A$1000,'Name Aliases'!$B$2:$B$1000),"")) -> 91 | Q29: =IF(ISBLANK($C29),"",$B29) -> 46233 | R29: =IF(ISBLANK($C29),"",IF(ISBLANK($I29),$D29,$I29)) -> Uber | S29: =IF(ISBLANK($C29),"",$F29 - $G29) -> 24.97 | T29: =IF(ISBLANK($C29),"",C29) -> UBER *TRIP MASTERCARD-XXXXXXWBKXK9-Robert Kolosky | U29: =IF(ISBLANK($C29),"",$D$1) -> Brex Credit Card | V29: =IF(ISBLANK($B29),"",IF(ISBLANK($K29),IF(_xlfn.XLOOKUP($W29,'Category Mapping'!$C:$C,'Category Mapping'!$B:$B)="Travel",_xlfn.XLOOKUP($P29,'Department Listing'!$A:$A,'Department Listing'!$M:$M),_xlfn.XLOOKUP($W29,'Category Mapping'!$C:$C,'Category Mapping'!$D:$D)),$K29)) -> Cost of Goods Sold:COGS- Travel Expenses: | W29: =IF(ISBLANK($B29),"",IF(ISBLANK($L29),RIGHT($E29,LEN($E29) - FIND("^",SUBSTITUTE($E29,":","^",LEN($E29) - LEN(SUBSTITUTE($E29,":",""))))),$L29)) -> Ground Transportation | X29: =IF(ISBLANK($J29),$V29&$W29,$J29) -> Cost of Goods Sold:COGS- Travel Expenses:Ground Transportation | Y29: =IF(ISBLANK($M29),IFERROR(_xlfn.XLOOKUP($P29,'Department Listing'!$A:$A,'Department Listing'!$L:$L),""),$M29) -> 300- ServiceNow:320- Engineering | Z29: =IF(ISBLANK($B29),"",MATCH($X29,COA!$B:$B,0)) -> 124
B30: 46233 | C30: UBER *TRIP MASTERCARD-XXXXXXLK316L-Jonathan Stricklin | E30: Sales & Marketing:Sales & Marketing- Travel Expenses:Ground Transportation | F30: 28.98 | I30: Uber | L30: Ground Transportation | O30: =IF(C30="", "", TRIM(RIGHT(C30, LEN(C30) - FIND("@@", SUBSTITUTE(C30, "-", "@@", LEN(C30) - LEN(SUBSTITUTE(C30, "-", ""))))))) -> Jonathan Stricklin | P30: =IFERROR(_xlfn.XLOOKUP(O30,'Department Listing'!$O$1:$O$395,'Department Listing'!$A$1:$A$395),IFERROR(_xlfn.XLOOKUP(O30,'Name Aliases'!$A$2:$A$1000,'Name Aliases'!$B$2:$B$1000),"")) -> 167 | Q30: =IF(ISBLANK($C30),"",$B30) -> 46233 | R30: =IF(ISBLANK($C30),"",IF(ISBLANK($I30),$D30,$I30)) -> Uber | S30: =IF(ISBLANK($C30),"",$F30 - $G30) -> 28.98 | T30: =IF(ISBLANK($C30),"",C30) -> UBER *TRIP MASTERCARD-XXXXXXLK316L-Jonathan Stricklin | U30: =IF(ISBLANK($C30),"",$D$1) -> Brex Credit Card | V30: =IF(ISBLANK($B30),"",IF(ISBLANK($K30),IF(_xlfn.XLOOKUP($W30,'Category Mapping'!$C:$C,'Category Mapping'!$B:$B)="Travel",_xlfn.XLOOKUP($P30,'Department Listing'!$A:$A,'Department Listing'!$M:$M),_xlfn.XLOOKUP($W30,'Category Mapping'!$C:$C,'Category Mapping'!$D:$D)),$K30)) -> Cost of Goods Sold:COGS- Travel Expenses: | W30: =IF(ISBLANK($B30),"",IF(ISBLANK($L30),RIGHT($E30,LEN($E30) - FIND("^",SUBSTITUTE($E30,":","^",LEN($E30) - LEN(SUBSTITUTE($E30,":",""))))),$L30)) -> Ground Transportation | X30: =IF(ISBLANK($J30),$V30&$W30,$J30) -> Cost of Goods Sold:COGS- Travel Expenses:Ground Transportation | Y30: =IF(ISBLANK($M30),IFERROR(_xlfn.XLOOKUP($P30,'Department Listing'!$A:$A,'Department Listing'!$L:$L),""),$M30) -> 300- ServiceNow:320- Engineering | Z30: =IF(ISBLANK($B30),"",MATCH($X30,COA!$B:$B,0)) -> 124
... B35: 46233 | C35: UBER *TRIP MASTERCARD-XXXXXXPOW1YO-Israel Baral | E35: Sales & Marketing:Sales & Marketing- Travel Expenses:Ground Transportation | F35: 12.94 | I35: Uber | L35: Ground Transportation | O35: =IF(C35="", "", TRIM(RIGHT(C35, LEN(C35) - FIND("@@", SUBSTITUTE(C35, "-", "@@", LEN(C35) - LEN(SUBSTITUTE(C35, "-", ""))))))) -> Israel Baral | P35: =IFERROR(_xlfn.XLOOKUP(O35,'Department Listing'!$O$1:$O$395,'Department Listing'!$A$1:$A$395),IFERROR(_xlfn.XLOOKUP(O35,'Name Aliases'!$A$2:$A$1000,'Name Aliases'!$B$2:$B$1000),"")) -> 215 | Q35: =IF(ISBLANK($C35),"",$B35) -> 46233 | R35: =IF(ISBLANK($C35),"",IF(ISBLANK($I35),$D35,$I35)) -> Uber | S35: =IF(ISBLANK($C35),"",$F35 - $G35) -> 12.94 | T35: =IF(ISBLANK($C35),"",C35) -> UBER *TRIP MASTERCARD-XXXXXXPOW1YO-Israel Baral | U35: =IF(ISBLANK($C35),"",$D$1) -> Brex Credit Card | V35: =IF(ISBLANK($B35),"",IF(ISBLANK($K35),IF(_xlfn.XLOOKUP($W35,'Category Mapping'!$C:$C,'Category Mapping'!$B:$B)="Travel",_xlfn.XLOOKUP($P35,'Department Listing'!$A:$A,'Department Listing'!$M:$M),_xlfn.XLOOKUP($W35,'Category Mapping'!$C:$C,'Category Mapping'!$D:$D)),$K35)) -> Cost of Goods Sold:COGS- Travel Expenses: | W35: =IF(ISBLANK($B35),"",IF(ISBLANK($L35),RIGHT($E35,LEN($E35) - FIND("^",SUBSTITUTE($E35,":","^",LEN($E35) - LEN(SUBSTITUTE($E35,":",""))))),$L35)) -> Ground Transportation | X35: =IF(ISBLANK($J35),$V35&$W35,$J35) -> Cost of Goods Sold:COGS- Travel Expenses:Ground Transportation | Y35: =IF(ISBLANK($M35),IFERROR(_xlfn.XLOOKUP($P35,'Department Listing'!$A:$A,'Department Listing'!$L:$L),""),$M35) -> 300- ServiceNow:320- Engineering | Z35: =IF(ISBLANK($B35),"",MATCH($X35,COA!$B:$B,0)) -> 124
B36: 46233 | C36: VPNE BackBayGarage MASTERCARD-XXXXXXYNKQQQ-Kevin Ebert | F36: 45 | I36: Back Bay Garage | L36: Ground Transportation | O36: =IF(C36="", "", TRIM(RIGHT(C36, LEN(C36) - FIND("@@", SUBSTITUTE(C36, "-", "@@", LEN(C36) - LEN(SUBSTITUTE(C36, "-", ""))))))) -> Kevin Ebert | P36: =IFERROR(_xlfn.XLOOKUP(O36,'Department Listing'!$O$1:$O$395,'Department Listing'!$A$1:$A$395),IFERROR(_xlfn.XLOOKUP(O36,'Name Aliases'!$A$2:$A$1000,'Name Aliases'!$B$2:$B$1000),"")) -> 187 | Q36: =IF(ISBLANK($C36),"",$B36) -> 46233 | R36: =IF(ISBLANK($C36),"",IF(ISBLANK($I36),$D36,$I36)) -> Back Bay Garage | S36: =IF(ISBLANK($C36),"",$F36 - $G36) -> 45 | T36: =IF(ISBLANK($C36),"",C36) -> VPNE BackBayGarage MASTERCARD-XXXXXXYNKQQQ-Kevin Ebert | U36: =IF(ISBLANK($C36),"",$D$1) -> Brex Credit Card | V36: =IF(ISBLANK($B36),"",IF(ISBLANK($K36),IF(_xlfn.XLOOKUP($W36,'Category Mapping'!$C:$C,'Category Mapping'!$B:$B)="Travel",_xlfn.XLOOKUP($P36,'Department Listing'!$A:$A,'Department Listing'!$M:$M),_xlfn.XLOOKUP($W36,'Category Mapping'!$C:$C,'Category Mapping'!$D:$D)),$K36)) -> General & Administrative:G&A- Travel Expenses: | W36: =IF(ISBLANK($B36),"",IF(ISBLANK($L36),RIGHT($E36,LEN($E36) - FIND("^",SUBSTITUTE($E36,":","^",LEN($E36) - LEN(SUBSTITUTE($E36,":",""))))),$L36)) -> Ground Transportation | X36: =IF(ISBLANK($J36),$V36&$W36,$J36) -> General & Administrative:G&A- Travel Expenses:Ground Transportation | Y36: =IF(ISBLANK($M36),IFERROR(_xlfn.XLOOKUP($P36,'Department Listing'!$A:$A,'Department Listing'!$L:$L),""),$M36) -> 100- Operations:110- G&A | Z36: =IF(ISBLANK($B36),"",MATCH($X36,COA!$B:$B,0)) -> 149
B37: 46233 | C37: UBER *TRIP MASTERCARD-XXXXXXJ2BIB9-Dor Vaknin | E37: Sales & Marketing:Sales & Marketing- Travel Expenses:Ground Transportation | F37: 50.48 | I37: Uber | L37: Ground Transportation | O37: =IF(C37="", "", TRIM(RIGHT(C37, LEN(C37) - FIND("@@", SUBSTITUTE(C37, "-", "@@", LEN(C37) - LEN(SUBSTITUTE(C37, "-", ""))))))) -> Dor Vaknin | P37: =IFERROR(_xlfn.XLOOKUP(O37,'Department Listing'!$O$1:$O$395,'Department Listing'!$A$1:$A$395),IFERROR(_xlfn.XLOOKUP(O37,'Name Aliases'!$A$2:$A$1000,'Name Aliases'!$B$2:$B$1000),"")) -> 28 | Q37: =IF(ISBLANK($C37),"",$B37) -> 46233 | R37: =IF(ISBLANK($C37),"",IF(ISBLANK($I37),$D37,$I37)) -> Uber | S37: =IF(ISBLANK($C37),"",$F37 - $G37) -> 50.48 | T37: =IF(ISBLANK($C37),"",C37) -> UBER *TRIP MASTERCARD-XXXXXXJ2BIB9-Dor Vaknin | U37: =IF(ISBLANK($C37),"",$D$1) -> Brex Credit Card | V37: =IF(ISBLANK($B37),"",IF(ISBLANK($K37),IF(_xlfn.XLOOKUP($W37,'Category Mapping'!$C:$C,'Category Mapping'!$B:$B)="Travel",_xlfn.XLOOKUP($P37,'Department Listing'!$A:$A,'Department Listing'!$M:$M),_xlfn.XLOOKUP($W37,'Category Mapping'!$C:$C,'Category Mapping'!$D:$D)),$K37)) -> Cost of Goods Sold:COGS- Travel Expenses: | W37: =IF(ISBLANK($B37),"",IF(ISBLANK($L37),RIGHT($E37,LEN($E37) - FIND("^",SUBSTITUTE($E37,":","^",LEN($E37) - LEN(SUBSTITUTE($E37,":",""))))),$L37)) -> Ground Transportation | X37: =IF(ISBLANK($J37),$V37&$W37,$J37) -> Cost of Goods Sold:COGS- Travel Expenses:Ground Transportation | Y37: =IF(ISBLANK($M37),IFERROR(_xlfn.XLOOKUP($P37,'Department Listing'!$A:$A,'Department Listing'!$L:$L),""),$M37) -> 300- ServiceNow:320- Engineering | Z37: =IF(ISBLANK($B37),"",MATCH($X37,COA!$B:$B,0)) -> 124
B38: 46233 | C38: UBER *TRIP MASTERCARD-XXXXXXFKYF9Q-Ryan Henrich | E38: Sales & Marketing:Sales & Marketing- Travel Expenses:Ground Transportation | F38: 47.98 | I38: Uber | L38: Ground Transportation | O38: =IF(C38="", "", TRIM(RIGHT(C38, LEN(C38) - FIND("@@", SUBSTITUTE(C38, "-", "@@", LEN(C38) - LEN(SUBSTITUTE(C38, "-", ""))))))) -> Ryan Henrich | P38: =IFERROR(_xlfn.XLOOKUP(O38,'Department Listing'!$O$1:$O$395,'Department Listing'!$A$1:$A$395),IFERROR(_xlfn.XLOOKUP(O38,'Name Aliases'!$A$2:$A$1000,'Name Aliases'!$B$2:$B$1000),"")) -> 154 | Q38: =IF(ISBLANK($C38),"",$B38) -> 46233 | R38: =IF(ISBLANK($C38),"",IF(ISBLANK($I38),$D38,$I38)) -> Uber | S38: =IF(ISBLANK($C38),"",$F38 - $G38) -> 47.98 | T38: =IF(ISBLANK($C38),"",C38) -> UBER *TRIP MASTERCARD-XXXXXXFKYF9Q-Ryan Henrich | U38: =IF(ISBLANK($C38),"",$D$1) -> Brex Credit Card | V38: =IF(ISBLANK($B38),"",IF(ISBLANK($K38),IF(_xlfn.XLOOKUP($W38,'Category Mapping'!$C:$C,'Category Mapping'!$B:$B)="Travel",_xlfn.XLOOKUP($P38,'Department Listing'!$A:$A,'Department Listing'!$M:$M),_xlfn.XLOOKUP($W38,'Category Mapping'!$C:$C,'Category Mapping'!$D:$D)),$K38)) -> Sales & Marketing:Sales & Marketing- Travel Expenses: | W38: =IF(ISBLANK($B38),"",IF(ISBLANK($L38),RIGHT($E38,LEN($E38) - FIND("^",SUBSTITUTE($E38,":","^",LEN($E38) - LEN(SUBSTITUTE($E38,":",""))))),$L38)) -> Ground Transportation | X38: =IF(ISBLANK($J38),$V38&$W38,$J38) -> Sales & Marketing:Sales & Marketing- Travel Expenses:Ground Transportation | Y38: =IF(ISBLANK($M38),IFERROR(_xlfn.XLOOKUP($P38,'Department Listing'!$A:$A,'Department Listing'!$L:$L),""),$M38) -> 200- Datadog:230- Sales | Z38: =IF(ISBLANK($B38),"",MATCH($X38,COA!$B:$B,0)) -> 200
B39: 46233 | C39: TST* YELLOW DOOR TAQUE MASTERCARD-XXXXXXN730G8-Mickenzi Krpec | E39: Sales & Marketing:Sales & Marketing- Travel Expenses:Meals & Entertainment | F39: 3500 | I39: Food Vendor | L39: Meals & Entertainment | O39: =IF(C39="", "", TRIM(RIGHT(C39, LEN(C39) - FIND("@@", SUBSTITUTE(C39, "-", "@@", LEN(C39) - LEN(SUBSTITUTE(C39, "-", ""))))))) -> Mickenzi Krpec | P39: =IFERROR(_xlfn.XLOOKUP(O39,'Department Listing'!$O$1:$O$395,'Department Listing'!$A$1:$A$395),IFERROR(_xlfn.XLOOKUP(O39,'Name Aliases'!$A$2:$A$1000,'Name Aliases'!$B$2:$B$1000),"")) -> 170 | Q39: =IF(ISBLANK($C39),"",$B39) -> 46233 | R39: =IF(ISBLANK($C39),"",IF(ISBLANK($I39),$D39,$I39)) -> Food Vendor | S39: =IF(ISBLANK($C39),"",$F39 - $G39) -> 3500 | T39: =IF(ISBLANK($C39),"",C39) -> TST* YELLOW DOOR TAQUE MASTERCARD-XXXXXXN730G8-Mickenzi Krpec | U39: =IF(ISBLANK($C39),"",$D$1) -> Brex Credit Card | V39: =IF(ISBLANK($B39),"",IF(ISBLANK($K39),IF(_xlfn.XLOOKUP($W39,'Category Mapping'!$C:$C,'Category Mapping'!$B:$B)="Travel",_xlfn.XLOOKUP($P39,'Department Listing'!$A:$A,'Department Listing'!$M:$M),_xlfn.XLOOKUP($W39,'Category Mapping'!$C:$C,'Category Mapping'!$D:$D)),$K39)) -> General & Administrative:G&A- Travel Expenses: | W39: =IF(ISBLANK($B39),"",IF(ISBLANK($L39),RIGHT($E39,LEN($E39) - FIND("^",SUBSTITUTE($E39,":","^",LEN($E39) - LEN(SUBSTITUTE($E39,":",""))))),$L39)) -> Meals & Entertainment | X39: =IF(ISBLANK($J39),$V39&$W39,$J39) -> General & Administrative:G&A- Travel Expenses:Meals & Entertainment | Y39: =IF(ISBLANK($M39),IFERROR(_xlfn.XLOOKUP($P39,'Department Listing'!$A:$A,'Department Listing'!$L:$L),""),$M39) -> 100- Operations:110- G&A | Z39: =IF(ISBLANK($B39),"",MATCH($X39,COA!$B:$B,0)) -> 151
B40: 46233 | C40: STOP & SHOP 0498 MASTERCARD-XXXXXXGEDZOR-Mickenzi Krpec | F40: 53.77 | I40: Stop & Shop | L40: Meals & Entertainment | O40: =IF(C40="", "", TRIM(RIGHT(C40, LEN(C40) - FIND("@@", SUBSTITUTE(C40, "-", "@@", LEN(C40) - LEN(SUBSTITUTE(C40, "-", ""))))))) -> Mickenzi Krpec | P40: =IFERROR(_xlfn.XLOOKUP(O40,'Department Listing'!$O$1:$O$395,'Department Listing'!$A$1:$A$395),IFERROR(_xlfn.XLOOKUP(O40,'Name Aliases'!$A$2:$A$1000,'Name Aliases'!$B$2:$B$1000),"")) -> 170 | Q40: =IF(ISBLANK($C40),"",$B40) -> 46233 | R40: =IF(ISBLANK($C40),"",IF(ISBLANK($I40),$D40,$I40)) -> Stop & Shop | S40: =IF(ISBLANK($C40),"",$F40 - $G40) -> 53.77 | T40: =IF(ISBLANK($C40),"",C40) -> STOP & SHOP 0498 MASTERCARD-XXXXXXGEDZOR-Mickenzi Krpec | U40: =IF(ISBLANK($C40),"",$D$1) -> Brex Credit Card | V40: =IF(ISBLANK($B40),"",IF(ISBLANK($K40),IF(_xlfn.XLOOKUP($W40,'Category Mapping'!$C:$C,'Category Mapping'!$B:$B)="Travel",_xlfn.XLOOKUP($P40,'Department Listing'!$A:$A,'Department Listing'!$M:$M),_xlfn.XLOOKUP($W40,'Category Mapping'!$C:$C,'Category Mapping'!$D:$D)),$K40)) -> General & Administrative:G&A- Travel Expenses: | W40: =IF(ISBLANK($B40),"",IF(ISBLANK($L40),RIGHT($E40,LEN($E40) - FIND("^",SUBSTITUTE($E40,":","^",LEN($E40) - LEN(SUBSTITUTE($E40,":",""))))),$L40)) -> Meals & Entertainment | X40: =IF(ISBLANK($J40),$V40&$W40,$J40) -> General & Administrative:G&A- Travel Expenses:Meals & Entertainment | Y40: =IF(ISBLANK($M40),IFERROR(_xlfn.XLOOKUP($P40,'Department Listing'!$A:$A,'Department Listing'!$L:$L),""),$M40) -> 100- Operations:110- G&A | Z40: =IF(ISBLANK($B40),"",MATCH($X40,COA!$B:$B,0)) -> 151
B41: 46233 | C41: UBER *TRIP MASTERCARD-XXXXXXVJL17O-Robert Kolosky | E41: Sales & Marketing:Sales & Marketing- Travel Expenses:Ground Transportation | F41: 4 | I41: Uber | L41: Ground Transportation | O41: =IF(C41="", "", TRIM(RIGHT(C41, LEN(C41) - FIND("@@", SUBSTITUTE(C41, "-", "@@", LEN(C41) - LEN(SUBSTITUTE(C41, "-", ""))))))) -> Robert Kolosky | P41: =IFERROR(_xlfn.XLOOKUP(O41,'Department Listing'!$O$1:$O$395,'Department Listing'!$A$1:$A$395),IFERROR(_xlfn.XLOOKUP(O41,'Name Aliases'!$A$2:$A$1000,'Name Aliases'!$B$2:$B$1000),"")) -> 91 | Q41: =IF(ISBLANK($C41),"",$B41) -> 46233 | R41: =IF(ISBLANK($C41),"",IF(ISBLANK($I41),$D41,$I41)) -> Uber | S41: =IF(ISBLANK($C41),"",$F41 - $G41) -> 4 | T41: =IF(ISBLANK($C41),"",C41) -> UBER *TRIP MASTERCARD-XXXXXXVJL17O-Robert Kolosky | U41: =IF(ISBLANK($C41),"",$D$1) -> Brex Credit Card | V41: =IF(ISBLANK($B41),"",IF(ISBLANK($K41),IF(_xlfn.XLOOKUP($W41,'Category Mapping'!$C:$C,'Category Mapping'!$B:$B)="Travel",_xlfn.XLOOKUP($P41,'Department Listing'!$A:$A,'Department Listing'!$M:$M),_xlfn.XLOOKUP($W41,'Category Mapping'!$C:$C,'Category Mapping'!$D:$D)),$K41)) -> Cost of Goods Sold:COGS- Travel Expenses: | W41: =IF(ISBLANK($B41),"",IF(ISBLANK($L41),RIGHT($E41,LEN($E41) - FIND("^",SUBSTITUTE($E41,":","^",LEN($E41) - LEN(SUBSTITUTE($E41,":",""))))),$L41)) -> Ground Transportation | X41: =IF(ISBLANK($J41),$V41&$W41,$J41) -> Cost of Goods Sold:COGS- Travel Expenses:Ground Transportation | Y41: =IF(ISBLANK($M41),IFERROR(_xlfn.XLOOKUP($P41,'Department Listing'!$A:$A,'Department Listing'!$L:$L),""),$M41) -> 300- ServiceNow:320- Engineering | Z41: =IF(ISBLANK($B41),"",MATCH($X41,COA!$B:$B,0)) -> 124
B42: 46233 | C42: TOTAL WINE AND MORE MASTERCARD-XXXXXXCLM50K-Mickenzi Krpec | F42: 668.04 | I42: Office Vendor | L42: Office Supplies | O42: =IF(C42="", "", TRIM(RIGHT(C42, LEN(C42) - FIND("@@", SUBSTITUTE(C42, "-", "@@", LEN(C42) - LEN(SUBSTITUTE(C42, "-", ""))))))) -> Mickenzi Krpec | P42: =IFERROR(_xlfn.XLOOKUP(O42,'Department Listing'!$O$1:$O$395,'Department Listing'!$A$1:$A$395),IFERROR(_xlfn.XLOOKUP(O42,'Name Aliases'!$A$2:$A$1000,'Name Aliases'!$B$2:$B$1000),"")) -> 170 | Q42: =IF(ISBLANK($C42),"",$B42) -> 46233 | R42: =IF(ISBLANK($C42),"",IF(ISBLANK($I42),$D42,$I42)) -> Office Vendor | S42: =IF(ISBLANK($C42),"",$F42 - $G42) -> 668.04 | T42: =IF(ISBLANK($C42),"",C42) -> TOTAL WINE AND MORE MASTERCARD-XXXXXXCLM50K-Mickenzi Krpec | U42: =IF(ISBLANK($C42),"",$D$1) -> Brex Credit Card | V42: =IF(ISBLANK($B42),"",IF(ISBLANK($K42),IF(_xlfn.XLOOKUP($W42,'Category Mapping'!$C:$C,'Category Mapping'!$B:$B)="Travel",_xlfn.XLOOKUP($P42,'Department Listing'!$A:$A,'Department Listing'!$M:$M),_xlfn.XLOOKUP($W42,'Category Mapping'!$C:$C,'Category Mapping'!$D:$D)),$K42)) -> General & Administrative:Office Expenses: | W42: =IF(ISBLANK($B42),"",IF(ISBLANK($L42),RIGHT($E42,LEN($E42) - FIND("^",SUBSTITUTE($E42,":","^",LEN($E42) - LEN(SUBSTITUTE($E42,":",""))))),$L42)) -> Office Supplies | X42: =IF(ISBLANK($J42),$V42&$W42,$J42) -> General & Administrative:Office Expenses:Office Supplies | Y42: =IF(ISBLANK($M42),IFERROR(_xlfn.XLOOKUP($P42,'Department Listing'!$A:$A,'Department Listing'!$L:$L),""),$M42) -> 100- Operations:110- G&A | Z42: =IF(ISBLANK($B42),"",MATCH($X42,COA!$B:$B,0)) -> 161
B43: 46233 | C43: UBER *EATS HELP.UBER.C MASTERCARD-XXXXXXRUTEXJ-Jeff Mu | E43: Sales & Marketing:Sales & Marketing- Travel Expenses:Ground Transportation | F43: 49.68 | I43: Uber | L43: Ground Transportation | O43: =IF(C43="", "", TRIM(RIGHT(C43, LEN(C43) - FIND("@@", SUBSTITUTE(C43, "-", "@@", LEN(C43) - LEN(SUBSTITUTE(C43, "-", ""))))))) -> Jeff Mu | P43: =IFERROR(_xlfn.XLOOKUP(O43,'Department Listing'!$O$1:$O$395,'Department Listing'!$A$1:$A$395),IFERROR(_xlfn.XLOOKUP(O43,'Name Aliases'!$A$2:$A$1000,'Name Aliases'!$B$2:$B$1000),"")) -> 4 | Q43: =IF(ISBLANK($C43),"",$B43) -> 46233 | R43: =IF(ISBLANK($C43),"",IF(ISBLANK($I43),$D43,$I43)) -> Uber | S43: =IF(ISBLANK($C43),"",$F43 - $G43) -> 49.68 | T43: =IF(ISBLANK($C43),"",C43) -> UBER *EATS HELP.UBER.C MASTERCARD-XXXXXXRUTEXJ-Jeff Mu | U43: =IF(ISBLANK($C43),"",$D$1) -> Brex Credit Card | V43: =IF(ISBLANK($B43),"",IF(ISBLANK($K43),IF(_xlfn.XLOOKUP($W43,'Category Mapping'!$C:$C,'Category Mapping'!$B:$B)="Travel",_xlfn.XLOOKUP($P43,'Department Listing'!$A:$A,'Department Listing'!$M:$M),_xlfn.XLOOKUP($W43,'Category Mapping'!$C:$C,'Category Mapping'!$D:$D)),$K43)) -> Cost of Goods Sold:COGS- Travel Expenses: | W43: =IF(ISBLANK($B43),"",IF(ISBLANK($L43),RIGHT($E43,LEN($E43) - FIND("^",SUBSTITUTE($E43,":","^",LEN($E43) - LEN(SUBSTITUTE($E43,":",""))))),$L43)) -> Ground Transportation | X43: =IF(ISBLANK($J43),$V43&$W43,$J43) -> Cost of Goods Sold:COGS- Travel Expenses:Ground Transportation | Y43: =IF(ISBLANK($M43),IFERROR(_xlfn.XLOOKUP($P43,'Department Listing'!$A:$A,'Department Listing'!$L:$L),""),$M43) -> 300- ServiceNow:320- Engineering | Z43: =IF(ISBLANK($B43),"",MATCH($X43,COA!$B:$B,0)) -> 124
B44: 46233 | C44: WEBFLOW.COM MASTERCARD-XXXXXXAHZL3M-Toni Manning | E44: General & Administrative:Software Licenses | F44: 200.81 | I44: webflow.com | L44: Software Licenses | O44: =IF(C44="", "", TRIM(RIGHT(C44, LEN(C44) - FIND("@@", SUBSTITUTE(C44, "-", "@@", LEN(C44) - LEN(SUBSTITUTE(C44, "-", ""))))))) -> Toni Manning | P44: =IFERROR(_xlfn.XLOOKUP(O44,'Department Listing'!$O$1:$O$395,'Department Listing'!$A$1:$A$395),IFERROR(_xlfn.XLOOKUP(O44,'Name Aliases'!$A$2:$A$1000,'Name Aliases'!$B$2:$B$1000),"")) -> 121 | Q44: =IF(ISBLANK($C44),"",$B44) -> 46233 | R44: =IF(ISBLANK($C44),"",IF(ISBLANK($I44),$D44,$I44)) -> webflow.com | S44: =IF(ISBLANK($C44),"",$F44 - $G44) -> 200.81 | T44: =IF(ISBLANK($C44),"",C44) -> WEBFLOW.COM MASTERCARD-XXXXXXAHZL3M-Toni Manning | U44: =IF(ISBLANK($C44),"",$D$1) -> Brex Credit Card | V44: =IF(ISBLANK($B44),"",IF(ISBLANK($K44),IF(_xlfn.XLOOKUP($W44,'Category Mapping'!$C:$C,'Category Mapping'!$B:$B)="Travel",_xlfn.XLOOKUP($P44,'Department Listing'!$A:$A,'Department Listing'!$M:$M),_xlfn.XLOOKUP($W44,'Category Mapping'!$C:$C,'Category Mapping'!$D:$D)),$K44)) -> General & Administrative: | W44: =IF(ISBLANK($B44),"",IF(ISBLANK($L44),RIGHT($E44,LEN($E44) - FIND("^",SUBSTITUTE($E44,":","^",LEN($E44) - LEN(SUBSTITUTE($E44,":",""))))),$L44)) -> Software Licenses | X44: =IF(ISBLANK($J44),$V44&$W44,$J44) -> General & Administrative:Software Licenses | Y44: =IF(ISBLANK($M44),IFERROR(_xlfn.XLOOKUP($P44,'Department Listing'!$A:$A,'Department Listing'!$L:$L),""),$M44) -> 100- Operations:120- Marketing | Z44: =IF(ISBLANK($B44),"",MATCH($X44,COA!$B:$B,0)) -> 170
B45: 46233 | C45: UBER *TRIP MASTERCARD-XXXXXXFWJPAP-Robert Kolosky | E45: Sales & Marketing:Sales & Marketing- Travel Expenses:Ground Transportation | F45: 9.96 | I45: Uber | L45: Ground Transportation | O45: =IF(C45="", "", TRIM(RIGHT(C45, LEN(C45) - FIND("@@", SUBSTITUTE(C45, "-", "@@", LEN(C45) - LEN(SUBSTITUTE(C45, "-", ""))))))) -> Robert Kolosky | P45: =IFERROR(_xlfn.XLOOKUP(O45,'Department Listing'!$O$1:$O$395,'Department Listing'!$A$1:$A$395),IFERROR(_xlfn.XLOOKUP(O45,'Name Aliases'!$A$2:$A$1000,'Name Aliases'!$B$2:$B$1000),"")) -> 91 | Q45: =IF(ISBLANK($C45),"",$B45) -> 46233 | R45: =IF(ISBLANK($C45),"",IF(ISBLANK($I45),$D45,$I45)) -> Uber | S45: =IF(ISBLANK($C45),"",$F45 - $G45) -> 9.96 | T45: =IF(ISBLANK($C45),"",C45) -> UBER *TRIP MASTERCARD-XXXXXXFWJPAP-Robert Kolosky | U45: =IF(ISBLANK($C45),"",$D$1) -> Brex Credit Card | V45: =IF(ISBLANK($B45),"",IF(ISBLANK($K45),IF(_xlfn.XLOOKUP($W45,'Category Mapping'!$C:$C,'Category Mapping'!$B:$B)="Travel",_xlfn.XLOOKUP($P45,'Department Listing'!$A:$A,'Department Listing'!$M:$M),_xlfn.XLOOKUP($W45,'Category Mapping'!$C:$C,'Category Mapping'!$D:$D)),$K45)) -> Cost of Goods Sold:COGS- Travel Expenses: | W45: =IF(ISBLANK($B45),"",IF(ISBLANK($L45),RIGHT($E45,LEN($E45) - FIND("^",SUBSTITUTE($E45,":","^",LEN($E45) - LEN(SUBSTITUTE($E45,":",""))))),$L45)) -> Ground Transportation | X45: =IF(ISBLANK($J45),$V45&$W45,$J45) -> Cost of Goods Sold:COGS- Travel Expenses:Ground Transportation | Y45: =IF(ISBLANK($M45),IFERROR(_xlfn.XLOOKUP($P45,'Department Listing'!$A:$A,'Department Listing'!$L:$L),""),$M45) -> 300- ServiceNow:320- Engineering | Z45: =IF(ISBLANK($B45),"",MATCH($X45,COA!$B:$B,0)) -> 124
B46: 46233 | C46: UBER *TRIP MASTERCARD-XXXXXXW4V34Y-Karalyn Sims | E46: Sales & Marketing:Sales & Marketing- Travel Expenses:Ground Transportation | F46: 28.09 | I46: Uber | L46: Ground Transportation | O46: =IF(C46="", "", TRIM(RIGHT(C46, LEN(C46) - FIND("@@", SUBSTITUTE(C46, "-", "@@", LEN(C46) - LEN(SUBSTITUTE(C46, "-", ""))))))) -> Karalyn Sims | P46: =IFERROR(_xlfn.XLOOKUP(O46,'Department Listing'!$O$1:$O$395,'Department Listing'!$A$1:$A$395),IFERROR(_xlfn.XLOOKUP(O46,'Name Aliases'!$A$2:$A$1000,'Name Aliases'!$B$2:$B$1000),"")) -> 144 | Q46: =IF(ISBLANK($C46),"",$B46) -> 46233 | R46: =IF(ISBLANK($C46),"",IF(ISBLANK($I46),$D46,$I46)) -> Uber | S46: =IF(ISBLANK($C46),"",$F46 - $G46) -> 28.09 | T46: =IF(ISBLANK($C46),"",C46) -> UBER *TRIP MASTERCARD-XXXXXXW4V34Y-Karalyn Sims | U46: =IF(ISBLANK($C46),"",$D$1) -> Brex Credit Card | V46: =IF(ISBLANK($B46),"",IF(ISBLANK($K46),IF(_xlfn.XLOOKUP($W46,'Category Mapping'!$C:$C,'Category Mapping'!$B:$B)="Travel",_xlfn.XLOOKUP($P46,'Department Listing'!$A:$A,'Department Listing'!$M:$M),_xlfn.XLOOKUP($W46,'Category Mapping'!$C:$C,'Category Mapping'!$D:$D)),$K46)) -> Sales & Marketing:Sales & Marketing- Travel Expenses: | W46: =IF(ISBLANK($B46),"",IF(ISBLANK($L46),RIGHT($E46,LEN($E46) - FIND("^",SUBSTITUTE($E46,":","^",LEN($E46) - LEN(SUBSTITUTE($E46,":",""))))),$L46)) -> Ground Transportation | X46: =IF(ISBLANK($J46),$V46&$W46,$J46) -> Sales & Marketing:Sales & Marketing- Travel Expenses:Ground Transportation | Y46: =IF(ISBLANK($M46),IFERROR(_xlfn.XLOOKUP($P46,'Department Listing'!$A:$A,'Department Listing'!$L:$L),""),$M46) -> 100- Operations:120- Marketing | Z46: =IF(ISBLANK($B46),"",MATCH($X46,COA!$B:$B,0)) -> 200
B47: 46233 | C47: UBER *TRIP MASTERCARD-XXXXXXMQI5KD-Jacob Woolf | E47: Sales & Marketing:Sales & Marketing- Travel Expenses:Ground Transportation | F47: 41.93 | I47: Uber | L47: Ground Transportation | O47: =IF(C47="", "", TRIM(RIGHT(C47, LEN(C47) - FIND("@@", SUBSTITUTE(C47, "-", "@@", LEN(C47) - LEN(SUBSTITUTE(C47, "-", ""))))))) -> Jacob Woolf | P47: =IFERROR(_xlfn.XLOOKUP(O47,'Department Listing'!$O$1:$O$395,'Department Listing'!$A$1:$A$395),IFERROR(_xlfn.XLOOKUP(O47,'Name Aliases'!$A$2:$A$1000,'Name Aliases'!$B$2:$B$1000),"")) -> 194 | Q47: =IF(ISBLANK($C47),"",$B47) -> 46233 | R47: =IF(ISBLANK($C47),"",IF(ISBLANK($I47),$D47,$I47)) -> Uber | S47: =IF(ISBLANK($C47),"",$F47 - $G47) -> 41.93 | T47: =IF(ISBLANK($C47),"",C47) -> UBER *TRIP MASTERCARD-XXXXXXMQI5KD-Jacob Woolf | U47: =IF(ISBLANK($C47),"",$D$1) -> Brex Credit Card | V47: =IF(ISBLANK($B47),"",IF(ISBLANK($K47),IF(_xlfn.XLOOKUP($W47,'Category Mapping'!$C:$C,'Category Mapping'!$B:$B)="Travel",_xlfn.XLOOKUP($P47,'Department Listing'!$A:$A,'Department Listing'!$M:$M),_xlfn.XLOOKUP($W47,'Category Mapping'!$C:$C,'Category Mapping'!$D:$D)),$K47)) -> Cost of Goods Sold:COGS- Travel Expenses: | W47: =IF(ISBLANK($B47),"",IF(ISBLANK($L47),RIGHT($E47,LEN($E47) - FIND("^",SUBSTITUTE($E47,":","^",LEN($E47) - LEN(SUBSTITUTE($E47,":",""))))),$L47)) -> Ground Transportation | X47: =IF(ISBLANK($J47),$V47&$W47,$J47) -> Cost of Goods Sold:COGS- Travel Expenses:Ground Transportation | Y47: =IF(ISBLANK($M47),IFERROR(_xlfn.XLOOKUP($P47,'Department Listing'!$A:$A,'Department Listing'!$L:$L),""),$M47) -> 300- ServiceNow:320- Engineering | Z47: =IF(ISBLANK($B47),"",MATCH($X47,COA!$B:$B,0)) -> 124
B48: 46233 | C48: UBER *TRIP MASTERCARD-XXXXXXBSMK5F-Dean DeMonte | E48: Sales & Marketing:Sales & Marketing- Travel Expenses:Ground Transportation | F48: 17.79 | I48: Uber | L48: Ground Transportation | O48: =IF(C48="", "", TRIM(RIGHT(C48, LEN(C48) - FIND("@@", SUBSTITUTE(C48, "-", "@@", LEN(C48) - LEN(SUBSTITUTE(C48, "-", ""))))))) -> Dean DeMonte | P48: =IFERROR(_xlfn.XLOOKUP(O48,'Department Listing'!$O$1:$O$395,'Department Listing'!$A$1:$A$395),IFERROR(_xlfn.XLOOKUP(O48,'Name Aliases'!$A$2:$A$1000,'Name Aliases'!$B$2:$B$1000),"")) -> 216 | Q48: =IF(ISBLANK($C48),"",$B48) -> 46233 | R48: =IF(ISBLANK($C48),"",IF(ISBLANK($I48),$D48,$I48)) -> Uber | S48: =IF(ISBLANK($C48),"",$F48 - $G48) -> 17.79 | T48: =IF(ISBLANK($C48),"",C48) -> UBER *TRIP MASTERCARD-XXXXXXBSMK5F-Dean DeMonte | U48: =IF(ISBLANK($C48),"",$D$1) -> Brex Credit Card | V48: =IF(ISBLANK($B48),"",IF(ISBLANK($K48),IF(_xlfn.XLOOKUP($W48,'Category Mapping'!$C:$C,'Category Mapping'!$B:$B)="Travel",_xlfn.XLOOKUP($P48,'Department Listing'!$A:$A,'Department Listing'!$M:$M),_xlfn.XLOOKUP($W48,'Category Mapping'!$C:$C,'Category Mapping'!$D:$D)),$K48)) -> Sales & Marketing:Sales & Marketing- Travel Expenses: | W48: =IF(ISBLANK($B48),"",IF(ISBLANK($L48),RIGHT($E48,LEN($E48) - FIND("^",SUBSTITUTE($E48,":","^",LEN($E48) - LEN(SUBSTITUTE($E48,":",""))))),$L48)) -> Ground Transportation | X48: =IF(ISBLANK($J48),$V48&$W48,$J48) -> Sales & Marketing:Sales & Marketing- Travel Expenses:Ground Transportation | Y48: =IF(ISBLANK($M48),IFERROR(_xlfn.XLOOKUP($P48,'Department Listing'!$A:$A,'Department Listing'!$L:$L),""),$M48) -> 200- Datadog:230- Sales | Z48: =IF(ISBLANK($B48),"",MATCH($X48,COA!$B:$B,0)) -> 200
B49: 46233 | C49: UBER *TRIP MASTERCARD-XXXXXXNRJ4KK-Jacy Hennawy | E49: Sales & Marketing:Sales & Marketing- Travel Expenses:Ground Transportation | F49: 18.97 | I49: Uber | L49: Ground Transportation | O49: =IF(C49="", "", TRIM(RIGHT(C49, LEN(C49) - FIND("@@", SUBSTITUTE(C49, "-", "@@", LEN(C49) - LEN(SUBSTITUTE(C49, "-", ""))))))) -> Jacy Hennawy | P49: =IFERROR(_xlfn.XLOOKUP(O49,'Department Listing'!$O$1:$O$395,'Department Listing'!$A$1:$A$395),IFERROR(_xlfn.XLOOKUP(O49,'Name Aliases'!$A$2:$A$1000,'Name Aliases'!$B$2:$B$1000),"")) -> 268 | Q49: =IF(ISBLANK($C49),"",$B49) -> 46233 | R49: =IF(ISBLANK($C49),"",IF(ISBLANK($I49),$D49,$I49)) -> Uber | S49: =IF(ISBLANK($C49),"",$F49 - $G49) -> 18.97 | T49: =IF(ISBLANK($C49),"",C49) -> UBER *TRIP MASTERCARD-XXXXXXNRJ4KK-Jacy Hennawy | U49: =IF(ISBLANK($C49),"",$D$1) -> Brex Credit Card | V49: =IF(ISBLANK($B49),"",IF(ISBLANK($K49),IF(_xlfn.XLOOKUP($W49,'Category Mapping'!$C:$C,'Category Mapping'!$B:$B)="Travel",_xlfn.XLOOKUP($P49,'Department Listing'!$A:$A,'Department Listing'!$M:$M),_xlfn.XLOOKUP($W49,'Category Mapping'!$C:$C,'Category Mapping'!$D:$D)),$K49)) -> General & Administrative:G&A- Travel Expenses: | W49: =IF(ISBLANK($B49),"",IF(ISBLANK($L49),RIGHT($E49,LEN($E49) - FIND("^",SUBSTITUTE($E49,":","^",LEN($E49) - LEN(SUBSTITUTE($E49,":",""))))),$L49)) -> Ground Transportation | X49: =IF(ISBLANK($J49),$V49&$W49,$J49) -> General & Administrative:G&A- Travel Expenses:Ground Transportation | Y49: =IF(ISBLANK($M49),IFERROR(_xlfn.XLOOKUP($P49,'Department Listing'!$A:$A,'Department Listing'!$L:$L),""),$M49) -> 100- Operations:110- G&A | Z49: =IF(ISBLANK($B49),"",MATCH($X49,COA!$B:$B,0)) -> 149
B50: 46233 | C50: WWW.PLAYPKL.COM MASTERCARD-XXXXXXIMHJE1-Aaron Rhodes | E50: Sales & Marketing:Sales & Marketing- Travel Expenses:Meals & Entertainment | F50: 80 | I50: PKL Boston | L50: Meals & Entertainment | O50: =IF(C50="", "", TRIM(RIGHT(C50, LEN(C50) - FIND("@@", SUBSTITUTE(C50, "-", "@@", LEN(C50) - LEN(SUBSTITUTE(C50, "-", ""))))))) -> Aaron Rhodes | P50: =IFERROR(_xlfn.XLOOKUP(O50,'Department Listing'!$O$1:$O$395,'Department Listing'!$A$1:$A$395),IFERROR(_xlfn.XLOOKUP(O50,'Name Aliases'!$A$2:$A$1000,'Name Aliases'!$B$2:$B$1000),"")) -> 109 | Q50: =IF(ISBLANK($C50),"",$B50) -> 46233 | R50: =IF(ISBLANK($C50),"",IF(ISBLANK($I50),$D50,$I50)) -> PKL Boston | S50: =IF(ISBLANK($C50),"",$F50 - $G50) -> 80 | T50: =IF(ISBLANK($C50),"",C50) -> WWW.PLAYPKL.COM MASTERCARD-XXXXXXIMHJE1-Aaron Rhodes | U50: =IF(ISBLANK($C50),"",$D$1) -> Brex Credit Card | V50: =IF(ISBLANK($B50),"",IF(ISBLANK($K50),IF(_xlfn.XLOOKUP($W50,'Category Mapping'!$C:$C,'Category Mapping'!$B:$B)="Travel",_xlfn.XLOOKUP($P50,'Department Listing'!$A:$A,'Department Listing'!$M:$M),_xlfn.XLOOKUP($W50,'Category Mapping'!$C:$C,'Category Mapping'!$D:$D)),$K50)) -> Cost of Goods Sold:COGS- Travel Expenses: | W50: =IF(ISBLANK($B50),"",IF(ISBLANK($L50),RIGHT($E50,LEN($E50) - FIND("^",SUBSTITUTE($E50,":","^",LEN($E50) - LEN(SUBSTITUTE($E50,":",""))))),$L50)) -> Meals & Entertainment | X50: =IF(ISBLANK($J50),$V50&$W50,$J50) -> Cost of Goods Sold:COGS- Travel Expenses:Meals & Entertainment | Y50: =IF(ISBLANK($M50),IFERROR(_xlfn.XLOOKUP($P50,'Department Listing'!$A:$A,'Department Listing'!$L:$L),""),$M50) -> 200- Datadog:220- Engineering | Z50: =IF(ISBLANK($B50),"",MATCH($X50,COA!$B:$B,0)) -> 126
B51: 46233 | C51: UBER *TRIP MASTERCARD-XXXXXXVVWVUJ-Harry Tomczyk | E51: Sales & Marketing:Sales & Marketing- Travel Expenses:Ground Transportation | F51: 49.97 | I51: Uber | L51: Ground Transportation | O51: =IF(C51="", "", TRIM(RIGHT(C51, LEN(C51) - FIND("@@", SUBSTITUTE(C51, "-", "@@", LEN(C51) - LEN(SUBSTITUTE(C51, "-", ""))))))) -> Harry Tomczyk | P51: =IFERROR(_xlfn.XLOOKUP(O51,'Department Listing'!$O$1:$O$395,'Department Listing'!$A$1:$A$395),IFERROR(_xlfn.XLOOKUP(O51,'Name Aliases'!$A$2:$A$1000,'Name Aliases'!$B$2:$B$1000),"")) -> 251 | Q51: =IF(ISBLANK($C51),"",$B51) -> 46233 | R51: =IF(ISBLANK($C51),"",IF(ISBLANK($I51),$D51,$I51)) -> Uber | S51: =IF(ISBLANK($C51),"",$F51 - $G51) -> 49.97 | T51: =IF(ISBLANK($C51),"",C51) -> UBER *TRIP MASTERCARD-XXXXXXVVWVUJ-Harry Tomczyk | U51: =IF(ISBLANK($C51),"",$D$1) -> Brex Credit Card | V51: =IF(ISBLANK($B51),"",IF(ISBLANK($K51),IF(_xlfn.XLOOKUP($W51,'Category Mapping'!$C:$C,'Category Mapping'!$B:$B)="Travel",_xlfn.XLOOKUP($P51,'Department Listing'!$A:$A,'Department Listing'!$M:$M),_xlfn.XLOOKUP($W51,'Category Mapping'!$C:$C,'Category Mapping'!$D:$D)),$K51)) -> Sales & Marketing:Sales & Marketing- Travel Expenses: | W51: =IF(ISBLANK($B51),"",IF(ISBLANK($L51),RIGHT($E51,LEN($E51) - FIND("^",SUBSTITUTE($E51,":","^",LEN($E51) - LEN(SUBSTITUTE($E51,":",""))))),$L51)) -> Ground Transportation | X51: =IF(ISBLANK($J51),$V51&$W51,$J51) -> Sales & Marketing:Sales & Marketing- Travel Expenses:Ground Transportation | Y51: =IF(ISBLANK($M51),IFERROR(_xlfn.XLOOKUP($P51,'Department Listing'!$A:$A,'Department Listing'!$L:$L),""),$M51) -> 300- ServiceNow:330- Sales | Z51: =IF(ISBLANK($B51),"",MATCH($X51,COA!$B:$B,0)) -> 200
B52: 46233 | C52: UK.BOOKSHOP.ORG MASTERCARD-XXXXXXE3IZSY-Mickenzi Krpec | F52: 23.23 | I52: Office Vendor | L52: Office Supplies | O52: =IF(C52="", "", TRIM(RIGHT(C52, LEN(C52) - FIND("@@", SUBSTITUTE(C52, "-", "@@", LEN(C52) - LEN(SUBSTITUTE(C52, "-", ""))))))) -> Mickenzi Krpec | P52: =IFERROR(_xlfn.XLOOKUP(O52,'Department Listing'!$O$1:$O$395,'Department Listing'!$A$1:$A$395),IFERROR(_xlfn.XLOOKUP(O52,'Name Aliases'!$A$2:$A$1000,'Name Aliases'!$B$2:$B$1000),"")) -> 170 | Q52: =IF(ISBLANK($C52),"",$B52) -> 46233 | R52: =IF(ISBLANK($C52),"",IF(ISBLANK($I52),$D52,$I52)) -> Office Vendor | S52: =IF(ISBLANK($C52),"",$F52 - $G52) -> 23.23 | T52: =IF(ISBLANK($C52),"",C52) -> UK.BOOKSHOP.ORG MASTERCARD-XXXXXXE3IZSY-Mickenzi Krpec | U52: =IF(ISBLANK($C52),"",$D$1) -> Brex Credit Card | V52: =IF(ISBLANK($B52),"",IF(ISBLANK($K52),IF(_xlfn.XLOOKUP($W52,'Category Mapping'!$C:$C,'Category Mapping'!$B:$B)="Travel",_xlfn.XLOOKUP($P52,'Department Listing'!$A:$A,'Department Listing'!$M:$M),_xlfn.XLOOKUP($W52,'Category Mapping'!$C:$C,'Category Mapping'!$D:$D)),$K52)) -> General & Administrative:Office Expenses: | W52: =IF(ISBLANK($B52),"",IF(ISBLANK($L52),RIGHT($E52,LEN($E52) - FIND("^",SUBSTITUTE($E52,":","^",LEN($E52) - LEN(SUBSTITUTE($E52,":",""))))),$L52)) -> Office Supplies | X52: =IF(ISBLANK($J52),$V52&$W52,$J52) -> General & Administrative:Office Expenses:Office Supplies | Y52: =IF(ISBLANK($M52),IFERROR(_xlfn.XLOOKUP($P52,'Department Listing'!$A:$A,'Department Listing'!$L:$L),""),$M52) -> 100- Operations:110- G&A | Z52: =IF(ISBLANK($B52),"",MATCH($X52,COA!$B:$B,0)) -> 161
B53: 46233 | C53: TATTEBAKERY MASTERCARD-XXXXXXPWTP5I-Chloe Brant | E53: Sales & Marketing:Sales & Marketing- Travel Expenses:Meals & Entertainment | F53: 225.72 | I53: Tatte | L53: Meals & Entertainment | O53: =IF(C53="", "", TRIM(RIGHT(C53, LEN(C53) - FIND("@@", SUBSTITUTE(C53, "-", "@@", LEN(C53) - LEN(SUBSTITUTE(C53, "-", ""))))))) -> Chloe Brant | P53: =IFERROR(_xlfn.XLOOKUP(O53,'Department Listing'!$O$1:$O$395,'Department Listing'!$A$1:$A$395),IFERROR(_xlfn.XLOOKUP(O53,'Name Aliases'!$A$2:$A$1000,'Name Aliases'!$B$2:$B$1000),"")) -> 77 | Q53: =IF(ISBLANK($C53),"",$B53) -> 46233 | R53: =IF(ISBLANK($C53),"",IF(ISBLANK($I53),$D53,$I53)) -> Tatte | S53: =IF(ISBLANK($C53),"",$F53 - $G53) -> 225.72 | T53: =IF(ISBLANK($C53),"",C53) -> TATTEBAKERY MASTERCARD-XXXXXXPWTP5I-Chloe Brant | U53: =IF(ISBLANK($C53),"",$D$1) -> Brex Credit Card | V53: =IF(ISBLANK($B53),"",IF(ISBLANK($K53),IF(_xlfn.XLOOKUP($W53,'Category Mapping'!$C:$C,'Category Mapping'!$B:$B)="Travel",_xlfn.XLOOKUP($P53,'Department Listing'!$A:$A,'Department Listing'!$M:$M),_xlfn.XLOOKUP($W53,'Category Mapping'!$C:$C,'Category Mapping'!$D:$D)),$K53)) -> Sales & Marketing:Sales & Marketing- Travel Expenses: | W53: =IF(ISBLANK($B53),"",IF(ISBLANK($L53),RIGHT($E53,LEN($E53) - FIND("^",SUBSTITUTE($E53,":","^",LEN($E53) - LEN(SUBSTITUTE($E53,":",""))))),$L53)) -> Meals & Entertainment | X53: =IF(ISBLANK($J53),$V53&$W53,$J53) -> Sales & Marketing:Sales & Marketing- Travel Expenses:Meals & Entertainment | Y53: =IF(ISBLANK($M53),IFERROR(_xlfn.XLOOKUP($P53,'Department Listing'!$A:$A,'Department Listing'!$L:$L),""),$M53) -> 300- ServiceNow:330- Sales | Z53: =IF(ISBLANK($B53),"",MATCH($X53,COA!$B:$B,0)) -> 202
B54: 46233 | C54: NEWSLINK 13 BOS MASTERCARD-XXXXXXC2BUXX-Tanner Ylvisaker | E54: Sales & Marketing:Sales & Marketing- Travel Expenses:Other Travel Expenses | F54: 5.1 | I54: Newslink | L54: Other Travel Expenses | O54: =IF(C54="", "", TRIM(RIGHT(C54, LEN(C54) - FIND("@@", SUBSTITUTE(C54, "-", "@@", LEN(C54) - LEN(SUBSTITUTE(C54, "-", ""))))))) -> Tanner Ylvisaker | P54: =IFERROR(_xlfn.XLOOKUP(O54,'Department Listing'!$O$1:$O$395,'Department Listing'!$A$1:$A$395),IFERROR(_xlfn.XLOOKUP(O54,'Name Aliases'!$A$2:$A$1000,'Name Aliases'!$B$2:$B$1000),"")) -> 99 | Q54: =IF(ISBLANK($C54),"",$B54) -> 46233 | R54: =IF(ISBLANK($C54),"",IF(ISBLANK($I54),$D54,$I54)) -> Newslink | S54: =IF(ISBLANK($C54),"",$F54 - $G54) -> 5.1 | T54: =IF(ISBLANK($C54),"",C54) -> NEWSLINK 13 BOS MASTERCARD-XXXXXXC2BUXX-Tanner Ylvisaker | U54: =IF(ISBLANK($C54),"",$D$1) -> Brex Credit Card | V54: =IF(ISBLANK($B54),"",IF(ISBLANK($K54),IF(_xlfn.XLOOKUP($W54,'Category Mapping'!$C:$C,'Category Mapping'!$B:$B)="Travel",_xlfn.XLOOKUP($P54,'Department Listing'!$A:$A,'Department Listing'!$M:$M),_xlfn.XLOOKUP($W54,'Category Mapping'!$C:$C,'Category Mapping'!$D:$D)),$K54)) -> Cost of Goods Sold:COGS- Travel Expenses: | W54: =IF(ISBLANK($B54),"",IF(ISBLANK($L54),RIGHT($E54,LEN($E54) - FIND("^",SUBSTITUTE($E54,":","^",LEN($E54) - LEN(SUBSTITUTE($E54,":",""))))),$L54)) -> Other Travel Expenses | X54: =IF(ISBLANK($J54),$V54&$W54,$J54) -> Cost of Goods Sold:COGS- Travel Expenses:Other Travel Expenses | Y54: =IF(ISBLANK($M54),IFERROR(_xlfn.XLOOKUP($P54,'Department Listing'!$A:$A,'Department Listing'!$L:$L),""),$M54) -> 300- ServiceNow:320- Engineering | Z54: =IF(ISBLANK($B54),"",MATCH($X54,COA!$B:$B,0)) -> 127
B55: 46233 | C55: UBER *EATS MASTERCARD-XXXXXX6XYIJ8-Ryan Henrich | E55: Sales & Marketing:Sales & Marketing- Travel Expenses:Ground Transportation | F55: 33.58 | I55: Uber | L55: Ground Transportation | O55: =IF(C55="", "", TRIM(RIGHT(C55, LEN(C55) - FIND("@@", SUBSTITUTE(C55, "-", "@@", LEN(C55) - LEN(SUBSTITUTE(C55, "-", ""))))))) -> Ryan Henrich | P55: =IFERROR(_xlfn.XLOOKUP(O55,'Department Listing'!$O$1:$O$395,'Department Listing'!$A$1:$A$395),IFERROR(_xlfn.XLOOKUP(O55,'Name Aliases'!$A$2:$A$1000,'Name Aliases'!$B$2:$B$1000),"")) -> 154 | Q55: =IF(ISBLANK($C55),"",$B55) -> 46233 | R55: =IF(ISBLANK($C55),"",IF(ISBLANK($I55),$D55,$I55)) -> Uber | S55: =IF(ISBLANK($C55),"",$F55 - $G55) -> 33.58 | T55: =IF(ISBLANK($C55),"",C55) -> UBER *EATS MASTERCARD-XXXXXX6XYIJ8-Ryan Henrich | U55: =IF(ISBLANK($C55),"",$D$1) -> Brex Credit Card | V55: =IF(ISBLANK($B55),"",IF(ISBLANK($K55),IF(_xlfn.XLOOKUP($W55,'Category Mapping'!$C:$C,'Category Mapping'!$B:$B)="Travel",_xlfn.XLOOKUP($P55,'Department Listing'!$A:$A,'Department Listing'!$M:$M),_xlfn.XLOOKUP($W55,'Category Mapping'!$C:$C,'Category Mapping'!$D:$D)),$K55)) -> Sales & Marketing:Sales & Marketing- Travel Expenses: | W55: =IF(ISBLANK($B55),"",IF(ISBLANK($L55),RIGHT($E55,LEN($E55) - FIND("^",SUBSTITUTE($E55,":","^",LEN($E55) - LEN(SUBSTITUTE($E55,":",""))))),$L55)) -> Ground Transportation | X55: =IF(ISBLANK($J55),$V55&$W55,$J55) -> Sales & Marketing:Sales & Marketing- Travel Expenses:Ground Transportation | Y55: =IF(ISBLANK($M55),IFERROR(_xlfn.XLOOKUP($P55,'Department Listing'!$A:$A,'Department Listing'!$L:$L),""),$M55) -> 200- Datadog:230- Sales | Z55: =IF(ISBLANK($B55),"",MATCH($X55,COA!$B:$B,0)) -> 200
B56: 46233 | C56: THE NEWBURY BOSTON F A MASTERCARD-XXXXXX2WPYC6-Elias Kapetanopoulos | E56: Sales & Marketing:Sales & Marketing- Travel Expenses:Lodging | F56: 127.72 | I56: The Newbury Boston | L56: Lodging | O56: =IF(C56="", "", TRIM(RIGHT(C56, LEN(C56) - FIND("@@", SUBSTITUTE(C56, "-", "@@", LEN(C56) - LEN(SUBSTITUTE(C56, "-", ""))))))) -> Elias Kapetanopoulos | P56: =IFERROR(_xlfn.XLOOKUP(O56,'Department Listing'!$O$1:$O$395,'Department Listing'!$A$1:$A$395),IFERROR(_xlfn.XLOOKUP(O56,'Name Aliases'!$A$2:$A$1000,'Name Aliases'!$B$2:$B$1000),"")) -> 12 | Q56: =IF(ISBLANK($C56),"",$B56) -> 46233 | R56: =IF(ISBLANK($C56),"",IF(ISBLANK($I56),$D56,$I56)) -> The Newbury Boston | S56: =IF(ISBLANK($C56),"",$F56 - $G56) -> 127.72 | T56: =IF(ISBLANK($C56),"",C56) -> THE NEWBURY BOSTON F A MASTERCARD-XXXXXX2WPYC6-Elias Kapetanopoulos | U56: =IF(ISBLANK($C56),"",$D$1) -> Brex Credit Card | V56: =IF(ISBLANK($B56),"",IF(ISBLANK($K56),IF(_xlfn.XLOOKUP($W56,'Category Mapping'!$C:$C,'Category Mapping'!$B:$B)="Travel",_xlfn.XLOOKUP($P56,'Department Listing'!$A:$A,'Department Listing'!$M:$M),_xlfn.XLOOKUP($W56,'Category Mapping'!$C:$C,'Category Mapping'!$D:$D)),$K56)) -> General & Administrative:G&A- Travel Expenses: | W56: =IF(ISBLANK($B56),"",IF(ISBLANK($L56),RIGHT($E56,LEN($E56) - FIND("^",SUBSTITUTE($E56,":","^",LEN($E56) - LEN(SUBSTITUTE($E56,":",""))))),$L56)) -> Lodging | X56: =IF(ISBLANK($J56),$V56&$W56,$J56) -> General & Administrative:G&A- Travel Expenses:Lodging | Y56: =IF(ISBLANK($M56),IFERROR(_xlfn.XLOOKUP($P56,'Department Listing'!$A:$A,'Department Listing'!$L:$L),""),$M56) -> 300- ServiceNow:320- Engineering | Z56: =IF(ISBLANK($B56),"",MATCH($X56,COA!$B:$B,0)) -> 150
B57: 46233 | C57: TST* DIG INN - BACK BA MASTERCARD-XXXXXXWO4XN1-Tyler Grimshaw | E57: Sales & Marketing:Sales & Marketing- Travel Expenses:Meals & Entertainment | F57: 15.41 | I57: Dig Inn | L57: Meals & Entertainment | O57: =IF(C57="", "", TRIM(RIGHT(C57, LEN(C57) - FIND("@@", SUBSTITUTE(C57, "-", "@@", LEN(C57) - LEN(SUBSTITUTE(C57, "-", ""))))))) -> Tyler Grimshaw | P57: =IFERROR(_xlfn.XLOOKUP(O57,'Department Listing'!$O$1:$O$395,'Department Listing'!$A$1:$A$395),IFERROR(_xlfn.XLOOKUP(O57,'Name Aliases'!$A$2:$A$1000,'Name Aliases'!$B$2:$B$1000),"")) -> 264 | Q57: =IF(ISBLANK($C57),"",$B57) -> 46233 | R57: =IF(ISBLANK($C57),"",IF(ISBLANK($I57),$D57,$I57)) -> Dig Inn | S57: =IF(ISBLANK($C57),"",$F57 - $G57) -> 15.41 | T57: =IF(ISBLANK($C57),"",C57) -> TST* DIG INN - BACK BA MASTERCARD-XXXXXXWO4XN1-Tyler Grimshaw | U57: =IF(ISBLANK($C57),"",$D$1) -> Brex Credit Card | V57: =IF(ISBLANK($B57),"",IF(ISBLANK($K57),IF(_xlfn.XLOOKUP($W57,'Category Mapping'!$C:$C,'Category Mapping'!$B:$B)="Travel",_xlfn.XLOOKUP($P57,'Department Listing'!$A:$A,'Department Listing'!$M:$M),_xlfn.XLOOKUP($W57,'Category Mapping'!$C:$C,'Category Mapping'!$D:$D)),$K57)) -> Sales & Marketing:Sales & Marketing- Travel Expenses: | W57: =IF(ISBLANK($B57),"",IF(ISBLANK($L57),RIGHT($E57,LEN($E57) - FIND("^",SUBSTITUTE($E57,":","^",LEN($E57) - LEN(SUBSTITUTE($E57,":",""))))),$L57)) -> Meals & Entertainment | X57: =IF(ISBLANK($J57),$V57&$W57,$J57) -> Sales & Marketing:Sales & Marketing- Travel Expenses:Meals & Entertainment | Y57: =IF(ISBLANK($M57),IFERROR(_xlfn.XLOOKUP($P57,'Department Listing'!$A:$A,'Department Listing'!$L:$L),""),$M57) -> 200- Datadog:230- Sales | Z57: =IF(ISBLANK($B57),"",MATCH($X57,COA!$B:$B,0)) -> 202
B58: 46233 | C58: UBER *TRIP MASTERCARD-XXXXXXZBBRRB-Michael Button | E58: Sales & Marketing:Sales & Marketing- Travel Expenses:Ground Transportation | F58: 13.98 | I58: Uber | L58: Ground Transportation | O58: =IF(C58="", "", TRIM(RIGHT(C58, LEN(C58) - FIND("@@", SUBSTITUTE(C58, "-", "@@", LEN(C58) - LEN(SUBSTITUTE(C58, "-", ""))))))) -> Michael Button | P58: =IFERROR(_xlfn.XLOOKUP(O58,'Department Listing'!$O$1:$O$395,'Department Listing'!$A$1:$A$395),IFERROR(_xlfn.XLOOKUP(O58,'Name Aliases'!$A$2:$A$1000,'Name Aliases'!$B$2:$B$1000),"")) -> 273 | Q58: =IF(ISBLANK($C58),"",$B58) -> 46233 | R58: =IF(ISBLANK($C58),"",IF(ISBLANK($I58),$D58,$I58)) -> Uber | S58: =IF(ISBLANK($C58),"",$F58 - $G58) -> 13.98 | T58: =IF(ISBLANK($C58),"",C58) -> UBER *TRIP MASTERCARD-XXXXXXZBBRRB-Michael Button | U58: =IF(ISBLANK($C58),"",$D$1) -> Brex Credit Card | V58: =IF(ISBLANK($B58),"",IF(ISBLANK($K58),IF(_xlfn.XLOOKUP($W58,'Category Mapping'!$C:$C,'Category Mapping'!$B:$B)="Travel",_xlfn.XLOOKUP($P58,'Department Listing'!$A:$A,'Department Listing'!$M:$M),_xlfn.XLOOKUP($W58,'Category Mapping'!$C:$C,'Category Mapping'!$D:$D)),$K58)) -> General & Administrative:G&A- Travel Expenses: | W58: =IF(ISBLANK($B58),"",IF(ISBLANK($L58),RIGHT($E58,LEN($E58) - FIND("^",SUBSTITUTE($E58,":","^",LEN($E58) - LEN(SUBSTITUTE($E58,":",""))))),$L58)) -> Ground Transportation | X58: =IF(ISBLANK($J58),$V58&$W58,$J58) -> General & Administrative:G&A- Travel Expenses:Ground Transportation | Y58: =IF(ISBLANK($M58),IFERROR(_xlfn.XLOOKUP($P58,'Department Listing'!$A:$A,'Department Listing'!$L:$L),""),$M58) -> 100- Operations:110- G&A | Z58: =IF(ISBLANK($B58),"",MATCH($X58,COA!$B:$B,0)) -> 149
B59: 46233 | C59: JIMMY JOHNS - 4455 MASTERCARD-XXXXXXKEL7Y8-Tanner Ylvisaker | F59: 10.48 | I59: Food Vendor | L59: Meals & Entertainment | O59: =IF(C59="", "", TRIM(RIGHT(C59, LEN(C59) - FIND("@@", SUBSTITUTE(C59, "-", "@@", LEN(C59) - LEN(SUBSTITUTE(C59, "-", ""))))))) -> Tanner Ylvisaker | P59: =IFERROR(_xlfn.XLOOKUP(O59,'Department Listing'!$O$1:$O$395,'Department Listing'!$A$1:$A$395),IFERROR(_xlfn.XLOOKUP(O59,'Name Aliases'!$A$2:$A$1000,'Name Aliases'!$B$2:$B$1000),"")) -> 99 | Q59: =IF(ISBLANK($C59),"",$B59) -> 46233 | R59: =IF(ISBLANK($C59),"",IF(ISBLANK($I59),$D59,$I59)) -> Food Vendor | S59: =IF(ISBLANK($C59),"",$F59 - $G59) -> 10.48 | T59: =IF(ISBLANK($C59),"",C59) -> JIMMY JOHNS - 4455 MASTERCARD-XXXXXXKEL7Y8-Tanner Ylvisaker | U59: =IF(ISBLANK($C59),"",$D$1) -> Brex Credit Card | V59: =IF(ISBLANK($B59),"",IF(ISBLANK($K59),IF(_xlfn.XLOOKUP($W59,'Category Mapping'!$C:$C,'Category Mapping'!$B:$B)="Travel",_xlfn.XLOOKUP($P59,'Department Listing'!$A:$A,'Department Listing'!$M:$M),_xlfn.XLOOKUP($W59,'Category Mapping'!$C:$C,'Category Mapping'!$D:$D)),$K59)) -> Cost of Goods Sold:COGS- Travel Expenses: | W59: =IF(ISBLANK($B59),"",IF(ISBLANK($L59),RIGHT($E59,LEN($E59) - FIND("^",SUBSTITUTE($E59,":","^",LEN($E59) - LEN(SUBSTITUTE($E59,":",""))))),$L59)) -> Meals & Entertainment | X59: =IF(ISBLANK($J59),$V59&$W59,$J59) -> Cost of Goods Sold:COGS- Travel Expenses:Meals & Entertainment | Y59: =IF(ISBLANK($M59),IFERROR(_xlfn.XLOOKUP($P59,'Department Listing'!$A:$A,'Department Listing'!$L:$L),""),$M59) -> 300- ServiceNow:320- Engineering | Z59: =IF(ISBLANK($B59),"",MATCH($X59,COA!$B:$B,0)) -> 126
B60: 46233 | C60: UBER *TRIP MASTERCARD-XXXXXXTG6329-Michael Button | E60: Sales & Marketing:Sales & Marketing- Travel Expenses:Ground Transportation | F60: 5 | I60: Uber | L60: Ground Transportation | O60: =IF(C60="", "", TRIM(RIGHT(C60, LEN(C60) - FIND("@@", SUBSTITUTE(C60, "-", "@@", LEN(C60) - LEN(SUBSTITUTE(C60, "-", ""))))))) -> Michael Button | P60: =IFERROR(_xlfn.XLOOKUP(O60,'Department Listing'!$O$1:$O$395,'Department Listing'!$A$1:$A$395),IFERROR(_xlfn.XLOOKUP(O60,'Name Aliases'!$A$2:$A$1000,'Name Aliases'!$B$2:$B$1000),"")) -> 273 | Q60: =IF(ISBLANK($C60),"",$B60) -> 46233 | R60: =IF(ISBLANK($C60),"",IF(ISBLANK($I60),$D60,$I60)) -> Uber | S60: =IF(ISBLANK($C60),"",$F60 - $G60) -> 5 | T60: =IF(ISBLANK($C60),"",C60) -> UBER *TRIP MASTERCARD-XXXXXXTG6329-Michael Button | U60: =IF(ISBLANK($C60),"",$D$1) -> Brex Credit Card | V60: =IF(ISBLANK($B60),"",IF(ISBLANK($K60),IF(_xlfn.XLOOKUP($W60,'Category Mapping'!$C:$C,'Category Mapping'!$B:$B)="Travel",_xlfn.XLOOKUP($P60,'Department Listing'!$A:$A,'Department Listing'!$M:$M),_xlfn.XLOOKUP($W60,'Category Mapping'!$C:$C,'Category Mapping'!$D:$D)),$K60)) -> General & Administrative:G&A- Travel Expenses: | W60: =IF(ISBLANK($B60),"",IF(ISBLANK($L60),RIGHT($E60,LEN($E60) - FIND("^",SUBSTITUTE($E60,":","^",LEN($E60) - LEN(SUBSTITUTE($E60,":",""))))),$L60)) -> Ground Transportation | X60: =IF(ISBLANK($J60),$V60&$W60,$J60) -> General & Administrative:G&A- Travel Expenses:Ground Transportation | Y60: =IF(ISBLANK($M60),IFERROR(_xlfn.XLOOKUP($P60,'Department Listing'!$A:$A,'Department Listing'!$L:$L),""),$M60) -> 100- Operations:110- G&A | Z60: =IF(ISBLANK($B60),"",MATCH($X60,COA!$B:$B,0)) -> 149
B61: 46233 | C61: ALLIANZ TRAVEL INS MASTERCARD-XXXXXXCDHONB-Karalyn Sims | E61: Sales & Marketing:Sales & Marketing- Travel Expenses:Other Travel Expenses | F61: 54.44 | I61: Allianz | L61: Other Travel Expenses | O61: =IF(C61="", "", TRIM(RIGHT(C61, LEN(C61) - FIND("@@", SUBSTITUTE(C61, "-", "@@", LEN(C61) - LEN(SUBSTITUTE(C61, "-", ""))))))) -> Karalyn Sims | P61: =IFERROR(_xlfn.XLOOKUP(O61,'Department Listing'!$O$1:$O$395,'Department Listing'!$A$1:$A$395),IFERROR(_xlfn.XLOOKUP(O61,'Name Aliases'!$A$2:$A$1000,'Name Aliases'!$B$2:$B$1000),"")) -> 144 | Q61: =IF(ISBLANK($C61),"",$B61) -> 46233 | R61: =IF(ISBLANK($C61),"",IF(ISBLANK($I61),$D61,$I61)) -> Allianz | S61: =IF(ISBLANK($C61),"",$F61 - $G61) -> 54.44 | T61: =IF(ISBLANK($C61),"",C61) -> ALLIANZ TRAVEL INS MASTERCARD-XXXXXXCDHONB-Karalyn Sims | U61: =IF(ISBLANK($C61),"",$D$1) -> Brex Credit Card | V61: =IF(ISBLANK($B61),"",IF(ISBLANK($K61),IF(_xlfn.XLOOKUP($W61,'Category Mapping'!$C:$C,'Category Mapping'!$B:$B)="Travel",_xlfn.XLOOKUP($P61,'Department Listing'!$A:$A,'Department Listing'!$M:$M),_xlfn.XLOOKUP($W61,'Category Mapping'!$C:$C,'Category Mapping'!$D:$D)),$K61)) -> Sales & Marketing:Sales & Marketing- Travel Expenses: | W61: =IF(ISBLANK($B61),"",IF(ISBLANK($L61),RIGHT($E61,LEN($E61) - FIND("^",SUBSTITUTE($E61,":","^",LEN($E61) - LEN(SUBSTITUTE($E61,":",""))))),$L61)) -> Other Travel Expenses | X61: =IF(ISBLANK($J61),$V61&$W61,$J61) -> Sales & Marketing:Sales & Marketing- Travel Expenses:Other Travel Expenses | Y61: =IF(ISBLANK($M61),IFERROR(_xlfn.XLOOKUP($P61,'Department Listing'!$A:$A,'Department Listing'!$L:$L),""),$M61) -> 100- Operations:120- Marketing | Z61: =IF(ISBLANK($B61),"",MATCH($X61,COA!$B:$B,0)) -> 203
B62: 46233 | C62: DELTA MASTERCARD-XXXXXXY5DIEO-Karalyn Sims | F62: 19.99 | I62: Delta | L62: Airfare | O62: =IF(C62="", "", TRIM(RIGHT(C62, LEN(C62) - FIND("@@", SUBSTITUTE(C62, "-", "@@", LEN(C62) - LEN(SUBSTITUTE(C62, "-", ""))))))) -> Karalyn Sims | P62: =IFERROR(_xlfn.XLOOKUP(O62,'Department Listing'!$O$1:$O$395,'Department Listing'!$A$1:$A$395),IFERROR(_xlfn.XLOOKUP(O62,'Name Aliases'!$A$2:$A$1000,'Name Aliases'!$B$2:$B$1000),"")) -> 144 | Q62: =IF(ISBLANK($C62),"",$B62) -> 46233 | R62: =IF(ISBLANK($C62),"",IF(ISBLANK($I62),$D62,$I62)) -> Delta | S62: =IF(ISBLANK($C62),"",$F62 - $G62) -> 19.99 | T62: =IF(ISBLANK($C62),"",C62) -> DELTA MASTERCARD-XXXXXXY5DIEO-Karalyn Sims | U62: =IF(ISBLANK($C62),"",$D$1) -> Brex Credit Card | V62: =IF(ISBLANK($B62),"",IF(ISBLANK($K62),IF(_xlfn.XLOOKUP($W62,'Category Mapping'!$C:$C,'Category Mapping'!$B:$B)="Travel",_xlfn.XLOOKUP($P62,'Department Listing'!$A:$A,'Department Listing'!$M:$M),_xlfn.XLOOKUP($W62,'Category Mapping'!$C:$C,'Category Mapping'!$D:$D)),$K62)) -> Sales & Marketing:Sales & Marketing- Travel Expenses: | W62: =IF(ISBLANK($B62),"",IF(ISBLANK($L62),RIGHT($E62,LEN($E62) - FIND("^",SUBSTITUTE($E62,":","^",LEN($E62) - LEN(SUBSTITUTE($E62,":",""))))),$L62)) -> Airfare | X62: =IF(ISBLANK($J62),$V62&$W62,$J62) -> Sales & Marketing:Sales & Marketing- Travel Expenses:Airfare | Y62: =IF(ISBLANK($M62),IFERROR(_xlfn.XLOOKUP($P62,'Department Listing'!$A:$A,'Department Listing'!$L:$L),""),$M62) -> 100- Operations:120- Marketing | Z62: =IF(ISBLANK($B62),"",MATCH($X62,COA!$B:$B,0)) -> 199
B63: 46233 | C63: DELTA MASTERCARD-XXXXXX7FENXD-Karalyn Sims | F63: 54.99 | I63: Delta | L63: Airfare | O63: =IF(C63="", "", TRIM(RIGHT(C63, LEN(C63) - FIND("@@", SUBSTITUTE(C63, "-", "@@", LEN(C63) - LEN(SUBSTITUTE(C63, "-", ""))))))) -> Karalyn Sims | P63: =IFERROR(_xlfn.XLOOKUP(O63,'Department Listing'!$O$1:$O$395,'Department Listing'!$A$1:$A$395),IFERROR(_xlfn.XLOOKUP(O63,'Name Aliases'!$A$2:$A$1000,'Name Aliases'!$B$2:$B$1000),"")) -> 144 | Q63: =IF(ISBLANK($C63),"",$B63) -> 46233 | R63: =IF(ISBLANK($C63),"",IF(ISBLANK($I63),$D63,$I63)) -> Delta | S63: =IF(ISBLANK($C63),"",$F63 - $G63) -> 54.99 | T63: =IF(ISBLANK($C63),"",C63) -> DELTA MASTERCARD-XXXXXX7FENXD-Karalyn Sims | U63: =IF(ISBLANK($C63),"",$D$1) -> Brex Credit Card | V63: =IF(ISBLANK($B63),"",IF(ISBLANK($K63),IF(_xlfn.XLOOKUP($W63,'Category Mapping'!$C:$C,'Category Mapping'!$B:$B)="Travel",_xlfn.XLOOKUP($P63,'Department Listing'!$A:$A,'Department Listing'!$M:$M),_xlfn.XLOOKUP($W63,'Category Mapping'!$C:$C,'Category Mapping'!$D:$D)),$K63)) -> Sales & Marketing:Sales & Marketing- Travel Expenses: | W63: =IF(ISBLANK($B63),"",IF(ISBLANK($L63),RIGHT($E63,LEN($E63) - FIND("^",SUBSTITUTE($E63,":","^",LEN($E63) - LEN(SUBSTITUTE($E63,":",""))))),$L63)) -> Airfare | X63: =IF(ISBLANK($J63),$V63&$W63,$J63) -> Sales & Marketing:Sales & Marketing- Travel Expenses:Airfare | Y63: =IF(ISBLANK($M63),IFERROR(_xlfn.XLOOKUP($P63,'Department Listing'!$A:$A,'Department Listing'!$L:$L),""),$M63) -> 100- Operations:120- Marketing | Z63: =IF(ISBLANK($B63),"",MATCH($X63,COA!$B:$B,0)) -> 199
B64: 46233 | C64: DELTA MASTERCARD-XXXXXX22AKKS-Karalyn Sims | F64: 39.99 | I64: Delta | L64: Airfare | O64: =IF(C64="", "", TRIM(RIGHT(C64, LEN(C64) - FIND("@@", SUBSTITUTE(C64, "-", "@@", LEN(C64) - LEN(SUBSTITUTE(C64, "-", ""))))))) -> Karalyn Sims | P64: =IFERROR(_xlfn.XLOOKUP(O64,'Department Listing'!$O$1:$O$395,'Department Listing'!$A$1:$A$395),IFERROR(_xlfn.XLOOKUP(O64,'Name Aliases'!$A$2:$A$1000,'Name Aliases'!$B$2:$B$1000),"")) -> 144 | Q64: =IF(ISBLANK($C64),"",$B64) -> 46233 | R64: =IF(ISBLANK($C64),"",IF(ISBLANK($I64),$D64,$I64)) -> Delta | S64: =IF(ISBLANK($C64),"",$F64 - $G64) -> 39.99 | T64: =IF(ISBLANK($C64),"",C64) -> DELTA MASTERCARD-XXXXXX22AKKS-Karalyn Sims | U64: =IF(ISBLANK($C64),"",$D$1) -> Brex Credit Card | V64: =IF(ISBLANK($B64),"",IF(ISBLANK($K64),IF(_xlfn.XLOOKUP($W64,'Category Mapping'!$C:$C,'Category Mapping'!$B:$B)="Travel",_xlfn.XLOOKUP($P64,'Department Listing'!$A:$A,'Department Listing'!$M:$M),_xlfn.XLOOKUP($W64,'Category Mapping'!$C:$C,'Category Mapping'!$D:$D)),$K64)) -> Sales & Marketing:Sales & Marketing- Travel Expenses: | W64: =IF(ISBLANK($B64),"",IF(ISBLANK($L64),RIGHT($E64,LEN($E64) - FIND("^",SUBSTITUTE($E64,":","^",LEN($E64) - LEN(SUBSTITUTE($E64,":",""))))),$L64)) -> Airfare | X64: =IF(ISBLANK($J64),$V64&$W64,$J64) -> Sales & Marketing:Sales & Marketing- Travel Expenses:Airfare | Y64: =IF(ISBLANK($M64),IFERROR(_xlfn.XLOOKUP($P64,'Department Listing'!$A:$A,'Department Listing'!$L:$L),""),$M64) -> 100- Operations:120- Marketing | Z64: =IF(ISBLANK($B64),"",MATCH($X64,COA!$B:$B,0)) -> 199
B65: 46233 | C65: DELTA MASTERCARD-XXXXXXO1FWMP-Karalyn Sims | F65: 691.6 | I65: Delta | L65: Airfare | O65: =IF(C65="", "", TRIM(RIGHT(C65, LEN(C65) - FIND("@@", SUBSTITUTE(C65, "-", "@@", LEN(C65) - LEN(SUBSTITUTE(C65, "-", ""))))))) -> Karalyn Sims | P65: =IFERROR(_xlfn.XLOOKUP(O65,'Department Listing'!$O$1:$O$395,'Department Listing'!$A$1:$A$395),IFERROR(_xlfn.XLOOKUP(O65,'Name Aliases'!$A$2:$A$1000,'Name Aliases'!$B$2:$B$1000),"")) -> 144 | Q65: =IF(ISBLANK($C65),"",$B65) -> 46233 | R65: =IF(ISBLANK($C65),"",IF(ISBLANK($I65),$D65,$I65)) -> Delta | S65: =IF(ISBLANK($C65),"",$F65 - $G65) -> 691.6 | T65: =IF(ISBLANK($C65),"",C65) -> DELTA MASTERCARD-XXXXXXO1FWMP-Karalyn Sims | U65: =IF(ISBLANK($C65),"",$D$1) -> Brex Credit Card | V65: =IF(ISBLANK($B65),"",IF(ISBLANK($K65),IF(_xlfn.XLOOKUP($W65,'Category Mapping'!$C:$C,'Category Mapping'!$B:$B)="Travel",_xlfn.XLOOKUP($P65,'Department Listing'!$A:$A,'Department Listing'!$M:$M),_xlfn.XLOOKUP($W65,'Category Mapping'!$C:$C,'Category Mapping'!$D:$D)),$K65)) -> Sales & Marketing:Sales & Marketing- Travel Expenses: | W65: =IF(ISBLANK($B65),"",IF(ISBLANK($L65),RIGHT($E65,LEN($E65) - FIND("^",SUBSTITUTE($E65,":","^",LEN($E65) - LEN(SUBSTITUTE($E65,":",""))))),$L65)) -> Airfare | X65: =IF(ISBLANK($J65),$V65&$W65,$J65) -> Sales & Marketing:Sales & Marketing- Travel Expenses:Airfare | Y65: =IF(ISBLANK($M65),IFERROR(_xlfn.XLOOKUP($P65,'Department Listing'!$A:$A,'Department Listing'!$L:$L),""),$M65) -> 100- Operations:120- Marketing | Z65: =IF(ISBLANK($B65),"",MATCH($X65,COA!$B:$B,0)) -> 199
B66: 46233 | C66: UBER *TRIP MASTERCARD-XXXXXXI1L1UK-Michael Button | E66: Sales & Marketing:Sales & Marketing- Travel Expenses:Ground Transportation | F66: 13.95 | I66: Uber | L66: Ground Transportation | O66: =IF(C66="", "", TRIM(RIGHT(C66, LEN(C66) - FIND("@@", SUBSTITUTE(C66, "-", "@@", LEN(C66) - LEN(SUBSTITUTE(C66, "-", ""))))))) -> Michael Button | P66: =IFERROR(_xlfn.XLOOKUP(O66,'Department Listing'!$O$1:$O$395,'Department Listing'!$A$1:$A$395),IFERROR(_xlfn.XLOOKUP(O66,'Name Aliases'!$A$2:$A$1000,'Name Aliases'!$B$2:$B$1000),"")) -> 273 | Q66: =IF(ISBLANK($C66),"",$B66) -> 46233 | R66: =IF(ISBLANK($C66),"",IF(ISBLANK($I66),$D66,$I66)) -> Uber | S66: =IF(ISBLANK($C66),"",$F66 - $G66) -> 13.95 | T66: =IF(ISBLANK($C66),"",C66) -> UBER *TRIP MASTERCARD-XXXXXXI1L1UK-Michael Button | U66: =IF(ISBLANK($C66),"",$D$1) -> Brex Credit Card | V66: =IF(ISBLANK($B66),"",IF(ISBLANK($K66),IF(_xlfn.XLOOKUP($W66,'Category Mapping'!$C:$C,'Category Mapping'!$B:$B)="Travel",_xlfn.XLOOKUP($P66,'Department Listing'!$A:$A,'Department Listing'!$M:$M),_xlfn.XLOOKUP($W66,'Category Mapping'!$C:$C,'Category Mapping'!$D:$D)),$K66)) -> General & Administrative:G&A- Travel Expenses: | W66: =IF(ISBLANK($B66),"",IF(ISBLANK($L66),RIGHT($E66,LEN($E66) - FIND("^",SUBSTITUTE($E66,":","^",LEN($E66) - LEN(SUBSTITUTE($E66,":",""))))),$L66)) -> Ground Transportation | X66: =IF(ISBLANK($J66),$V66&$W66,$J66) -> General & Administrative:G&A- Travel Expenses:Ground Transportation | Y66: =IF(ISBLANK($M66),IFERROR(_xlfn.XLOOKUP($P66,'Department Listing'!$A:$A,'Department Listing'!$L:$L),""),$M66) -> 100- Operations:110- G&A | Z66: =IF(ISBLANK($B66),"",MATCH($X66,COA!$B:$B,0)) -> 149
B67: 46233 | C67: UBER *TRIP MASTERCARD-XXXXXXCK940K-Tanner Ylvisaker | E67: Sales & Marketing:Sales & Marketing- Travel Expenses:Ground Transportation | F67: 41.95 | I67: Uber | L67: Ground Transportation | O67: =IF(C67="", "", TRIM(RIGHT(C67, LEN(C67) - FIND("@@", SUBSTITUTE(C67, "-", "@@", LEN(C67) - LEN(SUBSTITUTE(C67, "-", ""))))))) -> Tanner Ylvisaker | P67: =IFERROR(_xlfn.XLOOKUP(O67,'Department Listing'!$O$1:$O$395,'Department Listing'!$A$1:$A$395),IFERROR(_xlfn.XLOOKUP(O67,'Name Aliases'!$A$2:$A$1000,'Name Aliases'!$B$2:$B$1000),"")) -> 99 | Q67: =IF(ISBLANK($C67),"",$B67) -> 46233 | R67: =IF(ISBLANK($C67),"",IF(ISBLANK($I67),$D67,$I67)) -> Uber | S67: =IF(ISBLANK($C67),"",$F67 - $G67) -> 41.95 | T67: =IF(ISBLANK($C67),"",C67) -> UBER *TRIP MASTERCARD-XXXXXXCK940K-Tanner Ylvisaker | U67: =IF(ISBLANK($C67),"",$D$1) -> Brex Credit Card | V67: =IF(ISBLANK($B67),"",IF(ISBLANK($K67),IF(_xlfn.XLOOKUP($W67,'Category Mapping'!$C:$C,'Category Mapping'!$B:$B)="Travel",_xlfn.XLOOKUP($P67,'Department Listing'!$A:$A,'Department Listing'!$M:$M),_xlfn.XLOOKUP($W67,'Category Mapping'!$C:$C,'Category Mapping'!$D:$D)),$K67)) -> Cost of Goods Sold:COGS- Travel Expenses: | W67: =IF(ISBLANK($B67),"",IF(ISBLANK($L67),RIGHT($E67,LEN($E67) - FIND("^",SUBSTITUTE($E67,":","^",LEN($E67) - LEN(SUBSTITUTE($E67,":",""))))),$L67)) -> Ground Transportation | X67: =IF(ISBLANK($J67),$V67&$W67,$J67) -> Cost of Goods Sold:COGS- Travel Expenses:Ground Transportation | Y67: =IF(ISBLANK($M67),IFERROR(_xlfn.XLOOKUP($P67,'Department Listing'!$A:$A,'Department Listing'!$L:$L),""),$M67) -> 300- ServiceNow:320- Engineering | Z67: =IF(ISBLANK($B67),"",MATCH($X67,COA!$B:$B,0)) -> 124
B68: 46233 | C68: TST* TATTE BAKERY BACK MASTERCARD-XXXXXX9QFEIY-Michael Joyce | E68: Sales & Marketing:Sales & Marketing- Travel Expenses:Meals & Entertainment | F68: 15.25 | I68: Tatte | L68: Meals & Entertainment | O68: =IF(C68="", "", TRIM(RIGHT(C68, LEN(C68) - FIND("@@", SUBSTITUTE(C68, "-", "@@", LEN(C68) - LEN(SUBSTITUTE(C68, "-", ""))))))) -> Michael Joyce | P68: =IFERROR(_xlfn.XLOOKUP(O68,'Department Listing'!$O$1:$O$395,'Department Listing'!$A$1:$A$395),IFERROR(_xlfn.XLOOKUP(O68,'Name Aliases'!$A$2:$A$1000,'Name Aliases'!$B$2:$B$1000),"")) -> 290 | Q68: =IF(ISBLANK($C68),"",$B68) -> 46233 | R68: =IF(ISBLANK($C68),"",IF(ISBLANK($I68),$D68,$I68)) -> Tatte | S68: =IF(ISBLANK($C68),"",$F68 - $G68) -> 15.25 | T68: =IF(ISBLANK($C68),"",C68) -> TST* TATTE BAKERY BACK MASTERCARD-XXXXXX9QFEIY-Michael Joyce | U68: =IF(ISBLANK($C68),"",$D$1) -> Brex Credit Card | V68: =IF(ISBLANK($B68),"",IF(ISBLANK($K68),IF(_xlfn.XLOOKUP($W68,'Category Mapping'!$C:$C,'Category Mapping'!$B:$B)="Travel",_xlfn.XLOOKUP($P68,'Department Listing'!$A:$A,'Department Listing'!$M:$M),_xlfn.XLOOKUP($W68,'Category Mapping'!$C:$C,'Category Mapping'!$D:$D)),$K68)) -> Cost of Goods Sold:COGS- Travel Expenses: | W68: =IF(ISBLANK($B68),"",IF(ISBLANK($L68),RIGHT($E68,LEN($E68) - FIND("^",SUBSTITUTE($E68,":","^",LEN($E68) - LEN(SUBSTITUTE($E68,":",""))))),$L68)) -> Meals & Entertainment | X68: =IF(ISBLANK($J68),$V68&$W68,$J68) -> Cost of Goods Sold:COGS- Travel Expenses:Meals & Entertainment | Y68: =IF(ISBLANK($M68),IFERROR(_xlfn.XLOOKUP($P68,'Department Listing'!$A:$A,'Department Listing'!$L:$L),""),$M68) -> 300- ServiceNow:310- Delivery | Z68: =IF(ISBLANK($B68),"",MATCH($X68,COA!$B:$B,0)) -> 126
B69: 46233 | C69: TATTEBAKERY MASTERCARD-XXXXXXZZBWEZ-Mickenzi Krpec | E69: Sales & Marketing:Sales & Marketing- Travel Expenses:Meals & Entertainment | F69: 16.59 | I69: Tatte | L69: Meals & Entertainment | O69: =IF(C69="", "", TRIM(RIGHT(C69, LEN(C69) - FIND("@@", SUBSTITUTE(C69, "-", "@@", LEN(C69) - LEN(SUBSTITUTE(C69, "-", ""))))))) -> Mickenzi Krpec | P69: =IFERROR(_xlfn.XLOOKUP(O69,'Department Listing'!$O$1:$O$395,'Department Listing'!$A$1:$A$395),IFERROR(_xlfn.XLOOKUP(O69,'Name Aliases'!$A$2:$A$1000,'Name Aliases'!$B$2:$B$1000),"")) -> 170 | Q69: =IF(ISBLANK($C69),"",$B69) -> 46233 | R69: =IF(ISBLANK($C69),"",IF(ISBLANK($I69),$D69,$I69)) -> Tatte | S69: =IF(ISBLANK($C69),"",$F69 - $G69) -> 16.59 | T69: =IF(ISBLANK($C69),"",C69) -> TATTEBAKERY MASTERCARD-XXXXXXZZBWEZ-Mickenzi Krpec | U69: =IF(ISBLANK($C69),"",$D$1) -> Brex Credit Card | V69: =IF(ISBLANK($B69),"",IF(ISBLANK($K69),IF(_xlfn.XLOOKUP($W69,'Category Mapping'!$C:$C,'Category Mapping'!$B:$B)="Travel",_xlfn.XLOOKUP($P69,'Department Listing'!$A:$A,'Department Listing'!$M:$M),_xlfn.XLOOKUP($W69,'Category Mapping'!$C:$C,'Category Mapping'!$D:$D)),$K69)) -> General & Administrative:G&A- Travel Expenses: | W69: =IF(ISBLANK($B69),"",IF(ISBLANK($L69),RIGHT($E69,LEN($E69) - FIND("^",SUBSTITUTE($E69,":","^",LEN($E69) - LEN(SUBSTITUTE($E69,":",""))))),$L69)) -> Meals & Entertainment | X69: =IF(ISBLANK($J69),$V69&$W69,$J69) -> General & Administrative:G&A- Travel Expenses:Meals & Entertainment | Y69: =IF(ISBLANK($M69),IFERROR(_xlfn.XLOOKUP($P69,'Department Listing'!$A:$A,'Department Listing'!$L:$L),""),$M69) -> 100- Operations:110- G&A | Z69: =IF(ISBLANK($B69),"",MATCH($X69,COA!$B:$B,0)) -> 151
B70: 46233 | C70: UBER *TRIP MASTERCARD-XXXXXXJA4V8M-Michael Button | E70: Sales & Marketing:Sales & Marketing- Travel Expenses:Ground Transportation | F70: 5 | I70: Uber | L70: Ground Transportation | O70: =IF(C70="", "", TRIM(RIGHT(C70, LEN(C70) - FIND("@@", SUBSTITUTE(C70, "-", "@@", LEN(C70) - LEN(SUBSTITUTE(C70, "-", ""))))))) -> Michael Button | P70: =IFERROR(_xlfn.XLOOKUP(O70,'Department Listing'!$O$1:$O$395,'Department Listing'!$A$1:$A$395),IFERROR(_xlfn.XLOOKUP(O70,'Name Aliases'!$A$2:$A$1000,'Name Aliases'!$B$2:$B$1000),"")) -> 273 | Q70: =IF(ISBLANK($C70),"",$B70) -> 46233 | R70: =IF(ISBLANK($C70),"",IF(ISBLANK($I70),$D70,$I70)) -> Uber | S70: =IF(ISBLANK($C70),"",$F70 - $G70) -> 5 | T70: =IF(ISBLANK($C70),"",C70) -> UBER *TRIP MASTERCARD-XXXXXXJA4V8M-Michael Button | U70: =IF(ISBLANK($C70),"",$D$1) -> Brex Credit Card | V70: =IF(ISBLANK($B70),"",IF(ISBLANK($K70),IF(_xlfn.XLOOKUP($W70,'Category Mapping'!$C:$C,'Category Mapping'!$B:$B)="Travel",_xlfn.XLOOKUP($P70,'Department Listing'!$A:$A,'Department Listing'!$M:$M),_xlfn.XLOOKUP($W70,'Category Mapping'!$C:$C,'Category Mapping'!$D:$D)),$K70)) -> General & Administrative:G&A- Travel Expenses: | W70: =IF(ISBLANK($B70),"",IF(ISBLANK($L70),RIGHT($E70,LEN($E70) - FIND("^",SUBSTITUTE($E70,":","^",LEN($E70) - LEN(SUBSTITUTE($E70,":",""))))),$L70)) -> Ground Transportation | X70: =IF(ISBLANK($J70),$V70&$W70,$J70) -> General & Administrative:G&A- Travel Expenses:Ground Transportation | Y70: =IF(ISBLANK($M70),IFERROR(_xlfn.XLOOKUP($P70,'Department Listing'!$A:$A,'Department Listing'!$L:$L),""),$M70) -> 100- Operations:110- G&A | Z70: =IF(ISBLANK($B70),"",MATCH($X70,COA!$B:$B,0)) -> 149
B71: 46233 | C71: UBER *TRIP MASTERCARD-XXXXXXV1AKMB-Michael Button | E71: Sales & Marketing:Sales & Marketing- Travel Expenses:Ground Transportation | F71: 12.98 | I71: Uber | L71: Ground Transportation | O71: =IF(C71="", "", TRIM(RIGHT(C71, LEN(C71) - FIND("@@", SUBSTITUTE(C71, "-", "@@", LEN(C71) - LEN(SUBSTITUTE(C71, "-", ""))))))) -> Michael Button | P71: =IFERROR(_xlfn.XLOOKUP(O71,'Department Listing'!$O$1:$O$395,'Department Listing'!$A$1:$A$395),IFERROR(_xlfn.XLOOKUP(O71,'Name Aliases'!$A$2:$A$1000,'Name Aliases'!$B$2:$B$1000),"")) -> 273 | Q71: =IF(ISBLANK($C71),"",$B71) -> 46233 | R71: =IF(ISBLANK($C71),"",IF(ISBLANK($I71),$D71,$I71)) -> Uber | S71: =IF(ISBLANK($C71),"",$F71 - $G71) -> 12.98 | T71: =IF(ISBLANK($C71),"",C71) -> UBER *TRIP MASTERCARD-XXXXXXV1AKMB-Michael Button | U71: =IF(ISBLANK($C71),"",$D$1) -> Brex Credit Card | V71: =IF(ISBLANK($B71),"",IF(ISBLANK($K71),IF(_xlfn.XLOOKUP($W71,'Category Mapping'!$C:$C,'Category Mapping'!$B:$B)="Travel",_xlfn.XLOOKUP($P71,'Department Listing'!$A:$A,'Department Listing'!$M:$M),_xlfn.XLOOKUP($W71,'Category Mapping'!$C:$C,'Category Mapping'!$D:$D)),$K71)) -> General & Administrative:G&A- Travel Expenses: | W71: =IF(ISBLANK($B71),"",IF(ISBLANK($L71),RIGHT($E71,LEN($E71) - FIND("^",SUBSTITUTE($E71,":","^",LEN($E71) - LEN(SUBSTITUTE($E71,":",""))))),$L71)) -> Ground Transportation | X71: =IF(ISBLANK($J71),$V71&$W71,$J71) -> General & Administrative:G&A- Travel Expenses:Ground Transportation | Y71: =IF(ISBLANK($M71),IFERROR(_xlfn.XLOOKUP($P71,'Department Listing'!$A:$A,'Department Listing'!$L:$L),""),$M71) -> 100- Operations:110- G&A | Z71: =IF(ISBLANK($B71),"",MATCH($X71,COA!$B:$B,0)) -> 149
B72: 46233 | C72: TST* NAYA - 500 BOYLST MASTERCARD-XXXXXXSUJMT5-Chloe Brant | E72: Sales & Marketing:Sales & Marketing- Travel Expenses:Meals & Entertainment | F72: 35.86 | I72: Food Vendor | L72: Meals & Entertainment | O72: =IF(C72="", "", TRIM(RIGHT(C72, LEN(C72) - FIND("@@", SUBSTITUTE(C72, "-", "@@", LEN(C72) - LEN(SUBSTITUTE(C72, "-", ""))))))) -> Chloe Brant | P72: =IFERROR(_xlfn.XLOOKUP(O72,'Department Listing'!$O$1:$O$395,'Department Listing'!$A$1:$A$395),IFERROR(_xlfn.XLOOKUP(O72,'Name Aliases'!$A$2:$A$1000,'Name Aliases'!$B$2:$B$1000),"")) -> 77 | Q72: =IF(ISBLANK($C72),"",$B72) -> 46233 | R72: =IF(ISBLANK($C72),"",IF(ISBLANK($I72),$D72,$I72)) -> Food Vendor | S72: =IF(ISBLANK($C72),"",$F72 - $G72) -> 35.86 | T72: =IF(ISBLANK($C72),"",C72) -> TST* NAYA - 500 BOYLST MASTERCARD-XXXXXXSUJMT5-Chloe Brant | U72: =IF(ISBLANK($C72),"",$D$1) -> Brex Credit Card | V72: =IF(ISBLANK($B72),"",IF(ISBLANK($K72),IF(_xlfn.XLOOKUP($W72,'Category Mapping'!$C:$C,'Category Mapping'!$B:$B)="Travel",_xlfn.XLOOKUP($P72,'Department Listing'!$A:$A,'Department Listing'!$M:$M),_xlfn.XLOOKUP($W72,'Category Mapping'!$C:$C,'Category Mapping'!$D:$D)),$K72)) -> Sales & Marketing:Sales & Marketing- Travel Expenses: | W72: =IF(ISBLANK($B72),"",IF(ISBLANK($L72),RIGHT($E72,LEN($E72) - FIND("^",SUBSTITUTE($E72,":","^",LEN($E72) - LEN(SUBSTITUTE($E72,":",""))))),$L72)) -> Meals & Entertainment | X72: =IF(ISBLANK($J72),$V72&$W72,$J72) -> Sales & Marketing:Sales & Marketing- Travel Expenses:Meals & Entertainment | Y72: =IF(ISBLANK($M72),IFERROR(_xlfn.XLOOKUP($P72,'Department Listing'!$A:$A,'Department Listing'!$L:$L),""),$M72) -> 300- ServiceNow:330- Sales | Z72: =IF(ISBLANK($B72),"",MATCH($X72,COA!$B:$B,0)) -> 202
B73: 46233 | C73: TST* NAYA - 500 BOYLST MASTERCARD-XXXXXX6CWSC6-Vincent Planz | E73: Sales & Marketing:Sales & Marketing- Travel Expenses:Meals & Entertainment | F73: 17.93 | I73: Food Vendor | L73: Meals & Entertainment | O73: =IF(C73="", "", TRIM(RIGHT(C73, LEN(C73) - FIND("@@", SUBSTITUTE(C73, "-", "@@", LEN(C73) - LEN(SUBSTITUTE(C73, "-", ""))))))) -> Vincent Planz | P73: =IFERROR(_xlfn.XLOOKUP(O73,'Department Listing'!$O$1:$O$395,'Department Listing'!$A$1:$A$395),IFERROR(_xlfn.XLOOKUP(O73,'Name Aliases'!$A$2:$A$1000,'Name Aliases'!$B$2:$B$1000),"")) -> 107 | Q73: =IF(ISBLANK($C73),"",$B73) -> 46233 | R73: =IF(ISBLANK($C73),"",IF(ISBLANK($I73),$D73,$I73)) -> Food Vendor | S73: =IF(ISBLANK($C73),"",$F73 - $G73) -> 17.93 | T73: =IF(ISBLANK($C73),"",C73) -> TST* NAYA - 500 BOYLST MASTERCARD-XXXXXX6CWSC6-Vincent Planz | U73: =IF(ISBLANK($C73),"",$D$1) -> Brex Credit Card | V73: =IF(ISBLANK($B73),"",IF(ISBLANK($K73),IF(_xlfn.XLOOKUP($W73,'Category Mapping'!$C:$C,'Category Mapping'!$B:$B)="Travel",_xlfn.XLOOKUP($P73,'Department Listing'!$A:$A,'Department Listing'!$M:$M),_xlfn.XLOOKUP($W73,'Category Mapping'!$C:$C,'Category Mapping'!$D:$D)),$K73)) -> General & Administrative:G&A- Travel Expenses: | W73: =IF(ISBLANK($B73),"",IF(ISBLANK($L73),RIGHT($E73,LEN($E73) - FIND("^",SUBSTITUTE($E73,":","^",LEN($E73) - LEN(SUBSTITUTE($E73,":",""))))),$L73)) -> Meals & Entertainment | X73: =IF(ISBLANK($J73),$V73&$W73,$J73) -> General & Administrative:G&A- Travel Expenses:Meals & Entertainment | Y73: =IF(ISBLANK($M73),IFERROR(_xlfn.XLOOKUP($P73,'Department Listing'!$A:$A,'Department Listing'!$L:$L),""),$M73) -> 100- Operations:110- G&A | Z73: =IF(ISBLANK($B73),"",MATCH($X73,COA!$B:$B,0)) -> 151
B74: 46233 | C74: JINA.AI MASTERCARD-XXXXXX6XWJU0-Matthew Morris | F74: 50 | I74: Office Vendor | L74: Office Supplies | O74: =IF(C74="", "", TRIM(RIGHT(C74, LEN(C74) - FIND("@@", SUBSTITUTE(C74, "-", "@@", LEN(C74) - LEN(SUBSTITUTE(C74, "-", ""))))))) -> Matthew Morris | P74: =IFERROR(_xlfn.XLOOKUP(O74,'Department Listing'!$O$1:$O$395,'Department Listing'!$A$1:$A$395),IFERROR(_xlfn.XLOOKUP(O74,'Name Aliases'!$A$2:$A$1000,'Name Aliases'!$B$2:$B$1000),"")) -> 67 | Q74: =IF(ISBLANK($C74),"",$B74) -> 46233 | R74: =IF(ISBLANK($C74),"",IF(ISBLANK($I74),$D74,$I74)) -> Office Vendor | S74: =IF(ISBLANK($C74),"",$F74 - $G74) -> 50 | T74: =IF(ISBLANK($C74),"",C74) -> JINA.AI MASTERCARD-XXXXXX6XWJU0-Matthew Morris | U74: =IF(ISBLANK($C74),"",$D$1) -> Brex Credit Card | V74: =IF(ISBLANK($B74),"",IF(ISBLANK($K74),IF(_xlfn.XLOOKUP($W74,'Category Mapping'!$C:$C,'Category Mapping'!$B:$B)="Travel",_xlfn.XLOOKUP($P74,'Department Listing'!$A:$A,'Department Listing'!$M:$M),_xlfn.XLOOKUP($W74,'Category Mapping'!$C:$C,'Category Mapping'!$D:$D)),$K74)) -> General & Administrative:Office Expenses: | W74: =IF(ISBLANK($B74),"",IF(ISBLANK($L74),RIGHT($E74,LEN($E74) - FIND("^",SUBSTITUTE($E74,":","^",LEN($E74) - LEN(SUBSTITUTE($E74,":",""))))),$L74)) -> Office Supplies | X74: =IF(ISBLANK($J74),$V74&$W74,$J74) -> General & Administrative:Office Expenses:Office Supplies | Y74: =IF(ISBLANK($M74),IFERROR(_xlfn.XLOOKUP($P74,'Department Listing'!$A:$A,'Department Listing'!$L:$L),""),$M74) -> 300- ServiceNow:330- Sales | Z74: =IF(ISBLANK($B74),"",MATCH($X74,COA!$B:$B,0)) -> 161
B75: 46233 | C75: EXXON MERRITT PKWY GRE MASTERCARD-XXXXXX1AO3VQ-Ryan McStravick | F75: 28.59 | I75: Exxon | L75: Other Travel Expenses | O75: =IF(C75="", "", TRIM(RIGHT(C75, LEN(C75) - FIND("@@", SUBSTITUTE(C75, "-", "@@", LEN(C75) - LEN(SUBSTITUTE(C75, "-", ""))))))) -> Ryan McStravick | P75: =IFERROR(_xlfn.XLOOKUP(O75,'Department Listing'!$O$1:$O$395,'Department Listing'!$A$1:$A$395),IFERROR(_xlfn.XLOOKUP(O75,'Name Aliases'!$A$2:$A$1000,'Name Aliases'!$B$2:$B$1000),"")) -> 146 | Q75: =IF(ISBLANK($C75),"",$B75) -> 46233 | R75: =IF(ISBLANK($C75),"",IF(ISBLANK($I75),$D75,$I75)) -> Exxon | S75: =IF(ISBLANK($C75),"",$F75 - $G75) -> 28.59 | T75: =IF(ISBLANK($C75),"",C75) -> EXXON MERRITT PKWY GRE MASTERCARD-XXXXXX1AO3VQ-Ryan McStravick | U75: =IF(ISBLANK($C75),"",$D$1) -> Brex Credit Card | V75: =IF(ISBLANK($B75),"",IF(ISBLANK($K75),IF(_xlfn.XLOOKUP($W75,'Category Mapping'!$C:$C,'Category Mapping'!$B:$B)="Travel",_xlfn.XLOOKUP($P75,'Department Listing'!$A:$A,'Department Listing'!$M:$M),_xlfn.XLOOKUP($W75,'Category Mapping'!$C:$C,'Category Mapping'!$D:$D)),$K75)) -> Cost of Goods Sold:COGS- Travel Expenses: | W75: =IF(ISBLANK($B75),"",IF(ISBLANK($L75),RIGHT($E75,LEN($E75) - FIND("^",SUBSTITUTE($E75,":","^",LEN($E75) - LEN(SUBSTITUTE($E75,":",""))))),$L75)) -> Other Travel Expenses | X75: =IF(ISBLANK($J75),$V75&$W75,$J75) -> Cost of Goods Sold:COGS- Travel Expenses:Other Travel Expenses | Y75: =IF(ISBLANK($M75),IFERROR(_xlfn.XLOOKUP($P75,'Department Listing'!$A:$A,'Department Listing'!$L:$L),""),$M75) -> 300- ServiceNow:320- Engineering | Z75: =IF(ISBLANK($B75),"",MATCH($X75,COA!$B:$B,0)) -> 127
B76: 46233 | C76: UBER *TRIP MASTERCARD-XXXXXXEUJGUH-Matthew Morris | E76: Sales & Marketing:Sales & Marketing- Travel Expenses:Ground Transportation | F76: 30.94 | I76: Uber | L76: Ground Transportation | O76: =IF(C76="", "", TRIM(RIGHT(C76, LEN(C76) - FIND("@@", SUBSTITUTE(C76, "-", "@@", LEN(C76) - LEN(SUBSTITUTE(C76, "-", ""))))))) -> Matthew Morris | P76: =IFERROR(_xlfn.XLOOKUP(O76,'Department Listing'!$O$1:$O$395,'Department Listing'!$A$1:$A$395),IFERROR(_xlfn.XLOOKUP(O76,'Name Aliases'!$A$2:$A$1000,'Name Aliases'!$B$2:$B$1000),"")) -> 67 | Q76: =IF(ISBLANK($C76),"",$B76) -> 46233 | R76: =IF(ISBLANK($C76),"",IF(ISBLANK($I76),$D76,$I76)) -> Uber | S76: =IF(ISBLANK($C76),"",$F76 - $G76) -> 30.94 | T76: =IF(ISBLANK($C76),"",C76) -> UBER *TRIP MASTERCARD-XXXXXXEUJGUH-Matthew Morris | U76: =IF(ISBLANK($C76),"",$D$1) -> Brex Credit Card | V76: =IF(ISBLANK($B76),"",IF(ISBLANK($K76),IF(_xlfn.XLOOKUP($W76,'Category Mapping'!$C:$C,'Category Mapping'!$B:$B)="Travel",_xlfn.XLOOKUP($P76,'Department Listing'!$A:$A,'Department Listing'!$M:$M),_xlfn.XLOOKUP($W76,'Category Mapping'!$C:$C,'Category Mapping'!$D:$D)),$K76)) -> Sales & Marketing:Sales & Marketing- Travel Expenses: | W76: =IF(ISBLANK($B76),"",IF(ISBLANK($L76),RIGHT($E76,LEN($E76) - FIND("^",SUBSTITUTE($E76,":","^",LEN($E76) - LEN(SUBSTITUTE($E76,":",""))))),$L76)) -> Ground Transportation | X76: =IF(ISBLANK($J76),$V76&$W76,$J76) -> Sales & Marketing:Sales & Marketing- Travel Expenses:Ground Transportation | Y76: =IF(ISBLANK($M76),IFERROR(_xlfn.XLOOKUP($P76,'Department Listing'!$A:$A,'Department Listing'!$L:$L),""),$M76) -> 300- ServiceNow:330- Sales | Z76: =IF(ISBLANK($B76),"",MATCH($X76,COA!$B:$B,0)) -> 200
B77: 46233 | C77: UBER *TRIP MASTERCARD-XXXXXX6M94Y6-Ryan Henrich | E77: Sales & Marketing:Sales & Marketing- Travel Expenses:Ground Transportation | F77: 25.9 | I77: Uber | L77: Ground Transportation | O77: =IF(C77="", "", TRIM(RIGHT(C77, LEN(C77) - FIND("@@", SUBSTITUTE(C77, "-", "@@", LEN(C77) - LEN(SUBSTITUTE(C77, "-", ""))))))) -> Ryan Henrich | P77: =IFERROR(_xlfn.XLOOKUP(O77,'Department Listing'!$O$1:$O$395,'Department Listing'!$A$1:$A$395),IFERROR(_xlfn.XLOOKUP(O77,'Name Aliases'!$A$2:$A$1000,'Name Aliases'!$B$2:$B$1000),"")) -> 154 | Q77: =IF(ISBLANK($C77),"",$B77) -> 46233 | R77: =IF(ISBLANK($C77),"",IF(ISBLANK($I77),$D77,$I77)) -> Uber | S77: =IF(ISBLANK($C77),"",$F77 - $G77) -> 25.9 | T77: =IF(ISBLANK($C77),"",C77) -> UBER *TRIP MASTERCARD-XXXXXX6M94Y6-Ryan Henrich | U77: =IF(ISBLANK($C77),"",$D$1) -> Brex Credit Card | V77: =IF(ISBLANK($B77),"",IF(ISBLANK($K77),IF(_xlfn.XLOOKUP($W77,'Category Mapping'!$C:$C,'Category Mapping'!$B:$B)="Travel",_xlfn.XLOOKUP($P77,'Department Listing'!$A:$A,'Department Listing'!$M:$M),_xlfn.XLOOKUP($W77,'Category Mapping'!$C:$C,'Category Mapping'!$D:$D)),$K77)) -> Sales & Marketing:Sales & Marketing- Travel Expenses: | W77: =IF(ISBLANK($B77),"",IF(ISBLANK($L77),RIGHT($E77,LEN($E77) - FIND("^",SUBSTITUTE($E77,":","^",LEN($E77) - LEN(SUBSTITUTE($E77,":",""))))),$L77)) -> Ground Transportation | X77: =IF(ISBLANK($J77),$V77&$W77,$J77) -> Sales & Marketing:Sales & Marketing- Travel Expenses:Ground Transportation | Y77: =IF(ISBLANK($M77),IFERROR(_xlfn.XLOOKUP($P77,'Department Listing'!$A:$A,'Department Listing'!$L:$L),""),$M77) -> 200- Datadog:230- Sales | Z77: =IF(ISBLANK($B77),"",MATCH($X77,COA!$B:$B,0)) -> 200
B78: 46233 | C78: MCDONALD'S F20727 MASTERCARD-XXXXXXTQ251D-Jacob Woolf | E78: Sales & Marketing:Sales & Marketing- Travel Expenses:Meals & Entertainment | F78: 11.03 | I78: McDonald's | L78: Meals & Entertainment | O78: =IF(C78="", "", TRIM(RIGHT(C78, LEN(C78) - FIND("@@", SUBSTITUTE(C78, "-", "@@", LEN(C78) - LEN(SUBSTITUTE(C78, "-", ""))))))) -> Jacob Woolf | P78: =IFERROR(_xlfn.XLOOKUP(O78,'Department Listing'!$O$1:$O$395,'Department Listing'!$A$1:$A$395),IFERROR(_xlfn.XLOOKUP(O78,'Name Aliases'!$A$2:$A$1000,'Name Aliases'!$B$2:$B$1000),"")) -> 194 | Q78: =IF(ISBLANK($C78),"",$B78) -> 46233 | R78: =IF(ISBLANK($C78),"",IF(ISBLANK($I78),$D78,$I78)) -> McDonald's | S78: =IF(ISBLANK($C78),"",$F78 - $G78) -> 11.03 | T78: =IF(ISBLANK($C78),"",C78) -> MCDONALD'S F20727 MASTERCARD-XXXXXXTQ251D-Jacob Woolf | U78: =IF(ISBLANK($C78),"",$D$1) -> Brex Credit Card | V78: =IF(ISBLANK($B78),"",IF(ISBLANK($K78),IF(_xlfn.XLOOKUP($W78,'Category Mapping'!$C:$C,'Category Mapping'!$B:$B)="Travel",_xlfn.XLOOKUP($P78,'Department Listing'!$A:$A,'Department Listing'!$M:$M),_xlfn.XLOOKUP($W78,'Category Mapping'!$C:$C,'Category Mapping'!$D:$D)),$K78)) -> Cost of Goods Sold:COGS- Travel Expenses: | W78: =IF(ISBLANK($B78),"",IF(ISBLANK($L78),RIGHT($E78,LEN($E78) - FIND("^",SUBSTITUTE($E78,":","^",LEN($E78) - LEN(SUBSTITUTE($E78,":",""))))),$L78)) -> Meals & Entertainment | X78: =IF(ISBLANK($J78),$V78&$W78,$J78) -> Cost of Goods Sold:COGS- Travel Expenses:Meals & Entertainment | Y78: =IF(ISBLANK($M78),IFERROR(_xlfn.XLOOKUP($P78,'Department Listing'!$A:$A,'Department Listing'!$L:$L),""),$M78) -> 300- ServiceNow:320- Engineering | Z78: =IF(ISBLANK($B78),"",MATCH($X78,COA!$B:$B,0)) -> 126
B79: 46233 | C79: AIR ESSENTIALS 122 DFW MASTERCARD-XXXXXX0QTA9M-Jacob Woolf | F79: 14.65 | I79: Office Vendor | L79: Office Supplies | O79: =IF(C79="", "", TRIM(RIGHT(C79, LEN(C79) - FIND("@@", SUBSTITUTE(C79, "-", "@@", LEN(C79) - LEN(SUBSTITUTE(C79, "-", ""))))))) -> Jacob Woolf | P79: =IFERROR(_xlfn.XLOOKUP(O79,'Department Listing'!$O$1:$O$395,'Department Listing'!$A$1:$A$395),IFERROR(_xlfn.XLOOKUP(O79,'Name Aliases'!$A$2:$A$1000,'Name Aliases'!$B$2:$B$1000),"")) -> 194 | Q79: =IF(ISBLANK($C79),"",$B79) -> 46233 | R79: =IF(ISBLANK($C79),"",IF(ISBLANK($I79),$D79,$I79)) -> Office Vendor | S79: =IF(ISBLANK($C79),"",$F79 - $G79) -> 14.65 | T79: =IF(ISBLANK($C79),"",C79) -> AIR ESSENTIALS 122 DFW MASTERCARD-XXXXXX0QTA9M-Jacob Woolf | U79: =IF(ISBLANK($C79),"",$D$1) -> Brex Credit Card | V79: =IF(ISBLANK($B79),"",IF(ISBLANK($K79),IF(_xlfn.XLOOKUP($W79,'Category Mapping'!$C:$C,'Category Mapping'!$B:$B)="Travel",_xlfn.XLOOKUP($P79,'Department Listing'!$A:$A,'Department Listing'!$M:$M),_xlfn.XLOOKUP($W79,'Category Mapping'!$C:$C,'Category Mapping'!$D:$D)),$K79)) -> General & Administrative:Office Expenses: | W79: =IF(ISBLANK($B79),"",IF(ISBLANK($L79),RIGHT($E79,LEN($E79) - FIND("^",SUBSTITUTE($E79,":","^",LEN($E79) - LEN(SUBSTITUTE($E79,":",""))))),$L79)) -> Office Supplies | X79: =IF(ISBLANK($J79),$V79&$W79,$J79) -> General & Administrative:Office Expenses:Office Supplies | Y79: =IF(ISBLANK($M79),IFERROR(_xlfn.XLOOKUP($P79,'Department Listing'!$A:$A,'Department Listing'!$L:$L),""),$M79) -> 300- ServiceNow:320- Engineering | Z79: =IF(ISBLANK($B79),"",MATCH($X79,COA!$B:$B,0)) -> 161
B80: 46233 | C80: TST* RAMIS MASTERCARD-XXXXXX9NHJTH-Meghan Murray | E80: Sales & Marketing:Sales & Marketing- Travel Expenses:Meals & Entertainment | F80: 38.37 | I80: Food Vendor | L80: Meals & Entertainment | O80: =IF(C80="", "", TRIM(RIGHT(C80, LEN(C80) - FIND("@@", SUBSTITUTE(C80, "-", "@@", LEN(C80) - LEN(SUBSTITUTE(C80, "-", ""))))))) -> Meghan Murray | P80: =IFERROR(_xlfn.XLOOKUP(O80,'Department Listing'!$O$1:$O$395,'Department Listing'!$A$1:$A$395),IFERROR(_xlfn.XLOOKUP(O80,'Name Aliases'!$A$2:$A$1000,'Name Aliases'!$B$2:$B$1000),"")) -> 175 | Q80: =IF(ISBLANK($C80),"",$B80) -> 46233 | R80: =IF(ISBLANK($C80),"",IF(ISBLANK($I80),$D80,$I80)) -> Food Vendor | S80: =IF(ISBLANK($C80),"",$F80 - $G80) -> 38.37 | T80: =IF(ISBLANK($C80),"",C80) -> TST* RAMIS MASTERCARD-XXXXXX9NHJTH-Meghan Murray | U80: =IF(ISBLANK($C80),"",$D$1) -> Brex Credit Card | V80: =IF(ISBLANK($B80),"",IF(ISBLANK($K80),IF(_xlfn.XLOOKUP($W80,'Category Mapping'!$C:$C,'Category Mapping'!$B:$B)="Travel",_xlfn.XLOOKUP($P80,'Department Listing'!$A:$A,'Department Listing'!$M:$M),_xlfn.XLOOKUP($W80,'Category Mapping'!$C:$C,'Category Mapping'!$D:$D)),$K80)) -> Cost of Goods Sold:COGS- Travel Expenses: | W80: =IF(ISBLANK($B80),"",IF(ISBLANK($L80),RIGHT($E80,LEN($E80) - FIND("^",SUBSTITUTE($E80,":","^",LEN($E80) - LEN(SUBSTITUTE($E80,":",""))))),$L80)) -> Meals & Entertainment | X80: =IF(ISBLANK($J80),$V80&$W80,$J80) -> Cost of Goods Sold:COGS- Travel Expenses:Meals & Entertainment | Y80: =IF(ISBLANK($M80),IFERROR(_xlfn.XLOOKUP($P80,'Department Listing'!$A:$A,'Department Listing'!$L:$L),""),$M80) -> 300- ServiceNow:310- Delivery | Z80: =IF(ISBLANK($B80),"",MATCH($X80,COA!$B:$B,0)) -> 126
B81: 46233 | C81: 1042 CAFFE NERO COFFEE MASTERCARD-XXXXXX32OZSH-Nestor Abad Rodriguez | E81: Sales & Marketing:Sales & Marketing- Travel Expenses:Meals & Entertainment | F81: 12.08 | I81: Cafe Nero | L81: Meals & Entertainment | O81: =IF(C81="", "", TRIM(RIGHT(C81, LEN(C81) - FIND("@@", SUBSTITUTE(C81, "-", "@@", LEN(C81) - LEN(SUBSTITUTE(C81, "-", ""))))))) -> Nestor Abad Rodriguez | P81: =IFERROR(_xlfn.XLOOKUP(O81,'Department Listing'!$O$1:$O$395,'Department Listing'!$A$1:$A$395),IFERROR(_xlfn.XLOOKUP(O81,'Name Aliases'!$A$2:$A$1000,'Name Aliases'!$B$2:$B$1000),"")) -> 190 | Q81: =IF(ISBLANK($C81),"",$B81) -> 46233 | R81: =IF(ISBLANK($C81),"",IF(ISBLANK($I81),$D81,$I81)) -> Cafe Nero | S81: =IF(ISBLANK($C81),"",$F81 - $G81) -> 12.08 | T81: =IF(ISBLANK($C81),"",C81) -> 1042 CAFFE NERO COFFEE MASTERCARD-XXXXXX32OZSH-Nestor Abad Rodriguez | U81: =IF(ISBLANK($C81),"",$D$1) -> Brex Credit Card | V81: =IF(ISBLANK($B81),"",IF(ISBLANK($K81),IF(_xlfn.XLOOKUP($W81,'Category Mapping'!$C:$C,'Category Mapping'!$B:$B)="Travel",_xlfn.XLOOKUP($P81,'Department Listing'!$A:$A,'Department Listing'!$M:$M),_xlfn.XLOOKUP($W81,'Category Mapping'!$C:$C,'Category Mapping'!$D:$D)),$K81)) -> Sales & Marketing:Sales & Marketing- Travel Expenses: | W81: =IF(ISBLANK($B81),"",IF(ISBLANK($L81),RIGHT($E81,LEN($E81) - FIND("^",SUBSTITUTE($E81,":","^",LEN($E81) - LEN(SUBSTITUTE($E81,":",""))))),$L81)) -> Meals & Entertainment | X81: =IF(ISBLANK($J81),$V81&$W81,$J81) -> Sales & Marketing:Sales & Marketing- Travel Expenses:Meals & Entertainment | Y81: =IF(ISBLANK($M81),IFERROR(_xlfn.XLOOKUP($P81,'Department Listing'!$A:$A,'Department Listing'!$L:$L),""),$M81) -> 300- ServiceNow:330- Sales | Z81: =IF(ISBLANK($B81),"",MATCH($X81,COA!$B:$B,0)) -> 202
B82: 46233 | C82: UBER *TRIP MASTERCARD-XXXXXX9PUU2R-Chloe Brant | E82: Sales & Marketing:Sales & Marketing- Travel Expenses:Ground Transportation | F82: 39.99 | I82: Uber | L82: Ground Transportation | O82: =IF(C82="", "", TRIM(RIGHT(C82, LEN(C82) - FIND("@@", SUBSTITUTE(C82, "-", "@@", LEN(C82) - LEN(SUBSTITUTE(C82, "-", ""))))))) -> Chloe Brant | P82: =IFERROR(_xlfn.XLOOKUP(O82,'Department Listing'!$O$1:$O$395,'Department Listing'!$A$1:$A$395),IFERROR(_xlfn.XLOOKUP(O82,'Name Aliases'!$A$2:$A$1000,'Name Aliases'!$B$2:$B$1000),"")) -> 77 | Q82: =IF(ISBLANK($C82),"",$B82) -> 46233 | R82: =IF(ISBLANK($C82),"",IF(ISBLANK($I82),$D82,$I82)) -> Uber | S82: =IF(ISBLANK($C82),"",$F82 - $G82) -> 39.99 | T82: =IF(ISBLANK($C82),"",C82) -> UBER *TRIP MASTERCARD-XXXXXX9PUU2R-Chloe Brant | U82: =IF(ISBLANK($C82),"",$D$1) -> Brex Credit Card | V82: =IF(ISBLANK($B82),"",IF(ISBLANK($K82),IF(_xlfn.XLOOKUP($W82,'Category Mapping'!$C:$C,'Category Mapping'!$B:$B)="Travel",_xlfn.XLOOKUP($P82,'Department Listing'!$A:$A,'Department Listing'!$M:$M),_xlfn.XLOOKUP($W82,'Category Mapping'!$C:$C,'Category Mapping'!$D:$D)),$K82)) -> Sales & Marketing:Sales & Marketing- Travel Expenses: | W82: =IF(ISBLANK($B82),"",IF(ISBLANK($L82),RIGHT($E82,LEN($E82) - FIND("^",SUBSTITUTE($E82,":","^",LEN($E82) - LEN(SUBSTITUTE($E82,":",""))))),$L82)) -> Ground Transportation | X82: =IF(ISBLANK($J82),$V82&$W82,$J82) -> Sales & Marketing:Sales & Marketing- Travel Expenses:Ground Transportation | Y82: =IF(ISBLANK($M82),IFERROR(_xlfn.XLOOKUP($P82,'Department Listing'!$A:$A,'Department Listing'!$L:$L),""),$M82) -> 300- ServiceNow:330- Sales | Z82: =IF(ISBLANK($B82),"",MATCH($X82,COA!$B:$B,0)) -> 200
B83: 46233 | C83: SQ *CAFE #65224 BACK B MASTERCARD-XXXXXXRPL2E3-Brian McGonigal | F83: 9.6 | I83: Food Vendor | L83: Meals & Entertainment | O83: =IF(C83="", "", TRIM(RIGHT(C83, LEN(C83) - FIND("@@", SUBSTITUTE(C83, "-", "@@", LEN(C83) - LEN(SUBSTITUTE(C83, "-", ""))))))) -> Brian McGonigal | P83: =IFERROR(_xlfn.XLOOKUP(O83,'Department Listing'!$O$1:$O$395,'Department Listing'!$A$1:$A$395),IFERROR(_xlfn.XLOOKUP(O83,'Name Aliases'!$A$2:$A$1000,'Name Aliases'!$B$2:$B$1000),"")) -> 269 | Q83: =IF(ISBLANK($C83),"",$B83) -> 46233 | R83: =IF(ISBLANK($C83),"",IF(ISBLANK($I83),$D83,$I83)) -> Food Vendor | S83: =IF(ISBLANK($C83),"",$F83 - $G83) -> 9.6 | T83: =IF(ISBLANK($C83),"",C83) -> SQ *CAFE #65224 BACK B MASTERCARD-XXXXXXRPL2E3-Brian McGonigal | U83: =IF(ISBLANK($C83),"",$D$1) -> Brex Credit Card | V83: =IF(ISBLANK($B83),"",IF(ISBLANK($K83),IF(_xlfn.XLOOKUP($W83,'Category Mapping'!$C:$C,'Category Mapping'!$B:$B)="Travel",_xlfn.XLOOKUP($P83,'Department Listing'!$A:$A,'Department Listing'!$M:$M),_xlfn.XLOOKUP($W83,'Category Mapping'!$C:$C,'Category Mapping'!$D:$D)),$K83)) -> Sales & Marketing:Sales & Marketing- Travel Expenses: | W83: =IF(ISBLANK($B83),"",IF(ISBLANK($L83),RIGHT($E83,LEN($E83) - FIND("^",SUBSTITUTE($E83,":","^",LEN($E83) - LEN(SUBSTITUTE($E83,":",""))))),$L83)) -> Meals & Entertainment | X83: =IF(ISBLANK($J83),$V83&$W83,$J83) -> Sales & Marketing:Sales & Marketing- Travel Expenses:Meals & Entertainment | Y83: =IF(ISBLANK($M83),IFERROR(_xlfn.XLOOKUP($P83,'Department Listing'!$A:$A,'Department Listing'!$L:$L),""),$M83) -> 300- ServiceNow:330- Sales | Z83: =IF(ISBLANK($B83),"",MATCH($X83,COA!$B:$B,0)) -> 202
B84: 46233 | C84: SQ *THINKING CUP NEWBU MASTERCARD-XXXXXX0G91RL-Jared Kennedy | E84: Sales & Marketing:Sales & Marketing- Travel Expenses:Meals & Entertainment | F84: 7.15 | I84: Thinking Cup | L84: Meals & Entertainment | O84: =IF(C84="", "", TRIM(RIGHT(C84, LEN(C84) - FIND("@@", SUBSTITUTE(C84, "-", "@@", LEN(C84) - LEN(SUBSTITUTE(C84, "-", ""))))))) -> Jared Kennedy | P84: =IFERROR(_xlfn.XLOOKUP(O84,'Department Listing'!$O$1:$O$395,'Department Listing'!$A$1:$A$395),IFERROR(_xlfn.XLOOKUP(O84,'Name Aliases'!$A$2:$A$1000,'Name Aliases'!$B$2:$B$1000),"")) -> 289 | Q84: =IF(ISBLANK($C84),"",$B84) -> 46233 | R84: =IF(ISBLANK($C84),"",IF(ISBLANK($I84),$D84,$I84)) -> Thinking Cup | S84: =IF(ISBLANK($C84),"",$F84 - $G84) -> 7.15 | T84: =IF(ISBLANK($C84),"",C84) -> SQ *THINKING CUP NEWBU MASTERCARD-XXXXXX0G91RL-Jared Kennedy | U84: =IF(ISBLANK($C84),"",$D$1) -> Brex Credit Card | V84: =IF(ISBLANK($B84),"",IF(ISBLANK($K84),IF(_xlfn.XLOOKUP($W84,'Category Mapping'!$C:$C,'Category Mapping'!$B:$B)="Travel",_xlfn.XLOOKUP($P84,'Department Listing'!$A:$A,'Department Listing'!$M:$M),_xlfn.XLOOKUP($W84,'Category Mapping'!$C:$C,'Category Mapping'!$D:$D)),$K84)) -> Sales & Marketing:Sales & Marketing- Travel Expenses: | W84: =IF(ISBLANK($B84),"",IF(ISBLANK($L84),RIGHT($E84,LEN($E84) - FIND("^",SUBSTITUTE($E84,":","^",LEN($E84) - LEN(SUBSTITUTE($E84,":",""))))),$L84)) -> Meals & Entertainment | X84: =IF(ISBLANK($J84),$V84&$W84,$J84) -> Sales & Marketing:Sales & Marketing- Travel Expenses:Meals & Entertainment | Y84: =IF(ISBLANK($M84),IFERROR(_xlfn.XLOOKUP($P84,'Department Listing'!$A:$A,'Department Listing'!$L:$L),""),$M84) -> 200- Datadog:230- Sales | Z84: =IF(ISBLANK($B84),"",MATCH($X84,COA!$B:$B,0)) -> 202
B85: 46233 | C85: LinkedIn P3061358805 MASTERCARD-XXXXXXP8M8F9-Karalyn Sims | E85: General & Administrative:Office Expenses:Dues & Subscriptions | F85: 171.86 | I85: LinkedIn Corporation | L85: Dues & Subscriptions | O85: =IF(C85="", "", TRIM(RIGHT(C85, LEN(C85) - FIND("@@", SUBSTITUTE(C85, "-", "@@", LEN(C85) - LEN(SUBSTITUTE(C85, "-", ""))))))) -> Karalyn Sims | P85: =IFERROR(_xlfn.XLOOKUP(O85,'Department Listing'!$O$1:$O$395,'Department Listing'!$A$1:$A$395),IFERROR(_xlfn.XLOOKUP(O85,'Name Aliases'!$A$2:$A$1000,'Name Aliases'!$B$2:$B$1000),"")) -> 144 | Q85: =IF(ISBLANK($C85),"",$B85) -> 46233 | R85: =IF(ISBLANK($C85),"",IF(ISBLANK($I85),$D85,$I85)) -> LinkedIn Corporation | S85: =IF(ISBLANK($C85),"",$F85 - $G85) -> 171.86 | T85: =IF(ISBLANK($C85),"",C85) -> LinkedIn P3061358805 MASTERCARD-XXXXXXP8M8F9-Karalyn Sims | U85: =IF(ISBLANK($C85),"",$D$1) -> Brex Credit Card | V85: =IF(ISBLANK($B85),"",IF(ISBLANK($K85),IF(_xlfn.XLOOKUP($W85,'Category Mapping'!$C:$C,'Category Mapping'!$B:$B)="Travel",_xlfn.XLOOKUP($P85,'Department Listing'!$A:$A,'Department Listing'!$M:$M),_xlfn.XLOOKUP($W85,'Category Mapping'!$C:$C,'Category Mapping'!$D:$D)),$K85)) -> General & Administrative:Office Expenses: | W85: =IF(ISBLANK($B85),"",IF(ISBLANK($L85),RIGHT($E85,LEN($E85) - FIND("^",SUBSTITUTE($E85,":","^",LEN($E85) - LEN(SUBSTITUTE($E85,":",""))))),$L85)) -> Dues & Subscriptions | X85: =IF(ISBLANK($J85),$V85&$W85,$J85) -> General & Administrative:Office Expenses:Dues & Subscriptions | Y85: =IF(ISBLANK($M85),IFERROR(_xlfn.XLOOKUP($P85,'Department Listing'!$A:$A,'Department Listing'!$L:$L),""),$M85) -> 100- Operations:120- Marketing | Z85: =IF(ISBLANK($B85),"",MATCH($X85,COA!$B:$B,0)) -> 159
B86: 46233 | C86: TST* TATTE BAKERY - CO MASTERCARD-XXXXXX75F0H0-Ben Savage | E86: Sales & Marketing:Sales & Marketing- Travel Expenses:Meals & Entertainment | F86: 27.54 | I86: Tatte | L86: Meals & Entertainment | O86: =IF(C86="", "", TRIM(RIGHT(C86, LEN(C86) - FIND("@@", SUBSTITUTE(C86, "-", "@@", LEN(C86) - LEN(SUBSTITUTE(C86, "-", ""))))))) -> Ben Savage | P86: =IFERROR(_xlfn.XLOOKUP(O86,'Department Listing'!$O$1:$O$395,'Department Listing'!$A$1:$A$395),IFERROR(_xlfn.XLOOKUP(O86,'Name Aliases'!$A$2:$A$1000,'Name Aliases'!$B$2:$B$1000),"")) -> 71 | Q86: =IF(ISBLANK($C86),"",$B86) -> 46233 | R86: =IF(ISBLANK($C86),"",IF(ISBLANK($I86),$D86,$I86)) -> Tatte | S86: =IF(ISBLANK($C86),"",$F86 - $G86) -> 27.54 | T86: =IF(ISBLANK($C86),"",C86) -> TST* TATTE BAKERY - CO MASTERCARD-XXXXXX75F0H0-Ben Savage | U86: =IF(ISBLANK($C86),"",$D$1) -> Brex Credit Card | V86: =IF(ISBLANK($B86),"",IF(ISBLANK($K86),IF(_xlfn.XLOOKUP($W86,'Category Mapping'!$C:$C,'Category Mapping'!$B:$B)="Travel",_xlfn.XLOOKUP($P86,'Department Listing'!$A:$A,'Department Listing'!$M:$M),_xlfn.XLOOKUP($W86,'Category Mapping'!$C:$C,'Category Mapping'!$D:$D)),$K86)) -> Cost of Goods Sold:COGS- Travel Expenses: | W86: =IF(ISBLANK($B86),"",IF(ISBLANK($L86),RIGHT($E86,LEN($E86) - FIND("^",SUBSTITUTE($E86,":","^",LEN($E86) - LEN(SUBSTITUTE($E86,":",""))))),$L86)) -> Meals & Entertainment | X86: =IF(ISBLANK($J86),$V86&$W86,$J86) -> Cost of Goods Sold:COGS- Travel Expenses:Meals & Entertainment | Y86: =IF(ISBLANK($M86),IFERROR(_xlfn.XLOOKUP($P86,'Department Listing'!$A:$A,'Department Listing'!$L:$L),""),$M86) -> 300- ServiceNow:320- Engineering | Z86: =IF(ISBLANK($B86),"",MATCH($X86,COA!$B:$B,0)) -> 126
B87: 46233 | C87: CVS/PHARMACY #01217 MASTERCARD-XXXXXXWSMXI6-Gary Passaglia | E87: General & Administrative:Office Expenses:Office Supplies | F87: 5 | I87: CVS | L87: Office Supplies | O87: =IF(C87="", "", TRIM(RIGHT(C87, LEN(C87) - FIND("@@", SUBSTITUTE(C87, "-", "@@", LEN(C87) - LEN(SUBSTITUTE(C87, "-", ""))))))) -> Gary Passaglia | P87: =IFERROR(_xlfn.XLOOKUP(O87,'Department Listing'!$O$1:$O$395,'Department Listing'!$A$1:$A$395),IFERROR(_xlfn.XLOOKUP(O87,'Name Aliases'!$A$2:$A$1000,'Name Aliases'!$B$2:$B$1000),"")) -> 148 | Q87: =IF(ISBLANK($C87),"",$B87) -> 46233 | R87: =IF(ISBLANK($C87),"",IF(ISBLANK($I87),$D87,$I87)) -> CVS | S87: =IF(ISBLANK($C87),"",$F87 - $G87) -> 5 | T87: =IF(ISBLANK($C87),"",C87) -> CVS/PHARMACY #01217 MASTERCARD-XXXXXXWSMXI6-Gary Passaglia | U87: =IF(ISBLANK($C87),"",$D$1) -> Brex Credit Card | V87: =IF(ISBLANK($B87),"",IF(ISBLANK($K87),IF(_xlfn.XLOOKUP($W87,'Category Mapping'!$C:$C,'Category Mapping'!$B:$B)="Travel",_xlfn.XLOOKUP($P87,'Department Listing'!$A:$A,'Department Listing'!$M:$M),_xlfn.XLOOKUP($W87,'Category Mapping'!$C:$C,'Category Mapping'!$D:$D)),$K87)) -> General & Administrative:Office Expenses: | W87: =IF(ISBLANK($B87),"",IF(ISBLANK($L87),RIGHT($E87,LEN($E87) - FIND("^",SUBSTITUTE($E87,":","^",LEN($E87) - LEN(SUBSTITUTE($E87,":",""))))),$L87)) -> Office Supplies | X87: =IF(ISBLANK($J87),$V87&$W87,$J87) -> General & Administrative:Office Expenses:Office Supplies | Y87: =IF(ISBLANK($M87),IFERROR(_xlfn.XLOOKUP($P87,'Department Listing'!$A:$A,'Department Listing'!$L:$L),""),$M87) -> 300- ServiceNow:330- Sales | Z87: =IF(ISBLANK($B87),"",MATCH($X87,COA!$B:$B,0)) -> 161
B88: 46233 | C88: MBTA-550048231694 MASTERCARD-XXXXXXWMGEU8-Karalyn Sims | E88: General & Administrative:G&A- Travel Expenses:Ground Transportation | F88: 1.7 | I88: Mbta | L88: Ground Transportation | O88: =IF(C88="", "", TRIM(RIGHT(C88, LEN(C88) - FIND("@@", SUBSTITUTE(C88, "-", "@@", LEN(C88) - LEN(SUBSTITUTE(C88, "-", ""))))))) -> Karalyn Sims | P88: =IFERROR(_xlfn.XLOOKUP(O88,'Department Listing'!$O$1:$O$395,'Department Listing'!$A$1:$A$395),IFERROR(_xlfn.XLOOKUP(O88,'Name Aliases'!$A$2:$A$1000,'Name Aliases'!$B$2:$B$1000),"")) -> 144 | Q88: =IF(ISBLANK($C88),"",$B88) -> 46233 | R88: =IF(ISBLANK($C88),"",IF(ISBLANK($I88),$D88,$I88)) -> Mbta | S88: =IF(ISBLANK($C88),"",$F88 - $G88) -> 1.7 | T88: =IF(ISBLANK($C88),"",C88) -> MBTA-550048231694 MASTERCARD-XXXXXXWMGEU8-Karalyn Sims | U88: =IF(ISBLANK($C88),"",$D$1) -> Brex Credit Card | V88: =IF(ISBLANK($B88),"",IF(ISBLANK($K88),IF(_xlfn.XLOOKUP($W88,'Category Mapping'!$C:$C,'Category Mapping'!$B:$B)="Travel",_xlfn.XLOOKUP($P88,'Department Listing'!$A:$A,'Department Listing'!$M:$M),_xlfn.XLOOKUP($W88,'Category Mapping'!$C:$C,'Category Mapping'!$D:$D)),$K88)) -> Sales & Marketing:Sales & Marketing- Travel Expenses: | W88: =IF(ISBLANK($B88),"",IF(ISBLANK($L88),RIGHT($E88,LEN($E88) - FIND("^",SUBSTITUTE($E88,":","^",LEN($E88) - LEN(SUBSTITUTE($E88,":",""))))),$L88)) -> Ground Transportation | X88: =IF(ISBLANK($J88),$V88&$W88,$J88) -> Sales & Marketing:Sales & Marketing- Travel Expenses:Ground Transportation | Y88: =IF(ISBLANK($M88),IFERROR(_xlfn.XLOOKUP($P88,'Department Listing'!$A:$A,'Department Listing'!$L:$L),""),$M88) -> 100- Operations:120- Marketing | Z88: =IF(ISBLANK($B88),"",MATCH($X88,COA!$B:$B,0)) -> 200
B89: 46233 | C89: DUNKIN #300417 Q35 MASTERCARD-XXXXXX8FRDT2-Gary Passaglia | E89: Sales & Marketing:Sales & Marketing- Travel Expenses:Meals & Entertainment | F89: 4.91 | I89: Dunkin Donuts | L89: Meals & Entertainment | O89: =IF(C89="", "", TRIM(RIGHT(C89, LEN(C89) - FIND("@@", SUBSTITUTE(C89, "-", "@@", LEN(C89) - LEN(SUBSTITUTE(C89, "-", ""))))))) -> Gary Passaglia | P89: =IFERROR(_xlfn.XLOOKUP(O89,'Department Listing'!$O$1:$O$395,'Department Listing'!$A$1:$A$395),IFERROR(_xlfn.XLOOKUP(O89,'Name Aliases'!$A$2:$A$1000,'Name Aliases'!$B$2:$B$1000),"")) -> 148 | Q89: =IF(ISBLANK($C89),"",$B89) -> 46233 | R89: =IF(ISBLANK($C89),"",IF(ISBLANK($I89),$D89,$I89)) -> Dunkin Donuts | S89: =IF(ISBLANK($C89),"",$F89 - $G89) -> 4.91 | T89: =IF(ISBLANK($C89),"",C89) -> DUNKIN #300417 Q35 MASTERCARD-XXXXXX8FRDT2-Gary Passaglia | U89: =IF(ISBLANK($C89),"",$D$1) -> Brex Credit Card | V89: =IF(ISBLANK($B89),"",IF(ISBLANK($K89),IF(_xlfn.XLOOKUP($W89,'Category Mapping'!$C:$C,'Category Mapping'!$B:$B)="Travel",_xlfn.XLOOKUP($P89,'Department Listing'!$A:$A,'Department Listing'!$M:$M),_xlfn.XLOOKUP($W89,'Category Mapping'!$C:$C,'Category Mapping'!$D:$D)),$K89)) -> Sales & Marketing:Sales & Marketing- Travel Expenses: | W89: =IF(ISBLANK($B89),"",IF(ISBLANK($L89),RIGHT($E89,LEN($E89) - FIND("^",SUBSTITUTE($E89,":","^",LEN($E89) - LEN(SUBSTITUTE($E89,":",""))))),$L89)) -> Meals & Entertainment | X89: =IF(ISBLANK($J89),$V89&$W89,$J89) -> Sales & Marketing:Sales & Marketing- Travel Expenses:Meals & Entertainment | Y89: =IF(ISBLANK($M89),IFERROR(_xlfn.XLOOKUP($P89,'Department Listing'!$A:$A,'Department Listing'!$L:$L),""),$M89) -> 300- ServiceNow:330- Sales | Z89: =IF(ISBLANK($B89),"",MATCH($X89,COA!$B:$B,0)) -> 202
B90: 46233 | C90: UBER *TRIP MASTERCARD-XXXXXX16E23A-Gaby Catalano | E90: Sales & Marketing:Sales & Marketing- Travel Expenses:Ground Transportation | F90: 76.85 | I90: Uber | L90: Ground Transportation | O90: =IF(C90="", "", TRIM(RIGHT(C90, LEN(C90) - FIND("@@", SUBSTITUTE(C90, "-", "@@", LEN(C90) - LEN(SUBSTITUTE(C90, "-", ""))))))) -> Gaby Catalano | P90: =IFERROR(_xlfn.XLOOKUP(O90,'Department Listing'!$O$1:$O$395,'Department Listing'!$A$1:$A$395),IFERROR(_xlfn.XLOOKUP(O90,'Name Aliases'!$A$2:$A$1000,'Name Aliases'!$B$2:$B$1000),"")) -> 256 | Q90: =IF(ISBLANK($C90),"",$B90) -> 46233 | R90: =IF(ISBLANK($C90),"",IF(ISBLANK($I90),$D90,$I90)) -> Uber | S90: =IF(ISBLANK($C90),"",$F90 - $G90) -> 76.85 | T90: =IF(ISBLANK($C90),"",C90) -> UBER *TRIP MASTERCARD-XXXXXX16E23A-Gaby Catalano | U90: =IF(ISBLANK($C90),"",$D$1) -> Brex Credit Card | V90: =IF(ISBLANK($B90),"",IF(ISBLANK($K90),IF(_xlfn.XLOOKUP($W90,'Category Mapping'!$C:$C,'Category Mapping'!$B:$B)="Travel",_xlfn.XLOOKUP($P90,'Department Listing'!$A:$A,'Department Listing'!$M:$M),_xlfn.XLOOKUP($W90,'Category Mapping'!$C:$C,'Category Mapping'!$D:$D)),$K90)) -> Cost of Goods Sold:COGS- Travel Expenses: | W90: =IF(ISBLANK($B90),"",IF(ISBLANK($L90),RIGHT($E90,LEN($E90) - FIND("^",SUBSTITUTE($E90,":","^",LEN($E90) - LEN(SUBSTITUTE($E90,":",""))))),$L90)) -> Ground Transportation | X90: =IF(ISBLANK($J90),$V90&$W90,$J90) -> Cost of Goods Sold:COGS- Travel Expenses:Ground Transportation | Y90: =IF(ISBLANK($M90),IFERROR(_xlfn.XLOOKUP($P90,'Department Listing'!$A:$A,'Department Listing'!$L:$L),""),$M90) -> 300- ServiceNow:310- Delivery | Z90: =IF(ISBLANK($B90),"",MATCH($X90,COA!$B:$B,0)) -> 124
B91: 46233 | C91: OLO*Pressed Cafe MASTERCARD-XXXXXXPWVICO-Michael Joyce | E91: Sales & Marketing:Sales & Marketing- Travel Expenses:Meals & Entertainment | F91: 17.12 | I91: Food Vendor | K91: Sales & Marketing:Sales & Marketing- Travel Expenses:Meals & Entertainment | L91: Meals & Entertainment | O91: =IF(C91="", "", TRIM(RIGHT(C91, LEN(C91) - FIND("@@", SUBSTITUTE(C91, "-", "@@", LEN(C91) - LEN(SUBSTITUTE(C91, "-", ""))))))) -> Michael Joyce | P91: =IFERROR(_xlfn.XLOOKUP(O91,'Department Listing'!$O$1:$O$395,'Department Listing'!$A$1:$A$395),IFERROR(_xlfn.XLOOKUP(O91,'Name Aliases'!$A$2:$A$1000,'Name Aliases'!$B$2:$B$1000),"")) -> 290 | Q91: =IF(ISBLANK($C91),"",$B91) -> 46233 | R91: =IF(ISBLANK($C91),"",IF(ISBLANK($I91),$D91,$I91)) -> Food Vendor | S91: =IF(ISBLANK($C91),"",$F91 - $G91) -> 17.12 | T91: =IF(ISBLANK($C91),"",C91) -> OLO*Pressed Cafe MASTERCARD-XXXXXXPWVICO-Michael Joyce | U91: =IF(ISBLANK($C91),"",$D$1) -> Brex Credit Card | V91: =IF(ISBLANK($B91),"",IF(ISBLANK($K91),IF(_xlfn.XLOOKUP($W91,'Category Mapping'!$C:$C,'Category Mapping'!$B:$B)="Travel",_xlfn.XLOOKUP($P91,'Department Listing'!$A:$A,'Department Listing'!$M:$M),_xlfn.XLOOKUP($W91,'Category Mapping'!$C:$C,'Category Mapping'!$D:$D)),$K91)) -> Sales & Marketing:Sales & Marketing- Travel Expenses:Meals & Entertainment | W91: =IF(ISBLANK($B91),"",IF(ISBLANK($L91),RIGHT($E91,LEN($E91) - FIND("^",SUBSTITUTE($E91,":","^",LEN($E91) - LEN(SUBSTITUTE($E91,":",""))))),$L91)) -> Meals & Entertainment | X91: =IF(ISBLANK($J91),$V91&$W91,$J91) -> Sales & Marketing:Sales & Marketing- Travel Expenses:Meals & EntertainmentMeals & Entertainment | Y91: =IF(ISBLANK($M91),IFERROR(_xlfn.XLOOKUP($P91,'Department Listing'!$A:$A,'Department Listing'!$L:$L),""),$M91) -> 300- ServiceNow:310- Delivery | Z91: 202
B92: 46233 | C92: TST* TATTE BAKERY - CO MASTERCARD-XXXXXXFVGVVS-Maile Call | E92: Sales & Marketing:Sales & Marketing- Travel Expenses:Meals & Entertainment | F92: 10.35 | I92: Tatte | L92: Meals & Entertainment | O92: =IF(C92="", "", TRIM(RIGHT(C92, LEN(C92) - FIND("@@", SUBSTITUTE(C92, "-", "@@", LEN(C92) - LEN(SUBSTITUTE(C92, "-", ""))))))) -> Maile Call | P92: =IFERROR(_xlfn.XLOOKUP(O92,'Department Listing'!$O$1:$O$395,'Department Listing'!$A$1:$A$395),IFERROR(_xlfn.XLOOKUP(O92,'Name Aliases'!$A$2:$A$1000,'Name Aliases'!$B$2:$B$1000),"")) -> 241 | Q92: =IF(ISBLANK($C92),"",$B92) -> 46233 | R92: =IF(ISBLANK($C92),"",IF(ISBLANK($I92),$D92,$I92)) -> Tatte | S92: =IF(ISBLANK($C92),"",$F92 - $G92) -> 10.35 | T92: =IF(ISBLANK($C92),"",C92) -> TST* TATTE BAKERY - CO MASTERCARD-XXXXXXFVGVVS-Maile Call | U92: =IF(ISBLANK($C92),"",$D$1) -> Brex Credit Card | V92: =IF(ISBLANK($B92),"",IF(ISBLANK($K92),IF(_xlfn.XLOOKUP($W92,'Category Mapping'!$C:$C,'Category Mapping'!$B:$B)="Travel",_xlfn.XLOOKUP($P92,'Department Listing'!$A:$A,'Department Listing'!$M:$M),_xlfn.XLOOKUP($W92,'Category Mapping'!$C:$C,'Category Mapping'!$D:$D)),$K92)) -> Sales & Marketing:Sales & Marketing- Travel Expenses: | W92: =IF(ISBLANK($B92),"",IF(ISBLANK($L92),RIGHT($E92,LEN($E92) - FIND("^",SUBSTITUTE($E92,":","^",LEN($E92) - LEN(SUBSTITUTE($E92,":",""))))),$L92)) -> Meals & Entertainment | X92: =IF(ISBLANK($J92),$V92&$W92,$J92) -> Sales & Marketing:Sales & Marketing- Travel Expenses:Meals & Entertainment | Y92: =IF(ISBLANK($M92),IFERROR(_xlfn.XLOOKUP($P92,'Department Listing'!$A:$A,'Department Listing'!$L:$L),""),$M92) -> 300- ServiceNow:330- Sales | Z92: =IF(ISBLANK($B92),"",MATCH($X92,COA!$B:$B,0)) -> 202
B93: 46233 | C93: PRESSED CAFE PRUDENTI MASTERCARD-XXXXXXA52LG3-Mickenzi Krpec | F93: 1492.34 | I93: Food Vendor | L93: Meals & Entertainment | O93: =IF(C93="", "", TRIM(RIGHT(C93, LEN(C93) - FIND("@@", SUBSTITUTE(C93, "-", "@@", LEN(C93) - LEN(SUBSTITUTE(C93, "-", ""))))))) -> Mickenzi Krpec | P93: =IFERROR(_xlfn.XLOOKUP(O93,'Department Listing'!$O$1:$O$395,'Department Listing'!$A$1:$A$395),IFERROR(_xlfn.XLOOKUP(O93,'Name Aliases'!$A$2:$A$1000,'Name Aliases'!$B$2:$B$1000),"")) -> 170 | Q93: =IF(ISBLANK($C93),"",$B93) -> 46233 | R93: =IF(ISBLANK($C93),"",IF(ISBLANK($I93),$D93,$I93)) -> Food Vendor | S93: =IF(ISBLANK($C93),"",$F93 - $G93) -> 1492.34 | T93: =IF(ISBLANK($C93),"",C93) -> PRESSED CAFE PRUDENTI MASTERCARD-XXXXXXA52LG3-Mickenzi Krpec | U93: =IF(ISBLANK($C93),"",$D$1) -> Brex Credit Card | V93: =IF(ISBLANK($B93),"",IF(ISBLANK($K93),IF(_xlfn.XLOOKUP($W93,'Category Mapping'!$C:$C,'Category Mapping'!$B:$B)="Travel",_xlfn.XLOOKUP($P93,'Department Listing'!$A:$A,'Department Listing'!$M:$M),_xlfn.XLOOKUP($W93,'Category Mapping'!$C:$C,'Category Mapping'!$D:$D)),$K93)) -> General & Administrative:G&A- Travel Expenses: | W93: =IF(ISBLANK($B93),"",IF(ISBLANK($L93),RIGHT($E93,LEN($E93) - FIND("^",SUBSTITUTE($E93,":","^",LEN($E93) - LEN(SUBSTITUTE($E93,":",""))))),$L93)) -> Meals & Entertainment | X93: =IF(ISBLANK($J93),$V93&$W93,$J93) -> General & Administrative:G&A- Travel Expenses:Meals & Entertainment | Y93: =IF(ISBLANK($M93),IFERROR(_xlfn.XLOOKUP($P93,'Department Listing'!$A:$A,'Department Listing'!$L:$L),""),$M93) -> 100- Operations:110- G&A | Z93: =IF(ISBLANK($B93),"",MATCH($X93,COA!$B:$B,0)) -> 151
B94: 46232 | C94: TST*SWEENEYS MASTERCARD-XXXXXXLP8CJO-Tyler Grimshaw | E94: Sales & Marketing:Sales & Marketing- Travel Expenses:Meals & Entertainment | F94: 40.17 | I94: Sweeney's | L94: Meals & Entertainment | O94: =IF(C94="", "", TRIM(RIGHT(C94, LEN(C94) - FIND("@@", SUBSTITUTE(C94, "-", "@@", LEN(C94) - LEN(SUBSTITUTE(C94, "-", ""))))))) -> Tyler Grimshaw | P94: =IFERROR(_xlfn.XLOOKUP(O94,'Department Listing'!$O$1:$O$395,'Department Listing'!$A$1:$A$395),IFERROR(_xlfn.XLOOKUP(O94,'Name Aliases'!$A$2:$A$1000,'Name Aliases'!$B$2:$B$1000),"")) -> 264 | Q94: =IF(ISBLANK($C94),"",$B94) -> 46232 | R94: =IF(ISBLANK($C94),"",IF(ISBLANK($I94),$D94,$I94)) -> Sweeney's | S94: =IF(ISBLANK($C94),"",$F94 - $G94) -> 40.17 | T94: =IF(ISBLANK($C94),"",C94) -> TST*SWEENEYS MASTERCARD-XXXXXXLP8CJO-Tyler Grimshaw | U94: =IF(ISBLANK($C94),"",$D$1) -> Brex Credit Card | V94: =IF(ISBLANK($B94),"",IF(ISBLANK($K94),IF(_xlfn.XLOOKUP($W94,'Category Mapping'!$C:$C,'Category Mapping'!$B:$B)="Travel",_xlfn.XLOOKUP($P94,'Department Listing'!$A:$A,'Department Listing'!$M:$M),_xlfn.XLOOKUP($W94,'Category Mapping'!$C:$C,'Category Mapping'!$D:$D)),$K94)) -> Sales & Marketing:Sales & Marketing- Travel Expenses: | W94: =IF(ISBLANK($B94),"",IF(ISBLANK($L94),RIGHT($E94,LEN($E94) - FIND("^",SUBSTITUTE($E94,":","^",LEN($E94) - LEN(SUBSTITUTE($E94,":",""))))),$L94)) -> Meals & Entertainment | X94: =IF(ISBLANK($J94),$V94&$W94,$J94) -> Sales & Marketing:Sales & Marketing- Travel Expenses:Meals & Entertainment | Y94: =IF(ISBLANK($M94),IFERROR(_xlfn.XLOOKUP($P94,'Department Listing'!$A:$A,'Department Listing'!$L:$L),""),$M94) -> 200- Datadog:230- Sales | Z94: =IF(ISBLANK($B94),"",MATCH($X94,COA!$B:$B,0)) -> 202
B95: 46232 | C95: UBER *TRIP MASTERCARD-XXXXXXUTPOIB-Matt Hyman | E95: Sales & Marketing:Sales & Marketing- Travel Expenses:Ground Transportation | F95: 20.98 | I95: Uber | L95: Ground Transportation | O95: =IF(C95="", "", TRIM(RIGHT(C95, LEN(C95) - FIND("@@", SUBSTITUTE(C95, "-", "@@", LEN(C95) - LEN(SUBSTITUTE(C95, "-", ""))))))) -> Matt Hyman | P95: =IFERROR(_xlfn.XLOOKUP(O95,'Department Listing'!$O$1:$O$395,'Department Listing'!$A$1:$A$395),IFERROR(_xlfn.XLOOKUP(O95,'Name Aliases'!$A$2:$A$1000,'Name Aliases'!$B$2:$B$1000),"")) -> 24 | Q95: =IF(ISBLANK($C95),"",$B95) -> 46232 | R95: =IF(ISBLANK($C95),"",IF(ISBLANK($I95),$D95,$I95)) -> Uber | S95: =IF(ISBLANK($C95),"",$F95 - $G95) -> 20.98 | T95: =IF(ISBLANK($C95),"",C95) -> UBER *TRIP MASTERCARD-XXXXXXUTPOIB-Matt Hyman | U95: =IF(ISBLANK($C95),"",$D$1) -> Brex Credit Card | V95: =IF(ISBLANK($B95),"",IF(ISBLANK($K95),IF(_xlfn.XLOOKUP($W95,'Category Mapping'!$C:$C,'Category Mapping'!$B:$B)="Travel",_xlfn.XLOOKUP($P95,'Department Listing'!$A:$A,'Department Listing'!$M:$M),_xlfn.XLOOKUP($W95,'Category Mapping'!$C:$C,'Category Mapping'!$D:$D)),$K95)) -> Sales & Marketing:Sales & Marketing- Travel Expenses: | W95: =IF(ISBLANK($B95),"",IF(ISBLANK($L95),RIGHT($E95,LEN($E95) - FIND("^",SUBSTITUTE($E95,":","^",LEN($E95) - LEN(SUBSTITUTE($E95,":",""))))),$L95)) -> Ground Transportation | X95: =IF(ISBLANK($J95),$V95&$W95,$J95) -> Sales & Marketing:Sales & Marketing- Travel Expenses:Ground Transportation | Y95: =IF(ISBLANK($M95),IFERROR(_xlfn.XLOOKUP($P95,'Department Listing'!$A:$A,'Department Listing'!$L:$L),""),$M95) -> 300- ServiceNow:330- Sales | Z95: =IF(ISBLANK($B95),"",MATCH($X95,COA!$B:$B,0)) -> 200
B96: 46232 | C96: UBER *TRIP MASTERCARD-XXXXXXYKW01G-Ryan Henrich | E96: Sales & Marketing:Sales & Marketing- Travel Expenses:Ground Transportation | F96: 17.93 | I96: Uber | L96: Ground Transportation | O96: =IF(C96="", "", TRIM(RIGHT(C96, LEN(C96) - FIND("@@", SUBSTITUTE(C96, "-", "@@", LEN(C96) - LEN(SUBSTITUTE(C96, "-", ""))))))) -> Ryan Henrich | P96: =IFERROR(_xlfn.XLOOKUP(O96,'Department Listing'!$O$1:$O$395,'Department Listing'!$A$1:$A$395),IFERROR(_xlfn.XLOOKUP(O96,'Name Aliases'!$A$2:$A$1000,'Name Aliases'!$B$2:$B$1000),"")) -> 154 | Q96: =IF(ISBLANK($C96),"",$B96) -> 46232 | R96: =IF(ISBLANK($C96),"",IF(ISBLANK($I96),$D96,$I96)) -> Uber | S96: =IF(ISBLANK($C96),"",$F96 - $G96) -> 17.93 | T96: =IF(ISBLANK($C96),"",C96) -> UBER *TRIP MASTERCARD-XXXXXXYKW01G-Ryan Henrich | U96: =IF(ISBLANK($C96),"",$D$1) -> Brex Credit Card | V96: =IF(ISBLANK($B96),"",IF(ISBLANK($K96),IF(_xlfn.XLOOKUP($W96,'Category Mapping'!$C:$C,'Category Mapping'!$B:$B)="Travel",_xlfn.XLOOKUP($P96,'Department Listing'!$A:$A,'Department Listing'!$M:$M),_xlfn.XLOOKUP($W96,'Category Mapping'!$C:$C,'Category Mapping'!$D:$D)),$K96)) -> Sales & Marketing:Sales & Marketing- Travel Expenses: | W96: =IF(ISBLANK($B96),"",IF(ISBLANK($L96),RIGHT($E96,LEN($E96) - FIND("^",SUBSTITUTE($E96,":","^",LEN($E96) - LEN(SUBSTITUTE($E96,":",""))))),$L96)) -> Ground Transportation | X96: =IF(ISBLANK($J96),$V96&$W96,$J96) -> Sales & Marketing:Sales & Marketing- Travel Expenses:Ground Transportation | Y96: =IF(ISBLANK($M96),IFERROR(_xlfn.XLOOKUP($P96,'Department Listing'!$A:$A,'Department Listing'!$L:$L),""),$M96) -> 200- Datadog:230- Sales | Z96: =IF(ISBLANK($B96),"",MATCH($X96,COA!$B:$B,0)) -> 200
B97: 46232 | C97: PPL - FAN PIER MASTERCARD-XXXXXX9PARU8-Elyse Neumeier | F97: 38 | I97: Travel Vendor | L97: Other Travel Expenses | O97: =IF(C97="", "", TRIM(RIGHT(C97, LEN(C97) - FIND("@@", SUBSTITUTE(C97, "-", "@@", LEN(C97) - LEN(SUBSTITUTE(C97, "-", ""))))))) -> Elyse Neumeier | P97: =IFERROR(_xlfn.XLOOKUP(O97,'Department Listing'!$O$1:$O$395,'Department Listing'!$A$1:$A$395),IFERROR(_xlfn.XLOOKUP(O97,'Name Aliases'!$A$2:$A$1000,'Name Aliases'!$B$2:$B$1000),"")) -> 98 | Q97: =IF(ISBLANK($C97),"",$B97) -> 46232 | R97: =IF(ISBLANK($C97),"",IF(ISBLANK($I97),$D97,$I97)) -> Travel Vendor | S97: =IF(ISBLANK($C97),"",$F97 - $G97) -> 38 | T97: =IF(ISBLANK($C97),"",C97) -> PPL - FAN PIER MASTERCARD-XXXXXX9PARU8-Elyse Neumeier | U97: =IF(ISBLANK($C97),"",$D$1) -> Brex Credit Card | V97: =IF(ISBLANK($B97),"",IF(ISBLANK($K97),IF(_xlfn.XLOOKUP($W97,'Category Mapping'!$C:$C,'Category Mapping'!$B:$B)="Travel",_xlfn.XLOOKUP($P97,'Department Listing'!$A:$A,'Department Listing'!$M:$M),_xlfn.XLOOKUP($W97,'Category Mapping'!$C:$C,'Category Mapping'!$D:$D)),$K97)) -> General & Administrative:G&A- Travel Expenses: | W97: =IF(ISBLANK($B97),"",IF(ISBLANK($L97),RIGHT($E97,LEN($E97) - FIND("^",SUBSTITUTE($E97,":","^",LEN($E97) - LEN(SUBSTITUTE($E97,":",""))))),$L97)) -> Other Travel Expenses | X97: =IF(ISBLANK($J97),$V97&$W97,$J97) -> General & Administrative:G&A- Travel Expenses:Other Travel Expenses | Y97: =IF(ISBLANK($M97),IFERROR(_xlfn.XLOOKUP($P97,'Department Listing'!$A:$A,'Department Listing'!$L:$L),""),$M97) -> 100- Operations:110- G&A | Z97: =IF(ISBLANK($B97),"",MATCH($X97,COA!$B:$B,0)) -> 152
B98: 46232 | C98: TST*SWEENEYS MASTERCARD-XXXXXXXY71GE-Ben Savage | E98: Sales & Marketing:Sales & Marketing- Travel Expenses:Meals & Entertainment | F98: 16.91 | I98: Sweeney's | L98: Meals & Entertainment | O98: =IF(C98="", "", TRIM(RIGHT(C98, LEN(C98) - FIND("@@", SUBSTITUTE(C98, "-", "@@", LEN(C98) - LEN(SUBSTITUTE(C98, "-", ""))))))) -> Ben Savage | P98: =IFERROR(_xlfn.XLOOKUP(O98,'Department Listing'!$O$1:$O$395,'Department Listing'!$A$1:$A$395),IFERROR(_xlfn.XLOOKUP(O98,'Name Aliases'!$A$2:$A$1000,'Name Aliases'!$B$2:$B$1000),"")) -> 71 | Q98: =IF(ISBLANK($C98),"",$B98) -> 46232 | R98: =IF(ISBLANK($C98),"",IF(ISBLANK($I98),$D98,$I98)) -> Sweeney's | S98: =IF(ISBLANK($C98),"",$F98 - $G98) -> 16.91 | T98: =IF(ISBLANK($C98),"",C98) -> TST*SWEENEYS MASTERCARD-XXXXXXXY71GE-Ben Savage | U98: =IF(ISBLANK($C98),"",$D$1) -> Brex Credit Card | V98: =IF(ISBLANK($B98),"",IF(ISBLANK($K98),IF(_xlfn.XLOOKUP($W98,'Category Mapping'!$C:$C,'Category Mapping'!$B:$B)="Travel",_xlfn.XLOOKUP($P98,'Department Listing'!$A:$A,'Department Listing'!$M:$M),_xlfn.XLOOKUP($W98,'Category Mapping'!$C:$C,'Category Mapping'!$D:$D)),$K98)) -> Cost of Goods Sold:COGS- Travel Expenses: | W98: =IF(ISBLANK($B98),"",IF(ISBLANK($L98),RIGHT($E98,LEN($E98) - FIND("^",SUBSTITUTE($E98,":","^",LEN($E98) - LEN(SUBSTITUTE($E98,":",""))))),$L98)) -> Meals & Entertainment | X98: =IF(ISBLANK($J98),$V98&$W98,$J98) -> Cost of Goods Sold:COGS- Travel Expenses:Meals & Entertainment | Y98: =IF(ISBLANK($M98),IFERROR(_xlfn.XLOOKUP($P98,'Department Listing'!$A:$A,'Department Listing'!$L:$L),""),$M98) -> 300- ServiceNow:320- Engineering | Z98: =IF(ISBLANK($B98),"",MATCH($X98,COA!$B:$B,0)) -> 126
B99: 46232 | C99: Grill 23 Bar MASTERCARD-XXXXXXQEBO44-Ryan Henrich | F99: 627.51 | I99: Food Vendor | L99: Meals & Entertainment | O99: =IF(C99="", "", TRIM(RIGHT(C99, LEN(C99) - FIND("@@", SUBSTITUTE(C99, "-", "@@", LEN(C99) - LEN(SUBSTITUTE(C99, "-", ""))))))) -> Ryan Henrich | P99: =IFERROR(_xlfn.XLOOKUP(O99,'Department Listing'!$O$1:$O$395,'Department Listing'!$A$1:$A$395),IFERROR(_xlfn.XLOOKUP(O99,'Name Aliases'!$A$2:$A$1000,'Name Aliases'!$B$2:$B$1000),"")) -> 154 | Q99: =IF(ISBLANK($C99),"",$B99) -> 46232 | R99: =IF(ISBLANK($C99),"",IF(ISBLANK($I99),$D99,$I99)) -> Food Vendor | S99: =IF(ISBLANK($C99),"",$F99 - $G99) -> 627.51 | T99: =IF(ISBLANK($C99),"",C99) -> Grill 23 Bar MASTERCARD-XXXXXXQEBO44-Ryan Henrich | U99: =IF(ISBLANK($C99),"",$D$1) -> Brex Credit Card | V99: =IF(ISBLANK($B99),"",IF(ISBLANK($K99),IF(_xlfn.XLOOKUP($W99,'Category Mapping'!$C:$C,'Category Mapping'!$B:$B)="Travel",_xlfn.XLOOKUP($P99,'Department Listing'!$A:$A,'Department Listing'!$M:$M),_xlfn.XLOOKUP($W99,'Category Mapping'!$C:$C,'Category Mapping'!$D:$D)),$K99)) -> Sales & Marketing:Sales & Marketing- Travel Expenses: | W99: =IF(ISBLANK($B99),"",IF(ISBLANK($L99),RIGHT($E99,LEN($E99) - FIND("^",SUBSTITUTE($E99,":","^",LEN($E99) - LEN(SUBSTITUTE($E99,":",""))))),$L99)) -> Meals & Entertainment | X99: =IF(ISBLANK($J99),$V99&$W99,$J99) -> Sales & Marketing:Sales & Marketing- Travel Expenses:Meals & Entertainment | Y99: =IF(ISBLANK($M99),IFERROR(_xlfn.XLOOKUP($P99,'Department Listing'!$A:$A,'Department Listing'!$L:$L),""),$M99) -> 200- Datadog:230- Sales | Z99: =IF(ISBLANK($B99),"",MATCH($X99,COA!$B:$B,0)) -> 202
B100: 46233 | C100: PIER 4 GARAGE MASTERCARD-XXXXXX7MPX0L-Ashley Karpel | E100: General & Administrative:Office Expenses:Rent & Lease | F100: 27 | I100: Pier 4 | L100: Ground Transportation | O100: =IF(C100="", "", TRIM(RIGHT(C100, LEN(C100) - FIND("@@", SUBSTITUTE(C100, "-", "@@", LEN(C100) - LEN(SUBSTITUTE(C100, "-", ""))))))) -> Ashley Karpel | P100: =IFERROR(_xlfn.XLOOKUP(O100,'Department Listing'!$O$1:$O$395,'Department Listing'!$A$1:$A$395),IFERROR(_xlfn.XLOOKUP(O100,'Name Aliases'!$A$2:$A$1000,'Name Aliases'!$B$2:$B$1000),"")) -> 42 | Q100: =IF(ISBLANK($C100),"",$B100) -> 46233 | R100: =IF(ISBLANK($C100),"",IF(ISBLANK($I100),$D100,$I100)) -> Pier 4 | S100: =IF(ISBLANK($C100),"",$F100 - $G100) -> 27 | T100: =IF(ISBLANK($C100),"",C100) -> PIER 4 GARAGE MASTERCARD-XXXXXX7MPX0L-Ashley Karpel | U100: =IF(ISBLANK($C100),"",$D$1) -> Brex Credit Card | V100: =IF(ISBLANK($B100),"",IF(ISBLANK($K100),IF(_xlfn.XLOOKUP($W100,'Category Mapping'!$C:$C,'Category Mapping'!$B:$B)="Travel",_xlfn.XLOOKUP($P100,'Department Listing'!$A:$A,'Department Listing'!$M:$M),_xlfn.XLOOKUP($W100,'Category Mapping'!$C:$C,'Category Mapping'!$D:$D)),$K100)) -> Sales & Marketing:Sales & Marketing- Travel Expenses: | W100: =IF(ISBLANK($B100),"",IF(ISBLANK($L100),RIGHT($E100,LEN($E100) - FIND("^",SUBSTITUTE($E100,":","^",LEN($E100) - LEN(SUBSTITUTE($E100,":",""))))),$L100)) -> Ground Transportation | X100: =IF(ISBLANK($J100),$V100&$W100,$J100) -> Sales & Marketing:Sales & Marketing- Travel Expenses:Ground Transportation | Y100: =IF(ISBLANK($M100),IFERROR(_xlfn.XLOOKUP($P100,'Department Listing'!$A:$A,'Department Listing'!$L:$L),""),$M100) -> 300- ServiceNow:330- Sales | Z100: =IF(ISBLANK($B100),"",MATCH($X100,COA!$B:$B,0)) -> 200
B101: 46232 | C101: UBER *TRIP MASTERCARD-XXXXXXO5XP55-Robert Kolosky | E101: Sales & Marketing:Sales & Marketing- Travel Expenses:Ground Transportation | F101: 29.97 | I101: Uber | L101: Ground Transportation | O101: =IF(C101="", "", TRIM(RIGHT(C101, LEN(C101) - FIND("@@", SUBSTITUTE(C101, "-", "@@", LEN(C101) - LEN(SUBSTITUTE(C101, "-", ""))))))) -> Robert Kolosky | P101: =IFERROR(_xlfn.XLOOKUP(O101,'Department Listing'!$O$1:$O$395,'Department Listing'!$A$1:$A$395),IFERROR(_xlfn.XLOOKUP(O101,'Name Aliases'!$A$2:$A$1000,'Name Aliases'!$B$2:$B$1000),"")) -> 91 | Q101: =IF(ISBLANK($C101),"",$B101) -> 46232 | R101: =IF(ISBLANK($C101),"",IF(ISBLANK($I101),$D101,$I101)) -> Uber | S101: =IF(ISBLANK($C101),"",$F101 - $G101) -> 29.97 | T101: =IF(ISBLANK($C101),"",C101) -> UBER *TRIP MASTERCARD-XXXXXXO5XP55-Robert Kolosky | U101: =IF(ISBLANK($C101),"",$D$1) -> Brex Credit Card | V101: =IF(ISBLANK($B101),"",IF(ISBLANK($K101),IF(_xlfn.XLOOKUP($W101,'Category Mapping'!$C:$C,'Category Mapping'!$B:$B)="Travel",_xlfn.XLOOKUP($P101,'Department Listing'!$A:$A,'Department Listing'!$M:$M),_xlfn.XLOOKUP($W101,'Category Mapping'!$C:$C,'Category Mapping'!$D:$D)),$K101)) -> Cost of Goods Sold:COGS- Travel Expenses: | W101: =IF(ISBLANK($B101),"",IF(ISBLANK($L101),RIGHT($E101,LEN($E101) - FIND("^",SUBSTITUTE($E101,":","^",LEN($E101) - LEN(SUBSTITUTE($E101,":",""))))),$L101)) -> Ground Transportation | X101: =IF(ISBLANK($J101),$V101&$W101,$J101) -> Cost of Goods Sold:COGS- Travel Expenses:Ground Transportation | Y101: =IF(ISBLANK($M101),IFERROR(_xlfn.XLOOKUP($P101,'Department Listing'!$A:$A,'Department Listing'!$L:$L),""),$M101) -> 300- ServiceNow:320- Engineering | Z101: =IF(ISBLANK($B101),"",MATCH($X101,COA!$B:$B,0)) -> 124
B102: 46232 | C102: THE WILDDUCK MARKET PL MASTERCARD-XXXXXXGGM8ZB-Robert Kolosky | F102: 36.9 | I102: Food Vendor | L102: Meals & Entertainment | O102: =IF(C102="", "", TRIM(RIGHT(C102, LEN(C102) - FIND("@@", SUBSTITUTE(C102, "-", "@@", LEN(C102) - LEN(SUBSTITUTE(C102, "-", ""))))))) -> Robert Kolosky | P102: =IFERROR(_xlfn.XLOOKUP(O102,'Department Listing'!$O$1:$O$395,'Department Listing'!$A$1:$A$395),IFERROR(_xlfn.XLOOKUP(O102,'Name Aliases'!$A$2:$A$1000,'Name Aliases'!$B$2:$B$1000),"")) -> 91 | Q102: =IF(ISBLANK($C102),"",$B102) -> 46232 | R102: =IF(ISBLANK($C102),"",IF(ISBLANK($I102),$D102,$I102)) -> Food Vendor | S102: =IF(ISBLANK($C102),"",$F102 - $G102) -> 36.9 | T102: =IF(ISBLANK($C102),"",C102) -> THE WILDDUCK MARKET PL MASTERCARD-XXXXXXGGM8ZB-Robert Kolosky | U102: =IF(ISBLANK($C102),"",$D$1) -> Brex Credit Card | V102: =IF(ISBLANK($B102),"",IF(ISBLANK($K102),IF(_xlfn.XLOOKUP($W102,'Category Mapping'!$C:$C,'Category Mapping'!$B:$B)="Travel",_xlfn.XLOOKUP($P102,'Department Listing'!$A:$A,'Department Listing'!$M:$M),_xlfn.XLOOKUP($W102,'Category Mapping'!$C:$C,'Category Mapping'!$D:$D)),$K102)) -> Cost of Goods Sold:COGS- Travel Expenses: | W102: =IF(ISBLANK($B102),"",IF(ISBLANK($L102),RIGHT($E102,LEN($E102) - FIND("^",SUBSTITUTE($E102,":","^",LEN($E102) - LEN(SUBSTITUTE($E102,":",""))))),$L102)) -> Meals & Entertainment | X102: =IF(ISBLANK($J102),$V102&$W102,$J102) -> Cost of Goods Sold:COGS- Travel Expenses:Meals & Entertainment | Y102: =IF(ISBLANK($M102),IFERROR(_xlfn.XLOOKUP($P102,'Department Listing'!$A:$A,'Department Listing'!$L:$L),""),$M102) -> 300- ServiceNow:320- Engineering | Z102: =IF(ISBLANK($B102),"",MATCH($X102,COA!$B:$B,0)) -> 126
B103: 46232 | C103: One Seaport Garage MASTERCARD-XXXXXXH1JO6G-Kevin Ebert | F103: 44 | I103: Travel Vendor | L103: Other Travel Expenses | O103: =IF(C103="", "", TRIM(RIGHT(C103, LEN(C103) - FIND("@@", SUBSTITUTE(C103, "-", "@@", LEN(C103) - LEN(SUBSTITUTE(C103, "-", ""))))))) -> Kevin Ebert | P103: =IFERROR(_xlfn.XLOOKUP(O103,'Department Listing'!$O$1:$O$395,'Department Listing'!$A$1:$A$395),IFERROR(_xlfn.XLOOKUP(O103,'Name Aliases'!$A$2:$A$1000,'Name Aliases'!$B$2:$B$1000),"")) -> 187 | Q103: =IF(ISBLANK($C103),"",$B103) -> 46232 | R103: =IF(ISBLANK($C103),"",IF(ISBLANK($I103),$D103,$I103)) -> Travel Vendor | S103: =IF(ISBLANK($C103),"",$F103 - $G103) -> 44 | T103: =IF(ISBLANK($C103),"",C103) -> One Seaport Garage MASTERCARD-XXXXXXH1JO6G-Kevin Ebert | U103: =IF(ISBLANK($C103),"",$D$1) -> Brex Credit Card | V103: =IF(ISBLANK($B103),"",IF(ISBLANK($K103),IF(_xlfn.XLOOKUP($W103,'Category Mapping'!$C:$C,'Category Mapping'!$B:$B)="Travel",_xlfn.XLOOKUP($P103,'Department Listing'!$A:$A,'Department Listing'!$M:$M),_xlfn.XLOOKUP($W103,'Category Mapping'!$C:$C,'Category Mapping'!$D:$D)),$K103)) -> General & Administrative:G&A- Travel Expenses: | W103: =IF(ISBLANK($B103),"",IF(ISBLANK($L103),RIGHT($E103,LEN($E103) - FIND("^",SUBSTITUTE($E103,":","^",LEN($E103) - LEN(SUBSTITUTE($E103,":",""))))),$L103)) -> Other Travel Expenses | X103: =IF(ISBLANK($J103),$V103&$W103,$J103) -> General & Administrative:G&A- Travel Expenses:Other Travel Expenses | Y103: =IF(ISBLANK($M103),IFERROR(_xlfn.XLOOKUP($P103,'Department Listing'!$A:$A,'Department Listing'!$L:$L),""),$M103) -> 100- Operations:110- G&A | Z103: =IF(ISBLANK($B103),"",MATCH($X103,COA!$B:$B,0)) -> 152
B104: 46232 | C104: THE WILDDUCK MARKET PL MASTERCARD-XXXXXX1E5E3G-Jon Giara | F104: 19.95 | I104: Food Vendor | L104: Meals & Entertainment | O104: =IF(C104="", "", TRIM(RIGHT(C104, LEN(C104) - FIND("@@", SUBSTITUTE(C104, "-", "@@", LEN(C104) - LEN(SUBSTITUTE(C104, "-", ""))))))) -> Jon Giara | P104: =IFERROR(_xlfn.XLOOKUP(O104,'Department Listing'!$O$1:$O$395,'Department Listing'!$A$1:$A$395),IFERROR(_xlfn.XLOOKUP(O104,'Name Aliases'!$A$2:$A$1000,'Name Aliases'!$B$2:$B$1000),"")) -> 2 | Q104: =IF(ISBLANK($C104),"",$B104) -> 46232 | R104: =IF(ISBLANK($C104),"",IF(ISBLANK($I104),$D104,$I104)) -> Food Vendor | S104: =IF(ISBLANK($C104),"",$F104 - $G104) -> 19.95 | T104: =IF(ISBLANK($C104),"",C104) -> THE WILDDUCK MARKET PL MASTERCARD-XXXXXX1E5E3G-Jon Giara | U104: =IF(ISBLANK($C104),"",$D$1) -> Brex Credit Card | V104: =IF(ISBLANK($B104),"",IF(ISBLANK($K104),IF(_xlfn.XLOOKUP($W104,'Category Mapping'!$C:$C,'Category Mapping'!$B:$B)="Travel",_xlfn.XLOOKUP($P104,'Department Listing'!$A:$A,'Department Listing'!$M:$M),_xlfn.XLOOKUP($W104,'Category Mapping'!$C:$C,'Category Mapping'!$D:$D)),$K104)) -> Cost of Goods Sold:COGS- Travel Expenses: | W104: =IF(ISBLANK($B104),"",IF(ISBLANK($L104),RIGHT($E104,LEN($E104) - FIND("^",SUBSTITUTE($E104,":","^",LEN($E104) - LEN(SUBSTITUTE($E104,":",""))))),$L104)) -> Meals & Entertainment | X104: =IF(ISBLANK($J104),$V104&$W104,$J104) -> Cost of Goods Sold:COGS- Travel Expenses:Meals & Entertainment | Y104: =IF(ISBLANK($M104),IFERROR(_xlfn.XLOOKUP($P104,'Department Listing'!$A:$A,'Department Listing'!$L:$L),""),$M104) -> 300- ServiceNow:320- Engineering | Z104: =IF(ISBLANK($B104),"",MATCH($X104,COA!$B:$B,0)) -> 126
B105: 46232 | C105: UBER *TRIP MASTERCARD-XXXXXXRGUIDP-Robert Kolosky | E105: Sales & Marketing:Sales & Marketing- Travel Expenses:Ground Transportation | F105: 28.96 | I105: Uber | L105: Ground Transportation | O105: =IF(C105="", "", TRIM(RIGHT(C105, LEN(C105) - FIND("@@", SUBSTITUTE(C105, "-", "@@", LEN(C105) - LEN(SUBSTITUTE(C105, "-", ""))))))) -> Robert Kolosky | P105: =IFERROR(_xlfn.XLOOKUP(O105,'Department Listing'!$O$1:$O$395,'Department Listing'!$A$1:$A$395),IFERROR(_xlfn.XLOOKUP(O105,'Name Aliases'!$A$2:$A$1000,'Name Aliases'!$B$2:$B$1000),"")) -> 91 | Q105: =IF(ISBLANK($C105),"",$B105) -> 46232 | R105: =IF(ISBLANK($C105),"",IF(ISBLANK($I105),$D105,$I105)) -> Uber | S105: =IF(ISBLANK($C105),"",$F105 - $G105) -> 28.96 | T105: =IF(ISBLANK($C105),"",C105) -> UBER *TRIP MASTERCARD-XXXXXXRGUIDP-Robert Kolosky | U105: =IF(ISBLANK($C105),"",$D$1) -> Brex Credit Card | V105: =IF(ISBLANK($B105),"",IF(ISBLANK($K105),IF(_xlfn.XLOOKUP($W105,'Category Mapping'!$C:$C,'Category Mapping'!$B:$B)="Travel",_xlfn.XLOOKUP($P105,'Department Listing'!$A:$A,'Department Listing'!$M:$M),_xlfn.XLOOKUP($W105,'Category Mapping'!$C:$C,'Category Mapping'!$D:$D)),$K105)) -> Cost of Goods Sold:COGS- Travel Expenses: | W105: =IF(ISBLANK($B105),"",IF(ISBLANK($L105),RIGHT($E105,LEN($E105) - FIND("^",SUBSTITUTE($E105,":","^",LEN($E105) - LEN(SUBSTITUTE($E105,":",""))))),$L105)) -> Ground Transportation | X105: =IF(ISBLANK($J105),$V105&$W105,$J105) -> Cost of Goods Sold:COGS- Travel Expenses:Ground Transportation | Y105: =IF(ISBLANK($M105),IFERROR(_xlfn.XLOOKUP($P105,'Department Listing'!$A:$A,'Department Listing'!$L:$L),""),$M105) -> 300- ServiceNow:320- Engineering | Z105: =IF(ISBLANK($B105),"",MATCH($X105,COA!$B:$B,0)) -> 124
...

Sheet Card Mapping
B2: Card Number (last 4 Digits) | C2: Card Name | D2: Department | E2: EE ID | H2: Amex Accounts
B3: 2011 | C3: Matt Keyes | D3: 200- Datadog:230- Sales | E3: 104 | H3: Amex Plat 2 *51005
B4: 2219 | C4: Toni Manning | D4: 100- Operations:120- Marketing | E4: 121 | H4: Amex Plat *12006
B5: 3159 | C5: John Taylor | D5: 300- ServiceNow:330- Sales | E5: 118 | H5: Amex Centurion *01008
H6: Brex Credit Card
B7: 2193 | C7: Jacob McKenna | D7: 300- ServiceNow:320- Engineering | E7: 120 | H7: Amex Delta *13003
B8: 1302 | C8: Andrew Bissel | D8: 200- Datadog:220- Engineering | E8: 135
B9: 2110 | C9: Chris Breiner | D9: 200- Datadog:230- Sales | E9: 115
B10: 2094 | C10: Jon Lawer | D10: 300- ServiceNow:330- Sales | E10: 113
B11: 2243 | C11: Scott Lane | D11: 300- ServiceNow:330- Sales | E11: 132
B12: 2169 | C12: R Faria De Oliveira | D12: 200- Datadog:220- Engineering | E12: 125
B13: 2086 | C13: Richard Upshall | D13: 200- Datadog:230- Sales | E13: 112
B14: 2201 | C14: Eric Ledyard | D14: 100- Operations:110- G&A | E14: 123
B15: 2006 | C15: Tameem Hourani | D15: 100- Operations:110- G&A | E15: 1
B16: 1933 | C16: Nikita Ashok | D16: 100- Operations:120- Marketing | E16: 111
B17: 3418 | C17: Alta Abel | D17: 100- Operations:110- G&A | E17: 69
B18: 2675 | C18: Chloe Brant | D18: 300- ServiceNow:330- Sales | E18: 77
B19: 2170 | C19: Josh Van Harn | D19: 300- ServiceNow:330- Sales | E19: 23
... B125: 1799 | C125: Jacob Woolf | D125: 300- ServiceNow:320- Engineering | E125: 194
B126: 1823 | C126: Teresa Bobst | E126: 188
B127: 1856 | C127: Tim Lee | E127: 213
B128: 2813 | C128: Ona Kolosky | D128: 300- ServiceNow:320- Engineering | E128: 198
B129: 1864 | C129: Timothy Lau | D129: 200- Datadog:220- Engineering | E129: 210
B130: 1872 | C130: Sakshi Sasalate | D130: 300- ServiceNow:320- Engineering | E130: 209
B131: 1724 | C131: Sarah Dwyer | D131: 200- Datadog:210- Delivery | E131: 183
B132: 0151 | C132: Eric Rabkin | D132: 100- Operations:110- G&A | E132: 246
C133: Kyle Bense | D133: 300- ServiceNow:320- Engineering | E133: 252
C134: James O'Shaughnessy | D134: 300- ServiceNow:310- Delivery | E134: 239
C135: Cody Sanderford | D135: 300- ServiceNow:320- Engineering | E135: 245
C136: Harry Tomczyk | D136: 300- ServiceNow:330- Sales | E136: 251

Sheet Category Mapping
B3: Account Type | C3: Sub Account | D3: Parent Category
B4: Travel | C4: Airfare
B5: G&A | C5: Contractors | D5: General & Administrative:
B6: G&A | C6: Dues & Subscriptions | D6: General & Administrative:Office Expenses:
B7: Travel | C7: Ground Transportation
B8: G&A | C8: Hardware & Peripherals | D8: General & Administrative:Office Expenses:
B9: Travel | C9: Lodging
B10: Travel | C10: Meals & Entertainment
B11: G&A | C11: Office Supplies | D11: General & Administrative:Office Expenses:
B12: S&M | C12: Other Marketing Expenses | D12: Sales & Marketing:Marketing Expenses:
B13: Travel | C13: Other Travel Expenses
B14: G&A | C14: Shipping Expense | D14: General & Administrative:Office Expenses:
B15: G&A | C15: Software Licenses | D15: General & Administrative:
B16: G&A | C16: Misc. Taxes & Licenses | D16: General & Administrative:
B17: G&A | C17: Utilities | D17: General & Administrative:Office Expenses:
B18: G&A | C18: Communication Expense | D18: General & Administrative:Office Expenses:
B19: G&A | C19: Charitable Contribution | D19: General & Administrative:
B20: G&A | C20: General & Administrative:Office Expenses:Rent & Lease | D20: General & Administrative:

Sheet COA
B1: All QBO Accounts
B2: 45904
B4: BOA Checking 4855
B5: Brex Checking
B6: Cash
B7: Checking (Citizens)
B8: Northern Bank Checking 3097
B9: Accounts Receivable
B10: Accounts Receivable (A/R)
B11: Accounts Receivable (A/R) - CAD
B12: Accounts Receivable (A/R) - EUR
B13: Accounts Receivable (A/R) - GBP
B14: Asset Clearing
B15: Credit Card Receivables (deleted)
... B223: Other Expenses:Reconciliation Discrepancies

Sheet Instructions
B2: Purpose: Import Amex transactions with accurate department, account and description into QuickBooks Online
B4: Instructions
B5: 1. Duplicate File and ensure file name has today's date and the Amex account being entered
B6: 2. Review credit card transactions in QuickBooks, and manually enter credit card credits using "Card Mapping" tab as a reference. Ensure Vendor Name, Account, Department fields are populated and you add " - " & the Employee name to the end of the Memo field
B7: 3. CTRL+H Find and Replace "-" for " - "
B8: 4. Sort the transactions in QuickBooks based on Date
B9: 5. Export transactions from QuickBooks
B10: 6. Copy exported transactions, paste values in cells B-F of the "QBO Transactions" tab
B11: 7. Review Columns K-F of "QBO transactions" to ensure all cells are populated.
B12: 8. Ensure Column Q of "QBO Transactions" is showing the correct card account. Update in Cell D1 if incorrect
B13: 9. Filter Column R, Line Acct by each individual account to ensure transactions are coded accurately
B14: 10. Ensure transactions on "Credit Card Charge" tab, the transaction importer, match what's on "QBO Transactions" tab (transaction count and amount match)

Sheet Name Aliases
A1: Brex Name | B1: EE ID | C1: BambooHR Name | D1: Confirmed | E1: Note
A2: Zayn Moselhy | B2: 184 | C2: Zaynaldine Moselhy | D2: 2026-07-16 | E2: Preferred first name vs BambooHR legal name; confirmed by Zayn
A3: Michael Christinsen | B3: 58 | C3: Michael Christensen | D3: 2026-07-16 | E3: Spelling variant (Christinsen vs Christensen); confirmed by Zayn
A4: Jeff Mu | B4: 4 | C4: Jeffrey Mu | D4: 2026-07-30 | E4: Preferred first name vs BambooHR legal name; confirmed by Zayn
A5: Jon Giara | B5: 2 | C5: Jonathan Giara | D5: 2026-07-30 | E5: Preferred first name vs BambooHR legal name; confirmed by Zayn
A6: Talon Walz | B6: 260 | C6: Talon Walz | D6: 2026-07-30 | E6: BambooHR double/trailing-space name variant; confirmed by Zayn
A7: Anamaria Gramada | B7: 110 | C7: Ana Grămadă | D7: 2026-07-30 | E7: Diacritic name variant (Ana Grămadă); confirmed by Zayn

Sheet Department Listing
A1: Employee # | B1: First Name | C1: Last Name | D1: Last name, First name | E1: Hire Date | F1: Employment Status | G1: Employment Status: Date | H1: Division | I1: Department | J1: Location | K1: Billable Status | L1: QBO Department | M1: Prefix- Travel | N1: Prefix- Payroll
A2: 1 | B2: Tameem | C2: Hourani | D2: Hourani, Tameem | E2: 43651 | F2: Full-Time | G2: 2025-08-15 | H2: Operations | I2: Operations | J2: Boylston | K2: No | L2: 400- Synechron:410- Digital platforms G&A | M2: General & Administrative:G&A- Travel Expenses: | N2: General & Administrative:G&A- Personnel Expenses: | O2: =B2&" "&C2 -> Tameem Hourani
A3: 2 | B3: Jon | C3: Giara | D3: Giara, Jon | E3: 43647 | F3: Full-Time | G3: 2019-11-04 | H3: ServiceNow | I3: Engineering | J3: Remote | K3: Yes | L3: 300- ServiceNow:320- Engineering | M3: Cost of Goods Sold:COGS- Travel Expenses: | N3: Cost of Goods Sold:COGS- Personnel Expense: | O3: =B3&" "&C3 -> Jon Giara
A4: 3 | B4: Connor | C4: Brackett | D4: Brackett, Connor | E4: 43773 | F4: Full-Time | G4: 2019-11-04 | H4: ServiceNow | I4: Sales | J4: Boylston | K4: No | L4: 300- ServiceNow:330- Sales | M4: Sales & Marketing:Sales & Marketing- Travel Expenses: | N4: Sales & Marketing:Sales & Marketing- Personnel Expenses: | O4: =B4&" "&C4 -> Connor Brackett
A5: 4 | B5: Jeff | C5: Mu | D5: Mu, Jeff | E5: 43754 | F5: Full-Time | G5: 2019-10-16 | H5: ServiceNow | I5: Engineering | J5: Boylston | K5: Yes | L5: 300- ServiceNow:320- Engineering | M5: Cost of Goods Sold:COGS- Travel Expenses: | N5: Cost of Goods Sold:COGS- Personnel Expense: | O5: =B5&" "&C5 -> Jeff Mu
A6: 5 | B6: James | C6: Craveiro | D6: Craveiro, James | E6: 43871 | F6: Terminated | G6: 2022-10-01 | H6: Datadog | J6: Remote | L6: 200- Datadog:220- Engineering | M6: Cost of Goods Sold:COGS- Travel Expenses: | N6: Cost of Goods Sold:COGS- Personnel Expense: | O6: =B6&" "&C6 -> James Craveiro
A7: 6 | B7: Kristopher | C7: Borodiansky | D7: Borodiansky, Kristopher | E7: 43857 | F7: Terminated | G7: 2020-02-25 | H7: Datadog | J7: Remote | L7: 200- Datadog:220- Engineering | M7: Cost of Goods Sold:COGS- Travel Expenses: | N7: Cost of Goods Sold:COGS- Personnel Expense: | O7: =B7&" "&C7 -> Kristopher Borodiansky
A8: 7 | B8: Erik | C8: Williams | D8: Williams, Erik | E8: 43885 | F8: Full-Time | G8: 2020-02-24 | H8: Operations | I8: Strategy | J8: Remote | K8: Yes | L8: 400- Synechron:410- Digital platforms G&A | M8: Cost of Goods Sold:COGS- Travel Expenses: | N8: Cost of Goods Sold:COGS- Personnel Expense: | O8: =B8&" "&C8 -> Erik Williams
A9: 8 | B9: Logan | C9: Rohloff | D9: Rohloff, Logan | E9: 43906 | F9: Full-Time | G9: 2020-03-16 | H9: Datadog | I9: Sales | J9: Boylston | K9: No | L9: 200- Datadog:220- Engineering | M9: Cost of Goods Sold:COGS- Travel Expenses: | N9: Cost of Goods Sold:COGS- Personnel Expense: | O9: =B9&" "&C9 -> Logan Rohloff
A10: 9 | B10: Reese | C10: Boisse | D10: Boisse, Reese | E10: 43927 | F10: Full-Time | G10: 2020-04-06 | H10: ServiceNow | I10: Sales | J10: Boylston | K10: No | L10: 300- ServiceNow:330- Sales | M10: Sales & Marketing:Sales & Marketing- Travel Expenses: | N10: Sales & Marketing:Sales & Marketing- Personnel Expenses: | O10: =B10&" "&C10 -> Reese Boisse
A11: 10 | B11: Reuben | C11: Stump | D11: Stump, Reuben | E11: 43985 | F11: Full-Time | G11: 2020-06-03 | H11: Datadog | I11: Engineering | J11: Remote | K11: Yes | L11: 200- Datadog:220- Engineering | M11: Cost of Goods Sold:COGS- Travel Expenses: | N11: Cost of Goods Sold:COGS- Personnel Expense: | O11: =B11&" "&C11 -> Reuben Stump
A12: 11 | B12: Victoria | C12: Quinn | D12: Quinn, Victoria | E12: 43990 | F12: Terminated | G12: 2023-03-18 | H12: Operations | J12: Remote | L12: 100- Operations:110- G&A | M12: General & Administrative:G&A- Travel Expenses: | N12: General & Administrative:G&A- Personnel Expenses: | O12: =B12&" "&C12 -> Victoria Quinn
A13: 12 | B13: Elias | C13: Kapetanopoulos | D13: Kapetanopoulos, Elias | E13: 44060 | F13: Full-Time | G13: 2020-08-17 | H13: ServiceNow | I13: Engineering | J13: Boylston | K13: No | L13: 300- ServiceNow:320- Engineering | M13: General & Administrative:G&A- Travel Expenses: | N13: Sales & Marketing:Sales & Marketing- Personnel Expenses: | O13: =B13&" "&C13 -> Elias Kapetanopoulos
A14: 13 | B14: Adnan | C14: Usman | D14: Usman, Adnan | E14: 44060 | F14: Terminated | G14: 2022-04-23 | H14: ServiceNow | J14: Remote | L14: 300- ServiceNow:330- Sales | M14: Sales & Marketing:Sales & Marketing- Travel Expenses: | N14: Sales & Marketing:Sales & Marketing- Personnel Expenses: | O14: =B14&" "&C14 -> Adnan Usman
A15: 14 | B15: Christian | C15: Moua | D15: Moua, Christian | E15: 44088 | F15: Full-Time | G15: 2020-09-14 | H15: ServiceNow | I15: Engineering | J15: Boylston | K15: Yes | L15: 300- ServiceNow:320- Engineering | M15: Cost of Goods Sold:COGS- Travel Expenses: | N15: Cost of Goods Sold:COGS- Personnel Expense: | O15: =B15&" "&C15 -> Christian Moua
A16: 15 | B16: Jesse | C16: Eddy | D16: Eddy, Jesse | E16: 44102 | F16: Full-Time | G16: 2020-09-28 | H16: Datadog | I16: Sales | J16: Boylston | K16: No | L16: 200- Datadog:230- Sales | M16: Sales & Marketing:Sales & Marketing- Travel Expenses: | N16: General & Administrative:G&A- Personnel Expenses: | O16: =B16&" "&C16 -> Jesse Eddy
A17: 16 | B17: Maxime | C17: Berube | D17: Berube, Maxime | E17: 44102 | F17: Terminated | G17: 2021-01-30 | H17: Datadog | J17: Boylston | L17: 200- Datadog:220- Engineering | M17: Cost of Goods Sold:COGS- Travel Expenses: | N17: Cost of Goods Sold:COGS- Personnel Expense: | O17: =B17&" "&C17 -> Maxime Berube
A18: 17 | B18: Michael | C18: Thornton | D18: Thornton, Michael | E18: 44144 | F18: Terminated | G18: 2021-10-16 | H18: ServiceNow | J18: Boylston | L18: 300- ServiceNow:320- Engineering | M18: Cost of Goods Sold:COGS- Travel Expenses: | N18: Cost of Goods Sold:COGS- Personnel Expense: | O18: =B18&" "&C18 -> Michael Thornton
A19: 18 | B19: Tomas | C19: Cespedes | D19: Cespedes, Tomas | E19: 44151 | F19: Full-Time | G19: 2020-11-16 | H19: Datadog | I19: Sales | J19: Boylston | K19: No | L19: 200- Datadog:230- Sales | M19: Sales & Marketing:Sales & Marketing- Travel Expenses: | N19: General & Administrative:G&A- Personnel Expenses: | O19: =B19&" "&C19 -> Tomas Cespedes
A20: 19 | B20: Colin | C20: Galanaugh | D20: Galanaugh, Colin | E20: 44228 | F20: Full-Time | G20: 2021-02-01 | H20: Datadog | I20: Sales | J20: Boylston | K20: No | L20: 200- Datadog:230- Sales | M20: Sales & Marketing:Sales & Marketing- Travel Expenses: | N20: General & Administrative:G&A- Personnel Expenses: | O20: =B20&" "&C20 -> Colin Galanaugh
A21: 20 | B21: Charles | C21: Magnarelli | D21: Magnarelli, Charles | E21: 44228 | F21: Terminated | G21: 2021-02-27 | H21: Datadog | J21: Boylston | L21: 200- Datadog:220- Engineering | M21: Cost of Goods Sold:COGS- Travel Expenses: | N21: Cost of Goods Sold:COGS- Personnel Expense: | O21: =B21&" "&C21 -> Charles Magnarelli
A22: 21 | B22: Timothy | C22: Konick | D22: Konick, Timothy | E22: 44249 | F22: Terminated | G22: 2021-03-09 | H22: Datadog | J22: Boylston | L22: 200- Datadog:220- Engineering | M22: Cost of Goods Sold:COGS- Travel Expenses: | N22: Cost of Goods Sold:COGS- Personnel Expense: | O22: =B22&" "&C22 -> Timothy Konick
A23: 22 | B23: Dennis | C23: Wang | D23: Wang, Dennis | E23: 44284 | F23: Terminated | G23: 2021-06-26 | H23: Datadog | J23: Boylston | L23: 200- Datadog:220- Engineering | M23: Cost of Goods Sold:COGS- Travel Expenses: | N23: Cost of Goods Sold:COGS- Personnel Expense: | O23: =B23&" "&C23 -> Dennis Wang
A24: 23 | B24: Josh | C24: van Harn | D24: van Harn, Josh | E24: 44312 | F24: Terminated | G24: 2025-11-21 | H24: ServiceNow | J24: Remote | K24: No | L24: 300- ServiceNow:330- Sales | M24: Sales & Marketing:Sales & Marketing- Travel Expenses: | N24: Sales & Marketing:Sales & Marketing- Personnel Expenses: | O24: =B24&" "&C24 -> Josh van Harn
A25: 24 | B25: Matt | C25: Hyman | D25: Hyman, Matthew | E25: 44348 | F25: Full-Time | G25: 2021-06-01 | H25: ServiceNow | I25: Sales | J25: Remote | K25: No | L25: 300- ServiceNow:330- Sales | M25: Sales & Marketing:Sales & Marketing- Travel Expenses: | N25: Sales & Marketing:Sales & Marketing- Personnel Expenses: | O25: =B25&" "&C25 -> Matt Hyman
A26: 25 | B26: Mitchell | C26: Nethercott | D26: Nethercott, Mitchell | E26: 44361 | F26: Full-Time | G26: 2021-06-14 | H26: Datadog | I26: Engineering | J26: Boylston | K26: Yes | L26: 200- Datadog:220- Engineering | M26: Cost of Goods Sold:COGS- Travel Expenses: | N26: Cost of Goods Sold:COGS- Personnel Expense: | O26: =B26&" "&C26 -> Mitchell Nethercott
A27: 26 | B27: Mitchell | C27: Deaner | D27: Deaner, Mitchell | E27: 44383 | F27: Full-Time | G27: 2021-07-06 | H27: ServiceNow | I27: Engineering | J27: Non-US | K27: Yes | L27: 300- ServiceNow:320- Engineering | M27: Cost of Goods Sold:COGS- Travel Expenses: | N27: Cost of Goods Sold:COGS- Personnel Expense: | O27: =B27&" "&C27 -> Mitchell Deaner
A28: 27 | B28: Lyndsey | C28: Cohen | D28: Cohen, Lyndsey | E28: 44383 | F28: Full-Time | G28: 2021-07-06 | H28: ServiceNow | I28: Engineering | J28: Remote | K28: Yes | L28: 300- ServiceNow:320- Engineering | M28: Cost of Goods Sold:COGS- Travel Expenses: | N28: Cost of Goods Sold:COGS- Personnel Expense: | O28: =B28&" "&C28 -> Lyndsey Cohen
A29: 28 | B29: Dor | C29: Vaknin | D29: Vaknin, Dor | E29: 44383 | F29: Full-Time | G29: 2021-07-06 | H29: ServiceNow | I29: Engineering | J29: Boylston | K29: Yes | L29: 300- ServiceNow:320- Engineering | M29: Cost of Goods Sold:COGS- Travel Expenses: | N29: Cost of Goods Sold:COGS- Personnel Expense: | O29: =B29&" "&C29 -> Dor Vaknin
A30: 29 | B30: Caleb | C30: Cordes | D30: Cordes, Caleb | E30: 44410 | F30: Terminated | G30: 2024-09-12 | H30: ServiceNow | J30: Remote | K30: Yes | L30: 300- ServiceNow:320- Engineering | M30: Cost of Goods Sold:COGS- Travel Expenses: | N30: Cost of Goods Sold:COGS- Personnel Expense: | O30: =B30&" "&C30 -> Caleb Cordes
A31: 30 | B31: Brian | C31: Zhu | D31: Zhu, Brian | E31: 44410 | F31: Terminated | G31: 2023-04-22 | H31: Datadog | J31: Boylston | L31: 200- Datadog:210- Delivery | M31: Cost of Goods Sold:COGS- Travel Expenses: | N31: Cost of Goods Sold:COGS- Personnel Expense: | O31: =B31&" "&C31 -> Brian Zhu
A32: 31 | B32: Paul | C32: Kim | D32: Kim, Paul | E32: 44410 | F32: Full-Time | G32: 2021-08-02 | H32: Datadog | I32: Engineering | J32: Boylston | K32: Yes | L32: 200- Datadog:220- Engineering | M32: Cost of Goods Sold:COGS- Travel Expenses: | N32: Cost of Goods Sold:COGS- Personnel Expense: | O32: =B32&" "&C32 -> Paul Kim
A33: 32 | B33: Victoria | C33: Baldwin | D33: Baldwin, Victoria | E33: 44417 | F33: Terminated | G33: 2021-08-20 | H33: ServiceNow | J33: Remote | L33: 300- ServiceNow:310- Delivery | M33: Cost of Goods Sold:COGS- Travel Expenses: | N33: Cost of Goods Sold:COGS- Personnel Expense: | O33: =B33&" "&C33 -> Victoria Baldwin
A34: 33 | B34: Isabela | C34: Vazquez | D34: Vazquez, Isabela | E34: 44452 | F34: Terminated | G34: 2022-10-28 | H34: Operations | J34: Boylston | L34: 100- Operations:120- Marketing | M34: Sales & Marketing:Sales & Marketing- Travel Expenses: | N34: Sales & Marketing:Sales & Marketing- Personnel Expenses: | O34: =B34&" "&C34 -> Isabela Vazquez
A35: 34 | B35: Alexander | C35: Glenn | D35: Glenn, Alexander | E35: 44452 | F35: Full-Time | G35: 2021-09-13 | H35: Datadog | I35: Sales | J35: Boylston | K35: No | L35: 200- Datadog:220- Engineering | M35: Cost of Goods Sold:COGS- Travel Expenses: | N35: Cost of Goods Sold:COGS- Personnel Expense: | O35: =B35&" "&C35 -> Alexander Glenn
A36: 35 | B36: Trent | C36: Van Winkle | D36: Van Winkle, Trent | E36: 44445 | F36: Terminated | G36: 2022-02-05 | H36: ServiceNow | J36: Remote | L36: 300- ServiceNow:320- Engineering | M36: Cost of Goods Sold:COGS- Travel Expenses: | N36: Cost of Goods Sold:COGS- Personnel Expense: | O36: =B36&" "&C36 -> Trent Van Winkle
A37: 36 | B37: Panat | C37: Taranat | D37: Taranat, Panat | E37: 44452 | F37: Terminated | G37: 2022-01-14 | H37: Datadog | J37: Boylston | L37: 200- Datadog:220- Engineering | M37: Cost of Goods Sold:COGS- Travel Expenses: | N37: Cost of Goods Sold:COGS- Personnel Expense: | O37: =B37&" "&C37 -> Panat Taranat
A38: 37 | B38: Nadege | C38: Le Goff | D38: Le Goff, Nadege | E38: 44473 | F38: Full-Time | G38: 2021-10-04 | H38: ServiceNow | I38: Project Management | J38: Boylston | K38: Yes | L38: 300- ServiceNow:310- Delivery | M38: Cost of Goods Sold:COGS- Travel Expenses: | N38: Cost of Goods Sold:COGS- Personnel Expense: | O38: =B38&" "&C38 -> Nadege Le Goff
A39: 38 | B39: Nick | C39: Vecellio | D39: Vecellio, Nick | E39: 44480 | F39: Terminated | G39: 2023-11-03 | H39: Datadog | J39: Remote | K39: No | L39: 200- Datadog:230- Sales | M39: Sales & Marketing:Sales & Marketing- Travel Expenses: | N39: General & Administrative:G&A- Personnel Expenses: | O39: =B39&" "&C39 -> Nick Vecellio
A40: 39 | B40: Kyle | C40: Brueckner | D40: Brueckner, Kyle | E40: 44494 | F40: Full-Time | G40: 2021-10-25 | H40: ServiceNow | I40: Engineering | J40: Remote | K40: Yes | L40: 300- ServiceNow:320- Engineering | M40: Cost of Goods Sold:COGS- Travel Expenses: | N40: Cost of Goods Sold:COGS- Personnel Expense: | O40: =B40&" "&C40 -> Kyle Brueckner
A41: 40 | B41: Luke | C41: Scanlan | D41: Scanlan, Luke | E41: 44494 | F41: Terminated | G41: 2022-10-13 | H41: ServiceNow | J41: Boylston | L41: 300- ServiceNow:310- Delivery | M41: Cost of Goods Sold:COGS- Travel Expenses: | N41: Cost of Goods Sold:COGS- Personnel Expense: | O41: =B41&" "&C41 -> Luke Scanlan
A42: 41 | B42: Pallavi | C42: Gupta | D42: Gupta, Pallavi | E42: 44508 | F42: Terminated | G42: 2025-08-17 | H42: ServiceNow | J42: Remote | K42: Yes | L42: 300- ServiceNow:320- Engineering | M42: Cost of Goods Sold:COGS- Travel Expenses: | N42: Cost of Goods Sold:COGS- Personnel Expense: | O42: =B42&" "&C42 -> Pallavi Gupta
A43: 42 | B43: Ashley | C43: Karpel | D43: Karpel, Ashley | E43: 44536 | F43: Full-Time | G43: 2021-12-06 | H43: ServiceNow | I43: Sales | J43: Boylston | K43: No | L43: 300- ServiceNow:330- Sales | M43: Sales & Marketing:Sales & Marketing- Travel Expenses: | N43: Sales & Marketing:Sales & Marketing- Personnel Expenses: | O43: =B43&" "&C43 -> Ashley Karpel
A44: 43 | B44: Paul | C44: Dixon | D44: Dixon, Paul | E44: 44564 | F44: Terminated | G44: 2022-07-02 | H44: ServiceNow | J44: Remote | L44: 300- ServiceNow:330- Sales | M44: Sales & Marketing:Sales & Marketing- Travel Expenses: | N44: Sales & Marketing:Sales & Marketing- Personnel Expenses: | O44: =B44&" "&C44 -> Paul Dixon
A45: 44 | B45: James | C45: Lewis | D45: Lewis, James | E45: 44578 | F45: Terminated | G45: 2023-09-04 | H45: Operations | J45: Remote | K45: No | L45: 100- Operations:110- G&A | M45: General & Administrative:G&A- Travel Expenses: | N45: General & Administrative:G&A- Personnel Expenses: | O45: =B45&" "&C45 -> James Lewis
A46: 45 | B46: Andrew | C46: Sieg | D46: Sieg, Andrew | E46: 44579 | F46: Terminated | G46: 2022-03-04 | H46: Datadog | J46: Remote | L46: 200- Datadog:220- Engineering | M46: Cost of Goods Sold:COGS- Travel Expenses: | N46: Cost of Goods Sold:COGS- Personnel Expense: | O46: =B46&" "&C46 -> Andrew Sieg
A47: 46 | B47: Alexandra | C47: Hourani | D47: Hourani, Alexandra | E47: 44562 | F47: Terminated | G47: 2025-09-05 | H47: Operations | J47: Remote | L47: 100- Operations:110- G&A | M47: General & Administrative:G&A- Travel Expenses: | N47: General & Administrative:G&A- Personnel Expenses: | O47: =B47&" "&C47 -> Alexandra Hourani
A48: 47 | B48: Canaan | C48: Hourani | D48: Hourani, Canaan | E48: 44562 | F48: Terminated | G48: 2025-09-05 | H48: Operations | J48: Remote | L48: 100- Operations:110- G&A | M48: General & Administrative:G&A- Travel Expenses: | N48: General & Administrative:G&A- Personnel Expenses: | O48: =B48&" "&C48 -> Canaan Hourani
A49: 48 | B49: James | C49: Murphy | D49: Murphy, James | E49: 44592 | F49: Terminated | G49: 2022-09-03 | H49: Datadog | J49: Boylston | L49: 200- Datadog:210- Delivery | M49: Cost of Goods Sold:COGS- Travel Expenses: | N49: Cost of Goods Sold:COGS- Personnel Expense: | O49: =B49&" "&C49 -> James Murphy
A50: 49 | B50: Christina | C50: Metri | D50: Metri, Christina | E50: 44599 | F50: Terminated | G50: 2023-09-29 | H50: Operations | J50: Boylston | K50: No | L50: 100- Operations:110- G&A | M50: General & Administrative:G&A- Travel Expenses: | N50: General & Administrative:G&A- Personnel Expenses: | O50: =B50&" "&C50 -> Christina Metri
A51: 50 | B51: Shakara | C51: Whitehead | D51: Whitehead, Shakara | E51: 44599 | F51: Full-Time | G51: 2022-02-07 | H51: ServiceNow | I51: Engineering | J51: Remote | K51: Yes | L51: 300- ServiceNow:320- Engineering | M51: Cost of Goods Sold:COGS- Travel Expenses: | N51: Cost of Goods Sold:COGS- Personnel Expense: | O51: =B51&" "&C51 -> Shakara Whitehead
A52: 51 | B52: Adonis | C52: Peguero | D52: Peguero, Adonis | E52: 44599 | F52: Terminated | G52: 2023-04-22 | H52: ServiceNow | J52: Remote | L52: 300- ServiceNow:320- Engineering | M52: Cost of Goods Sold:COGS- Travel Expenses: | N52: Cost of Goods Sold:COGS- Personnel Expense: | O52: =B52&" "&C52 -> Adonis Peguero
A53: 52 | B53: Anaflor | C53: Pernalete | D53: Pernalete, Anaflor | E53: 44606 | F53: Terminated | G53: 2023-06-22 | H53: Datadog | J53: Remote | L53: 200- Datadog:220- Engineering | M53: Cost of Goods Sold:COGS- Travel Expenses: | N53: Cost of Goods Sold:COGS- Personnel Expense: | O53: =B53&" "&C53 -> Anaflor Pernalete
A54: 53 | B54: William | C54: Gilleran | D54: Gilleran, William | E54: 44617 | F54: Terminated | G54: 2025-07-11 | H54: Datadog | J54: Boylston | K54: Yes | L54: 200- Datadog:220- Engineering | M54: Cost of Goods Sold:COGS- Travel Expenses: | N54: Cost of Goods Sold:COGS- Personnel Expense: | O54: =B54&" "&C54 -> William Gilleran
A55: 54 | B55: Anthony | C55: Younes | D55: Younes, Anthony | E55: 44621 | F55: Terminated | G55: 2023-11-10 | H55: Datadog | J55: Boylston | K55: No | L55: 200- Datadog:230- Sales | M55: Sales & Marketing:Sales & Marketing- Travel Expenses: | N55: General & Administrative:G&A- Personnel Expenses: | O55: =B55&" "&C55 -> Anthony Younes
A56: 55 | B56: Joseph | C56: Chima | D56: Chima, Joseph | E56: 44620 | F56: Terminated | G56: 2022-05-31 | H56: Datadog | J56: Boylston | L56: 200- Datadog:220- Engineering | M56: Cost of Goods Sold:COGS- Travel Expenses: | N56: Cost of Goods Sold:COGS- Personnel Expense: | O56: =B56&" "&C56 -> Joseph Chima
A57: 56 | B57: Cameron | C57: Buckner | D57: Buckner, Cameron | E57: 44627 | F57: Terminated | G57: 2024-03-22 | H57: Datadog | J57: Remote | K57: Yes | L57: 200- Datadog:220- Engineering | M57: Cost of Goods Sold:COGS- Travel Expenses: | N57: Cost of Goods Sold:COGS- Personnel Expense: | O57: =B57&" "&C57 -> Cameron Buckner
A58: 57 | B58: Alexander | C58: Mittell | D58: Mittell, Alexander | E58: 44634 | F58: Terminated | G58: 2023-03-11 | H58: ServiceNow | J58: Remote | L58: 300- ServiceNow:320- Engineering | M58: Cost of Goods Sold:COGS- Travel Expenses: | N58: Cost of Goods Sold:COGS- Personnel Expense: | O58: =B58&" "&C58 -> Alexander Mittell
A59: 58 | B59: Michael | C59: Christinsen | D59: Christinsen, Michael | E59: 44641 | F59: Full-Time | G59: 2022-03-21 | H59: Datadog | I59: Engineering | J59: Remote | K59: Yes | L59: 200- Datadog:220- Engineering | M59: Cost of Goods Sold:COGS- Travel Expenses: | N59: Cost of Goods Sold:COGS- Personnel Expense: | O59: =B59&" "&C59 -> Michael Christinsen
A60: 59 | B60: Justin | C60: Shaver | D60: Shaver, Justin | E60: 44679 | F60: Terminated | G60: 2022-06-10 | H60: ServiceNow | J60: Remote | L60: 300- ServiceNow:320- Engineering | M60: Cost of Goods Sold:COGS- Travel Expenses: | N60: Cost of Goods Sold:COGS- Personnel Expense: | O60: =B60&" "&C60 -> Justin Shaver
A61: 60 | B61: Pooja | C61: Manjeshwar | D61: Manjeshwar, Pooja Pandurang | E61: 44679 | F61: Full-Time | G61: 2022-04-28 | H61: ServiceNow | I61: Engineering | J61: Boylston | K61: Yes | L61: 300- ServiceNow:320- Engineering | M61: Cost of Goods Sold:COGS- Travel Expenses: | N61: Cost of Goods Sold:COGS- Personnel Expense: | O61: =B61&" "&C61 -> Pooja Manjeshwar
A62: 61 | B62: Evan | C62: Guby | D62: Guby, Evan | E62: 44679 | F62: Terminated | G62: 2025-10-10 | H62: ServiceNow | J62: Remote | K62: Yes | L62: 300- ServiceNow:320- Engineering | M62: Cost of Goods Sold:COGS- Travel Expenses: | N62: Cost of Goods Sold:COGS- Personnel Expense: | O62: =B62&" "&C62 -> Evan Guby
A63: 62 | B63: Ashle | C63: Craig | D63: Craig, Ashle | E63: 44704 | F63: Terminated | G63: 2022-10-15 | H63: ServiceNow | J63: Remote | L63: 300- ServiceNow:320- Engineering | M63: Cost of Goods Sold:COGS- Travel Expenses: | N63: Cost of Goods Sold:COGS- Personnel Expense: | O63: =B63&" "&C63 -> Ashle Craig
A64: 63 | B64: Henri | C64: Hatch | D64: Hatch, Henri | E64: 45068 | F64: Terminated | G64: 2026-01-02 | H64: Datadog | J64: Remote | K64: Yes | L64: 200- Datadog:220- Engineering | M64: Cost of Goods Sold:COGS- Travel Expenses: | N64: Cost of Goods Sold:COGS- Personnel Expense: | O64: =B64&" "&C64 -> Henri Hatch
A65: 64 | B65: Dalton | C65: Ryan | D65: Ryan, Dalton | E65: 44725 | F65: Terminated | G65: 2023-02-18 | H65: Datadog | J65: Boylston | L65: 200- Datadog:220- Engineering | M65: Cost of Goods Sold:COGS- Travel Expenses: | N65: Cost of Goods Sold:COGS- Personnel Expense: | O65: =B65&" "&C65 -> Dalton Ryan
A66: 65 | B66: Patrick | C66: Dennis | D66: Dennis, Patrick | E66: 44733 | F66: Full-Time | G66: 2022-06-21 | H66: ServiceNow | I66: Project Management | J66: Remote | K66: Yes | L66: 300- ServiceNow:310- Delivery | M66: Cost of Goods Sold:COGS- Travel Expenses: | N66: Cost of Goods Sold:COGS- Personnel Expense: | O66: =B66&" "&C66 -> Patrick Dennis
A67: 66 | B67: Daniel | C67: Bench | D67: Bench, Daniel | E67: 44739 | F67: Full-Time | G67: 2022-06-27 | H67: ServiceNow | I67: Engineering | J67: Remote | K67: Yes | L67: 300- ServiceNow:320- Engineering | M67: Cost of Goods Sold:COGS- Travel Expenses: | N67: Cost of Goods Sold:COGS- Personnel Expense: | O67: =B67&" "&C67 -> Daniel Bench
A68: 67 | B68: Matthew | C68: Morris | D68: Morris, Matthew | E68: 44732 | F68: Full-Time | G68: 2022-06-20 | H68: ServiceNow | I68: Sales | J68: Remote | K68: No | L68: 300- ServiceNow:330- Sales | M68: Sales & Marketing:Sales & Marketing- Travel Expenses: | N68: Sales & Marketing:Sales & Marketing- Personnel Expenses: | O68: =B68&" "&C68 -> Matthew Morris
A69: 68 | B69: Alexander | C69: Bennett | D69: Bennett, Alexander | E69: 44747 | F69: Terminated | G69: 2022-09-02 | H69: ServiceNow | J69: Remote | L69: 300- ServiceNow:320- Engineering | M69: Cost of Goods Sold:COGS- Travel Expenses: | N69: Cost of Goods Sold:COGS- Personnel Expense: | O69: =B69&" "&C69 -> Alexander Bennett
A70: 69 | B70: Alta | C70: Abel | D70: Abel, Alta | E70: 44753 | F70: Full-Time | G70: 2022-07-11 | H70: Operations | I70: People Operations | J70: Boylston | K70: No | L70: 400- Synechron:410- Digital platforms G&A | M70: General & Administrative:G&A- Travel Expenses: | N70: General & Administrative:G&A- Personnel Expenses: | O70: =B70&" "&C70 -> Alta Abel
A71: 70 | B71: Daniel | C71: Hamilton | D71: Hamilton, Daniel | E71: 44767 | F71: Full-Time | G71: 2022-07-25 | H71: Datadog | I71: Project Management | J71: Boylston | K71: Yes | L71: 200- Datadog:210- Delivery | M71: Cost of Goods Sold:COGS- Travel Expenses: | N71: Cost of Goods Sold:COGS- Personnel Expense: | O71: =B71&" "&C71 -> Daniel Hamilton
A72: 71 | B72: Ben | C72: Savage | D72: Savage, Ben | E72: 44772 | F72: Full-Time | G72: 2022-07-30 | H72: ServiceNow | I72: Engineering | J72: Non-US | K72: Yes | L72: 300- ServiceNow:320- Engineering | M72: Cost of Goods Sold:COGS- Travel Expenses: | N72: Cost of Goods Sold:COGS- Personnel Expense: | O72: =B72&" "&C72 -> Ben Savage
A73: 72 | B73: Julian | C73: Wukitsch | D73: Wukitsch, Julian | E73: 44781 | F73: Terminated | G73: 2023-03-16 | H73: Datadog | J73: Remote | L73: 200- Datadog:230- Sales | M73: Sales & Marketing:Sales & Marketing- Travel Expenses: | N73: General & Administrative:G&A- Personnel Expenses: | O73: =B73&" "&C73 -> Julian Wukitsch
A74: 73 | B74: Thomas | C74: Sobczak | D74: Sobczak, Thomas | E74: 44788 | F74: Terminated | G74: 2023-04-22 | H74: ServiceNow | J74: Remote | L74: 300- ServiceNow:310- Delivery | M74: Cost of Goods Sold:COGS- Travel Expenses: | N74: Cost of Goods Sold:COGS- Personnel Expense: | O74: =B74&" "&C74 -> Thomas Sobczak
A75: 74 | B75: Robert | C75: Witty | D75: Witty, Robert | E75: 44795 | F75: Full-Time | G75: 2022-08-22 | H75: ServiceNow | I75: Engineering | J75: Remote | K75: Yes | L75: 300- ServiceNow:320- Engineering | M75: Cost of Goods Sold:COGS- Travel Expenses: | N75: Cost of Goods Sold:COGS- Personnel Expense: | O75: =B75&" "&C75 -> Robert Witty
