Workbook

Sheet GAAP Summary
B1: GAAP Management Reporting
B2: 46174
B4: Q4 - OPERATING GOALS
B6: millions | C6: Actuals - 4Q22 | D6: Actuals - 4Q23 | E6: Target | G6: Operating Goals | J6: Achievement | Q6: Inputs
B7: Revenue | C7: ='GAAP Analysis'!DN13 -> 4885562 | D7: ='GAAP Analysis'!DH13 -> 5095749 | E7: =6700000/1000/1000 -> 6.7 | G7: =(E7-E8)*1000000/R10/R9/3 -> 134.41358 | H7: monthly billable hours per resource | Q7: Deposit % of revenue | R7: 0.22
B8: from deposits | E8: =E7*R7 -> 1.474 | Q8: Avg deposit amount | R8: 0.2
B9: from billable work | E9: =E7-E8 -> 5.226 | Q9: Rate | R9: 270
B10: Bookings | C10: ='GAAP Analysis'!DN7 -> 7894608.2 | D10: ='GAAP Analysis'!DH7 -> 8144285.3 | E10: =E8/R8 -> 7.37 | G10: =E10/R11*1000000/3 -> 223333.33 | H10: monthly bookings per AE | Q10: Billable HC | R10: 48
Q11: AE HC | R11: 11
B14: Bookings / Revenue / EBITDA - Monthly
B44: Bookings - FY25 vs. FY24 vs. FY23 vs. FY22
B68: YoY Revenue - FY25 vs. FY24 vs. FY23 vs. FY22
B92: YoY Performance by Quarter
B138: TTM Bookings, Revenue & EBITDA as of Date
B188: Bookings Composition - SN vs DD
AD189: GP + 15%
AC190: 65 | AD190: =AC190*1.15 -> 74.75 | AE190: 74.75
AC191: 61 | AD191: =AC191*1.15 -> 70.15 | AE191: 70.15
AC192: 67 | AD192: =AC192*1.15 -> 77.05 | AE192: 77.05
AC193: 62 | AD193: =AC193*1.15 -> 71.3 | AE193: 71.3
AC194: 57 | AD194: =AC194*1.15 -> 65.55 | AE194: 65.55
AC195: 57 | AD195: =AC195*1.15 -> 65.55 | AE195: 65.55
AC196: 58 | AD196: =AC196*1.15 -> 66.7 | AE196: 66.7
AC197: 57 | AD197: =AC197*1.15 -> 65.55 | AE197: 65.55
AC198: 62 | AD198: =AC198*1.15 -> 71.3 | AE198: 71.3
AC199: 58 | AD199: =AC199*1.15 -> 66.7 | AE199: 66.7
AC200: 59 | AD200: =AC200*1.15 -> 67.85 | AE200: 67.85
AC201: 61 | AD201: =AC201*1.15 -> 70.15 | AE201: 70.15
AC202: =AC203/100 -> 0.007475 | AD202: =AD203/100 -> 0.007015 | AE202: =AE203/100 -> 0.007705 | AF202: =AF203/100 -> 0.00713 | AG202: =AG203/100 -> 0.006555 | AH202: =AH203/100 -> 0.006555 | AI202: =AI203/100 -> 0.00667 | AJ202: =AJ203/100 -> 0.006555 | ... AN202: =AN203/100 -> 0.007015
AC203: 0.7475 | AD203: 0.7015 | AE203: 0.7705 | AF203: 0.713 | AG203: 0.6555 | AH203: 0.6555 | AI203: 0.667 | AJ203: 0.6555 | AK203: 0.713 | AL203: 0.667 | AM203: 0.6785 | AN203: 0.7015
B210: Revenue & Gross Profit
B234: Monthly Expenses
B256: Forecast vs. Actuals- Calendar Year 2026
B297: Billable vs Non-Billable Headcount
B318: Hours billed per head & Padding
B340: Real Rate vs. Net Income

Sheet GAAP Analysis
C2: 2020 | O2: 2021 | AA2: 2022 | AM2: 2023 | DS2: TTM As Of:
C3: 43831 | D3: 43862 | E3: 43891 | F3: 43922 | G3: 43952 | H3: 43983 | I3: 44013 | J3: 44044 | K3: 44075 | L3: 44105 | M3: 44136 | N3: 44166 | O3: 44197 | P3: 44228 | Q3: 44256 | R3: 44287 | S3: 44317 | T3: 44348 | U3: 44378 | V3: 44409 | W3: 44440 | X3: 44470 | Y3: 44501 | Z3: 44531 | AA3: 44562 | AB3: 44593 | AC3: 44621 | AD3: 44652 | AE3: 44682 | AF3: 44713 | AG3: 44743 | AH3: 44774 | AI3: 44805 | AJ3: 44835 | AK3: 44866 | AL3: 44896 | AM3: 44927 | AN3: 44958 | AO3: 44986 | AP3: 45017 | AQ3: 45047 | AR3: 45078 | AS3: 45108 | AT3: 45139 | AU3: 45170 | AV3: 45200 | AW3: 45231 | AX3: 45261 | AY3: 45292 | AZ3: 45323 | BA3: 45352 | BB3: 45383 | BC3: 45413 | BD3: 45444 | BE3: 45474 | BF3: 45505 | BG3: 45536 | BH3: 45566 | BI3: 45597 | BJ3: 45627 | BK3: 45658 | BL3: 45689 | BM3: 45717 | BN3: 45748 | BO3: 45778 | BP3: 45809 | BQ3: 45839 | BR3: 45870 | BS3: 45901 | BT3: 45931 | BU3: 45962 | BV3: 45992 | BW3: 46023 | BX3: 46054 | BY3: 46082 | BZ3: 46113 | CA3: 46143 | CB3: 46174 | CC3: 46204 | CD3: 46235 | CE3: 46266 | CF3: 46296 | CG3: 46327 | CH3: 46357 | CK3: ="TTM as of "&TEXT('GAAP Summary'!B2,"MMM 'YY") -> TTM as of Jun '26 | CM3: 4Q25 | CN3: 1Q26 | CO3: 2Q26 | CP3: 3Q26 | CQ3: CY26 | CS3: 4Q24 | CT3: 1Q25 | CU3: 2Q25 | CV3: 3Q25 | CW3: CY25 | CY3: 4Q23 | CZ3: 1Q24 | DA3: 2Q24 | DB3: 3Q24 | DC3: FY24 | DE3: 4Q22 | DF3: 1Q23 | DG3: 2Q23 | DH3: 3Q23 | DI3: FY23 | DK3: 4Q21 | DL3: 1Q22 | DM3: 2Q22 | DN3: 3Q22 | DO3: FY22 | DQ3: FY21 | DS3: 44197 | DT3: 44228 | DU3: 44256 | DV3: 44287 | DW3: 44317 | DX3: 44348 | DY3: 44378 | DZ3: 44409 | EA3: 44440 | EB3: 44470 | EC3: 44501 | ED3: 44531 | EE3: 44562 | EF3: 44593 | EG3: 44621 | EH3: 44652 | EI3: 44682 | EJ3: 44713 | EK3: 44743 | EL3: 44774 | EM3: 44805 | EN3: 44835 | EO3: 44866 | EP3: 44896 | EQ3: 44927 | ER3: 44958 | ES3: 44986 | ET3: 45017 | EU3: 45047 | EV3: 45078 | EW3: 45108 | EX3: 45139 | EY3: 45170 | EZ3: 45200 | FA3: 45231 | FB3: 45261 | FC3: 45292 | FD3: 45323 | FE3: 45352 | FF3: 45383 | FG3: 45413 | FH3: 45444 | FI3: 45474 | FJ3: 45505 | FK3: 45536 | FL3: 45566 | FM3: 45597 | FN3: 45627 | FO3: 45658 | FP3: 45689 | FQ3: 45717 | FR3: 45748 | FS3: 45778 | FT3: 45809 | FU3: 45839 | FV3: 45870 | FW3: 45901 | FX3: 45931 | FY3: 45962 | FZ3: 45992 | GA3: 46023 | GB3: 46054 | GC3: 46082 | GD3: 46113 | GE3: 46143 | GF3: 46174 | GG3: 46204 | GH3: 46235 | GI3: 46266 | GJ3: 46296 | GK3: 46327 | GL3: 46357
B5: Actuals
CM6: =CM7/CM13 -> 1.1303556 | CS6: =CS7/CS13 -> 1.1307252 | CT6: =CT7/CT13 -> 1.5391623 | CU6: =CU7/CU13 -> 1.3006619 | CV6: =CV7/CV13 -> 1.6265529 | CY6: =CY7/CY13 -> 1.0765554 | CZ6: =CZ7/CZ13 -> 1.1380873 | DA6: =DA7/DA13 -> 0.96709459 | DB6: =DB7/DB13 -> 1.2340552 | DE6: =DE7/DE13 -> 0.44561878 | DF6: =DF7/DF13 -> 0.67674018 | DG6: =DG7/DG13 -> 0.83586857 | DH6: =DH7/DH13 -> 1.5982509
B7: Bookings | C7: =sum(C8:C11) -> 0 | D7: =sum(D8:D11) -> 0 | E7: =sum(E8:E11) -> 0 | F7: =sum(F8:F11) -> 0 | G7: =sum(G8:G11) -> 0 | H7: =sum(H8:H11) -> 0 | I7: =sum(I8:I11) -> 0 | J7: =sum(J8:J11) -> 0 | ... CH7: =sum(CH8:CH11) -> 0 | CK7: {=SUM(INDIRECT(XLOOKUP('GAAP Summary'!$B$2,'TTM Dates'!$B:$B,'TTM Dates'!$E:$E)&ROW($CJ7)&":"&XLOOKUP('GAAP Summary'!$B$2,'TTM Dates'!$B:$B,'TTM Dates'!$C:$C)&ROW($CJ7)))} -> 53144206 | CM7: =sum(BW7:BY7) -> 14213363 | CN7: =sum(BZ7:CB7) -> 8764995.3 | CO7: 0 | CP7: 0 | CQ7: =sum(CM7:CP7) -> 22978358 | CS7: =sum(BK7:BM7) -> 8394063.9 | CT7: =sum(BN7:BP7) -> 12379014 | CU7: =sum(BQ7:BS7) -> 12354635 | CV7: =sum(BT7:BV7) -> 17811213 | CW7: =sum(BK7:BV7) -> 50938925 | CX7: =sum(CT7:CV7)/sum(CZ7:DB7)-1 -> 0.90927214 | CY7: =sum(AY7:BA7) -> 5881823 | CZ7: =sum(BB7:BD7) -> 6544902 | DA7: =sum(BE7:BG7) -> 6201507 | DB7: =sum(BH7:BJ7) -> 9536879.1 | DC7: =sum(AY7:BJ7) -> 28165111 | DE7: =sum(AM7:AO7) -> 2808888 | DF7: =sum(AP7:AR7) -> 3780640.8 | DG7: =sum(AS7:AU7) -> 4345506 | DH7: =sum(AV7:AX7) -> 8144285.3 | DI7: =sum(DE8:DH10) -> 19079320 | DK7: =sum(AA7:AC7) -> 3491390 | DL7: =sum(AD7:AF7) -> 7507668 | DM7: =sum(AG7:AI7) -> 5709804.4 | DN7: =sum(AJ7:AL7) -> 7894608.2 | DO7: =sum(AA7:AL7) -> 24603471 | DQ7: =sum(O7:Z7) -> 0 | DS7: {=IF(DS$3>'GAAP Summary'!$B$2,0,SUM(INDIRECT(XLOOKUP(DS$3,'TTM Dates'!$B:$B,'TTM Dates'!$E:$E)&ROW($CJ7)&":"&XLOOKUP(DS$3,'TTM Dates'!$B:$B,'TTM Dates'!$C:$C)&ROW($CJ7))))} -> 0 | DT7: {=IF(DT$3>'GAAP Summary'!$B$2,0,SUM(INDIRECT(XLOOKUP(DT$3,'TTM Dates'!$B:$B,'TTM Dates'!$E:$E)&ROW($CJ7)&":"&XLOOKUP(DT$3,'TTM Dates'!$B:$B,'TTM Dates'!$C:$C)&ROW($CJ7))))} -> 0 | DU7: {=IF(DU$3>'GAAP Summary'!$B$2,0,SUM(INDIRECT(XLOOKUP(DU$3,'TTM Dates'!$B:$B,'TTM Dates'!$E:$E)&ROW($CJ7)&":"&XLOOKUP(DU$3,'TTM Dates'!$B:$B,'TTM Dates'!$C:$C)&ROW($CJ7))))} -> 0 | DV7: {=IF(DV$3>'GAAP Summary'!$B$2,0,SUM(INDIRECT(XLOOKUP(DV$3,'TTM Dates'!$B:$B,'TTM Dates'!$E:$E)&ROW($CJ7)&":"&XLOOKUP(DV$3,'TTM Dates'!$B:$B,'TTM Dates'!$C:$C)&ROW($CJ7))))} -> 0 | DW7: {=IF(DW$3>'GAAP Summary'!$B$2,0,SUM(INDIRECT(XLOOKUP(DW$3,'TTM Dates'!$B:$B,'TTM Dates'!$E:$E)&ROW($CJ7)&":"&XLOOKUP(DW$3,'TTM Dates'!$B:$B,'TTM Dates'!$C:$C)&ROW($CJ7))))} -> 0 | DX7: {=IF(DX$3>'GAAP Summary'!$B$2,0,SUM(INDIRECT(XLOOKUP(DX$3,'TTM Dates'!$B:$B,'TTM Dates'!$E:$E)&ROW($CJ7)&":"&XLOOKUP(DX$3,'TTM Dates'!$B:$B,'TTM Dates'!$C:$C)&ROW($CJ7))))} -> 0 | DY7: {=IF(DY$3>'GAAP Summary'!$B$2,0,SUM(INDIRECT(XLOOKUP(DY$3,'TTM Dates'!$B:$B,'TTM Dates'!$E:$E)&ROW($CJ7)&":"&XLOOKUP(DY$3,'TTM Dates'!$B:$B,'TTM Dates'!$C:$C)&ROW($CJ7))))} -> 0 | DZ7: {=IF(DZ$3>'GAAP Summary'!$B$2,0,SUM(INDIRECT(XLOOKUP(DZ$3,'TTM Dates'!$B:$B,'TTM Dates'!$E:$E)&ROW($CJ7)&":"&XLOOKUP(DZ$3,'TTM Dates'!$B:$B,'TTM Dates'!$C:$C)&ROW($CJ7))))} -> 0 | ... GL7: {=IF(GL$3>'GAAP Summary'!$B$2,0,SUM(INDIRECT(XLOOKUP(GL$3,'TTM Dates'!$B:$B,'TTM Dates'!$E:$E)&ROW($CJ7)&":"&XLOOKUP(GL$3,'TTM Dates'!$B:$B,'TTM Dates'!$C:$C)&ROW($CJ7))))} -> 0
B8: DD | AA8: 99720 | AB8: 80640 | AC8: 204640 | AD8: 415440 | AE8: 586400 | AF8: 1074960 | AG8: 1328420 | AH8: 79040 | AI8: 922672 | AJ8: 1649000 | AK8: 427800 | AL8: 813970 | AM8: 134400 | AN8: 349104 | AO8: 801544 | AP8: 331413.01 | AQ8: 732202 | AR8: 985245 | AS8: 111000 | AT8: 1120200 | AU8: 293440 | AV8: =57600+216000+87680+106880+25000+345900 -> 839060 | AW8: 2468100 | AX8: 1607072 | AY8: 0 | AZ8: =60700+34560 -> 95260 | BA8: 664160 | BB8: 245840 | BC8: 1070080 | BD8: 595296 | BE8: 710760 | BF8: 1387561 | BG8: 286700 | BH8: 436906 | BI8: 2447618 | BJ8: 1341556 | BK8: 119460 | BL8: 115760 | BM8: 404780 | BN8: 1148000 | BO8: 433500 | BP8: 1071080 | BQ8: 825056 | BR8: 951820 | BS8: 610240 | BT8: 555824 | BU8: 2429600 | BV8: 2964830 | BW8: 109440 | BX8: 718652 | BY8: 2704916 | BZ8: 106832 | CA8: 551080 | CB8: 328016 | CK8: {=SUM(INDIRECT(XLOOKUP('GAAP Summary'!$B$2,'TTM Dates'!$B:$B,'TTM Dates'!$E:$E)&ROW($CJ8)&":"&XLOOKUP('GAAP Summary'!$B$2,'TTM Dates'!$B:$B,'TTM Dates'!$C:$C)&ROW($CJ8)))} -> 12856306 | CM8: =sum(BW8:BY8) -> 3533008 | CN8: =sum(BZ8:CB8) -> 985928 | CO8: =sum(CC8:CE8) -> 0 | CP8: =sum(CF8:CH8) -> 0 | CQ8: =sum(BW8:CH8) -> 4518936 | CS8: =sum(BK8:BM8) -> 640000 | CT8: =sum(BN8:BP8) -> 2652580 | CU8: =sum(BQ8:BS8) -> 2387116 | CV8: =sum(BT8:BV8) -> 5950254 | CW8: =sum(BK8:BV8) -> 11629950 | CX8: =sum(CT8:CV8)/sum(CZ8:DB8)-1 -> 0.28954954 | CY8: =sum(AY8:BA8) -> 759420 | CZ8: =sum(BB8:BD8) -> 1911216 | DA8: =sum(BE8:BG8) -> 2385021 | DB8: =sum(BH8:BJ8) -> 4226080 | DC8: =sum(AY8:BJ8) -> 9281737 | DE8: =sum(AM8:AO8) -> 1285048 | DF8: =sum(AP8:AR8) -> 2048860 | DG8: =sum(AS8:AU8) -> 1524640 | DH8: =sum(AV8:AX8) -> 4914232 | DI8: =sum(AM8:AX8) -> 9772780 | DK8: =sum(AA8:AC8) -> 385000 | DL8: =sum(AD8:AF8) -> 2076800 | DM8: =sum(AG8:AI8) -> 2330132 | DN8: =sum(AJ8:AL8) -> 2890770 | DO8: =sum(AA8:AL8) -> 7682702 | DQ8: =SUM(O8:Z8) -> 0 | DS8: {=IF(DS$3>'GAAP Summary'!$B$2,0,SUM(INDIRECT(XLOOKUP(DS$3,'TTM Dates'!$B:$B,'TTM Dates'!$E:$E)&ROW($CJ8)&":"&XLOOKUP(DS$3,'TTM Dates'!$B:$B,'TTM Dates'!$C:$C)&ROW($CJ8))))} -> 0 | DT8: {=IF(DT$3>'GAAP Summary'!$B$2,0,SUM(INDIRECT(XLOOKUP(DT$3,'TTM Dates'!$B:$B,'TTM Dates'!$E:$E)&ROW($CJ8)&":"&XLOOKUP(DT$3,'TTM Dates'!$B:$B,'TTM Dates'!$C:$C)&ROW($CJ8))))} -> 0 | DU8: {=IF(DU$3>'GAAP Summary'!$B$2,0,SUM(INDIRECT(XLOOKUP(DU$3,'TTM Dates'!$B:$B,'TTM Dates'!$E:$E)&ROW($CJ8)&":"&XLOOKUP(DU$3,'TTM Dates'!$B:$B,'TTM Dates'!$C:$C)&ROW($CJ8))))} -> 0 | DV8: {=IF(DV$3>'GAAP Summary'!$B$2,0,SUM(INDIRECT(XLOOKUP(DV$3,'TTM Dates'!$B:$B,'TTM Dates'!$E:$E)&ROW($CJ8)&":"&XLOOKUP(DV$3,'TTM Dates'!$B:$B,'TTM Dates'!$C:$C)&ROW($CJ8))))} -> 0 | DW8: {=IF(DW$3>'GAAP Summary'!$B$2,0,SUM(INDIRECT(XLOOKUP(DW$3,'TTM Dates'!$B:$B,'TTM Dates'!$E:$E)&ROW($CJ8)&":"&XLOOKUP(DW$3,'TTM Dates'!$B:$B,'TTM Dates'!$C:$C)&ROW($CJ8))))} -> 0 | DX8: {=IF(DX$3>'GAAP Summary'!$B$2,0,SUM(INDIRECT(XLOOKUP(DX$3,'TTM Dates'!$B:$B,'TTM Dates'!$E:$E)&ROW($CJ8)&":"&XLOOKUP(DX$3,'TTM Dates'!$B:$B,'TTM Dates'!$C:$C)&ROW($CJ8))))} -> 0 | DY8: {=IF(DY$3>'GAAP Summary'!$B$2,0,SUM(INDIRECT(XLOOKUP(DY$3,'TTM Dates'!$B:$B,'TTM Dates'!$E:$E)&ROW($CJ8)&":"&XLOOKUP(DY$3,'TTM Dates'!$B:$B,'TTM Dates'!$C:$C)&ROW($CJ8))))} -> 0 | DZ8: {=IF(DZ$3>'GAAP Summary'!$B$2,0,SUM(INDIRECT(XLOOKUP(DZ$3,'TTM Dates'!$B:$B,'TTM Dates'!$E:$E)&ROW($CJ8)&":"&XLOOKUP(DZ$3,'TTM Dates'!$B:$B,'TTM Dates'!$C:$C)&ROW($CJ8))))} -> 0 | ... GL8: {=IF(GL$3>'GAAP Summary'!$B$2,0,SUM(INDIRECT(XLOOKUP(GL$3,'TTM Dates'!$B:$B,'TTM Dates'!$E:$E)&ROW($CJ8)&":"&XLOOKUP(GL$3,'TTM Dates'!$B:$B,'TTM Dates'!$C:$C)&ROW($CJ8))))} -> 0
B9: SN | AA9: 45100 | AB9: 34560 | AC9: 2906490 | AD9: 240400 | AE9: 3445490 | AF9: 1705200 | AG9: 1642900 | AH9: 240000 | AI9: 1323460 | AJ9: 977400 | AK9: 459420 | AL9: 3326280 | AM9: 0 | AN9: 245760 | AO9: 1007040 | AP9: 220200 | AQ9: 103200 | AR9: 1237328 | AS9: 796400 | AT9: 968070 | AU9: 929178 | AV9: =249600+81000+40500+20025+103200 -> 494325 | AW9: 874546 | AX9: 1259600 | AY9: 57000 | AZ9: 235790 | BA9: 4709700 | BB9: 1366812 | BC9: 2795784 | BD9: 395700 | BE9: 689600 | BF9: 685920 | BG9: 2020630 | BH9: 2156205.2 | BI9: 479693.52 | BJ9: 2235526.2 | BK9: 919568.5 | BL9: 2372860 | BM9: 3187678 | BN9: 4195676 | BO9: 2326386 | BP9: 2388176.5 | BQ9: 3882712 | BR9: 1782484 | BS9: 3813550 | BT9: 5355617 | BU9: 947810 | BV9: 4188499 | BW9: 888340 | BX9: 3672409 | BY9: 5681048 | BZ9: 1330840 | CA9: 3464011 | CB9: 2354221 | CK9: {=SUM(INDIRECT(XLOOKUP('GAAP Summary'!$B$2,'TTM Dates'!$B:$B,'TTM Dates'!$E:$E)&ROW($CJ9)&":"&XLOOKUP('GAAP Summary'!$B$2,'TTM Dates'!$B:$B,'TTM Dates'!$C:$C)&ROW($CJ9)))} -> 37361541 | CM9: =sum(BW9:BY9) -> 10241797 | CN9: =sum(BZ9:CB9) -> 7149072 | CO9: =sum(CC9:CE9) -> 0 | CP9: =sum(CF9:CH9) -> 0 | CQ9: =sum(BW9:CH9) -> 17390869 | CS9: =sum(BK9:BM9) -> 6480106.5 | CT9: =sum(BN9:BP9) -> 8910238.5 | CU9: =sum(BQ9:BS9) -> 9478746 | CV9: =sum(BT9:BV9) -> 10491926 | CW9: =sum(BK9:BV9) -> 35361017 | CX9: =sum(CT9:CV9)/sum(CZ9:DB9)-1 -> 1.2517699 | CY9: =sum(AY9:BA9) -> 5002490 | CZ9: =sum(BB9:BD9) -> 4558296 | DA9: =sum(BE9:BG9) -> 3396150 | DB9: =sum(BH9:BJ9) -> 4871424.9 | DC9: =sum(AY9:BJ9) -> 17828361 | DE9: =sum(AM9:AO9) -> 1252800 | DF9: =sum(AP9:AR9) -> 1560728 | DG9: =sum(AS9:AU9) -> 2693648 | DH9: =sum(AV9:AX9) -> 2628471 | DI9: =sum(AM9:AX9) -> 8135647 | DK9: =sum(AA9:AC9) -> 2986150 | DL9: =sum(AD9:AF9) -> 5391090 | DM9: =sum(AG9:AI9) -> 3206360 | DN9: =sum(AJ9:AL9) -> 4763100 | DO9: =sum(AA9:AL9) -> 16346700 | DQ9: =SUM(O9:Z9) -> 0 | DS9: {=IF(DS$3>'GAAP Summary'!$B$2,0,SUM(INDIRECT(XLOOKUP(DS$3,'TTM Dates'!$B:$B,'TTM Dates'!$E:$E)&ROW($CJ9)&":"&XLOOKUP(DS$3,'TTM Dates'!$B:$B,'TTM Dates'!$C:$C)&ROW($CJ9))))} -> 0 | DT9: {=IF(DT$3>'GAAP Summary'!$B$2,0,SUM(INDIRECT(XLOOKUP(DT$3,'TTM Dates'!$B:$B,'TTM Dates'!$E:$E)&ROW($CJ9)&":"&XLOOKUP(DT$3,'TTM Dates'!$B:$B,'TTM Dates'!$C:$C)&ROW($CJ9))))} -> 0 | DU9: {=IF(DU$3>'GAAP Summary'!$B$2,0,SUM(INDIRECT(XLOOKUP(DU$3,'TTM Dates'!$B:$B,'TTM Dates'!$E:$E)&ROW($CJ9)&":"&XLOOKUP(DU$3,'TTM Dates'!$B:$B,'TTM Dates'!$C:$C)&ROW($CJ9))))} -> 0 | DV9: {=IF(DV$3>'GAAP Summary'!$B$2,0,SUM(INDIRECT(XLOOKUP(DV$3,'TTM Dates'!$B:$B,'TTM Dates'!$E:$E)&ROW($CJ9)&":"&XLOOKUP(DV$3,'TTM Dates'!$B:$B,'TTM Dates'!$C:$C)&ROW($CJ9))))} -> 0 | DW9: {=IF(DW$3>'GAAP Summary'!$B$2,0,SUM(INDIRECT(XLOOKUP(DW$3,'TTM Dates'!$B:$B,'TTM Dates'!$E:$E)&ROW($CJ9)&":"&XLOOKUP(DW$3,'TTM Dates'!$B:$B,'TTM Dates'!$C:$C)&ROW($CJ9))))} -> 0 | DX9: {=IF(DX$3>'GAAP Summary'!$B$2,0,SUM(INDIRECT(XLOOKUP(DX$3,'TTM Dates'!$B:$B,'TTM Dates'!$E:$E)&ROW($CJ9)&":"&XLOOKUP(DX$3,'TTM Dates'!$B:$B,'TTM Dates'!$C:$C)&ROW($CJ9))))} -> 0 | DY9: {=IF(DY$3>'GAAP Summary'!$B$2,0,SUM(INDIRECT(XLOOKUP(DY$3,'TTM Dates'!$B:$B,'TTM Dates'!$E:$E)&ROW($CJ9)&":"&XLOOKUP(DY$3,'TTM Dates'!$B:$B,'TTM Dates'!$C:$C)&ROW($CJ9))))} -> 0 | DZ9: {=IF(DZ$3>'GAAP Summary'!$B$2,0,SUM(INDIRECT(XLOOKUP(DZ$3,'TTM Dates'!$B:$B,'TTM Dates'!$E:$E)&ROW($CJ9)&":"&XLOOKUP(DZ$3,'TTM Dates'!$B:$B,'TTM Dates'!$C:$C)&ROW($CJ9))))} -> 0 | ... GL9: {=IF(GL$3>'GAAP Summary'!$B$2,0,SUM(INDIRECT(XLOOKUP(GL$3,'TTM Dates'!$B:$B,'TTM Dates'!$E:$E)&ROW($CJ9)&":"&XLOOKUP(GL$3,'TTM Dates'!$B:$B,'TTM Dates'!$C:$C)&ROW($CJ9))))} -> 0
B10: SW | AA10: 0 | AB10: 120240 | AC10: 0 | AD10: 9120 | AE10: 11375 | AF10: 19283 | AG10: 164022 | AH10: 7980 | AI10: 1310.4 | AJ10: 14208 | AK10: 104678.8 | AL10: 121851.36 | AM10: 0 | AN10: 252000 | AO10: 19040 | AP10: 1310.4 | AQ10: 22188 | AR10: 147554.4 | AS10: 108510 | AT10: 14208 | AU10: 4500 | AV10: 92818 | AW10: 56866.32 | AX10: 451898 | AY10: 0 | AZ10: 52800 | BA10: 67113 | BC10: 1890 | BD10: 73500 | BE10: 5860 | BF10: 47660 | BH10: 3931.2 | BI10: 84511.25 | BJ10: 229832.7 | BK10: 92097.6 | BL10: 0 | BN10: 11088 | BP10: 73500 | BQ10: 0 | BS10: 258006 | BT10: 29269.17 | BU10: 80732 | BV10: 289031.47 | BW10: 7426 | BX10: 81692 | BY10: 19440 | BZ10: 0 | CB10: 64800 | CK10: {=SUM(INDIRECT(XLOOKUP('GAAP Summary'!$B$2,'TTM Dates'!$B:$B,'TTM Dates'!$E:$E)&ROW($CJ10)&":"&XLOOKUP('GAAP Summary'!$B$2,'TTM Dates'!$B:$B,'TTM Dates'!$C:$C)&ROW($CJ10)))} -> 830396.64 | CM10: =sum(BW10:BY10) -> 108558 | CN10: =sum(BZ10:CB10) -> 64800 | CO10: =sum(CC10:CE10) -> 0 | CP10: =sum(CF10:CH10) -> 0 | CQ10: =sum(BW10:CH10) -> 173358 | CS10: =sum(BK10:BM10) -> 92097.6 | CT10: =sum(BN10:BP10) -> 84588 | CU10: =sum(BQ10:BS10) -> 258006 | CV10: =sum(BT10:BV10) -> 399032.64 | CW10: =sum(BK10:BV10) -> 833724.24 | CX10: =sum(CT10:CV10)/sum(CZ10:DB10)-1 -> 0.65843307 | CY10: =sum(AY10:BA10) -> 119913 | CZ10: =sum(BB10:BD10) -> 75390 | DA10: =sum(BE10:BG10) -> 53520 | DB10: =sum(BH10:BJ10) -> 318275.15 | DC10: =sum(AY10:BJ10) -> 567098.15 | DE10: =sum(AM10:AO10) -> 271040 | DF10: =sum(AP10:AR10) -> 171052.8 | DG10: =sum(AS10:AU10) -> 127218 | DH10: =sum(AV10:AX10) -> 601582.32 | DI10: =sum(AM10:AX10) -> 1170893.1 | DK10: =sum(AA10:AC10) -> 120240 | DL10: =sum(AD10:AF10) -> 39778 | DM10: =sum(AG10:AI10) -> 173312.4 | DN10: =sum(AJ10:AL10) -> 240738.16 | DO10: =sum(AA10:AL10) -> 574068.56 | DS10: {=IF(DS$3>'GAAP Summary'!$B$2,0,SUM(INDIRECT(XLOOKUP(DS$3,'TTM Dates'!$B:$B,'TTM Dates'!$E:$E)&ROW($CJ10)&":"&XLOOKUP(DS$3,'TTM Dates'!$B:$B,'TTM Dates'!$C:$C)&ROW($CJ10))))} -> 0 | DT10: {=IF(DT$3>'GAAP Summary'!$B$2,0,SUM(INDIRECT(XLOOKUP(DT$3,'TTM Dates'!$B:$B,'TTM Dates'!$E:$E)&ROW($CJ10)&":"&XLOOKUP(DT$3,'TTM Dates'!$B:$B,'TTM Dates'!$C:$C)&ROW($CJ10))))} -> 0 | DU10: {=IF(DU$3>'GAAP Summary'!$B$2,0,SUM(INDIRECT(XLOOKUP(DU$3,'TTM Dates'!$B:$B,'TTM Dates'!$E:$E)&ROW($CJ10)&":"&XLOOKUP(DU$3,'TTM Dates'!$B:$B,'TTM Dates'!$C:$C)&ROW($CJ10))))} -> 0 | DV10: {=IF(DV$3>'GAAP Summary'!$B$2,0,SUM(INDIRECT(XLOOKUP(DV$3,'TTM Dates'!$B:$B,'TTM Dates'!$E:$E)&ROW($CJ10)&":"&XLOOKUP(DV$3,'TTM Dates'!$B:$B,'TTM Dates'!$C:$C)&ROW($CJ10))))} -> 0 | DW10: {=IF(DW$3>'GAAP Summary'!$B$2,0,SUM(INDIRECT(XLOOKUP(DW$3,'TTM Dates'!$B:$B,'TTM Dates'!$E:$E)&ROW($CJ10)&":"&XLOOKUP(DW$3,'TTM Dates'!$B:$B,'TTM Dates'!$C:$C)&ROW($CJ10))))} -> 0 | DX10: {=IF(DX$3>'GAAP Summary'!$B$2,0,SUM(INDIRECT(XLOOKUP(DX$3,'TTM Dates'!$B:$B,'TTM Dates'!$E:$E)&ROW($CJ10)&":"&XLOOKUP(DX$3,'TTM Dates'!$B:$B,'TTM Dates'!$C:$C)&ROW($CJ10))))} -> 0 | DY10: {=IF(DY$3>'GAAP Summary'!$B$2,0,SUM(INDIRECT(XLOOKUP(DY$3,'TTM Dates'!$B:$B,'TTM Dates'!$E:$E)&ROW($CJ10)&":"&XLOOKUP(DY$3,'TTM Dates'!$B:$B,'TTM Dates'!$C:$C)&ROW($CJ10))))} -> 0 | DZ10: {=IF(DZ$3>'GAAP Summary'!$B$2,0,SUM(INDIRECT(XLOOKUP(DZ$3,'TTM Dates'!$B:$B,'TTM Dates'!$E:$E)&ROW($CJ10)&":"&XLOOKUP(DZ$3,'TTM Dates'!$B:$B,'TTM Dates'!$C:$C)&ROW($CJ10))))} -> 0 | ... GL10: {=IF(GL$3>'GAAP Summary'!$B$2,0,SUM(INDIRECT(XLOOKUP(GL$3,'TTM Dates'!$B:$B,'TTM Dates'!$E:$E)&ROW($CJ10)&":"&XLOOKUP(GL$3,'TTM Dates'!$B:$B,'TTM Dates'!$C:$C)&ROW($CJ10))))} -> 0
B11: MSP | BF11: 366816 | BH11: 21117 | BI11: 79982 | BJ11: 20000 | BL11: 900000 | BM11: 281859.85 | BN11: 303607 | BO11: 180000 | BP11: 248000 | BQ11: 0 | BR11: 75000 | BS11: =148962.96+6804 -> 155766.96 | BT11: 435000 | BU11: 535000 | BV11: 0 | BY11: 330000 | BZ11: 0 | CA11: 465195.32 | CB11: 100000 | CK11: {=SUM(INDIRECT(XLOOKUP('GAAP Summary'!$B$2,'TTM Dates'!$B:$B,'TTM Dates'!$E:$E)&ROW($CJ11)&":"&XLOOKUP('GAAP Summary'!$B$2,'TTM Dates'!$B:$B,'TTM Dates'!$C:$C)&ROW($CJ11)))} -> 2095962.3 | CM11: =sum(BW11:BY11) -> 330000 | CN11: =sum(BZ11:CB11) -> 565195.32 | CO11: =sum(CC11:CE11) -> 0 | CP11: =sum(CF11:CH11) -> 0 | CQ11: =sum(BW11:CH11) -> 895195.32 | CS11: =sum(BK11:BM11) -> 1181859.9 | CT11: =sum(BN11:BP11) -> 731607 | CU11: =sum(BQ11:BS11) -> 230766.96 | CV11: =sum(BT11:BV11) -> 970000 | CW11: =sum(BK11:BV11) -> 3114233.8 | CX11: =sum(CT11:CV11)/sum(CZ11:DB11)-1 -> 2.9604725 | CY11: =sum(AY11:BA11) -> 0 | CZ11: =sum(BB11:BD11) -> 0 | DA11: =sum(BE11:BG11) -> 366816 | DB11: =sum(BH11:BJ11) -> 121099 | DC11: =sum(AY11:BJ11) -> 487915 | DK11: =sum(AA11:AC11) -> 0 | DL11: =sum(AD11:AF11) -> 0 | DM11: =sum(AG11:AI11) -> 0 | DN11: =sum(AJ11:AL11) -> 0 | DO11: =sum(AA11:AL11) -> 0 | EE11: {=IF(EE$3>'GAAP Summary'!$B$2,0,SUM(INDIRECT(XLOOKUP(EE$3,'TTM Dates'!$B:$B,'TTM Dates'!$E:$E)&ROW($CJ11)&":"&XLOOKUP(EE$3,'TTM Dates'!$B:$B,'TTM Dates'!$C:$C)&ROW($CJ11))))} -> 0 | EF11: {=IF(EF$3>'GAAP Summary'!$B$2,0,SUM(INDIRECT(XLOOKUP(EF$3,'TTM Dates'!$B:$B,'TTM Dates'!$E:$E)&ROW($CJ11)&":"&XLOOKUP(EF$3,'TTM Dates'!$B:$B,'TTM Dates'!$C:$C)&ROW($CJ11))))} -> 0 | EG11: {=IF(EG$3>'GAAP Summary'!$B$2,0,SUM(INDIRECT(XLOOKUP(EG$3,'TTM Dates'!$B:$B,'TTM Dates'!$E:$E)&ROW($CJ11)&":"&XLOOKUP(EG$3,'TTM Dates'!$B:$B,'TTM Dates'!$C:$C)&ROW($CJ11))))} -> 0 | EH11: {=IF(EH$3>'GAAP Summary'!$B$2,0,SUM(INDIRECT(XLOOKUP(EH$3,'TTM Dates'!$B:$B,'TTM Dates'!$E:$E)&ROW($CJ11)&":"&XLOOKUP(EH$3,'TTM Dates'!$B:$B,'TTM Dates'!$C:$C)&ROW($CJ11))))} -> 0 | EI11: {=IF(EI$3>'GAAP Summary'!$B$2,0,SUM(INDIRECT(XLOOKUP(EI$3,'TTM Dates'!$B:$B,'TTM Dates'!$E:$E)&ROW($CJ11)&":"&XLOOKUP(EI$3,'TTM Dates'!$B:$B,'TTM Dates'!$C:$C)&ROW($CJ11))))} -> 0 | EJ11: {=IF(EJ$3>'GAAP Summary'!$B$2,0,SUM(INDIRECT(XLOOKUP(EJ$3,'TTM Dates'!$B:$B,'TTM Dates'!$E:$E)&ROW($CJ11)&":"&XLOOKUP(EJ$3,'TTM Dates'!$B:$B,'TTM Dates'!$C:$C)&ROW($CJ11))))} -> 0 | EK11: {=IF(EK$3>'GAAP Summary'!$B$2,0,SUM(INDIRECT(XLOOKUP(EK$3,'TTM Dates'!$B:$B,'TTM Dates'!$E:$E)&ROW($CJ11)&":"&XLOOKUP(EK$3,'TTM Dates'!$B:$B,'TTM Dates'!$C:$C)&ROW($CJ11))))} -> 0 | EL11: {=IF(EL$3>'GAAP Summary'!$B$2,0,SUM(INDIRECT(XLOOKUP(EL$3,'TTM Dates'!$B:$B,'TTM Dates'!$E:$E)&ROW($CJ11)&":"&XLOOKUP(EL$3,'TTM Dates'!$B:$B,'TTM Dates'!$C:$C)&ROW($CJ11))))} -> 0 | ... GL11: {=IF(GL$3>'GAAP Summary'!$B$2,0,SUM(INDIRECT(XLOOKUP(GL$3,'TTM Dates'!$B:$B,'TTM Dates'!$E:$E)&ROW($CJ11)&":"&XLOOKUP(GL$3,'TTM Dates'!$B:$B,'TTM Dates'!$C:$C)&ROW($CJ11))))} -> 0
B12: Data Label | AM12: =IF(AM7=0,"", TEXT(AM7,"0,000")&" "&"("&TEXT((AM7-AA7)/AA7,"0%")&" YoY)") -> 134,400 (-7% YoY) | AN12: =IF(AN7=0,"", TEXT(AN7,"0,000")&" "&"("&TEXT((AN7-AB7)/AB7,"0%")&" YoY)") -> 846,864 (260% YoY) | AO12: =IF(AO7=0,"", TEXT(AO7,"0,000")&" "&"("&TEXT((AO7-AC7)/AC7,"0%")&" YoY)") -> 1,827,624 (-41% YoY) | AP12: =IF(AP7=0,"", TEXT(AP7,"0,000")&" "&"("&TEXT((AP7-AD7)/AD7,"0%")&" YoY)") -> 552,923 (-17% YoY) | AQ12: =IF(AQ7=0,"", TEXT(AQ7,"0,000")&" "&"("&TEXT((AQ7-AE7)/AE7,"0%")&" YoY)") -> 857,590 (-79% YoY) | AR12: =IF(AR7=0,"", TEXT(AR7,"0,000")&" "&"("&TEXT((AR7-AF7)/AF7,"0%")&" YoY)") -> 2,370,127 (-15% YoY) | AS12: =IF(AS7=0,"", TEXT(AS7,"0,000")&" "&"("&TEXT((AS7-AG7)/AG7,"0%")&" YoY)") -> 1,015,910 (-68% YoY) | AT12: =IF(AT7=0,"", TEXT(AT7,"0,000")&" "&"("&TEXT((AT7-AH7)/AH7,"0%")&" YoY)") -> 2,102,478 (543% YoY) | ... CH12: =IF(CH7=0,"", TEXT(CH7,"0,000")&" "&"("&TEXT((CH7-BV7)/BV7,"0%")&" YoY)") | CM12: =IF(CM7=0,"", TEXT(CM7,"0,000")&" "&"("&TEXT((CM7-CS7)/CS7,"0%")&" YoY)") -> 14,213,363 (69% YoY) | CN12: =IF(CN7=0,"", TEXT(CN7,"0,000")&" "&"("&TEXT((CN7-CT7)/CT7,"0%")&" YoY)") -> 8,764,995 (-29% YoY) | CS12: =IF(CS7=0,"", TEXT(CS7,"0,000")&" "&"("&TEXT((CS7-CY7)/CY7,"0%")&" YoY)") -> 8,394,064 (43% YoY) | CT12: =IF(CT7=0,"", TEXT(CT7,"0,000")&" "&"("&TEXT((CT7-CZ7)/CZ7,"0%")&" YoY)") -> 12,379,014 (89% YoY) | CU12: =IF(CU7=0,"", TEXT(CU7,"0,000")&" "&"("&TEXT((CU7-DA7)/DA7,"0%")&" YoY)") -> 12,354,635 (99% YoY) | CV12: =IF(CV7=0,"", TEXT(CV7,"0,000")&" "&"("&TEXT((CV7-DB7)/DB7,"0%")&" YoY)") -> 17,811,213 (87% YoY) | CY12: =IF(CY7=0,"", TEXT(CY7,"0,000")&" "&"("&TEXT((CY7-DE7)/DE7,"0%")&" YoY)") -> 5,881,823 (109% YoY) | CZ12: =IF(CZ7=0,"", TEXT(CZ7,"0,000")&" "&"("&TEXT((CZ7-DF7)/DF7,"0%")&" YoY)") -> 6,544,902 (73% YoY) | DA12: =IF(DA7=0,"", TEXT(DA7,"0,000")&" "&"("&TEXT((DA7-DG7)/DG7,"0%")&" YoY)") -> 6,201,507 (43% YoY) | DB12: =IF(DB7=0,"", TEXT(DB7,"0,000")&" "&"("&TEXT((DB7-DH7)/DH7,"0%")&" YoY)") -> 9,536,879 (17% YoY) | DF12: =DF13*1.25 -> 6983183.8 | DG12: =DG13*1.35 -> 7018367.8 | DH12: =DH13*1.25 -> 6369686.2
B13: Revenue | C13: =C14+C19 -> 0 | D13: =D14+D19 -> 0 | E13: =E14+E19 -> 0 | F13: =F14+F19 -> 0 | G13: =G14+G19 -> 0 | H13: =H14+H19 -> 0 | I13: =I14+I19 -> 0 | J13: =J14+J19 -> 0 | ... Z13: =Z14+Z19 -> 0 | AA13: 1174821 | AB13: 1058642 | AC13: 1382675 | AD13: 1197302 | AE13: 1277152 | AF13: 1539826 | AG13: 1326478 | AH13: 1933412 | AI13: 1626732 | AJ13: 1863172 | AK13: 1785275 | AL13: 1237115 | AM13: 2132202 | AN13: 1943840 | AO13: 2227301 | AP13: 1844526 | AQ13: 1900795 | AR13: 1841226 | AS13: 1634207 | AT13: 1985443 | AU13: 1579141 | AV13: 1868299 | AW13: 1657348 | AX13: 1570102 | AY13: =AY14+AY19 -> 1682341.9 | AZ13: =AZ14+AZ19 -> 1868928.9 | BA13: =BA14+BA19 -> 1912287.5 | BB13: =BB14+BB19 -> 2003722.6 | BC13: =BC14+BC19 -> 1916051.2 | BD13: =BD14+BD19 -> 1831016.7 | BE13: =BE14+BE19 -> 2080921.4 | BF13: =BF14+BF19 -> 2167206.4 | ... CH13: =CH14+CH19 -> 0 | CK13: {=SUM(INDIRECT(XLOOKUP('GAAP Summary'!$B$2,'TTM Dates'!$B:$B,'TTM Dates'!$E:$E)&ROW($CJ13)&":"&XLOOKUP('GAAP Summary'!$B$2,'TTM Dates'!$B:$B,'TTM Dates'!$C:$C)&ROW($CJ13)))} -> 46667706 | CM13: =sum(BW13:BY13) -> 12574241 | CN13: =sum(BZ13:CB13) -> 13644454 | CO13: =sum(CC13:CE13) -> 0 | CP13: =sum(CF13:CH13) -> 0 | CQ13: =sum(BW13:CH13) -> 26218695 | CS13: =sum(BK13:BM13) -> 7423611 | CT13: =sum(BN13:BP13) -> 8042695.1 | CU13: =sum(BQ13:BS13) -> 9498729.3 | CV13: =sum(BT13:BV13) -> 10950282 | CW13: =sum(BK13:BV13) -> 35915317 | CY13: =sum(AY13:BA13) -> 5463558.3 | CZ13: =sum(BB13:BD13) -> 5750790.6 | DA13: =sum(BE13:BG13) -> 6412513.4 | DB13: =sum(BH13:BJ13) -> 7728081.2 | DC13: =sum(AY13:BJ13) -> 25354944 | DE13: =sum(AM13:AO13) -> 6303343 | DF13: =sum(AP13:AR13) -> 5586547 | DG13: =sum(AS13:AU13) -> 5198791 | DH13: =sum(AV13:AX13) -> 5095749 | DI13: =sum(AM13:AX13) -> 22184430 | DK13: =sum(AA13:AC13) -> 3616138 | DL13: =sum(AD13:AF13) -> 4014280 | DM13: =sum(AG13:AI13) -> 4886622 | DN13: =sum(AJ13:AL13) -> 4885562 | DO13: =sum(AA13:AL13) -> 17402602 | DQ13: =SUM(O13:Z13) -> 0 | DS13: {=IF(DS$3>'GAAP Summary'!$B$2,0,SUM(INDIRECT(XLOOKUP(DS$3,'TTM Dates'!$B:$B,'TTM Dates'!$E:$E)&ROW($CJ13)&":"&XLOOKUP(DS$3,'TTM Dates'!$B:$B,'TTM Dates'!$C:$C)&ROW($CJ13))))} -> 0 | DT13: {=IF(DT$3>'GAAP Summary'!$B$2,0,SUM(INDIRECT(XLOOKUP(DT$3,'TTM Dates'!$B:$B,'TTM Dates'!$E:$E)&ROW($CJ13)&":"&XLOOKUP(DT$3,'TTM Dates'!$B:$B,'TTM Dates'!$C:$C)&ROW($CJ13))))} -> 0 | DU13: {=IF(DU$3>'GAAP Summary'!$B$2,0,SUM(INDIRECT(XLOOKUP(DU$3,'TTM Dates'!$B:$B,'TTM Dates'!$E:$E)&ROW($CJ13)&":"&XLOOKUP(DU$3,'TTM Dates'!$B:$B,'TTM Dates'!$C:$C)&ROW($CJ13))))} -> 0 | DV13: {=IF(DV$3>'GAAP Summary'!$B$2,0,SUM(INDIRECT(XLOOKUP(DV$3,'TTM Dates'!$B:$B,'TTM Dates'!$E:$E)&ROW($CJ13)&":"&XLOOKUP(DV$3,'TTM Dates'!$B:$B,'TTM Dates'!$C:$C)&ROW($CJ13))))} -> 0 | DW13: {=IF(DW$3>'GAAP Summary'!$B$2,0,SUM(INDIRECT(XLOOKUP(DW$3,'TTM Dates'!$B:$B,'TTM Dates'!$E:$E)&ROW($CJ13)&":"&XLOOKUP(DW$3,'TTM Dates'!$B:$B,'TTM Dates'!$C:$C)&ROW($CJ13))))} -> 0 | DX13: {=IF(DX$3>'GAAP Summary'!$B$2,0,SUM(INDIRECT(XLOOKUP(DX$3,'TTM Dates'!$B:$B,'TTM Dates'!$E:$E)&ROW($CJ13)&":"&XLOOKUP(DX$3,'TTM Dates'!$B:$B,'TTM Dates'!$C:$C)&ROW($CJ13))))} -> 0 | DY13: {=IF(DY$3>'GAAP Summary'!$B$2,0,SUM(INDIRECT(XLOOKUP(DY$3,'TTM Dates'!$B:$B,'TTM Dates'!$E:$E)&ROW($CJ13)&":"&XLOOKUP(DY$3,'TTM Dates'!$B:$B,'TTM Dates'!$C:$C)&ROW($CJ13))))} -> 0 | DZ13: {=IF(DZ$3>'GAAP Summary'!$B$2,0,SUM(INDIRECT(XLOOKUP(DZ$3,'TTM Dates'!$B:$B,'TTM Dates'!$E:$E)&ROW($CJ13)&":"&XLOOKUP(DZ$3,'TTM Dates'!$B:$B,'TTM Dates'!$C:$C)&ROW($CJ13))))} -> 0 | ... GL13: {=IF(GL$3>'GAAP Summary'!$B$2,0,SUM(INDIRECT(XLOOKUP(GL$3,'TTM Dates'!$B:$B,'TTM Dates'!$E:$E)&ROW($CJ13)&":"&XLOOKUP(GL$3,'TTM Dates'!$B:$B,'TTM Dates'!$C:$C)&ROW($CJ13))))} -> 0
B14: DD | C14: =SUM(C15:C18) -> 0 | D14: =SUM(D15:D18) -> 0 | E14: =SUM(E15:E18) -> 0 | F14: =SUM(F15:F18) -> 0 | G14: =SUM(G15:G18) -> 0 | H14: =SUM(H15:H18) -> 0 | I14: =SUM(I15:I18) -> 0 | J14: =SUM(J15:J18) -> 0 | ... CH14: =SUM(CH15:CH18) -> 0 | CK14: {=SUM(INDIRECT(XLOOKUP('GAAP Summary'!$B$2,'TTM Dates'!$B:$B,'TTM Dates'!$E:$E)&ROW($CJ14)&":"&XLOOKUP('GAAP Summary'!$B$2,'TTM Dates'!$B:$B,'TTM Dates'!$C:$C)&ROW($CJ14)))} -> 13577110 | CM14: =sum(BW14:BY14) -> 3468495.1 | CN14: =sum(BZ14:CB14) -> 4388143.9 | CO14: =sum(CC14:CE14) -> 0 | CP14: =sum(CF14:CH14) -> 0 | CQ14: =sum(BW14:CH14) -> 7856639.1 | CS14: =sum(BK14:BM14) -> 2653528 | CT14: =sum(BN14:BP14) -> 2590280.1 | CU14: =sum(BQ14:BS14) -> 2722537 | CV14: =sum(BT14:BV14) -> 2997934 | CW14: =sum(BK14:BV14) -> 10964279 | CY14: =sum(AY14:BA14) -> 3062767 | CZ14: =sum(BB14:BD14) -> 2411844.2 | DA14: =sum(BE14:BG14) -> 2484964.8 | DB14: =sum(BH14:BJ14) -> 3157902.1 | DC14: =sum(AY14:BJ14) -> 11117478 | DE14: =sum(AM14:AO14) -> 0 | DF14: =sum(AP14:AR14) -> 0 | DG14: =sum(AS14:AU14) -> 0 | DH14: =sum(AV14:AX14) -> 0 | DI14: =sum(AM14:AX14) -> 0 | DK14: =sum(AA14:AC14) -> 0 | DL14: =sum(AD14:AF14) -> 0 | DM14: =sum(AG14:AI14) -> 0 | DN14: =sum(AJ14:AL14) -> 0 | DO14: =sum(AA14:AL14) -> 0 | DS14: {=IF(DS$3>'GAAP Summary'!$B$2,0,SUM(INDIRECT(XLOOKUP(DS$3,'TTM Dates'!$B:$B,'TTM Dates'!$E:$E)&ROW($CJ14)&":"&XLOOKUP(DS$3,'TTM Dates'!$B:$B,'TTM Dates'!$C:$C)&ROW($CJ14))))} -> 0 | DT14: {=IF(DT$3>'GAAP Summary'!$B$2,0,SUM(INDIRECT(XLOOKUP(DT$3,'TTM Dates'!$B:$B,'TTM Dates'!$E:$E)&ROW($CJ14)&":"&XLOOKUP(DT$3,'TTM Dates'!$B:$B,'TTM Dates'!$C:$C)&ROW($CJ14))))} -> 0 | DU14: {=IF(DU$3>'GAAP Summary'!$B$2,0,SUM(INDIRECT(XLOOKUP(DU$3,'TTM Dates'!$B:$B,'TTM Dates'!$E:$E)&ROW($CJ14)&":"&XLOOKUP(DU$3,'TTM Dates'!$B:$B,'TTM Dates'!$C:$C)&ROW($CJ14))))} -> 0 | DV14: {=IF(DV$3>'GAAP Summary'!$B$2,0,SUM(INDIRECT(XLOOKUP(DV$3,'TTM Dates'!$B:$B,'TTM Dates'!$E:$E)&ROW($CJ14)&":"&XLOOKUP(DV$3,'TTM Dates'!$B:$B,'TTM Dates'!$C:$C)&ROW($CJ14))))} -> 0 | DW14: {=IF(DW$3>'GAAP Summary'!$B$2,0,SUM(INDIRECT(XLOOKUP(DW$3,'TTM Dates'!$B:$B,'TTM Dates'!$E:$E)&ROW($CJ14)&":"&XLOOKUP(DW$3,'TTM Dates'!$B:$B,'TTM Dates'!$C:$C)&ROW($CJ14))))} -> 0 | DX14: {=IF(DX$3>'GAAP Summary'!$B$2,0,SUM(INDIRECT(XLOOKUP(DX$3,'TTM Dates'!$B:$B,'TTM Dates'!$E:$E)&ROW($CJ14)&":"&XLOOKUP(DX$3,'TTM Dates'!$B:$B,'TTM Dates'!$C:$C)&ROW($CJ14))))} -> 0 | DY14: {=IF(DY$3>'GAAP Summary'!$B$2,0,SUM(INDIRECT(XLOOKUP(DY$3,'TTM Dates'!$B:$B,'TTM Dates'!$E:$E)&ROW($CJ14)&":"&XLOOKUP(DY$3,'TTM Dates'!$B:$B,'TTM Dates'!$C:$C)&ROW($CJ14))))} -> 0 | DZ14: {=IF(DZ$3>'GAAP Summary'!$B$2,0,SUM(INDIRECT(XLOOKUP(DZ$3,'TTM Dates'!$B:$B,'TTM Dates'!$E:$E)&ROW($CJ14)&":"&XLOOKUP(DZ$3,'TTM Dates'!$B:$B,'TTM Dates'!$C:$C)&ROW($CJ14))))} -> 0 | ... GL14: {=IF(GL$3>'GAAP Summary'!$B$2,0,SUM(INDIRECT(XLOOKUP(GL$3,'TTM Dates'!$B:$B,'TTM Dates'!$E:$E)&ROW($CJ14)&":"&XLOOKUP(GL$3,'TTM Dates'!$B:$B,'TTM Dates'!$C:$C)&ROW($CJ14))))} -> 0
B15: Services | AY15: 830517.09 | AZ15: 966762.28 | BA15: 1023745.7 | BB15: 879742.33 | BC15: 672022.87 | BD15: 621978.96 | BE15: 736704.73 | BF15: 730984.54 | BG15: 781523.54 | BH15: 1033979.3 | BI15: 839033.27 | BJ15: 753392.62 | BK15: 875394 | BL15: 757328 | BM15: 612975 | BN15: 779274 | BO15: 723585 | BP15: 690883 | BQ15: 696347 | BR15: 724050 | BS15: 827944.01 | BT15: 758558.2 | BU15: 715157.84 | BV15: 775176.62 | BW15: 876689.99 | BX15: 930965.7 | BY15: 934939.53 | BZ15: =1178761.51+28660.75 -> 1207422.3 | CA15: =1398699.17-10982.96+36137.21 -> 1423853.4 | CB15: =972695.35+36035.57 -> 1008730.9 | CK15: {=SUM(INDIRECT(XLOOKUP('GAAP Summary'!$B$2,'TTM Dates'!$B:$B,'TTM Dates'!$E:$E)&ROW($CJ15)&":"&XLOOKUP('GAAP Summary'!$B$2,'TTM Dates'!$B:$B,'TTM Dates'!$C:$C)&ROW($CJ15)))} -> 10879835 | CM15: =sum(BW15:BY15) -> 2742595.2 | CN15: =sum(BZ15:CB15) -> 3640006.6 | CO15: =sum(CC15:CE15) -> 0 | CP15: =sum(CF15:CH15) -> 0 | CQ15: =sum(BW15:CH15) -> 6382601.8 | CS15: =sum(BK15:BM15) -> 2245697 | CT15: =sum(BN15:BP15) -> 2193742 | CU15: =sum(BQ15:BS15) -> 2248341 | CV15: =sum(BT15:BV15) -> 2248892.7 | CW15: =sum(BK15:BV15) -> 8936672.7 | CY15: =sum(AY15:BA15) -> 2821025 | CZ15: =sum(BB15:BD15) -> 2173744.2 | DA15: =sum(BE15:BG15) -> 2249212.8 | DB15: =sum(BH15:BJ15) -> 2626405.1 | DC15: =sum(AY15:BJ15) -> 9870387.2 | DE15: =sum(AM15:AO15) -> 0 | DF15: =sum(AP15:AR15) -> 0 | DG15: =sum(AS15:AU15) -> 0 | DH15: =sum(AV15:AX15) -> 0 | DI15: =sum(AM15:AX15) -> 0 | DK15: =sum(AA15:AC15) -> 0 | DL15: =sum(AD15:AF15) -> 0 | DM15: =sum(AG15:AI15) -> 0 | DN15: =sum(AJ15:AL15) -> 0 | DO15: =sum(AA15:AL15) -> 0 | DS15: {=IF(DS$3>'GAAP Summary'!$B$2,0,SUM(INDIRECT(XLOOKUP(DS$3,'TTM Dates'!$B:$B,'TTM Dates'!$E:$E)&ROW($CJ15)&":"&XLOOKUP(DS$3,'TTM Dates'!$B:$B,'TTM Dates'!$C:$C)&ROW($CJ15))))} -> 0 | DT15: {=IF(DT$3>'GAAP Summary'!$B$2,0,SUM(INDIRECT(XLOOKUP(DT$3,'TTM Dates'!$B:$B,'TTM Dates'!$E:$E)&ROW($CJ15)&":"&XLOOKUP(DT$3,'TTM Dates'!$B:$B,'TTM Dates'!$C:$C)&ROW($CJ15))))} -> 0 | DU15: {=IF(DU$3>'GAAP Summary'!$B$2,0,SUM(INDIRECT(XLOOKUP(DU$3,'TTM Dates'!$B:$B,'TTM Dates'!$E:$E)&ROW($CJ15)&":"&XLOOKUP(DU$3,'TTM Dates'!$B:$B,'TTM Dates'!$C:$C)&ROW($CJ15))))} -> 0 | DV15: {=IF(DV$3>'GAAP Summary'!$B$2,0,SUM(INDIRECT(XLOOKUP(DV$3,'TTM Dates'!$B:$B,'TTM Dates'!$E:$E)&ROW($CJ15)&":"&XLOOKUP(DV$3,'TTM Dates'!$B:$B,'TTM Dates'!$C:$C)&ROW($CJ15))))} -> 0 | DW15: {=IF(DW$3>'GAAP Summary'!$B$2,0,SUM(INDIRECT(XLOOKUP(DW$3,'TTM Dates'!$B:$B,'TTM Dates'!$E:$E)&ROW($CJ15)&":"&XLOOKUP(DW$3,'TTM Dates'!$B:$B,'TTM Dates'!$C:$C)&ROW($CJ15))))} -> 0 | DX15: {=IF(DX$3>'GAAP Summary'!$B$2,0,SUM(INDIRECT(XLOOKUP(DX$3,'TTM Dates'!$B:$B,'TTM Dates'!$E:$E)&ROW($CJ15)&":"&XLOOKUP(DX$3,'TTM Dates'!$B:$B,'TTM Dates'!$C:$C)&ROW($CJ15))))} -> 0 | DY15: {=IF(DY$3>'GAAP Summary'!$B$2,0,SUM(INDIRECT(XLOOKUP(DY$3,'TTM Dates'!$B:$B,'TTM Dates'!$E:$E)&ROW($CJ15)&":"&XLOOKUP(DY$3,'TTM Dates'!$B:$B,'TTM Dates'!$C:$C)&ROW($CJ15))))} -> 0 | DZ15: {=IF(DZ$3>'GAAP Summary'!$B$2,0,SUM(INDIRECT(XLOOKUP(DZ$3,'TTM Dates'!$B:$B,'TTM Dates'!$E:$E)&ROW($CJ15)&":"&XLOOKUP(DZ$3,'TTM Dates'!$B:$B,'TTM Dates'!$C:$C)&ROW($CJ15))))} -> 0 | ... GL15: {=IF(GL$3>'GAAP Summary'!$B$2,0,SUM(INDIRECT(XLOOKUP(GL$3,'TTM Dates'!$B:$B,'TTM Dates'!$E:$E)&ROW($CJ15)&":"&XLOOKUP(GL$3,'TTM Dates'!$B:$B,'TTM Dates'!$C:$C)&ROW($CJ15))))} -> 0
B16: Software | AY16: 80743 | AZ16: 79623 | BA16: 81376 | BB16: 72606 | BC16: 79646 | BD16: 72514 | BE16: 74182 | BF16: 74307 | BG16: 75211 | BH16: 87133 | BI16: 86683 | BJ16: 86797 | BK16: 127809 | BL16: 84064 | BM16: 93790 | BN16: 77607 | BO16: 48652 | BP16: 45404 | BQ16: 50745.93 | BR16: 66270.69 | BS16: 69253.69 | BT16: 69413.5 | BU16: 95773.09 | BV16: 70032.69 | BW16: 84906.83 | BX16: 89329.83 | BY16: 87046.32 | BZ16: 81991.83 | CA16: 86060.79 | CB16: 78619.8 | CK16: {=SUM(INDIRECT(XLOOKUP('GAAP Summary'!$B$2,'TTM Dates'!$B:$B,'TTM Dates'!$E:$E)&ROW($CJ16)&":"&XLOOKUP('GAAP Summary'!$B$2,'TTM Dates'!$B:$B,'TTM Dates'!$C:$C)&ROW($CJ16)))} -> 929444.99 | CM16: =sum(BW16:BY16) -> 261282.98 | CN16: =sum(BZ16:CB16) -> 246672.42 | CO16: =sum(CC16:CE16) -> 0 | CP16: =sum(CF16:CH16) -> 0 | CQ16: =sum(BW16:CH16) -> 507955.4 | CS16: =sum(BK16:BM16) -> 305663 | CT16: =sum(BN16:BP16) -> 171663 | CU16: =sum(BQ16:BS16) -> 186270.31 | CV16: =sum(BT16:BV16) -> 235219.28 | CW16: =sum(BK16:BV16) -> 898815.59 | CY16: =sum(AY16:BA16) -> 241742 | CZ16: =sum(BB16:BD16) -> 224766 | DA16: =sum(BE16:BG16) -> 223700 | DB16: =sum(BH16:BJ16) -> 260613 | DC16: =sum(AY16:BJ16) -> 950821 | DE16: =sum(AM16:AO16) -> 0 | DF16: =sum(AP16:AR16) -> 0 | DG16: =sum(AS16:AU16) -> 0 | DH16: =sum(AV16:AX16) -> 0 | DI16: =sum(AM16:AX16) -> 0 | DK16: =sum(AA16:AC16) -> 0 | DL16: =sum(AD16:AF16) -> 0 | DM16: =sum(AG16:AI16) -> 0 | DN16: =sum(AJ16:AL16) -> 0 | DO16: =sum(AA16:AL16) -> 0 | DS16: {=IF(DS$3>'GAAP Summary'!$B$2,0,SUM(INDIRECT(XLOOKUP(DS$3,'TTM Dates'!$B:$B,'TTM Dates'!$E:$E)&ROW($CJ16)&":"&XLOOKUP(DS$3,'TTM Dates'!$B:$B,'TTM Dates'!$C:$C)&ROW($CJ16))))} -> 0 | DT16: {=IF(DT$3>'GAAP Summary'!$B$2,0,SUM(INDIRECT(XLOOKUP(DT$3,'TTM Dates'!$B:$B,'TTM Dates'!$E:$E)&ROW($CJ16)&":"&XLOOKUP(DT$3,'TTM Dates'!$B:$B,'TTM Dates'!$C:$C)&ROW($CJ16))))} -> 0 | DU16: {=IF(DU$3>'GAAP Summary'!$B$2,0,SUM(INDIRECT(XLOOKUP(DU$3,'TTM Dates'!$B:$B,'TTM Dates'!$E:$E)&ROW($CJ16)&":"&XLOOKUP(DU$3,'TTM Dates'!$B:$B,'TTM Dates'!$C:$C)&ROW($CJ16))))} -> 0 | DV16: {=IF(DV$3>'GAAP Summary'!$B$2,0,SUM(INDIRECT(XLOOKUP(DV$3,'TTM Dates'!$B:$B,'TTM Dates'!$E:$E)&ROW($CJ16)&":"&XLOOKUP(DV$3,'TTM Dates'!$B:$B,'TTM Dates'!$C:$C)&ROW($CJ16))))} -> 0 | DW16: {=IF(DW$3>'GAAP Summary'!$B$2,0,SUM(INDIRECT(XLOOKUP(DW$3,'TTM Dates'!$B:$B,'TTM Dates'!$E:$E)&ROW($CJ16)&":"&XLOOKUP(DW$3,'TTM Dates'!$B:$B,'TTM Dates'!$C:$C)&ROW($CJ16))))} -> 0 | DX16: {=IF(DX$3>'GAAP Summary'!$B$2,0,SUM(INDIRECT(XLOOKUP(DX$3,'TTM Dates'!$B:$B,'TTM Dates'!$E:$E)&ROW($CJ16)&":"&XLOOKUP(DX$3,'TTM Dates'!$B:$B,'TTM Dates'!$C:$C)&ROW($CJ16))))} -> 0 | DY16: {=IF(DY$3>'GAAP Summary'!$B$2,0,SUM(INDIRECT(XLOOKUP(DY$3,'TTM Dates'!$B:$B,'TTM Dates'!$E:$E)&ROW($CJ16)&":"&XLOOKUP(DY$3,'TTM Dates'!$B:$B,'TTM Dates'!$C:$C)&ROW($CJ16))))} -> 0 | DZ16: {=IF(DZ$3>'GAAP Summary'!$B$2,0,SUM(INDIRECT(XLOOKUP(DZ$3,'TTM Dates'!$B:$B,'TTM Dates'!$E:$E)&ROW($CJ16)&":"&XLOOKUP(DZ$3,'TTM Dates'!$B:$B,'TTM Dates'!$C:$C)&ROW($CJ16))))} -> 0 | ... GL16: {=IF(GL$3>'GAAP Summary'!$B$2,0,SUM(INDIRECT(XLOOKUP(GL$3,'TTM Dates'!$B:$B,'TTM Dates'!$E:$E)&ROW($CJ16)&":"&XLOOKUP(GL$3,'TTM Dates'!$B:$B,'TTM Dates'!$C:$C)&ROW($CJ16))))} -> 0
B17: Managed DD | AY17: 0 | AZ17: 0 | BA17: 0 | BB17: 0 | BC17: 6667 | BD17: 6667 | BE17: 6667 | BF17: 0 | BG17: 5385 | BH17: 88580 | BI17: 88580 | BJ17: 93724 | BK17: 35588 | BL17: 33290 | BM17: 33290 | BN17: 33290.15 | BO17: 48290.15 | BP17: 48290.15 | BQ17: 48290.15 | BR17: 48290.15 | BS17: 54540.12 | BT17: 92612.38 | BU17: 103862.28 | BV17: 98718.08 | BW17: 98718.08 | BX17: 57884.79 | BY17: 58718.08 | BZ17: 64968.08 | CA17: 72468.07 | CB17: 72468.07 | CK17: {=SUM(INDIRECT(XLOOKUP('GAAP Summary'!$B$2,'TTM Dates'!$B:$B,'TTM Dates'!$E:$E)&ROW($CJ17)&":"&XLOOKUP('GAAP Summary'!$B$2,'TTM Dates'!$B:$B,'TTM Dates'!$C:$C)&ROW($CJ17)))} -> 871538.33 | CM17: =sum(BW17:BY17) -> 215320.95 | CN17: =sum(BZ17:CB17) -> 209904.22 | CO17: =sum(CC17:CE17) -> 0 | CP17: =sum(CF17:CH17) -> 0 | CQ17: =sum(BW17:CH17) -> 425225.17 | CS17: =sum(BK17:BM17) -> 102168 | CT17: =sum(BN17:BP17) -> 129870.45 | CU17: =sum(BQ17:BS17) -> 151120.42 | CV17: =sum(BT17:BV17) -> 295192.74 | CW17: =sum(BK17:BV17) -> 678351.61 | CY17: =sum(AY17:BA17) -> 0 | CZ17: =sum(BB17:BD17) -> 13334 | DA17: =sum(BE17:BG17) -> 12052 | DB17: =sum(BH17:BJ17) -> 270884 | DC17: =sum(AY17:BJ17) -> 296270 | DE17: =sum(AM17:AO17) -> 0 | DF17: =sum(AP17:AR17) -> 0 | DG17: =sum(AS17:AU17) -> 0 | DH17: =sum(AV17:AX17) -> 0 | DI17: =sum(AM17:AX17) -> 0 | DK17: =sum(AA17:AC17) -> 0 | DL17: =sum(AD17:AF17) -> 0 | DM17: =sum(AG17:AI17) -> 0 | DN17: =sum(AJ17:AL17) -> 0 | DO17: =sum(AA17:AL17) -> 0 | DS17: {=IF(DS$3>'GAAP Summary'!$B$2,0,SUM(INDIRECT(XLOOKUP(DS$3,'TTM Dates'!$B:$B,'TTM Dates'!$E:$E)&ROW($CJ17)&":"&XLOOKUP(DS$3,'TTM Dates'!$B:$B,'TTM Dates'!$C:$C)&ROW($CJ17))))} -> 0 | DT17: {=IF(DT$3>'GAAP Summary'!$B$2,0,SUM(INDIRECT(XLOOKUP(DT$3,'TTM Dates'!$B:$B,'TTM Dates'!$E:$E)&ROW($CJ17)&":"&XLOOKUP(DT$3,'TTM Dates'!$B:$B,'TTM Dates'!$C:$C)&ROW($CJ17))))} -> 0 | DU17: {=IF(DU$3>'GAAP Summary'!$B$2,0,SUM(INDIRECT(XLOOKUP(DU$3,'TTM Dates'!$B:$B,'TTM Dates'!$E:$E)&ROW($CJ17)&":"&XLOOKUP(DU$3,'TTM Dates'!$B:$B,'TTM Dates'!$C:$C)&ROW($CJ17))))} -> 0 | DV17: {=IF(DV$3>'GAAP Summary'!$B$2,0,SUM(INDIRECT(XLOOKUP(DV$3,'TTM Dates'!$B:$B,'TTM Dates'!$E:$E)&ROW($CJ17)&":"&XLOOKUP(DV$3,'TTM Dates'!$B:$B,'TTM Dates'!$C:$C)&ROW($CJ17))))} -> 0 | DW17: {=IF(DW$3>'GAAP Summary'!$B$2,0,SUM(INDIRECT(XLOOKUP(DW$3,'TTM Dates'!$B:$B,'TTM Dates'!$E:$E)&ROW($CJ17)&":"&XLOOKUP(DW$3,'TTM Dates'!$B:$B,'TTM Dates'!$C:$C)&ROW($CJ17))))} -> 0 | DX17: {=IF(DX$3>'GAAP Summary'!$B$2,0,SUM(INDIRECT(XLOOKUP(DX$3,'TTM Dates'!$B:$B,'TTM Dates'!$E:$E)&ROW($CJ17)&":"&XLOOKUP(DX$3,'TTM Dates'!$B:$B,'TTM Dates'!$C:$C)&ROW($CJ17))))} -> 0 | DY17: {=IF(DY$3>'GAAP Summary'!$B$2,0,SUM(INDIRECT(XLOOKUP(DY$3,'TTM Dates'!$B:$B,'TTM Dates'!$E:$E)&ROW($CJ17)&":"&XLOOKUP(DY$3,'TTM Dates'!$B:$B,'TTM Dates'!$C:$C)&ROW($CJ17))))} -> 0 | DZ17: {=IF(DZ$3>'GAAP Summary'!$B$2,0,SUM(INDIRECT(XLOOKUP(DZ$3,'TTM Dates'!$B:$B,'TTM Dates'!$E:$E)&ROW($CJ17)&":"&XLOOKUP(DZ$3,'TTM Dates'!$B:$B,'TTM Dates'!$C:$C)&ROW($CJ17))))} -> 0 | ... GL17: {=IF(GL$3>'GAAP Summary'!$B$2,0,SUM(INDIRECT(XLOOKUP(GL$3,'TTM Dates'!$B:$B,'TTM Dates'!$E:$E)&ROW($CJ17)&":"&XLOOKUP(GL$3,'TTM Dates'!$B:$B,'TTM Dates'!$C:$C)&ROW($CJ17))))} -> 0
B18: Managed SOC | BN18: 14801.17 | BO18: 40101.75 | BP18: 40101.75 | BQ18: 45601.75 | BR18: 45601.75 | BS18: 45601.75 | BT18: 70098.66 | BU18: 70098.66 | BV18: 78431.99 | BW18: 78431.99 | BX18: 85431.99 | BY18: 85431.99 | BZ18: 85431.99 | CA18: 98897.69 | CB18: 107231.02 | CK18: {=SUM(INDIRECT(XLOOKUP('GAAP Summary'!$B$2,'TTM Dates'!$B:$B,'TTM Dates'!$E:$E)&ROW($CJ18)&":"&XLOOKUP('GAAP Summary'!$B$2,'TTM Dates'!$B:$B,'TTM Dates'!$C:$C)&ROW($CJ18)))} -> 896291.23 | CM18: =sum(BW18:BY18) -> 249295.97 | CN18: =sum(BZ18:CB18) -> 291560.7 | CO18: =sum(CC18:CE18) -> 0 | CP18: =sum(CF18:CH18) -> 0 | CQ18: =sum(BW18:CH18) -> 540856.67 | CS18: =sum(BK18:BM18) -> 0 | CT18: =sum(BN18:BP18) -> 95004.67 | CU18: =sum(BQ18:BS18) -> 136805.25 | CV18: =sum(BT18:BV18) -> 218629.31 | CW18: =sum(BK18:BV18) -> 450439.23 | CY18: =sum(AY18:BA18) -> 0 | CZ18: =sum(BB18:BD18) -> 0 | DA18: =sum(BE18:BG18) -> 0 | DB18: =sum(BH18:BJ18) -> 0 | DC18: =sum(AY18:BJ18) -> 0 | DE18: =sum(AM18:AO18) -> 0 | DF18: =sum(AP18:AR18) -> 0 | DG18: =sum(AS18:AU18) -> 0 | DH18: =sum(AV18:AX18) -> 0 | DI18: =sum(AM18:AX18) -> 0 | DK18: =sum(AA18:AC18) -> 0 | DL18: =sum(AD18:AF18) -> 0 | DM18: =sum(AG18:AI18) -> 0 | DN18: =sum(AJ18:AL18) -> 0 | DO18: =sum(AA18:AL18) -> 0
B19: SN | C19: =SUM(C20:C22) -> 0 | D19: =SUM(D20:D22) -> 0 | E19: =SUM(E20:E22) -> 0 | F19: =SUM(F20:F22) -> 0 | G19: =SUM(G20:G22) -> 0 | H19: =SUM(H20:H22) -> 0 | I19: =SUM(I20:I22) -> 0 | J19: =SUM(J20:J22) -> 0 | ... CH19: =SUM(CH20:CH22) -> 0 | CK19: {=SUM(INDIRECT(XLOOKUP('GAAP Summary'!$B$2,'TTM Dates'!$B:$B,'TTM Dates'!$E:$E)&ROW($CJ19)&":"&XLOOKUP('GAAP Summary'!$B$2,'TTM Dates'!$B:$B,'TTM Dates'!$C:$C)&ROW($CJ19)))} -> 33090596 | CM19: =sum(BW19:BY19) -> 9105745.6 | CN19: =sum(BZ19:CB19) -> 9256310 | CO19: =sum(CC19:CE19) -> 0 | CP19: =sum(CF19:CH19) -> 0 | CQ19: =sum(BW19:CH19) -> 18362056 | CS19: =sum(BK19:BM19) -> 4770083 | CT19: =sum(BN19:BP19) -> 5452415 | CU19: =sum(BQ19:BS19) -> 6776192.3 | CV19: =sum(BT19:BV19) -> 7952347.7 | CW19: =sum(BK19:BV19) -> 24951038 | CY19: =sum(AY19:BA19) -> 2400791.3 | CZ19: =sum(BB19:BD19) -> 3338946.4 | DA19: =sum(BE19:BG19) -> 3927548.6 | DB19: =sum(BH19:BJ19) -> 4570179.1 | DC19: =sum(AY19:BJ19) -> 14237465 | DE19: =sum(AM19:AO19) -> 0 | DF19: =sum(AP19:AR19) -> 0 | DG19: =sum(AS19:AU19) -> 0 | DH19: =sum(AV19:AX19) -> 0 | DI19: =sum(AM19:AX19) -> 0 | DS19: {=IF(DS$3>'GAAP Summary'!$B$2,0,SUM(INDIRECT(XLOOKUP(DS$3,'TTM Dates'!$B:$B,'TTM Dates'!$E:$E)&ROW($CJ19)&":"&XLOOKUP(DS$3,'TTM Dates'!$B:$B,'TTM Dates'!$C:$C)&ROW($CJ19))))} -> 0 | DT19: {=IF(DT$3>'GAAP Summary'!$B$2,0,SUM(INDIRECT(XLOOKUP(DT$3,'TTM Dates'!$B:$B,'TTM Dates'!$E:$E)&ROW($CJ19)&":"&XLOOKUP(DT$3,'TTM Dates'!$B:$B,'TTM Dates'!$C:$C)&ROW($CJ19))))} -> 0 | DU19: {=IF(DU$3>'GAAP Summary'!$B$2,0,SUM(INDIRECT(XLOOKUP(DU$3,'TTM Dates'!$B:$B,'TTM Dates'!$E:$E)&ROW($CJ19)&":"&XLOOKUP(DU$3,'TTM Dates'!$B:$B,'TTM Dates'!$C:$C)&ROW($CJ19))))} -> 0 | DV19: {=IF(DV$3>'GAAP Summary'!$B$2,0,SUM(INDIRECT(XLOOKUP(DV$3,'TTM Dates'!$B:$B,'TTM Dates'!$E:$E)&ROW($CJ19)&":"&XLOOKUP(DV$3,'TTM Dates'!$B:$B,'TTM Dates'!$C:$C)&ROW($CJ19))))} -> 0 | DW19: {=IF(DW$3>'GAAP Summary'!$B$2,0,SUM(INDIRECT(XLOOKUP(DW$3,'TTM Dates'!$B:$B,'TTM Dates'!$E:$E)&ROW($CJ19)&":"&XLOOKUP(DW$3,'TTM Dates'!$B:$B,'TTM Dates'!$C:$C)&ROW($CJ19))))} -> 0 | DX19: {=IF(DX$3>'GAAP Summary'!$B$2,0,SUM(INDIRECT(XLOOKUP(DX$3,'TTM Dates'!$B:$B,'TTM Dates'!$E:$E)&ROW($CJ19)&":"&XLOOKUP(DX$3,'TTM Dates'!$B:$B,'TTM Dates'!$C:$C)&ROW($CJ19))))} -> 0 | DY19: {=IF(DY$3>'GAAP Summary'!$B$2,0,SUM(INDIRECT(XLOOKUP(DY$3,'TTM Dates'!$B:$B,'TTM Dates'!$E:$E)&ROW($CJ19)&":"&XLOOKUP(DY$3,'TTM Dates'!$B:$B,'TTM Dates'!$C:$C)&ROW($CJ19))))} -> 0 | DZ19: {=IF(DZ$3>'GAAP Summary'!$B$2,0,SUM(INDIRECT(XLOOKUP(DZ$3,'TTM Dates'!$B:$B,'TTM Dates'!$E:$E)&ROW($CJ19)&":"&XLOOKUP(DZ$3,'TTM Dates'!$B:$B,'TTM Dates'!$C:$C)&ROW($CJ19))))} -> 0 | ... GL19: {=IF(GL$3>'GAAP Summary'!$B$2,0,SUM(INDIRECT(XLOOKUP(GL$3,'TTM Dates'!$B:$B,'TTM Dates'!$E:$E)&ROW($CJ19)&":"&XLOOKUP(GL$3,'TTM Dates'!$B:$B,'TTM Dates'!$C:$C)&ROW($CJ19))))} -> 0
B20: Services | AY20: 771081.83 | AZ20: 769743.59 | BA20: 807165.84 | BB20: 1051374.3 | BC20: 1157715.4 | BD20: 1129856.8 | BE20: 1257534.6 | BF20: 1356081.8 | BG20: 1296433.1 | BH20: 1615619.4 | BI20: 1448123.6 | BJ20: 1488937.1 | BK20: 1533472 | BL20: 1536951 | BM20: 1682161 | BN20: 1798995 | BO20: 1781972 | BP20: 1853949 | BQ20: 2268372 | BR20: 2040001 | BS20: 2467819.4 | BT20: 3001139.8 | BU20: 2302939.9 | BV20: 2467373.7 | BW20: 2942831.8 | BX20: 2880949.1 | BY20: 3280298 | BZ20: =2585543.06+560383.68 -> 3145926.7 | CA20: =2457304.79+216386.75 -> 2673691.5 | CB20: =3393716.51+29780.3+9861.58 -> 3433358.4 | CK20: {=SUM(INDIRECT(XLOOKUP('GAAP Summary'!$B$2,'TTM Dates'!$B:$B,'TTM Dates'!$E:$E)&ROW($CJ20)&":"&XLOOKUP('GAAP Summary'!$B$2,'TTM Dates'!$B:$B,'TTM Dates'!$C:$C)&ROW($CJ20)))} -> 32904701 | CM20: =sum(BW20:BY20) -> 9104079 | CN20: =sum(BZ20:CB20) -> 9252976.7 | CO20: =sum(CC20:CE20) -> 0 | CP20: =sum(CF20:CH20) -> 0 | CQ20: =sum(BW20:CH20) -> 18357056 | CS20: =sum(BK20:BM20) -> 4752584 | CT20: =sum(BN20:BP20) -> 5434916 | CU20: =sum(BQ20:BS20) -> 6776192.3 | CV20: =sum(BT20:BV20) -> 7771453.4 | CW20: =sum(BK20:BV20) -> 24735146 | CY20: =sum(AY20:BA20) -> 2347991.3 | CZ20: =sum(BB20:BD20) -> 3338946.4 | DA20: =sum(BE20:BG20) -> 3910049.6 | DB20: =sum(BH20:BJ20) -> 4552680.1 | DC20: =sum(AY20:BJ20) -> 14149667 | DE20: =sum(AM20:AO20) -> 0 | DF20: =sum(AP20:AR20) -> 0 | DG20: =sum(AS20:AU20) -> 0 | DH20: =sum(AV20:AX20) -> 0 | DI20: =sum(AM20:AX20) -> 0 | DK20: =sum(AA20:AC20) -> 0 | DL20: =sum(AD20:AF20) -> 0 | DM20: =sum(AG20:AI20) -> 0 | DN20: =sum(AJ20:AL20) -> 0 | DO20: =sum(AA20:AL20) -> 0 | DS20: {=IF(DS$3>'GAAP Summary'!$B$2,0,SUM(INDIRECT(XLOOKUP(DS$3,'TTM Dates'!$B:$B,'TTM Dates'!$E:$E)&ROW($CJ20)&":"&XLOOKUP(DS$3,'TTM Dates'!$B:$B,'TTM Dates'!$C:$C)&ROW($CJ20))))} -> 0 | DT20: {=IF(DT$3>'GAAP Summary'!$B$2,0,SUM(INDIRECT(XLOOKUP(DT$3,'TTM Dates'!$B:$B,'TTM Dates'!$E:$E)&ROW($CJ20)&":"&XLOOKUP(DT$3,'TTM Dates'!$B:$B,'TTM Dates'!$C:$C)&ROW($CJ20))))} -> 0 | DU20: {=IF(DU$3>'GAAP Summary'!$B$2,0,SUM(INDIRECT(XLOOKUP(DU$3,'TTM Dates'!$B:$B,'TTM Dates'!$E:$E)&ROW($CJ20)&":"&XLOOKUP(DU$3,'TTM Dates'!$B:$B,'TTM Dates'!$C:$C)&ROW($CJ20))))} -> 0 | DV20: {=IF(DV$3>'GAAP Summary'!$B$2,0,SUM(INDIRECT(XLOOKUP(DV$3,'TTM Dates'!$B:$B,'TTM Dates'!$E:$E)&ROW($CJ20)&":"&XLOOKUP(DV$3,'TTM Dates'!$B:$B,'TTM Dates'!$C:$C)&ROW($CJ20))))} -> 0 | DW20: {=IF(DW$3>'GAAP Summary'!$B$2,0,SUM(INDIRECT(XLOOKUP(DW$3,'TTM Dates'!$B:$B,'TTM Dates'!$E:$E)&ROW($CJ20)&":"&XLOOKUP(DW$3,'TTM Dates'!$B:$B,'TTM Dates'!$C:$C)&ROW($CJ20))))} -> 0 | DX20: {=IF(DX$3>'GAAP Summary'!$B$2,0,SUM(INDIRECT(XLOOKUP(DX$3,'TTM Dates'!$B:$B,'TTM Dates'!$E:$E)&ROW($CJ20)&":"&XLOOKUP(DX$3,'TTM Dates'!$B:$B,'TTM Dates'!$C:$C)&ROW($CJ20))))} -> 0 | DY20: {=IF(DY$3>'GAAP Summary'!$B$2,0,SUM(INDIRECT(XLOOKUP(DY$3,'TTM Dates'!$B:$B,'TTM Dates'!$E:$E)&ROW($CJ20)&":"&XLOOKUP(DY$3,'TTM Dates'!$B:$B,'TTM Dates'!$C:$C)&ROW($CJ20))))} -> 0 | DZ20: {=IF(DZ$3>'GAAP Summary'!$B$2,0,SUM(INDIRECT(XLOOKUP(DZ$3,'TTM Dates'!$B:$B,'TTM Dates'!$E:$E)&ROW($CJ20)&":"&XLOOKUP(DZ$3,'TTM Dates'!$B:$B,'TTM Dates'!$C:$C)&ROW($CJ20))))} -> 0 | ... GL20: {=IF(GL$3>'GAAP Summary'!$B$2,0,SUM(INDIRECT(XLOOKUP(GL$3,'TTM Dates'!$B:$B,'TTM Dates'!$E:$E)&ROW($CJ20)&":"&XLOOKUP(GL$3,'TTM Dates'!$B:$B,'TTM Dates'!$C:$C)&ROW($CJ20))))} -> 0
B21: Software | AY21: 0 | AZ21: 52800 | BA21: 0 | BB21: 0 | BC21: 0 | BD21: 0 | BE21: 5833 | BF21: 5833 | BG21: 5833 | BH21: 5833 | BI21: 5833 | BJ21: 5833 | BK21: 5833 | BL21: 5833 | BM21: 5833 | BN21: 5833 | BO21: 5833 | BP21: 5833 | BQ21: 0 | BS21: 0 | BT21: 29269.17 | BV21: 151625.04 | BY21: 1666.67 | BZ21: 1666.67 | CB21: 1666.67 | CK21: {=SUM(INDIRECT(XLOOKUP('GAAP Summary'!$B$2,'TTM Dates'!$B:$B,'TTM Dates'!$E:$E)&ROW($CJ21)&":"&XLOOKUP('GAAP Summary'!$B$2,'TTM Dates'!$B:$B,'TTM Dates'!$C:$C)&ROW($CJ21)))} -> 185894.22 | CM21: =sum(BW21:BY21) -> 1666.67 | CN21: =sum(BZ21:CB21) -> 3333.34 | CO21: =sum(CC21:CE21) -> 0 | CP21: =sum(CF21:CH21) -> 0 | CQ21: =sum(BW21:CH21) -> 5000.01 | CS21: =sum(BK21:BM21) -> 17499 | CT21: =sum(BN21:BP21) -> 17499 | CU21: =sum(BQ21:BS21) -> 0 | CV21: =sum(BT21:BV21) -> 180894.21 | CW21: =sum(BK21:BV21) -> 215892.21 | CY21: =sum(AY21:BA21) -> 52800 | CZ21: =sum(BB21:BD21) -> 0 | DA21: =sum(BE21:BG21) -> 17499 | DB21: =sum(BH21:BJ21) -> 17499 | DC21: =sum(AY21:BJ21) -> 87798 | DE21: =sum(AM21:AO21) -> 0 | DF21: =sum(AP21:AR21) -> 0 | DG21: =sum(AS21:AU21) -> 0 | DH21: =sum(AV21:AX21) -> 0 | DI21: =sum(AM21:AX21) -> 0 | DK21: =sum(AA21:AC21) -> 0 | DL21: =sum(AD21:AF21) -> 0 | DM21: =sum(AG21:AI21) -> 0 | DN21: =sum(AJ21:AL21) -> 0 | DO21: =sum(AA21:AL21) -> 0 | DS21: {=IF(DS$3>'GAAP Summary'!$B$2,0,SUM(INDIRECT(XLOOKUP(DS$3,'TTM Dates'!$B:$B,'TTM Dates'!$E:$E)&ROW($CJ21)&":"&XLOOKUP(DS$3,'TTM Dates'!$B:$B,'TTM Dates'!$C:$C)&ROW($CJ21))))} -> 0 | DT21: {=IF(DT$3>'GAAP Summary'!$B$2,0,SUM(INDIRECT(XLOOKUP(DT$3,'TTM Dates'!$B:$B,'TTM Dates'!$E:$E)&ROW($CJ21)&":"&XLOOKUP(DT$3,'TTM Dates'!$B:$B,'TTM Dates'!$C:$C)&ROW($CJ21))))} -> 0 | DU21: {=IF(DU$3>'GAAP Summary'!$B$2,0,SUM(INDIRECT(XLOOKUP(DU$3,'TTM Dates'!$B:$B,'TTM Dates'!$E:$E)&ROW($CJ21)&":"&XLOOKUP(DU$3,'TTM Dates'!$B:$B,'TTM Dates'!$C:$C)&ROW($CJ21))))} -> 0 | DV21: {=IF(DV$3>'GAAP Summary'!$B$2,0,SUM(INDIRECT(XLOOKUP(DV$3,'TTM Dates'!$B:$B,'TTM Dates'!$E:$E)&ROW($CJ21)&":"&XLOOKUP(DV$3,'TTM Dates'!$B:$B,'TTM Dates'!$C:$C)&ROW($CJ21))))} -> 0 | DW21: {=IF(DW$3>'GAAP Summary'!$B$2,0,SUM(INDIRECT(XLOOKUP(DW$3,'TTM Dates'!$B:$B,'TTM Dates'!$E:$E)&ROW($CJ21)&":"&XLOOKUP(DW$3,'TTM Dates'!$B:$B,'TTM Dates'!$C:$C)&ROW($CJ21))))} -> 0 | DX21: {=IF(DX$3>'GAAP Summary'!$B$2,0,SUM(INDIRECT(XLOOKUP(DX$3,'TTM Dates'!$B:$B,'TTM Dates'!$E:$E)&ROW($CJ21)&":"&XLOOKUP(DX$3,'TTM Dates'!$B:$B,'TTM Dates'!$C:$C)&ROW($CJ21))))} -> 0 | DY21: {=IF(DY$3>'GAAP Summary'!$B$2,0,SUM(INDIRECT(XLOOKUP(DY$3,'TTM Dates'!$B:$B,'TTM Dates'!$E:$E)&ROW($CJ21)&":"&XLOOKUP(DY$3,'TTM Dates'!$B:$B,'TTM Dates'!$C:$C)&ROW($CJ21))))} -> 0 | DZ21: {=IF(DZ$3>'GAAP Summary'!$B$2,0,SUM(INDIRECT(XLOOKUP(DZ$3,'TTM Dates'!$B:$B,'TTM Dates'!$E:$E)&ROW($CJ21)&":"&XLOOKUP(DZ$3,'TTM Dates'!$B:$B,'TTM Dates'!$C:$C)&ROW($CJ21))))} -> 0 | ... GL21: {=IF(GL$3>'GAAP Summary'!$B$2,0,SUM(INDIRECT(XLOOKUP(GL$3,'TTM Dates'!$B:$B,'TTM Dates'!$E:$E)&ROW($CJ21)&":"&XLOOKUP(GL$3,'TTM Dates'!$B:$B,'TTM Dates'!$C:$C)&ROW($CJ21))))} -> 0
B22: MSP | BS22: 0 | CK22: {=SUM(INDIRECT(XLOOKUP('GAAP Summary'!$B$2,'TTM Dates'!$B:$B,'TTM Dates'!$E:$E)&ROW($CJ22)&":"&XLOOKUP('GAAP Summary'!$B$2,'TTM Dates'!$B:$B,'TTM Dates'!$C:$C)&ROW($CJ22)))} -> 0 | CM22: =sum(BW22:BY22) -> 0 | CN22: =sum(BZ22:CB22) -> 0 | CO22: =sum(CC22:CE22) -> 0 | CP22: =sum(CF22:CH22) -> 0 | CQ22: =sum(BW22:CH22) -> 0 | CS22: =sum(BK22:BM22) -> 0 | CT22: =sum(BN22:BP22) -> 0 | CU22: =sum(BQ22:BS22) -> 0 | CV22: =sum(BT22:BV22) -> 0 | CW22: =sum(BK22:BV22) -> 0 | CY22: =sum(AY22:BA22) -> 0 | CZ22: =sum(BB22:BD22) -> 0 | DA22: =sum(BE22:BG22) -> 0 | DB22: =sum(BH22:BJ22) -> 0 | DC22: =sum(AY22:BJ22) -> 0 | DE22: =sum(AM22:AO22) -> 0 | DF22: =sum(AP22:AR22) -> 0 | DG22: =sum(AS22:AU22) -> 0 | DH22: =sum(AV22:AX22) -> 0 | DI22: =sum(AM22:AX22) -> 0 | DK22: =sum(AA22:AC22) -> 0 | DL22: =sum(AD22:AF22) -> 0 | DM22: =sum(AG22:AI22) -> 0 | DN22: =sum(AJ22:AL22) -> 0 | DO22: =sum(AA22:AL22) -> 0 | DS22: {=IF(DS$3>'GAAP Summary'!$B$2,0,SUM(INDIRECT(XLOOKUP(DS$3,'TTM Dates'!$B:$B,'TTM Dates'!$E:$E)&ROW($CJ22)&":"&XLOOKUP(DS$3,'TTM Dates'!$B:$B,'TTM Dates'!$C:$C)&ROW($CJ22))))} -> 0 | DT22: {=IF(DT$3>'GAAP Summary'!$B$2,0,SUM(INDIRECT(XLOOKUP(DT$3,'TTM Dates'!$B:$B,'TTM Dates'!$E:$E)&ROW($CJ22)&":"&XLOOKUP(DT$3,'TTM Dates'!$B:$B,'TTM Dates'!$C:$C)&ROW($CJ22))))} -> 0 | DU22: {=IF(DU$3>'GAAP Summary'!$B$2,0,SUM(INDIRECT(XLOOKUP(DU$3,'TTM Dates'!$B:$B,'TTM Dates'!$E:$E)&ROW($CJ22)&":"&XLOOKUP(DU$3,'TTM Dates'!$B:$B,'TTM Dates'!$C:$C)&ROW($CJ22))))} -> 0 | DV22: {=IF(DV$3>'GAAP Summary'!$B$2,0,SUM(INDIRECT(XLOOKUP(DV$3,'TTM Dates'!$B:$B,'TTM Dates'!$E:$E)&ROW($CJ22)&":"&XLOOKUP(DV$3,'TTM Dates'!$B:$B,'TTM Dates'!$C:$C)&ROW($CJ22))))} -> 0 | DW22: {=IF(DW$3>'GAAP Summary'!$B$2,0,SUM(INDIRECT(XLOOKUP(DW$3,'TTM Dates'!$B:$B,'TTM Dates'!$E:$E)&ROW($CJ22)&":"&XLOOKUP(DW$3,'TTM Dates'!$B:$B,'TTM Dates'!$C:$C)&ROW($CJ22))))} -> 0 | DX22: {=IF(DX$3>'GAAP Summary'!$B$2,0,SUM(INDIRECT(XLOOKUP(DX$3,'TTM Dates'!$B:$B,'TTM Dates'!$E:$E)&ROW($CJ22)&":"&XLOOKUP(DX$3,'TTM Dates'!$B:$B,'TTM Dates'!$C:$C)&ROW($CJ22))))} -> 0 | DY22: {=IF(DY$3>'GAAP Summary'!$B$2,0,SUM(INDIRECT(XLOOKUP(DY$3,'TTM Dates'!$B:$B,'TTM Dates'!$E:$E)&ROW($CJ22)&":"&XLOOKUP(DY$3,'TTM Dates'!$B:$B,'TTM Dates'!$C:$C)&ROW($CJ22))))} -> 0 | DZ22: {=IF(DZ$3>'GAAP Summary'!$B$2,0,SUM(INDIRECT(XLOOKUP(DZ$3,'TTM Dates'!$B:$B,'TTM Dates'!$E:$E)&ROW($CJ22)&":"&XLOOKUP(DZ$3,'TTM Dates'!$B:$B,'TTM Dates'!$C:$C)&ROW($CJ22))))} -> 0 | ... GL22: {=IF(GL$3>'GAAP Summary'!$B$2,0,SUM(INDIRECT(XLOOKUP(GL$3,'TTM Dates'!$B:$B,'TTM Dates'!$E:$E)&ROW($CJ22)&":"&XLOOKUP(GL$3,'TTM Dates'!$B:$B,'TTM Dates'!$C:$C)&ROW($CJ22))))} -> 0
B23: Total Services | AA23: 1143669 | AB23: 1028683 | AC23: 1352064 | AD23: 1147004 | AE23: 1244549 | AF23: 1491129 | AG23: 1287410 | AH23: 1888401 | AI23: 1579699 | AJ23: 1828195 | AK23: 1724117 | AL23: 1178549 | AM23: 2070143 | AN23: 1837048 | AO23: 2158000 | AP23: 1764880 | AQ23: 1839846 | AR23: 1763751 | AS23: 1526951 | AT23: 1895072 | AU23: 1506266 | AV23: 1727134 | AW23: 1582123 | AX23: 1495367 | AY23: =AY15+AY20 -> 1601598.9 | AZ23: =AZ15+AZ20 -> 1736505.9 | BA23: =BA15+BA20 -> 1830911.5 | BB23: =BB15+BB20 -> 1931116.6 | BC23: =BC15+BC20 -> 1829738.2 | BD23: =BD15+BD20 -> 1751835.7 | BE23: =BE15+BE20 -> 1994239.4 | BF23: =BF15+BF20 -> 2087066.4 | ... CH23: =CH15+CH20 -> 0 | CK23: {=SUM(INDIRECT(XLOOKUP('GAAP Summary'!$B$2,'TTM Dates'!$B:$B,'TTM Dates'!$E:$E)&ROW($CJ23)&":"&XLOOKUP('GAAP Summary'!$B$2,'TTM Dates'!$B:$B,'TTM Dates'!$C:$C)&ROW($CJ23)))} -> 43784537 | CM23: =sum(BW23:BY23) -> 11846674 | CN23: =sum(BZ23:CB23) -> 12892983 | CO23: =sum(CC23:CE23) -> 0 | CP23: =sum(CF23:CH23) -> 0 | CQ23: =sum(BW23:CH23) -> 24739657 | CS23: =sum(BK23:BM23) -> 6998281 | CT23: =sum(BN23:BP23) -> 7628658 | CU23: =sum(BQ23:BS23) -> 9024533.4 | CV23: =sum(BT23:BV23) -> 10020346 | CW23: =sum(BK23:BV23) -> 33671818 | CY23: =sum(AY23:BA23) -> 5169016.3 | CZ23: =sum(BB23:BD23) -> 5512690.6 | DA23: =sum(BE23:BG23) -> 6159262.4 | DB23: =sum(BH23:BJ23) -> 7179085.2 | DC23: =sum(AY23:BJ23) -> 24020055 | DE23: =sum(AM23:AO23) -> 6065191 | DF23: =sum(AP23:AR23) -> 5368477 | DG23: =sum(AS23:AU23) -> 4928289 | DH23: =sum(AV23:AX23) -> 4804624 | DI23: =sum(AM23:AX23) -> 21166581 | DK23: =sum(AA23:AC23) -> 3524416 | DL23: =sum(AD23:AF23) -> 3882682 | DM23: =sum(AG23:AI23) -> 4755510 | DN23: =sum(AJ23:AL23) -> 4730861 | DO23: =sum(AA23:AL23) -> 16893469 | DS23: {=IF(DS$3>'GAAP Summary'!$B$2,0,SUM(INDIRECT(XLOOKUP(DS$3,'TTM Dates'!$B:$B,'TTM Dates'!$E:$E)&ROW($CJ23)&":"&XLOOKUP(DS$3,'TTM Dates'!$B:$B,'TTM Dates'!$C:$C)&ROW($CJ23))))} -> 0 | DT23: {=IF(DT$3>'GAAP Summary'!$B$2,0,SUM(INDIRECT(XLOOKUP(DT$3,'TTM Dates'!$B:$B,'TTM Dates'!$E:$E)&ROW($CJ23)&":"&XLOOKUP(DT$3,'TTM Dates'!$B:$B,'TTM Dates'!$C:$C)&ROW($CJ23))))} -> 0 | DU23: {=IF(DU$3>'GAAP Summary'!$B$2,0,SUM(INDIRECT(XLOOKUP(DU$3,'TTM Dates'!$B:$B,'TTM Dates'!$E:$E)&ROW($CJ23)&":"&XLOOKUP(DU$3,'TTM Dates'!$B:$B,'TTM Dates'!$C:$C)&ROW($CJ23))))} -> 0 | DV23: {=IF(DV$3>'GAAP Summary'!$B$2,0,SUM(INDIRECT(XLOOKUP(DV$3,'TTM Dates'!$B:$B,'TTM Dates'!$E:$E)&ROW($CJ23)&":"&XLOOKUP(DV$3,'TTM Dates'!$B:$B,'TTM Dates'!$C:$C)&ROW($CJ23))))} -> 0 | DW23: {=IF(DW$3>'GAAP Summary'!$B$2,0,SUM(INDIRECT(XLOOKUP(DW$3,'TTM Dates'!$B:$B,'TTM Dates'!$E:$E)&ROW($CJ23)&":"&XLOOKUP(DW$3,'TTM Dates'!$B:$B,'TTM Dates'!$C:$C)&ROW($CJ23))))} -> 0 | DX23: {=IF(DX$3>'GAAP Summary'!$B$2,0,SUM(INDIRECT(XLOOKUP(DX$3,'TTM Dates'!$B:$B,'TTM Dates'!$E:$E)&ROW($CJ23)&":"&XLOOKUP(DX$3,'TTM Dates'!$B:$B,'TTM Dates'!$C:$C)&ROW($CJ23))))} -> 0 | DY23: {=IF(DY$3>'GAAP Summary'!$B$2,0,SUM(INDIRECT(XLOOKUP(DY$3,'TTM Dates'!$B:$B,'TTM Dates'!$E:$E)&ROW($CJ23)&":"&XLOOKUP(DY$3,'TTM Dates'!$B:$B,'TTM Dates'!$C:$C)&ROW($CJ23))))} -> 0 | DZ23: {=IF(DZ$3>'GAAP Summary'!$B$2,0,SUM(INDIRECT(XLOOKUP(DZ$3,'TTM Dates'!$B:$B,'TTM Dates'!$E:$E)&ROW($CJ23)&":"&XLOOKUP(DZ$3,'TTM Dates'!$B:$B,'TTM Dates'!$C:$C)&ROW($CJ23))))} -> 0 | ... GL23: {=IF(GL$3>'GAAP Summary'!$B$2,0,SUM(INDIRECT(XLOOKUP(GL$3,'TTM Dates'!$B:$B,'TTM Dates'!$E:$E)&ROW($CJ23)&":"&XLOOKUP(GL$3,'TTM Dates'!$B:$B,'TTM Dates'!$C:$C)&ROW($CJ23))))} -> 0
B24: Total SW | AA24: 31151 | AB24: 29959 | AC24: 30610 | AD24: 50298 | AE24: 32603 | AF24: 48697 | AG24: 39067 | AH24: 45011 | AI24: 47033 | AJ24: 34977 | AK24: 61158 | AL24: 58566 | AM24: 62059 | AN24: 106792 | AO24: 69301 | AP24: 79646 | AQ24: 60949 | AR24: 77475 | AS24: 107256 | AT24: 90370 | AU24: 72875 | AV24: 141165 | AW24: 75225 | AX24: 74735 | AY24: =AY16+AY21 -> 80743 | AZ24: =AZ16+AZ21 -> 132423 | BA24: =BA16+BA21 -> 81376 | BB24: =BB16+BB21 -> 72606 | BC24: =BC16+BC21 -> 79646 | BD24: =BD16+BD21 -> 72514 | BE24: =BE16+BE21 -> 80015 | BF24: =BF16+BF21 -> 80140 | ... CH24: =CH16+CH21 -> 0 | CK24: {=SUM(INDIRECT(XLOOKUP('GAAP Summary'!$B$2,'TTM Dates'!$B:$B,'TTM Dates'!$E:$E)&ROW($CJ24)&":"&XLOOKUP('GAAP Summary'!$B$2,'TTM Dates'!$B:$B,'TTM Dates'!$C:$C)&ROW($CJ24)))} -> 1115339.2 | CM24: =sum(BW24:BY24) -> 262949.65 | CN24: =sum(BZ24:CB24) -> 250005.76 | CO24: =sum(CC24:CE24) -> 0 | CP24: =sum(CF24:CH24) -> 0 | CQ24: =sum(BW24:CH24) -> 512955.41 | CS24: =sum(BK24:BM24) -> 323162 | CT24: =sum(BN24:BP24) -> 189162 | CU24: =sum(BQ24:BS24) -> 186270.31 | CV24: =sum(BT24:BV24) -> 416113.49 | CW24: =sum(BK24:BV24) -> 1114707.8 | CY24: =sum(AY24:BA24) -> 294542 | CZ24: =sum(BB24:BD24) -> 224766 | DA24: =sum(BE24:BG24) -> 241199 | DB24: =sum(BH24:BJ24) -> 278112 | DC24: =sum(AY24:BJ24) -> 1038619 | DE24: =sum(AM24:AO24) -> 238152 | DF24: =sum(AP24:AR24) -> 218070 | DG24: =sum(AS24:AU24) -> 270501 | DH24: =sum(AV24:AX24) -> 291125 | DI24: =sum(AM24:AX24) -> 1017848 | DK24: =sum(AA24:AC24) -> 91720 | DL24: =sum(AD24:AF24) -> 131598 | DM24: =sum(AG24:AI24) -> 131111 | DN24: =sum(AJ24:AL24) -> 154701 | DO24: =sum(AA24:AL24) -> 509130 | DS24: {=IF(DS$3>'GAAP Summary'!$B$2,0,SUM(INDIRECT(XLOOKUP(DS$3,'TTM Dates'!$B:$B,'TTM Dates'!$E:$E)&ROW($CJ24)&":"&XLOOKUP(DS$3,'TTM Dates'!$B:$B,'TTM Dates'!$C:$C)&ROW($CJ24))))} -> 0 | DT24: {=IF(DT$3>'GAAP Summary'!$B$2,0,SUM(INDIRECT(XLOOKUP(DT$3,'TTM Dates'!$B:$B,'TTM Dates'!$E:$E)&ROW($CJ24)&":"&XLOOKUP(DT$3,'TTM Dates'!$B:$B,'TTM Dates'!$C:$C)&ROW($CJ24))))} -> 0 | DU24: {=IF(DU$3>'GAAP Summary'!$B$2,0,SUM(INDIRECT(XLOOKUP(DU$3,'TTM Dates'!$B:$B,'TTM Dates'!$E:$E)&ROW($CJ24)&":"&XLOOKUP(DU$3,'TTM Dates'!$B:$B,'TTM Dates'!$C:$C)&ROW($CJ24))))} -> 0 | DV24: {=IF(DV$3>'GAAP Summary'!$B$2,0,SUM(INDIRECT(XLOOKUP(DV$3,'TTM Dates'!$B:$B,'TTM Dates'!$E:$E)&ROW($CJ24)&":"&XLOOKUP(DV$3,'TTM Dates'!$B:$B,'TTM Dates'!$C:$C)&ROW($CJ24))))} -> 0 | DW24: {=IF(DW$3>'GAAP Summary'!$B$2,0,SUM(INDIRECT(XLOOKUP(DW$3,'TTM Dates'!$B:$B,'TTM Dates'!$E:$E)&ROW($CJ24)&":"&XLOOKUP(DW$3,'TTM Dates'!$B:$B,'TTM Dates'!$C:$C)&ROW($CJ24))))} -> 0 | DX24: {=IF(DX$3>'GAAP Summary'!$B$2,0,SUM(INDIRECT(XLOOKUP(DX$3,'TTM Dates'!$B:$B,'TTM Dates'!$E:$E)&ROW($CJ24)&":"&XLOOKUP(DX$3,'TTM Dates'!$B:$B,'TTM Dates'!$C:$C)&ROW($CJ24))))} -> 0 | DY24: {=IF(DY$3>'GAAP Summary'!$B$2,0,SUM(INDIRECT(XLOOKUP(DY$3,'TTM Dates'!$B:$B,'TTM Dates'!$E:$E)&ROW($CJ24)&":"&XLOOKUP(DY$3,'TTM Dates'!$B:$B,'TTM Dates'!$C:$C)&ROW($CJ24))))} -> 0 | DZ24: {=IF(DZ$3>'GAAP Summary'!$B$2,0,SUM(INDIRECT(XLOOKUP(DZ$3,'TTM Dates'!$B:$B,'TTM Dates'!$E:$E)&ROW($CJ24)&":"&XLOOKUP(DZ$3,'TTM Dates'!$B:$B,'TTM Dates'!$C:$C)&ROW($CJ24))))} -> 0 | ... GL24: {=IF(GL$3>'GAAP Summary'!$B$2,0,SUM(INDIRECT(XLOOKUP(GL$3,'TTM Dates'!$B:$B,'TTM Dates'!$E:$E)&ROW($CJ24)&":"&XLOOKUP(GL$3,'TTM Dates'!$B:$B,'TTM Dates'!$C:$C)&ROW($CJ24))))} -> 0
B25: Total MSP | AA25: =AA17+AA18+AA22 -> 0 | AB25: =AB17+AB18+AB22 -> 0 | AC25: =AC17+AC18+AC22 -> 0 | AD25: =AD17+AD18+AD22 -> 0 | AE25: =AE17+AE18+AE22 -> 0 | AF25: =AF17+AF18+AF22 -> 0 | AG25: =AG17+AG18+AG22 -> 0 | AH25: =AH17+AH18+AH22 -> 0 | ... CH25: =CH17+CH18+CH22 -> 0 | CK25: {=SUM(INDIRECT(XLOOKUP('GAAP Summary'!$B$2,'TTM Dates'!$B:$B,'TTM Dates'!$E:$E)&ROW($CJ25)&":"&XLOOKUP('GAAP Summary'!$B$2,'TTM Dates'!$B:$B,'TTM Dates'!$C:$C)&ROW($CJ25)))} -> 1767829.6 | CM25: =sum(BW25:BY25) -> 464616.92 | CN25: =sum(BZ25:CB25) -> 501464.92 | CO25: =sum(CC25:CE25) -> 0 | CP25: =sum(CF25:CH25) -> 0 | CQ25: =sum(BW25:CH25) -> 966081.84 | CS25: =sum(BK25:BM25) -> 102168 | CT25: =sum(BN25:BP25) -> 224875.12 | CU25: =sum(BQ25:BS25) -> 287925.67 | CV25: =sum(BT25:BV25) -> 513822.05 | CW25: =sum(BK25:BV25) -> 1128790.8 | CY25: =sum(AY25:BA25) -> 0 | CZ25: =sum(BB25:BD25) -> 13334 | DA25: =sum(BE25:BG25) -> 12052 | DB25: =sum(BH25:BJ25) -> 270884 | DC25: =sum(AY25:BJ25) -> 296270 | DE25: =sum(AM25:AO25) -> 0 | DF25: =sum(AP25:AR25) -> 0 | DG25: =sum(AS25:AU25) -> 0 | DH25: =sum(AV25:AX25) -> 0 | DI25: =sum(AM25:AX25) -> 0 | DK25: =sum(AA25:AC25) -> 0 | DL25: =sum(AD25:AF25) -> 0 | DM25: =sum(AG25:AI25) -> 0 | DN25: =sum(AJ25:AL25) -> 0 | DO25: =sum(AA25:AL25) -> 0 | DS25: {=IF(DS$3>'GAAP Summary'!$B$2,0,SUM(INDIRECT(XLOOKUP(DS$3,'TTM Dates'!$B:$B,'TTM Dates'!$E:$E)&ROW($CJ25)&":"&XLOOKUP(DS$3,'TTM Dates'!$B:$B,'TTM Dates'!$C:$C)&ROW($CJ25))))} -> 0 | DT25: {=IF(DT$3>'GAAP Summary'!$B$2,0,SUM(INDIRECT(XLOOKUP(DT$3,'TTM Dates'!$B:$B,'TTM Dates'!$E:$E)&ROW($CJ25)&":"&XLOOKUP(DT$3,'TTM Dates'!$B:$B,'TTM Dates'!$C:$C)&ROW($CJ25))))} -> 0 | DU25: {=IF(DU$3>'GAAP Summary'!$B$2,0,SUM(INDIRECT(XLOOKUP(DU$3,'TTM Dates'!$B:$B,'TTM Dates'!$E:$E)&ROW($CJ25)&":"&XLOOKUP(DU$3,'TTM Dates'!$B:$B,'TTM Dates'!$C:$C)&ROW($CJ25))))} -> 0 | DV25: {=IF(DV$3>'GAAP Summary'!$B$2,0,SUM(INDIRECT(XLOOKUP(DV$3,'TTM Dates'!$B:$B,'TTM Dates'!$E:$E)&ROW($CJ25)&":"&XLOOKUP(DV$3,'TTM Dates'!$B:$B,'TTM Dates'!$C:$C)&ROW($CJ25))))} -> 0 | DW25: {=IF(DW$3>'GAAP Summary'!$B$2,0,SUM(INDIRECT(XLOOKUP(DW$3,'TTM Dates'!$B:$B,'TTM Dates'!$E:$E)&ROW($CJ25)&":"&XLOOKUP(DW$3,'TTM Dates'!$B:$B,'TTM Dates'!$C:$C)&ROW($CJ25))))} -> 0 | DX25: {=IF(DX$3>'GAAP Summary'!$B$2,0,SUM(INDIRECT(XLOOKUP(DX$3,'TTM Dates'!$B:$B,'TTM Dates'!$E:$E)&ROW($CJ25)&":"&XLOOKUP(DX$3,'TTM Dates'!$B:$B,'TTM Dates'!$C:$C)&ROW($CJ25))))} -> 0 | DY25: {=IF(DY$3>'GAAP Summary'!$B$2,0,SUM(INDIRECT(XLOOKUP(DY$3,'TTM Dates'!$B:$B,'TTM Dates'!$E:$E)&ROW($CJ25)&":"&XLOOKUP(DY$3,'TTM Dates'!$B:$B,'TTM Dates'!$C:$C)&ROW($CJ25))))} -> 0 | DZ25: {=IF(DZ$3>'GAAP Summary'!$B$2,0,SUM(INDIRECT(XLOOKUP(DZ$3,'TTM Dates'!$B:$B,'TTM Dates'!$E:$E)&ROW($CJ25)&":"&XLOOKUP(DZ$3,'TTM Dates'!$B:$B,'TTM Dates'!$C:$C)&ROW($CJ25))))} -> 0 | ... GL25: {=IF(GL$3>'GAAP Summary'!$B$2,0,SUM(INDIRECT(XLOOKUP(GL$3,'TTM Dates'!$B:$B,'TTM Dates'!$E:$E)&ROW($CJ25)&":"&XLOOKUP(GL$3,'TTM Dates'!$B:$B,'TTM Dates'!$C:$C)&ROW($CJ25))))} -> 0
B26: Data Label | AA26: =AA13-SUM(AA23:AA25) -> 1 | AB26: =AB13-SUM(AB23:AB25) -> 0 | AC26: =AC13-SUM(AC23:AC25) -> 1 | AD26: =AD13-SUM(AD23:AD25) -> 0 | AE26: =AE13-SUM(AE23:AE25) -> 0 | AF26: =AF13-SUM(AF23:AF25) -> 0 | AG26: =AG13-SUM(AG23:AG25) -> 1 | AH26: =AH13-SUM(AH23:AH25) -> 0 | ... AL26: =AL13-SUM(AL23:AL25) -> 0 | AM26: =IF(AM13=0,"", TEXT(AM13,"0,000")&" "&"("&TEXT((AM13-AA13)/AA13,"0%")&" YoY)") -> 2,132,202 (81% YoY) | AN26: =IF(AN13=0,"", TEXT(AN13,"0,000")&" "&"("&TEXT((AN13-AB13)/AB13,"0%")&" YoY)") -> 1,943,840 (84% YoY) | AO26: =IF(AO13=0,"", TEXT(AO13,"0,000")&" "&"("&TEXT((AO13-AC13)/AC13,"0%")&" YoY)") -> 2,227,301 (61% YoY) | AP26: =IF(AP13=0,"", TEXT(AP13,"0,000")&" "&"("&TEXT((AP13-AD13)/AD13,"0%")&" YoY)") -> 1,844,526 (54% YoY) | AQ26: =IF(AQ13=0,"", TEXT(AQ13,"0,000")&" "&"("&TEXT((AQ13-AE13)/AE13,"0%")&" YoY)") -> 1,900,795 (49% YoY) | AR26: =IF(AR13=0,"", TEXT(AR13,"0,000")&" "&"("&TEXT((AR13-AF13)/AF13,"0%")&" YoY)") -> 1,841,226 (20% YoY) | AS26: =IF(AS13=0,"", TEXT(AS13,"0,000")&" "&"("&TEXT((AS13-AG13)/AG13,"0%")&" YoY)") -> 1,634,207 (23% YoY) | AT26: =IF(AT13=0,"", TEXT(AT13,"0,000")&" "&"("&TEXT((AT13-AH13)/AH13,"0%")&" YoY)") -> 1,985,443 (3% YoY) | ... CH26: =IF(CH13=0,"", TEXT(CH13,"0,000")&" "&"("&TEXT((CH13-BV13)/BV13,"0%")&" YoY)") | CM26: =IF(CM13=0,"", TEXT(CM13,"0,000")&" "&"("&TEXT((CM13-CS13)/CS13,"0%")&" YoY)") -> 12,574,241 (69% YoY) | CN26: =IF(CN13=0,"", TEXT(CN13,"0,000")&" "&"("&TEXT((CN13-CT13)/CT13,"0%")&" YoY)") -> 13,644,454 (70% YoY) | CO26: =IF(CO13=0,"", TEXT(CO13,"0,000")&" "&"("&TEXT((CO13-CU13)/CU13,"0%")&" YoY)") | CP26: =IF(CP13=0,"", TEXT(CP13,"0,000")&" "&"("&TEXT((CP13-CV13)/CV13,"0%")&" YoY)") | CQ26: =(CQ13-CW13)/CW13 -> -0.26998571 | CS26: =IF(CS13=0,"", TEXT(CS13,"0,000")&" "&"("&TEXT((CS13-CY13)/CY13,"0%")&" YoY)") -> 7,423,611 (36% YoY) | CT26: =IF(CT13=0,"", TEXT(CT13,"0,000")&" "&"("&TEXT((CT13-CZ13)/CZ13,"0%")&" YoY)") -> 8,042,695 (40% YoY) | CU26: =IF(CU13=0,"", TEXT(CU13,"0,000")&" "&"("&TEXT((CU13-DA13)/DA13,"0%")&" YoY)") -> 9,498,729 (48% YoY) | CV26: =IF(CV13=0,"", TEXT(CV13,"0,000")&" "&"("&TEXT((CV13-DB13)/DB13,"0%")&" YoY)") -> 10,950,282 (42% YoY) | CW26: =(CW13-DC13)/DC13 -> 0.41650156 | CY26: =IF(CY13=0,"", TEXT(CY13,"0,000")&" "&"("&TEXT((CY13-DE13)/DE13,"0%")&" YoY)") -> 5,463,558 (-13% YoY) | CZ26: =IF(CZ13=0,"", TEXT(CZ13,"0,000")&" "&"("&TEXT((CZ13-DF13)/DF13,"0%")&" YoY)") -> 5,750,791 (3% YoY) | DA26: =IF(DA13=0,"", TEXT(DA13,"0,000")&" "&"("&TEXT((DA13-DG13)/DG13,"0%")&" YoY)") -> 6,412,513 (23% YoY) | DB26: =IF(DB13=0,"", TEXT(DB13,"0,000")&" "&"("&TEXT((DB13-DH13)/DH13,"0%")&" YoY)") -> 7,728,081 (52% YoY) | DC26: =(DC13-DI13)/DI13 -> 0.14291616 | DE26: =IF(DE13=0,"", TEXT(DE13,"0,000")&" "&"("&TEXT((DE13-DK13)/DK13,"0%")&" YoY)") -> 6,303,343 (74% YoY) | DF26: =IF(DF13=0,"", TEXT(DF13,"0,000")&" "&"("&TEXT((DF13-DL13)/DL13,"0%")&" YoY)") -> 5,586,547 (39% YoY) | DG26: =IF(DG13=0,"", TEXT(DG13,"0,000")&" "&"("&TEXT((DG13-DM13)/DM13,"0%")&" YoY)") -> 5,198,791 (6% YoY) | DH26: =IF(DH13=0,"", TEXT(DH13,"0,000")&" "&"("&TEXT((DH13-DN13)/DN13,"0%")&" YoY)") -> 5,095,749 (4% YoY) | DI26: =(DI13-DO13)/DO13 -> 0.27477661
B28: COGS | AA28: 285690 | AB28: 371270 | AC28: 361550 | AD28: 420980 | AE28: 391670 | AF28: 388050 | AG28: 448730 | AH28: 445170 | AI28: 459930 | AJ28: 435680 | AK28: 530320 | AL28: 496380 | AM28: =AM29+AM39+AM42+AM43 -> 828508.74 | AN28: =AN29+AN39+AN42+AN43 -> 603747.44 | AO28: =AO29+AO39+AO42+AO43 -> 625311.64 | AP28: =AP29+AP39+AP42+AP43 -> 761722.62 | AQ28: =AQ29+AQ39+AQ42+AQ43 -> 636848.46 | AR28: =AR29+AR39+AR42+AR43 -> 592880.64 | AS28: =AS29+AS39+AS42+AS43 -> 650592.72 | AT28: =AT29+AT39+AT42+AT43 -> 961832.56 | ... BX28: =BX29+BX39+BX42+BX43 -> 1685443 | BY28: =BY44+BY45 -> 1937350.7 | BZ28: =BZ29+BZ39 -> 1922012.3 | CA28: =CA29+CA39+CA42+CA43 -> 1760059.6 | CB28: =CB29+CB39+CB42+CB43 -> 1851450.7 | CC28: =CC29+CC39+CC42+CC43 -> 0 | CD28: =CD29+CD39+CD42+CD43 -> 0 | CE28: =CE29+CE39+CE42+CE43 -> 0 | CF28: =CF29+CF39+CF42+CF43 -> 0 | CG28: =CG29+CG39+CG42+CG43 -> 0 | CH28: =CH29+CH39+CH42+CH43 -> 0 | CK28: {=SUM(INDIRECT(XLOOKUP('GAAP Summary'!$B$2,'TTM Dates'!$B:$B,'TTM Dates'!$E:$E)&ROW($CJ28)&":"&XLOOKUP('GAAP Summary'!$B$2,'TTM Dates'!$B:$B,'TTM Dates'!$C:$C)&ROW($CJ28)))} -> 19795675 | CM28: =sum(BW28:BY28) -> 5462056 | CN28: =sum(BZ28:CB28) -> 5533522.6 | CO28: =sum(CC28:CE28) -> 0 | CP28: =sum(CF28:CH28) -> 0 | CQ28: =sum(BW28:CH28) -> 10995579 | CS28: =sum(BK28:BM28) -> 3225319.5 | CT28: =sum(BN28:BP28) -> 3346329.7 | CU28: =sum(BQ28:BS28) -> 3994705.5 | CV28: =sum(BT28:BV28) -> 4805391.1 | CW28: =sum(BK28:BV28) -> 15371746 | CY28: =sum(AY28:BA28) -> 2169706.1 | CZ28: =sum(BB28:BD28) -> 2468305.7 | DA28: =sum(BE28:BG28) -> 2846515 | DB28: =sum(BH28:BJ28) -> 2949067.9 | DC28: =sum(AY28:BJ28) -> 10433595 | DD28: =(DC13-DC28)/DC13 -> 0.5884986 | DE28: =sum(AM28:AO28) -> 2057567.8 | DF28: =sum(AP28:AR28) -> 1991451.7 | DG28: =sum(AS28:AU28) -> 2332101.6 | DH28: =sum(AV28:AX28) -> 2150685 | DI28: =sum(AM28:AX28) -> 8531806.2 | DK28: =sum(AA28:AC28) -> 1018510 | DL28: =sum(AD28:AF28) -> 1200700 | DM28: =sum(AG28:AI28) -> 1353830 | DN28: =sum(AJ28:AL28) -> 1462380 | DO28: =sum(AA28:AL28) -> 5035420 | DS28: {=IF(DS$3>'GAAP Summary'!$B$2,0,SUM(INDIRECT(XLOOKUP(DS$3,'TTM Dates'!$B:$B,'TTM Dates'!$E:$E)&ROW($CJ28)&":"&XLOOKUP(DS$3,'TTM Dates'!$B:$B,'TTM Dates'!$C:$C)&ROW($CJ28))))} -> 0 | DT28: {=IF(DT$3>'GAAP Summary'!$B$2,0,SUM(INDIRECT(XLOOKUP(DT$3,'TTM Dates'!$B:$B,'TTM Dates'!$E:$E)&ROW($CJ28)&":"&XLOOKUP(DT$3,'TTM Dates'!$B:$B,'TTM Dates'!$C:$C)&ROW($CJ28))))} -> 0 | DU28: {=IF(DU$3>'GAAP Summary'!$B$2,0,SUM(INDIRECT(XLOOKUP(DU$3,'TTM Dates'!$B:$B,'TTM Dates'!$E:$E)&ROW($CJ28)&":"&XLOOKUP(DU$3,'TTM Dates'!$B:$B,'TTM Dates'!$C:$C)&ROW($CJ28))))} -> 0 | DV28: {=IF(DV$3>'GAAP Summary'!$B$2,0,SUM(INDIRECT(XLOOKUP(DV$3,'TTM Dates'!$B:$B,'TTM Dates'!$E:$E)&ROW($CJ28)&":"&XLOOKUP(DV$3,'TTM Dates'!$B:$B,'TTM Dates'!$C:$C)&ROW($CJ28))))} -> 0 | DW28: {=IF(DW$3>'GAAP Summary'!$B$2,0,SUM(INDIRECT(XLOOKUP(DW$3,'TTM Dates'!$B:$B,'TTM Dates'!$E:$E)&ROW($CJ28)&":"&XLOOKUP(DW$3,'TTM Dates'!$B:$B,'TTM Dates'!$C:$C)&ROW($CJ28))))} -> 0 | DX28: {=IF(DX$3>'GAAP Summary'!$B$2,0,SUM(INDIRECT(XLOOKUP(DX$3,'TTM Dates'!$B:$B,'TTM Dates'!$E:$E)&ROW($CJ28)&":"&XLOOKUP(DX$3,'TTM Dates'!$B:$B,'TTM Dates'!$C:$C)&ROW($CJ28))))} -> 0 | DY28: {=IF(DY$3>'GAAP Summary'!$B$2,0,SUM(INDIRECT(XLOOKUP(DY$3,'TTM Dates'!$B:$B,'TTM Dates'!$E:$E)&ROW($CJ28)&":"&XLOOKUP(DY$3,'TTM Dates'!$B:$B,'TTM Dates'!$C:$C)&ROW($CJ28))))} -> 0 | DZ28: {=IF(DZ$3>'GAAP Summary'!$B$2,0,SUM(INDIRECT(XLOOKUP(DZ$3,'TTM Dates'!$B:$B,'TTM Dates'!$E:$E)&ROW($CJ28)&":"&XLOOKUP(DZ$3,'TTM Dates'!$B:$B,'TTM Dates'!$C:$C)&ROW($CJ28))))} -> 0 | ... GL28: {=IF(GL$3>'GAAP Summary'!$B$2,0,SUM(INDIRECT(XLOOKUP(GL$3,'TTM Dates'!$B:$B,'TTM Dates'!$E:$E)&ROW($CJ28)&":"&XLOOKUP(GL$3,'TTM Dates'!$B:$B,'TTM Dates'!$C:$C)&ROW($CJ28))))} -> 0
B29: COGS Payroll | AM29: 828508.74 | AN29: 603717.91 | AO29: 625311.64 | AP29: 761722.62 | AQ29: 636848.46 | AR29: 592880.64 | AS29: 647258.9 | AT29: 941032.69 | AU29: 708524.58 | AV29: 679060.78 | AW29: 680053.75 | AX29: 742152.92 | AY29: 756742.61 | AZ29: 685393.08 | BA29: 678405.55 | BB29: 963966.16 | BC29: 668206.56 | BD29: 659582.9 | BE29: 679212.33 | BF29: 1189293.1 | BG29: 820289.67 | BH29: 911229.56 | BI29: 913595.35 | BJ29: 1019934.3 | BK29: 1072422.6 | BL29: 967878.36 | BM29: 1014416.5 | BN29: 1040436.1 | BO29: 1104830.9 | BP29: 1123883.2 | BQ29: 1223413.8 | BR29: 1182437.8 | BS29: 1412310.6 | BT29: 1564719.6 | BU29: 1453235.4 | BV29: 1666713.3 | BW29: 1766252.4 | BX29: =SUM(BX30,BX35) -> 1615595.6 | BY29: =SUM(BY30,BY35) -> 1924772.4 | BZ29: =SUM(BZ30,BZ35) -> 1897295.8 | CA29: =SUM(CA30,CA35) -> 1692237.6 | CB29: =1765551.64+14845.09 -> 1780396.7 | CM29: =sum(BW29:BY29) -> 5306620.5 | CN29: =sum(BZ29:CB29) -> 5369930.1 | CO29: =sum(CC29:CE29) -> 0 | CP29: =sum(CF29:CH29) -> 0 | CQ29: =sum(BW29:CH29) -> 10676551 | CS29: =sum(BK29:BM29) -> 3054717.5 | CT29: =sum(BN29:BP29) -> 3269150.2 | CU29: =sum(BQ29:BS29) -> 3818162.3 | CV29: =sum(BT29:BV29) -> 4684668.2 | CW29: =sum(BK29:BV29) -> 14826698 | FW29: =sum(BH29:BS29) -> 12986789
B30: DD | AM30: =SUM(AM31:AM34) -> 306092.07 | AN30: =SUM(AN31:AN34) -> 215414.83 | AO30: =SUM(AO31:AO34) -> 237738.41 | AP30: =SUM(AP31:AP34) -> 232861.57 | AQ30: =SUM(AQ31:AQ34) -> 212231.63 | AR30: =SUM(AR31:AR34) -> 241697.47 | AS30: =SUM(AS31:AS34) -> 241093.83 | AT30: =SUM(AT31:AT34) -> 383792.6 | ... BT30: =SUM(BT31:BT34) -> 552450 | BU30: =SUM(BU31:BU34,BU40,BU42) -> 532628.36 | BV30: =SUM(BV31:BV34,BV40,BV42) -> 604383.48 | BW30: =SUM(BW31:BW34,BW40,BW42) -> 606590.88 | BX30: =SUM(BX31:BX34) -> 507460.14 | BY30: =SUM(BY31:BY34,BY40,BY42) -> 676650.82 | BZ30: =SUM(BZ31:BZ34,BZ40,BZ42) -> 671450.94 | CA30: =SUM(CA31:CA34) -> 553048.51 | CB30: =SUM(CB31:CB34,CB40,CB42) -> 571420.37 | CC30: =SUM(CC31:CC34,CC40,CC42) -> 0 | CD30: =SUM(CD31:CD34,CD40,CD42) -> 0 | CE30: =SUM(CE31:CE34,CE40,CE42) -> 0 | CF30: =SUM(CF31:CF34,CF40,CF42) -> 0 | CG30: =SUM(CG31:CG34,CG40,CG42) -> 0 | CH30: =SUM(CH31:CH34,CH40,CH42) -> 0 | CM30: =sum(BW30:BY30) -> 1790701.8 | CN30: =sum(BZ30:CB30) -> 1795919.8 | CO30: =sum(CC30:CE30) -> 0 | CP30: =sum(CF30:CH30) -> 0 | CQ30: =sum(BW30:CH30) -> 3586621.7 | CS30: =sum(BK30:BM30) -> 1197417.9 | CT30: =sum(BN30:BP30) -> 1211582.6 | CU30: =sum(BQ30:BS30) -> 1309002.2 | CV30: =sum(BT30:BV30) -> 1689461.8 | CW30: =sum(BK30:BV30) -> 5407464.6
B31: DD Services | AM31: 306092.07 | AN31: 215414.83 | AO31: 237738.41 | AP31: 232861.57 | AQ31: 212231.63 | AR31: 241697.47 | AS31: 241093.83 | AT31: 383792.6 | AU31: 276480.29 | AV31: 279900.6 | AW31: 279835.8 | AX31: 342440.65 | AY31: 329785.06 | AZ31: 305130.08 | BA31: 286603.84 | BB31: 408304.32 | BC31: 261859.17 | BD31: 262200.4 | BE31: 267364.03 | BF31: 458084.23 | BG31: 322098.08 | BH31: 341500.24 | BI31: 336556.42 | BJ31: 400658.11 | BK31: 415288.96 | BL31: 342495.35 | BM31: 349268.25 | BN31: 346977.75 | BO31: 379162.22 | BP31: 360402.88 | BQ31: 384013.17 | BR31: 339049.57 | BS31: =467664.43-BS33-BS34 -> 396494.95 | BT31: =552450-BT33-BT34 -> 460773.65 | BU31: =493213.39-BU33-BU34 -> 410933.23 | BV31: =581188.18-BV33-BV34 -> 491181.13 | BW31: 494421.14 | BX31: =507460.14-70536.89 -> 436923.25 | BY31: =636296.14-BY33-BY34 -> 559158.24 | BZ31: =637628.54-49770.03-28203.64 -> 559654.87 | CA31: =553048.51- 14027.1 - 48132.51 -> 490888.9 | CB31: =536348.74-CB33-CB34 -> 454819.44 | CM31: =sum(BW31:BY31) -> 1490502.6 | CN31: =sum(BZ31:CB31) -> 1505363.2 | CO31: =sum(CC31:CE31) -> 0 | CP31: =sum(CF31:CH31) -> 0 | CQ31: =sum(BW31:CH31) -> 2995865.8 | CS31: =sum(BK31:BM31) -> 1107052.6 | CT31: =sum(BN31:BP31) -> 1086542.9 | CU31: =sum(BQ31:BS31) -> 1119557.7 | CV31: =sum(BT31:BV31) -> 1362888 | CW31: =sum(BK31:BV31) -> 4676041.1
B32: DD Software | CM32: =sum(BW32:BY32) -> 0 | CN32: =sum(BZ32:CB32) -> 0 | CO32: =sum(CC32:CE32) -> 0 | CP32: =sum(CF32:CH32) -> 0 | CQ32: =sum(BW32:CH32) -> 0 | CS32: =sum(BK32:BM32) -> 0 | CT32: =sum(BN32:BP32) -> 0 | CU32: =sum(BQ32:BS32) -> 0 | CV32: =sum(BT32:BV32) -> 0 | CW32: =sum(BK32:BV32) -> 0
B33: Managed DD | AY33: 0 | AZ33: 0 | BA33: 0 | BB33: 0 | BC33: 0 | BD33: 0 | BE33: 0 | BF33: 0 | BG33: 16988.86 | BH33: 43038.9 | BI33: 25354.49 | BJ33: 27225.16 | BK33: 28521.12 | BL33: 25529.25 | BM33: 24725.98 | BN33: 30567.51 | BO33: 30050.76 | BP33: 27746.5 | BQ33: 30163.5 | BR33: 36239.69 | BS33: 40348.09 | BT33: 60933.2 | BU33: 40539.48 | BV33: 39400.81 | BW33: 33246.44 | BX33: 26481.72 | BY33: 28164.73 | BZ33: 28203.64 | CA33: 14027.1 | CB33: 30805.01 | CM33: =sum(BW33:BY33) -> 87892.89 | CN33: =sum(BZ33:CB33) -> 73035.75 | CO33: =sum(CC33:CE33) -> 0 | CP33: =sum(CF33:CH33) -> 0 | CQ33: =sum(BW33:CH33) -> 160928.64 | CS33: =sum(BK33:BM33) -> 78776.35 | CT33: =sum(BN33:BP33) -> 88364.77 | CU33: =sum(BQ33:BS33) -> 106751.28 | CV33: =sum(BT33:BV33) -> 140873.49 | CW33: =sum(BK33:BV33) -> 414765.89
B34: Managed Security | AY34: 0 | AZ34: 0 | BA34: 0 | BB34: 0 | BC34: 0 | BD34: 0 | BE34: 0 | BF34: 0 | BG34: 0 | BH34: 0 | BI34: 0 | BJ34: 0 | BK34: 0 | BL34: 0 | BM34: 11589.03 | BN34: 12503.92 | BO34: 12326.13 | BP34: 11844.93 | BQ34: 23062.46 | BR34: 28809.38 | BS34: 30821.39 | BT34: 30743.15 | BU34: 41740.68 | BV34: 50606.24 | BW34: 41852 | BX34: 44055.17 | BY34: 48973.17 | BZ34: 49770.03 | CA34: 48132.51 | CB34: 50724.29 | CM34: =sum(BW34:BY34) -> 134880.34 | CN34: =sum(BZ34:CB34) -> 148626.83 | CO34: =sum(CC34:CE34) -> 0 | CP34: =sum(CF34:CH34) -> 0 | CQ34: =sum(BW34:CH34) -> 283507.17 | CS34: =sum(BK34:BM34) -> 11589.03 | CT34: =sum(BN34:BP34) -> 36674.98 | CU34: =sum(BQ34:BS34) -> 82693.23 | CV34: =sum(BT34:BV34) -> 123090.07 | CW34: =sum(BK34:BV34) -> 254047.31
B35: SN | AM35: =SUM(AM36:AM38) -> 522416.67 | AN35: =SUM(AN36:AN38) -> 388303.08 | AO35: =SUM(AO36:AO38) -> 387573.23 | AP35: =SUM(AP36:AP38) -> 528861.05 | AQ35: =SUM(AQ36:AQ38) -> 424616.83 | AR35: =SUM(AR36:AR38) -> 351183.17 | AS35: =SUM(AS36:AS38) -> 406165.07 | AT35: =SUM(AT36:AT38) -> 557240.09 | ... BW35: =SUM(BW36:BW38) -> 1159661.5 | BX35: =SUM(BX36,BX38) -> 1108135.5 | BY35: =SUM(BY36:BY38) -> 1248121.6 | BZ35: =SUM(BZ36:BZ38) -> 1225844.8 | CA35: =SUM(CA36:CA38) -> 1139189.1 | CB35: =SUM(CB36:CB38) -> 1244048 | CC35: =SUM(CC36:CC38) -> 0 | CD35: =SUM(CD36:CD38) -> 0 | CE35: =SUM(CE36:CE38) -> 0 | CF35: =SUM(CF36:CF38) -> 0 | ... CH35: =SUM(CH36:CH38) -> 0 | CM35: =sum(BW35:BY35) -> 3515918.6 | CN35: =sum(BZ35:CB35) -> 3609081.9 | CO35: =sum(CC35:CE35) -> 0 | CP35: =sum(CF35:CH35) -> 0 | CQ35: =sum(BW35:CH35) -> 7125000.5 | CS35: =sum(BK35:BM35) -> 1857299.1 | CT35: =sum(BN35:BP35) -> 2057567.4 | CU35: =sum(BQ35:BS35) -> 2509160.2 | CV35: =sum(BT35:BV35) -> 3057816.7 | CW35: =sum(BK35:BV35) -> 9481843.3
B36: SN Services | AM36: 522416.67 | AN36: 388303.08 | AO36: 387573.23 | AP36: 528861.05 | AQ36: 424616.83 | AR36: 351183.17 | AS36: 406165.07 | AT36: 557240.09 | AU36: 432044.29 | AV36: =-1375.72+397784.46 -> 396408.74 | AW36: =-3611.77+396607.18 -> 392995.41 | AX36: 399712.27 | AY36: =-374.4+427332.55 -> 426958.15 | AZ36: 380263 | BA36: =-499+392300.71 -> 391801.71 | BB36: =-499.16+556160.84 -> 555661.68 | BC36: =-499+406846.39 -> 406347.39 | BD36: =-501.98+397884.48 -> 397382.5 | BE36: 411848.3 | BF36: =-4392.15+735601.05 -> 731208.9 | BG36: =12112.38+469090.35 -> 481202.73 | BH36: =5835.96+532526.38 -> 538362.34 | BI36: =23+551661.44 -> 551684.44 | BJ36: =589534.37+2516 -> 592050.37 | BK36: =-1649.62+630262.54 -> 628612.92 | BL36: =-4250.36+604103.76 -> 599853.4 | BM36: =-3390.61+632223.35 -> 628832.74 | BN36: =-1480.49+651867.31 -> 650386.82 | BO36: =7373.89+675918 -> 683291.89 | BP36: =7254.83+716633.86 -> 723888.69 | BQ36: =778388.99+7785.88 -> 786174.87 | BR36: 778339.14 | BS36: 944646.21 | BT36: 1012269.6 | BU36: 960022.01 | BV36: 1085525.1 | BW36: =1147986.56+11674.95 -> 1159661.5 | BX36: =1093718.13+14417.35 -> 1108135.5 | BY36: =1233785.64+14335.94 -> 1248121.6 | BZ36: =1211047.94+14796.87 -> 1225844.8 | CA36: =1124173.69+15015.44 -> 1139189.1 | CB36: =1229202.9+14845.09 -> 1244048 | CM36: =sum(BW36:BY36) -> 3515918.6 | CN36: =sum(BZ36:CB36) -> 3609081.9 | CO36: =sum(CC36:CE36) -> 0 | CP36: =sum(CF36:CH36) -> 0 | CQ36: =sum(BW36:CH36) -> 7125000.5 | CS36: =sum(BK36:BM36) -> 1857299.1 | CT36: =sum(BN36:BP36) -> 2057567.4 | CU36: =sum(BQ36:BS36) -> 2509160.2 | CV36: =sum(BT36:BV36) -> 3057816.7 | CW36: =sum(BK36:BV36) -> 9481843.3
B37: SN Software | CM37: =sum(BW37:BY37) -> 0 | CN37: =sum(BZ37:CB37) -> 0 | CO37: =sum(CC37:CE37) -> 0 | CP37: =sum(CF37:CH37) -> 0 | CQ37: =sum(BW37:CH37) -> 0 | CS37: =sum(BK37:BM37) -> 0 | CT37: =sum(BN37:BP37) -> 0 | CU37: =sum(BQ37:BS37) -> 0 | CV37: =sum(BT37:BV37) -> 0 | CW37: =sum(BK37:BV37) -> 0
B38: SN MSP | CM38: =sum(BW38:BY38) -> 0 | CN38: =sum(BZ38:CB38) -> 0 | CO38: =sum(CC38:CE38) -> 0 | CP38: =sum(CF38:CH38) -> 0 | CQ38: =sum(BW38:CH38) -> 0 | CS38: =sum(BK38:BM38) -> 0 | CT38: =sum(BN38:BP38) -> 0 | CU38: =sum(BQ38:BS38) -> 0 | CV38: =sum(BT38:BV38) -> 0 | CW38: =sum(BK38:BV38) -> 0
B39: COGS Travel | AN39: 29.53 | AS39: 3333.82 | AT39: 20799.87 | AU39: 11151.79 | AV39: 4737.28 | AW39: 25760.6 | AX39: 18919.63 | AY39: 33215.67 | AZ39: 10234.94 | BA39: 5714.25 | BB39: 21267.85 | BC39: 41362.2 | BD39: 23920.06 | BE39: 13805.86 | BF39: 48205.8 | BG39: 10708.23 | BH39: 5814.45 | BI39: 10713.14 | BJ39: 15901.12 | BK39: =SUM(BK40:BK41) -> 19663.72 | BL39: =SUM(BL40:BL41) -> 32386.54 | BM39: =SUM(BM40:BM41) -> 13031.72 | BN39: =SUM(BN40:BN41) -> 7012.64 | BO39: =SUM(BO40:BO41) -> 35723.43 | BP39: =SUM(BP40:BP41) -> 14203.39 | BQ39: =SUM(BQ40:BQ41) -> 17192.73 | BR39: =SUM(BR40:BR41) -> 103359.7 | ... CH39: =SUM(CH40:CH41) -> 0 | CM39: =sum(BW39:BY39) -> 119150.58 | CN39: =sum(BZ39:CB39) -> 115312.83 | CO39: =sum(CC39:CE39) -> 0 | CP39: =sum(CF39:CH39) -> 0 | CQ39: =sum(BW39:CH39) -> 234463.41 | CS39: =sum(BK39:BM39) -> 65081.98 | CT39: =sum(BN39:BP39) -> 56939.46 | CU39: =sum(BQ39:BS39) -> 139598.04 | CV39: =sum(BT39:BV39) -> 55236.61 | CW39: =sum(BK39:BV39) -> 316856.09
B40: DD | AY40: 11007.83 | AZ40: 1541.06 | BA40: 2157.48 | BB40: 9375.99 | BC40: 12447.67 | BD40: 4955 | BE40: 5690.34 | BF40: 7451.24 | BG40: 7096.92 | BH40: 2513.97 | BI40: 5288.27 | BJ40: 3039.37 | BK40: 10443.23 | BL40: 7763.67 | BM40: 3905.16 | BN40: 2158.4 | BO40: 16326.19 | BP40: 6450.11 | BQ40: 4621.4 | BR40: 26894.86 | BS40: 6057.61 | BT40: 7193.08 | BU40: 12376.22 | BV40: 3878.67 | BW40: 11911.5 | BX40: 17972.29 | BY40: 15361.53 | BZ40: 10345.6 | CA40: 10396.55 | CB40: 11797.94 | CM40: =sum(BW40:BY40) -> 45245.32 | CN40: =sum(BZ40:CB40) -> 32540.09 | CO40: =sum(CC40:CE40) -> 0 | CP40: =sum(CF40:CH40) -> 0 | CQ40: =sum(BW40:CH40) -> 77785.41 | CS40: =sum(BK40:BM40) -> 22112.06 | CT40: =sum(BN40:BP40) -> 24934.7 | CU40: =sum(BQ40:BS40) -> 37573.87 | CV40: =sum(BT40:BV40) -> 23447.97 | CW40: =sum(BK40:BV40) -> 108068.6
B41: SN | AY41: 22207.84 | AZ41: 8693.88 | BA41: 3556.77 | BB41: 11891.86 | BC41: 28914.53 | BD41: 18965.06 | BE41: 8115.52 | BF41: 40754.56 | BG41: 3611.31 | BH41: 3300.48 | BI41: 5424.87 | BJ41: 12861.75 | BK41: 9220.49 | BL41: 24622.87 | BM41: 9126.56 | BN41: 4854.24 | BO41: 19397.24 | BP41: 7753.28 | BQ41: 12571.33 | BR41: 76464.84 | BS41: 12988 | BT41: 12625.02 | BU41: 14239.52 | BV41: 4924.1 | BW41: 35938.57 | BX41: 25388.37 | BY41: 12578.32 | BZ41: 14370.93 | CA41: 32419.45 | CB41: 35982.36 | CM41: =sum(BW41:BY41) -> 73905.26 | CN41: =sum(BZ41:CB41) -> 82772.74 | CO41: =sum(CC41:CE41) -> 0 | CP41: =sum(CF41:CH41) -> 0 | CQ41: =sum(BW41:CH41) -> 156678 | CS41: =sum(BK41:BM41) -> 42969.92 | CT41: =sum(BN41:BP41) -> 32004.76 | CU41: =sum(BQ41:BS41) -> 102024.17 | CV41: =sum(BT41:BV41) -> 31788.64 | CW41: =sum(BK41:BV41) -> 208787.49
B42: Marketplace Fees | BK42: 0 | BL42: 0 | BM42: 0 | BN42: 0 | BO42: 0 | BP42: 0 | BQ42: 0 | BR42: 17815.43 | BS42: 19129.73 | BT42: 19130.87 | BU42: 27038.75 | BV42: 19316.63 | BW42: 25159.8 | BX42: 26486.7 | BY42: 24993.15 | BZ42: 23476.8 | CA42: 25005.99 | CB42: 23273.69 | CM42: =sum(BW42:BY42) -> 76639.65 | CN42: =sum(BZ42:CB42) -> 71756.48 | CO42: =sum(CC42:CE42) -> 0 | CP42: =sum(CF42:CH42) -> 0 | CQ42: =sum(BW42:CH42) -> 148396.13 | CS42: =sum(BK42:BM42) -> 0 | CT42: =sum(BN42:BP42) -> 0 | CU42: =sum(BQ42:BS42) -> 36945.16 | CV42: =sum(BT42:BV42) -> 65486.25 | CW42: =sum(BK42:BV42) -> 102431.41
B43: Contractor Fees | BB43: 30000 | BC43: 30000 | BD43: 30000 | BE43: 30000 | BF43: 40000 | BG43: 15000 | BH43: 25000 | BI43: 18160 | BJ43: 28720 | BK43: 27840 | BL43: 48080 | BM43: 29600 | BN43: 880 | BO43: 19360 | BP43: 0 | BQ43: 0 | BR43: 0 | BS43: 0 | BT43: 0 | BU43: 0 | BV43: 0 | CM43: =sum(BW43:BY43) -> 0 | CN43: =sum(BZ43:CB43) -> 0 | CO43: =sum(CC43:CE43) -> 0 | CP43: =sum(CF43:CH43) -> 0 | CQ43: =sum(BW43:CH43) -> 0 | CS43: =sum(BK43:BM43) -> 105520 | CT43: =sum(BN43:BP43) -> 20240 | CU43: =sum(BQ43:BS43) -> 0 | CV43: =sum(BT43:BV43) -> 0 | CW43: =sum(BK43:BV43) -> 125760
B44: Total DD COGS | AY44: =AY42+AY40+AY30 -> 340792.89 | AZ44: =AZ42+AZ40+AZ30 -> 306671.14 | BA44: =BA42+BA40+BA30 -> 288761.32 | BB44: =BB42+BB40+BB30 -> 417680.31 | BC44: =BC42+BC40+BC30 -> 274306.84 | BD44: =BD42+BD40+BD30 -> 267155.4 | BE44: =BE42+BE40+BE30 -> 273054.37 | BF44: =BF42+BF40+BF30 -> 465535.47 | ... BW44: =BW42+BW40+BW30 -> 643662.18 | BX44: =BX30 -> 507460.14 | BY44: =BY30 -> 676650.82 | BZ44: =BZ42+BZ40+BZ30 -> 705273.34 | CA44: =CA42+CA40+CA30 -> 588451.05 | CB44: =CB42+CB40+CB30 -> 606492 | CC44: =CC42+CC40+CC30 -> 0 | CD44: =CD42+CD40+CD30 -> 0 | CE44: =CE42+CE40+CE30 -> 0 | CF44: =CF42+CF40+CF30 -> 0 | CG44: =CG42+CG40+CG30 -> 0 | CH44: =CH42+CH40+CH30 -> 0 | CM44: =sum(BW44:BY44) -> 1827773.1 | CN44: =sum(BZ44:CB44) -> 1900216.4 | CO44: =sum(CC44:CE44) -> 0 | CP44: =sum(CF44:CH44) -> 0 | CQ44: =sum(BW44:CH44) -> 3727989.5 | CS44: =sum(BK44:BM44) -> 1219530 | CT44: =sum(BN44:BP44) -> 1236517.3 | CU44: =sum(BQ44:BS44) -> 1383521.2 | CV44: =sum(BT44:BV44) -> 1778396.1 | CW44: =sum(BK44:BV44) -> 5617964.6
B45: Total SN COGS | AY45: =AY43+AY41+AY35 -> 449165.99 | AZ45: =AZ43+AZ41+AZ35 -> 388956.88 | BA45: =BA43+BA41+BA35 -> 395358.48 | BB45: =BB43+BB41+BB35 -> 597553.54 | BC45: =BC43+BC41+BC35 -> 465261.92 | BD45: =BD43+BD41+BD35 -> 446347.56 | BE45: =BE43+BE41+BE35 -> 449963.82 | BF45: =BF43+BF41+BF35 -> 811963.46 | ... CH45: =CH43+CH41+CH35 -> 0 | CM45: =sum(BW45:BY45) -> 3589823.8 | CN45: =sum(BZ45:CB45) -> 3691854.7 | CO45: =sum(CC45:CE45) -> 0 | CP45: =sum(CF45:CH45) -> 0 | CQ45: =sum(BW45:CH45) -> 7281678.5 | CS45: =sum(BK45:BM45) -> 2005789 | CT45: =sum(BN45:BP45) -> 2109812.2 | CU45: =sum(BQ45:BS45) -> 2611184.4 | CV45: =sum(BT45:BV45) -> 3089605.3 | CW45: =sum(BK45:BV45) -> 9816390.8
B47: Gross Margin $ | AM47: =AM13-AM28 -> 1303693.3 | AN47: =AN13-AN28 -> 1340092.6 | AO47: =AO13-AO28 -> 1601989.4 | AP47: =AP13-AP28 -> 1082803.4 | AQ47: =AQ13-AQ28 -> 1263946.5 | AR47: =AR13-AR28 -> 1248345.4 | AS47: =AS13-AS28 -> 983614.28 | AT47: =AT13-AT28 -> 1023610.4 | ... CH47: =CH13-CH28 -> 0 | CM47: =sum(BW47:BY47) -> 7112184.7 | CN47: =sum(BZ47:CB47) -> 8110931.3 | CS47: =CS13-CS28 -> 4198291.5 | CT47: =CT13-CT28 -> 4696365.4 | CU47: =CU13-CU28 -> 5504023.9 | CV47: =CV13-CV28 -> 6144890.5 | CW47: =CW13-CW28 -> 20543571 | CY47: =CY13-CY28 -> 3293852.2 | CZ47: =CZ13-CZ28 -> 3282484.9 | DA47: =DA13-DA28 -> 3565998.4 | DB47: =DB13-DB28 -> 4779013.3 | DC47: =DC13-DC28 -> 14921349 | FW47: =FW13-FW28 -> 19177694
B48: DD | AY48: =AY14-AY30 -> 581475.03 | AZ48: =AZ14-AZ30 -> 741255.2 | BA48: =BA14-BA30 -> 818517.84 | BB48: =BB14-BB30 -> 544044.01 | BC48: =BC14-BC30 -> 496476.7 | BD48: =BD14-BD30 -> 438959.56 | BE48: =BE14-BE30 -> 550189.7 | BF48: =BF14-BF30 -> 347207.31 | ... BS48: =BS14-BS30 -> 529675.14 | BT48: =BT14-BT44 -> 411908.79 | BU48: =BU14-BU30 -> 452263.51 | BV48: =BV14-BV30 -> 417975.9 | BW48: =BW14-BW30 -> 532156.01 | BX48: =BX14-BX30 -> 656152.17 | BY48: =BY14-BY30 -> 489485.1 | BZ48: =BZ14-BZ30 -> 768363.22 | CA48: =CA14-CA30 -> 1128231.5 | CB48: =CB14-CB30 -> 695629.44 | ... CH48: =CH14-CH30 -> 0
B49: DD Services | AY49: =AY15-AY31-AY40 -> 489724.2 | AZ49: =AZ15-AZ31-AZ40 -> 660091.14 | BA49: =BA15-BA31-BA40 -> 734984.36 | BB49: =BB15-BB31-BB40 -> 462062.02 | BC49: =BC15-BC31-BC40 -> 397716.03 | BD49: =BD15-BD31-BD40 -> 354823.56 | BE49: =BE15-BE31-BE40 -> 463650.36 | BF49: =BF15-BF31-BF40 -> 265449.07 | ... CH49: =CH15-CH31-CH40 -> 0 | EE49: {=IF(EE$3>'GAAP Summary'!$B$2,0,SUM(INDIRECT(XLOOKUP(EE$3,'TTM Dates'!$B:$B,'TTM Dates'!$E:$E)&ROW($CJ49)&":"&XLOOKUP(EE$3,'TTM Dates'!$B:$B,'TTM Dates'!$C:$C)&ROW($CJ49))))} -> 0
B50: DD Software | BR50: =BR16-BR42 -> 48455.26 | BS50: =BS16-BS42 -> 50123.96 | BT50: =BT16-BT42 -> 50282.63 | BU50: =BU16-BU42 -> 68734.34 | BV50: =BV16-BV42 -> 50716.06 | BW50: =BW16-BW42 -> 59747.03 | BX50: =BX16-BX42 -> 62843.13 | BY50: =BY16-BY42 -> 62053.17 | ... CH50: =CH16-CH42 -> 0 | EE50: {=IF(EE$3>'GAAP Summary'!$B$2,0,SUM(INDIRECT(XLOOKUP(EE$3,'TTM Dates'!$B:$B,'TTM Dates'!$E:$E)&ROW($CJ50)&":"&XLOOKUP(EE$3,'TTM Dates'!$B:$B,'TTM Dates'!$C:$C)&ROW($CJ50))))} -> 0
B51: Managed DD | BC51: =BC17-BC33 -> 6667 | BD51: =BD17-BD33 -> 6667 | BE51: =BE17-BE33 -> 6667 | BF51: =BF17-BF33 -> 0 | BG51: =BG17-BG33 -> -11603.86 | BH51: =BH17-BH33 -> 45541.1 | BI51: =BI17-BI33 -> 63225.51 | BJ51: =BJ17-BJ33 -> 66498.84 | ... CH51: =CH17-CH33 -> 0 | CM51: =sum(BW51:BY51) -> 127428.06 | CN51: =sum(BZ51:CB51) -> 136868.47 | CO51: =sum(CC51:CE51) -> 0 | CP51: =sum(CF51:CH51) -> 0 | CQ51: =sum(BW51:CH51) -> 264296.53 | CS51: =sum(BK51:BM51) -> 23391.65 | CT51: =sum(BN51:BP51) -> 41505.68 | CU51: =sum(BQ51:BS51) -> 44369.14 | CV51: =sum(BT51:BV51) -> 154319.25 | CW51: =sum(BK51:BV51) -> 263585.72
B52: Managed Security | BK52: =BK18-BK34 -> 0 | BL52: =BL18-BL34 -> 0 | BM52: =BM18-BM34 -> -11589.03 | BN52: =BN18-BN34 -> 2297.25 | BO52: =BO18-BO34 -> 27775.62 | BP52: =BP18-BP34 -> 28256.82 | BQ52: =BQ18-BQ34 -> 22539.29 | BR52: =BR18-BR34 -> 16792.37 | ... CH52: =CH18-CH34 -> 0 | CM52: =sum(BW52:BY52) -> 114415.63 | CN52: =sum(BZ52:CB52) -> 142933.87 | CO52: =sum(CC52:CE52) -> 0 | CP52: =sum(CF52:CH52) -> 0 | CQ52: =sum(BW52:CH52) -> 257349.5 | CS52: =sum(BK52:BM52) -> -11589.03 | CT52: =sum(BN52:BP52) -> 58329.69 | CU52: =sum(BQ52:BS52) -> 54112.02 | CV52: =sum(BT52:BV52) -> 95539.24 | CW52: =sum(BK52:BV52) -> 196391.92
B53: SN | AY53: =AY19-AY35 -> 344123.68 | AZ53: =AZ19-AZ35 -> 442280.59 | BA53: =BA19-BA35 -> 415364.13 | BB53: =BB19-BB35 -> 495712.64 | BC53: =BC19-BC35 -> 751367.97 | BD53: =BD19-BD35 -> 732474.25 | BE53: =BE19-BE35 -> 851519.33 | BF53: =BF19-BF35 -> 630705.94 | ... BS53: =BS19-BS35 -> 1523173.1 | BT53: =BT19-BT45 -> 2005514.4 | BU53: =BU19-BU35 -> 1342917.9 | BV53: =BV19-BV35 -> 1533473.7 | BW53: =BW19-BW35 -> 1783170.3 | BX53: =BX19-BX35 -> 1772813.6 | BY53: =BY19-BY35 -> 2033843.1 | BZ53: =BZ19-BZ35 -> 1921748.6 | CA53: =CA19-CA35 -> 1534502.4 | CB53: =CB19-CB35 -> 2190977.1 | ... CH53: =CH19-CH35 -> 0
B54: SN Services | AY54: =AY20-AY36 -> 344123.68 | AZ54: =AZ20-AZ36 -> 389480.59 | BA54: =BA20-BA36 -> 415364.13 | BB54: =BB20-BB36 -> 495712.64 | BC54: =BC20-BC36 -> 751367.97 | BD54: =BD20-BD36 -> 732474.25 | BE54: =BE20-BE36 -> 845686.33 | BF54: =BF20-BF36 -> 624872.94 | ... CH54: =CH20-CH36 -> 0
B55: SN Software
B56: SN MSP
B57: Gross Margin % | AM57: =AM47/AM13 -> 0.61143046 | AN57: =AN47/AN13 -> 0.68940477 | AO57: =AO47/AO13 -> 0.7192514 | AP57: =AP47/AP13 -> 0.58703612 | AQ57: =AQ47/AQ13 -> 0.66495679 | AR57: =AR47/AR13 -> 0.67799681 | AS57: =AS47/AS13 -> 0.60189087 | AT57: =AT47/AT13 -> 0.51555771 | ... CH57: =CH47/CH13 -> #DIV/0! | CM57: =CM47/CM13 -> 0.56561544 | CN57: =CN47/CN13 -> 0.59444895 | CO57: =CO47/CO13 -> #DIV/0! | CP57: =CP47/CP13 -> #DIV/0! | CS57: =CS47/CS13 -> 0.56553227 | CT57: =CT47/CT13 -> 0.58392931 | CU57: =CU47/CU13 -> 0.57944844 | CV57: =CV47/CV13 -> 0.56116279 | CW57: =CW47/CW13 -> 0.57200028 | CY57: =CY47/CY13 -> 0.60287674 | CZ57: =CZ47/CZ13 -> 0.57078845 | DA57: =DA47/DA13 -> 0.55609995 | DB57: =DB47/DB13 -> 0.61839585 | DC57: =DC47/DC13 -> 0.5884986 | FW57: =FW47/FW13 -> 0.58659731
B58: DD | AY58: =AY48/AY14 -> 0.63809996 | AZ58: =AZ48/AZ14 -> 0.70839605 | BA58: =BA48/BA14 -> 0.74065857 | BB58: =BB48/BB14 -> 0.57126578 | BC58: =BC48/BC14 -> 0.65469236 | BD58: =BD48/BD14 -> 0.62604767 | BE58: =BE48/BE14 -> 0.67297069 | BF58: =BF48/BF14 -> 0.43115728 | ... CH58: =CH48/CH14 -> #DIV/0!
B59: DD Services | AY59: =AY49/AY15 -> 0.5896618 | AZ59: =AZ49/AZ15 -> 0.68278537 | BA59: =BA49/BA15 -> 0.71793647 | BB59: =BB49/BB15 -> 0.52522427 | BC59: =BC49/BC15 -> 0.59181919 | BD59: =BD49/BD15 -> 0.57047518 | BE59: =BE49/BE15 -> 0.62935711 | BF59: =BF49/BF15 -> 0.3631391 | ... CH59: =CH49/CH15 -> #DIV/0!
B60: DD Software | BR60: =BR50/BR16 -> 0.7311718 | BS60: =BS50/BS16 -> 0.72377313 | BT60: =BT50/BT16 -> 0.72439266 | BU60: =BU50/BU16 -> 0.71767905 | BV60: =BV50/BV16 -> 0.72417695 | BW60: =BW50/BW16 -> 0.70367755 | BX60: =BX50/BX16 -> 0.70349546 | BY60: =BY50/BY16 -> 0.71287528 | ... CH60: =CH50/CH16 -> #DIV/0!
B61: Managed DD | BC61: =BC51/BC17 -> 1 | BD61: =BD51/BD17 -> 1 | BE61: =BE51/BE17 -> 1 | BG61: =BG51/BG17 -> -2.1548487 | BH61: =BH51/BH17 -> 0.51412396 | BI61: =BI51/BI17 -> 0.71376733 | BJ61: =BJ51/BJ17 -> 0.70951773 | BK61: =BK51/BK17 -> 0.1985748 | BL61: =BL51/BL17 -> 0.23312556 | BM61: =BM51/BM17 -> 0.25725503 | BN61: =BN51/BN17 -> 0.081785153 | ... CH61: =CH51/CH17 -> #DIV/0! | CS61: =CS51/CS17 -> 0.2289528 | CT61: =CT51/CT17 -> 0.31959295 | CU61: =CU51/CU17 -> 0.29360122 | CV61: =CV51/CV17 -> 0.52277454
B62: Managed Security | BN62: =BN52/BN18 -> 0.15520732 | BO62: =BO52/BO18 -> 0.69262863 | BP62: =BP52/BP18 -> 0.7046281 | BQ62: =BQ52/BQ18 -> 0.49426371 | BR62: =BR52/BR18 -> 0.3682396 | BS62: =BS52/BS18 -> 0.32411826 | BT62: =BT52/BT18 -> 0.56143028 | BU62: =BU52/BU18 -> 0.40454382 | ... CH62: =CH52/CH18 -> #DIV/0! | CS62: =CS52/CS18 -> #DIV/0! | CT62: =CT52/CT18 -> 0.61396656 | CU62: =CU52/CU18 -> 0.39554052 | CV62: =CV52/CV18 -> 0.43699191
B63: SN | AY63: =AY53/AY19 -> 0.44628685 | AZ63: =AZ53/AZ19 -> 0.53769866 | BA63: =BA53/BA19 -> 0.51459577 | BB63: =BB53/BB19 -> 0.47149015 | BC63: =BC53/BC19 -> 0.64900924 | BD63: =BD53/BD19 -> 0.64828948 | BE63: =BE53/BE19 -> 0.67400756 | BF63: =BF53/BF19 -> 0.46310233 | ... CH63: =CH53/CH19 -> #DIV/0!
B64: SN Services | AY64: =AY54/AY20 -> 0.44628685 | AZ64: =AZ54/AZ20 -> 0.50598744 | BA64: =BA54/BA20 -> 0.51459577 | BB64: =BB54/BB20 -> 0.47149015 | BC64: =BC54/BC20 -> 0.64900924 | BD64: =BD54/BD20 -> 0.64828948 | BE64: =BE54/BE20 -> 0.67249546 | BF64: =BF54/BF20 -> 0.46079294 | ... CH64: =CH54/CH20 -> #DIV/0!
B65: SN Software
B66: SN MSP
B67: Gross Margin % | AA67: =1-IFERROR(AA28/AA13,0) -> 0.75682253 | AB67: =1-IFERROR(AB28/AB13,0) -> 0.64929598 | AC67: =1-IFERROR(AC28/AC13,0) -> 0.73851411 | AD67: =1-IFERROR(AD28/AD13,0) -> 0.6483928 | AE67: =1-IFERROR(AE28/AE13,0) -> 0.69332546 | AF67: =1-IFERROR(AF28/AF13,0) -> 0.74799101 | AG67: =1-IFERROR(AG28/AG13,0) -> 0.6617132 | AH67: =1-IFERROR(AH28/AH13,0) -> 0.76974902 | ... CH67: =1-IFERROR(CH28/CH13,0) -> 1
B69: Operating Expenses | C69: =SUM(C70:C81) -> 0 | D69: =SUM(D70:D81) -> 0 | E69: =SUM(E70:E81) -> 0 | F69: =SUM(F70:F81) -> 0 | G69: =SUM(G70:G81) -> 0 | H69: =SUM(H70:H81) -> 0 | I69: =SUM(I70:I81) -> 0 | J69: =SUM(J70:J81) -> 0 | ... AL69: =SUM(AL70:AL81) -> 806633 | AM69: =SUM(AM70,AM74,AM78) -> 750785 | AN69: =SUM(AN70,AN74,AN78) -> 807790 | AO69: =SUM(AO70,AO74,AO78) -> 833956 | AP69: =SUM(AP70,AP74,AP78) -> 1057484 | AQ69: =SUM(AQ70,AQ74,AQ78) -> 935219 | AR69: =SUM(AR70,AR74,AR78) -> 975779 | AS69: =SUM(AS70,AS74,AS78) -> 1202190 | AT69: =SUM(AT70,AT74,AT78) -> 1006119 | ... AX69: =SUM(AX70,AX74,AX78) -> 942178 | AY69: 1312056.9 | AZ69: 1056956 | BA69: 1205039.9 | BB69: 1159760 | BC69: 1264048.2 | BD69: 1325176.6 | BE69: 1148718.9 | BF69: 1082979.5 | BG69: 1177369.5 | BH69: 1174269 | BI69: 1110814.7 | BJ69: 1193483.1 | BK69: 1349799 | BL69: 1003637.8 | BM69: 1072361.9 | BN69: 1413998.2 | BO69: 1451019.7 | BP69: 1362210.6 | BQ69: 1337099.6 | BR69: =SUM(BR70,BR74,BR78) -> 1504466 | BS69: =SUM(BS70,BS74,BS78) -> 1743412.6 | BT69: =SUM(BT70,BT74,BT78) -> 1737967.5 | BU69: =SUM(BU70,BU74,BU78) -> 1469663.5 | BV69: =SUM(BV70,BV74,BV78) -> 828493.58 | BW69: =SUM(BW70,BW74,BW78) -> 1753777.2 | BX69: =SUM(BX70,BX74,BX78) -> 1757748 | BY69: =SUM(BY70,BY74,BY78) -> 1791395.3 | ... CH69: =SUM(CH70,CH74,CH78) -> 0 | CK69: {=SUM(INDIRECT(XLOOKUP('GAAP Summary'!$B$2,'TTM Dates'!$B:$B,'TTM Dates'!$E:$E)&ROW($CJ69)&":"&XLOOKUP('GAAP Summary'!$B$2,'TTM Dates'!$B:$B,'TTM Dates'!$C:$C)&ROW($CJ69)))} -> 19953708 | CM69: =sum(BW69:BY69) -> 5302920.6 | CN69: =sum(BZ69:CB69) -> 6029685 | CO69: =sum(CC69:CE69) -> 0 | CP69: =sum(CF69:CH69) -> 0 | CQ69: =sum(BW69:CH69) -> 11332606 | CS69: =sum(BK69:BM69) -> 3425798.7 | CT69: =sum(BN69:BP69) -> 4227228.5 | CU69: =sum(BQ69:BS69) -> 4584978.3 | CV69: =sum(BT69:BV69) -> 4036124.6 | CW69: =sum(BK69:BV69) -> 16274130 | CY69: =sum(AY69:BA69) -> 3574052.7 | CZ69: =sum(BB69:BD69) -> 3748984.7 | DA69: =sum(BE69:BG69) -> 3409067.9 | DB69: =sum(BH69:BJ69) -> 3478566.8 | DC69: =sum(AY69:BJ69) -> 14210672 | DE69: =sum(AM69:AO69) -> 2392531 | DF69: =sum(AP69:AR69) -> 2968482 | DG69: =sum(AS69:AU69) -> 3222857 | DH69: =sum(AV69:AX69) -> 3041814 | DI69: =sum(AM69:AX69) -> 11625684 | DK69: =sum(AA69:AC69) -> 1582384 | DL69: =sum(AD69:AF69) -> 1727131 | DM69: =sum(AG69:AI69) -> 1853346 | DN69: =sum(AJ69:AL69) -> 2417418 | DO69: =sum(DO70:DO78) -> 7580279 | DQ69: =sum(DQ70:DQ78) -> 0 | DS69: {=IF(DS$3>'GAAP Summary'!$B$2,0,SUM(INDIRECT(XLOOKUP(DS$3,'TTM Dates'!$B:$B,'TTM Dates'!$E:$E)&ROW($CJ69)&":"&XLOOKUP(DS$3,'TTM Dates'!$B:$B,'TTM Dates'!$C:$C)&ROW($CJ69))))} -> 0 | DT69: {=IF(DT$3>'GAAP Summary'!$B$2,0,SUM(INDIRECT(XLOOKUP(DT$3,'TTM Dates'!$B:$B,'TTM Dates'!$E:$E)&ROW($CJ69)&":"&XLOOKUP(DT$3,'TTM Dates'!$B:$B,'TTM Dates'!$C:$C)&ROW($CJ69))))} -> 0 | DU69: {=IF(DU$3>'GAAP Summary'!$B$2,0,SUM(INDIRECT(XLOOKUP(DU$3,'TTM Dates'!$B:$B,'TTM Dates'!$E:$E)&ROW($CJ69)&":"&XLOOKUP(DU$3,'TTM Dates'!$B:$B,'TTM Dates'!$C:$C)&ROW($CJ69))))} -> 0 | DV69: {=IF(DV$3>'GAAP Summary'!$B$2,0,SUM(INDIRECT(XLOOKUP(DV$3,'TTM Dates'!$B:$B,'TTM Dates'!$E:$E)&ROW($CJ69)&":"&XLOOKUP(DV$3,'TTM Dates'!$B:$B,'TTM Dates'!$C:$C)&ROW($CJ69))))} -> 0 | DW69: {=IF(DW$3>'GAAP Summary'!$B$2,0,SUM(INDIRECT(XLOOKUP(DW$3,'TTM Dates'!$B:$B,'TTM Dates'!$E:$E)&ROW($CJ69)&":"&XLOOKUP(DW$3,'TTM Dates'!$B:$B,'TTM Dates'!$C:$C)&ROW($CJ69))))} -> 0 | DX69: {=IF(DX$3>'GAAP Summary'!$B$2,0,SUM(INDIRECT(XLOOKUP(DX$3,'TTM Dates'!$B:$B,'TTM Dates'!$E:$E)&ROW($CJ69)&":"&XLOOKUP(DX$3,'TTM Dates'!$B:$B,'TTM Dates'!$C:$C)&ROW($CJ69))))} -> 0 | DY69: {=IF(DY$3>'GAAP Summary'!$B$2,0,SUM(INDIRECT(XLOOKUP(DY$3,'TTM Dates'!$B:$B,'TTM Dates'!$E:$E)&ROW($CJ69)&":"&XLOOKUP(DY$3,'TTM Dates'!$B:$B,'TTM Dates'!$C:$C)&ROW($CJ69))))} -> 0 | DZ69: {=IF(DZ$3>'GAAP Summary'!$B$2,0,SUM(INDIRECT(XLOOKUP(DZ$3,'TTM Dates'!$B:$B,'TTM Dates'!$E:$E)&ROW($CJ69)&":"&XLOOKUP(DZ$3,'TTM Dates'!$B:$B,'TTM Dates'!$C:$C)&ROW($CJ69))))} -> 0 | ... GL69: {=IF(GL$3>'GAAP Summary'!$B$2,0,SUM(INDIRECT(XLOOKUP(GL$3,'TTM Dates'!$B:$B,'TTM Dates'!$E:$E)&ROW($CJ69)&":"&XLOOKUP(GL$3,'TTM Dates'!$B:$B,'TTM Dates'!$C:$C)&ROW($CJ69))))} -> 0
B70: Total General & Administrative | C70: =SUM(C71:C73) -> 0 | D70: =SUM(D71:D73) -> 0 | E70: =SUM(E71:E73) -> 0 | F70: =SUM(F71:F73) -> 0 | G70: =SUM(G71:G73) -> 0 | H70: =SUM(H71:H73) -> 0 | I70: =SUM(I71:I73) -> 0 | J70: =SUM(J71:J73) -> 0 | ... Z70: =SUM(Z71:Z73) -> 0 | AA70: 88236 | AB70: 114630 | AC70: 102679 | AD70: 96679 | AE70: 101159 | AF70: 106891 | AG70: 115084 | AH70: 88548 | AI70: 150570 | AJ70: 159203 | AK70: 236348 | AL70: 169573 | AM70: 145164 | AN70: 131830 | AO70: 96082 | AP70: 158825 | AQ70: 100797 | AR70: 149868 | AS70: 130304 | AT70: 168903 | AU70: 155356 | AV70: 150802 | AW70: 132597 | AX70: 149474 | AY70: 156897 | AZ70: 182877 | BA70: 193516 | BB70: 169018 | BC70: 143886 | BD70: 130321 | BE70: 135692 | BF70: 139356 | BG70: 250729 | BH70: 143546 | BI70: 161291 | BJ70: 153253 | BK70: 194896 | BL70: 160730 | BM70: 168697 | BN70: 179355 | BO70: 170717 | BP70: 159610 | BQ70: 184811 | BR70: 253451 | BS70: 907972.77 | BT70: 728083.67 | BU70: 583065.15 | BV70: 622004.37 | BW70: 778978.06 | BX70: 866208.81 | BY70: 695908.27 | BZ70: 709332.27 | CA70: 831959.78 | CB70: 1039460.6 | CK70: {=SUM(INDIRECT(XLOOKUP('GAAP Summary'!$B$2,'TTM Dates'!$B:$B,'TTM Dates'!$E:$E)&ROW($CJ70)&":"&XLOOKUP('GAAP Summary'!$B$2,'TTM Dates'!$B:$B,'TTM Dates'!$C:$C)&ROW($CJ70)))} -> 8201235.8 | CM70: =sum(BW70:BY70) -> 2341095.1 | CN70: =sum(BZ70:CB70) -> 2580752.6 | CO70: =sum(CC70:CE70) -> 0 | CP70: =sum(CF70:CH70) -> 0 | CQ70: =sum(BW70:CH70) -> 4921847.8 | CS70: =sum(BK70:BM70) -> 524323 | CT70: =sum(BN70:BP70) -> 509682 | CU70: =sum(BQ70:BS70) -> 1346234.8 | CV70: =sum(BT70:BV70) -> 1933153.2 | CW70: =sum(BK70:BV70) -> 4313393 | CY70: =sum(AY70:BA70) -> 533290 | CZ70: =sum(BB70:BD70) -> 443225 | DA70: =sum(BE70:BG70) -> 525777 | DB70: =sum(BH70:BJ70) -> 458090 | DC70: =sum(AY70:BJ70) -> 1960382 | DE70: =sum(AM70:AO70) -> 373076 | DF70: =sum(AP70:AR70) -> 409490 | DG70: =sum(AS70:AU70) -> 454563 | DH70: =sum(AV70:AX70) -> 432873 | DI70: =sum(AM70:AX70) -> 1670002 | DK70: =sum(AA70:AC70) -> 305545 | DL70: =sum(AD70:AF70) -> 304729 | DM70: =sum(AG70:AI70) -> 354202 | DN70: =sum(AJ70:AL70) -> 565124 | DO70: =sum(AA70:AL70) -> 1529600 | DQ70: =SUM(O70:Z70) -> 0 | DS70: {=IF(DS$3>'GAAP Summary'!$B$2,0,SUM(INDIRECT(XLOOKUP(DS$3,'TTM Dates'!$B:$B,'TTM Dates'!$E:$E)&ROW($CJ70)&":"&XLOOKUP(DS$3,'TTM Dates'!$B:$B,'TTM Dates'!$C:$C)&ROW($CJ70))))} -> 0 | DT70: {=IF(DT$3>'GAAP Summary'!$B$2,0,SUM(INDIRECT(XLOOKUP(DT$3,'TTM Dates'!$B:$B,'TTM Dates'!$E:$E)&ROW($CJ70)&":"&XLOOKUP(DT$3,'TTM Dates'!$B:$B,'TTM Dates'!$C:$C)&ROW($CJ70))))} -> 0 | DU70: {=IF(DU$3>'GAAP Summary'!$B$2,0,SUM(INDIRECT(XLOOKUP(DU$3,'TTM Dates'!$B:$B,'TTM Dates'!$E:$E)&ROW($CJ70)&":"&XLOOKUP(DU$3,'TTM Dates'!$B:$B,'TTM Dates'!$C:$C)&ROW($CJ70))))} -> 0 | DV70: {=IF(DV$3>'GAAP Summary'!$B$2,0,SUM(INDIRECT(XLOOKUP(DV$3,'TTM Dates'!$B:$B,'TTM Dates'!$E:$E)&ROW($CJ70)&":"&XLOOKUP(DV$3,'TTM Dates'!$B:$B,'TTM Dates'!$C:$C)&ROW($CJ70))))} -> 0 | DW70: {=IF(DW$3>'GAAP Summary'!$B$2,0,SUM(INDIRECT(XLOOKUP(DW$3,'TTM Dates'!$B:$B,'TTM Dates'!$E:$E)&ROW($CJ70)&":"&XLOOKUP(DW$3,'TTM Dates'!$B:$B,'TTM Dates'!$C:$C)&ROW($CJ70))))} -> 0 | DX70: {=IF(DX$3>'GAAP Summary'!$B$2,0,SUM(INDIRECT(XLOOKUP(DX$3,'TTM Dates'!$B:$B,'TTM Dates'!$E:$E)&ROW($CJ70)&":"&XLOOKUP(DX$3,'TTM Dates'!$B:$B,'TTM Dates'!$C:$C)&ROW($CJ70))))} -> 0 | DY70: {=IF(DY$3>'GAAP Summary'!$B$2,0,SUM(INDIRECT(XLOOKUP(DY$3,'TTM Dates'!$B:$B,'TTM Dates'!$E:$E)&ROW($CJ70)&":"&XLOOKUP(DY$3,'TTM Dates'!$B:$B,'TTM Dates'!$C:$C)&ROW($CJ70))))} -> 0 | DZ70: {=IF(DZ$3>'GAAP Summary'!$B$2,0,SUM(INDIRECT(XLOOKUP(DZ$3,'TTM Dates'!$B:$B,'TTM Dates'!$E:$E)&ROW($CJ70)&":"&XLOOKUP(DZ$3,'TTM Dates'!$B:$B,'TTM Dates'!$C:$C)&ROW($CJ70))))} -> 0 | ... GL70: {=IF(GL$3>'GAAP Summary'!$B$2,0,SUM(INDIRECT(XLOOKUP(GL$3,'TTM Dates'!$B:$B,'TTM Dates'!$E:$E)&ROW($CJ70)&":"&XLOOKUP(GL$3,'TTM Dates'!$B:$B,'TTM Dates'!$C:$C)&ROW($CJ70))))} -> 0
B71: DD | CK71: {=SUM(INDIRECT(XLOOKUP('GAAP Summary'!$B$2,'TTM Dates'!$B:$B,'TTM Dates'!$E:$E)&ROW($CJ71)&":"&XLOOKUP('GAAP Summary'!$B$2,'TTM Dates'!$B:$B,'TTM Dates'!$C:$C)&ROW($CJ71)))} -> 0 | CM71: =sum(BW71:BY71) -> 0 | CN71: =sum(BZ71:CB71) -> 0 | CO71: =sum(CC71:CE71) -> 0 | CP71: =sum(CF71:CH71) -> 0 | CQ71: =sum(BW71:CH71) -> 0 | CS71: =sum(BK71:BM71) -> 0 | CT71: =sum(BN71:BP71) -> 0 | CU71: =sum(BQ71:BS71) -> 0 | CV71: =sum(BT71:BV71) -> 0 | CW71: =sum(BK71:BV71) -> 0 | CY71: =sum(AY71:BA71) -> 0 | CZ71: =sum(BB71:BD71) -> 0 | DA71: =sum(BE71:BG71) -> 0 | DB71: =sum(BH71:BJ71) -> 0 | DC71: =sum(AY71:BJ71) -> 0 | DE71: =sum(AM71:AO71) -> 0 | DF71: =sum(AP71:AR71) -> 0 | DG71: =sum(AS71:AU71) -> 0 | DH71: =sum(AV71:AX71) -> 0 | DI71: =sum(AM71:AX71) -> 0 | DS71: {=IF(DS$3>'GAAP Summary'!$B$2,0,SUM(INDIRECT(XLOOKUP(DS$3,'TTM Dates'!$B:$B,'TTM Dates'!$E:$E)&ROW($CJ71)&":"&XLOOKUP(DS$3,'TTM Dates'!$B:$B,'TTM Dates'!$C:$C)&ROW($CJ71))))} -> 0 | DT71: {=IF(DT$3>'GAAP Summary'!$B$2,0,SUM(INDIRECT(XLOOKUP(DT$3,'TTM Dates'!$B:$B,'TTM Dates'!$E:$E)&ROW($CJ71)&":"&XLOOKUP(DT$3,'TTM Dates'!$B:$B,'TTM Dates'!$C:$C)&ROW($CJ71))))} -> 0 | DU71: {=IF(DU$3>'GAAP Summary'!$B$2,0,SUM(INDIRECT(XLOOKUP(DU$3,'TTM Dates'!$B:$B,'TTM Dates'!$E:$E)&ROW($CJ71)&":"&XLOOKUP(DU$3,'TTM Dates'!$B:$B,'TTM Dates'!$C:$C)&ROW($CJ71))))} -> 0 | DV71: {=IF(DV$3>'GAAP Summary'!$B$2,0,SUM(INDIRECT(XLOOKUP(DV$3,'TTM Dates'!$B:$B,'TTM Dates'!$E:$E)&ROW($CJ71)&":"&XLOOKUP(DV$3,'TTM Dates'!$B:$B,'TTM Dates'!$C:$C)&ROW($CJ71))))} -> 0 | DW71: {=IF(DW$3>'GAAP Summary'!$B$2,0,SUM(INDIRECT(XLOOKUP(DW$3,'TTM Dates'!$B:$B,'TTM Dates'!$E:$E)&ROW($CJ71)&":"&XLOOKUP(DW$3,'TTM Dates'!$B:$B,'TTM Dates'!$C:$C)&ROW($CJ71))))} -> 0 | DX71: {=IF(DX$3>'GAAP Summary'!$B$2,0,SUM(INDIRECT(XLOOKUP(DX$3,'TTM Dates'!$B:$B,'TTM Dates'!$E:$E)&ROW($CJ71)&":"&XLOOKUP(DX$3,'TTM Dates'!$B:$B,'TTM Dates'!$C:$C)&ROW($CJ71))))} -> 0 | DY71: {=IF(DY$3>'GAAP Summary'!$B$2,0,SUM(INDIRECT(XLOOKUP(DY$3,'TTM Dates'!$B:$B,'TTM Dates'!$E:$E)&ROW($CJ71)&":"&XLOOKUP(DY$3,'TTM Dates'!$B:$B,'TTM Dates'!$C:$C)&ROW($CJ71))))} -> 0 | DZ71: {=IF(DZ$3>'GAAP Summary'!$B$2,0,SUM(INDIRECT(XLOOKUP(DZ$3,'TTM Dates'!$B:$B,'TTM Dates'!$E:$E)&ROW($CJ71)&":"&XLOOKUP(DZ$3,'TTM Dates'!$B:$B,'TTM Dates'!$C:$C)&ROW($CJ71))))} -> 0 | ... GL71: {=IF(GL$3>'GAAP Summary'!$B$2,0,SUM(INDIRECT(XLOOKUP(GL$3,'TTM Dates'!$B:$B,'TTM Dates'!$E:$E)&ROW($CJ71)&":"&XLOOKUP(GL$3,'TTM Dates'!$B:$B,'TTM Dates'!$C:$C)&ROW($CJ71))))} -> 0
B72: SN | CK72: {=SUM(INDIRECT(XLOOKUP('GAAP Summary'!$B$2,'TTM Dates'!$B:$B,'TTM Dates'!$E:$E)&ROW($CJ72)&":"&XLOOKUP('GAAP Summary'!$B$2,'TTM Dates'!$B:$B,'TTM Dates'!$C:$C)&ROW($CJ72)))} -> 0 | CM72: =sum(BW72:BY72) -> 0 | CN72: =sum(BZ72:CB72) -> 0 | CO72: =sum(CC72:CE72) -> 0 | CP72: =sum(CF72:CH72) -> 0 | CQ72: =sum(BW72:CH72) -> 0 | CS72: =sum(BK72:BM72) -> 0 | CT72: =sum(BN72:BP72) -> 0 | CU72: =sum(BQ72:BS72) -> 0 | CV72: =sum(BT72:BV72) -> 0 | CW72: =sum(BK72:BV72) -> 0 | CY72: =sum(AY72:BA72) -> 0 | CZ72: =sum(BB72:BD72) -> 0 | DA72: =sum(BE72:BG72) -> 0 | DB72: =sum(BH72:BJ72) -> 0 | DC72: =sum(AY72:BJ72) -> 0 | DE72: =sum(AM72:AO72) -> 0 | DF72: =sum(AP72:AR72) -> 0 | DG72: =sum(AS72:AU72) -> 0 | DH72: =sum(AV72:AX72) -> 0 | DI72: =sum(AM72:AX72) -> 0 | DS72: {=IF(DS$3>'GAAP Summary'!$B$2,0,SUM(INDIRECT(XLOOKUP(DS$3,'TTM Dates'!$B:$B,'TTM Dates'!$E:$E)&ROW($CJ72)&":"&XLOOKUP(DS$3,'TTM Dates'!$B:$B,'TTM Dates'!$C:$C)&ROW($CJ72))))} -> 0 | DT72: {=IF(DT$3>'GAAP Summary'!$B$2,0,SUM(INDIRECT(XLOOKUP(DT$3,'TTM Dates'!$B:$B,'TTM Dates'!$E:$E)&ROW($CJ72)&":"&XLOOKUP(DT$3,'TTM Dates'!$B:$B,'TTM Dates'!$C:$C)&ROW($CJ72))))} -> 0 | DU72: {=IF(DU$3>'GAAP Summary'!$B$2,0,SUM(INDIRECT(XLOOKUP(DU$3,'TTM Dates'!$B:$B,'TTM Dates'!$E:$E)&ROW($CJ72)&":"&XLOOKUP(DU$3,'TTM Dates'!$B:$B,'TTM Dates'!$C:$C)&ROW($CJ72))))} -> 0 | DV72: {=IF(DV$3>'GAAP Summary'!$B$2,0,SUM(INDIRECT(XLOOKUP(DV$3,'TTM Dates'!$B:$B,'TTM Dates'!$E:$E)&ROW($CJ72)&":"&XLOOKUP(DV$3,'TTM Dates'!$B:$B,'TTM Dates'!$C:$C)&ROW($CJ72))))} -> 0 | DW72: {=IF(DW$3>'GAAP Summary'!$B$2,0,SUM(INDIRECT(XLOOKUP(DW$3,'TTM Dates'!$B:$B,'TTM Dates'!$E:$E)&ROW($CJ72)&":"&XLOOKUP(DW$3,'TTM Dates'!$B:$B,'TTM Dates'!$C:$C)&ROW($CJ72))))} -> 0 | DX72: {=IF(DX$3>'GAAP Summary'!$B$2,0,SUM(INDIRECT(XLOOKUP(DX$3,'TTM Dates'!$B:$B,'TTM Dates'!$E:$E)&ROW($CJ72)&":"&XLOOKUP(DX$3,'TTM Dates'!$B:$B,'TTM Dates'!$C:$C)&ROW($CJ72))))} -> 0 | DY72: {=IF(DY$3>'GAAP Summary'!$B$2,0,SUM(INDIRECT(XLOOKUP(DY$3,'TTM Dates'!$B:$B,'TTM Dates'!$E:$E)&ROW($CJ72)&":"&XLOOKUP(DY$3,'TTM Dates'!$B:$B,'TTM Dates'!$C:$C)&ROW($CJ72))))} -> 0 | DZ72: {=IF(DZ$3>'GAAP Summary'!$B$2,0,SUM(INDIRECT(XLOOKUP(DZ$3,'TTM Dates'!$B:$B,'TTM Dates'!$E:$E)&ROW($CJ72)&":"&XLOOKUP(DZ$3,'TTM Dates'!$B:$B,'TTM Dates'!$C:$C)&ROW($CJ72))))} -> 0 | ... GL72: {=IF(GL$3>'GAAP Summary'!$B$2,0,SUM(INDIRECT(XLOOKUP(GL$3,'TTM Dates'!$B:$B,'TTM Dates'!$E:$E)&ROW($CJ72)&":"&XLOOKUP(GL$3,'TTM Dates'!$B:$B,'TTM Dates'!$C:$C)&ROW($CJ72))))} -> 0
B73: Operations | CK73: {=SUM(INDIRECT(XLOOKUP('GAAP Summary'!$B$2,'TTM Dates'!$B:$B,'TTM Dates'!$E:$E)&ROW($CJ73)&":"&XLOOKUP('GAAP Summary'!$B$2,'TTM Dates'!$B:$B,'TTM Dates'!$C:$C)&ROW($CJ73)))} -> 0 | CM73: =sum(BW73:BY73) -> 0 | CN73: =sum(BZ73:CB73) -> 0 | CO73: =sum(CC73:CE73) -> 0 | CP73: =sum(CF73:CH73) -> 0 | CQ73: =sum(BW73:CH73) -> 0 | CS73: =sum(BK73:BM73) -> 0 | CT73: =sum(BN73:BP73) -> 0 | CU73: =sum(BQ73:BS73) -> 0 | CV73: =sum(BT73:BV73) -> 0 | CW73: =sum(BK73:BV73) -> 0 | CY73: =sum(AY73:BA73) -> 0 | CZ73: =sum(BB73:BD73) -> 0 | DA73: =sum(BE73:BG73) -> 0 | DB73: =sum(BH73:BJ73) -> 0 | DC73: =sum(AY73:BJ73) -> 0 | DE73: =sum(AM73:AO73) -> 0 | DF73: =sum(AP73:AR73) -> 0 | DG73: =sum(AS73:AU73) -> 0 | DH73: =sum(AV73:AX73) -> 0 | DI73: =sum(AM73:AX73) -> 0 | DS73: {=IF(DS$3>'GAAP Summary'!$B$2,0,SUM(INDIRECT(XLOOKUP(DS$3,'TTM Dates'!$B:$B,'TTM Dates'!$E:$E)&ROW($CJ73)&":"&XLOOKUP(DS$3,'TTM Dates'!$B:$B,'TTM Dates'!$C:$C)&ROW($CJ73))))} -> 0 | DT73: {=IF(DT$3>'GAAP Summary'!$B$2,0,SUM(INDIRECT(XLOOKUP(DT$3,'TTM Dates'!$B:$B,'TTM Dates'!$E:$E)&ROW($CJ73)&":"&XLOOKUP(DT$3,'TTM Dates'!$B:$B,'TTM Dates'!$C:$C)&ROW($CJ73))))} -> 0 | DU73: {=IF(DU$3>'GAAP Summary'!$B$2,0,SUM(INDIRECT(XLOOKUP(DU$3,'TTM Dates'!$B:$B,'TTM Dates'!$E:$E)&ROW($CJ73)&":"&XLOOKUP(DU$3,'TTM Dates'!$B:$B,'TTM Dates'!$C:$C)&ROW($CJ73))))} -> 0 | DV73: {=IF(DV$3>'GAAP Summary'!$B$2,0,SUM(INDIRECT(XLOOKUP(DV$3,'TTM Dates'!$B:$B,'TTM Dates'!$E:$E)&ROW($CJ73)&":"&XLOOKUP(DV$3,'TTM Dates'!$B:$B,'TTM Dates'!$C:$C)&ROW($CJ73))))} -> 0 | DW73: {=IF(DW$3>'GAAP Summary'!$B$2,0,SUM(INDIRECT(XLOOKUP(DW$3,'TTM Dates'!$B:$B,'TTM Dates'!$E:$E)&ROW($CJ73)&":"&XLOOKUP(DW$3,'TTM Dates'!$B:$B,'TTM Dates'!$C:$C)&ROW($CJ73))))} -> 0 | DX73: {=IF(DX$3>'GAAP Summary'!$B$2,0,SUM(INDIRECT(XLOOKUP(DX$3,'TTM Dates'!$B:$B,'TTM Dates'!$E:$E)&ROW($CJ73)&":"&XLOOKUP(DX$3,'TTM Dates'!$B:$B,'TTM Dates'!$C:$C)&ROW($CJ73))))} -> 0 | DY73: {=IF(DY$3>'GAAP Summary'!$B$2,0,SUM(INDIRECT(XLOOKUP(DY$3,'TTM Dates'!$B:$B,'TTM Dates'!$E:$E)&ROW($CJ73)&":"&XLOOKUP(DY$3,'TTM Dates'!$B:$B,'TTM Dates'!$C:$C)&ROW($CJ73))))} -> 0 | DZ73: {=IF(DZ$3>'GAAP Summary'!$B$2,0,SUM(INDIRECT(XLOOKUP(DZ$3,'TTM Dates'!$B:$B,'TTM Dates'!$E:$E)&ROW($CJ73)&":"&XLOOKUP(DZ$3,'TTM Dates'!$B:$B,'TTM Dates'!$C:$C)&ROW($CJ73))))} -> 0 | ... GL73: {=IF(GL$3>'GAAP Summary'!$B$2,0,SUM(INDIRECT(XLOOKUP(GL$3,'TTM Dates'!$B:$B,'TTM Dates'!$E:$E)&ROW($CJ73)&":"&XLOOKUP(GL$3,'TTM Dates'!$B:$B,'TTM Dates'!$C:$C)&ROW($CJ73))))} -> 0
B74: Total Personnel Expenses | C74: =SUM(C75:C77) -> 0 | D74: =SUM(D75:D77) -> 0 | E74: =SUM(E75:E77) -> 0 | F74: =SUM(F75:F77) -> 0 | G74: =SUM(G75:G77) -> 0 | H74: =SUM(H75:H77) -> 0 | I74: =SUM(I75:I77) -> 0 | J74: =SUM(J75:J77) -> 0 | ... Z74: =SUM(Z75:Z77) -> 0 | AA74: 316042 | AB74: 329104 | AC74: 343840 | AD74: 326413 | AE74: 326413 | AF74: 347275 | AG74: 332800 | AH74: 348966 | AI74: 366089 | AJ74: 363389 | AK74: 379387 | AL74: 379387 | AM74: 504622 | AN74: 448787 | AO74: 566310 | AP74: 558635 | AQ74: 609628 | AR74: 642142 | AS74: 780132 | AT74: 639478 | AU74: 699620 | AV74: 756693 | AW74: 759401 | AX74: 618302 | AY74: 849306 | AZ74: 673323 | BA74: 769356 | BB74: 774307 | BC74: 724301 | BD74: 752863 | BE74: 875098 | BF74: 677594 | BG74: 780849 | BH74: 809566 | BI74: 726097 | BJ74: 868026 | BK74: 892047 | BL74: 622086 | BM74: 698078 | BN74: 1043790 | BO74: 782003 | BP74: 771751 | BQ74: 881455 | BR74: 743331 | BS74: 0 | BT74: 0 | BU74: 0 | BV74: 0 | BW74: 0 | BX74: 0 | BY74: 0 | BZ74: 0 | CA74: 0 | CB74: 0 | CC74: 0 | CD74: 0 | CE74: 0 | CF74: 0 | CG74: 0 | CH74: 0 | CK74: {=SUM(INDIRECT(XLOOKUP('GAAP Summary'!$B$2,'TTM Dates'!$B:$B,'TTM Dates'!$E:$E)&ROW($CJ74)&":"&XLOOKUP('GAAP Summary'!$B$2,'TTM Dates'!$B:$B,'TTM Dates'!$C:$C)&ROW($CJ74)))} -> 1624786 | CM74: =sum(BW74:BY74) -> 0 | CN74: =sum(BZ74:CB74) -> 0 | CO74: =sum(CC74:CE74) -> 0 | CP74: =sum(CF74:CH74) -> 0 | CQ74: =sum(BW74:CH74) -> 0 | CS74: =sum(BK74:BM74) -> 2212211 | CT74: =sum(BN74:BP74) -> 2597544 | CU74: =sum(BQ74:BS74) -> 1624786 | CV74: =sum(BT74:BV74) -> 0 | CW74: =sum(BK74:BV74) -> 6434541 | CY74: =sum(AY74:BA74) -> 2291985 | CZ74: =sum(BB74:BD74) -> 2251471 | DA74: =sum(BE74:BG74) -> 2333541 | DB74: =sum(BH74:BJ74) -> 2403689 | DC74: =sum(AY74:BJ74) -> 9280686 | DE74: =sum(AM74:AO74) -> 1519719 | DF74: =sum(AP74:AR74) -> 1810405 | DG74: =sum(AS74:AU74) -> 2119230 | DH74: =sum(AV74:AX74) -> 2134396 | DI74: =sum(AM74:AX74) -> 7583750 | DK74: =sum(AA74:AC74) -> 988986 | DL74: =sum(AD74:AF74) -> 1000101 | DM74: =sum(AG74:AI74) -> 1047855 | DN74: =sum(AJ74:AL74) -> 1122163 | DO74: =sum(AA74:AL74) -> 4159105 | DQ74: =SUM(O74:Z74) -> 0 | DS74: {=IF(DS$3>'GAAP Summary'!$B$2,0,SUM(INDIRECT(XLOOKUP(DS$3,'TTM Dates'!$B:$B,'TTM Dates'!$E:$E)&ROW($CJ74)&":"&XLOOKUP(DS$3,'TTM Dates'!$B:$B,'TTM Dates'!$C:$C)&ROW($CJ74))))} -> 0 | DT74: {=IF(DT$3>'GAAP Summary'!$B$2,0,SUM(INDIRECT(XLOOKUP(DT$3,'TTM Dates'!$B:$B,'TTM Dates'!$E:$E)&ROW($CJ74)&":"&XLOOKUP(DT$3,'TTM Dates'!$B:$B,'TTM Dates'!$C:$C)&ROW($CJ74))))} -> 0 | DU74: {=IF(DU$3>'GAAP Summary'!$B$2,0,SUM(INDIRECT(XLOOKUP(DU$3,'TTM Dates'!$B:$B,'TTM Dates'!$E:$E)&ROW($CJ74)&":"&XLOOKUP(DU$3,'TTM Dates'!$B:$B,'TTM Dates'!$C:$C)&ROW($CJ74))))} -> 0 | DV74: {=IF(DV$3>'GAAP Summary'!$B$2,0,SUM(INDIRECT(XLOOKUP(DV$3,'TTM Dates'!$B:$B,'TTM Dates'!$E:$E)&ROW($CJ74)&":"&XLOOKUP(DV$3,'TTM Dates'!$B:$B,'TTM Dates'!$C:$C)&ROW($CJ74))))} -> 0 | DW74: {=IF(DW$3>'GAAP Summary'!$B$2,0,SUM(INDIRECT(XLOOKUP(DW$3,'TTM Dates'!$B:$B,'TTM Dates'!$E:$E)&ROW($CJ74)&":"&XLOOKUP(DW$3,'TTM Dates'!$B:$B,'TTM Dates'!$C:$C)&ROW($CJ74))))} -> 0 | DX74: {=IF(DX$3>'GAAP Summary'!$B$2,0,SUM(INDIRECT(XLOOKUP(DX$3,'TTM Dates'!$B:$B,'TTM Dates'!$E:$E)&ROW($CJ74)&":"&XLOOKUP(DX$3,'TTM Dates'!$B:$B,'TTM Dates'!$C:$C)&ROW($CJ74))))} -> 0 | DY74: {=IF(DY$3>'GAAP Summary'!$B$2,0,SUM(INDIRECT(XLOOKUP(DY$3,'TTM Dates'!$B:$B,'TTM Dates'!$E:$E)&ROW($CJ74)&":"&XLOOKUP(DY$3,'TTM Dates'!$B:$B,'TTM Dates'!$C:$C)&ROW($CJ74))))} -> 0 | DZ74: {=IF(DZ$3>'GAAP Summary'!$B$2,0,SUM(INDIRECT(XLOOKUP(DZ$3,'TTM Dates'!$B:$B,'TTM Dates'!$E:$E)&ROW($CJ74)&":"&XLOOKUP(DZ$3,'TTM Dates'!$B:$B,'TTM Dates'!$C:$C)&ROW($CJ74))))} -> 0 | ... GL74: {=IF(GL$3>'GAAP Summary'!$B$2,0,SUM(INDIRECT(XLOOKUP(GL$3,'TTM Dates'!$B:$B,'TTM Dates'!$E:$E)&ROW($CJ74)&":"&XLOOKUP(GL$3,'TTM Dates'!$B:$B,'TTM Dates'!$C:$C)&ROW($CJ74))))} -> 0
B75: DD | CK75: {=SUM(INDIRECT(XLOOKUP('GAAP Summary'!$B$2,'TTM Dates'!$B:$B,'TTM Dates'!$E:$E)&ROW($CJ75)&":"&XLOOKUP('GAAP Summary'!$B$2,'TTM Dates'!$B:$B,'TTM Dates'!$C:$C)&ROW($CJ75)))} -> 0 | CM75: =sum(BW75:BY75) -> 0 | CN75: =sum(BZ75:CB75) -> 0 | CO75: =sum(CC75:CE75) -> 0 | CP75: =sum(CF75:CH75) -> 0 | CQ75: =sum(BW75:CH75) -> 0 | CS75: =sum(BK75:BM75) -> 0 | CT75: =sum(BN75:BP75) -> 0 | CU75: =sum(BQ75:BS75) -> 0 | CV75: =sum(BT75:BV75) -> 0 | CW75: =sum(BK75:BV75) -> 0 | CY75: =sum(AY75:BA75) -> 0 | CZ75: =sum(BB75:BD75) -> 0 | DA75: =sum(BE75:BG75) -> 0 | DB75: =sum(BH75:BJ75) -> 0 | DC75: =sum(AY75:BJ75) -> 0 | DE75: =sum(AM75:AO75) -> 0 | DF75: =sum(AP75:AR75) -> 0 | DG75: =sum(AS75:AU75) -> 0 | DH75: =sum(AV75:AX75) -> 0 | DI75: =sum(AM75:AX75) -> 0 | DS75: {=IF(DS$3>'GAAP Summary'!$B$2,0,SUM(INDIRECT(XLOOKUP(DS$3,'TTM Dates'!$B:$B,'TTM Dates'!$E:$E)&ROW($CJ75)&":"&XLOOKUP(DS$3,'TTM Dates'!$B:$B,'TTM Dates'!$C:$C)&ROW($CJ75))))} -> 0 | DT75: {=IF(DT$3>'GAAP Summary'!$B$2,0,SUM(INDIRECT(XLOOKUP(DT$3,'TTM Dates'!$B:$B,'TTM Dates'!$E:$E)&ROW($CJ75)&":"&XLOOKUP(DT$3,'TTM Dates'!$B:$B,'TTM Dates'!$C:$C)&ROW($CJ75))))} -> 0 | DU75: {=IF(DU$3>'GAAP Summary'!$B$2,0,SUM(INDIRECT(XLOOKUP(DU$3,'TTM Dates'!$B:$B,'TTM Dates'!$E:$E)&ROW($CJ75)&":"&XLOOKUP(DU$3,'TTM Dates'!$B:$B,'TTM Dates'!$C:$C)&ROW($CJ75))))} -> 0 | DV75: {=IF(DV$3>'GAAP Summary'!$B$2,0,SUM(INDIRECT(XLOOKUP(DV$3,'TTM Dates'!$B:$B,'TTM Dates'!$E:$E)&ROW($CJ75)&":"&XLOOKUP(DV$3,'TTM Dates'!$B:$B,'TTM Dates'!$C:$C)&ROW($CJ75))))} -> 0 | DW75: {=IF(DW$3>'GAAP Summary'!$B$2,0,SUM(INDIRECT(XLOOKUP(DW$3,'TTM Dates'!$B:$B,'TTM Dates'!$E:$E)&ROW($CJ75)&":"&XLOOKUP(DW$3,'TTM Dates'!$B:$B,'TTM Dates'!$C:$C)&ROW($CJ75))))} -> 0 | DX75: {=IF(DX$3>'GAAP Summary'!$B$2,0,SUM(INDIRECT(XLOOKUP(DX$3,'TTM Dates'!$B:$B,'TTM Dates'!$E:$E)&ROW($CJ75)&":"&XLOOKUP(DX$3,'TTM Dates'!$B:$B,'TTM Dates'!$C:$C)&ROW($CJ75))))} -> 0 | DY75: {=IF(DY$3>'GAAP Summary'!$B$2,0,SUM(INDIRECT(XLOOKUP(DY$3,'TTM Dates'!$B:$B,'TTM Dates'!$E:$E)&ROW($CJ75)&":"&XLOOKUP(DY$3,'TTM Dates'!$B:$B,'TTM Dates'!$C:$C)&ROW($CJ75))))} -> 0 | DZ75: {=IF(DZ$3>'GAAP Summary'!$B$2,0,SUM(INDIRECT(XLOOKUP(DZ$3,'TTM Dates'!$B:$B,'TTM Dates'!$E:$E)&ROW($CJ75)&":"&XLOOKUP(DZ$3,'TTM Dates'!$B:$B,'TTM Dates'!$C:$C)&ROW($CJ75))))} -> 0 | ... GL75: {=IF(GL$3>'GAAP Summary'!$B$2,0,SUM(INDIRECT(XLOOKUP(GL$3,'TTM Dates'!$B:$B,'TTM Dates'!$E:$E)&ROW($CJ75)&":"&XLOOKUP(GL$3,'TTM Dates'!$B:$B,'TTM Dates'!$C:$C)&ROW($CJ75))))} -> 0
B76: SN | CK76: {=SUM(INDIRECT(XLOOKUP('GAAP Summary'!$B$2,'TTM Dates'!$B:$B,'TTM Dates'!$E:$E)&ROW($CJ76)&":"&XLOOKUP('GAAP Summary'!$B$2,'TTM Dates'!$B:$B,'TTM Dates'!$C:$C)&ROW($CJ76)))} -> 0 | CM76: =sum(BW76:BY76) -> 0 | CN76: =sum(BZ76:CB76) -> 0 | CO76: =sum(CC76:CE76) -> 0 | CP76: =sum(CF76:CH76) -> 0 | CQ76: =sum(BW76:CH76) -> 0 | CS76: =sum(BK76:BM76) -> 0 | CT76: =sum(BN76:BP76) -> 0 | CU76: =sum(BQ76:BS76) -> 0 | CV76: =sum(BT76:BV76) -> 0 | CW76: =sum(BK76:BV76) -> 0 | CY76: =sum(AY76:BA76) -> 0 | CZ76: =sum(BB76:BD76) -> 0 | DA76: =sum(BE76:BG76) -> 0 | DB76: =sum(BH76:BJ76) -> 0 | DC76: =sum(AY76:BJ76) -> 0 | DE76: =sum(AM76:AO76) -> 0 | DF76: =sum(AP76:AR76) -> 0 | DG76: =sum(AS76:AU76) -> 0 | DH76: =sum(AV76:AX76) -> 0 | DI76: =sum(AM76:AX76) -> 0 | DS76: {=IF(DS$3>'GAAP Summary'!$B$2,0,SUM(INDIRECT(XLOOKUP(DS$3,'TTM Dates'!$B:$B,'TTM Dates'!$E:$E)&ROW($CJ76)&":"&XLOOKUP(DS$3,'TTM Dates'!$B:$B,'TTM Dates'!$C:$C)&ROW($CJ76))))} -> 0 | DT76: {=IF(DT$3>'GAAP Summary'!$B$2,0,SUM(INDIRECT(XLOOKUP(DT$3,'TTM Dates'!$B:$B,'TTM Dates'!$E:$E)&ROW($CJ76)&":"&XLOOKUP(DT$3,'TTM Dates'!$B:$B,'TTM Dates'!$C:$C)&ROW($CJ76))))} -> 0 | DU76: {=IF(DU$3>'GAAP Summary'!$B$2,0,SUM(INDIRECT(XLOOKUP(DU$3,'TTM Dates'!$B:$B,'TTM Dates'!$E:$E)&ROW($CJ76)&":"&XLOOKUP(DU$3,'TTM Dates'!$B:$B,'TTM Dates'!$C:$C)&ROW($CJ76))))} -> 0 | DV76: {=IF(DV$3>'GAAP Summary'!$B$2,0,SUM(INDIRECT(XLOOKUP(DV$3,'TTM Dates'!$B:$B,'TTM Dates'!$E:$E)&ROW($CJ76)&":"&XLOOKUP(DV$3,'TTM Dates'!$B:$B,'TTM Dates'!$C:$C)&ROW($CJ76))))} -> 0 | DW76: {=IF(DW$3>'GAAP Summary'!$B$2,0,SUM(INDIRECT(XLOOKUP(DW$3,'TTM Dates'!$B:$B,'TTM Dates'!$E:$E)&ROW($CJ76)&":"&XLOOKUP(DW$3,'TTM Dates'!$B:$B,'TTM Dates'!$C:$C)&ROW($CJ76))))} -> 0 | DX76: {=IF(DX$3>'GAAP Summary'!$B$2,0,SUM(INDIRECT(XLOOKUP(DX$3,'TTM Dates'!$B:$B,'TTM Dates'!$E:$E)&ROW($CJ76)&":"&XLOOKUP(DX$3,'TTM Dates'!$B:$B,'TTM Dates'!$C:$C)&ROW($CJ76))))} -> 0 | DY76: {=IF(DY$3>'GAAP Summary'!$B$2,0,SUM(INDIRECT(XLOOKUP(DY$3,'TTM Dates'!$B:$B,'TTM Dates'!$E:$E)&ROW($CJ76)&":"&XLOOKUP(DY$3,'TTM Dates'!$B:$B,'TTM Dates'!$C:$C)&ROW($CJ76))))} -> 0 | DZ76: {=IF(DZ$3>'GAAP Summary'!$B$2,0,SUM(INDIRECT(XLOOKUP(DZ$3,'TTM Dates'!$B:$B,'TTM Dates'!$E:$E)&ROW($CJ76)&":"&XLOOKUP(DZ$3,'TTM Dates'!$B:$B,'TTM Dates'!$C:$C)&ROW($CJ76))))} -> 0 | ... GL76: {=IF(GL$3>'GAAP Summary'!$B$2,0,SUM(INDIRECT(XLOOKUP(GL$3,'TTM Dates'!$B:$B,'TTM Dates'!$E:$E)&ROW($CJ76)&":"&XLOOKUP(GL$3,'TTM Dates'!$B:$B,'TTM Dates'!$C:$C)&ROW($CJ76))))} -> 0
B77: Operations | CK77: {=SUM(INDIRECT(XLOOKUP('GAAP Summary'!$B$2,'TTM Dates'!$B:$B,'TTM Dates'!$E:$E)&ROW($CJ77)&":"&XLOOKUP('GAAP Summary'!$B$2,'TTM Dates'!$B:$B,'TTM Dates'!$C:$C)&ROW($CJ77)))} -> 0 | CM77: =sum(BW77:BY77) -> 0 | CN77: =sum(BZ77:CB77) -> 0 | CO77: =sum(CC77:CE77) -> 0 | CP77: =sum(CF77:CH77) -> 0 | CQ77: =sum(BW77:CH77) -> 0 | CS77: =sum(BK77:BM77) -> 0 | CT77: =sum(BN77:BP77) -> 0 | CU77: =sum(BQ77:BS77) -> 0 | CV77: =sum(BT77:BV77) -> 0 | CW77: =sum(BK77:BV77) -> 0 | CY77: =sum(AY77:BA77) -> 0 | CZ77: =sum(BB77:BD77) -> 0 | DA77: =sum(BE77:BG77) -> 0 | DB77: =sum(BH77:BJ77) -> 0 | DC77: =sum(AY77:BJ77) -> 0 | DE77: =sum(AM77:AO77) -> 0 | DF77: =sum(AP77:AR77) -> 0 | DG77: =sum(AS77:AU77) -> 0 | DH77: =sum(AV77:AX77) -> 0 | DI77: =sum(AM77:AX77) -> 0 | DS77: {=IF(DS$3>'GAAP Summary'!$B$2,0,SUM(INDIRECT(XLOOKUP(DS$3,'TTM Dates'!$B:$B,'TTM Dates'!$E:$E)&ROW($CJ77)&":"&XLOOKUP(DS$3,'TTM Dates'!$B:$B,'TTM Dates'!$C:$C)&ROW($CJ77))))} -> 0 | DT77: {=IF(DT$3>'GAAP Summary'!$B$2,0,SUM(INDIRECT(XLOOKUP(DT$3,'TTM Dates'!$B:$B,'TTM Dates'!$E:$E)&ROW($CJ77)&":"&XLOOKUP(DT$3,'TTM Dates'!$B:$B,'TTM Dates'!$C:$C)&ROW($CJ77))))} -> 0 | DU77: {=IF(DU$3>'GAAP Summary'!$B$2,0,SUM(INDIRECT(XLOOKUP(DU$3,'TTM Dates'!$B:$B,'TTM Dates'!$E:$E)&ROW($CJ77)&":"&XLOOKUP(DU$3,'TTM Dates'!$B:$B,'TTM Dates'!$C:$C)&ROW($CJ77))))} -> 0 | DV77: {=IF(DV$3>'GAAP Summary'!$B$2,0,SUM(INDIRECT(XLOOKUP(DV$3,'TTM Dates'!$B:$B,'TTM Dates'!$E:$E)&ROW($CJ77)&":"&XLOOKUP(DV$3,'TTM Dates'!$B:$B,'TTM Dates'!$C:$C)&ROW($CJ77))))} -> 0 | DW77: {=IF(DW$3>'GAAP Summary'!$B$2,0,SUM(INDIRECT(XLOOKUP(DW$3,'TTM Dates'!$B:$B,'TTM Dates'!$E:$E)&ROW($CJ77)&":"&XLOOKUP(DW$3,'TTM Dates'!$B:$B,'TTM Dates'!$C:$C)&ROW($CJ77))))} -> 0 | DX77: {=IF(DX$3>'GAAP Summary'!$B$2,0,SUM(INDIRECT(XLOOKUP(DX$3,'TTM Dates'!$B:$B,'TTM Dates'!$E:$E)&ROW($CJ77)&":"&XLOOKUP(DX$3,'TTM Dates'!$B:$B,'TTM Dates'!$C:$C)&ROW($CJ77))))} -> 0 | DY77: {=IF(DY$3>'GAAP Summary'!$B$2,0,SUM(INDIRECT(XLOOKUP(DY$3,'TTM Dates'!$B:$B,'TTM Dates'!$E:$E)&ROW($CJ77)&":"&XLOOKUP(DY$3,'TTM Dates'!$B:$B,'TTM Dates'!$C:$C)&ROW($CJ77))))} -> 0 | DZ77: {=IF(DZ$3>'GAAP Summary'!$B$2,0,SUM(INDIRECT(XLOOKUP(DZ$3,'TTM Dates'!$B:$B,'TTM Dates'!$E:$E)&ROW($CJ77)&":"&XLOOKUP(DZ$3,'TTM Dates'!$B:$B,'TTM Dates'!$C:$C)&ROW($CJ77))))} -> 0 | ... GL77: {=IF(GL$3>'GAAP Summary'!$B$2,0,SUM(INDIRECT(XLOOKUP(GL$3,'TTM Dates'!$B:$B,'TTM Dates'!$E:$E)&ROW($CJ77)&":"&XLOOKUP(GL$3,'TTM Dates'!$B:$B,'TTM Dates'!$C:$C)&ROW($CJ77))))} -> 0
B78: Total Sales & Marketing | C78: =SUM(C79:C81) -> 0 | D78: =SUM(D79:D81) -> 0 | E78: =SUM(E79:E81) -> 0 | F78: =SUM(F79:F81) -> 0 | G78: =SUM(G79:G81) -> 0 | H78: =SUM(H79:H81) -> 0 | I78: =SUM(I79:I81) -> 0 | J78: =SUM(J79:J81) -> 0 | ... Z78: =SUM(Z79:Z81) -> 0 | AA78: 53025 | AB78: 80594 | AC78: 154234 | AD78: 124519 | AE78: 153292 | AF78: 144490 | AG78: 154575 | AH78: 130723 | AI78: 165991 | AJ78: 329009 | AK78: 143449 | AL78: 257673 | AM78: 100999 | AN78: 227173 | AO78: 171564 | AP78: 340024 | AQ78: 224794 | AR78: 183769 | AS78: 291754 | AT78: 197738 | AU78: 159572 | AV78: 146742 | AW78: 153401 | AX78: 174402 | AY78: 305854 | AZ78: 200756 | BA78: 242168 | BB78: 216435 | BC78: 395861 | BD78: 441992 | BE78: 137928 | BF78: 266030 | BG78: 145792 | BH78: 221157 | BI78: 223426 | BJ78: 172204 | BK78: 262855 | BL78: 220821 | BM78: 205587 | BN78: 190853 | BO78: 498299 | BP78: 430849 | BQ78: 270834 | BR78: 507684 | BS78: 835439.87 | BT78: 1009883.8 | BU78: 886598.33 | BV78: 206489.21 | BW78: 974799.16 | BX78: 891539.23 | BY78: 1095487.1 | BZ78: 992134.25 | CA78: 1202813.1 | CB78: 1253985 | CK78: {=SUM(INDIRECT(XLOOKUP('GAAP Summary'!$B$2,'TTM Dates'!$B:$B,'TTM Dates'!$E:$E)&ROW($CJ78)&":"&XLOOKUP('GAAP Summary'!$B$2,'TTM Dates'!$B:$B,'TTM Dates'!$C:$C)&ROW($CJ78)))} -> 10127687 | CM78: =sum(BW78:BY78) -> 2961825.5 | CN78: =sum(BZ78:CB78) -> 3448932.3 | CO78: =sum(CC78:CE78) -> 0 | CP78: =sum(CF78:CH78) -> 0 | CQ78: =sum(BW78:CH78) -> 6410757.8 | CS78: =sum(BK78:BM78) -> 689263 | CT78: =sum(BN78:BP78) -> 1120001 | CU78: =sum(BQ78:BS78) -> 1613957.9 | CV78: =sum(BT78:BV78) -> 2102971.4 | CW78: =sum(BK78:BV78) -> 5526193.2 | CY78: =sum(AY78:BA78) -> 748778 | CZ78: =sum(BB78:BD78) -> 1054288 | DA78: =sum(BE78:BG78) -> 549750 | DB78: =sum(BH78:BJ78) -> 616787 | DC78: =sum(AY78:BJ78) -> 2969603 | DE78: =sum(AM78:AO78) -> 499736 | DF78: =sum(AP78:AR78) -> 748587 | DG78: =sum(AS78:AU78) -> 649064 | DH78: =sum(AV78:AX78) -> 474545 | DI78: =sum(AM78:AX78) -> 2371932 | DK78: =sum(AA78:AC78) -> 287853 | DL78: =sum(AD78:AF78) -> 422301 | DM78: =sum(AG78:AI78) -> 451289 | DN78: =sum(AJ78:AL78) -> 730131 | DO78: =sum(AA78:AL78) -> 1891574 | DQ78: =SUM(O78:Z78) -> 0 | DS78: {=IF(DS$3>'GAAP Summary'!$B$2,0,SUM(INDIRECT(XLOOKUP(DS$3,'TTM Dates'!$B:$B,'TTM Dates'!$E:$E)&ROW($CJ78)&":"&XLOOKUP(DS$3,'TTM Dates'!$B:$B,'TTM Dates'!$C:$C)&ROW($CJ78))))} -> 0 | DT78: {=IF(DT$3>'GAAP Summary'!$B$2,0,SUM(INDIRECT(XLOOKUP(DT$3,'TTM Dates'!$B:$B,'TTM Dates'!$E:$E)&ROW($CJ78)&":"&XLOOKUP(DT$3,'TTM Dates'!$B:$B,'TTM Dates'!$C:$C)&ROW($CJ78))))} -> 0 | DU78: {=IF(DU$3>'GAAP Summary'!$B$2,0,SUM(INDIRECT(XLOOKUP(DU$3,'TTM Dates'!$B:$B,'TTM Dates'!$E:$E)&ROW($CJ78)&":"&XLOOKUP(DU$3,'TTM Dates'!$B:$B,'TTM Dates'!$C:$C)&ROW($CJ78))))} -> 0 | DV78: {=IF(DV$3>'GAAP Summary'!$B$2,0,SUM(INDIRECT(XLOOKUP(DV$3,'TTM Dates'!$B:$B,'TTM Dates'!$E:$E)&ROW($CJ78)&":"&XLOOKUP(DV$3,'TTM Dates'!$B:$B,'TTM Dates'!$C:$C)&ROW($CJ78))))} -> 0 | DW78: {=IF(DW$3>'GAAP Summary'!$B$2,0,SUM(INDIRECT(XLOOKUP(DW$3,'TTM Dates'!$B:$B,'TTM Dates'!$E:$E)&ROW($CJ78)&":"&XLOOKUP(DW$3,'TTM Dates'!$B:$B,'TTM Dates'!$C:$C)&ROW($CJ78))))} -> 0 | DX78: {=IF(DX$3>'GAAP Summary'!$B$2,0,SUM(INDIRECT(XLOOKUP(DX$3,'TTM Dates'!$B:$B,'TTM Dates'!$E:$E)&ROW($CJ78)&":"&XLOOKUP(DX$3,'TTM Dates'!$B:$B,'TTM Dates'!$C:$C)&ROW($CJ78))))} -> 0 | DY78: {=IF(DY$3>'GAAP Summary'!$B$2,0,SUM(INDIRECT(XLOOKUP(DY$3,'TTM Dates'!$B:$B,'TTM Dates'!$E:$E)&ROW($CJ78)&":"&XLOOKUP(DY$3,'TTM Dates'!$B:$B,'TTM Dates'!$C:$C)&ROW($CJ78))))} -> 0 | DZ78: {=IF(DZ$3>'GAAP Summary'!$B$2,0,SUM(INDIRECT(XLOOKUP(DZ$3,'TTM Dates'!$B:$B,'TTM Dates'!$E:$E)&ROW($CJ78)&":"&XLOOKUP(DZ$3,'TTM Dates'!$B:$B,'TTM Dates'!$C:$C)&ROW($CJ78))))} -> 0 | ... GL78: {=IF(GL$3>'GAAP Summary'!$B$2,0,SUM(INDIRECT(XLOOKUP(GL$3,'TTM Dates'!$B:$B,'TTM Dates'!$E:$E)&ROW($CJ78)&":"&XLOOKUP(GL$3,'TTM Dates'!$B:$B,'TTM Dates'!$C:$C)&ROW($CJ78))))} -> 0
B79: DD | CK79: {=SUM(INDIRECT(XLOOKUP('GAAP Summary'!$B$2,'TTM Dates'!$B:$B,'TTM Dates'!$E:$E)&ROW($CJ79)&":"&XLOOKUP('GAAP Summary'!$B$2,'TTM Dates'!$B:$B,'TTM Dates'!$C:$C)&ROW($CJ79)))} -> 0 | CM79: =sum(BW79:BY79) -> 0 | CN79: =sum(BZ79:CB79) -> 0 | CO79: =sum(CC79:CE79) -> 0 | CP79: =sum(CF79:CH79) -> 0 | CQ79: =sum(BW79:CH79) -> 0 | CS79: =sum(BK79:BM79) -> 0 | CT79: =sum(BN79:BP79) -> 0 | CU79: =sum(BQ79:BS79) -> 0 | CV79: =sum(BT79:BV79) -> 0 | CW79: =sum(BK79:BV79) -> 0 | CY79: =sum(AY79:BA79) -> 0 | CZ79: =sum(BB79:BD79) -> 0 | DA79: =sum(BE79:BG79) -> 0 | DB79: =sum(BH79:BJ79) -> 0 | DC79: =sum(AY79:BJ79) -> 0 | DE79: =sum(AM79:AO79) -> 0 | DF79: =sum(AP79:AR79) -> 0 | DG79: =sum(AS79:AU79) -> 0 | DH79: =sum(AV79:AX79) -> 0 | DI79: =sum(AM79:AX79) -> 0 | DS79: {=IF(DS$3>'GAAP Summary'!$B$2,0,SUM(INDIRECT(XLOOKUP(DS$3,'TTM Dates'!$B:$B,'TTM Dates'!$E:$E)&ROW($CJ79)&":"&XLOOKUP(DS$3,'TTM Dates'!$B:$B,'TTM Dates'!$C:$C)&ROW($CJ79))))} -> 0 | DT79: {=IF(DT$3>'GAAP Summary'!$B$2,0,SUM(INDIRECT(XLOOKUP(DT$3,'TTM Dates'!$B:$B,'TTM Dates'!$E:$E)&ROW($CJ79)&":"&XLOOKUP(DT$3,'TTM Dates'!$B:$B,'TTM Dates'!$C:$C)&ROW($CJ79))))} -> 0 | DU79: {=IF(DU$3>'GAAP Summary'!$B$2,0,SUM(INDIRECT(XLOOKUP(DU$3,'TTM Dates'!$B:$B,'TTM Dates'!$E:$E)&ROW($CJ79)&":"&XLOOKUP(DU$3,'TTM Dates'!$B:$B,'TTM Dates'!$C:$C)&ROW($CJ79))))} -> 0 | DV79: {=IF(DV$3>'GAAP Summary'!$B$2,0,SUM(INDIRECT(XLOOKUP(DV$3,'TTM Dates'!$B:$B,'TTM Dates'!$E:$E)&ROW($CJ79)&":"&XLOOKUP(DV$3,'TTM Dates'!$B:$B,'TTM Dates'!$C:$C)&ROW($CJ79))))} -> 0 | DW79: {=IF(DW$3>'GAAP Summary'!$B$2,0,SUM(INDIRECT(XLOOKUP(DW$3,'TTM Dates'!$B:$B,'TTM Dates'!$E:$E)&ROW($CJ79)&":"&XLOOKUP(DW$3,'TTM Dates'!$B:$B,'TTM Dates'!$C:$C)&ROW($CJ79))))} -> 0 | DX79: {=IF(DX$3>'GAAP Summary'!$B$2,0,SUM(INDIRECT(XLOOKUP(DX$3,'TTM Dates'!$B:$B,'TTM Dates'!$E:$E)&ROW($CJ79)&":"&XLOOKUP(DX$3,'TTM Dates'!$B:$B,'TTM Dates'!$C:$C)&ROW($CJ79))))} -> 0 | DY79: {=IF(DY$3>'GAAP Summary'!$B$2,0,SUM(INDIRECT(XLOOKUP(DY$3,'TTM Dates'!$B:$B,'TTM Dates'!$E:$E)&ROW($CJ79)&":"&XLOOKUP(DY$3,'TTM Dates'!$B:$B,'TTM Dates'!$C:$C)&ROW($CJ79))))} -> 0 | DZ79: {=IF(DZ$3>'GAAP Summary'!$B$2,0,SUM(INDIRECT(XLOOKUP(DZ$3,'TTM Dates'!$B:$B,'TTM Dates'!$E:$E)&ROW($CJ79)&":"&XLOOKUP(DZ$3,'TTM Dates'!$B:$B,'TTM Dates'!$C:$C)&ROW($CJ79))))} -> 0 | ... GL79: {=IF(GL$3>'GAAP Summary'!$B$2,0,SUM(INDIRECT(XLOOKUP(GL$3,'TTM Dates'!$B:$B,'TTM Dates'!$E:$E)&ROW($CJ79)&":"&XLOOKUP(GL$3,'TTM Dates'!$B:$B,'TTM Dates'!$C:$C)&ROW($CJ79))))} -> 0
B80: SN | CK80: {=SUM(INDIRECT(XLOOKUP('GAAP Summary'!$B$2,'TTM Dates'!$B:$B,'TTM Dates'!$E:$E)&ROW($CJ80)&":"&XLOOKUP('GAAP Summary'!$B$2,'TTM Dates'!$B:$B,'TTM Dates'!$C:$C)&ROW($CJ80)))} -> 0 | CM80: =sum(BW80:BY80) -> 0 | CN80: =sum(BZ80:CB80) -> 0 | CO80: =sum(CC80:CE80) -> 0 | CP80: =sum(CF80:CH80) -> 0 | CQ80: =sum(BW80:CH80) -> 0 | CS80: =sum(BK80:BM80) -> 0 | CT80: =sum(BN80:BP80) -> 0 | CU80: =sum(BQ80:BS80) -> 0 | CV80: =sum(BT80:BV80) -> 0 | CW80: =sum(BK80:BV80) -> 0 | CY80: =sum(AY80:BA80) -> 0 | CZ80: =sum(BB80:BD80) -> 0 | DA80: =sum(BE80:BG80) -> 0 | DB80: =sum(BH80:BJ80) -> 0 | DC80: =sum(AY80:BJ80) -> 0 | DE80: =sum(AM80:AO80) -> 0 | DF80: =sum(AP80:AR80) -> 0 | DG80: =sum(AS80:AU80) -> 0 | DH80: =sum(AV80:AX80) -> 0 | DI80: =sum(AM80:AX80) -> 0 | DS80: {=IF(DS$3>'GAAP Summary'!$B$2,0,SUM(INDIRECT(XLOOKUP(DS$3,'TTM Dates'!$B:$B,'TTM Dates'!$E:$E)&ROW($CJ80)&":"&XLOOKUP(DS$3,'TTM Dates'!$B:$B,'TTM Dates'!$C:$C)&ROW($CJ80))))} -> 0 | DT80: {=IF(DT$3>'GAAP Summary'!$B$2,0,SUM(INDIRECT(XLOOKUP(DT$3,'TTM Dates'!$B:$B,'TTM Dates'!$E:$E)&ROW($CJ80)&":"&XLOOKUP(DT$3,'TTM Dates'!$B:$B,'TTM Dates'!$C:$C)&ROW($CJ80))))} -> 0 | DU80: {=IF(DU$3>'GAAP Summary'!$B$2,0,SUM(INDIRECT(XLOOKUP(DU$3,'TTM Dates'!$B:$B,'TTM Dates'!$E:$E)&ROW($CJ80)&":"&XLOOKUP(DU$3,'TTM Dates'!$B:$B,'TTM Dates'!$C:$C)&ROW($CJ80))))} -> 0 | DV80: {=IF(DV$3>'GAAP Summary'!$B$2,0,SUM(INDIRECT(XLOOKUP(DV$3,'TTM Dates'!$B:$B,'TTM Dates'!$E:$E)&ROW($CJ80)&":"&XLOOKUP(DV$3,'TTM Dates'!$B:$B,'TTM Dates'!$C:$C)&ROW($CJ80))))} -> 0 | DW80: {=IF(DW$3>'GAAP Summary'!$B$2,0,SUM(INDIRECT(XLOOKUP(DW$3,'TTM Dates'!$B:$B,'TTM Dates'!$E:$E)&ROW($CJ80)&":"&XLOOKUP(DW$3,'TTM Dates'!$B:$B,'TTM Dates'!$C:$C)&ROW($CJ80))))} -> 0 | DX80: {=IF(DX$3>'GAAP Summary'!$B$2,0,SUM(INDIRECT(XLOOKUP(DX$3,'TTM Dates'!$B:$B,'TTM Dates'!$E:$E)&ROW($CJ80)&":"&XLOOKUP(DX$3,'TTM Dates'!$B:$B,'TTM Dates'!$C:$C)&ROW($CJ80))))} -> 0 | DY80: {=IF(DY$3>'GAAP Summary'!$B$2,0,SUM(INDIRECT(XLOOKUP(DY$3,'TTM Dates'!$B:$B,'TTM Dates'!$E:$E)&ROW($CJ80)&":"&XLOOKUP(DY$3,'TTM Dates'!$B:$B,'TTM Dates'!$C:$C)&ROW($CJ80))))} -> 0 | DZ80: {=IF(DZ$3>'GAAP Summary'!$B$2,0,SUM(INDIRECT(XLOOKUP(DZ$3,'TTM Dates'!$B:$B,'TTM Dates'!$E:$E)&ROW($CJ80)&":"&XLOOKUP(DZ$3,'TTM Dates'!$B:$B,'TTM Dates'!$C:$C)&ROW($CJ80))))} -> 0 | ... GL80: {=IF(GL$3>'GAAP Summary'!$B$2,0,SUM(INDIRECT(XLOOKUP(GL$3,'TTM Dates'!$B:$B,'TTM Dates'!$E:$E)&ROW($CJ80)&":"&XLOOKUP(GL$3,'TTM Dates'!$B:$B,'TTM Dates'!$C:$C)&ROW($CJ80))))} -> 0
B81: Operations | CK81: {=SUM(INDIRECT(XLOOKUP('GAAP Summary'!$B$2,'TTM Dates'!$B:$B,'TTM Dates'!$E:$E)&ROW($CJ81)&":"&XLOOKUP('GAAP Summary'!$B$2,'TTM Dates'!$B:$B,'TTM Dates'!$C:$C)&ROW($CJ81)))} -> 0 | CM81: =sum(BW81:BY81) -> 0 | CN81: =sum(BZ81:CB81) -> 0 | CO81: =sum(CC81:CE81) -> 0 | CP81: =sum(CF81:CH81) -> 0 | CQ81: =sum(BW81:CH81) -> 0 | CS81: =sum(BK81:BM81) -> 0 | CT81: =sum(BN81:BP81) -> 0 | CU81: =sum(BQ81:BS81) -> 0 | CV81: =sum(BT81:BV81) -> 0 | CW81: =sum(BK81:BV81) -> 0 | CY81: =sum(AY81:BA81) -> 0 | CZ81: =sum(BB81:BD81) -> 0 | DA81: =sum(BE81:BG81) -> 0 | DB81: =sum(BH81:BJ81) -> 0 | DC81: =sum(AY81:BJ81) -> 0 | DE81: =sum(AM81:AO81) -> 0 | DF81: =sum(AP81:AR81) -> 0 | DG81: =sum(AS81:AU81) -> 0 | DH81: =sum(AV81:AX81) -> 0 | DI81: =sum(AM81:AX81) -> 0 | DS81: {=IF(DS$3>'GAAP Summary'!$B$2,0,SUM(INDIRECT(XLOOKUP(DS$3,'TTM Dates'!$B:$B,'TTM Dates'!$E:$E)&ROW($CJ81)&":"&XLOOKUP(DS$3,'TTM Dates'!$B:$B,'TTM Dates'!$C:$C)&ROW($CJ81))))} -> 0 | DT81: {=IF(DT$3>'GAAP Summary'!$B$2,0,SUM(INDIRECT(XLOOKUP(DT$3,'TTM Dates'!$B:$B,'TTM Dates'!$E:$E)&ROW($CJ81)&":"&XLOOKUP(DT$3,'TTM Dates'!$B:$B,'TTM Dates'!$C:$C)&ROW($CJ81))))} -> 0 | DU81: {=IF(DU$3>'GAAP Summary'!$B$2,0,SUM(INDIRECT(XLOOKUP(DU$3,'TTM Dates'!$B:$B,'TTM Dates'!$E:$E)&ROW($CJ81)&":"&XLOOKUP(DU$3,'TTM Dates'!$B:$B,'TTM Dates'!$C:$C)&ROW($CJ81))))} -> 0 | DV81: {=IF(DV$3>'GAAP Summary'!$B$2,0,SUM(INDIRECT(XLOOKUP(DV$3,'TTM Dates'!$B:$B,'TTM Dates'!$E:$E)&ROW($CJ81)&":"&XLOOKUP(DV$3,'TTM Dates'!$B:$B,'TTM Dates'!$C:$C)&ROW($CJ81))))} -> 0 | DW81: {=IF(DW$3>'GAAP Summary'!$B$2,0,SUM(INDIRECT(XLOOKUP(DW$3,'TTM Dates'!$B:$B,'TTM Dates'!$E:$E)&ROW($CJ81)&":"&XLOOKUP(DW$3,'TTM Dates'!$B:$B,'TTM Dates'!$C:$C)&ROW($CJ81))))} -> 0 | DX81: {=IF(DX$3>'GAAP Summary'!$B$2,0,SUM(INDIRECT(XLOOKUP(DX$3,'TTM Dates'!$B:$B,'TTM Dates'!$E:$E)&ROW($CJ81)&":"&XLOOKUP(DX$3,'TTM Dates'!$B:$B,'TTM Dates'!$C:$C)&ROW($CJ81))))} -> 0 | DY81: {=IF(DY$3>'GAAP Summary'!$B$2,0,SUM(INDIRECT(XLOOKUP(DY$3,'TTM Dates'!$B:$B,'TTM Dates'!$E:$E)&ROW($CJ81)&":"&XLOOKUP(DY$3,'TTM Dates'!$B:$B,'TTM Dates'!$C:$C)&ROW($CJ81))))} -> 0 | DZ81: {=IF(DZ$3>'GAAP Summary'!$B$2,0,SUM(INDIRECT(XLOOKUP(DZ$3,'TTM Dates'!$B:$B,'TTM Dates'!$E:$E)&ROW($CJ81)&":"&XLOOKUP(DZ$3,'TTM Dates'!$B:$B,'TTM Dates'!$C:$C)&ROW($CJ81))))} -> 0 | ... GL81: {=IF(GL$3>'GAAP Summary'!$B$2,0,SUM(INDIRECT(XLOOKUP(GL$3,'TTM Dates'!$B:$B,'TTM Dates'!$E:$E)&ROW($CJ81)&":"&XLOOKUP(GL$3,'TTM Dates'!$B:$B,'TTM Dates'!$C:$C)&ROW($CJ81))))} -> 0
B83: Other Expenses | C83: =SUM(C84:C85) -> 0 | D83: =SUM(D84:D85) -> 0 | E83: =SUM(E84:E85) -> 0 | F83: =SUM(F84:F85) -> 0 | G83: =SUM(G84:G85) -> 0 | H83: =SUM(H84:H85) -> 0 | I83: =SUM(I84:I85) -> 0 | J83: =SUM(J84:J85) -> 0 | ... CH83: =SUM(CH84:CH85) -> 0 | CK83: {=SUM(INDIRECT(XLOOKUP('GAAP Summary'!$B$2,'TTM Dates'!$B:$B,'TTM Dates'!$E:$E)&ROW($CJ83)&":"&XLOOKUP('GAAP Summary'!$B$2,'TTM Dates'!$B:$B,'TTM Dates'!$C:$C)&ROW($CJ83)))} -> 655369.37 | CM83: =sum(BW83:BY83) -> 221867.62 | CN83: =sum(BZ83:CB83) -> 197122.61 | CO83: =sum(CC83:CE83) -> 0 | CP83: =sum(CF83:CH83) -> 0 | CQ83: =sum(BW83:CH83) -> 418990.23
B84: Other Expenses | BS84: 32571.88 | BT84: 32569.67 | BU84: 33183.1 | BV84: 98864.24 | BW84: 64549.62 | BX84: 58458 | BY84: 64614 | CA84: =503.25+30980.43+43867.28 -> 75350.96 | CB84: =111896.16-CB85 -> 101985.99 | CK84: {=SUM(INDIRECT(XLOOKUP('GAAP Summary'!$B$2,'TTM Dates'!$B:$B,'TTM Dates'!$E:$E)&ROW($CJ84)&":"&XLOOKUP('GAAP Summary'!$B$2,'TTM Dates'!$B:$B,'TTM Dates'!$C:$C)&ROW($CJ84)))} -> 562147.46 | CM84: =sum(BW84:BY84) -> 187621.62 | CN84: =sum(BZ84:CB84) -> 177336.95 | CO84: =sum(CC84:CE84) -> 0 | CP84: =sum(CF84:CH84) -> 0 | CQ84: =sum(BW84:CH84) -> 364958.57
B85: Other Expenses - EBITDA Add Back | BS85: 9866.82 | BT85: 9551.74 | BU85: 9366.08 | BV85: 10405.61 | BW85: 9433 | BX85: 10183 | BY85: 14630 | CA85: =128.18+2330.23+7417.08 -> 9875.49 | CB85: =7451.76+2330.23+128.18 -> 9910.17 | CK85: {=SUM(INDIRECT(XLOOKUP('GAAP Summary'!$B$2,'TTM Dates'!$B:$B,'TTM Dates'!$E:$E)&ROW($CJ85)&":"&XLOOKUP('GAAP Summary'!$B$2,'TTM Dates'!$B:$B,'TTM Dates'!$C:$C)&ROW($CJ85)))} -> 93221.91 | CM85: =sum(BW85:BY85) -> 34246 | CN85: =sum(BZ85:CB85) -> 19785.66 | CO85: =sum(CC85:CE85) -> 0 | CP85: =sum(CF85:CH85) -> 0 | CQ85: =sum(BW85:CH85) -> 54031.66
B87: EBITDA Adjustments | AF87: =SUM(AF88:AF89) -> 0 | AG87: =SUM(AG88:AG89) -> 0 | AH87: =SUM(AH88:AH89) -> 0 | AI87: =SUM(AI88:AI89) -> 0 | AJ87: =SUM(AJ88:AJ89) -> 0 | AK87: =SUM(AK88:AK89) -> 0 | AL87: =SUM(AL88:AL89) -> 0 | AM87: =SUM(AM88:AM89) -> 0 | ... CH87: =SUM(CH88:CH89) -> 0 | CK87: {=SUM(INDIRECT(XLOOKUP('GAAP Summary'!$B$2,'TTM Dates'!$B:$B,'TTM Dates'!$E:$E)&ROW($CJ87)&":"&XLOOKUP('GAAP Summary'!$B$2,'TTM Dates'!$B:$B,'TTM Dates'!$C:$C)&ROW($CJ87)))} -> 482148.51 | CM87: =sum(BW87:BY87) -> 47882 | CN87: =sum(BZ87:CB87) -> 39332.97 | CO87: =sum(CC87:CE87) -> 0 | CP87: =sum(CF87:CH87) -> 0 | CQ87: =sum(BW87:CH87) -> 87214.97
B88: McDermott, Will & Emery | BS88: 232205.27 | BT88: 113975.54 | BU88: 24797.7 | BV88: 23955.03 | BW88: 20704 | BX88: 12717 | BY88: 14461 | CA88: 10284.66 | CB88: 29048.31 | CK88: {=SUM(INDIRECT(XLOOKUP('GAAP Summary'!$B$2,'TTM Dates'!$B:$B,'TTM Dates'!$E:$E)&ROW($CJ88)&":"&XLOOKUP('GAAP Summary'!$B$2,'TTM Dates'!$B:$B,'TTM Dates'!$C:$C)&ROW($CJ88)))} -> 482148.51 | CM88: =sum(BW88:BY88) -> 47882 | CN88: =sum(BZ88:CB88) -> 39332.97 | CO88: =sum(CC88:CE88) -> 0 | CP88: =sum(CF88:CH88) -> 0 | CQ88: =sum(BW88:CH88) -> 87214.97
CK89: {=SUM(INDIRECT(XLOOKUP('GAAP Summary'!$B$2,'TTM Dates'!$B:$B,'TTM Dates'!$E:$E)&ROW($CJ89)&":"&XLOOKUP('GAAP Summary'!$B$2,'TTM Dates'!$B:$B,'TTM Dates'!$C:$C)&ROW($CJ89)))} -> 0 | CM89: =sum(BW89:BY89) -> 0 | CN89: =sum(BZ89:CB89) -> 0 | CO89: =sum(CC89:CE89) -> 0 | CP89: =sum(CF89:CH89) -> 0 | CQ89: =sum(BW89:CH89) -> 0
BX90: =sum(BW91,BX91) -> 1000323 | CM90: =sum(BW90:BY90) -> 1000323 | CN90: =sum(BZ90:CB90) -> 0 | CO90: =sum(CC90:CE90) -> 0 | CP90: =sum(CF90:CH90) -> 0 | CQ90: =sum(BW90:CH90) -> 1000323
B91: Adj EBITDA | C91: =C13-C28-C69-C83+C85+C87 -> 0 | D91: =D13-D28-D69-D83+D85+D87 -> 0 | E91: =E13-E28-E69-E83+E85+E87 -> 0 | F91: =F13-F28-F69-F83+F85+F87 -> 0 | G91: =G13-G28-G69-G83+G85+G87 -> 0 | H91: =H13-H28-H69-H83+H85+H87 -> 0 | I91: =I13-I28-I69-I83+I85+I87 -> 0 | J91: =J13-J28-J69-J83+J85+J87 -> 0 | ... CH91: =CH13-CH28-CH69-CH83+CH85+CH87 -> 0 | CK91: {=SUM(INDIRECT(XLOOKUP('GAAP Summary'!$B$2,'TTM Dates'!$B:$B,'TTM Dates'!$E:$E)&ROW($CJ91)&":"&XLOOKUP('GAAP Summary'!$B$2,'TTM Dates'!$B:$B,'TTM Dates'!$C:$C)&ROW($CJ91)))} -> 6838323.1 | CM91: =sum(BW91:BY91) -> 1669524.5 | CN91: =sum(BZ91:CB91) -> 1943242.4 | CO91: =sum(CC91:CE91) -> 0 | CP91: =sum(CF91:CH91) -> 0 | CQ91: =sum(BW91:CH91) -> 3612766.9 | CS91: =sum(BK91:BM91) -> 772492.81 | CT91: =sum(BN91:BP91) -> 469136.94 | CU91: =sum(BQ91:BS91) -> 1118679 | CV91: =sum(BT91:BV91) -> 2106877.2 | CW91: =sum(BK91:BV91) -> 4467186 | CY91: =sum(AY91:BA91) -> -280200.53 | CZ91: =sum(BB91:BD91) -> -466499.87 | DA91: =sum(BE91:BG91) -> 156930.49 | DB91: =sum(BH91:BJ91) -> 1300446.6 | DC91: =sum(AY91:BJ91) -> 710676.67 | DD91: =sum(DA91:DB91)/DB6 -> 1180965.8 | DE91: =sum(AM91:AO91) -> 1853244.2 | DF91: =sum(AP91:AR91) -> 626613.28 | DG91: =sum(AS91:AU91) -> -356167.65 | DH91: =sum(AV91:AX91) -> -96749.96 | DI91: =sum(AM91:AX91) -> 2026939.9 | DK91: =sum(AA91:AC91) -> 1015244 | DL91: =sum(AD91:AF91) -> 1086449 | DM91: =sum(AG91:AI91) -> 1679446 | DN91: =sum(AJ91:AL91) -> 1005764 | DO91: =sum(DK91:DN91) -> 4786903 | DQ91: =DQ13-DQ69 -> 0 | DS91: {=IF(DS$3>'GAAP Summary'!$B$2,0,SUM(INDIRECT(XLOOKUP(DS$3,'TTM Dates'!$B:$B,'TTM Dates'!$E:$E)&ROW($CJ91)&":"&XLOOKUP(DS$3,'TTM Dates'!$B:$B,'TTM Dates'!$C:$C)&ROW($CJ91))))} -> 0 | DT91: {=IF(DT$3>'GAAP Summary'!$B$2,0,SUM(INDIRECT(XLOOKUP(DT$3,'TTM Dates'!$B:$B,'TTM Dates'!$E:$E)&ROW($CJ91)&":"&XLOOKUP(DT$3,'TTM Dates'!$B:$B,'TTM Dates'!$C:$C)&ROW($CJ91))))} -> 0 | DU91: {=IF(DU$3>'GAAP Summary'!$B$2,0,SUM(INDIRECT(XLOOKUP(DU$3,'TTM Dates'!$B:$B,'TTM Dates'!$E:$E)&ROW($CJ91)&":"&XLOOKUP(DU$3,'TTM Dates'!$B:$B,'TTM Dates'!$C:$C)&ROW($CJ91))))} -> 0 | DV91: {=IF(DV$3>'GAAP Summary'!$B$2,0,SUM(INDIRECT(XLOOKUP(DV$3,'TTM Dates'!$B:$B,'TTM Dates'!$E:$E)&ROW($CJ91)&":"&XLOOKUP(DV$3,'TTM Dates'!$B:$B,'TTM Dates'!$C:$C)&ROW($CJ91))))} -> 0 | DW91: {=IF(DW$3>'GAAP Summary'!$B$2,0,SUM(INDIRECT(XLOOKUP(DW$3,'TTM Dates'!$B:$B,'TTM Dates'!$E:$E)&ROW($CJ91)&":"&XLOOKUP(DW$3,'TTM Dates'!$B:$B,'TTM Dates'!$C:$C)&ROW($CJ91))))} -> 0 | DX91: {=IF(DX$3>'GAAP Summary'!$B$2,0,SUM(INDIRECT(XLOOKUP(DX$3,'TTM Dates'!$B:$B,'TTM Dates'!$E:$E)&ROW($CJ91)&":"&XLOOKUP(DX$3,'TTM Dates'!$B:$B,'TTM Dates'!$C:$C)&ROW($CJ91))))} -> 0 | DY91: {=IF(DY$3>'GAAP Summary'!$B$2,0,SUM(INDIRECT(XLOOKUP(DY$3,'TTM Dates'!$B:$B,'TTM Dates'!$E:$E)&ROW($CJ91)&":"&XLOOKUP(DY$3,'TTM Dates'!$B:$B,'TTM Dates'!$C:$C)&ROW($CJ91))))} -> 0 | DZ91: {=IF(DZ$3>'GAAP Summary'!$B$2,0,SUM(INDIRECT(XLOOKUP(DZ$3,'TTM Dates'!$B:$B,'TTM Dates'!$E:$E)&ROW($CJ91)&":"&XLOOKUP(DZ$3,'TTM Dates'!$B:$B,'TTM Dates'!$C:$C)&ROW($CJ91))))} -> 0 | ... GL91: {=IF(GL$3>'GAAP Summary'!$B$2,0,SUM(INDIRECT(XLOOKUP(GL$3,'TTM Dates'!$B:$B,'TTM Dates'!$E:$E)&ROW($CJ91)&":"&XLOOKUP(GL$3,'TTM Dates'!$B:$B,'TTM Dates'!$C:$C)&ROW($CJ91))))} -> 0
B92: EBITDA % | C92: =C91/C13 -> #DIV/0! | D92: =D91/D13 -> #DIV/0! | E92: =E91/E13 -> #DIV/0! | F92: =F91/F13 -> #DIV/0! | G92: =G91/G13 -> #DIV/0! | H92: =H91/H13 -> #DIV/0! | I92: =I91/I13 -> #DIV/0! | J92: =J91/J13 -> #DIV/0! | ... CH92: =CH91/CH13 -> #DIV/0! | CK92: =CK91/CK13 -> 0.14653223 | CM92: =IFERROR(CM91/CM13,0) -> 0.13277339 | CN92: =IFERROR(CN91/CN13,0) -> 0.14241994 | CO92: =IFERROR(CO91/CO13,0) -> 0 | CP92: =IFERROR(CP91/CP13,0) -> 0 | CQ92: =IFERROR(CQ91/CQ13,0) -> 0.13779354 | CS92: =IFERROR(CS91/CS13,0) -> 0.1040589 | CT92: =IFERROR(CT91/CT13,0) -> 0.058330812 | CU92: =IFERROR(CU91/CU13,0) -> 0.11777143 | CV92: =IFERROR(CV91/CV13,0) -> 0.19240393 | CW92: =CW91/CW13 -> 0.12438108 | CY92: =IFERROR(CY91/CY13,0) -> -0.051285355 | CZ92: =IFERROR(CZ91/CZ13,0) -> -0.081119259 | DA92: =IFERROR(DA91/DA13,0) -> 0.02447254 | DB92: =IFERROR(DB91/DB13,0) -> 0.16827548 | DC92: =DC91/DC13 -> 0.028029117 | DE92: =IFERROR(DE91/DE13,0) -> 0.29400973 | DF92: =IFERROR(DF91/DF13,0) -> 0.11216468 | DG92: =IFERROR(DG91/DG13,0) -> -0.068509707 | DH92: =IFERROR(DH91/DH13,0) -> -0.018986406 | DI92: =DI91/DI13 -> 0.091367678 | DK92: =IFERROR(DK91/DK13,0) -> 0.28075367 | DL92: =IFERROR(DL91/DL13,0) -> 0.27064604 | DM92: =IFERROR(DM91/DM13,0) -> 0.3436824 | DN92: =IFERROR(DN91/DN13,0) -> 0.20586455 | DO92: =DO91/DO13 -> 0.27506823 | DQ92: =DQ91/DQ13 -> #DIV/0! | FG92: -150000 | FH92: =400000 -> 400000 | FI92: =400000 -> 400000 | FJ92: =400000 -> 400000 | FK92: =400000 -> 400000 | FL92: =400000 -> 400000 | FM92: =400000 -> 400000 | FN92: =400000 -> 400000 | FO92: =FO91/FO13 -> 0.047188099 | FP92: =FP91/FP13 -> 0.05551871 | FQ92: =FQ91/FQ13 -> 0.064556846 | FR92: =FR91/FR13 -> 0.077874055 | FS92: =FS91/FS13 -> 0.080240099 | FT92: =FT91/FT13 -> 0.09116141 | FU92: =FU91/FU13 -> 0.098627059 | FV92: =FV91/FV13 -> 0.10610485 | ... GE92: =GE91/GE13 -> 0.14643298
B93: Data Label | BX93: =BX90/BX12 -> #VALUE! | CM93: =IF(CM91=0,"", TEXT(CM91,"0,000")&" "&"("&TEXT((CM91-CS91)/CS91,"0%")&" YoY)") -> 1,669,525 (116% YoY) | CN93: =IF(CN91=0,"", TEXT(CN91,"0,000")&" "&"("&TEXT((CN91-CT91)/CT91,"0%")&" YoY)") -> 1,943,242 (314% YoY) | CO93: =IF(CO91=0,"", TEXT(CO91,"0,000")&" "&"("&TEXT((CO91-CU91)/CU91,"0%")&" YoY)") | CP93: =IF(CP91=0,"", TEXT(CP91,"0,000")&" "&"("&TEXT((CP91-CV91)/CV91,"0%")&" YoY)") | CQ93: =IF(CQ91=0,"", TEXT(CQ91,"0,000")&" "&"("&TEXT((CQ91-CW91)/CW91,"0%")&" YoY)") -> 3,612,767 (-19% YoY) | CS93: =IF(CS91=0,"", TEXT(CS91,"0,000")&" "&"("&TEXT((CS91-CY91)/CY91,"0%")&" YoY)") -> 772,493 (-376% YoY) | CT93: =IF(CT91=0,"", TEXT(CT91,"0,000")&" "&"("&TEXT((CT91-CZ91)/CZ91,"0%")&" YoY)") -> 469,137 (-201% YoY) | CU93: =IF(CU91=0,"", TEXT(CU91,"0,000")&" "&"("&TEXT((CU91-DA91)/DA91,"0%")&" YoY)") -> 1,118,679 (613% YoY) | CV93: =IF(CV91=0,"", TEXT(CV91,"0,000")&" "&"("&TEXT((CV91-DB91)/DB91,"0%")&" YoY)") -> 2,106,877 (62% YoY) | CY93: =IF(CY91=0,"", TEXT(CY91,"0,000")&" "&"("&TEXT((CY91-DE91)/DE91,"0%")&" YoY)") -> -280,201 (-115% YoY) | CZ93: =IF(CZ91=0,"", TEXT(CZ91,"0,000")&" "&"("&TEXT((CZ91-DF91)/DF91,"0%")&" YoY)") -> -466,500 (-174% YoY) | DA93: =IF(DA91=0,"", TEXT(DA91,"0,000")&" "&"("&TEXT((DA91-DG91)/DG91,"0%")&" YoY)") -> 156,930 (-144% YoY) | DB93: =IF(DB91=0,"", TEXT(DB91,"0,000")&" "&"("&TEXT((DB91-DH91)/DH91,"0%")&" YoY)") -> 1,300,447 (-1444% YoY) | DE93: =IF(DE91=0,"", TEXT(DE91,"0,000")&" "&"("&TEXT((DE91-DK91)/DK91,"0%")&" YoY)") -> 1,853,244 (83% YoY) | DF93: =IF(DF91=0,"", TEXT(DF91,"0,000")&" "&"("&TEXT((DF91-DL91)/DL91,"0%")&" YoY)") -> 626,613 (-42% YoY) | DG93: =IF(DG91=0,"", TEXT(DG91,"0,000")&" "&"("&TEXT((DG91-DM91)/DM91,"0%")&" YoY)") -> -356,168 (-121% YoY) | DH93: =IF(DH91=0,"", TEXT(DH91,"0,000")&" "&"("&TEXT((DH91-DN91)/DN91,"0%")&" YoY)") -> -96,750 (-110% YoY)
AY94: 26499 | AZ94: 35621 | BA94: 112263 | BB94: 51121 | BC94: 126296 | BD94: 106944 | BE94: 30389 | BF94: -6574 | BG94: 30672 | BH94: 72560 | BI94: 33075 | BJ94: 32789 | CY94: =sum(AY94:BA94) -> 174383 | CZ94: =sum(BB94:BD94) -> 284361 | DA94: =sum(BE94:BG94) -> 54487 | DB94: =sum(BH94:BJ94) -> 138424 | DC94: =sum(AY94:BJ94) -> 651655 | FG94: =FF91+FG92 -> -453095.58 | FH94: =FG94+FH92 -> -53095.58 | FI94: =FH94+FI92 -> 346904.42 | FJ94: =FI94+FJ92 -> 746904.42 | FK94: =FJ94+FK92 -> 1146904.4 | FL94: =FK94+FL92 -> 1546904.4 | FM94: =FL94+FM92 -> 1946904.4 | FN94: =FM94+FN92 -> 2346904.4 | FS94: =FR91+FS92 -> 2182114.7 | FT94: =FS94+FT92 -> 2182114.8 | FU94: =FT94+FU92 -> 2182114.9 | FV94: =FU94+FV92 -> 2182115 | FW94: =FV94+FW92 -> 2182115.1 | FX94: =FW94+FX92 -> 2182115.2 | FY94: =FX94+FY92 -> 2182115.3 | FZ94: =FY94+FZ92 -> 2182115.5 | GA94: =FZ94+GA92 -> 2182115.6 | ... GL94: =GK94+GL92 -> 2182116.1
B95: Analysis | AY95: 286449 | AZ95: 174891 | BA95: 133306 | BB95: 168489 | BC95: 278236 | BD95: 335289 | BE95: 107540 | BF95: 272604 | BG95: 115120 | BH95: 148596 | BI95: 190351 | BJ95: 139415 | CY95: =sum(AY95:BA95) -> 594646 | CZ95: =sum(BB95:BD95) -> 782014 | DA95: =sum(BE95:BG95) -> 495264 | DB95: =sum(BH95:BJ95) -> 478362 | DC95: =sum(AY95:BJ95) -> 2350286
B97: Bookings
B98: DD Share of Bookings | AA98: =AA8/AA7 -> 0.68857893 | AB98: =AB8/AB7 -> 0.34250765 | AC98: =AC8/AC7 -> 0.065776743 | AD98: =AD8/AD7 -> 0.62475938 | AE98: =AE8/AE7 -> 0.14503131 | AF98: =AF8/AF7 -> 0.38399067 | AG98: =AG8/AG7 -> 0.42369222 | AH98: =AH8/AH7 -> 0.24169776 | ... AX98: =AX8/AX7 -> 0.48426642 | AY98: =IFERROR((AY8+AY10+AY11)/AY7,0) -> 0 | AZ98: =IFERROR((AZ8+AZ10+AZ11)/AZ7,0) -> 0.38572359 | BA98: =IFERROR((BA8+BA10+BA11)/BA7,0) -> 0.13440114 | BB98: =IFERROR((BB8+BB10+BB11)/BB7,0) -> 0.15244454 | BC98: =IFERROR((BC8+BC10+BC11)/BC7,0) -> 0.27715568 | BD98: =IFERROR((BD8+BD10+BD11)/BD7,0) -> 0.62827479 | BE98: =IFERROR((BE8+BE10+BE11)/BE7,0) -> 0.50960732 | BF98: =IFERROR((BF8+BF10+BF11)/BF7,0) -> 0.72430392 | ... BM98: =IFERROR((BM8+BM10+BM11)/BM7,0) -> 0.17722858 | BN98: =IFERROR(BN8/BN7,0) -> 0.20288525 | BO98: =IFERROR(BO8/BO7,0) -> 0.1474547 | BP98: =IFERROR(BP8/BP7,0) -> 0.2832978 | BQ98: =IFERROR(BQ8/BQ7,0) -> 0.17525418 | BR98: =IFERROR(BR8/BR7,0) -> 0.3388099 | BS98: =IFERROR(BS8/BS7,0) -> 0.12614616 | BT98: =IFERROR(BT8/BT7,0) -> 0.087178367 | BU98: =IFERROR(BU8/BU7,0) -> 0.60844318 | ... CH98: =IFERROR(CH8/CH7,0) -> 0 | CK98: =CK8/CK7 -> 0.2419136 | CM98: =IFERROR(CM8/CM7,0) -> 0.24856946 | CN98: =IFERROR(CN8/CN7,0) -> 0.11248471 | CO98: =IFERROR(CO8/CO7,0) -> 0 | CP98: =IFERROR(CP8/CP7,0) -> 0 | CQ98: =IFERROR(CQ8/CQ7,0) -> 0.19666052 | CS98: =IFERROR(CS8/CS7,0) -> 0.076244356 | CT98: =IFERROR(CT8/CT7,0) -> 0.2142804 | CU98: =IFERROR(CU8/CU7,0) -> 0.19321623 | CV98: =IFERROR(CV8/CV7,0) -> 0.33407349 | CW98: =IFERROR(CW8/CW7,0) -> 0.22831165 | CY98: =IFERROR(CY8/CY7,0) -> 0.12911303 | CZ98: =IFERROR(CZ8/CZ7,0) -> 0.29201598 | DA98: =IFERROR(DA8/DA7,0) -> 0.38458733 | DB98: =IFERROR(DB8/DB7,0) -> 0.44313029 | DC98: =IFERROR(DC8/DC7,0) -> 0.32954732 | DE98: =DE8/DE7 -> 0.4574935 | DF98: =DF8/DF7 -> 0.54193459 | DG98: =DG8/DG7 -> 0.35085442 | DH98: =DH8/DH7 -> 0.60339635 | DI98: =DI8/DI7 -> 0.51221846 | DK98: =DK8/DK7 -> 0.11027127 | DL98: =DL8/DL7 -> 0.27662385 | DM98: =DM8/DM7 -> 0.40809314 | DN98: =DN8/DN7 -> 0.36617017 | DO98: =DO8/DO7 -> 0.31226091 | DQ98: =DQ8/DQ7 -> #DIV/0!
B99: SN Share of Bookings | AA99: =AA9/AA7 -> 0.31142107 | AB99: =AB9/AB7 -> 0.14678899 | AC99: =AC9/AC7 -> 0.93422326 | AD99: =AD9/AD7 -> 0.36152551 | AE99: =AE9/AE7 -> 0.85215537 | AF99: =AF9/AF7 -> 0.60912117 | AG99: =AG9/AG7 -> 0.52399387 | AH99: =AH9/AH7 -> 0.73390007 | ... AX99: =AX9/AX7 -> 0.37956108 | AY99: =IFERROR(AY9/AY7,0) -> 1 | AZ99: =IFERROR(AZ9/AZ7,0) -> 0.61427641 | BA99: =IFERROR(BA9/BA7,0) -> 0.86559886 | BB99: =IFERROR(BB9/BB7,0) -> 0.84755546 | BC99: =IFERROR(BC9/BC7,0) -> 0.72284432 | BD99: =IFERROR(BD9/BD7,0) -> 0.37172521 | BE99: =IFERROR(BE9/BE7,0) -> 0.49039268 | BF99: =IFERROR(BF9/BF7,0) -> 0.27569608 | ... CH99: =IFERROR(CH9/CH7,0) -> 0 | CK99: =CK9/CK7 -> 0.70302191 | CM99: =IFERROR(CM9/CM7,0) -> 0.72057521 | CN99: =IFERROR(CN9/CN7,0) -> 0.815639 | CO99: =IFERROR(CO9/CO7,0) -> 0 | CP99: =IFERROR(CP9/CP7,0) -> 0 | CQ99: =IFERROR(CQ9/CQ7,0) -> 0.75683688 | CS99: =IFERROR(CS9/CS7,0) -> 0.77198679 | CT99: =IFERROR(CT9/CT7,0) -> 0.71978583 | CU99: =IFERROR(CU9/CU7,0) -> 0.76722186 | CV99: =IFERROR(CV9/CV7,0) -> 0.58906298 | CW99: =IFERROR(CW9/CW7,0) -> 0.69418459 | CY99: =IFERROR(CY9/CY7,0) -> 0.85049992 | CZ99: =IFERROR(CZ9/CZ7,0) -> 0.69646513 | DA99: =IFERROR(DA9/DA7,0) -> 0.54763302 | DB99: =IFERROR(DB9/DB7,0) -> 0.51079865 | DC99: =IFERROR(DC9/DC7,0) -> 0.63299452 | DE99: =DE9/DE7 -> 0.4460128 | DF99: =DF9/DF7 -> 0.41282102 | DG99: =DG9/DG7 -> 0.61986981 | DH99: =DH9/DH7 -> 0.32273808 | DI99: =DI9/DI7 -> 0.42641179 | DK99: =DK9/DK7 -> 0.85528973 | DL99: =DL9/DL7 -> 0.71807784 | DM99: =DM9/DM7 -> 0.56155339 | DN99: =DN9/DN7 -> 0.60333583 | DO99: =DO9/DO7 -> 0.66440627 | DQ99: =DQ9/DQ7 -> #DIV/0!
B101: Gross Profit | CM101: =SUM(CM102,CM104) -> 7267620.3 | CN101: =SUM(CN102,CN104) -> 8239452.2 | CO101: =SUM(CO102,CO104) -> 0 | CP101: =SUM(CP102,CP104) -> 0 | CQ101: =SUM(CQ102,CQ104) -> 15507073 | CS101: =SUM(CS102,CS104) -> 4368894 | CT101: =SUM(CT102,CT104) -> 4773545.1 | CU101: =SUM(CU102,CU104) -> 5680566.9 | CV101: =SUM(CV102,CV104) -> 6203003.1 | CW101: =SUM(CW102,CW104) -> 21026009 | CY101: =SUM(CY102,CY104) -> #REF! | CZ101: =SUM(CZ102,CZ104) -> #REF! | DA101: =SUM(DA102,DA104) -> #REF! | DB101: =SUM(DB102,DB104) -> #REF! | DC101: =SUM(DC102,DC104) -> #REF!
B102: DD Gross Profit | AM102: =AM$14 -> 0 | AN102: =AN$14 -> 0 | AO102: =AO$14 -> 0 | AP102: =AP$14 -> 0 | AQ102: =AQ$14 -> 0 | AR102: =AR$14 -> 0 | AS102: =AS$14 -> 0 | AT102: =AT$14 -> 0 | ... AX102: =AX$14 -> 0 | AY102: =AY$48 -> 581475.03 | AZ102: =AZ$48 -> 741255.2 | BA102: =BA$48 -> 818517.84 | BB102: =BB$48 -> 544044.01 | BC102: =BC$48 -> 496476.7 | BD102: =BD$48 -> 438959.56 | BE102: =BE$48 -> 550189.7 | BF102: =BF$48 -> 347207.31 | ... CH102: =CH$48 -> 0 | CK102: =CK$14-#REF! -> #REF! | CM102: =CM$14-CM$30 -> 1677793.3 | CN102: =CN$14-CN$30 -> 2592224.1 | CO102: =CO$14-CO$30 -> 0 | CP102: =CP$14-CP$30 -> 0 | CQ102: =CQ$14-CQ$30 -> 4270017.4 | CS102: =CS$14-CS$30 -> 1456110.1 | CT102: =CT$14-CT$30 -> 1378697.5 | CU102: =CU$14-CU$30 -> 1413534.8 | CV102: =CV$14-CV$30 -> 1308472.1 | CW102: =CW$14-CW$30 -> 5556814.5 | CY102: =CY$14-#REF! -> #REF! | CZ102: =CZ$14-#REF! -> #REF! | DA102: =DA$14-#REF! -> #REF! | DB102: =DB$14-#REF! -> #REF! | DC102: =DC$14-#REF! -> #REF! | DE102: =sum(AM102:AO102) -> 0 | DF102: =sum(AP102:AR102) -> 0 | DG102: =sum(AS102:AU102) -> 0 | DH102: =sum(AV102:AX102) -> 0 | DI102: =DI$14-#REF! -> #REF! | DK102: =sum(AA102:AC102) -> 0 | DL102: =sum(AD102:AF102) -> 0 | DM102: =sum(AG102:AI102) -> 0 | DN102: =sum(AJ102:AL102) -> 0 | DO102: =sum(AA102:AL102) -> 0
B103: DD Gross Profit % | AM103: =IFERROR(AM$102/AM$14,0) -> 0 | AN103: =IFERROR(AN$102/AN$14,0) -> 0 | AO103: =IFERROR(AO$102/AO$14,0) -> 0 | AP103: =IFERROR(AP$102/AP$14,0) -> 0 | AQ103: =IFERROR(AQ$102/AQ$14,0) -> 0 | AR103: =IFERROR(AR$102/AR$14,0) -> 0 | AS103: =IFERROR(AS$102/AS$14,0) -> 0 | AT103: =IFERROR(AT$102/AT$14,0) -> 0 | ... CH103: =IFERROR(CH$102/CH$14,0) -> 0 | CK103: =IFERROR(CK$102/CK$14,0) -> 0 | CM103: =IFERROR(CM$102/CM$14,0) -> 0.4837237 | CN103: =IFERROR(CN$102/CN$14,0) -> 0.59073361 | CO103: =IFERROR(CO$102/CO$14,0) -> 0 | CP103: =IFERROR(CP$102/CP$14,0) -> 0 | CQ103: =IFERROR(CQ$102/CQ$14,0) -> 0.54349161 | CS103: =IFERROR(CS$102/CS$14,0) -> 0.54874494 | CT103: =IFERROR(CT$102/CT$14,0) -> 0.53225808 | CU103: =IFERROR(CU$102/CU$14,0) -> 0.51919764 | CV103: =IFERROR(CV$102/CV$14,0) -> 0.43645796 | CW103: =IFERROR(CW$102/CW$14,0) -> 0.50681075 | CY103: =IFERROR(CY$102/CY$14,0) -> 0 | CZ103: =IFERROR(CZ$102/CZ$14,0) -> 0 | DA103: =IFERROR(DA$102/DA$14,0) -> 0 | DB103: =IFERROR(DB$102/DB$14,0) -> 0 | DC103: =IFERROR(DC$102/DC$14,0) -> 0 | DE103: =IFERROR(DE$102/DE$14,0) -> 0 | DF103: =IFERROR(DF$102/DF$14,0) -> 0 | DG103: =IFERROR(DG$102/DG$14,0) -> 0 | DH103: =IFERROR(DH$102/DH$14,0) -> 0 | DI103: =IFERROR(DI$102/DI$14,0) -> 0 | DK103: =IFERROR(DK$102/DK$14,0) -> 0 | DL103: =IFERROR(DL$102/DL$14,0) -> 0 | DM103: =IFERROR(DM$102/DM$14,0) -> 0 | DN103: =IFERROR(DN$102/DN$14,0) -> 0 | DO103: =IFERROR(DO$102/DO$14,0) -> 0
B104: SN Gross Profit | AM104: =AM$19 -> 0 | AN104: =AN$19 -> 0 | AO104: =AO$19 -> 0 | AP104: =AP$19 -> 0 | AQ104: =AQ$19 -> 0 | AR104: =AR$19 -> 0 | AS104: =AS$19 -> 0 | AT104: =AT$19 -> 0 | ... AX104: =AX$19 -> 0 | AY104: =AY$53 -> 344123.68 | AZ104: =AZ$53 -> 442280.59 | BA104: =BA$53 -> 415364.13 | BB104: =BB$53 -> 495712.64 | BC104: =BC$53 -> 751367.97 | BD104: =BD$53 -> 732474.25 | BE104: =BE$53 -> 851519.33 | BF104: =BF$53 -> 630705.94 | ... CH104: =CH$53 -> 0 | CK104: =CK$19-#REF! -> #REF! | CM104: =CM$19-CM$35 -> 5589827.1 | CN104: =CN$19-CN$35 -> 5647228.1 | CO104: =CO$19-CO$35 -> 0 | CP104: =CP$19-CP$35 -> 0 | CQ104: =CQ$19-CQ$35 -> 11237055 | CS104: =CS$19-CS$35 -> 2912783.9 | CT104: =CT$19-CT$35 -> 3394847.6 | CU104: =CU$19-CU$35 -> 4267032.1 | CV104: =CV$19-CV$35 -> 4894531 | CW104: =CW$19-CW$35 -> 15469195 | CY104: =CY$19-#REF! -> #REF! | CZ104: =CZ$19-#REF! -> #REF! | DA104: =DA$19-#REF! -> #REF! | DB104: =DB$19-#REF! -> #REF! | DC104: =DC$19-#REF! -> #REF! | DE104: =sum(AM104:AO104) -> 0 | DF104: =sum(AP104:AR104) -> 0 | DG104: =sum(AS104:AU104) -> 0 | DH104: =sum(AV104:AX104) -> 0 | DI104: =DI$19-#REF! -> #REF! | DK104: =sum(AA104:AC104) -> 0 | DL104: =sum(AD104:AF104) -> 0 | DM104: =sum(AG104:AI104) -> 0 | DN104: =sum(AJ104:AL104) -> 0 | DO104: =sum(AA104:AL104) -> 0
B105: SN Gross Profit % | AM105: =IFERROR(AM$104/AM$19,0) -> 0 | AN105: =IFERROR(AN$104/AN$19,0) -> 0 | AO105: =IFERROR(AO$104/AO$19,0) -> 0 | AP105: =IFERROR(AP$104/AP$19,0) -> 0 | AQ105: =IFERROR(AQ$104/AQ$19,0) -> 0 | AR105: =IFERROR(AR$104/AR$19,0) -> 0 | AS105: =IFERROR(AS$104/AS$19,0) -> 0 | AT105: =IFERROR(AT$104/AT$19,0) -> 0 | ... CH105: =IFERROR(CH$104/CH$19,0) -> 0 | CK105: =IFERROR(CK$104/CK$19,0) -> 0 | CM105: =IFERROR(CM$104/CM$19,0) -> 0.61387911 | CN105: =IFERROR(CN$104/CN$19,0) -> 0.61009496 | CO105: =IFERROR(CO$104/CO$19,0) -> 0 | CP105: =IFERROR(CP$104/CP$19,0) -> 0 | CQ105: =IFERROR(CQ$104/CQ$19,0) -> 0.61197152 | CS105: =IFERROR(CS$104/CS$19,0) -> 0.6106359 | CT105: =IFERROR(CT$104/CT$19,0) -> 0.62263192 | CU105: =IFERROR(CU$104/CU$19,0) -> 0.62970942 | CV105: =IFERROR(CV$104/CV$19,0) -> 0.61548252 | CW105: =IFERROR(CW$104/CW$19,0) -> 0.61998201 | CY105: =IFERROR(CY$104/CY$19,0) -> 0 | CZ105: =IFERROR(CZ$104/CZ$19,0) -> 0 | DA105: =IFERROR(DA$104/DA$19,0) -> 0 | DB105: =IFERROR(DB$104/DB$19,0) -> 0 | DC105: =IFERROR(DC$104/DC$19,0) -> 0 | DE105: =IFERROR(DE$104/DE$19,0) -> 0 | DF105: =IFERROR(DF$104/DF$19,0) -> 0 | DG105: =IFERROR(DG$104/DG$19,0) -> 0 | DH105: =IFERROR(DH$104/DH$19,0) -> 0 | DI105: =IFERROR(DI$104/DI$19,0) -> 0 | DK105: =IFERROR(DK$104/DK$19,0) -> 0 | DL105: =IFERROR(DL$104/DL$19,0) -> 0 | DM105: =IFERROR(DM$104/DM$19,0) -> 0 | DN105: =IFERROR(DN$104/DN$19,0) -> 0 | DO105: =IFERROR(DO$104/DO$19,0) -> 0
B106: Total Gross Profit | AA106: =AA13-AA28 -> 889131 | AB106: =AB13-AB28 -> 687372 | AC106: =AC13-AC28 -> 1021125 | AD106: =AD13-AD28 -> 776322 | AE106: =AE13-AE28 -> 885482 | AF106: =AF13-AF28 -> 1151776 | AG106: =AG13-AG28 -> 877748 | AH106: =AH13-AH28 -> 1488242 | ... CH106: =CH13-CH28 -> 0 | CK106: =CK13-CK28 -> 26872030 | CM106: =CM13-CM28 -> 7112184.7 | CN106: =CN13-CN28 -> 8110931.3 | CO106: =CO13-CO28 -> 0 | CP106: =CP13-CP28 -> 0 | CQ106: =CQ13-CQ28 -> 15223116 | CS106: =CS13-CS28 -> 4198291.5 | CT106: =CT13-CT28 -> 4696365.4 | CU106: =CU13-CU28 -> 5504023.9 | CV106: =CV13-CV28 -> 6144890.5 | CW106: =CW13-CW28 -> 20543571 | CY106: =CY13-CY28 -> 3293852.2 | CZ106: =CZ13-CZ28 -> 3282484.9 | DA106: =DA13-DA28 -> 3565998.4 | DB106: =DB13-DB28 -> 4779013.3 | DC106: =DC13-DC28 -> 14921349 | DE106: =DE13-DE28 -> 4245775.2 | DF106: =DF13-DF28 -> 3595095.3 | DG106: =DG13-DG28 -> 2866689.4 | DH106: =DH13-DH28 -> 2945064 | DI106: =DI13-DI28 -> 13652624 | DK106: =sum(AA106:AC106) -> 2597628 | DL106: =sum(AD106:AF106) -> 2813580 | DM106: =sum(AG106:AI106) -> 3532792 | DN106: =sum(AJ106:AL106) -> 3423182 | DO106: =sum(AA106:AL106) -> 12367182
B107: Total Gross Profit % | AA107: =IFERROR(AA106/AA13,0) -> 0.75682253 | AB107: =IFERROR(AB106/AB13,0) -> 0.64929598 | AC107: =IFERROR(AC106/AC13,0) -> 0.73851411 | AD107: =IFERROR(AD106/AD13,0) -> 0.6483928 | AE107: =IFERROR(AE106/AE13,0) -> 0.69332546 | AF107: =IFERROR(AF106/AF13,0) -> 0.74799101 | AG107: =IFERROR(AG106/AG13,0) -> 0.6617132 | AH107: =IFERROR(AH106/AH13,0) -> 0.76974902 | ... CH107: =IFERROR(CH106/CH13,0) -> 0 | CK107: =IFERROR(CK106/CK13,0) -> 0.5758164 | CM107: =IFERROR(CM$106/CM$13,0) -> 0.56561544 | CN107: =IFERROR(CN$106/CN$13,0) -> 0.59444895 | CO107: =IFERROR(CO$106/CO$13,0) -> 0 | CP107: =IFERROR(CP$106/CP$13,0) -> 0 | CQ107: =IFERROR(CQ$106/CQ$13,0) -> 0.58062067 | CS107: =IFERROR(CS$106/CS$13,0) -> 0.56553227 | CT107: =IFERROR(CT$106/CT$13,0) -> 0.58392931 | CU107: =IFERROR(CU$106/CU$13,0) -> 0.57944844 | CV107: =IFERROR(CV$106/CV$13,0) -> 0.56116279 | CW107: =IFERROR(CW$106/CW$13,0) -> 0.57200028 | CY107: =IFERROR(CY$106/CY$13,0) -> 0.60287674 | CZ107: =IFERROR(CZ$106/CZ$13,0) -> 0.57078845 | DA107: =IFERROR(DA$106/DA$13,0) -> 0.55609995 | DB107: =IFERROR(DB$106/DB$13,0) -> 0.61839585 | DC107: =IFERROR(DC$106/DC$13,0) -> 0.5884986 | DE107: =IFERROR(DE$106/DE$13,0) -> 0.67357515 | DF107: =IFERROR(DF$106/DF$13,0) -> 0.64352726 | DG107: =IFERROR(DG$106/DG$13,0) -> 0.55141462 | DH107: =IFERROR(DH$106/DH$13,0) -> 0.57794527 | DI107: =IFERROR(DI$106/DI$13,0) -> 0.61541468 | DK107: =IFERROR(DK$106/DK$13,0) -> 0.71834316 | DL107: =IFERROR(DL$106/DL$13,0) -> 0.70089281 | DM107: =IFERROR(DM$106/DM$13,0) -> 0.72295177 | DN107: =IFERROR(DN$106/DN$13,0) -> 0.70067313 | DO107: =IFERROR(DO$106/DO$13,0) -> 0.71065132
B108: Data Label | CM108: =IF(CM106=0,"", TEXT(CM106,"0,000")&" "&"("&TEXT((CM106-CS106)/CS106,"0%")&" YoY)") -> 7,112,185 (69% YoY) | CN108: =IF(CN106=0,"", TEXT(CN106,"0,000")&" "&"("&TEXT((CN106-CT106)/CT106,"0%")&" YoY)") -> 8,110,931 (73% YoY) | CO108: =IF(CO106=0,"", TEXT(CO106,"0,000")&" "&"("&TEXT((CO106-CU106)/CU106,"0%")&" YoY)") | CP108: =IF(CP106=0,"", TEXT(CP106,"0,000")&" "&"("&TEXT((CP106-CV106)/CV106,"0%")&" YoY)") | CQ108: =IF(CQ106=0,"", TEXT(CQ106,"0,000")&" "&"("&TEXT((CQ106-CW106)/CW106,"0%")&" YoY)") -> 15,223,116 (-26% YoY) | CS108: =IF(CS106=0,"", TEXT(CS106,"0,000")&" "&"("&TEXT((CS106-CY106)/CY106,"0%")&" YoY)") -> 4,198,292 (27% YoY) | CT108: =IF(CT106=0,"", TEXT(CT106,"0,000")&" "&"("&TEXT((CT106-CZ106)/CZ106,"0%")&" YoY)") -> 4,696,365 (43% YoY) | CU108: =IF(CU106=0,"", TEXT(CU106,"0,000")&" "&"("&TEXT((CU106-DA106)/DA106,"0%")&" YoY)") -> 5,504,024 (54% YoY) | CV108: =IF(CV106=0,"", TEXT(CV106,"0,000")&" "&"("&TEXT((CV106-DB106)/DB106,"0%")&" YoY)") -> 6,144,891 (29% YoY) | CY108: =IF(CY106=0,"", TEXT(CY106,"0,000")&" "&"("&TEXT((CY106-DE106)/DE106,"0%")&" YoY)") -> 3,293,852 (-22% YoY) | CZ108: =IF(CZ106=0,"", TEXT(CZ106,"0,000")&" "&"("&TEXT((CZ106-DF106)/DF106,"0%")&" YoY)") -> 3,282,485 (-9% YoY) | DA108: =IF(DA106=0,"", TEXT(DA106,"0,000")&" "&"("&TEXT((DA106-DG106)/DG106,"0%")&" YoY)") -> 3,565,998 (24% YoY) | DB108: =IF(DB106=0,"", TEXT(DB106,"0,000")&" "&"("&TEXT((DB106-DH106)/DH106,"0%")&" YoY)") -> 4,779,013 (62% YoY) | DE108: =IF(DE106=0,"", TEXT(DE106,"0,000")&" "&"("&TEXT((DE106-DK106)/DK106,"0%")&" YoY)") -> 4,245,775 (63% YoY) | DF108: =IF(DF106=0,"", TEXT(DF106,"0,000")&" "&"("&TEXT((DF106-DL106)/DL106,"0%")&" YoY)") -> 3,595,095 (28% YoY) | DG108: =IF(DG106=0,"", TEXT(DG106,"0,000")&" "&"("&TEXT((DG106-DM106)/DM106,"0%")&" YoY)") -> 2,866,689 (-19% YoY) | DH108: =IF(DH106=0,"", TEXT(DH106,"0,000")&" "&"("&TEXT((DH106-DN106)/DN106,"0%")&" YoY)") -> 2,945,064 (-14% YoY)
B110: COGS + Opex | AA110: =AA69+AA28 -> 742993 | AB110: =AB69+AB28 -> 895598 | AC110: =AC69+AC28 -> 962303 | AD110: =AD69+AD28 -> 968591 | AE110: =AE69+AE28 -> 972534 | AF110: =AF69+AF28 -> 986706 | AG110: =AG69+AG28 -> 1051189 | AH110: =AH69+AH28 -> 1013407 | ... CH110: =CH69+CH28 -> 0 | CK110: =CK69+CK28 -> 39749384 | CM110: =CM69+CM28 -> 10764977 | CN110: =CN69+CN28 -> 11563208 | CO110: =CO69+CO28 -> 0 | CP110: =CP69+CP28 -> 0 | CQ110: =CQ69+CQ28 -> 22328184 | CS110: =CS69+CS28 -> 6651118.2 | CT110: =CT69+CT28 -> 7573558.2 | CU110: =CU69+CU28 -> 8579683.8 | CV110: =CV69+CV28 -> 8841515.7 | CW110: =CW69+CW28 -> 31645876 | CY110: =CY69+CY28 -> 5743758.8 | CZ110: =CZ69+CZ28 -> 6217290.5 | DA110: =DA69+DA28 -> 6255582.9 | DB110: =DB69+DB28 -> 6427634.6 | DC110: =DC69+DC28 -> 24644267 | DE110: =DE69+DE28 -> 4450098.8 | DF110: =DF69+DF28 -> 4959933.7 | DG110: =DG69+DG28 -> 5554958.7 | DH110: =DH69+DH28 -> 5192499 | DI110: =DI69+DI28 -> 20157490 | DK110: =DK69+DK28 -> 2600894 | DL110: =DL69+DL28 -> 2927831 | DM110: =DM69+DM28 -> 3207176 | DN110: =DN69+DN28 -> 3879798 | DO110: =DO69+DO28 -> 12615699
...

Sheet Sandbox
B3: Monthly Services Revenue | D3: Billabe HC | E3: ='QBO Analysis'!AV69 -> 51 | G3: Revenue @ 90% Utilization | H3: =$E$5*$E$4*0.9 -> 2148120
D4: Monthly available hours | E4: =(40*52/12)*E3 -> 8840 | G4: Revenue @ 80% Utilization | H4: =$E$5*$E$4*0.8 -> 1909440
D5: Rate | E5: 270 | G5: Revenue @ 70% Utilization | H5: =$E$5*$E$4*0.7 -> 1670760
K6: 7 | L6: 2 | N6: 38 | O6: =N6/K6 -> 5.4285714 | Q6: =5*9 -> 45
B7: Monthly Deposit Revenue | D7: Deposit Rate | E7: 0.25 | G7: Revenue @10mm quarterly bookings | H7: =10000000*$E$7/3 -> 833333.33 | K7: 5 | L7: 2 | N7: 10 | O7: =N7/K7 -> 2 | Q7: =2*7 -> 14
G8: Revenue @8mm quarterly bookings | H8: =8000000*$E$7/3 -> 666666.67 | K8: 1
G9: Revenue @6mm quarterly bookings | H9: =6000000*$E$7/3 -> 500000
B11: TOTAL Revenue | H11: =sum(H3,H7) -> 2981453.3
H12: =sum(H4,H8) -> 2576106.7
H13: =sum(H5,H9) -> 2170760
B17: $ / HC Math
D19: Q1 | E19: Q2 | F19: Q3 | G19: Q4 | H19: FY23
B20: Rev | D20: 5518015.8 | E20: 4494229.3 | F20: 5206792 | G20: 6829659.6 | H20: =sum(D20:G20) -> 22048697
B21: Billable HC | D21: ='QBO Analysis'!BT69 -> 50 | E21: ='QBO Analysis'!BU69 -> 46 | F21: ='QBO Analysis'!BV69 -> 50.666667 | G21: ='QBO Analysis'!BW69 -> 49.666667 | H21: =average('QBO Analysis'!AM69:AX69) -> 49.083333
B22: $ / Billable HC | D22: =D20/D21 -> 110360.32 | E22: =E20/E21 -> 97700.637 | F22: =F20/F21 -> 102765.63 | G22: =G20/G21 -> 137509.93 | H22: =H20/H21 -> 449209.44
B23: Total HC | D23: =sum('QBO Analysis'!BT68:BT69) -> 76.333333 | E23: =sum('QBO Analysis'!BU68:BU69) -> 78 | F23: =sum('QBO Analysis'!BV68:BV69) -> 85.333333 | G23: =sum('QBO Analysis'!BW68:BW69) -> 90.666667 | H23: 87
B24: $ / Total HC | D24: =D20/D23 -> 72288.416 | E24: =E20/E23 -> 57618.325 | F24: =F20/F23 -> 61017.093 | G24: =G20/G23 -> 75327.128 | H24: =H20/H23 -> 253433.3 | I24: =H24/4 -> 63358.324
D28: Q1 | E28: Q2 | F28: Q3 | G28: Q4 | H28: FY24
B29: Rev | D29: 4000000 | E29: 7000000 | F29: 8000000 | G29: 9000000 | H29: =sum(D29:G29) -> 28000000
B30: Billable HC | D30: 48 | E30: 62 | F30: 67 | G30: 71
B31: $ / Billable HC | D31: 110360.32 | E31: 97700.637 | F31: 102765.63 | G31: 137509.93
B32: Non Billable HC | D32: 43 | E32: 43 | F32: 43 | G32: 42
D33: =D32+D30 -> 91 | E33: =E32+E30 -> 105 | F33: =F32+F30 -> 110 | G33: =G32+G30 -> 113 | H33: 113
B34: $ / Total HC | D34: =D29/D33 -> 43956.044 | E34: =E29/E33 -> 66666.667 | F34: =F29/F33 -> 72727.273 | G34: =G29/G33 -> 79646.018 | H34: =H29/H33/4 -> 61946.903 | I34: =H34/I24 -> 0.97772319
D35: =D34/D24 -> 0.60806483 | E35: =E34/E24 -> 1.1570393 | F35: =F34/F24 -> 1.1919164 | G35: =G34/G24 -> 1.0573351
H38: 527197.27 | I38: 394514.59 | J38: 498308.91 | K38: 391804.75 | L38: 736952.26 | M38: 461093.24 | N38: 710208.99 | O38: 819073.8 | P38: 655594.4 | Q38: 721630.35 | R38: 660148.61 | S38: 617741.94 | T38: 662290.41 | U38: 767687.8 | V38: 629309.68
B43: SN Eng Revenue Scenarios
B45: YTD Rev (ex deposits) | C45: 4563965
B46: Monthly Hrs Remaining | C46: =1056+80 -> 1136 | K46: Bookings | L46: 12000000
B47: Utilization | C47: 0.8 | K47: Deposits | L47: 0.25
B48: Monthly Hrs Remaining | C48: =C46*C47 -> 908.8 | L48: =L46*L47 -> 3000000
B49: Real Rate | C49: 325
E50: Real Rate
E51: 300 | F51: 325 | G51: 350 | H51: 375 | I51: 400
D52: 23 | E52: =(($D52*E$51*$C$48)+$C$45)/1000 -> 10834.685 | F52: =(($D52*F$51*$C$48)+$C$45)/1000 -> 11357.245 | G52: =(($D52*G$51*$C$48)+$C$45)/1000 -> 11879.805 | H52: =(($D52*H$51*$C$48)+$C$45)/1000 -> 12402.365 | I52: =(($D52*I$51*$C$48)+$C$45)/1000 -> 12924.925
D53: 24 | E53: =(($D53*E$51*$C$48)+$C$45)/1000 -> 11107.325 | F53: =(($D53*F$51*$C$48)+$C$45)/1000 -> 11652.605 | G53: =(($D53*G$51*$C$48)+$C$45)/1000 -> 12197.885 | H53: =(($D53*H$51*$C$48)+$C$45)/1000 -> 12743.165 | I53: =(($D53*I$51*$C$48)+$C$45)/1000 -> 13288.445
D54: 25 | E54: =(($D54*E$51*$C$48)+$C$45)/1000 -> 11379.965 | F54: =(($D54*F$51*$C$48)+$C$45)/1000 -> 11947.965 | G54: =(($D54*G$51*$C$48)+$C$45)/1000 -> 12515.965 | H54: =(($D54*H$51*$C$48)+$C$45)/1000 -> 13083.965 | I54: =(($D54*I$51*$C$48)+$C$45)/1000 -> 13651.965
C55: Avg Eng Heads | D55: 26 | E55: =(($D55*E$51*$C$48)+$C$45)/1000 -> 11652.605 | F55: =(($D55*F$51*$C$48)+$C$45)/1000 -> 12243.325 | G55: =(($D55*G$51*$C$48)+$C$45)/1000 -> 12834.045 | H55: =(($D55*H$51*$C$48)+$C$45)/1000 -> 13424.765 | I55: =(($D55*I$51*$C$48)+$C$45)/1000 -> 14015.485
D56: 27 | E56: =(($D56*E$51*$C$48)+$C$45)/1000 -> 11925.245 | F56: =(($D56*F$51*$C$48)+$C$45)/1000 -> 12538.685 | G56: =(($D56*G$51*$C$48)+$C$45)/1000 -> 13152.125 | H56: =(($D56*H$51*$C$48)+$C$45)/1000 -> 13765.565 | I56: =(($D56*I$51*$C$48)+$C$45)/1000 -> 14379.005 | K56: Heads | L56: Hours | M56: Rate | N56: $
D57: 28 | E57: =(($D57*E$51*$C$48)+$C$45)/1000 -> 12197.885 | F57: =(($D57*F$51*$C$48)+$C$45)/1000 -> 12834.045 | G57: =(($D57*G$51*$C$48)+$C$45)/1000 -> 13470.205 | H57: =(($D57*H$51*$C$48)+$C$45)/1000 -> 14106.365 | I57: =(($D57*I$51*$C$48)+$C$45)/1000 -> 14742.525 | K57: 22 | L57: 1040 | M57: 320 | N57: =K57*L57*M57 -> 7321600
D58: 29 | E58: =(($D58*E$51*$C$48)+$C$45)/1000 -> 12470.525 | F58: =(($D58*F$51*$C$48)+$C$45)/1000 -> 13129.405 | G58: =(($D58*G$51*$C$48)+$C$45)/1000 -> 13788.285 | H58: =(($D58*H$51*$C$48)+$C$45)/1000 -> 14447.165 | I58: =(($D58*I$51*$C$48)+$C$45)/1000 -> 15106.045
D59: 30 | E59: =(($D59*E$51*$C$48)+$C$45)/1000 -> 12743.165 | F59: =(($D59*F$51*$C$48)+$C$45)/1000 -> 13424.765 | G59: =(($D59*G$51*$C$48)+$C$45)/1000 -> 14106.365 | H59: =(($D59*H$51*$C$48)+$C$45)/1000 -> 14787.965 | I59: =(($D59*I$51*$C$48)+$C$45)/1000 -> 15469.565 | N59: =(N57/1000)+I59 -> 22791.165
E63: Avg Utilization
E64: 0.7 | F64: 0.75 | G64: 0.8 | H64: 0.85 | I64: 0.9
D65: 23 | E65: =(($D65*E$64*$C$49*$C$46)+$C$45)/1000 -> 10508.085 | F65: =(($D65*F$64*$C$49*$C$46)+$C$45)/1000 -> 10932.665 | G65: =(($D65*G$64*$C$49*$C$46)+$C$45)/1000 -> 11357.245 | H65: =(($D65*H$64*$C$49*$C$46)+$C$45)/1000 -> 11781.825 | I65: =(($D65*I$64*$C$49*$C$46)+$C$45)/1000 -> 12206.405
D66: 24 | E66: =(($D66*E$64*$C$49*$C$46)+$C$45)/1000 -> 10766.525 | F66: =(($D66*F$64*$C$49*$C$46)+$C$45)/1000 -> 11209.565 | G66: =(($D66*G$64*$C$49*$C$46)+$C$45)/1000 -> 11652.605 | H66: =(($D66*H$64*$C$49*$C$46)+$C$45)/1000 -> 12095.645 | I66: =(($D66*I$64*$C$49*$C$46)+$C$45)/1000 -> 12538.685
D67: 25 | E67: =(($D67*E$64*$C$49*$C$46)+$C$45)/1000 -> 11024.965 | F67: =(($D67*F$64*$C$49*$C$46)+$C$45)/1000 -> 11486.465 | G67: =(($D67*G$64*$C$49*$C$46)+$C$45)/1000 -> 11947.965 | H67: =(($D67*H$64*$C$49*$C$46)+$C$45)/1000 -> 12409.465 | I67: =(($D67*I$64*$C$49*$C$46)+$C$45)/1000 -> 12870.965
C68: Avg Eng Heads | D68: 26 | E68: =(($D68*E$64*$C$49*$C$46)+$C$45)/1000 -> 11283.405 | F68: =(($D68*F$64*$C$49*$C$46)+$C$45)/1000 -> 11763.365 | G68: =(($D68*G$64*$C$49*$C$46)+$C$45)/1000 -> 12243.325 | H68: =(($D68*H$64*$C$49*$C$46)+$C$45)/1000 -> 12723.285 | I68: =(($D68*I$64*$C$49*$C$46)+$C$45)/1000 -> 13203.245
D69: 27 | E69: =(($D69*E$64*$C$49*$C$46)+$C$45)/1000 -> 11541.845 | F69: =(($D69*F$64*$C$49*$C$46)+$C$45)/1000 -> 12040.265 | G69: =(($D69*G$64*$C$49*$C$46)+$C$45)/1000 -> 12538.685 | H69: =(($D69*H$64*$C$49*$C$46)+$C$45)/1000 -> 13037.105 | I69: =(($D69*I$64*$C$49*$C$46)+$C$45)/1000 -> 13535.525
D70: 28 | E70: =(($D70*E$64*$C$49*$C$46)+$C$45)/1000 -> 11800.285 | F70: =(($D70*F$64*$C$49*$C$46)+$C$45)/1000 -> 12317.165 | G70: =(($D70*G$64*$C$49*$C$46)+$C$45)/1000 -> 12834.045 | H70: =(($D70*H$64*$C$49*$C$46)+$C$45)/1000 -> 13350.925 | I70: =(($D70*I$64*$C$49*$C$46)+$C$45)/1000 -> 13867.805
D71: 29 | E71: =(($D71*E$64*$C$49*$C$46)+$C$45)/1000 -> 12058.725 | F71: =(($D71*F$64*$C$49*$C$46)+$C$45)/1000 -> 12594.065 | G71: =(($D71*G$64*$C$49*$C$46)+$C$45)/1000 -> 13129.405 | H71: =(($D71*H$64*$C$49*$C$46)+$C$45)/1000 -> 13664.745 | I71: =(($D71*I$64*$C$49*$C$46)+$C$45)/1000 -> 14200.085
D72: 30 | E72: =(($D72*E$64*$C$49*$C$46)+$C$45)/1000 -> 12317.165 | F72: =(($D72*F$64*$C$49*$C$46)+$C$45)/1000 -> 12870.965 | G72: =(($D72*G$64*$C$49*$C$46)+$C$45)/1000 -> 13424.765 | H72: =(($D72*H$64*$C$49*$C$46)+$C$45)/1000 -> 13978.565 | I72: =(($D72*I$64*$C$49*$C$46)+$C$45)/1000 -> 14532.365
B78: As of | C78: TTM EBITDA | D78: Bookings | E78: Revenue | F78: OpEx | G78: Utilization | H78: Non-billable personnel
B79: 44949 | C79: 3988181.1 | D79: 134400 | E79: 1954210.2 | F79: 1035424.8 | G79: 0.68064904 | H79: 527197.27
B80: 44980 | C80: 3975692.5 | D80: 846864 | E80: 1936196.7 | F80: 1078554.4 | G80: 0.58169379 | H80: 394514.59
B81: 45008 | C81: 4027017.5 | D81: 1827624 | E81: 1627608.9 | F81: 962816.82 | G81: 0.74007692 | H81: 498308.91
B82: 45039 | C82: 3796139.5 | D82: 552923.41 | E82: 1380644.8 | F82: 1128874.9 | G82: 0.70538462 | H82: 391804.75
B83: 45069 | C83: 1983813.5 | D83: 857590 | E83: 1024531.6 | F83: 1192177.8 | G83: 0.70610368 | H83: 736952.26
B84: 45100 | C84: 1575213.4 | D84: 2370127.4 | E84: 2089052.9 | F84: 935614.2 | G84: 0.64148936 | H84: 461093.24
B85: 45130 | C85: 216949.49 | D85: 1015910 | E85: 1094866.2 | F85: 1194415.8 | G85: 0.48320251 | H85: 710208.99
B86: 45161 | C86: 374396.18 | D86: 2102478 | E86: 2367443.7 | F86: 1342642.2 | G86: 0.57747781 | H86: 819073.8
B87: 45192 | C87: -101258.43 | D87: 1227118 | E87: 1744482 | F87: 1035135.8 | G87: 0.52443439 | H87: 655594.4
B88: 45222 | C88: -981011.19 | D88: 1426203 | E88: 1462805 | F88: 1104682.4 | G88: 0.6199095 | H88: 721630.35
B89: 45253 | C89: 151631.95 | D89: 3399512.3 | E89: 2745143.6 | F89: 1030364.2 | G89: 0.58096154 | H89: 660148.61
B90: 45283 | C90: 584784.29 | D90: 3318570 | E90: 2708165.3 | F90: 1062589.9 | G90: 0.54903846 | H90: 617741.94
... B93: 45374 | C93: -697563.51 | D93: 5460271 | E93: 3025187.9 | F93: 1216485 | G93: 0.60397436 | H93: 629309.68
B98: Year | C98: Month | D98: Week | E98: Utilization | F98: Monthly utilization | G98: SN Eng HC | H98: Hours / Month | I98: Rev at $290/hr
B99: 2023 | C99: Jan | D99: 1 | E99: 94 | F99: =average(E99:E102) -> 95.75 | G99: 24 | H99: 176 | I99: =(G99*H99)*290*(F99/100) -> 1172899.2
D100: 2 | E100: 93
D101: 3 | E101: 108
D102: 4 | E102: 88
C103: Feb | D103: 5 | E103: 94 | F103: =average(E103:E107) -> 82 | G103: 25 | H103: 160 | I103: =(G103*H103)*290*(F103/100) -> 951200
D104: 6 | E104: 90
D105: 7 | E105: 84
D106: 8 | E106: 72
D107: 9 | E107: 70
C108: Mar | D108: 10 | E108: 80 | F108: =average(E108:E111) -> 63 | G108: 24 | H108: 184 | I108: =(G108*H108)*290*(F108/100) -> 806803.2
D109: 11 | E109: 88
D110: 12 | E110: 9
D111: 13 | E111: 75
C112: Apr | D112: 14 | E112: 81 | F112: =average(E112:E115) -> 86 | G112: 22 | H112: 160 | I112: =(G112*H112)*290*(F112/100) -> 877888
D113: 15 | E113: 73
D114: 16 | E114: 85
D115: 17 | E115: 105
C116: May | D116: 18 | E116: 95 | F116: =average(E116:E119) -> 92.25 | G116: 22 | H116: 184 | I116: =(G116*H116)*290*(F116/100) -> 1082941.2
D117: 19 | E117: 105
D118: 20 | E118: 71
D119: 21 | E119: 98
C120: Jun | D120: 22 | E120: 96 | F120: =average(E120:E123) -> 91.5 | G120: 23 | H120: 176 | I120: =(G120*H120)*290*(F120/100) -> 1074136.8
D121: 23 | E121: 97
D122: 24 | E122: 85
D123: 25 | E123: 88
C124: Jul | D124: 26 | E124: 86 | F124: =average(E124:E128) -> 75.2 | G124: 24 | H124: 168 | I124: =(G124*H124)*290*(F124/100) -> 879298.56
D125: 27 | E125: 71
D126: 28 | E126: 88
D127: 29 | E127: 45
D128: 30 | E128: 86
C129: Aug | D129: 31 | E129: 80 | F129: =average(E129:E132) -> 74.75 | G129: 25 | H129: 184 | I129: =(G129*H129)*290*(F129/100) -> 997165
D130: 32 | E130: 70
D131: 33 | E131: 75
...

Sheet Copy of GAAP Analysis
C2: 2020 | O2: 2021 | AA2: 2022 | AM2: 2023 | CZ2: TTM As Of:
C3: 43831 | D3: 43862 | E3: 43891 | F3: 43922 | G3: 43952 | H3: 43983 | I3: 44013 | J3: 44044 | K3: 44075 | L3: 44105 | M3: 44136 | N3: 44166 | O3: 44197 | P3: 44228 | Q3: 44256 | R3: 44287 | S3: 44317 | T3: 44348 | U3: 44378 | V3: 44409 | W3: 44440 | X3: 44470 | Y3: 44501 | Z3: 44531 | AA3: 44562 | AB3: 44593 | AC3: 44621 | AD3: 44652 | AE3: 44682 | AF3: 44713 | AG3: 44743 | AH3: 44774 | AI3: 44805 | AJ3: 44835 | AK3: 44866 | AL3: 44896 | AM3: 44927 | AN3: 44958 | AO3: 44986 | AP3: 45017 | AQ3: 45047 | AR3: 45078 | AS3: 45108 | AT3: 45139 | AU3: 45170 | AV3: 45200 | AW3: 45231 | AX3: 45261 | AY3: 45292 | AZ3: 45323 | BA3: 45352 | BB3: 45383 | BC3: 45413 | BD3: 45444 | BE3: 45474 | BF3: 45505 | BG3: 45536 | BH3: 45566 | BI3: 45597 | BJ3: 45627 | BK3: 45658 | BL3: 45689 | BM3: 45717 | BN3: 45748 | BO3: 45778 | BP3: 45809 | BQ3: 45839 | BR3: 45870 | BS3: 45901 | BT3: 45931 | BU3: 45962 | BV3: 45992 | BX3: ="TTM as of "&TEXT('GAAP Summary'!B2,"MMM 'YY") -> TTM as of Jun '26 | BZ3: 1Q25 | CA3: 2Q25 | CB3: 3Q25 | CC3: 4Q25 | CD3: FY25 | CF3: 1Q24 | CG3: 2Q24 | CH3: 3Q24 | CI3: 4Q24 | CJ3: FY24 | CL3: 1Q23 | CM3: 2Q23 | CN3: 3Q23 | CO3: 4Q23 | CP3: FY23 | CR3: 1Q22 | CS3: 2Q22 | CT3: 3Q22 | CU3: 4Q22 | CV3: FY22 | CX3: FY21 | CZ3: 44197 | DA3: 44228 | DB3: 44256 | DC3: 44287 | DD3: 44317 | DE3: 44348 | DF3: 44378 | DG3: 44409 | DH3: 44440 | DI3: 44470 | DJ3: 44501 | DK3: 44531 | DL3: 44562 | DM3: 44593 | DN3: 44621 | DO3: 44652 | DP3: 44682 | DQ3: 44713 | DR3: 44743 | DS3: 44774 | DT3: 44805 | DU3: 44835 | DV3: 44866 | DW3: 44896 | DX3: 44927 | DY3: 44958 | DZ3: 44986 | EA3: 45017 | EB3: 45047 | EC3: 45078 | ED3: 45108 | EE3: 45139 | EF3: 45170 | EG3: 45200 | EH3: 45231 | EI3: 45261 | EJ3: 45292 | EK3: 45323 | EL3: 45352 | EM3: 45383 | EN3: 45413 | EO3: 45444 | EP3: 45474 | EQ3: 45505 | ER3: 45536 | ES3: 45566 | ET3: 45597 | EU3: 45627 | EV3: 45658 | EW3: 45689 | EX3: 45717 | EY3: 45748 | EZ3: 45778 | FA3: 45809 | FB3: 45839 | FC3: 45870 | FD3: 45901 | FE3: 45931 | FF3: 45962 | FG3: 45992
AA6: =AA18/AA117 -> 48950.875 | AB6: =AB18/AB117 -> 37808.643 | AC6: =AC18/AC117 -> 44602.419 | AD6: =AD18/AD117 -> 35214.765 | AE6: =AE18/AE117 -> 36490.057 | AF6: =AF18/AF117 -> 42772.944 | AG6: =AG18/AG117 -> 34012.256 | AH6: =AH18/AH117 -> 47156.39 | ... BR6: =BR18/BR117 -> 36438.125
AA7: =AA18/sum(AA116:AA117) -> 29370.525 | AB7: =AB18/sum(AB116:AB117) -> 23525.378 | AC7: =AC18/sum(AC116:AC117) -> 28217.857 | AD7: =AD18/sum(AD116:AD117) -> 23476.51 | AE7: =AE18/sum(AE116:AE117) -> 24560.615 | AF7: =AF18/sum(AF116:AF117) -> 27996.836 | AG7: =AG18/sum(AG116:AG117) -> 22870.31 | AH7: =AH18/sum(AH116:AH117) -> 31184.065 | ... BR7: =BR18/sum(BR116:BR117) -> 23595.179
BZ8: =BZ18/sum(BZ116,BZ117) -> 69164.078 | CA8: =CA18/sum(CA116,CA117) -> 69921.03 | CB8: =CB18/sum(CB116,CB117) -> 73362.555 | CF8: =CF18/sum(CF116,CF117) -> 61388.296 | CG8: =CG18/sum(CG116,CG117) -> 65103.29 | CH8: =CH18/sum(CH116,CH117) -> 66108.386 | CI8: =CI18/sum(CI116,CI117) -> 74787.883 | CJ8: =CJ18/sum(CJ116,CJ117) -> 245370.42 | CL8: =CL18/sum(CL116,CL117) -> 82576.546 | CM8: =CM18/sum(CM116,CM117) -> 71622.397 | CN8: =CN18/sum(CN116,CN117) -> 60923.332 | CO8: =CO18/sum(CO116,CO117) -> 56203.114 | CP8: =CP18/sum(CP116,CP117) -> 244681.21 | CR8: =CR18/sum(CR116,CR117) -> 80958.313 | CS8: =CS18/sum(CS116,CS117) -> 76220.506 | CT8: =CT18/sum(CT116,CT117) -> 79242.519 | CU8: =CU18/sum(CU116,CU117) -> 72200.424 | CV8: =CV18/sum(CV116,CV117) -> 257181.31
B10: Actuals
CL11: =CL13/$CP$13 -> 0.13149257 | CM11: =CM13/$CP$13 -> 0.20964966 | CN11: =CN13/$CP$13 -> 0.15600883 | CO11: =CO13/$CP$13 -> 0.50284893
B12: Bookings | C12: =sum(C13:C16) -> 0 | D12: =sum(D13:D16) -> 0 | E12: =sum(E13:E16) -> 0 | F12: =sum(F13:F16) -> 0 | G12: =sum(G13:G16) -> 0 | H12: =sum(H13:H16) -> 0 | I12: =sum(I13:I16) -> 0 | J12: =sum(J13:J16) -> 0 | ... BV12: =sum(BV13:BV16) -> 0 | BX12: {=SUM(INDIRECT(XLOOKUP('GAAP Summary'!$B$2,'TTM Dates'!$B:$B,'TTM Dates'!$E:$E)&ROW($BW12)&":"&XLOOKUP('GAAP Summary'!$B$2,'TTM Dates'!$B:$B,'TTM Dates'!$C:$C)&ROW($BW12)))} -> #REF! | BZ12: =sum(BK12:BM12) -> 8394063.9 | CA12: =sum(BN12:BP12) -> 12379014 | CB12: =sum(BQ12:BS12) -> 7517072 | CC12: =sum(BT12:BV12) -> 0 | CD12: =sum(BK12:BV12) -> 28290149 | CF12: =sum(AY12:BA12) -> 5881823 | CG12: =sum(BB12:BD12) -> 6544902 | CH12: =sum(BE12:BG12) -> 6201507 | CI12: =sum(BH12:BJ12) -> 9536879.1 | CJ12: =sum(AY12:BJ12) -> 28165111 | CL12: =sum(AM12:AO12) -> 2808888 | CM12: =sum(AP12:AR12) -> 3780640.8 | CN12: =sum(AS12:AU12) -> 4345506 | CO12: =sum(AV12:AX12) -> 8144285.3 | CP12: =sum(CL13:CO15) -> 19079320 | CR12: =sum(AA12:AC12) -> 3491390 | CS12: =sum(AD12:AF12) -> 7507668 | CT12: =sum(AG12:AI12) -> 5709804.4 | CU12: =sum(AJ12:AL12) -> 7894608.2 | CV12: =sum(AA12:AL12) -> 24603471 | CX12: =sum(O12:Z12) -> 0 | CZ12: {=IF(CZ$3>'GAAP Summary'!$B$2,0,SUM(INDIRECT(XLOOKUP(CZ$3,'TTM Dates'!$B:$B,'TTM Dates'!$E:$E)&ROW($BW12)&":"&XLOOKUP(CZ$3,'TTM Dates'!$B:$B,'TTM Dates'!$C:$C)&ROW($BW12))))} -> 0 | DA12: {=IF(DA$3>'GAAP Summary'!$B$2,0,SUM(INDIRECT(XLOOKUP(DA$3,'TTM Dates'!$B:$B,'TTM Dates'!$E:$E)&ROW($BW12)&":"&XLOOKUP(DA$3,'TTM Dates'!$B:$B,'TTM Dates'!$C:$C)&ROW($BW12))))} -> 0 | DB12: {=IF(DB$3>'GAAP Summary'!$B$2,0,SUM(INDIRECT(XLOOKUP(DB$3,'TTM Dates'!$B:$B,'TTM Dates'!$E:$E)&ROW($BW12)&":"&XLOOKUP(DB$3,'TTM Dates'!$B:$B,'TTM Dates'!$C:$C)&ROW($BW12))))} -> 0 | DC12: {=IF(DC$3>'GAAP Summary'!$B$2,0,SUM(INDIRECT(XLOOKUP(DC$3,'TTM Dates'!$B:$B,'TTM Dates'!$E:$E)&ROW($BW12)&":"&XLOOKUP(DC$3,'TTM Dates'!$B:$B,'TTM Dates'!$C:$C)&ROW($BW12))))} -> 0 | DD12: {=IF(DD$3>'GAAP Summary'!$B$2,0,SUM(INDIRECT(XLOOKUP(DD$3,'TTM Dates'!$B:$B,'TTM Dates'!$E:$E)&ROW($BW12)&":"&XLOOKUP(DD$3,'TTM Dates'!$B:$B,'TTM Dates'!$C:$C)&ROW($BW12))))} -> 0 | DE12: {=IF(DE$3>'GAAP Summary'!$B$2,0,SUM(INDIRECT(XLOOKUP(DE$3,'TTM Dates'!$B:$B,'TTM Dates'!$E:$E)&ROW($BW12)&":"&XLOOKUP(DE$3,'TTM Dates'!$B:$B,'TTM Dates'!$C:$C)&ROW($BW12))))} -> 0 | DF12: {=IF(DF$3>'GAAP Summary'!$B$2,0,SUM(INDIRECT(XLOOKUP(DF$3,'TTM Dates'!$B:$B,'TTM Dates'!$E:$E)&ROW($BW12)&":"&XLOOKUP(DF$3,'TTM Dates'!$B:$B,'TTM Dates'!$C:$C)&ROW($BW12))))} -> 0 | DG12: {=IF(DG$3>'GAAP Summary'!$B$2,0,SUM(INDIRECT(XLOOKUP(DG$3,'TTM Dates'!$B:$B,'TTM Dates'!$E:$E)&ROW($BW12)&":"&XLOOKUP(DG$3,'TTM Dates'!$B:$B,'TTM Dates'!$C:$C)&ROW($BW12))))} -> 0 | ... FG12: {=IF(FG$3>'GAAP Summary'!$B$2,0,SUM(INDIRECT(XLOOKUP(FG$3,'TTM Dates'!$B:$B,'TTM Dates'!$E:$E)&ROW($BW12)&":"&XLOOKUP(FG$3,'TTM Dates'!$B:$B,'TTM Dates'!$C:$C)&ROW($BW12))))} -> 28290149
B13: DD | AA13: 99720 | AB13: 80640 | AC13: 204640 | AD13: 415440 | AE13: 586400 | AF13: 1074960 | AG13: 1328420 | AH13: 79040 | AI13: 922672 | AJ13: 1649000 | AK13: 427800 | AL13: 813970 | AM13: 134400 | AN13: 349104 | AO13: 801544 | AP13: 331413.01 | AQ13: 732202 | AR13: 985245 | AS13: 111000 | AT13: 1120200 | AU13: 293440 | AV13: =57600+216000+87680+106880+25000+345900 -> 839060 | AW13: 2468100 | AX13: 1607072 | AY13: 0 | AZ13: =60700+34560 -> 95260 | BA13: 664160 | BB13: 245840 | BC13: 1070080 | BD13: 595296 | BE13: 710760 | BF13: 1387561 | BG13: 286700 | BH13: 436906 | BI13: 2447618 | BJ13: 1341556 | BK13: 119460 | BL13: 115760 | BM13: 404780 | BN13: 1148000 | BO13: 433500 | BP13: 1071080 | BQ13: 825056 | BR13: 951820 | BX13: {=SUM(INDIRECT(XLOOKUP('GAAP Summary'!$B$2,'TTM Dates'!$B:$B,'TTM Dates'!$E:$E)&ROW($BW13)&":"&XLOOKUP('GAAP Summary'!$B$2,'TTM Dates'!$B:$B,'TTM Dates'!$C:$C)&ROW($BW13)))} -> #REF! | BZ13: =sum(BK13:BM13) -> 640000 | CA13: =sum(BN13:BP13) -> 2652580 | CB13: =sum(BQ13:BS13) -> 1776876 | CC13: =sum(BT13:BV13) -> 0 | CD13: =sum(BK13:BV13) -> 5069456 | CF13: =sum(AY13:BA13) -> 759420 | CG13: =sum(BB13:BD13) -> 1911216 | CH13: =sum(BE13:BG13) -> 2385021 | CI13: =sum(BH13:BJ13) -> 4226080 | CJ13: =sum(AY13:BJ13) -> 9281737 | CL13: =sum(AM13:AO13) -> 1285048 | CM13: =sum(AP13:AR13) -> 2048860 | CN13: =sum(AS13:AU13) -> 1524640 | CO13: =sum(AV13:AX13) -> 4914232 | CP13: =sum(AM13:AX13) -> 9772780 | CR13: =sum(AA13:AC13) -> 385000 | CS13: =sum(AD13:AF13) -> 2076800 | CT13: =sum(AG13:AI13) -> 2330132 | CU13: =sum(AJ13:AL13) -> 2890770 | CV13: =sum(AA13:AL13) -> 7682702 | CX13: =SUM(O13:Z13) -> 0 | CZ13: {=IF(CZ$3>'GAAP Summary'!$B$2,0,SUM(INDIRECT(XLOOKUP(CZ$3,'TTM Dates'!$B:$B,'TTM Dates'!$E:$E)&ROW($BW13)&":"&XLOOKUP(CZ$3,'TTM Dates'!$B:$B,'TTM Dates'!$C:$C)&ROW($BW13))))} -> 0 | DA13: {=IF(DA$3>'GAAP Summary'!$B$2,0,SUM(INDIRECT(XLOOKUP(DA$3,'TTM Dates'!$B:$B,'TTM Dates'!$E:$E)&ROW($BW13)&":"&XLOOKUP(DA$3,'TTM Dates'!$B:$B,'TTM Dates'!$C:$C)&ROW($BW13))))} -> 0 | DB13: {=IF(DB$3>'GAAP Summary'!$B$2,0,SUM(INDIRECT(XLOOKUP(DB$3,'TTM Dates'!$B:$B,'TTM Dates'!$E:$E)&ROW($BW13)&":"&XLOOKUP(DB$3,'TTM Dates'!$B:$B,'TTM Dates'!$C:$C)&ROW($BW13))))} -> 0 | DC13: {=IF(DC$3>'GAAP Summary'!$B$2,0,SUM(INDIRECT(XLOOKUP(DC$3,'TTM Dates'!$B:$B,'TTM Dates'!$E:$E)&ROW($BW13)&":"&XLOOKUP(DC$3,'TTM Dates'!$B:$B,'TTM Dates'!$C:$C)&ROW($BW13))))} -> 0 | DD13: {=IF(DD$3>'GAAP Summary'!$B$2,0,SUM(INDIRECT(XLOOKUP(DD$3,'TTM Dates'!$B:$B,'TTM Dates'!$E:$E)&ROW($BW13)&":"&XLOOKUP(DD$3,'TTM Dates'!$B:$B,'TTM Dates'!$C:$C)&ROW($BW13))))} -> 0 | DE13: {=IF(DE$3>'GAAP Summary'!$B$2,0,SUM(INDIRECT(XLOOKUP(DE$3,'TTM Dates'!$B:$B,'TTM Dates'!$E:$E)&ROW($BW13)&":"&XLOOKUP(DE$3,'TTM Dates'!$B:$B,'TTM Dates'!$C:$C)&ROW($BW13))))} -> 0 | DF13: {=IF(DF$3>'GAAP Summary'!$B$2,0,SUM(INDIRECT(XLOOKUP(DF$3,'TTM Dates'!$B:$B,'TTM Dates'!$E:$E)&ROW($BW13)&":"&XLOOKUP(DF$3,'TTM Dates'!$B:$B,'TTM Dates'!$C:$C)&ROW($BW13))))} -> 0 | DG13: {=IF(DG$3>'GAAP Summary'!$B$2,0,SUM(INDIRECT(XLOOKUP(DG$3,'TTM Dates'!$B:$B,'TTM Dates'!$E:$E)&ROW($BW13)&":"&XLOOKUP(DG$3,'TTM Dates'!$B:$B,'TTM Dates'!$C:$C)&ROW($BW13))))} -> 0 | ... FG13: {=IF(FG$3>'GAAP Summary'!$B$2,0,SUM(INDIRECT(XLOOKUP(FG$3,'TTM Dates'!$B:$B,'TTM Dates'!$E:$E)&ROW($BW13)&":"&XLOOKUP(FG$3,'TTM Dates'!$B:$B,'TTM Dates'!$C:$C)&ROW($BW13))))} -> 5069456
B14: SN | AA14: 45100 | AB14: 34560 | AC14: 2906490 | AD14: 240400 | AE14: 3445490 | AF14: 1705200 | AG14: 1642900 | AH14: 240000 | AI14: 1323460 | AJ14: 977400 | AK14: 459420 | AL14: 3326280 | AM14: 0 | AN14: 245760 | AO14: 1007040 | AP14: 220200 | AQ14: 103200 | AR14: 1237328 | AS14: 796400 | AT14: 968070 | AU14: 929178 | AV14: =249600+81000+40500+20025+103200 -> 494325 | AW14: 874546 | AX14: 1259600 | AY14: 57000 | AZ14: 235790 | BA14: 4709700 | BB14: 1366812 | BC14: 2795784 | BD14: 395700 | BE14: 689600 | BF14: 685920 | BG14: 2020630 | BH14: 2156205.2 | BI14: 479693.52 | BJ14: 2235526.2 | BK14: 919568.5 | BL14: 2372860 | BM14: 3187678 | BN14: 4195676 | BO14: 2326386 | BP14: 2388176.5 | BQ14: 3882712 | BR14: 1782484 | BX14: {=SUM(INDIRECT(XLOOKUP('GAAP Summary'!$B$2,'TTM Dates'!$B:$B,'TTM Dates'!$E:$E)&ROW($BW14)&":"&XLOOKUP('GAAP Summary'!$B$2,'TTM Dates'!$B:$B,'TTM Dates'!$C:$C)&ROW($BW14)))} -> #REF! | BZ14: =sum(BK14:BM14) -> 6480106.5 | CA14: =sum(BN14:BP14) -> 8910238.5 | CB14: =sum(BQ14:BS14) -> 5665196 | CC14: =sum(BT14:BV14) -> 0 | CD14: =sum(BK14:BV14) -> 21055541 | CF14: =sum(AY14:BA14) -> 5002490 | CG14: =sum(BB14:BD14) -> 4558296 | CH14: =sum(BE14:BG14) -> 3396150 | CI14: =sum(BH14:BJ14) -> 4871424.9 | CJ14: =sum(AY14:BJ14) -> 17828361 | CL14: =sum(AM14:AO14) -> 1252800 | CM14: =sum(AP14:AR14) -> 1560728 | CN14: =sum(AS14:AU14) -> 2693648 | CO14: =sum(AV14:AX14) -> 2628471 | CP14: =sum(AM14:AX14) -> 8135647 | CR14: =sum(AA14:AC14) -> 2986150 | CS14: =sum(AD14:AF14) -> 5391090 | CT14: =sum(AG14:AI14) -> 3206360 | CU14: =sum(AJ14:AL14) -> 4763100 | CV14: =sum(AA14:AL14) -> 16346700 | CX14: =SUM(O14:Z14) -> 0 | CZ14: {=IF(CZ$3>'GAAP Summary'!$B$2,0,SUM(INDIRECT(XLOOKUP(CZ$3,'TTM Dates'!$B:$B,'TTM Dates'!$E:$E)&ROW($BW14)&":"&XLOOKUP(CZ$3,'TTM Dates'!$B:$B,'TTM Dates'!$C:$C)&ROW($BW14))))} -> 0 | DA14: {=IF(DA$3>'GAAP Summary'!$B$2,0,SUM(INDIRECT(XLOOKUP(DA$3,'TTM Dates'!$B:$B,'TTM Dates'!$E:$E)&ROW($BW14)&":"&XLOOKUP(DA$3,'TTM Dates'!$B:$B,'TTM Dates'!$C:$C)&ROW($BW14))))} -> 0 | DB14: {=IF(DB$3>'GAAP Summary'!$B$2,0,SUM(INDIRECT(XLOOKUP(DB$3,'TTM Dates'!$B:$B,'TTM Dates'!$E:$E)&ROW($BW14)&":"&XLOOKUP(DB$3,'TTM Dates'!$B:$B,'TTM Dates'!$C:$C)&ROW($BW14))))} -> 0 | DC14: {=IF(DC$3>'GAAP Summary'!$B$2,0,SUM(INDIRECT(XLOOKUP(DC$3,'TTM Dates'!$B:$B,'TTM Dates'!$E:$E)&ROW($BW14)&":"&XLOOKUP(DC$3,'TTM Dates'!$B:$B,'TTM Dates'!$C:$C)&ROW($BW14))))} -> 0 | DD14: {=IF(DD$3>'GAAP Summary'!$B$2,0,SUM(INDIRECT(XLOOKUP(DD$3,'TTM Dates'!$B:$B,'TTM Dates'!$E:$E)&ROW($BW14)&":"&XLOOKUP(DD$3,'TTM Dates'!$B:$B,'TTM Dates'!$C:$C)&ROW($BW14))))} -> 0 | DE14: {=IF(DE$3>'GAAP Summary'!$B$2,0,SUM(INDIRECT(XLOOKUP(DE$3,'TTM Dates'!$B:$B,'TTM Dates'!$E:$E)&ROW($BW14)&":"&XLOOKUP(DE$3,'TTM Dates'!$B:$B,'TTM Dates'!$C:$C)&ROW($BW14))))} -> 0 | DF14: {=IF(DF$3>'GAAP Summary'!$B$2,0,SUM(INDIRECT(XLOOKUP(DF$3,'TTM Dates'!$B:$B,'TTM Dates'!$E:$E)&ROW($BW14)&":"&XLOOKUP(DF$3,'TTM Dates'!$B:$B,'TTM Dates'!$C:$C)&ROW($BW14))))} -> 0 | DG14: {=IF(DG$3>'GAAP Summary'!$B$2,0,SUM(INDIRECT(XLOOKUP(DG$3,'TTM Dates'!$B:$B,'TTM Dates'!$E:$E)&ROW($BW14)&":"&XLOOKUP(DG$3,'TTM Dates'!$B:$B,'TTM Dates'!$C:$C)&ROW($BW14))))} -> 0 | ... FG14: {=IF(FG$3>'GAAP Summary'!$B$2,0,SUM(INDIRECT(XLOOKUP(FG$3,'TTM Dates'!$B:$B,'TTM Dates'!$E:$E)&ROW($BW14)&":"&XLOOKUP(FG$3,'TTM Dates'!$B:$B,'TTM Dates'!$C:$C)&ROW($BW14))))} -> 21055541
B15: SW | AA15: 0 | AB15: 120240 | AC15: 0 | AD15: 9120 | AE15: 11375 | AF15: 19283 | AG15: 164022 | AH15: 7980 | AI15: 1310.4 | AJ15: 14208 | AK15: 104678.8 | AL15: 121851.36 | AM15: 0 | AN15: 252000 | AO15: 19040 | AP15: 1310.4 | AQ15: 22188 | AR15: 147554.4 | AS15: 108510 | AT15: 14208 | AU15: 4500 | AV15: 92818 | AW15: 56866.32 | AX15: 451898 | AY15: 0 | AZ15: 52800 | BA15: 67113 | BC15: 1890 | BD15: 73500 | BE15: 5860 | BF15: 47660 | BH15: 3931.2 | BI15: 84511.25 | BJ15: 229832.7 | BK15: 92097.6 | BL15: 0 | BN15: 11088 | BP15: 73500 | BQ15: 0 | BX15: {=SUM(INDIRECT(XLOOKUP('GAAP Summary'!$B$2,'TTM Dates'!$B:$B,'TTM Dates'!$E:$E)&ROW($BW15)&":"&XLOOKUP('GAAP Summary'!$B$2,'TTM Dates'!$B:$B,'TTM Dates'!$C:$C)&ROW($BW15)))} -> #REF! | BZ15: =sum(BK15:BM15) -> 92097.6 | CA15: =sum(BN15:BP15) -> 84588 | CB15: =sum(BQ15:BS15) -> 0 | CC15: =sum(BT15:BV15) -> 0 | CD15: =sum(BK15:BV15) -> 176685.6 | CF15: =sum(AY15:BA15) -> 119913 | CG15: =sum(BB15:BD15) -> 75390 | CH15: =sum(BE15:BG15) -> 53520 | CI15: =sum(BH15:BJ15) -> 318275.15 | CJ15: =sum(AY15:BJ15) -> 567098.15 | CL15: =sum(AM15:AO15) -> 271040 | CM15: =sum(AP15:AR15) -> 171052.8 | CN15: =sum(AS15:AU15) -> 127218 | CO15: =sum(AV15:AX15) -> 601582.32 | CP15: =sum(AM15:AX15) -> 1170893.1 | CR15: =sum(AA15:AC15) -> 120240 | CS15: =sum(AD15:AF15) -> 39778 | CT15: =sum(AG15:AI15) -> 173312.4 | CU15: =sum(AJ15:AL15) -> 240738.16 | CV15: =sum(AA15:AL15) -> 574068.56 | CZ15: {=IF(CZ$3>'GAAP Summary'!$B$2,0,SUM(INDIRECT(XLOOKUP(CZ$3,'TTM Dates'!$B:$B,'TTM Dates'!$E:$E)&ROW($BW15)&":"&XLOOKUP(CZ$3,'TTM Dates'!$B:$B,'TTM Dates'!$C:$C)&ROW($BW15))))} -> 0 | DA15: {=IF(DA$3>'GAAP Summary'!$B$2,0,SUM(INDIRECT(XLOOKUP(DA$3,'TTM Dates'!$B:$B,'TTM Dates'!$E:$E)&ROW($BW15)&":"&XLOOKUP(DA$3,'TTM Dates'!$B:$B,'TTM Dates'!$C:$C)&ROW($BW15))))} -> 0 | DB15: {=IF(DB$3>'GAAP Summary'!$B$2,0,SUM(INDIRECT(XLOOKUP(DB$3,'TTM Dates'!$B:$B,'TTM Dates'!$E:$E)&ROW($BW15)&":"&XLOOKUP(DB$3,'TTM Dates'!$B:$B,'TTM Dates'!$C:$C)&ROW($BW15))))} -> 0 | DC15: {=IF(DC$3>'GAAP Summary'!$B$2,0,SUM(INDIRECT(XLOOKUP(DC$3,'TTM Dates'!$B:$B,'TTM Dates'!$E:$E)&ROW($BW15)&":"&XLOOKUP(DC$3,'TTM Dates'!$B:$B,'TTM Dates'!$C:$C)&ROW($BW15))))} -> 0 | DD15: {=IF(DD$3>'GAAP Summary'!$B$2,0,SUM(INDIRECT(XLOOKUP(DD$3,'TTM Dates'!$B:$B,'TTM Dates'!$E:$E)&ROW($BW15)&":"&XLOOKUP(DD$3,'TTM Dates'!$B:$B,'TTM Dates'!$C:$C)&ROW($BW15))))} -> 0 | DE15: {=IF(DE$3>'GAAP Summary'!$B$2,0,SUM(INDIRECT(XLOOKUP(DE$3,'TTM Dates'!$B:$B,'TTM Dates'!$E:$E)&ROW($BW15)&":"&XLOOKUP(DE$3,'TTM Dates'!$B:$B,'TTM Dates'!$C:$C)&ROW($BW15))))} -> 0 | DF15: {=IF(DF$3>'GAAP Summary'!$B$2,0,SUM(INDIRECT(XLOOKUP(DF$3,'TTM Dates'!$B:$B,'TTM Dates'!$E:$E)&ROW($BW15)&":"&XLOOKUP(DF$3,'TTM Dates'!$B:$B,'TTM Dates'!$C:$C)&ROW($BW15))))} -> 0 | DG15: {=IF(DG$3>'GAAP Summary'!$B$2,0,SUM(INDIRECT(XLOOKUP(DG$3,'TTM Dates'!$B:$B,'TTM Dates'!$E:$E)&ROW($BW15)&":"&XLOOKUP(DG$3,'TTM Dates'!$B:$B,'TTM Dates'!$C:$C)&ROW($BW15))))} -> 0 | ... FG15: {=IF(FG$3>'GAAP Summary'!$B$2,0,SUM(INDIRECT(XLOOKUP(FG$3,'TTM Dates'!$B:$B,'TTM Dates'!$E:$E)&ROW($BW15)&":"&XLOOKUP(FG$3,'TTM Dates'!$B:$B,'TTM Dates'!$C:$C)&ROW($BW15))))} -> 176685.6
B16: MSP | BF16: 366816 | BH16: 21117 | BI16: 79982 | BJ16: 20000 | BL16: 900000 | BM16: 281859.85 | BN16: 303607 | BO16: 180000 | BP16: 248000 | BQ16: 0 | BR16: 75000 | BZ16: =sum(BK16:BM16) -> 1181859.9 | CA16: =sum(BN16:BP16) -> 731607 | CB16: =sum(BQ16:BS16) -> 75000 | CC16: =sum(BT16:BV16) -> 0 | CD16: =sum(BK16:BV16) -> 1988466.9 | CF16: =sum(AY16:BA16) -> 0 | CG16: =sum(BB16:BD16) -> 0 | CH16: =sum(BE16:BG16) -> 366816 | CI16: =sum(BH16:BJ16) -> 121099 | CJ16: =sum(AY16:BJ16) -> 487915 | CR16: =sum(AA16:AC16) -> 0 | CS16: =sum(AD16:AF16) -> 0 | CT16: =sum(AG16:AI16) -> 0 | CU16: =sum(AJ16:AL16) -> 0 | CV16: =sum(AA16:AL16) -> 0 | DL16: {=IF(DL$3>'GAAP Summary'!$B$2,0,SUM(INDIRECT(XLOOKUP(DL$3,'TTM Dates'!$B:$B,'TTM Dates'!$E:$E)&ROW($BW16)&":"&XLOOKUP(DL$3,'TTM Dates'!$B:$B,'TTM Dates'!$C:$C)&ROW($BW16))))} -> 0 | DM16: {=IF(DM$3>'GAAP Summary'!$B$2,0,SUM(INDIRECT(XLOOKUP(DM$3,'TTM Dates'!$B:$B,'TTM Dates'!$E:$E)&ROW($BW16)&":"&XLOOKUP(DM$3,'TTM Dates'!$B:$B,'TTM Dates'!$C:$C)&ROW($BW16))))} -> 0 | DN16: {=IF(DN$3>'GAAP Summary'!$B$2,0,SUM(INDIRECT(XLOOKUP(DN$3,'TTM Dates'!$B:$B,'TTM Dates'!$E:$E)&ROW($BW16)&":"&XLOOKUP(DN$3,'TTM Dates'!$B:$B,'TTM Dates'!$C:$C)&ROW($BW16))))} -> 0 | DO16: {=IF(DO$3>'GAAP Summary'!$B$2,0,SUM(INDIRECT(XLOOKUP(DO$3,'TTM Dates'!$B:$B,'TTM Dates'!$E:$E)&ROW($BW16)&":"&XLOOKUP(DO$3,'TTM Dates'!$B:$B,'TTM Dates'!$C:$C)&ROW($BW16))))} -> 0 | DP16: {=IF(DP$3>'GAAP Summary'!$B$2,0,SUM(INDIRECT(XLOOKUP(DP$3,'TTM Dates'!$B:$B,'TTM Dates'!$E:$E)&ROW($BW16)&":"&XLOOKUP(DP$3,'TTM Dates'!$B:$B,'TTM Dates'!$C:$C)&ROW($BW16))))} -> 0 | DQ16: {=IF(DQ$3>'GAAP Summary'!$B$2,0,SUM(INDIRECT(XLOOKUP(DQ$3,'TTM Dates'!$B:$B,'TTM Dates'!$E:$E)&ROW($BW16)&":"&XLOOKUP(DQ$3,'TTM Dates'!$B:$B,'TTM Dates'!$C:$C)&ROW($BW16))))} -> 0 | DR16: {=IF(DR$3>'GAAP Summary'!$B$2,0,SUM(INDIRECT(XLOOKUP(DR$3,'TTM Dates'!$B:$B,'TTM Dates'!$E:$E)&ROW($BW16)&":"&XLOOKUP(DR$3,'TTM Dates'!$B:$B,'TTM Dates'!$C:$C)&ROW($BW16))))} -> 0 | DS16: {=IF(DS$3>'GAAP Summary'!$B$2,0,SUM(INDIRECT(XLOOKUP(DS$3,'TTM Dates'!$B:$B,'TTM Dates'!$E:$E)&ROW($BW16)&":"&XLOOKUP(DS$3,'TTM Dates'!$B:$B,'TTM Dates'!$C:$C)&ROW($BW16))))} -> 0 | ... FG16: {=IF(FG$3>'GAAP Summary'!$B$2,0,SUM(INDIRECT(XLOOKUP(FG$3,'TTM Dates'!$B:$B,'TTM Dates'!$E:$E)&ROW($BW16)&":"&XLOOKUP(FG$3,'TTM Dates'!$B:$B,'TTM Dates'!$C:$C)&ROW($BW16))))} -> 1988466.9
CM17: =CM18*1.25 -> 6983183.8 | CN17: =CN18*1.35 -> 7018367.8 | CO17: =CO18*1.25 -> 6369686.2
B18: Revenue | C18: =C19+C24 -> 0 | D18: =D19+D24 -> 0 | E18: =E19+E24 -> 0 | F18: =F19+F24 -> 0 | G18: =G19+G24 -> 0 | H18: =H19+H24 -> 0 | I18: =I19+I24 -> 0 | J18: =J19+J24 -> 0 | ... Z18: =Z19+Z24 -> 0 | AA18: 1174821 | AB18: 1058642 | AC18: 1382675 | AD18: 1197302 | AE18: 1277152 | AF18: 1539826 | AG18: 1326478 | AH18: 1933412 | AI18: 1626732 | AJ18: 1863172 | AK18: 1785275 | AL18: 1237115 | AM18: 2132202 | AN18: 1943840 | AO18: 2227301 | AP18: 1844526 | AQ18: 1900795 | AR18: 1841226 | AS18: 1634207 | AT18: 1985443 | AU18: 1579141 | AV18: 1868299 | AW18: 1657348 | AX18: 1570102 | AY18: =AY19+AY24 -> 1682341.9 | AZ18: =AZ19+AZ24 -> 1868928.9 | BA18: =BA19+BA24 -> 1912287.5 | BB18: =BB19+BB24 -> 2003722.6 | BC18: =BC19+BC24 -> 1916051.2 | BD18: =BD19+BD24 -> 1831016.7 | BE18: =BE19+BE24 -> 2080921.4 | BF18: =BF19+BF24 -> 2167206.4 | ... BV18: =BV19+BV24 -> 0 | BX18: {=SUM(INDIRECT(XLOOKUP('GAAP Summary'!$B$2,'TTM Dates'!$B:$B,'TTM Dates'!$E:$E)&ROW($BW18)&":"&XLOOKUP('GAAP Summary'!$B$2,'TTM Dates'!$B:$B,'TTM Dates'!$C:$C)&ROW($BW18)))} -> #REF! | BZ18: =sum(BK18:BM18) -> 7423611 | CA18: =sum(BN18:BP18) -> 7947690.5 | CB18: =sum(BQ18:BS18) -> 5942366.9 | CC18: =sum(BT18:BV18) -> 0 | CD18: =sum(BK18:BV18) -> 21313668 | CF18: =sum(AY18:BA18) -> 5463558.3 | CG18: =sum(BB18:BD18) -> 5750790.6 | CH18: =sum(BE18:BG18) -> 6412513.4 | CI18: =sum(BH18:BJ18) -> 7728081.2 | CJ18: =sum(AY18:BJ18) -> 25354944 | CL18: =sum(AM18:AO18) -> 6303343 | CM18: =sum(AP18:AR18) -> 5586547 | CN18: =sum(AS18:AU18) -> 5198791 | CO18: =sum(AV18:AX18) -> 5095749 | CP18: =sum(AM18:AX18) -> 22184430 | CR18: =sum(AA18:AC18) -> 3616138 | CS18: =sum(AD18:AF18) -> 4014280 | CT18: =sum(AG18:AI18) -> 4886622 | CU18: =sum(AJ18:AL18) -> 4885562 | CV18: =sum(AA18:AL18) -> 17402602 | CX18: =SUM(O18:Z18) -> 0 | CZ18: {=IF(CZ$3>'GAAP Summary'!$B$2,0,SUM(INDIRECT(XLOOKUP(CZ$3,'TTM Dates'!$B:$B,'TTM Dates'!$E:$E)&ROW($BW18)&":"&XLOOKUP(CZ$3,'TTM Dates'!$B:$B,'TTM Dates'!$C:$C)&ROW($BW18))))} -> 0 | DA18: {=IF(DA$3>'GAAP Summary'!$B$2,0,SUM(INDIRECT(XLOOKUP(DA$3,'TTM Dates'!$B:$B,'TTM Dates'!$E:$E)&ROW($BW18)&":"&XLOOKUP(DA$3,'TTM Dates'!$B:$B,'TTM Dates'!$C:$C)&ROW($BW18))))} -> 0 | DB18: {=IF(DB$3>'GAAP Summary'!$B$2,0,SUM(INDIRECT(XLOOKUP(DB$3,'TTM Dates'!$B:$B,'TTM Dates'!$E:$E)&ROW($BW18)&":"&XLOOKUP(DB$3,'TTM Dates'!$B:$B,'TTM Dates'!$C:$C)&ROW($BW18))))} -> 0 | DC18: {=IF(DC$3>'GAAP Summary'!$B$2,0,SUM(INDIRECT(XLOOKUP(DC$3,'TTM Dates'!$B:$B,'TTM Dates'!$E:$E)&ROW($BW18)&":"&XLOOKUP(DC$3,'TTM Dates'!$B:$B,'TTM Dates'!$C:$C)&ROW($BW18))))} -> 0 | DD18: {=IF(DD$3>'GAAP Summary'!$B$2,0,SUM(INDIRECT(XLOOKUP(DD$3,'TTM Dates'!$B:$B,'TTM Dates'!$E:$E)&ROW($BW18)&":"&XLOOKUP(DD$3,'TTM Dates'!$B:$B,'TTM Dates'!$C:$C)&ROW($BW18))))} -> 0 | DE18: {=IF(DE$3>'GAAP Summary'!$B$2,0,SUM(INDIRECT(XLOOKUP(DE$3,'TTM Dates'!$B:$B,'TTM Dates'!$E:$E)&ROW($BW18)&":"&XLOOKUP(DE$3,'TTM Dates'!$B:$B,'TTM Dates'!$C:$C)&ROW($BW18))))} -> 0 | DF18: {=IF(DF$3>'GAAP Summary'!$B$2,0,SUM(INDIRECT(XLOOKUP(DF$3,'TTM Dates'!$B:$B,'TTM Dates'!$E:$E)&ROW($BW18)&":"&XLOOKUP(DF$3,'TTM Dates'!$B:$B,'TTM Dates'!$C:$C)&ROW($BW18))))} -> 0 | DG18: {=IF(DG$3>'GAAP Summary'!$B$2,0,SUM(INDIRECT(XLOOKUP(DG$3,'TTM Dates'!$B:$B,'TTM Dates'!$E:$E)&ROW($BW18)&":"&XLOOKUP(DG$3,'TTM Dates'!$B:$B,'TTM Dates'!$C:$C)&ROW($BW18))))} -> 0 | ... FG18: {=IF(FG$3>'GAAP Summary'!$B$2,0,SUM(INDIRECT(XLOOKUP(FG$3,'TTM Dates'!$B:$B,'TTM Dates'!$E:$E)&ROW($BW18)&":"&XLOOKUP(FG$3,'TTM Dates'!$B:$B,'TTM Dates'!$C:$C)&ROW($BW18))))} -> 21313668
B19: DD | C19: =SUM(C20:C22) -> 0 | D19: =SUM(D20:D22) -> 0 | E19: =SUM(E20:E22) -> 0 | F19: =SUM(F20:F22) -> 0 | G19: =SUM(G20:G22) -> 0 | H19: =SUM(H20:H22) -> 0 | I19: =SUM(I20:I22) -> 0 | J19: =SUM(J20:J22) -> 0 | ... BV19: =SUM(BV20:BV22) -> 0 | BX19: {=SUM(INDIRECT(XLOOKUP('GAAP Summary'!$B$2,'TTM Dates'!$B:$B,'TTM Dates'!$E:$E)&ROW($BW19)&":"&XLOOKUP('GAAP Summary'!$B$2,'TTM Dates'!$B:$B,'TTM Dates'!$C:$C)&ROW($BW19)))} -> #REF! | BZ19: =sum(BK19:BM19) -> 2653528 | CA19: =sum(BN19:BP19) -> 2495275.5 | CB19: =sum(BQ19:BS19) -> 1633993.9 | CC19: =sum(BT19:BV19) -> 0 | CD19: =sum(BK19:BV19) -> 6782797.4 | CF19: =sum(AY19:BA19) -> 3062767 | CG19: =sum(BB19:BD19) -> 2411844.2 | CH19: =sum(BE19:BG19) -> 2484964.8 | CI19: =sum(BH19:BJ19) -> 3157902.1 | CJ19: =sum(AY19:BJ19) -> 11117478 | CL19: =sum(AM19:AO19) -> 0 | CM19: =sum(AP19:AR19) -> 0 | CN19: =sum(AS19:AU19) -> 0 | CO19: =sum(AV19:AX19) -> 0 | CP19: =sum(AM19:AX19) -> 0 | CR19: =sum(AA19:AC19) -> 0 | CS19: =sum(AD19:AF19) -> 0 | CT19: =sum(AG19:AI19) -> 0 | CU19: =sum(AJ19:AL19) -> 0 | CV19: =sum(AA19:AL19) -> 0 | CZ19: {=IF(CZ$3>'GAAP Summary'!$B$2,0,SUM(INDIRECT(XLOOKUP(CZ$3,'TTM Dates'!$B:$B,'TTM Dates'!$E:$E)&ROW($BW19)&":"&XLOOKUP(CZ$3,'TTM Dates'!$B:$B,'TTM Dates'!$C:$C)&ROW($BW19))))} -> 0 | DA19: {=IF(DA$3>'GAAP Summary'!$B$2,0,SUM(INDIRECT(XLOOKUP(DA$3,'TTM Dates'!$B:$B,'TTM Dates'!$E:$E)&ROW($BW19)&":"&XLOOKUP(DA$3,'TTM Dates'!$B:$B,'TTM Dates'!$C:$C)&ROW($BW19))))} -> 0 | DB19: {=IF(DB$3>'GAAP Summary'!$B$2,0,SUM(INDIRECT(XLOOKUP(DB$3,'TTM Dates'!$B:$B,'TTM Dates'!$E:$E)&ROW($BW19)&":"&XLOOKUP(DB$3,'TTM Dates'!$B:$B,'TTM Dates'!$C:$C)&ROW($BW19))))} -> 0 | DC19: {=IF(DC$3>'GAAP Summary'!$B$2,0,SUM(INDIRECT(XLOOKUP(DC$3,'TTM Dates'!$B:$B,'TTM Dates'!$E:$E)&ROW($BW19)&":"&XLOOKUP(DC$3,'TTM Dates'!$B:$B,'TTM Dates'!$C:$C)&ROW($BW19))))} -> 0 | DD19: {=IF(DD$3>'GAAP Summary'!$B$2,0,SUM(INDIRECT(XLOOKUP(DD$3,'TTM Dates'!$B:$B,'TTM Dates'!$E:$E)&ROW($BW19)&":"&XLOOKUP(DD$3,'TTM Dates'!$B:$B,'TTM Dates'!$C:$C)&ROW($BW19))))} -> 0 | DE19: {=IF(DE$3>'GAAP Summary'!$B$2,0,SUM(INDIRECT(XLOOKUP(DE$3,'TTM Dates'!$B:$B,'TTM Dates'!$E:$E)&ROW($BW19)&":"&XLOOKUP(DE$3,'TTM Dates'!$B:$B,'TTM Dates'!$C:$C)&ROW($BW19))))} -> 0 | DF19: {=IF(DF$3>'GAAP Summary'!$B$2,0,SUM(INDIRECT(XLOOKUP(DF$3,'TTM Dates'!$B:$B,'TTM Dates'!$E:$E)&ROW($BW19)&":"&XLOOKUP(DF$3,'TTM Dates'!$B:$B,'TTM Dates'!$C:$C)&ROW($BW19))))} -> 0 | DG19: {=IF(DG$3>'GAAP Summary'!$B$2,0,SUM(INDIRECT(XLOOKUP(DG$3,'TTM Dates'!$B:$B,'TTM Dates'!$E:$E)&ROW($BW19)&":"&XLOOKUP(DG$3,'TTM Dates'!$B:$B,'TTM Dates'!$C:$C)&ROW($BW19))))} -> 0 | ... FG19: {=IF(FG$3>'GAAP Summary'!$B$2,0,SUM(INDIRECT(XLOOKUP(FG$3,'TTM Dates'!$B:$B,'TTM Dates'!$E:$E)&ROW($BW19)&":"&XLOOKUP(FG$3,'TTM Dates'!$B:$B,'TTM Dates'!$C:$C)&ROW($BW19))))} -> 6782797.4
B20: Services | AY20: 830517.09 | AZ20: 966762.28 | BA20: 1023745.7 | BB20: 879742.33 | BC20: 672022.87 | BD20: 621978.96 | BE20: 736704.73 | BF20: 730984.54 | BG20: 781523.54 | BH20: 1033979.3 | BI20: 839033.27 | BJ20: 753392.62 | BK20: 875394 | BL20: 757328 | BM20: 612975 | BN20: 779274 | BO20: 723585 | BP20: 690883 | BQ20: 696347 | BR20: 724050 | BX20: {=SUM(INDIRECT(XLOOKUP('GAAP Summary'!$B$2,'TTM Dates'!$B:$B,'TTM Dates'!$E:$E)&ROW($BW20)&":"&XLOOKUP('GAAP Summary'!$B$2,'TTM Dates'!$B:$B,'TTM Dates'!$C:$C)&ROW($BW20)))} -> #REF! | BZ20: =sum(BK20:BM20) -> 2245697 | CA20: =sum(BN20:BP20) -> 2193742 | CB20: =sum(BQ20:BS20) -> 1420397 | CC20: =sum(BT20:BV20) -> 0 | CD20: =sum(BK20:BV20) -> 5859836 | CF20: =sum(AY20:BA20) -> 2821025 | CG20: =sum(BB20:BD20) -> 2173744.2 | CH20: =sum(BE20:BG20) -> 2249212.8 | CI20: =sum(BH20:BJ20) -> 2626405.1 | CJ20: =sum(AY20:BJ20) -> 9870387.2 | CL20: =sum(AM20:AO20) -> 0 | CM20: =sum(AP20:AR20) -> 0 | CN20: =sum(AS20:AU20) -> 0 | CO20: =sum(AV20:AX20) -> 0 | CP20: =sum(AM20:AX20) -> 0 | CR20: =sum(AA20:AC20) -> 0 | CS20: =sum(AD20:AF20) -> 0 | CT20: =sum(AG20:AI20) -> 0 | CU20: =sum(AJ20:AL20) -> 0 | CV20: =sum(AA20:AL20) -> 0 | CZ20: {=IF(CZ$3>'GAAP Summary'!$B$2,0,SUM(INDIRECT(XLOOKUP(CZ$3,'TTM Dates'!$B:$B,'TTM Dates'!$E:$E)&ROW($BW20)&":"&XLOOKUP(CZ$3,'TTM Dates'!$B:$B,'TTM Dates'!$C:$C)&ROW($BW20))))} -> 0 | DA20: {=IF(DA$3>'GAAP Summary'!$B$2,0,SUM(INDIRECT(XLOOKUP(DA$3,'TTM Dates'!$B:$B,'TTM Dates'!$E:$E)&ROW($BW20)&":"&XLOOKUP(DA$3,'TTM Dates'!$B:$B,'TTM Dates'!$C:$C)&ROW($BW20))))} -> 0 | DB20: {=IF(DB$3>'GAAP Summary'!$B$2,0,SUM(INDIRECT(XLOOKUP(DB$3,'TTM Dates'!$B:$B,'TTM Dates'!$E:$E)&ROW($BW20)&":"&XLOOKUP(DB$3,'TTM Dates'!$B:$B,'TTM Dates'!$C:$C)&ROW($BW20))))} -> 0 | DC20: {=IF(DC$3>'GAAP Summary'!$B$2,0,SUM(INDIRECT(XLOOKUP(DC$3,'TTM Dates'!$B:$B,'TTM Dates'!$E:$E)&ROW($BW20)&":"&XLOOKUP(DC$3,'TTM Dates'!$B:$B,'TTM Dates'!$C:$C)&ROW($BW20))))} -> 0 | DD20: {=IF(DD$3>'GAAP Summary'!$B$2,0,SUM(INDIRECT(XLOOKUP(DD$3,'TTM Dates'!$B:$B,'TTM Dates'!$E:$E)&ROW($BW20)&":"&XLOOKUP(DD$3,'TTM Dates'!$B:$B,'TTM Dates'!$C:$C)&ROW($BW20))))} -> 0 | DE20: {=IF(DE$3>'GAAP Summary'!$B$2,0,SUM(INDIRECT(XLOOKUP(DE$3,'TTM Dates'!$B:$B,'TTM Dates'!$E:$E)&ROW($BW20)&":"&XLOOKUP(DE$3,'TTM Dates'!$B:$B,'TTM Dates'!$C:$C)&ROW($BW20))))} -> 0 | DF20: {=IF(DF$3>'GAAP Summary'!$B$2,0,SUM(INDIRECT(XLOOKUP(DF$3,'TTM Dates'!$B:$B,'TTM Dates'!$E:$E)&ROW($BW20)&":"&XLOOKUP(DF$3,'TTM Dates'!$B:$B,'TTM Dates'!$C:$C)&ROW($BW20))))} -> 0 | DG20: {=IF(DG$3>'GAAP Summary'!$B$2,0,SUM(INDIRECT(XLOOKUP(DG$3,'TTM Dates'!$B:$B,'TTM Dates'!$E:$E)&ROW($BW20)&":"&XLOOKUP(DG$3,'TTM Dates'!$B:$B,'TTM Dates'!$C:$C)&ROW($BW20))))} -> 0 | ... FG20: {=IF(FG$3>'GAAP Summary'!$B$2,0,SUM(INDIRECT(XLOOKUP(FG$3,'TTM Dates'!$B:$B,'TTM Dates'!$E:$E)&ROW($BW20)&":"&XLOOKUP(FG$3,'TTM Dates'!$B:$B,'TTM Dates'!$C:$C)&ROW($BW20))))} -> 5859836
