Workbook

Sheet Wkly Cash Flow
B1: Week Number | AC1: 31 | AD1: 32 | AE1: 33 | AF1: 34 | AG1: 35 | AH1: 36 | AI1: 37 | AJ1: 38 | AK1: 39 | AL1: 40 | AM1: 41 | AN1: 42 | AO1: 43 | AP1: 44 | AQ1: 45 | AR1: 46 | AS1: 47 | AT1: 48 | AU1: 49 | AV1: 50 | AW1: 51 | AX1: 52 | AY1: 1 | AZ1: 2 | BA1: 3 | BB1: 4 | BC1: 5 | BD1: 6 | BE1: 7 | BF1: 8 | BG1: 9 | BH1: 10 | BI1: 11 | BJ1: 12 | BK1: 13 | BL1: 14 | BM1: 15 | BN1: 16 | BO1: 17 | BP1: 18 | BQ1: 19 | BR1: 20 | BS1: 21 | BT1: 22 | BU1: 23 | BV1: 24 | BW1: 25 | BX1: 26 | BY1: 27 | BZ1: 28 | CA1: 29 | CB1: 30 | CC1: 31 | CD1: 32 | CE1: 33 | CF1: 34 | CG1: 35 | CH1: 36 | CI1: 37 | CJ1: 38 | CK1: 39 | CL1: 40 | CM1: 41 | CN1: 42 | CO1: 43 | CP1: 44 | CQ1: 45 | CR1: 46 | CS1: 47 | CT1: 48 | CU1: 49 | CV1: 50 | CW1: 51 | CX1: 52 | CY1: 1 | CZ1: 2 | DA1: 3 | DB1: 4 | DC1: 5 | DD1: 6 | DE1: 7 | DF1: 8 | DG1: 9 | DH1: 10 | DI1: 11 | DJ1: 12 | DK1: 13 | DL1: 14 | DM1: 15 | DN1: 16 | DO1: 17 | DP1: 18 | DQ1: 19 | DR1: 20 | DS1: 21 | DT1: 22 | DU1: 23 | DV1: 24 | DW1: 25 | DX1: 26 | DY1: 27 | DZ1: 28 | EA1: 29 | EB1: 30 | EC1: 31 | ED1: 32 | EE1: 33 | EF1: 34 | EG1: 35 | EH1: 36 | EI1: 37 | EJ1: 38 | EK1: 39 | EL1: 40
B2: Week Ending | C2: 45324 | D2: =C2+7 -> 45331 | E2: =D2+7 -> 45338 | F2: =E2+7 -> 45345 | G2: =F2+7 -> 45352 | H2: =G2+7 -> 45359 | I2: =H2+7 -> 45366 | J2: =I2+7 -> 45373 | K2: =J2+7 -> 45380 | ... AC2: =AB2+7 -> 45506 | AD2: 45513 | AE2: 45520 | AF2: 45527 | AG2: 45534 | AH2: 45541 | AI2: 45548 | AJ2: 45555 | AK2: 45562 | AL2: 45569 | AM2: 45576 | AN2: 45583 | AO2: 45590 | AP2: 45597 | AQ2: 45604 | AR2: 45611 | AS2: 45618 | AT2: 45625 | AU2: 45632 | AV2: 45639 | AW2: 45646 | AX2: 45653 | AY2: 45660 | AZ2: 45667 | BA2: 45674 | BB2: 45681 | BC2: 45688 | BD2: 45695 | BE2: 45702 | BF2: 45709 | BG2: 45716 | BH2: 45723 | BI2: 45730 | BJ2: 45737 | BK2: 45744 | BL2: 45751 | BM2: =BL2+7 -> 45758 | BN2: =BM2+7 -> 45765 | BO2: =BN2+7 -> 45772 | BP2: =BO2+7 -> 45779 | BQ2: =BP2+7 -> 45786 | BR2: =BQ2+7 -> 45793 | BS2: =BR2+7 -> 45800 | BT2: =BS2+7 -> 45807 | ... EL2: =EK2+7 -> 46297
B3: Beginning Cash | C3: 2862667.4 | D3: =C23 -> 2288807.5 | E3: =D23 -> 2604552.4 | F3: =E23 -> 1994376.4 | G3: =F23 -> 2251105.2 | H3: =G23 -> 1595981.2 | I3: =H23 -> 1633425.3 | J3: =I23 -> 1364115.8 | K3: =J23 -> 1102620.9 | ... EL3: =EK23 -> 11740408
B5: Cash In
B6: From Signed Contracts | C6: 577355.68 | D6: 350179.33 | E6: 255119 | F6: 291250 | G6: 404489.39 | H6: 133965.47 | I6: 351395 | J6: 36246 | K6: 187600 | L6: 61920 | M6: 93057.55 | N6: 109250.4 | O6: 130293 | P6: 0 | Q6: 0 | R6: 0 | S6: 0 | T6: 1784872.9 | U6: 465002 | V6: 202128 | W6: 127840 | X6: 264560.27 | Y6: 1101416.2 | Z6: 222930 | AA6: 287760.11 | AB6: 146160 | AC6: 413707.8 | AD6: 49781.2 | AE6: 209731 | AF6: 418221.27 | AG6: =551093.51+2700 -> 553793.51 | AH6: 422712.26 | AI6: =298700.38+22650 -> 321350.38 | AJ6: 124679.25 | AK6: =757789+1001215 -> 1759004 | AL6: =-49900+680960.42+9000 -> 640060.42 | AM6: 389310 | AN6: 261855.32 | AO6: 312301.37 | AP6: =600629.64+55646 -> 656275.64 | AQ6: =393367.96+5320 -> 398687.96 | AR6: =269523.08+162648.87 -> 432171.95 | AS6: =696113.8+18065 -> 714178.8 | AT6: =199060.96+42960 -> 242020.96 | AU6: =547827.64+188883.64+49950 -> 786661.28 | AV6: 702792.8 | AW6: =295109+1866.69 -> 296975.69 | AX6: 928667.37 | AY6: =1023665.35+50240 -> 1073905.4 | AZ6: 527136.59 | BA6: =449417.34+626838 -> 1076255.3 | BB6: =547504.69+434093.31 -> 981598 | BC6: =277595.58+235859.82 -> 513455.4 | BD6: =172220.16+361231.6 -> 533451.76 | BE6: =131489.4 -> 131489.4 | BF6: =36975+4560+3120+68511.34+68750 -> 181916.34 | BG6: =178081.6+4082.08 -> 182163.68 | BH6: =34270+128242.38 -> 162512.38 | BI6: =50250+83159.38 -> 133409.38 | BJ6: =373137.5+588710.72 -> 961848.22 | BK6: =490775.48+67320 -> 558095.48 | BL6: =718301.19+193335.81 -> 911637 | BM6: =509848.98+254215 -> 764063.98 | BN6: =175936+141500 -> 317436 | BO6: =132030+1324777 -> 1456807 | BP6: =645986.27+353854.5 -> 999840.77 | BQ6: =561719.65+379593.29 -> 941312.94 | BR6: =559436.75+171130 -> 730566.75 | BS6: =99831.86+249128.58 -> 348960.44 | BT6: =48237.5+33134+19200 -> 100571.5 | BU6: =636665.88+439935.16 -> 1076601 | BV6: =83671.12+ 222379.08 -> 306050.2 | BW6: =197658.39+ 197207.58 -> 394865.97 | BX6: =327218.86+24960 -> 352178.86 | BY6: =334398.75+184175 -> 518573.75 | BZ6: =231945.01+134139.58+15390+13199.85+29529.58+1209.51 -> 425413.53 | CA6: =163775.02+451047 -> 614822.02 | CB6: =285108.66+454884.58 -> 739993.24 | CC6: =431858.18+391157.45 -> 823015.63 | CD6: =126379.26+331928.55 -> 458307.81 | CE6: =378441.4+72800+135023.88 -> 586265.28 | CF6: =261864+470747.58 -> 732611.58 | CG6: =618836+107754.75 -> 726590.75 | CH6: =153218+446177.82 -> 599395.82 | CI6: =183640.1+422819.69+25000 -> 631459.79 | CJ6: =66769+272583.05 -> 339352.05 | CK6: =66578+360613.55 -> 427191.55 | CL6: =371509.52+120091+898463.66 -> 1390064.2 | CM6: =108115+784429+75600 -> 968144 | CN6: =29700+555834.21+170944 -> 756478.21 | CO6: =491091.61+93538.87+38800 -> 623430.48 | CP6: =104185.6+931344.73 -> 1035530.3 | CQ6: =856704.96+740210.32 -> 1596915.3 | CR6: =166490+455489.72 -> 621979.72 | CS6: =487934.4+169831.16 -> 657765.56 | CT6: =65560+735597.91 -> 801157.91 | CU6: =1696717.5+65475 -> 1762192.5 | CV6: =63077.4+230322+62100 -> 355499.4 | CW6: =1727606.3+52000 -> 1779606.3 | CX6: =61843.75+476164.58 -> 538008.33 | CY6: =477992+585766.08 -> 1063758.1 | CZ6: =368297.93+268500.5 -> 636798.43 | DA6: =214455.6+746479.75 -> 960935.35 | DB6: =421077.24+162810.58 -> 583887.82 | DC6: =540817.6+367688.88+622976+14400 -> 1545882.5 | DD6: =442488.81+896309.06 -> 1338797.9 | DE6: =846381.07+221543.24 -> 1067924.3 | DF6: =513075.3+110637.3 -> 623712.6 | DG6: =443651.5+707527.1 -> 1151178.6 | DH6: =358010.25+855581.13 -> 1213591.4 | DI6: =335938+308875.97+420661.2 -> 1065475.2 | DJ6: =258810.6+272026.5+101920 -> 632757.1 | DK6: =45892.8+196721.58 -> 242614.38 | DL6: =579871+287763.49+332732.8 -> 1200367.3 | DM6: =279234.5+315484 -> 594718.5 | DN6: =134608.33+760891.89+25300.58 -> 920800.8 | DO6: =_xlfn.XLOOKUP(DO$2,'AR Aging 20260320'!$S:$S,'AR Aging 20260320'!$U:$U) -> 11000 | DP6: =_xlfn.XLOOKUP(DP$2,'AR Aging 20260320'!$S:$S,'AR Aging 20260320'!$U:$U) -> 430690.5 | DQ6: =_xlfn.XLOOKUP(DQ$2,'AR Aging 20260320'!$S:$S,'AR Aging 20260320'!$U:$U) -> 1398444.2 | DR6: =_xlfn.XLOOKUP(DR$2,'AR Aging 20260320'!$S:$S,'AR Aging 20260320'!$U:$U) -> 981511.67 | DS6: =_xlfn.XLOOKUP(DS$2,'AR Aging 20260320'!$S:$S,'AR Aging 20260320'!$U:$U) -> 0 | DT6: =_xlfn.XLOOKUP(DT$2,'AR Aging 20260320'!$S:$S,'AR Aging 20260320'!$U:$U) -> 2522706.8 | DU6: =_xlfn.XLOOKUP(DU$2,'AR Aging 20260320'!$S:$S,'AR Aging 20260320'!$U:$U) -> 177216.75 | DV6: =_xlfn.XLOOKUP(DV$2,'AR Aging 20260320'!$S:$S,'AR Aging 20260320'!$U:$U) -> 2735404.4 | ... EL6: =_xlfn.XLOOKUP(EL$2,'AR Aging 20260320'!$S:$S,'AR Aging 20260320'!$U:$U) -> 1528567.5
B7: From Bookings | C7: 0 | D7: 0 | E7: 0 | F7: 0 | G7: 0 | H7: 0 | I7: 0 | J7: 0 | K7: 0 | L7: 0 | M7: 770000 | N7: 0 | O7: 0 | P7: 0 | Q7: 0 | R7: 0 | S7: 0 | T7: 0 | U7: 0 | V7: 0 | W7: 0 | X7: 0 | Y7: 0 | Z7: 0 | AA7: 0 | AB7: 0 | AC7: 0 | AD7: 0 | AE7: 0 | AF7: 0 | AG7: 0 | AH7: 0 | AI7: 0 | AJ7: 0 | AK7: 0 | AL7: 0 | AM7: 0 | AN7: 0 | AO7: 0 | AP7: 0 | AQ7: 0 | AR7: 0 | AS7: 0 | AT7: 0 | AU7: =SUMIFS(Bookings!$W:$W,Bookings!$T:$T,'Wkly Cash Flow'!AU$2) -> 0 | AV7: =SUMIFS(Bookings!$W:$W,Bookings!$T:$T,'Wkly Cash Flow'!AV$2) -> 0 | AW7: =SUMIFS(Bookings!$W:$W,Bookings!$T:$T,'Wkly Cash Flow'!AW$2) -> 0 | AX7: =SUMIFS(Bookings!$W:$W,Bookings!$T:$T,'Wkly Cash Flow'!AX$2) -> 0 | AY7: =SUMIFS(Bookings!$W:$W,Bookings!$T:$T,'Wkly Cash Flow'!AY$2) -> 0 | AZ7: =SUMIFS(Bookings!$W:$W,Bookings!$T:$T,'Wkly Cash Flow'!AZ$2) -> 0 | BA7: =SUMIFS(Bookings!$W:$W,Bookings!$T:$T,'Wkly Cash Flow'!BA$2) -> 0 | BB7: =SUMIFS(Bookings!$W:$W,Bookings!$T:$T,'Wkly Cash Flow'!BB$2) -> 0 | BC7: =SUMIFS(Bookings!$W:$W,Bookings!$T:$T,'Wkly Cash Flow'!BC$2) -> 0 | BD7: 0 | BE7: =SUMIFS(Bookings!$W:$W,Bookings!$T:$T,'Wkly Cash Flow'!BE$2) -> 0 | BF7: =SUMIFS(Bookings!$W:$W,Bookings!$T:$T,'Wkly Cash Flow'!BF$2) -> 0 | BX7: =SUMIFS(Bookings!$W:$W,Bookings!$T:$T,'Wkly Cash Flow'!BX$2) -> 0 | BY7: =SUMIFS(Bookings!$W:$W,Bookings!$T:$T,'Wkly Cash Flow'!BY$2) -> 0 | BZ7: =SUMIFS(Bookings!$W:$W,Bookings!$T:$T,'Wkly Cash Flow'!BZ$2) -> 0 | CA7: =SUMIFS(Bookings!$W:$W,Bookings!$T:$T,'Wkly Cash Flow'!CA$2) -> 0 | CB7: =SUMIFS(Bookings!$W:$W,Bookings!$T:$T,'Wkly Cash Flow'!CB$2) -> 0 | CC7: =SUMIFS(Bookings!$W:$W,Bookings!$T:$T,'Wkly Cash Flow'!CC$2) -> 0 | CD7: =SUMIFS(Bookings!$W:$W,Bookings!$T:$T,'Wkly Cash Flow'!CD$2) -> 0 | CE7: =SUMIFS(Bookings!$W:$W,Bookings!$T:$T,'Wkly Cash Flow'!CE$2) -> 0 | CF7: =SUMIFS(Bookings!$W:$W,Bookings!$T:$T,'Wkly Cash Flow'!CF$2) -> 0 | CH7: =SUMIFS(Bookings!$W:$W,Bookings!$T:$T,'Wkly Cash Flow'!CH$2) -> 0 | CI7: =SUMIFS(Bookings!$W:$W,Bookings!$T:$T,'Wkly Cash Flow'!CI$2) -> 0 | CJ7: =SUMIFS(Bookings!$W:$W,Bookings!$T:$T,'Wkly Cash Flow'!CJ$2) -> 0 | CL7: =SUMIFS(Bookings!$W:$W,Bookings!$T:$T,'Wkly Cash Flow'!CL$2) -> 0 | CM7: =SUMIFS(Bookings!$W:$W,Bookings!$T:$T,'Wkly Cash Flow'!CM$2) -> 0 | CN7: =SUMIFS(Bookings!$W:$W,Bookings!$T:$T,'Wkly Cash Flow'!CN$2) -> 0 | CS7: =SUMIFS(Bookings!$W:$W,Bookings!$T:$T,'Wkly Cash Flow'!CS$2) -> 0 | CU7: 0 | CV7: =SUMIFS(Bookings!$W:$W,Bookings!$T:$T,'Wkly Cash Flow'!CV$2) -> 0 | CX7: =SUMIFS(Bookings!$W:$W,Bookings!$T:$T,'Wkly Cash Flow'!CX$2) -> 0 | DH7: =_xlfn.XLOOKUP(DH$2,Bookings!$T:$T,Bookings!$W:$W) -> 0 | DK7: =_xlfn.XLOOKUP(DK$2,Bookings!$T:$T,Bookings!$W:$W) -> 0 | DM7: =_xlfn.XLOOKUP(DM$2,Bookings!$T:$T,Bookings!$W:$W) -> 0 | DO7: =_xlfn.XLOOKUP(DO$2,Bookings!$T:$T,Bookings!$W:$W) -> 0 | DP7: =_xlfn.XLOOKUP(DP$2,Bookings!$T:$T,Bookings!$W:$W) -> 0 | DQ7: =_xlfn.XLOOKUP(DQ$2,Bookings!$T:$T,Bookings!$W:$W) -> 0 | DR7: =_xlfn.XLOOKUP(DR$2,Bookings!$T:$T,Bookings!$W:$W) -> 0 | DS7: =_xlfn.XLOOKUP(DS$2,Bookings!$T:$T,Bookings!$W:$W) -> 0 | DT7: =_xlfn.XLOOKUP(DT$2,Bookings!$T:$T,Bookings!$W:$W) -> 0 | DU7: =_xlfn.XLOOKUP(DU$2,Bookings!$T:$T,Bookings!$W:$W) -> 0 | DV7: =_xlfn.XLOOKUP(DV$2,Bookings!$T:$T,Bookings!$W:$W) -> 0 | ... EL7: =_xlfn.XLOOKUP(EL$2,Bookings!$T:$T,Bookings!$W:$W) -> 4000000
B8: External Funding | L8: 500000 | N8: 1940000 | O8: 952054.59 | Y8: 550000 | Z8: 689000 | AG8: 600000 | AV8: 430000 | BF8: 600000 | BH8: 200000 | BI8: 400000 | BK8: 200000 | BU8: 500000 | BW8: 1500000 | BX8: 700000 | CA8: =300000 -> 300000 | CE8: =18094708.55 -> 18094709 | CR8: 213795 | CT8: =204312 -> 204312
B9: Cash Out
B10: Payroll | C10: -486239.44 | E10: -479000 | G10: -457093.02 | I10: -469959.91 | J10: 21.49 | K10: -471832.45 | M10: -485000 | O10: -485000 | Q10: -490000 | S10: -490000 | U10: -450603.76 | W10: -507095.7 | Y10: -460000 | AA10: -460000 | AC10: -490000 | AE10: -488297.24 | AG10: =-713222.48-AG11 -> -521554.18 | AI10: -525173.09 | AK10: =-672927+117564.09 -> -555362.91 | AM10: -500072.79 | AO10: -579638.45 | AQ10: -521222.51 | AS10: -553535.47 | AU10: -524725.96 | AV10: -1958.14 | AW10: -626469.52 | AY10: -571065.76 | BA10: -557810.57 | BC10: -577090.03 | BE10: -559835 | BG10: -564444.79 | BI10: -556561.81 | BK10: -579826.37 | BM10: -558465.81 | BO10: -557392.87 | BQ10: -578607.75 | BS10: =-588831.05-3280.07+1478.1 -> -590633.02 | BU10: -583994.98 | BW10: -614501.64 | BY10: =-598670.19 -> -598670.19 | CA10: =-604531.81 -> -604531.81 | CC10: -616962 | CE10: =-633064.48 -> -633064.48 | CG10: -822215.94 | CI10: -624037.09 | CK10: -678441.1 | CM10: -740246.79 | CO10: =-685708.64 -> -685708.64 | CP10: =-308529.71 -> -308529.71 | CQ10: =-684765.8 -> -684765.8 | CS10: =-761855.96 -> -761855.96 | CT10: -298101.66 | CU10: -746662.23 | CW10: =-764439.25 -> -764439.25 | CY10: =-824720.16 -> -824720.16 | DA10: -841297.88 | DC10: =-1506934.58 -> -1506934.6 | DE10: =-802575.13 -> -802575.13 | DG10: -1080029.4 | DI10: =-836039.47 -> -836039.47 | DK10: =-834536.36 -> -834536.36 | DM10: =-845077.81 -> -845077.81 | DO10: -880000 | DQ10: -890000 | DS10: -890000 | DU10: -900000 | DW10: -900000 | DY10: -900000 | EA10: -900000 | EC10: -900000 | EE10: -910000 | EG10: -910000 | EI10: -910000 | EK10: -910000
B11: Commission/Bonuses | C11: -106753.96 | G11: -235369.33 | K11: -86851.37 | O11: -100000 | T11: -292849 | X11: -135000 | AC11: -150000 | AG11: =-191668.3 -> -191668.3 | AK11: -131717.46 | AP11: -150968.47 | AT11: -189304.86 | AX11: -147897.35 | AY11: -194609.73 | BC11: -254504.33 | BE11: -8796.32 | BG11: -265882.85 | BK11: -98622.43 | BO11: -156573.57 | BP11: -223996.81 | BT11: -480222.88 | BX11: -177215.52 | CC11: -185940.88 | CF11: -17629224 | CL11: -131031.48 | CY11: =-315545.79 -> -315545.79 | DL11: -420008.56 | DO11: -250000 | DT11: -250000 | DX11: -250000 | EC11: -250000 | EG11: -250000 | EK11: -250000
B12: Health Insurance | C12: -85053.24 | G12: -78906.19 | L12: -78000 | P12: -78000 | U12: -74429.3 | Y12: -78000 | AC12: -78000 | AH12: -86047.42 | AL12: -72792.41 | AP12: -115474.84 | AU12: -102027.2 | AY12: -104693.15 | BD12: =-100200.84-3364.89 -> -103565.73 | BH12: =-106343.19-2205.82 -> -108549.01 | BL12: -103571.15 | BP12: -108967.13 | BU12: -116241.15 | BY12: =-110585.38 -> -110585.38 | CA12: =-179.1 -> -179.1 | CB12: -70271.89 | CC12: -181343.38 | CE12: =-73464.74-363.79 -> -73828.53 | CG12: =-75985.49 -> -75985.49 | CH12: =-111266.15 -> -111266.15 | CI12: -77160.92 | CJ12: =-429.84 -> -429.84 | CL12: -132521.39 | CM12: -90103.71 | CO12: -87574.68 | CP12: =-10000 -> -10000 | CQ12: =-249028.7 -> -249028.7 | CU12: -250505.51 | CW12: =-93327.42 -> -93327.42 | CY12: =-165682.73 -> -165682.73 | CZ12: =-104132.05 -> -104132.05 | DA12: =-101280.94 -> -101280.94 | DC12: -99371.87 | DD12: =-179485.14 -> -179485.14 | DE12: =-102116.03 -> -102116.03 | DH12: =-178326.85 -> -178326.85 | DI12: =-109690.73 -> -109690.73 | DL12: =-180322.52 -> -180322.52 | DM12: =-113261.19 -> -113261.19 | DO12: -100000 | DP12: -175000 | DQ12: -100000 | DR12: -5000 | DS12: -100000 | DT12: -5000 | DU12: =-175000-95000 -> -270000 | DV12: -5000 | DW12: -100000 | DX12: -10000 | DY12: -175000 | ED12: -175000 | EH12: -270000 | EL12: -175000
B13: Other Benefits | C13: -64666.1 | D13: -410.23 | E13: -51000 | F13: -589.21 | G13: -55973.41 | H13: -12640.81 | I13: -55907.52 | J13: -1199.52 | K13: -3270.66 | M13: -56000 | O13: -56000 | Q13: -56000 | S13: -56000 | U13: -65049.56 | V13: 1743.15 | W13: -57151.02 | X13: -4642.18 | Y13: -60000 | AA13: -60000 | AC13: -60000 | AE13: 976.15 | AF13: =-763.96-57764 -> -58527.96 | AG13: =-251.95-63613.42+19.9 -> -63845.47 | AH13: -2296.96 | AI13: =3901.91-61933.73 -> -58031.82 | AJ13: =-263.88-2091.18 -> -2355.06 | AK13: -74610 | AL13: -14439.93 | AM13: =-55780.75-789.65 -> -56570.4 | AN13: -8597.61 | AO13: -62129.14 | AP13: =-9409.09-108.89 -> -9517.98 | AQ13: -69638.84 | AR13: -14941.94 | AS13: -61253.47 | AT13: -11775.93 | AU13: -73212.22 | AV13: -10172.42 | AW13: -69095.65 | AX13: -11029.49 | AY13: -77089.8 | AZ13: -10945.52 | BA13: -66746.59 | BB13: =-8755.85-460 -> -9215.85 | BC13: -68038.7 | BD13: =-20807.62-274 -> -21081.62 | BE13: -68880.61 | BF13: =-8018.8-181.95 -> -8200.75 | BG13: =-65561.23-370.7 -> -65931.93 | BH13: -23978.86 | BI13: -67803.26 | BJ13: -7207.5 | BK13: -72265.59 | BL13: -20125.49 | BM13: -69054.44 | BN13: -8647.51 | BO13: -68522.39 | BP13: -6779.2 | BQ13: -84648.18 | BR13: =-268.65-6844.36 -> -7113.01 | BS13: =-923.06-70895 -> -71818.06 | BT13: =-6831.05-4863.6 -> -11694.65 | BU13: -85624.72 | BV13: -6624.8 | BW13: =-73386.4-89.55 -> -73475.95 | BX13: =-9397.94 -> -9397.94 | BY13: =-19111.17-71387.42 -> -90498.59 | BZ13: =-441.28-1312.62 -> -1753.9 | CA13: -5574.37 | CB13: -5828.84 | CC13: -5437.08 | CD13: =-5022.88 -> -5022.88 | CE13: =-913.93 -> -913.93 | CF13: =-6796.03-452.17-288.45 -> -7536.65 | CG13: =-832.96 -> -832.96 | CH13: =-6592.99 -> -6592.99 | CI13: -791.56 | CJ13: =-4285.9- 53.48 -> -4339.38 | CK13: -5151.61 | CN13: -8444.84 | CO13: =-7060.16 -> -7060.16 | CP13: =-589.34-119.82 -> -709.16 | CQ13: =-15902.43-1678.56 -> -17580.99 | CR13: =-647.87 -> -647.87 | CS13: =-1238.71-88957.39-89.55 -> -90285.65 | CT13: =-8608.58 -> -8608.58 | CU13: -54492.27 | CV13: -10512.61 | CW13: =-1353.91 -> -1353.91 | CX13: =-8819.24 -> -8819.24 | CY13: =-6964.65 -> -6964.65 | CZ13: =-23474.87-84 -> -23558.87 | DA13: =-179.1-5163.61 -> -5342.71 | DB13: =2102.73-9259.44 -> -7156.71 | DC13: =-3005.51 -> -3005.51 | DD13: =-13713.59 -> -13713.59 | DE13: =-951.06 -> -951.06 | DF13: =-9808.77 -> -9808.77 | DG13: =-3494.6-108523.97 -> -112018.57 | DH13: =-12865.48 -> -12865.48 | DI13: =-1215.07 -> -1215.07 | DJ13: =-10018.94 -> -10018.94 | DK13: =-121380.06 -> -121380.06 | DL13: =-25245.82 -> -25245.82 | DM13: =-1741.56 -> -1741.56 | DN13: =-14602.41-461.39 -> -15063.8 | DO13: -10000 | DP13: -10000 | DQ13: -10000 | DR13: -10000 | DS13: -10000 | DT13: -10000 | DU13: -10000 | DV13: -10000 | DW13: -10000 | DX13: -10000 | DY13: -10000 | DZ13: -10000 | EA13: -10000 | EB13: -10000 | EC13: -10000 | ED13: -10000 | EE13: -10000 | EF13: -10000 | EG13: -10000 | EH13: -10000 | EI13: -10000 | EJ13: -10000 | EK13: -10000
B14: Credit Cards | D14: -7639.83 | E14: -295000 | F14: -28000 | H14: -7095.26 | I14: -78581.11 | J14: -192788.83 | M14: 7000 | N14: -250000.38 | O14: -50000 | Q14: 7000 | R14: -225000 | S14: -50000 | U14: -247520.21 | V14: -154282.23 | W14: -36073.11 | Y14: -72821.68 | AA14: -226530.09 | AD14: 7000 | AE14: -40000 | AF14: -178145.39 | AH14: =-5427.14-169099.3 -> -174526.44 | AI14: -75000 | AJ14: =-128937.38-501.27 -> -129438.65 | AK14: -50016 | AL14: -25000 | AM14: =-9296.36-25000-41813.41 -> -76109.77 | AN14: =-25000-228.89 -> -25228.89 | AO14: =-40000-174282.69 -> -214282.69 | AP14: -35000 | AQ14: =-57888.44-31554.98 -> -89443.42 | AR14: =-50000-124.78 -> -50124.78 | AS14: -128111.97 | AT14: -25000 | AU14: =-100000-98133.45-7835.34 -> -205968.79 | AV14: -25000 | AW14: -137232.12 | AX14: -15.94 | AZ14: =-12513.16-145575.65 -> -158088.81 | BA14: -75132.16 | BB14: -208560.93 | BC14: -149012.29 | BD14: =-7490.24-50000 -> -57490.24 | BE14: -100000 | BF14: -130521.36 | BG14: -25015.94 | BH14: =-8192.73-109339.54 -> -117532.27 | BI14: -50000 | BJ14: -260623.07 | BK14: -100000 | BL14: -109782.88 | BM14: =-16262.39-75000 -> -91262.39 | BN14: -80000 | BP14: -75000 | BQ14: =-2812.54-100000-53045.18 -> -155857.72 | BR14: -50000 | BS14: -202443.54 | BT14: -25000 | BU14: =-122545.72-10580.93 -> -133126.65 | BV14: =-150000 -> -150000 | BW14: =-229599.44 -> -229599.44 | BX14: -75000 | BY14: =-50000+7280 -> -42720 | BZ14: =-19961.25-155933.03-29529.58 -> -205423.86 | CA14: =-25000 -> -25000 | CB14: =-233139.47 -> -233139.47 | CC14: =-95000 -> -95000 | CD14: =-107674.85-3453.39 -> -111128.24 | CE14: =-50000 -> -50000 | CF14: -169796.14 | CG14: -50000 | CH14: =-299297 -> -299297 | CI14: =-29625.29-116638.07 -> -146263.36 | CJ14: -100000 | CK14: -190289.73 | CL14: -50000 | CM14: =-10935.72-161278.04 -> -172213.76 | CN14: -25000 | CO14: =-137554.39 -> -137554.39 | CP14: =-25000 -> -25000 | CQ14: =-174954.19-12577.32 -> -187531.51 | CS14: =-204856.01 -> -204856.01 | CU14: -50000 | CV14: =25850-10415.68-11806.11 -> 3628.21 | CX14: =-118554.35 -> -118554.35 | CY14: =-91965.51 -> -91965.51 | CZ14: =-43327.07+5000-33007.08 -> -71334.15 | DA14: =-192420.18 -> -192420.18 | DB14: =-50000-25000 -> -75000 | DC14: -50000 | DD14: =-129423.64-95421.93 -> -224845.57 | DF14: =-373584.76 -> -373584.76 | DG14: -15.94 | DH14: =-172550.74 -> -172550.74 | DI14: =-150000 -> -150000 | DJ14: =-200000 -> -200000 | DM14: =-276546.06 -> -276546.06 | DO14: -100000 | DP14: -100000 | DQ14: -50000 | DR14: -100000 | DT14: -100000 | DU14: -100000 | DV14: -100000 | DW14: -100000 | DX14: -10000 | DY14: -100000 | DZ14: -50000 | EA14: -100000 | ED14: -100000 | EE14: -50000 | EF14: -100000 | EH14: -100000 | EI14: -50000 | EJ14: -100000
B15: Office Rent | C15: -71000 | E15: -5885 | G15: -71031.15 | L15: -71000 | P15: -71000 | U15: -71031 | Y15: -71000 | AC15: -71000 | AH15: =-47373.08-25000 -> -72373.08 | AL15: -100 | AM15: -72373.08 | AP15: -25000 | AQ15: -47373.08 | AU15: -25000 | AV15: -47373.08 | BD15: =-47373.08-25000 -> -72373.08 | BH15: =-47373.08-25000 -> -72373.08 | BL15: -47373.08 | BP15: -25000 | BQ15: -47373.08 | BV15: -100134.08 | CC15: -31500 | CH15: -25000 | CU15: -48755.28 | DD15: =-58259.35 -> -58259.35 | DM15: -48755.28 | DP15: -48755.28 | DU15: -48755.28 | DY15: -48755.28 | ED15: -48755.28 | EH15: -48755.28
B16: International EE's | C16: -50514.18 | D16: -16669.96 | G16: -115000 | H16: 35140.8 | K16: -98981.99 | O16: -115000 | T16: -115000 | X16: -99000 | AB16: -110000 | AG16: -111756.12 | AK16: -117564.09 | AP16: -107427.21 | AT16: -107975.3 | AX16: -99187.85 | AY16: -6479.12 | BB16: -22995.38 | BC16: =-101515.24-4995.71 -> -106510.95 | BG16: -127805.9 | BK16: -136855.9 | BM16: -24099.43 | BN16: -16424.04 | BO16: -141883.03 | BP16: =-12170.03-13400.91 -> -25570.94 | BS16: -2805.67 | BT16: -183813.17 | BX16: -232223.99 | CC16: -200817.64 | CG16: -234773.39 | CI16: -19467.13 | CL16: -201840.51 | CP16: -135667.97 | CT16: =-187183.96 -> -187183.96 | CW16: =-21950.71 -> -21950.71 | CX16: -197275.83 | CY16: =-9995.95 -> -9995.95 | DC16: -236673.32 | DG16: -236435.99 | DK16: =-261524.26 -> -261524.26 | DN16: =-12834.44 -> -12834.44 | DO16: -230000 | DT16: -230000 | DX16: -230000 | EC16: -230000 | EG16: -230000 | EK16: -230000
B17: Contractors | U17: -32000 | V17: 30000 | X17: -30000 | AB17: -30000 | AG17: -40000 | BD17: -12000 | BG17: -12000
B18: Marketing Expenses | E18: -22410 | N18: -50000 | R18: -50000 | W18: -47125.14 | AA18: -50000 | AM18: 25000 | AS18: -19751.91 | BM18: -1410.49 | BX18: -15000 | DG18: -27500
B19: Other Misc Expenses | C19: -8000 | D19: -9714.41 | E19: -12000 | F19: -5932 | G19: -1161.28 | H19: -11926.13 | I19: -16255.92 | J19: -103774.01 | K19: -20384.05 | L19: -10000 | M19: -10000 | N19: -10000 | O19: -10000 | P19: -10000 | Q19: -10000 | R19: -10000 | S19: -239526 | T19: -10000 | U19: -10063.16 | V19: -27847.8 | W19: -29036.06 | X19: -95000 | Y19: -10000 | Z19: -60000 | AA19: -60000 | AB19: -10000 | AC19: -25000 | AD19: =-60000-10845 -> -70845 | AE19: =-3002.07-2426- 27177.9 -> -32605.97 | AF19: =-22934.5-2598.94 -> -25533.44 | AG19: =-988.79-25500-9149 -> -35637.79 | AH19: =-300000-24651.83+300000 -> -24651.83 | AI19: =-300000-1945.7+300000-4807.5 -> -6753.2 | AJ19: =-306333.13+300000 -> -6333.13 | AK19: =-47187.81-4433 -> -51620.81 | AL19: =-11897.31-83446 -> -95343.31 | AM19: =-28793.79-500000+492363.61 -> -36430.18 | AN19: =-304206.99+273750 -> -30456.99 | AO19: =-813157.27+795798.33 -> -17358.94 | AP19: =-4731.99-25000 -> -29731.99 | AQ19: =-37934.4-700000-423.54+669750 -> -68607.94 | AR19: =-6868.85-24529.01 -> -31397.86 | AS19: =-554852.12+544448.89 -> -10403.23 | AT19: =-509092.21+338250 -> -170842.21 | AU19: =-507659.49+665340.71-200000-1501 -> -43819.78 | AV19: =-6045.67-12033.97 -> -18079.64 | AW19: =-1019473.79+849944.19+150785 -> -18744.6 | AX19: =-238326.96-45616.73+230000 -> -53943.69 | AY19: =-1511720.6+1461393.6 -> -50327 | AZ19: =-24164.38-374484-423.54+288107.53 -> -110964.39 | BA19: =-121779.19+45610.01 -> -76169.18 | BB19: =-752753.9+701003.21 -> -51750.69 | BC19: =-157230.23-20103.06+67.29 -> -177266 | BD19: =-412654.34+315462.95+25000 -> -72191.39 | BE19: =-87542.12+69582.35 -> -17959.77 | BF19: =-53792.32-35511.34+39035.33-7680+7680-1591.11 -> -51859.44 | BG19: =-837431.6+655298.57+ 148719.55+12000 -> -21413.48 | BH19: =-9850.77+247628.11+5147.24-262678.12-0.06 -> -19753.6 | BI19: =518134.14-522840.88 -> -4706.74 | BJ19: =-284484.43+278766.83-40743.07-476.88 -> -46937.55 | BK19: =-490298.6+457710.73 -> -32587.87 | BL19: =-758633.25+631460.84 -> -127172.41 | BM19: =-346515.06-255328.98+537214.83-315.84-11675.81 -> -76620.86 | BN19: =-176441.37-1464.34 -> -177905.71 | BO19: =-46760.21-165761.62+32932.79 -> -179589.04 | BP19: =-602815.85+496538.77 -> -106277.08 | BQ19: =-85639.61+472518.18-450886.5 -> -64007.93 | BR19: =-108257.98+10000+85974.26-18745.99 -> -31029.71 | BS19: =-323474.43-19605.79+171022.9+130125 -> -41932.32 | BT19: =-1457.91-81501.55 -> -82959.46 | BU19: =152299.94-204676.16 -> -52376.22 | BV19: =48246.62-59165.06 -> -10918.44 | BW19: =-172073.9+146895.93 -> -25177.97 | BX19: =-54705.96-554468.86+550392.86 -> -58781.96 | BY19: =-154706.62+870647.18-910176.21 -> -194235.65 | BZ19: =-156621.29+184048.47-15390-13199.85+1312.62-1209.51-45443.9 -> -46503.46 | CA19: =-354425.98+302523.71 -> -51902.27 | CB19: =-183364.28+154800.19 -> -28564.09 | CC19: =529421.94-566157.58 -> -36735.64 | CD19: =159725.5-265976.16 -> -106250.66 | CE19: =67237.01 - 91423.81 -> -24186.8 | CF19: =-196099.28+180026.88 -> -16072.4 | CG19: =24224.04-64178.73 -> -39954.69 | CH19: =316883.78-391717.46 -> -74833.68 | CI19: =-54977.13+40063.32 -> -14913.81 | CJ19: =-163413.22+116510.62 -> -46902.6 | CK19: -31730.81 | CL19: =-11646.65-468317.37-57011.9 -> -536975.92 | CM19: =-108999.5-22796.51+55000 -> -76796.01 | CN19: =-89079.5-28725.45 -> -117804.95 | CO19: =-95237.26+99279.01-161141.52 -> -157099.77 | CP19: =10835.24-10136.25-2983.83-18078.6 -> -20363.44 | CQ19: =727381.36-12273.55-727633 -> -12525.19 | CR19: =-177902.09+167017.94-169013.53 -> -179897.68 | CS19: =128546.16-183601.27-95389.74 -> -150444.85 | CT19: =-65772.7-17420.06 -> -83192.76 | CU19: -229823.28 | CV19: =-72576.78+63968.52-427948.05 -> -436556.31 | CW19: =-124539.36+53545.52-51905.01 -> -122898.85 | CX19: =-61843.75-52627.26+59343.75 -> -55127.26 | CY19: =-10840.89+585495.13-585766.08 -> -11111.84 | CZ19: =-324970.86+324066.46-112838.74 -> -113743.14 | DA19: =-89826.71-8616.11+123312.26+27360 -> 52229.44 | DB19: =-511172.23+380340.44+124449.79-38856.88 -> -45238.88 | DC19: -69849.83 | DD19: =947286.27-89464+58259.35-1258968.82 -> -342887.2 | DE19: =47370.23-73495.39-75444.39 -> -101569.55 | DF19: =74032.31-58899.94-130722.92 -> -115590.55 | DG19: =459137.4-43777.97-2598.18-459137.4-2000 -> -48376.15 | DH19: =1092160.79-128058.55-1132562.13 -> -168459.89 | DI19: =640191.68-24549.43-221625.47-420661.2 -> -26644.42 | DJ19: -31080.46 | DK19: =-45892.8+47104.8-11591.57 -> -10379.57 | DL19: =-595531+473921-98820.71 -> -220430.71 | DM19: -16729.45 | DN19: -80922.49 | DO19: -110000 | DP19: -110000 | DQ19: -110000 | DR19: -110000 | DS19: -110000 | DT19: -110000 | DU19: -110000 | DV19: -110000 | DW19: -110000 | DX19: -110000 | DY19: -110000 | DZ19: -110000 | EA19: -110000 | EB19: -110000 | EC19: -110000 | ED19: -110000 | EE19: -110000 | EF19: -110000 | EG19: -110000 | EH19: -110000 | EI19: -110000 | EJ19: -110000 | EK19: -110000 | EL19: -110000
B20: Draw | C20: -250000 | H20: -100000 | L20: -100000 | P20: -100000 | AE20: -293633.88 | AH20: -100000 | AL20: -30000 | AO20: =-100000-100000 -> -200000 | AP20: -50000 | AW20: -150785 | BA20: -250000 | BO20: -75000 | BR20: -100000 | BS20: -110000 | BU20: -125000 | BV20: =-25000-22779.07 -> -47779.07 | BW20: -1275000 | BX20: -25000 | BY20: =-25000 -> -25000 | BZ20: =-25000 -> -25000 | CA20: =-100000 -> -100000 | CB20: =-75000 -> -75000 | CC20: 175000 | CD20: -25000 | CE20: -25000 | CF20: -25000 | CG20: -25000 | CI20: =-100000 -> -100000 | CJ20: 100000.03 | CM20: -55000
B21: Payments on Funding | C21: -28988.61 | G21: -45079 | L21: -45079 | P21: =-47222-45079 -> -92301 | Q21: -47222 | R21: -47222 | S21: -47222 | T21: -47222 | U21: -47222 | V21: -47222 | W21: -47222.2 | X21: -47222.2 | Y21: =-47222-32000 -> -79222 | AC21: -45079 | AE21: =-300000+300000 -> 0 | AF21: =-300000+300000 -> 0 | AG21: =-400000+400000 -> 0 | AH21: -91528.5 | AL21: -95266.2 | AN21: -43200 | AP21: -95920.17 | AU21: -94841.2 | AY21: -98255.31 | BB21: -43200 | BD21: -99067.53 | BG21: -56224 | BH21: -95526.03 | BJ21: -50000 | BK21: -50000 | BL21: -98602.9 | BP21: =-50000-97488.78 -> -147488.78 | BS21: -72000 | BT21: =-5000-50000 -> -55000 | BU21: =-98656.01-25000 -> -123656.01 | BX21: -25000 | BY21: =-97488.77 -> -97488.77 | CB21: -20000 | CC21: -98656.01 | CD21: -45000 | CF21: -20000 | CJ21: 141298.97 | CK21: =-145669-62208+66578.03 -> -141298.97
B23: Ending Cash | C23: =SUM(C3:C22) -> 2288807.5 | D23: =SUM(D3:D22) -> 2604552.4 | E23: =SUM(E3:E22) -> 1994376.4 | F23: =SUM(F3:F22) -> 2251105.2 | G23: =SUM(G3:G22) -> 1595981.2 | H23: =SUM(H3:H22) -> 1633425.3 | I23: =SUM(I3:I22) -> 1364115.8 | J23: =SUM(J3:J22) -> 1102620.9 | ... EL23: =SUM(EL3:EL22) -> 16983976
B24: Cash Inflow/Outflow | CV24: =CV23-CU23 -> -87941.31 | CW24: =CW23-CV23 -> 775636.16 | CX24: =CX23-CW23 -> 158231.65 | CY24: =CY23-CX23 -> -362228.55 | CZ24: =CZ23-CY23 -> 324030.22 | DA24: =DA23-CZ23 -> -127176.92 | DB24: =DB23-DA23 -> 456492.23 | DC24: =DC23-DB23 -> -419952.63 | ... EL24: =EL23-EK23 -> 5243567.5
B26: Prior Fcst (20260127) | U26: 1815788.5 | V26: 1707304.5 | W26: 1088371.9 | X26: 1078140.3 | Y26: 1898512.9 | Z26: 2750442.9 | AA26: 2181672.9 | AB26: 2177832.9 | AC26: 1672461.7 | AD26: 1658397.9 | AE26: 1014567.9 | AF26: 1170582.4 | AG26: 1359914.1 | AH26: 1231202.1 | AI26: 887594.36 | AJ26: 874146.77 | AK26: 1652259.5 | AL26: 1959378.1 | AM26: 1632131.9 | AN26: 1786503.7 | AO26: 1025395.8 | AP26: 1062630.8 | AQ26: 665032.98 | AR26: 1000740.4 | AS26: 941863.1 | AT26: 678985.76 | AU26: 396051.89 | AV26: 1426261.4 | AW26: 720910.21 | AX26: 922139.42 | AY26: 1308888.7 | AZ26: 1556026.6 | BA26: 1606423.5 | BB26: 2252298.6 | BC26: 1433331.7 | BD26: 1529013.9 | BE26: 905031.57 | BF26: 1496366.4 | BG26: 539811.15 | BH26: 464610.68 | BI26: 318948.25 | BJ26: 916028.35 | BK26: 603965.67 | BL26: 1008974.8 | BM26: 952125.32 | BN26: 986584.06 | BO26: 1264430.2 | BP26: 1545191 | BQ26: 1556009.3 | BR26: 2098433.3 | BS26: 1355761.1 | BT26: 617642.47 | BU26: 974223.78 | BV26: 964817.59 | BW26: 641928.56 | BX26: 1076488 | BY26: 435863.18 | BZ26: 582595.49 | CA26: 713880.82 | CB26: 119680.82 | CC26: -52240.54 | CD26: -69224.9 | CE26: 83185.1 | CF26: 3185.1 | CG26: 129583.1 | CH26: -307789.98 | CI26: 396121.02 | CJ26: 46121.02 | CK26: -578878.98 | CL26: 782166.02 | CM26: 782166.02 | CN26: 782166.02 | CO26: 782166.02 | CP26: 782166.02 | CQ26: 782166.02 | CR26: 782166.02 | CS26: 782166.02 | CT26: 782166.02 | CU26: 2708001.7 | CV26: 2620060.3 | CW26: 3395696.5 | CX26: 3553928.2 | CY26: 3191699.6 | CZ26: 3515729.8 | DA26: 3388552.9 | DB26: 3845045.1 | DC26: 4215565.7 | DD26: 4964367.7 | DE26: 5632200.1 | DF26: 5848852.3 | DG26: 5410791.3 | DH26: 5145447.5 | DI26: 4106397.5 | DJ26: 6988732 | DK26: 5418732 | DL26: 6949897.2 | DM26: 5799897.2 | DN26: 7906021.4 | DO26: 6326021.4 | DP26: 7527720.6 | DQ26: 6367720.6 | DR26: 8329607.6 | DS26: 7219607.6 | DT26: 7704608.4 | DU26: 6355853.1 | DV26: 6909469.2 | DW26: 5839469.2 | DX26: 5459469.2 | DY26: 4583012.7 | DZ26: 4583013.7 | EA26: 4583014.7 | EB26: 4583015.7 | EC26: 4583016.7 | ED26: 4583017.7 | EE26: 4583018.7 | EF26: 4583019.7 | EG26: 4583020.7 | EH26: 4583021.7 | EI26: 4583022.7 | EJ26: 4583023.7 | EK26: 4583024.7 | EL26: 4583025.7
B27: Change from last Fcst | U27: =U23-U26 -> 0 | V27: =V23-V26 -> 113003.12 | W27: =W23-W26 -> 136072.55 | X27: =X23-X26 -> 0 | Y27: =Y23-Y26 -> 0 | Z27: =Z23-Z26 -> 0 | AA27: =AA23-AA26 -> 0 | AB27: =AB23-AB26 -> 0 | ... EL27: =EL23-EL26 -> 12400950
B29: Ending Bank Bal
B30: BOA | X30: 962287.64 | Y30: 1063205.2 | Z30: 1665588.4 | AA30: 932923 | AB30: 1100457.6 | AC30: 261394.1 | AD30: 783718.13 | AE30: 395363.33 | AF30: 489886.14 | AG30: 614238.91 | AH30: 448451.7 | AI30: 467856.38 | AJ30: 285938.62 | AK30: 996539.81 | AL30: 1512810.5 | AM30: 1316657.3 | AN30: 1206105.6 | AO30: 465249.71 | AP30: 835672.52 | AQ30: 390741.02 | AR30: 603395.25 | AS30: 724905.02 | AT30: 414873.77 | AU30: 120705.58 | AV30: 770079.63 | AW30: 45714.84 | AX30: 736055.25 | AY30: 248000 | AZ30: 363551.51 | BA30: 441189.66 | BB30: 235940.45 | BC30: 356305.8 | BD30: 108381.38 | BE30: 152328.66 | BF30: 768750 | BG30: 109400 | BH30: 141771.5 | BI30: 102090 | BJ30: 99523.12 | BK30: 250000 | BL30: 209667.94 | BM30: 99684.16 | BN30: 99178.79 | BO30: 109448.58 | BP30: 77619 | BQ30: 100000 | BR30: 460910.12 | BS30: 127267.55 | BT30: 48100 | BU30: 122778.07 | BV30: 99505.06 | BW30: 350000 | BX30: 797750 | BY30: 196972.54 | BZ30: 84085.68 | CA30: 93255.62 | CB30: 100000 | CC30: 68500 | CD30: 60999 | CE30: 79235.28 | CF30: 100000 | CG30: 68576.02 | CH30: 98036.38 | CI30: 97074.06 | CJ30: 241299 | CK30: 100000 | CL30: 121271.25 | CM30: 188182.15 | CN30: 128802.65 | CO30: 12425.32 | CP30: 127446.16 | CQ30: 100000 | CR30: 88587.91 | CS30: 100000 | CT30: 99787.3 | CU30: 121210.5 | CV30: 99905.01 | CW30: 100000 | CX30: 100000 | CY30: 100000 | CZ30: 100000 | DA30: 224449.79 | DB30: 134354.8 | DC30: 462659.76 | DD30: 4578.07 | DE30: 150676.92 | DF30: 130591.3 | DG30: 376981 | DH30: 100000 | DI30: 187250.5 | DJ30: 100000 | DK30: 100000 | DL30: 84340 | DM30: 221562.5 | DN30: 172777.63
B31: NB | Y31: 549498.47 | Z31: 1036610.1 | AA31: 1036610.1 | AB31: 1036610.1 | AC31: 973001.72 | AD31: 874679.51 | AE31: 619204.37 | AF31: 680696.31 | AG31: 745675.19 | AH31: 782750.43 | AI31: 419738.02 | AJ31: 588208.19 | AK31: 655719.69 | AL31: 446567.56 | AM31: 315474.57 | AN31: 580398.07 | AO31: 560146.12 | AP31: 226958.29 | AQ31: 274291.96 | AR31: 397345.1 | AS31: 216958.08 | AT31: 264111.99 | AU31: 275346.31 | AV31: 656181.78 | AW31: 675195.37 | AX31: 601448.01 | AY31: 1060888.7 | AZ31: 1192475.1 | BA31: 1165233.8 | BB31: 2016358.1 | BC31: 1077025.9 | BD31: 1420632.5 | BE31: 752702.91 | BF31: 727616.36 | BG31: 430411.15 | BH31: 322839.18 | BI31: 216858.25 | BJ31: 816505.23 | BK31: 353965.67 | BL31: 799306.82 | BM31: 852441.16 | BN31: 887405.27 | BO31: 1154981.6 | BP31: 1467572 | BQ31: 1456009.3 | BR31: 1637523.2 | BS31: 1228493.6 | BT31: 569542.47 | BU31: 851445.71 | BV31: 865312.53 | BW31: 291928.56 | BX31: 278738.01 | BY31: 238890.64 | BZ31: 498509.81 | CA31: 616974.34 | CB31: 917418.91 | CC31: 494541.91 | CD31: 667948.94 | CE31: 18523693 | CF31: 1367910.7 | CG31: 877163 | CH31: 930108.64 | CI31: 579896.88 | CJ31: 864651.17 | CK31: 386229.5 | CL31: 702653.13 | CM31: 469525.96 | CN31: =1054607.05+79526.83 -> 1134133.9 | CO31: 798944.05 | CP31: 1219183.3 | CQ31: 1692112.5 | CR31: 2358753.8 | CS31: 1797664.8 | CT31: 2226260.4 | CU31: 2586791.1 | CV31: 2520155.3 | CW31: 3295696.5 | CX31: 3453928.1 | CY31: 3091699.6 | CZ31: 3415729.8 | DA31: 3164103.1 | DB31: 3710690.3 | DC31: 2962432.7 | DD31: 3940121.5 | DE31: 3854735.1 | DF31: 3999549.3 | DG31: 3399962.1 | DH31: 4358331.6 | DI31: 4212966.5 | DJ31: 4691874.7 | DK31: 3706668.9 | DL31: 4076688.5 | DM31: 3232073.2 | DN31: 4092838.1
B32: Total Bank Ending Bal | X32: =SUM(X30:X31) -> 962287.64 | Y32: =SUM(Y30:Y31) -> 1612703.6 | Z32: =SUM(Z30:Z31) -> 2702198.6 | AA32: =SUM(AA30:AA31) -> 1969533.1 | AB32: =SUM(AB30:AB31) -> 2137067.7 | AC32: =SUM(AC30:AC31) -> 1234395.8 | AD32: =SUM(AD30:AD31) -> 1658397.6 | AE32: =SUM(AE30:AE31) -> 1014567.7 | ... EL32: =SUM(EL30:EL31) -> 0
B33: Variance | X33: =X23-X32 -> 115852.66 | Y33: =Y23-Y32 -> 285809.2 | Z33: =Z23-Z32 -> 48244.29 | AA33: =AA23-AA32 -> 212139.74 | AB33: =AB23-AB32 -> 40765.17 | AC33: =AC23-AC32 -> 438065.85 | AD33: =AD23-AD32 -> 0.23 | AE33: =AE23-AE32 -> 0.23 | ... EL33: =EL23-EL32 -> 16983976
B35: AR Balance (End Of Week) | O35: {=_xludf.XLOOKUP(O$2,'AR Aging Balance'!$A:$A,'AR Aging Balance'!$F:$F)} -> #NAME? | P35: {=_xludf.XLOOKUP(P$2,'AR Aging Balance'!$A:$A,'AR Aging Balance'!$F:$F)} -> #NAME? | Q35: {=_xludf.XLOOKUP(Q$2,'AR Aging Balance'!$A:$A,'AR Aging Balance'!$F:$F)} -> #NAME? | R35: {=_xludf.XLOOKUP(R$2,'AR Aging Balance'!$A:$A,'AR Aging Balance'!$F:$F)} -> #NAME? | S35: {=_xludf.XLOOKUP(S$2,'AR Aging Balance'!$A:$A,'AR Aging Balance'!$F:$F)} -> #NAME? | T35: {=_xludf.XLOOKUP(T$2,'AR Aging Balance'!$A:$A,'AR Aging Balance'!$F:$F)} -> #NAME? | U35: {=_xludf.XLOOKUP(U$2,'AR Aging Balance'!$A:$A,'AR Aging Balance'!$F:$F)} -> #NAME? | V35: {=_xludf.XLOOKUP(V$2,'AR Aging Balance'!$A:$A,'AR Aging Balance'!$F:$F)} -> #NAME? | CL35: =_xlfn.XLOOKUP(CL$2,'AR Aging Balance'!$A:$A,'AR Aging Balance'!$F:$F) -> #N/A | CM35: =_xlfn.XLOOKUP(CM$2,'AR Aging Balance'!$A:$A,'AR Aging Balance'!$F:$F) -> #N/A | CN35: =_xlfn.XLOOKUP(CN$2,'AR Aging Balance'!$A:$A,'AR Aging Balance'!$F:$F) -> #N/A | CO35: =_xlfn.XLOOKUP(CO$2,'AR Aging Balance'!$A:$A,'AR Aging Balance'!$F:$F) -> #N/A | CP35: =_xlfn.XLOOKUP(CP$2,'AR Aging Balance'!$A:$A,'AR Aging Balance'!$F:$F) -> #N/A | CQ35: =_xlfn.XLOOKUP(CQ$2,'AR Aging Balance'!$A:$A,'AR Aging Balance'!$F:$F) -> #N/A | CR35: =_xlfn.XLOOKUP(CR$2,'AR Aging Balance'!$A:$A,'AR Aging Balance'!$F:$F) -> #N/A | CS35: =_xlfn.XLOOKUP(CS$2,'AR Aging Balance'!$A:$A,'AR Aging Balance'!$F:$F) -> #N/A | CT35: =_xlfn.XLOOKUP(CT$2,'AR Aging Balance'!$A:$A,'AR Aging Balance'!$F:$F) -> #N/A | CU35: 0 | CV35: 0 | CW35: 0 | CX35: 0 | CY35: =_xlfn.XLOOKUP(CY$2,'AR Aging Balance'!$A:$A,'AR Aging Balance'!$F:$F) -> 0 | CZ35: =_xlfn.XLOOKUP(CZ$2,'AR Aging Balance'!$A:$A,'AR Aging Balance'!$F:$F) -> 0 | DA35: =_xlfn.XLOOKUP(DA$2,'AR Aging Balance'!$A:$A,'AR Aging Balance'!$F:$F) -> 0 | DB35: =_xlfn.XLOOKUP(DB$2,'AR Aging Balance'!$A:$A,'AR Aging Balance'!$F:$F) -> 0 | DC35: =_xlfn.XLOOKUP(DC$2,'AR Aging Balance'!$A:$A,'AR Aging Balance'!$F:$F) -> 0 | DD35: =_xlfn.XLOOKUP(DD$2,'AR Aging Balance'!$A:$A,'AR Aging Balance'!$F:$F) -> 0 | DE35: =_xlfn.XLOOKUP(DE$2,'AR Aging Balance'!$A:$A,'AR Aging Balance'!$F:$F) -> 0 | DF35: =_xlfn.XLOOKUP(DF$2,'AR Aging Balance'!$A:$A,'AR Aging Balance'!$F:$F) -> 0 | ... EL35: =_xlfn.XLOOKUP(EL$2,'AR Aging Balance'!$A:$A,'AR Aging Balance'!$F:$F) -> 15901379
B37: Cash Out
B38: Operations | X38: =SUM(U10:X17,U18:X19) -> -2141207.1 | AB38: =SUM(Y10:AB17,Y18:AB19) -> -1818351.8 | AG38: =SUM(AC10:AG17,AC18:AG19) -> -2724440.7 | AK38: =SUM(AH10:AK17,AH18:AK19) -> -2143872 | AO38: =SUM(AL10:AO17,AL18:AO19) -> -1861924.6 | AT38: =SUM(AP10:AT17,AP18:AT19) -> -2643825.2 | AX38: =SUM(AU10:AX17,AU18:AX19) -> -2240953.4 | BC38: =SUM(AY10:BC17,AY18:BC19) -> -3685066.9 | BG38: =SUM(BD10:BG17,BD18:BG19) -> -2367250.2 | BK38: =SUM(BH10:BK17,BH18:BK19) -> -2356184.9 | BO38: =SUM(BL10:BO17,BL18:BO19) -> -2615876.6 | BT38: =SUM(BP10:BT17,BP18:BT19) -> -3283551.3 | BX38: =SUM(BU10:BX17,BU18:BX19) -> -2749415.5 | CB38: =SUM(BY10:CB17,BY18:CB19) -> -2315382.9 | CG38: =SUM(CC10:CG17,CC18:CG19) -> -21404523 | CK38: =SUM(CH10:CK17,CH18:CK19) -> -2456908.8
B39: Financing | X39: =SUM(U21:X21) -> -188888.4 | AB39: =SUM(Y21:AB21) -> -79222 | AG39: =SUM(AC21:AG21) -> -45079 | AK39: =SUM(AH21:AK21) -> -91528.5 | AO39: =SUM(AL21:AO21) -> -138466.2 | AT39: =SUM(AP21:AT21) -> -95920.17 | AX39: =SUM(AU21:AX21) -> -94841.2 | BC39: =SUM(AY21:BC21) -> -141455.31 | BG39: =SUM(BD21:BG21) -> -155291.53 | BK39: =SUM(BH21:BK21) -> -195526.03 | BO39: =SUM(BL21:BO21) -> -98602.9 | BT39: =SUM(BP21:BT21) -> -274488.78 | BX39: =SUM(BU21:BX21) -> -148656.01 | CB39: =SUM(BY21:CB21) -> -117488.77 | CG39: =SUM(CC21:CG21) -> -163656.01 | CK39: =SUM(CH21:CK21) -> 0
B40: Draw | X40: =SUM(U20:X20) -> 0 | AB40: =SUM(Y20:AB20) -> 0 | AG40: =SUM(AC20:AG20) -> -293633.88 | AK40: =SUM(AH20:AK20) -> -100000 | AO40: =SUM(AL20:AO20) -> -230000 | AT40: =SUM(AP20:AT20) -> -50000 | AX40: =SUM(AU20:AX20) -> -150785 | BC40: =SUM(AY20:BC20) -> -250000 | BG40: =SUM(BD20:BG20) -> 0 | BK40: =SUM(BH20:BK20) -> 0 | BO40: =SUM(BL20:BO20) -> -75000 | BT40: =SUM(BQ20:BT20) -> -210000 | BX40: =SUM(BU20:BX20) -> -1472779.1 | CB40: =SUM(BY20:CB20) -> -225000 | CG40: =SUM(CD20:CG20) -> -100000 | CK40: =SUM(CH20:CK20) -> 0.03
B41: Total Cash Out | X41: =SUM(X38:X40) -> -2330095.5 | AB41: =SUM(AB38:AB40) -> -1897573.8 | AG41: =SUM(AG38:AG40) -> -3063153.6 | AK41: =SUM(AK38:AK40) -> -2335400.5 | AO41: =SUM(AO38:AO40) -> -2230390.8 | AT41: =SUM(AT38:AT40) -> -2789745.4 | AX41: =SUM(AX38:AX40) -> -2486579.6 | BC41: =SUM(BC38:BC40) -> -4076522.2 | BG41: =SUM(BG38:BG40) -> -2522541.7 | BK41: =SUM(BK38:BK40) -> -2551710.9 | BO41: =SUM(BO38:BO40) -> -2789479.5 | BT41: =SUM(BT38:BT40) -> -3768040.1 | BX41: =SUM(BX38:BX40) -> -4370850.5 | CB41: =SUM(CB38:CB40) -> -2657871.6 | CG41: =SUM(CG38:CG40) -> -21668179 | CK41: =SUM(CK38:CK40) -> -2456908.7
AS43: =2.6*3 -> 7.8 | BH43: 816505.23
AL44: 996539.81 | BH44: 216858.25
AL45: 1512810.5 | BH45: 322839.18
AL46: 1206105.6
AL47: 465249.71 | BD47: Libertas Payments | BF47: 25 | BG47: 25 | BH47: 25 | BI47: 25 | BJ47: 25 | BK47: 25 | BL47: 25 | BM47: 25 | BN47: 25 | BO47: 25 | BP47: 25 | BQ47: 25 | BR47: 25 | BS47: 25 | BT47: 25 | BU47: 25 | BV47: 25 | BW47: 25 | BX47: 25 | BY47: 25 | BZ47: 25 | CA47: 25 | CB47: 25 | CC47: 25 | CD47: 25 | CE47: 25 | CF47: 25 | CG47: 25 | CH47: 25 | CI47: 25 | CJ47: 25 | CK47: 25
AL48: 835672.52 | BD48: Cumulative | BG48: =SUM(BF47:BG47) -> 50 | BH48: =SUM(BG48,BH47) -> 75 | BI48: =SUM(BH48,BI47) -> 100 | BJ48: =SUM(BI48,BJ47) -> 125 | BK48: =SUM(BJ48,BK47) -> 150 | BL48: =SUM(BK48,BL47) -> 175 | BM48: =SUM(BL48,BM47) -> 200 | BN48: =SUM(BM48,BN47) -> 225 | BO48: =SUM(BN48,BO47) -> 250 | ... CK48: =SUM(CJ48,CK47) -> 800
B49: Cash In | BD49: Remaining | BF49: =1200-BF47 -> 1175 | BG49: =1200-BG48 -> 1150 | BH49: =1200-BH48 -> 1125 | BI49: =1200-BI48 -> 1100 | BJ49: =1200-BJ48 -> 1075 | BK49: =1200-BK48 -> 1050 | BL49: =1200-BL48 -> 1025 | BM49: =1200-BM48 -> 1000 | BN49: =1200-BN48 -> 975 | ... CK49: =1200-CK48 -> 400
B50: Signed Contracts | BC50: =0.6*AY6+AZ6+BA6+BB6+BC6 -> 3742788.5 | BG50: =BD6+BE6+BF6+BG6 -> 1029021.2 | BK50: =BH6+BI6+BJ6+BK6+0.2*BL6 -> 1998192.9 | BO50: =0.8*BL6+BM6+BN6+BO6+0.6*BP6 -> 3867521 | BT50: =0.4*BP6+BQ6+BR6+BS6+BT6 -> 2521347.9 | BX50: =BU6+BV6+BW6+BX6+0.2*BY6 -> 2233410.8 | CB50: =0.8*BY6+BZ6+CA6+CB6+0.8*CC6 -> 2853500.3 | CG50: =0.2*CC6+CD6+CF6+CE6+CG6 -> 2668378.5 | CK50: =CH6+CI6+CJ6+CK6+0.4*CL6 -> 2553424.9 | CP50: =0.6*CL6+CM6+CN6+CO6+CP6 -> 4217621.5 | CT50: =CQ6+CR6+CS6+CT6 -> 3677818.5 | CX50: =CU6+CV6+CW6+CX6+0.6*CY6 -> 5073561.4
B51: Bookings | BC51: =0.6*AY7+AZ7+BA7+BB7+BC7 -> 0 | BG51: =BD7+BE7+BF7+BG7 -> 0 | BK51: =BH7+BI7+BJ7+BK7+0.2*BL7 -> 0 | BO51: =0.8*BL7+BM7+BN7+BO7+0.6*BP7 -> 0 | BT51: =0.4*BP7+BQ7+BR7+BS7+BT7 -> 0 | CB51: =0.8*BY7+BZ7+CA7+CB7+0.8*CC7 -> 0 | CG51: =0.2*CC7+CD7+CF7+CE7+CG7+0.4*CH7 -> 0 | CK51: =CH7+CI7+CJ7+CK7+0.4*CL7 -> 0 | CP51: =0.6*CL7+CM7+CN7+CO7+CP7 -> 0 | CT51: =CQ7+CR7+CS7+CT7 -> 0 | CX51: =CU7+CV7+CW7+CX7+0.6*CY7 -> 0
B52: External Funding | BC52: =0.6*AY8+AZ8+BA8+BB8+BC8 -> 0 | BG52: =BD8+BE8+BF8+BG8 -> 600000 | BK52: =BH8+BI8+BJ8+BK8+0.2*BL8 -> 800000 | BO52: =0.8*BL8+BM8+BN8+BO8+0.6*BP8 -> 0 | BT52: =0.4*BP8+BQ8+BR8+BS8+BT8 -> 0 | BX52: =BU8+BV8+BW8+BX8+0.2*BY8 -> 2700000 | CB52: =0.8*BY8+BZ8+CA8+CB8+0.8*CC8 -> 300000 | CG52: =0.2*CC8+CD8+CF8+CE8+CG8+0.4*CH8 -> 18094709 | CK52: =CH8+CI8+CJ8+CK8+0.4*CL8 -> 0 | CP52: =0.6*CL8+CM8+CN8+CO8+CP8 -> 0 | CT52: =CQ8+CR8+CS8+CT8 -> 418107 | CX52: =CU8+CV8+CW8+CX8+0.6*CY8 -> 0
B53: Total Cash In (Calendar-Aligned) | BC53: =BC50+BC51+BC52 -> 3742788.5 | BG53: =BG50+BG51+BG52 -> 1629021.2 | BK53: =BK50+BK51+BK52 -> 2798192.9 | BO53: =BO50+BO51+BO52 -> 3867521 | BT53: =BT50+BT51+BT52 -> 2521347.9 | BX53: =BX51+BX50+BX52 -> 4933410.8 | CB53: =CB50+CB51+CB52 -> 3153500.3 | CG53: =CG50+CG51+CG52 -> 20763087 | CK53: =CK50+CK51+CK52 -> 2553424.9 | CP53: =CP50+CP51+CP52 -> 4217621.5 | CT53: =CT50+CT51+CT52 -> 4095925.5 | CX53: =CX50+CX51+CX52 -> 5073561.4
BC58: =BC41+BC53 -> -333733.7 | BG58: =BG41+BG53 -> -893520.55 | BK58: =BK41+BK53 -> 246481.92 | BO58: =BO41+BO53 -> 1078041.6 | BT58: =BT41+BT53 -> -1246692.2

Sheet AR Aging Balance
A2: Week End Date | B2: Year | C2: Week | D2: Inovice Sent | E2: AR Collected | F2: End Balance
A3: 46024 | B3: 2026 | C3: 1 | D3: =SUMIFS('AR Aging 20260320'!$H:$H,'AR Aging 20260320'!$J:$J,$B3,'AR Aging 20260320'!$K:$K,$C3)+SUMIFS(Bookings!$E:$E,Bookings!$L:$L,$B3,Bookings!$K:$K,$C3) -> 300800 | E3: =SUMIFS('AR Aging 20260320'!$H:$H, 'AR Aging 20260320'!$N:$N,$C3,'AR Aging 20260320'!$M:$M,$B3)+SUMIFS(Bookings!$E:$E,Bookings!$P:$P,$B3,Bookings!$O:$O,$C3) -> 0 | F3: 0
A4: =A3+7 -> 46031 | B4: 2026 | C4: 2 | D4: =SUMIFS('AR Aging 20260320'!$H:$H,'AR Aging 20260320'!$J:$J,$B4,'AR Aging 20260320'!$K:$K,$C4)+SUMIFS(Bookings!$E:$E,Bookings!$L:$L,$B4,Bookings!$K:$K,$C4) -> 0 | E4: =SUMIFS('AR Aging 20260320'!$H:$H, 'AR Aging 20260320'!$N:$N,$C4,'AR Aging 20260320'!$M:$M,$B4)+SUMIFS(Bookings!$E:$E,Bookings!$P:$P,$B4,Bookings!$O:$O,$C4) -> 0 | F4: 0
A5: =A4+7 -> 46038 | B5: 2026 | C5: 3 | D5: =SUMIFS('AR Aging 20260320'!$H:$H,'AR Aging 20260320'!$J:$J,$B5,'AR Aging 20260320'!$K:$K,$C5)+SUMIFS(Bookings!$E:$E,Bookings!$L:$L,$B5,Bookings!$K:$K,$C5) -> 209760 | E5: =SUMIFS('AR Aging 20260320'!$H:$H, 'AR Aging 20260320'!$N:$N,$C5,'AR Aging 20260320'!$M:$M,$B5)+SUMIFS(Bookings!$E:$E,Bookings!$P:$P,$B5,Bookings!$O:$O,$C5) -> 297412.6 | F5: 0
A6: =A5+7 -> 46045 | B6: 2026 | C6: 4 | D6: =SUMIFS('AR Aging 20260320'!$H:$H,'AR Aging 20260320'!$J:$J,$B6,'AR Aging 20260320'!$K:$K,$C6)+SUMIFS(Bookings!$E:$E,Bookings!$L:$L,$B6,Bookings!$K:$K,$C6) -> 21592.9 | E6: =SUMIFS('AR Aging 20260320'!$H:$H, 'AR Aging 20260320'!$N:$N,$C6,'AR Aging 20260320'!$M:$M,$B6)+SUMIFS(Bookings!$E:$E,Bookings!$P:$P,$B6,Bookings!$O:$O,$C6) -> 0 | F6: 0
A7: =A6+7 -> 46052 | B7: 2026 | C7: 5 | D7: =SUMIFS('AR Aging 20260320'!$H:$H,'AR Aging 20260320'!$J:$J,$B7,'AR Aging 20260320'!$K:$K,$C7)+SUMIFS(Bookings!$E:$E,Bookings!$L:$L,$B7,Bookings!$K:$K,$C7) -> 419605 | E7: =SUMIFS('AR Aging 20260320'!$H:$H, 'AR Aging 20260320'!$N:$N,$C7,'AR Aging 20260320'!$M:$M,$B7)+SUMIFS(Bookings!$E:$E,Bookings!$P:$P,$B7,Bookings!$O:$O,$C7) -> 0 | F7: 0
A8: =A7+7 -> 46059 | B8: 2026 | C8: 6 | D8: =SUMIFS('AR Aging 20260320'!$H:$H,'AR Aging 20260320'!$J:$J,$B8,'AR Aging 20260320'!$K:$K,$C8)+SUMIFS(Bookings!$E:$E,Bookings!$L:$L,$B8,Bookings!$K:$K,$C8) -> 104761.6 | E8: =SUMIFS('AR Aging 20260320'!$H:$H, 'AR Aging 20260320'!$N:$N,$C8,'AR Aging 20260320'!$M:$M,$B8)+SUMIFS(Bookings!$E:$E,Bookings!$P:$P,$B8,Bookings!$O:$O,$C8) -> 0 | F8: 0
A9: =A8+7 -> 46066 | B9: 2026 | C9: 7 | D9: =SUMIFS('AR Aging 20260320'!$H:$H,'AR Aging 20260320'!$J:$J,$B9,'AR Aging 20260320'!$K:$K,$C9)+SUMIFS(Bookings!$E:$E,Bookings!$L:$L,$B9,Bookings!$K:$K,$C9) -> 0 | E9: =SUMIFS('AR Aging 20260320'!$H:$H, 'AR Aging 20260320'!$N:$N,$C9,'AR Aging 20260320'!$M:$M,$B9)+SUMIFS(Bookings!$E:$E,Bookings!$P:$P,$B9,Bookings!$O:$O,$C9) -> 272280 | F9: 0
A10: =A9+7 -> 46073 | B10: 2026 | C10: 8 | D10: =SUMIFS('AR Aging 20260320'!$H:$H,'AR Aging 20260320'!$J:$J,$B10,'AR Aging 20260320'!$K:$K,$C10)+SUMIFS(Bookings!$E:$E,Bookings!$L:$L,$B10,Bookings!$K:$K,$C10) -> 412451.4 | E10: =SUMIFS('AR Aging 20260320'!$H:$H, 'AR Aging 20260320'!$N:$N,$C10,'AR Aging 20260320'!$M:$M,$B10)+SUMIFS(Bookings!$E:$E,Bookings!$P:$P,$B10,Bookings!$O:$O,$C10) -> 33667.2 | F10: 0
A11: =A10+7 -> 46080 | B11: 2026 | C11: 9 | D11: =SUMIFS('AR Aging 20260320'!$H:$H,'AR Aging 20260320'!$J:$J,$B11,'AR Aging 20260320'!$K:$K,$C11)+SUMIFS(Bookings!$E:$E,Bookings!$L:$L,$B11,Bookings!$K:$K,$C11) -> 461827.26 | E11: =SUMIFS('AR Aging 20260320'!$H:$H, 'AR Aging 20260320'!$N:$N,$C11,'AR Aging 20260320'!$M:$M,$B11)+SUMIFS(Bookings!$E:$E,Bookings!$P:$P,$B11,Bookings!$O:$O,$C11) -> 209760
A12: =A11+7 -> 46087 | B12: 2026 | C12: 10 | D12: =SUMIFS('AR Aging 20260320'!$H:$H,'AR Aging 20260320'!$J:$J,$B12,'AR Aging 20260320'!$K:$K,$C12)+SUMIFS(Bookings!$E:$E,Bookings!$L:$L,$B12,Bookings!$K:$K,$C12) -> 222163.5 | E12: =SUMIFS('AR Aging 20260320'!$H:$H, 'AR Aging 20260320'!$N:$N,$C12,'AR Aging 20260320'!$M:$M,$B12)+SUMIFS(Bookings!$E:$E,Bookings!$P:$P,$B12,Bookings!$O:$O,$C12) -> 0
A13: =A12+7 -> 46094 | B13: 2026 | C13: 11 | D13: =SUMIFS('AR Aging 20260320'!$H:$H,'AR Aging 20260320'!$J:$J,$B13,'AR Aging 20260320'!$K:$K,$C13)+SUMIFS(Bookings!$E:$E,Bookings!$L:$L,$B13,Bookings!$K:$K,$C13) -> 1128000 | E13: =SUMIFS('AR Aging 20260320'!$H:$H, 'AR Aging 20260320'!$N:$N,$C13,'AR Aging 20260320'!$M:$M,$B13)+SUMIFS(Bookings!$E:$E,Bookings!$P:$P,$B13,Bookings!$O:$O,$C13) -> 4315.72
A14: =A13+7 -> 46101 | B14: 2026 | C14: 12 | D14: =SUMIFS('AR Aging 20260320'!$H:$H,'AR Aging 20260320'!$J:$J,$B14,'AR Aging 20260320'!$K:$K,$C14)+SUMIFS(Bookings!$E:$E,Bookings!$L:$L,$B14,Bookings!$K:$K,$C14) -> 347953 | E14: =SUMIFS('AR Aging 20260320'!$H:$H, 'AR Aging 20260320'!$N:$N,$C14,'AR Aging 20260320'!$M:$M,$B14)+SUMIFS(Bookings!$E:$E,Bookings!$P:$P,$B14,Bookings!$O:$O,$C14) -> 80420
A15: =A14+7 -> 46108 | B15: 2026 | C15: 13 | D15: =SUMIFS('AR Aging 20260320'!$H:$H,'AR Aging 20260320'!$J:$J,$B15,'AR Aging 20260320'!$K:$K,$C15)+SUMIFS(Bookings!$E:$E,Bookings!$L:$L,$B15,Bookings!$K:$K,$C15) -> 1036710.3 | E15: =SUMIFS('AR Aging 20260320'!$H:$H, 'AR Aging 20260320'!$N:$N,$C15,'AR Aging 20260320'!$M:$M,$B15)+SUMIFS(Bookings!$E:$E,Bookings!$P:$P,$B15,Bookings!$O:$O,$C15) -> 172530
A16: =A15+7 -> 46115 | B16: 2026 | C16: 14 | D16: =SUMIFS('AR Aging 20260320'!$H:$H,'AR Aging 20260320'!$J:$J,$B16,'AR Aging 20260320'!$K:$K,$C16)+SUMIFS(Bookings!$E:$E,Bookings!$L:$L,$B16,Bookings!$K:$K,$C16) -> 1904566.7 | E16: =SUMIFS('AR Aging 20260320'!$H:$H, 'AR Aging 20260320'!$N:$N,$C16,'AR Aging 20260320'!$M:$M,$B16)+SUMIFS(Bookings!$E:$E,Bookings!$P:$P,$B16,Bookings!$O:$O,$C16) -> 368726.4 | F16: 9461543
A17: =A16+7 -> 46122 | B17: 2026 | C17: 15 | D17: =SUMIFS('AR Aging 20260320'!$H:$H,'AR Aging 20260320'!$J:$J,$B17,'AR Aging 20260320'!$K:$K,$C17)+SUMIFS(Bookings!$E:$E,Bookings!$L:$L,$B17,Bookings!$K:$K,$C17) -> 0 | E17: =SUMIFS('AR Aging 20260320'!$H:$H, 'AR Aging 20260320'!$N:$N,$C17,'AR Aging 20260320'!$M:$M,$B17)+SUMIFS(Bookings!$E:$E,Bookings!$P:$P,$B17,Bookings!$O:$O,$C17) -> 41126.66 | F17: =F16+D17-E17 -> 9420416.3
A18: =A17+7 -> 46129 | B18: 2026 | C18: 16 | D18: =SUMIFS('AR Aging 20260320'!$H:$H,'AR Aging 20260320'!$J:$J,$B18,'AR Aging 20260320'!$K:$K,$C18)+SUMIFS(Bookings!$E:$E,Bookings!$L:$L,$B18,Bookings!$K:$K,$C18) -> 946169.81 | E18: =SUMIFS('AR Aging 20260320'!$H:$H, 'AR Aging 20260320'!$N:$N,$C18,'AR Aging 20260320'!$M:$M,$B18)+SUMIFS(Bookings!$E:$E,Bookings!$P:$P,$B18,Bookings!$O:$O,$C18) -> 285706.8 | F18: =F17+D18-E18 -> 10080879
A19: =A18+7 -> 46136 | B19: 2026 | C19: 17 | D19: =SUMIFS('AR Aging 20260320'!$H:$H,'AR Aging 20260320'!$J:$J,$B19,'AR Aging 20260320'!$K:$K,$C19)+SUMIFS(Bookings!$E:$E,Bookings!$L:$L,$B19,Bookings!$K:$K,$C19) -> 267244.5 | E19: =SUMIFS('AR Aging 20260320'!$H:$H, 'AR Aging 20260320'!$N:$N,$C19,'AR Aging 20260320'!$M:$M,$B19)+SUMIFS(Bookings!$E:$E,Bookings!$P:$P,$B19,Bookings!$O:$O,$C19) -> 11000 | F19: =F18+D19-E19 -> 10337124
A20: =A19+7 -> 46143 | B20: 2026 | C20: 18 | D20: =SUMIFS('AR Aging 20260320'!$H:$H,'AR Aging 20260320'!$J:$J,$B20,'AR Aging 20260320'!$K:$K,$C20)+SUMIFS(Bookings!$E:$E,Bookings!$L:$L,$B20,Bookings!$K:$K,$C20) -> 5692757.1 | E20: =SUMIFS('AR Aging 20260320'!$H:$H, 'AR Aging 20260320'!$N:$N,$C20,'AR Aging 20260320'!$M:$M,$B20)+SUMIFS(Bookings!$E:$E,Bookings!$P:$P,$B20,Bookings!$O:$O,$C20) -> 430690.5 | F20: =F19+D20-E20 -> 15599190
A21: =A20+7 -> 46150 | B21: 2026 | C21: 19 | D21: =SUMIFS('AR Aging 20260320'!$H:$H,'AR Aging 20260320'!$J:$J,$B21,'AR Aging 20260320'!$K:$K,$C21)+SUMIFS(Bookings!$E:$E,Bookings!$L:$L,$B21,Bookings!$K:$K,$C21) -> 0 | E21: =SUMIFS('AR Aging 20260320'!$H:$H, 'AR Aging 20260320'!$N:$N,$C21,'AR Aging 20260320'!$M:$M,$B21)+SUMIFS(Bookings!$E:$E,Bookings!$P:$P,$B21,Bookings!$O:$O,$C21) -> 1398444.2 | F21: =F20+D21-E21 -> 14200746
A22: =A21+7 -> 46157 | B22: 2026 | C22: 20 | D22: =SUMIFS('AR Aging 20260320'!$H:$H,'AR Aging 20260320'!$J:$J,$B22,'AR Aging 20260320'!$K:$K,$C22)+SUMIFS(Bookings!$E:$E,Bookings!$L:$L,$B22,Bookings!$K:$K,$C22) -> 0 | E22: =SUMIFS('AR Aging 20260320'!$H:$H, 'AR Aging 20260320'!$N:$N,$C22,'AR Aging 20260320'!$M:$M,$B22)+SUMIFS(Bookings!$E:$E,Bookings!$P:$P,$B22,Bookings!$O:$O,$C22) -> 981511.67 | F22: =F21+D22-E22 -> 13219235
A23: =A22+7 -> 46164 | B23: 2026 | C23: 21 | D23: =SUMIFS('AR Aging 20260320'!$H:$H,'AR Aging 20260320'!$J:$J,$B23,'AR Aging 20260320'!$K:$K,$C23)+SUMIFS(Bookings!$E:$E,Bookings!$L:$L,$B23,Bookings!$K:$K,$C23) -> 0 | E23: =SUMIFS('AR Aging 20260320'!$H:$H, 'AR Aging 20260320'!$N:$N,$C23,'AR Aging 20260320'!$M:$M,$B23)+SUMIFS(Bookings!$E:$E,Bookings!$P:$P,$B23,Bookings!$O:$O,$C23) -> 0 | F23: =F22+D23-E23 -> 13219235
A24: =A23+7 -> 46171 | B24: 2026 | C24: 22 | D24: =SUMIFS('AR Aging 20260320'!$H:$H,'AR Aging 20260320'!$J:$J,$B24,'AR Aging 20260320'!$K:$K,$C24)+SUMIFS(Bookings!$E:$E,Bookings!$L:$L,$B24,Bookings!$K:$K,$C24) -> 0 | E24: =SUMIFS('AR Aging 20260320'!$H:$H, 'AR Aging 20260320'!$N:$N,$C24,'AR Aging 20260320'!$M:$M,$B24)+SUMIFS(Bookings!$E:$E,Bookings!$P:$P,$B24,Bookings!$O:$O,$C24) -> 2522706.8 | F24: =F23+D24-E24 -> 10696528
A25: =A24+7 -> 46178 | B25: 2026 | C25: 23 | D25: =SUMIFS('AR Aging 20260320'!$H:$H,'AR Aging 20260320'!$J:$J,$B25,'AR Aging 20260320'!$K:$K,$C25)+SUMIFS(Bookings!$E:$E,Bookings!$L:$L,$B25,Bookings!$K:$K,$C25) -> 6768980.2 | E25: =SUMIFS('AR Aging 20260320'!$H:$H, 'AR Aging 20260320'!$N:$N,$C25,'AR Aging 20260320'!$M:$M,$B25)+SUMIFS(Bookings!$E:$E,Bookings!$P:$P,$B25,Bookings!$O:$O,$C25) -> 177216.75 | F25: =F24+D25-E25 -> 17288291
A26: =A25+7 -> 46185 | B26: 2026 | C26: 24 | D26: =SUMIFS('AR Aging 20260320'!$H:$H,'AR Aging 20260320'!$J:$J,$B26,'AR Aging 20260320'!$K:$K,$C26)+SUMIFS(Bookings!$E:$E,Bookings!$L:$L,$B26,Bookings!$K:$K,$C26) -> 0 | E26: =SUMIFS('AR Aging 20260320'!$H:$H, 'AR Aging 20260320'!$N:$N,$C26,'AR Aging 20260320'!$M:$M,$B26)+SUMIFS(Bookings!$E:$E,Bookings!$P:$P,$B26,Bookings!$O:$O,$C26) -> 2735404.4 | F26: =F25+D26-E26 -> 14552887
A27: =A26+7 -> 46192 | B27: 2026 | C27: 25 | D27: =SUMIFS('AR Aging 20260320'!$H:$H,'AR Aging 20260320'!$J:$J,$B27,'AR Aging 20260320'!$K:$K,$C27)+SUMIFS(Bookings!$E:$E,Bookings!$L:$L,$B27,Bookings!$K:$K,$C27) -> 0 | E27: =SUMIFS('AR Aging 20260320'!$H:$H, 'AR Aging 20260320'!$N:$N,$C27,'AR Aging 20260320'!$M:$M,$B27)+SUMIFS(Bookings!$E:$E,Bookings!$P:$P,$B27,Bookings!$O:$O,$C27) -> 49761.6 | F27: =F26+D27-E27 -> 14503125
A28: =A27+7 -> 46199 | B28: 2026 | C28: 26 | D28: =SUMIFS('AR Aging 20260320'!$H:$H,'AR Aging 20260320'!$J:$J,$B28,'AR Aging 20260320'!$K:$K,$C28)+SUMIFS(Bookings!$E:$E,Bookings!$L:$L,$B28,Bookings!$K:$K,$C28) -> 0 | E28: =SUMIFS('AR Aging 20260320'!$H:$H, 'AR Aging 20260320'!$N:$N,$C28,'AR Aging 20260320'!$M:$M,$B28)+SUMIFS(Bookings!$E:$E,Bookings!$P:$P,$B28,Bookings!$O:$O,$C28) -> 0 | F28: =F27+D28-E28 -> 14503125
... A107: =A106+7 -> 46752 | B107: 2027 | C107: 53 | D107: =SUMIFS('AR Aging 20260320'!$H:$H,'AR Aging 20260320'!$J:$J,$B107,'AR Aging 20260320'!$K:$K,$C107)+SUMIFS(Bookings!$E:$E,Bookings!$L:$L,$B107,Bookings!$K:$K,$C107) -> 0 | E107: =SUMIFS('AR Aging 20260320'!$H:$H, 'AR Aging 20260320'!$N:$N,$C107,'AR Aging 20260320'!$M:$M,$B107)+SUMIFS(Bookings!$E:$E,Bookings!$P:$P,$B107,Bookings!$O:$O,$C107) -> 0 | F107: =F106+D107-E107 -> 1865056
D111: =SUM(D3:D109) -> 54287218 | E111: =SUM(E3:E32) -> 15762212
D112: =D111-'AR Aging 20260320'!H4-Bookings!E1 -> -2465407.3 | E112: =SUM(Bookings!$E$1,'AR Aging 20260320'!$H$4)-'AR Aging Balance'!E111 -> 40990414

Sheet Bookings
E1: =SUBTOTAL(9,$E$3:$E$4919) -> 30000000 | I1: Check | J1: =SUM($E$3:$E$4920)-SUM($W:$W) -> 0 | N1: # Weeks Past Due | O1: ='AR Aging 20260320'!$N$2 -> 2 | R1: Receivables Summary
B2: Est Close Date | C2: Customer | D2: Deal Name | E2: Inv Amt | F2: Inv Date | G2: Payment Terms | H2: Due Date | I2: Bookings Month | J2: Bookings Year | K2: Inv Week | L2: Inv Year | M2: Due Week # | N2: Due Year | O2: Expected Pmt Wk # | P2: Expcted Pmt Year | R2: Year | S2: Wk # | T2: Wk Ending | U2: Est. Amt | V2: Adj | W2: Amt for Fcst
R3: 2026 | S3: 1 | T3: 46024 | U3: =SUMIFS($E:$E,$O:$O,$S3,$P:$P,$R3) -> 0 | W3: =SUM(U3:V3) -> 0
R4: 2026 | S4: 2 | T4: =T3+7 -> 46031 | U4: =SUMIFS($E:$E,$O:$O,$S4,$P:$P,$R4) -> 0 | W4: =SUM(U4:V4) -> 0
R5: 2026 | S5: 3 | T5: =T4+7 -> 46038 | U5: =SUMIFS($E:$E,$O:$O,$S5,$P:$P,$R5) -> 0 | W5: =SUM(U5:V5) -> 0
R6: 2026 | S6: 4 | T6: =T5+7 -> 46045 | U6: =SUMIFS($E:$E,$O:$O,$S6,$P:$P,$R6) -> 0 | W6: =SUM(U6:V6) -> 0
R7: 2026 | S7: 5 | T7: =T6+7 -> 46052 | U7: =SUMIFS($E:$E,$O:$O,$S7,$P:$P,$R7) -> 0 | W7: =SUM(U7:V7) -> 0
B8: 46142 | C8: Q2 Bookings Plug ($15M) -$5M Apr, $5M May, $5M Jun | E8: 1000000 | F8: 46142 | G8: 45 | H8: =F8+G8 -> 46187 | I8: =MONTH(B8) -> 4 | J8: =YEAR(B8) -> 2026 | K8: =WEEKNUM($F8) -> 18 | L8: =YEAR($F8) -> 2026 | M8: =WEEKNUM($H8) -> 25 | N8: =YEAR(H8) -> 2026 | O8: =IF(ISBLANK($B8),"",IF($M8<51,$M8+$O$1,$M8-52+$O$1)) -> 27 | P8: =IF(ISBLANK($B8),"",IF($M8<51,YEAR($H8),YEAR($H8)+1)) -> 2026 | R8: 2026 | S8: 6 | T8: =T7+7 -> 46059 | U8: =SUMIFS($E:$E,$O:$O,$S8,$P:$P,$R8) -> 0 | W8: =SUM(U8:V8) -> 0
B9: 46142 | C9: Q2 Bookings Plug ($15M) -$5M Apr, $5M May, $5M Jun | E9: 1000000 | F9: 46173 | G9: 45 | H9: =F9+G9 -> 46218 | I9: =MONTH(B9) -> 4 | J9: =YEAR(B9) -> 2026 | K9: =WEEKNUM($F9) -> 23 | L9: =YEAR($F9) -> 2026 | M9: =WEEKNUM($H9) -> 29 | N9: =YEAR(H9) -> 2026 | O9: =IF(ISBLANK($B9),"",IF($M9<51,$M9+$O$1,$M9-52+$O$1)) -> 31 | P9: =IF(ISBLANK($B9),"",IF($M9<51,YEAR($H9),YEAR($H9)+1)) -> 2026 | R9: 2026 | S9: 7 | T9: =T8+7 -> 46066 | U9: =SUMIFS($E:$E,$O:$O,$S9,$P:$P,$R9) -> 0 | W9: =SUM(U9:V9) -> 0
B10: 46142 | C10: Q2 Bookings Plug ($15M) -$5M Apr, $5M May, $5M Jun | E10: 1000000 | F10: 46203 | G10: 45 | H10: =F10+G10 -> 46248 | I10: =MONTH(B10) -> 4 | J10: =YEAR(B10) -> 2026 | K10: =WEEKNUM($F10) -> 27 | L10: =YEAR($F10) -> 2026 | M10: =WEEKNUM($H10) -> 33 | N10: =YEAR(H10) -> 2026 | O10: =IF(ISBLANK($B10),"",IF($M10<51,$M10+$O$1,$M10-52+$O$1)) -> 35 | P10: =IF(ISBLANK($B10),"",IF($M10<51,YEAR($H10),YEAR($H10)+1)) -> 2026 | R10: 2026 | S10: 8 | T10: =T9+7 -> 46073 | U10: =SUMIFS($E:$E,$O:$O,$S10,$P:$P,$R10) -> 0 | W10: =SUM(U10:V10) -> 0
B11: 46142 | C11: Q2 Bookings Plug ($15M) -$5M Apr, $5M May, $5M Jun | E11: 1000000 | F11: 46234 | G11: 45 | H11: =F11+G11 -> 46279 | I11: =MONTH(B11) -> 4 | J11: =YEAR(B11) -> 2026 | K11: =WEEKNUM($F11) -> 31 | L11: =YEAR($F11) -> 2026 | M11: =WEEKNUM($H11) -> 38 | N11: =YEAR(H11) -> 2026 | O11: =IF(ISBLANK($B11),"",IF($M11<51,$M11+$O$1,$M11-52+$O$1)) -> 40 | P11: =IF(ISBLANK($B11),"",IF($M11<51,YEAR($H11),YEAR($H11)+1)) -> 2026 | R11: 2026 | S11: 9 | T11: =T10+7 -> 46080 | U11: =SUMIFS($E:$E,$O:$O,$S11,$P:$P,$R11) -> 0 | W11: =SUM(U11:V11) -> 0
B12: 46142 | C12: Q2 Bookings Plug ($15M) -$5M Apr, $5M May, $5M Jun | E12: 1000000 | F12: 46265 | G12: 45 | H12: =F12+G12 -> 46310 | I12: =MONTH(B12) -> 4 | J12: =YEAR(B12) -> 2026 | K12: =WEEKNUM($F12) -> 36 | L12: =YEAR($F12) -> 2026 | M12: =WEEKNUM($H12) -> 42 | N12: =YEAR(H12) -> 2026 | O12: =IF(ISBLANK($B12),"",IF($M12<51,$M12+$O$1,$M12-52+$O$1)) -> 44 | P12: =IF(ISBLANK($B12),"",IF($M12<51,YEAR($H12),YEAR($H12)+1)) -> 2026 | R12: 2026 | S12: 10 | T12: =T11+7 -> 46087 | U12: =SUMIFS($E:$E,$O:$O,$S12,$P:$P,$R12) -> 0 | W12: =SUM(U12:V12) -> 0
B13: 46173 | C13: Q2 Bookings Plug ($15M) -$5M Apr, $5M May, $5M Jun | E13: 1000000 | F13: 46173 | G13: 45 | H13: =F13+G13 -> 46218 | I13: =MONTH(B13) -> 5 | J13: =YEAR(B13) -> 2026 | K13: =WEEKNUM($F13) -> 23 | L13: =YEAR($F13) -> 2026 | M13: =WEEKNUM($H13) -> 29 | N13: =YEAR(H13) -> 2026 | O13: =IF(ISBLANK($B13),"",IF($M13<51,$M13+$O$1,$M13-52+$O$1)) -> 31 | P13: =IF(ISBLANK($B13),"",IF($M13<51,YEAR($H13),YEAR($H13)+1)) -> 2026 | R13: 2026 | S13: 11 | T13: =T12+7 -> 46094 | U13: =SUMIFS($E:$E,$O:$O,$S13,$P:$P,$R13) -> 0 | W13: =SUM(U13:V13) -> 0
B14: 46173 | C14: Q2 Bookings Plug ($15M) -$5M Apr, $5M May, $5M Jun | E14: 1000000 | F14: 46203 | G14: 45 | H14: =F14+G14 -> 46248 | I14: =MONTH(B14) -> 5 | J14: =YEAR(B14) -> 2026 | K14: =WEEKNUM($F14) -> 27 | L14: =YEAR($F14) -> 2026 | M14: =WEEKNUM($H14) -> 33 | N14: =YEAR(H14) -> 2026 | O14: =IF(ISBLANK($B14),"",IF($M14<51,$M14+$O$1,$M14-52+$O$1)) -> 35 | P14: =IF(ISBLANK($B14),"",IF($M14<51,YEAR($H14),YEAR($H14)+1)) -> 2026 | R14: 2026 | S14: 12 | T14: =T13+7 -> 46101 | U14: =SUMIFS($E:$E,$O:$O,$S14,$P:$P,$R14) -> 0 | W14: =SUM(U14:V14) -> 0
B15: 46173 | C15: Q2 Bookings Plug ($15M) -$5M Apr, $5M May, $5M Jun | E15: 1000000 | F15: 46234 | G15: 45 | H15: =F15+G15 -> 46279 | I15: =MONTH(B15) -> 5 | J15: =YEAR(B15) -> 2026 | K15: =WEEKNUM($F15) -> 31 | L15: =YEAR($F15) -> 2026 | M15: =WEEKNUM($H15) -> 38 | N15: =YEAR(H15) -> 2026 | O15: =IF(ISBLANK($B15),"",IF($M15<51,$M15+$O$1,$M15-52+$O$1)) -> 40 | P15: =IF(ISBLANK($B15),"",IF($M15<51,YEAR($H15),YEAR($H15)+1)) -> 2026 | R15: 2026 | S15: 13 | T15: =T14+7 -> 46108 | U15: =SUMIFS($E:$E,$O:$O,$S15,$P:$P,$R15) -> 0 | W15: =SUM(U15:V15) -> 0
B16: 46173 | C16: Q2 Bookings Plug ($15M) -$5M Apr, $5M May, $5M Jun | E16: 1000000 | F16: 46265 | G16: 45 | H16: =F16+G16 -> 46310 | I16: =MONTH(B16) -> 5 | J16: =YEAR(B16) -> 2026 | K16: =WEEKNUM($F16) -> 36 | L16: =YEAR($F16) -> 2026 | M16: =WEEKNUM($H16) -> 42 | N16: =YEAR(H16) -> 2026 | O16: =IF(ISBLANK($B16),"",IF($M16<51,$M16+$O$1,$M16-52+$O$1)) -> 44 | P16: =IF(ISBLANK($B16),"",IF($M16<51,YEAR($H16),YEAR($H16)+1)) -> 2026 | R16: 2026 | S16: 14 | T16: =T15+7 -> 46115 | U16: =SUMIFS($E:$E,$O:$O,$S16,$P:$P,$R16) -> 0 | W16: =SUM(U16:V16) -> 0
B17: 46173 | C17: Q2 Bookings Plug ($15M) -$5M Apr, $5M May, $5M Jun | E17: 1000000 | F17: 46295 | G17: 45 | H17: =F17+G17 -> 46340 | I17: =MONTH(B17) -> 5 | J17: =YEAR(B17) -> 2026 | K17: =WEEKNUM($F17) -> 40 | L17: =YEAR($F17) -> 2026 | M17: =WEEKNUM($H17) -> 46 | N17: =YEAR(H17) -> 2026 | O17: =IF(ISBLANK($B17),"",IF($M17<51,$M17+$O$1,$M17-52+$O$1)) -> 48 | P17: =IF(ISBLANK($B17),"",IF($M17<51,YEAR($H17),YEAR($H17)+1)) -> 2026 | R17: 2026 | S17: 15 | T17: =T16+7 -> 46122 | U17: =SUMIFS($E:$E,$O:$O,$S17,$P:$P,$R17) -> 0 | W17: =SUM(U17:V17) -> 0
B18: 46203 | C18: Q2 Bookings Plug ($15M) -$5M Apr, $5M May, $5M Jun | E18: 1000000 | F18: 46203 | G18: 45 | H18: =F18+G18 -> 46248 | I18: =MONTH(B18) -> 6 | J18: =YEAR(B18) -> 2026 | K18: =WEEKNUM($F18) -> 27 | L18: =YEAR($F18) -> 2026 | M18: =WEEKNUM($H18) -> 33 | N18: =YEAR(H18) -> 2026 | O18: =IF(ISBLANK($B18),"",IF($M18<51,$M18+$O$1,$M18-52+$O$1)) -> 35 | P18: =IF(ISBLANK($B18),"",IF($M18<51,YEAR($H18),YEAR($H18)+1)) -> 2026 | R18: 2026 | S18: 16 | T18: =T17+7 -> 46129 | U18: =SUMIFS($E:$E,$O:$O,$S18,$P:$P,$R18) -> 0 | W18: =SUM(U18:V18) -> 0
B19: 46203 | C19: Q2 Bookings Plug ($15M) -$5M Apr, $5M May, $5M Jun | E19: 1000000 | F19: 46234 | G19: 45 | H19: =F19+G19 -> 46279 | I19: =MONTH(B19) -> 6 | J19: =YEAR(B19) -> 2026 | K19: =WEEKNUM($F19) -> 31 | L19: =YEAR($F19) -> 2026 | M19: =WEEKNUM($H19) -> 38 | N19: =YEAR(H19) -> 2026 | O19: =IF(ISBLANK($B19),"",IF($M19<51,$M19+$O$1,$M19-52+$O$1)) -> 40 | P19: =IF(ISBLANK($B19),"",IF($M19<51,YEAR($H19),YEAR($H19)+1)) -> 2026 | R19: 2026 | S19: 17 | T19: =T18+7 -> 46136 | U19: =SUMIFS($E:$E,$O:$O,$S19,$P:$P,$R19) -> 0 | W19: =SUM(U19:V19) -> 0
... B26: 46234 | C26: Q3 Bookings Plug ($15M) - $5M July, $5M Aug, $5M Sep | E26: 1000000 | F26: 46326 | G26: 45 | H26: =F26+G26 -> 46371 | I26: =MONTH(B26) -> 7 | J26: =YEAR(B26) -> 2026 | K26: =WEEKNUM($F26) -> 44 | L26: =YEAR($F26) -> 2026 | M26: =WEEKNUM($H26) -> 51 | N26: =YEAR(H26) -> 2026 | O26: =IF(ISBLANK($B26),"",IF($M26<51,$M26+$O$1,$M26-52+$O$1)) -> 1 | P26: =IF(ISBLANK($B26),"",IF($M26<51,YEAR($H26),YEAR($H26)+1)) -> 2027 | R26: 2026 | S26: 24 | T26: =T25+7 -> 46185 | U26: =SUMIFS($E:$E,$O:$O,$S26,$P:$P,$R26) -> 0 | W26: =SUM(U26:V26) -> 0
B27: 46234 | C27: Q3 Bookings Plug ($15M) - $5M July, $5M Aug, $5M Sep | E27: 1000000 | F27: 46356 | G27: 45 | H27: 46402 | I27: =MONTH(B27) -> 7 | J27: =YEAR(B27) -> 2026 | K27: =WEEKNUM($F27) -> 49 | L27: =YEAR($F27) -> 2026 | M27: =WEEKNUM($H27) -> 3 | N27: =YEAR(H27) -> 2027 | O27: =IF(ISBLANK($B27),"",IF($M27<51,$M27+$O$1,$M27-52+$O$1)) -> 5 | P27: =IF(ISBLANK($B27),"",IF($M27<51,YEAR($H27),YEAR($H27)+1)) -> 2027 | R27: 2026 | S27: 25 | T27: =T26+7 -> 46192 | U27: =SUMIFS($E:$E,$O:$O,$S27,$P:$P,$R27) -> 0 | W27: =SUM(U27:V27) -> 0
B28: 46265 | C28: Q3 Bookings Plug ($15M) - $5M July, $5M Aug, $5M Sep | E28: 1000000 | F28: 46265 | G28: 45 | H28: =F28+G28 -> 46310 | I28: =MONTH(B28) -> 8 | J28: =YEAR(B28) -> 2026 | K28: =WEEKNUM($F28) -> 36 | L28: =YEAR($F28) -> 2026 | M28: =WEEKNUM($H28) -> 42 | N28: =YEAR(H28) -> 2026 | O28: =IF(ISBLANK($B28),"",IF($M28<51,$M28+$O$1,$M28-52+$O$1)) -> 44 | P28: =IF(ISBLANK($B28),"",IF($M28<51,YEAR($H28),YEAR($H28)+1)) -> 2026 | R28: 2026 | S28: 26 | T28: =T27+7 -> 46199 | U28: =SUMIFS($E:$E,$O:$O,$S28,$P:$P,$R28) -> 0 | W28: =SUM(U28:V28) -> 0
B29: 46265 | C29: Q3 Bookings Plug ($15M) - $5M July, $5M Aug, $5M Sep | E29: 1000000 | F29: 46295 | G29: 45 | H29: =F29+G29 -> 46340 | I29: =MONTH(B29) -> 8 | J29: =YEAR(B29) -> 2026 | K29: =WEEKNUM($F29) -> 40 | L29: =YEAR($F29) -> 2026 | M29: =WEEKNUM($H29) -> 46 | N29: =YEAR(H29) -> 2026 | O29: =IF(ISBLANK($B29),"",IF($M29<51,$M29+$O$1,$M29-52+$O$1)) -> 48 | P29: =IF(ISBLANK($B29),"",IF($M29<51,YEAR($H29),YEAR($H29)+1)) -> 2026 | R29: 2026 | S29: 27 | T29: =T28+7 -> 46206 | U29: =SUMIFS($E:$E,$O:$O,$S29,$P:$P,$R29) -> 1000000 | W29: =SUM(U29:V29) -> 1000000
B30: 46265 | C30: Q3 Bookings Plug ($15M) - $5M July, $5M Aug, $5M Sep | E30: 1000000 | F30: 46326 | G30: 45 | H30: =F30+G30 -> 46371 | I30: =MONTH(B30) -> 8 | J30: =YEAR(B30) -> 2026 | K30: =WEEKNUM($F30) -> 44 | L30: =YEAR($F30) -> 2026 | M30: =WEEKNUM($H30) -> 51 | N30: =YEAR(H30) -> 2026 | O30: =IF(ISBLANK($B30),"",IF($M30<51,$M30+$O$1,$M30-52+$O$1)) -> 1 | P30: =IF(ISBLANK($B30),"",IF($M30<51,YEAR($H30),YEAR($H30)+1)) -> 2027 | R30: 2026 | S30: 28 | T30: =T29+7 -> 46213 | U30: =SUMIFS($E:$E,$O:$O,$S30,$P:$P,$R30) -> 0 | W30: =SUM(U30:V30) -> 0
B31: 46265 | C31: Q3 Bookings Plug ($15M) - $5M July, $5M Aug, $5M Sep | E31: 1000000 | F31: 46356 | G31: 45 | H31: 46402 | I31: =MONTH(B31) -> 8 | J31: =YEAR(B31) -> 2026 | K31: =WEEKNUM($F31) -> 49 | L31: =YEAR($F31) -> 2026 | M31: =WEEKNUM($H31) -> 3 | N31: =YEAR(H31) -> 2027 | O31: =IF(ISBLANK($B31),"",IF($M31<51,$M31+$O$1,$M31-52+$O$1)) -> 5 | P31: =IF(ISBLANK($B31),"",IF($M31<51,YEAR($H31),YEAR($H31)+1)) -> 2027 | R31: 2026 | S31: 29 | T31: =T30+7 -> 46220 | U31: =SUMIFS($E:$E,$O:$O,$S31,$P:$P,$R31) -> 0 | W31: =SUM(U31:V31) -> 0
B32: 46265 | C32: Q3 Bookings Plug ($15M) - $5M July, $5M Aug, $5M Sep | E32: 1000000 | F32: 46387 | G32: 45 | H32: 46432 | I32: =MONTH(B32) -> 8 | J32: =YEAR(B32) -> 2026 | K32: =WEEKNUM($F32) -> 53 | L32: =YEAR($F32) -> 2026 | M32: =WEEKNUM($H32) -> 8 | N32: =YEAR(H32) -> 2027 | O32: =IF(ISBLANK($B32),"",IF($M32<51,$M32+$O$1,$M32-52+$O$1)) -> 10 | P32: =IF(ISBLANK($B32),"",IF($M32<51,YEAR($H32),YEAR($H32)+1)) -> 2027 | R32: 2026 | S32: 30 | T32: =T31+7 -> 46227 | U32: =SUMIFS($E:$E,$O:$O,$S32,$P:$P,$R32) -> 0 | W32: =SUM(U32:V32) -> 0
B33: 46295 | C33: Q3 Bookings Plug ($15M) - $5M July, $5M Aug, $5M Sep | E33: 1000000 | F33: 46295 | G33: 45 | H33: =F33+G33 -> 46340 | I33: =MONTH(B33) -> 9 | J33: =YEAR(B33) -> 2026 | K33: =WEEKNUM($F33) -> 40 | L33: =YEAR($F33) -> 2026 | M33: =WEEKNUM($H33) -> 46 | N33: =YEAR(H33) -> 2026 | O33: =IF(ISBLANK($B33),"",IF($M33<51,$M33+$O$1,$M33-52+$O$1)) -> 48 | P33: =IF(ISBLANK($B33),"",IF($M33<51,YEAR($H33),YEAR($H33)+1)) -> 2026 | R33: 2026 | S33: 31 | T33: =T32+7 -> 46234 | U33: =SUMIFS($E:$E,$O:$O,$S33,$P:$P,$R33) -> 2000000 | W33: =SUM(U33:V33) -> 2000000
B34: 46295 | C34: Q3 Bookings Plug ($15M) - $5M July, $5M Aug, $5M Sep | E34: 1000000 | F34: 46326 | G34: 45 | H34: =F34+G34 -> 46371 | I34: =MONTH(B34) -> 9 | J34: =YEAR(B34) -> 2026 | K34: =WEEKNUM($F34) -> 44 | L34: =YEAR($F34) -> 2026 | M34: =WEEKNUM($H34) -> 51 | N34: =YEAR(H34) -> 2026 | O34: =IF(ISBLANK($B34),"",IF($M34<51,$M34+$O$1,$M34-52+$O$1)) -> 1 | P34: =IF(ISBLANK($B34),"",IF($M34<51,YEAR($H34),YEAR($H34)+1)) -> 2027 | R34: 2026 | S34: 32 | T34: =T33+7 -> 46241 | U34: =SUMIFS($E:$E,$O:$O,$S34,$P:$P,$R34) -> 0 | W34: =SUM(U34:V34) -> 0
B35: 46295 | C35: Q3 Bookings Plug ($15M) - $5M July, $5M Aug, $5M Sep | E35: 1000000 | F35: 46356 | G35: 45 | H35: 46402 | I35: =MONTH(B35) -> 9 | J35: =YEAR(B35) -> 2026 | K35: =WEEKNUM($F35) -> 49 | L35: =YEAR($F35) -> 2026 | M35: =WEEKNUM($H35) -> 3 | N35: =YEAR(H35) -> 2027 | O35: =IF(ISBLANK($B35),"",IF($M35<51,$M35+$O$1,$M35-52+$O$1)) -> 5 | P35: =IF(ISBLANK($B35),"",IF($M35<51,YEAR($H35),YEAR($H35)+1)) -> 2027 | R35: 2026 | S35: 33 | T35: =T34+7 -> 46248 | U35: =SUMIFS($E:$E,$O:$O,$S35,$P:$P,$R35) -> 0 | W35: =SUM(U35:V35) -> 0
B36: 46295 | C36: Q3 Bookings Plug ($15M) - $5M July, $5M Aug, $5M Sep | E36: 1000000 | F36: 46387 | G36: 45 | H36: 46432 | I36: =MONTH(B36) -> 9 | J36: =YEAR(B36) -> 2026 | K36: =WEEKNUM($F36) -> 53 | L36: =YEAR($F36) -> 2026 | M36: =WEEKNUM($H36) -> 8 | N36: =YEAR(H36) -> 2027 | O36: =IF(ISBLANK($B36),"",IF($M36<51,$M36+$O$1,$M36-52+$O$1)) -> 10 | P36: =IF(ISBLANK($B36),"",IF($M36<51,YEAR($H36),YEAR($H36)+1)) -> 2027 | R36: 2026 | S36: 34 | T36: =T35+7 -> 46255 | U36: =SUMIFS($E:$E,$O:$O,$S36,$P:$P,$R36) -> 0 | W36: =SUM(U36:V36) -> 0
B37: 46295 | C37: Q3 Bookings Plug ($15M) - $5M July, $5M Aug, $5M Sep | E37: 1000000 | F37: 46418 | G37: 45 | H37: 46461 | I37: =MONTH(B37) -> 9 | J37: =YEAR(B37) -> 2026 | K37: =WEEKNUM($F37) -> 6 | L37: =YEAR($F37) -> 2027 | M37: =WEEKNUM($H37) -> 12 | N37: =YEAR(H37) -> 2027 | O37: =IF(ISBLANK($B37),"",IF($M37<51,$M37+$O$1,$M37-52+$O$1)) -> 14 | P37: =IF(ISBLANK($B37),"",IF($M37<51,YEAR($H37),YEAR($H37)+1)) -> 2027 | R37: 2026 | S37: 35 | T37: =T36+7 -> 46262 | U37: =SUMIFS($E:$E,$O:$O,$S37,$P:$P,$R37) -> 3000000 | W37: =SUM(U37:V37) -> 3000000
R38: 2026 | S38: 36 | T38: =T37+7 -> 46269 | U38: =SUMIFS($E:$E,$O:$O,$S38,$P:$P,$R38) -> 0 | W38: =SUM(U38:V38) -> 0
R39: 2026 | S39: 37 | T39: =T38+7 -> 46276 | U39: =SUMIFS($E:$E,$O:$O,$S39,$P:$P,$R39) -> 0 | W39: =SUM(U39:V39) -> 0
R40: 2026 | S40: 38 | T40: =T39+7 -> 46283 | U40: =SUMIFS($E:$E,$O:$O,$S40,$P:$P,$R40) -> 0 | W40: =SUM(U40:V40) -> 0
R41: 2026 | S41: 39 | T41: =T40+7 -> 46290 | U41: =SUMIFS($E:$E,$O:$O,$S41,$P:$P,$R41) -> 0 | W41: =SUM(U41:V41) -> 0
R42: 2026 | S42: 40 | T42: =T41+7 -> 46297 | U42: =SUMIFS($E:$E,$O:$O,$S42,$P:$P,$R42) -> 4000000 | W42: =SUM(U42:V42) -> 4000000
R43: 2026 | S43: 41 | T43: =T42+7 -> 46304 | U43: =SUMIFS($E:$E,$O:$O,$S43,$P:$P,$R43) -> 0 | W43: =SUM(U43:V43) -> 0
R44: 2026 | S44: 42 | T44: =T43+7 -> 46311 | U44: =SUMIFS($E:$E,$O:$O,$S44,$P:$P,$R44) -> 0 | W44: =SUM(U44:V44) -> 0
R45: 2026 | S45: 43 | T45: =T44+7 -> 46318 | U45: =SUMIFS($E:$E,$O:$O,$S45,$P:$P,$R45) -> 0 | W45: =SUM(U45:V45) -> 0
R46: 2026 | S46: 44 | T46: =T45+7 -> 46325 | U46: =SUMIFS($E:$E,$O:$O,$S46,$P:$P,$R46) -> 5000000 | W46: =SUM(U46:V46) -> 5000000
R47: 2026 | S47: 45 | T47: =T46+7 -> 46332 | U47: =SUMIFS($E:$E,$O:$O,$S47,$P:$P,$R47) -> 0 | W47: =SUM(U47:V47) -> 0
R48: 2026 | S48: 46 | T48: =T47+7 -> 46339 | U48: =SUMIFS($E:$E,$O:$O,$S48,$P:$P,$R48) -> 0 | W48: =SUM(U48:V48) -> 0
R49: 2026 | S49: 47 | T49: =T48+7 -> 46346 | U49: =SUMIFS($E:$E,$O:$O,$S49,$P:$P,$R49) -> 0 | W49: =SUM(U49:V49) -> 0
... R106: 2027 | S106: 52 | T106: =T105+7 -> 46745 | U106: =SUMIFS($E:$E,$O:$O,$S106,$P:$P,$R106) -> 0 | W106: =SUM(U106:V106) -> 0

Sheet AR Aging 20260320
A1: RapDev LLC | R1: Check | S1: =SUM($H:$H)-SUM($U:$U)-H4 -> 0
A2: A/R Aging Detail | L2: # Weeks Past Due | N2: 2
A3: As of April 23, 2026 | Q3: Receivables Summary
G4: =SUBTOTAL(9,$G$6:$G$4657) -> 26764154 | H4: =SUBTOTAL(9,$H$6:$H$4657) -> 26752626
B5: Date | C5: Transaction Type | D5: Num | E5: Customer | F5: Due Date | G5: Amount | H5: Open Balance | I5: Terms | J5: Inv Send Year # | K5: Inv Send Week # | L5: Inv Due Week # | M5: Payment Year | N5: Expected Pmt Wk # | Q5: Year | R5: Wk # | S5: Wk Ending | T5: Est. Amt | U5: Amt for Fcst
B6: 03/01/2025 | C6: Invoice | D6: 3186 | E6: Epidata Argentina:RDC0001917 - Epidata Argentina - DD - MP - Solaris Agent | F6: 46023 | G6: 7425.6 | H6: 7425.6 | I6: 120 | J6: =IF(ISBLANK($B6),"",YEAR($B6)) -> 2025 | K6: =IF(ISBLANK($B6),"",WEEKNUM($B6)) -> 9 | L6: =IF(ISBLANK($B6),"",WEEKNUM($F6)) -> 1 | M6: =IF(ISBLANK($B6),"",IF($L6<51,YEAR($F6),YEAR($F6)+1)) -> 2026 | N6: =IF(ISBLANK($B6),"",IF($L6<51,$L6+$N$2,$L6-52+$N$2)) -> 3 | Q6: 2026 | R6: 1 | S6: 46024 | T6: =SUMIFS($H:$H,$N:$N,$R6,$M:$M,$Q6) -> 0 | U6: =SUM(T6:T6) -> 0
B7: 09/30/2025 | C7: Invoice | D7: 3577 | E7: Claro Pay:RDC0001994 - Claro Pay - DD - Modern Ops + MGD DD | F7: 46023 | G7: 14880 | H7: 14880 | I7: 30 | J7: =IF(ISBLANK($B7),"",YEAR($B7)) -> 2025 | K7: =IF(ISBLANK($B7),"",WEEKNUM($B7)) -> 40 | L7: =IF(ISBLANK($B7),"",WEEKNUM($F7)) -> 1 | M7: =IF(ISBLANK($B7),"",IF($L7<51,YEAR($F7),YEAR($F7)+1)) -> 2026 | N7: =IF(ISBLANK($B7),"",IF($L7<51,$L7+$N$2,$L7-52+$N$2)) -> 3 | Q7: 2026 | R7: 2 | S7: =S6+7 -> 46031 | T7: =SUMIFS($H:$H,$N:$N,$R7,$M:$M,$Q7) -> 0 | U7: =SUM(T7:T7) -> 0
B8: 08/31/2025 | C8: Invoice | D8: 3511 | E8: Discovery Communications, LLC:RDC0001976 - Warner Bros. Discovery - SN - ITOM Health | F8: 46023 | G8: 11685 | H8: 11685 | I8: 90 | J8: =IF(ISBLANK($B8),"",YEAR($B8)) -> 2025 | K8: =IF(ISBLANK($B8),"",WEEKNUM($B8)) -> 36 | L8: =IF(ISBLANK($B8),"",WEEKNUM($F8)) -> 1 | M8: =IF(ISBLANK($B8),"",IF($L8<51,YEAR($F8),YEAR($F8)+1)) -> 2026 | N8: =IF(ISBLANK($B8),"",IF($L8<51,$L8+$N$2,$L8-52+$N$2)) -> 3 | Q8: 2026 | R8: 3 | S8: =S7+7 -> 46038 | T8: =SUMIFS($H:$H,$N:$N,$R8,$M:$M,$Q8) -> 297412.6 | U8: =SUM(T8:T8) -> 297412.6
B9: 10/31/2025 | C9: Invoice | D9: 3649 | E9: Claro Pay:RDC0001994 - Claro Pay - DD - Modern Ops + MGD DD | F9: 46023 | G9: 24000 | H9: 24000 | I9: 30 | J9: =IF(ISBLANK($B9),"",YEAR($B9)) -> 2025 | K9: =IF(ISBLANK($B9),"",WEEKNUM($B9)) -> 44 | L9: =IF(ISBLANK($B9),"",WEEKNUM($F9)) -> 1 | M9: =IF(ISBLANK($B9),"",IF($L9<51,YEAR($F9),YEAR($F9)+1)) -> 2026 | N9: =IF(ISBLANK($B9),"",IF($L9<51,$L9+$N$2,$L9-52+$N$2)) -> 3 | Q9: 2026 | R9: 4 | S9: =S8+7 -> 46045 | T9: =SUMIFS($H:$H,$N:$N,$R9,$M:$M,$Q9) -> 0 | U9: =SUM(T9:T9) -> 0
B10: 11/28/2025 | C10: Invoice | D10: 3683 | E10: Constellation Energy Generation, LLC:RDC0002011 - Constellation Energy - SN - Foundational Data Cleanup (RFP) | F10: 46023 | G10: 48402 | H10: 48402 | I10: 30 | J10: =IF(ISBLANK($B10),"",YEAR($B10)) -> 2025 | K10: =IF(ISBLANK($B10),"",WEEKNUM($B10)) -> 48 | L10: =IF(ISBLANK($B10),"",WEEKNUM($F10)) -> 1 | M10: =IF(ISBLANK($B10),"",IF($L10<51,YEAR($F10),YEAR($F10)+1)) -> 2026 | N10: =IF(ISBLANK($B10),"",IF($L10<51,$L10+$N$2,$L10-52+$N$2)) -> 3 | Q10: 2026 | R10: 5 | S10: =S9+7 -> 46052 | T10: =SUMIFS($H:$H,$N:$N,$R10,$M:$M,$Q10) -> 0 | U10: =SUM(T10:T10) -> 0
B11: 09/30/2025 | C11: Invoice | D11: 3578 | E11: Discovery Communications, LLC:RDC0001976 - Warner Bros. Discovery - SN - ITOM Health | F11: 46023 | G11: 11400 | H11: 11400 | I11: 90 | J11: =IF(ISBLANK($B11),"",YEAR($B11)) -> 2025 | K11: =IF(ISBLANK($B11),"",WEEKNUM($B11)) -> 40 | L11: =IF(ISBLANK($B11),"",WEEKNUM($F11)) -> 1 | M11: =IF(ISBLANK($B11),"",IF($L11<51,YEAR($F11),YEAR($F11)+1)) -> 2026 | N11: =IF(ISBLANK($B11),"",IF($L11<51,$L11+$N$2,$L11-52+$N$2)) -> 3 | Q11: 2026 | R11: 6 | S11: =S10+7 -> 46059 | T11: =SUMIFS($H:$H,$N:$N,$R11,$M:$M,$Q11) -> 0 | U11: =SUM(T11:T11) -> 0
B12: 11/30/2025 | C12: Invoice | D12: 3707 | E12: Vitality Global:RDC0001946 - Vitality Global - SN - DevOps | F12: 46023 | G12: 44000 | H12: 44000 | I12: 30 | J12: =IF(ISBLANK($B12),"",YEAR($B12)) -> 2025 | K12: =IF(ISBLANK($B12),"",WEEKNUM($B12)) -> 49 | L12: =IF(ISBLANK($B12),"",WEEKNUM($F12)) -> 1 | M12: =IF(ISBLANK($B12),"",IF($L12<51,YEAR($F12),YEAR($F12)+1)) -> 2026 | N12: =IF(ISBLANK($B12),"",IF($L12<51,$L12+$N$2,$L12-52+$N$2)) -> 3 | Q12: 2026 | R12: 7 | S12: =S11+7 -> 46066 | T12: =SUMIFS($H:$H,$N:$N,$R12,$M:$M,$Q12) -> 272280 | U12: =SUM(T12:T12) -> 272280
B13: 11/30/2025 | C13: Invoice | D13: 3714 | E13: Chipotle Mexican Grill:RDC0002360 - Chipotle Mexican Grill, Inc. - DD - Account Migration | F13: 46023 | G13: 120500 | H13: 120500 | I13: 30 | J13: =IF(ISBLANK($B13),"",YEAR($B13)) -> 2025 | K13: =IF(ISBLANK($B13),"",WEEKNUM($B13)) -> 49 | L13: =IF(ISBLANK($B13),"",WEEKNUM($F13)) -> 1 | M13: =IF(ISBLANK($B13),"",IF($L13<51,YEAR($F13),YEAR($F13)+1)) -> 2026 | N13: =IF(ISBLANK($B13),"",IF($L13<51,$L13+$N$2,$L13-52+$N$2)) -> 3 | Q13: 2026 | R13: 8 | S13: =S12+7 -> 46073 | T13: =SUMIFS($H:$H,$N:$N,$R13,$M:$M,$Q13) -> 33667.2 | U13: =SUM(T13:T13) -> 33667.2
B14: 11/30/2025 | C14: Invoice | D14: 3727 | E14: Claro Pay:RDC0001994 - Claro Pay - DD - Modern Ops + MGD DD | F14: 46023 | G14: 15120 | H14: 15120 | I14: 30 | J14: =IF(ISBLANK($B14),"",YEAR($B14)) -> 2025 | K14: =IF(ISBLANK($B14),"",WEEKNUM($B14)) -> 49 | L14: =IF(ISBLANK($B14),"",WEEKNUM($F14)) -> 1 | M14: =IF(ISBLANK($B14),"",IF($L14<51,YEAR($F14),YEAR($F14)+1)) -> 2026 | N14: =IF(ISBLANK($B14),"",IF($L14<51,$L14+$N$2,$L14-52+$N$2)) -> 3 | Q14: 2026 | R14: 9 | S14: =S13+7 -> 46080 | T14: =SUMIFS($H:$H,$N:$N,$R14,$M:$M,$Q14) -> 209760 | U14: =SUM(T14:T14) -> 209760
B15: 12/31/2025 | C15: Invoice | D15: 3810 | E15: Claro Pay:RDC0001994 - Claro Pay - DD - Modern Ops + MGD DD | F15: 01/30/2026 | G15: 16080 | H15: 16080 | I15: 30 | J15: =IF(ISBLANK($B15),"",YEAR($B15)) -> 2025 | K15: =IF(ISBLANK($B15),"",WEEKNUM($B15)) -> 53 | L15: =IF(ISBLANK($B15),"",WEEKNUM($F15)) -> 5 | M15: =IF(ISBLANK($B15),"",IF($L15<51,YEAR($F15),YEAR($F15)+1)) -> 2026 | N15: =IF(ISBLANK($B15),"",IF($L15<51,$L15+$N$2,$L15-52+$N$2)) -> 7 | Q15: 2026 | R15: 10 | S15: =S14+7 -> 46087 | T15: =SUMIFS($H:$H,$N:$N,$R15,$M:$M,$Q15) -> 0 | U15: =SUM(T15:T15) -> 0
B16: 12/31/2025 | C16: Invoice | D16: 3811 | E16: Komatsu:RDC0002032 - Komatsu - ServiceNow Drawdown | F16: 01/30/2026 | G16: 13000 | H16: 13000 | I16: 30 | J16: =IF(ISBLANK($B16),"",YEAR($B16)) -> 2025 | K16: =IF(ISBLANK($B16),"",WEEKNUM($B16)) -> 53 | L16: =IF(ISBLANK($B16),"",WEEKNUM($F16)) -> 5 | M16: =IF(ISBLANK($B16),"",IF($L16<51,YEAR($F16),YEAR($F16)+1)) -> 2026 | N16: =IF(ISBLANK($B16),"",IF($L16<51,$L16+$N$2,$L16-52+$N$2)) -> 7 | Q16: 2026 | R16: 11 | S16: =S15+7 -> 46094 | T16: =SUMIFS($H:$H,$N:$N,$R16,$M:$M,$Q16) -> 4315.72 | U16: =SUM(T16:T16) -> 4315.72
B17: 01/01/2026 | C17: Invoice | D17: 3748 | E17: Coppel:RDC0002228 - Coppel - DD - SVC - FP - IT DBM & Core Servers | F17: 01/31/2026 | G17: 243200 | H17: 243200 | I17: 30 | J17: =IF(ISBLANK($B17),"",YEAR($B17)) -> 2026 | K17: =IF(ISBLANK($B17),"",WEEKNUM($B17)) -> 1 | L17: =IF(ISBLANK($B17),"",WEEKNUM($F17)) -> 5 | M17: =IF(ISBLANK($B17),"",IF($L17<51,YEAR($F17),YEAR($F17)+1)) -> 2026 | N17: =IF(ISBLANK($B17),"",IF($L17<51,$L17+$N$2,$L17-52+$N$2)) -> 7 | Q17: 2026 | R17: 12 | S17: =S16+7 -> 46101 | T17: =SUMIFS($H:$H,$N:$N,$R17,$M:$M,$Q17) -> 80420 | U17: =SUM(T17:T17) -> 80420
B18: 12/23/2025 | C18: Invoice | D18: 3791 | E18: London Stock Exchange Group:RDC0002477 - London Stock Exchange Group - DD - MP - Solaris - 2026 | F18: 02/06/2026 | G18: 33667.2 | H18: 33667.2 | I18: 45 | J18: =IF(ISBLANK($B18),"",YEAR($B18)) -> 2025 | K18: =IF(ISBLANK($B18),"",WEEKNUM($B18)) -> 52 | L18: =IF(ISBLANK($B18),"",WEEKNUM($F18)) -> 6 | M18: =IF(ISBLANK($B18),"",IF($L18<51,YEAR($F18),YEAR($F18)+1)) -> 2026 | N18: =IF(ISBLANK($B18),"",IF($L18<51,$L18+$N$2,$L18-52+$N$2)) -> 8 | Q18: 2026 | R18: 13 | S18: =S17+7 -> 46108 | T18: =SUMIFS($H:$H,$N:$N,$R18,$M:$M,$Q18) -> 172530 | U18: =SUM(T18:T18) -> 172530
B19: 01/14/2026 | C19: Invoice | D19: 3827 | E19: OneMain Financial:RDC0001958 - OneMain Financial - SN - SAM Enterprise | F19: 02/13/2026 | G19: 27360 | H19: 27360 | I19: 30 | J19: =IF(ISBLANK($B19),"",YEAR($B19)) -> 2026 | K19: =IF(ISBLANK($B19),"",WEEKNUM($B19)) -> 3 | L19: =IF(ISBLANK($B19),"",WEEKNUM($F19)) -> 7 | M19: =IF(ISBLANK($B19),"",IF($L19<51,YEAR($F19),YEAR($F19)+1)) -> 2026 | N19: =IF(ISBLANK($B19),"",IF($L19<51,$L19+$N$2,$L19-52+$N$2)) -> 9 | Q19: 2026 | R19: 14 | S19: =S18+7 -> 46115 | T19: =SUMIFS($H:$H,$N:$N,$R19,$M:$M,$Q19) -> 368726.4 | U19: =SUM(T19:T19) -> 368726.4
B20: 01/14/2026 | C20: Invoice | D20: 3835 | E20: Coppel:RDC0002228 - Coppel - DD - SVC - FP - IT DBM & Core Servers | F20: 02/13/2026 | G20: 182400 | H20: 182400 | I20: 30 | J20: =IF(ISBLANK($B20),"",YEAR($B20)) -> 2026 | K20: =IF(ISBLANK($B20),"",WEEKNUM($B20)) -> 3 | L20: =IF(ISBLANK($B20),"",WEEKNUM($F20)) -> 7 | M20: =IF(ISBLANK($B20),"",IF($L20<51,YEAR($F20),YEAR($F20)+1)) -> 2026 | N20: =IF(ISBLANK($B20),"",IF($L20<51,$L20+$N$2,$L20-52+$N$2)) -> 9 | Q20: 2026 | R20: 15 | S20: =S19+7 -> 46122 | T20: =SUMIFS($H:$H,$N:$N,$R20,$M:$M,$Q20) -> 41126.66 | U20: =SUM(T20:T20) -> 41126.66
B21: 11/28/2025 | C21: Invoice | D21: 3749 | E21: Datadog | F21: 02/26/2026 | G21: 15844.08 | H21: 4315.72 | I21: 90 | J21: =IF(ISBLANK($B21),"",YEAR($B21)) -> 2025 | K21: =IF(ISBLANK($B21),"",WEEKNUM($B21)) -> 48 | L21: =IF(ISBLANK($B21),"",WEEKNUM($F21)) -> 9 | M21: =IF(ISBLANK($B21),"",IF($L21<51,YEAR($F21),YEAR($F21)+1)) -> 2026 | N21: =IF(ISBLANK($B21),"",IF($L21<51,$L21+$N$2,$L21-52+$N$2)) -> 11 | Q21: 2026 | R21: 16 | S21: =S20+7 -> 46129 | T21: =SUMIFS($H:$H,$N:$N,$R21,$M:$M,$Q21) -> 285706.8 | U21: =SUM(T21:T21) -> 285706.8
B22: 01/30/2026 | C22: Invoice | D22: 3867 | E22: Claro Pay:RDC0001994 - Claro Pay - DD - Modern Ops + MGD DD | F22: 03/01/2026 | G22: 18720 | H22: 18720 | I22: 30 | J22: =IF(ISBLANK($B22),"",YEAR($B22)) -> 2026 | K22: =IF(ISBLANK($B22),"",WEEKNUM($B22)) -> 5 | L22: =IF(ISBLANK($B22),"",WEEKNUM($F22)) -> 10 | M22: =IF(ISBLANK($B22),"",IF($L22<51,YEAR($F22),YEAR($F22)+1)) -> 2026 | N22: =IF(ISBLANK($B22),"",IF($L22<51,$L22+$N$2,$L22-52+$N$2)) -> 12 | Q22: 2026 | R22: 17 | S22: =S21+7 -> 46136 | T22: =SUMIFS($H:$H,$N:$N,$R22,$M:$M,$Q22) -> 11000 | U22: =SUM(T22:T22) -> 11000
B23: 01/30/2026 | C23: Invoice | D23: 3869 | E23: Komatsu:RDC0002032 - Komatsu - ServiceNow Drawdown | F23: 03/01/2026 | G23: 11500 | H23: 11500 | I23: 30 | J23: =IF(ISBLANK($B23),"",YEAR($B23)) -> 2026 | K23: =IF(ISBLANK($B23),"",WEEKNUM($B23)) -> 5 | L23: =IF(ISBLANK($B23),"",WEEKNUM($F23)) -> 10 | M23: =IF(ISBLANK($B23),"",IF($L23<51,YEAR($F23),YEAR($F23)+1)) -> 2026 | N23: =IF(ISBLANK($B23),"",IF($L23<51,$L23+$N$2,$L23-52+$N$2)) -> 12 | Q23: 2026 | R23: 18 | S23: =S22+7 -> 46143 | T23: =SUMIFS($H:$H,$N:$N,$R23,$M:$M,$Q23) -> 430690.5 | U23: =SUM(T23:T23) -> 430690.5
B24: 01/30/2026 | C24: Invoice | D24: 3870 | E24: Nomura International PLC:RDC0002038 - Nomura - SN - DevOps Extension | F24: 03/01/2026 | G24: 2200 | H24: 2200 | I24: 30 | J24: =IF(ISBLANK($B24),"",YEAR($B24)) -> 2026 | K24: =IF(ISBLANK($B24),"",WEEKNUM($B24)) -> 5 | L24: =IF(ISBLANK($B24),"",WEEKNUM($F24)) -> 10 | M24: =IF(ISBLANK($B24),"",IF($L24<51,YEAR($F24),YEAR($F24)+1)) -> 2026 | N24: =IF(ISBLANK($B24),"",IF($L24<51,$L24+$N$2,$L24-52+$N$2)) -> 12 | Q24: 2026 | R24: 19 | S24: =S23+7 -> 46150 | T24: =SUMIFS($H:$H,$N:$N,$R24,$M:$M,$Q24) -> 1398444.2 | U24: =SUM(T24:T24) -> 1398444.2
B25: 02/03/2026 | C25: Invoice | D25: 3857 | E25: Berkley Technology Services:RDC0002215 - Wr Berkley - DD - SOW - Dynatrace to DDOG | F25: 03/05/2026 | G25: 48000 | H25: 48000 | I25: 30 | J25: =IF(ISBLANK($B25),"",YEAR($B25)) -> 2026 | K25: =IF(ISBLANK($B25),"",WEEKNUM($B25)) -> 6 | L25: =IF(ISBLANK($B25),"",WEEKNUM($F25)) -> 10 | M25: =IF(ISBLANK($B25),"",IF($L25<51,YEAR($F25),YEAR($F25)+1)) -> 2026 | N25: =IF(ISBLANK($B25),"",IF($L25<51,$L25+$N$2,$L25-52+$N$2)) -> 12 | Q25: 2026 | R25: 20 | S25: =S24+7 -> 46157 | T25: =SUMIFS($H:$H,$N:$N,$R25,$M:$M,$Q25) -> 981511.67 | U25: =SUM(T25:T25) -> 981511.67
B26: 01/27/2026 | C26: Invoice | D26: 3848 | E26: V2X:RDC0002057 - V2X - SN - CMDB + ITAM | F26: 03/13/2026 | G26: 172530 | H26: 172530 | I26: 45 | J26: =IF(ISBLANK($B26),"",YEAR($B26)) -> 2026 | K26: =IF(ISBLANK($B26),"",WEEKNUM($B26)) -> 5 | L26: =IF(ISBLANK($B26),"",WEEKNUM($F26)) -> 11 | M26: =IF(ISBLANK($B26),"",IF($L26<51,YEAR($F26),YEAR($F26)+1)) -> 2026 | N26: =IF(ISBLANK($B26),"",IF($L26<51,$L26+$N$2,$L26-52+$N$2)) -> 13 | Q26: 2026 | R26: 21 | S26: =S25+7 -> 46164 | T26: =SUMIFS($H:$H,$N:$N,$R26,$M:$M,$Q26) -> 0 | U26: =SUM(T26:T26) -> 0
... B54: 03/23/2026 | C54: Invoice | D54: 3968 | E54: Crowley Maritime Corporation:RDC0002079 - Crowley - DD - MSP Migration | F54: 04/22/2026 | G54: 71456 | H54: 71456 | I54: 30 | J54: =IF(ISBLANK($B54),"",YEAR($B54)) -> 2026 | K54: =IF(ISBLANK($B54),"",WEEKNUM($B54)) -> 13 | L54: =IF(ISBLANK($B54),"",WEEKNUM($F54)) -> 17 | M54: =IF(ISBLANK($B54),"",IF($L54<51,YEAR($F54),YEAR($F54)+1)) -> 2026 | N54: =IF(ISBLANK($B54),"",IF($L54<51,$L54+$N$2,$L54-52+$N$2)) -> 19 | Q54: 2026 | R54: 49 | S54: =S53+7 -> 46360 | T54: =SUMIFS($H:$H,$N:$N,$R54,$M:$M,$Q54) -> 0 | U54: =SUM(T54:T54) -> 0
B55: 04/22/2026 | C55: Journal Entry | D55: Qualcomm PMT 202604 | E55: Qualcomm Incorporated:RDC0001903 - Qualcomm - Solaris (2025-2026) - Renewal | F55: 04/22/2026 | G55: -42336 | H55: -42336 | J55: =IF(ISBLANK($B55),"",YEAR($B55)) -> 2026 | K55: =IF(ISBLANK($B55),"",WEEKNUM($B55)) -> 17 | L55: =IF(ISBLANK($B55),"",WEEKNUM($F55)) -> 17 | M55: =IF(ISBLANK($B55),"",IF($L55<51,YEAR($F55),YEAR($F55)+1)) -> 2026 | N55: =IF(ISBLANK($B55),"",IF($L55<51,$L55+$N$2,$L55-52+$N$2)) -> 19 | Q55: 2026 | R55: 50 | S55: =S54+7 -> 46367 | T55: =SUMIFS($H:$H,$N:$N,$R55,$M:$M,$Q55) -> 0 | U55: =SUM(T55:T55) -> 0
B56: 01/23/2026 | C56: Invoice | D56: 3840 | E56: Datadog | F56: 04/23/2026 | G56: 21592.9 | H56: 21592.9 | I56: 90 | J56: =IF(ISBLANK($B56),"",YEAR($B56)) -> 2026 | K56: =IF(ISBLANK($B56),"",WEEKNUM($B56)) -> 4 | L56: =IF(ISBLANK($B56),"",WEEKNUM($F56)) -> 17 | M56: =IF(ISBLANK($B56),"",IF($L56<51,YEAR($F56),YEAR($F56)+1)) -> 2026 | N56: =IF(ISBLANK($B56),"",IF($L56<51,$L56+$N$2,$L56-52+$N$2)) -> 19 | Q56: 2026 | R56: 51 | S56: =S55+7 -> 46374 | T56: =SUMIFS($H:$H,$N:$N,$R56,$M:$M,$Q56) -> 232020.4 | U56: =SUM(T56:T56) -> 232020.4
B57: 03/10/2026 | C57: Invoice | D57: 3946 | E57: Canadian Imperial Bank of Commerce:RDC0002362 - CIBC - SN - OOTB ITSM, Integrations, CSDM | F57: 04/24/2026 | G57: 1117000 | H57: 1117000 | I57: 45 | J57: =IF(ISBLANK($B57),"",YEAR($B57)) -> 2026 | K57: =IF(ISBLANK($B57),"",WEEKNUM($B57)) -> 11 | L57: =IF(ISBLANK($B57),"",WEEKNUM($F57)) -> 17 | M57: =IF(ISBLANK($B57),"",IF($L57<51,YEAR($F57),YEAR($F57)+1)) -> 2026 | N57: =IF(ISBLANK($B57),"",IF($L57<51,$L57+$N$2,$L57-52+$N$2)) -> 19 | Q57: 2026 | R57: 52 | S57: =S56+7 -> 46381 | T57: =SUMIFS($H:$H,$N:$N,$R57,$M:$M,$Q57) -> 0 | U57: =SUM(T57:T57) -> 0
B58: 03/26/2026 | C58: Invoice | D58: 3971 | E58: Centrica PLC (GBP):RDC0002097 - Centrica - SN - SAM | F58: 04/25/2026 | G58: 74858.47 | H58: 74858.465 | I58: 30 | J58: =IF(ISBLANK($B58),"",YEAR($B58)) -> 2026 | K58: =IF(ISBLANK($B58),"",WEEKNUM($B58)) -> 13 | L58: =IF(ISBLANK($B58),"",WEEKNUM($F58)) -> 17 | M58: =IF(ISBLANK($B58),"",IF($L58<51,YEAR($F58),YEAR($F58)+1)) -> 2026 | N58: =IF(ISBLANK($B58),"",IF($L58<51,$L58+$N$2,$L58-52+$N$2)) -> 19 | Q58: 2027 | R58: 1 | S58: =S57+7 -> 46388 | T58: =SUMIFS($H:$H,$N:$N,$R58,$M:$M,$Q58) -> 31200 | U58: =SUM(T58:T58) -> 31200
B59: 03/26/2026 | C59: Invoice | D59: 3973 | E59: Rate:RDC0002012 - Rate - DD - SOW - Tool Consolidation | F59: 04/25/2026 | G59: 26500 | H59: 26500 | I59: 30 | J59: =IF(ISBLANK($B59),"",YEAR($B59)) -> 2026 | K59: =IF(ISBLANK($B59),"",WEEKNUM($B59)) -> 13 | L59: =IF(ISBLANK($B59),"",WEEKNUM($F59)) -> 17 | M59: =IF(ISBLANK($B59),"",IF($L59<51,YEAR($F59),YEAR($F59)+1)) -> 2026 | N59: =IF(ISBLANK($B59),"",IF($L59<51,$L59+$N$2,$L59-52+$N$2)) -> 19 | Q59: 2027 | R59: 2 | S59: =S58+7 -> 46395 | T59: =SUMIFS($H:$H,$N:$N,$R59,$M:$M,$Q59) -> 0 | U59: =SUM(T59:T59) -> 0
B60: 03/26/2026 | C60: Invoice | D60: 3975 | E60: Ahold Delhaize:RDC0002037 - ADUSA - SN - Tufin Integration | F60: 04/25/2026 | G60: 18892.8 | H60: 18892.8 | I60: 30 | J60: =IF(ISBLANK($B60),"",YEAR($B60)) -> 2026 | K60: =IF(ISBLANK($B60),"",WEEKNUM($B60)) -> 13 | L60: =IF(ISBLANK($B60),"",WEEKNUM($F60)) -> 17 | M60: =IF(ISBLANK($B60),"",IF($L60<51,YEAR($F60),YEAR($F60)+1)) -> 2026 | N60: =IF(ISBLANK($B60),"",IF($L60<51,$L60+$N$2,$L60-52+$N$2)) -> 19 | Q60: 2027 | R60: 3 | S60: =S59+7 -> 46402 | T60: =SUMIFS($H:$H,$N:$N,$R60,$M:$M,$Q60) -> 0 | U60: =SUM(T60:T60) -> 0
B61: 03/26/2026 | C61: Invoice | D61: 3978 | E61: Switch LTD:RDC0002527 - Switch - SN - Current Platform Assessment | F61: 04/25/2026 | G61: 50000 | H61: 50000 | I61: 30 | J61: =IF(ISBLANK($B61),"",YEAR($B61)) -> 2026 | K61: =IF(ISBLANK($B61),"",WEEKNUM($B61)) -> 13 | L61: =IF(ISBLANK($B61),"",WEEKNUM($F61)) -> 17 | M61: =IF(ISBLANK($B61),"",IF($L61<51,YEAR($F61),YEAR($F61)+1)) -> 2026 | N61: =IF(ISBLANK($B61),"",IF($L61<51,$L61+$N$2,$L61-52+$N$2)) -> 19 | Q61: 2027 | R61: 4 | S61: =S60+7 -> 46409 | T61: =SUMIFS($H:$H,$N:$N,$R61,$M:$M,$Q61) -> 0 | U61: =SUM(T61:T61) -> 0
B62: 02/27/2026 | C62: Invoice | D62: 3938 | E62: TTEC Government Solutions, LLC:RDC0001970 - TTEC - DD - Drawdown Renewal | F62: 04/28/2026 | G62: 10640 | H62: 10640 | I62: 60 | J62: =IF(ISBLANK($B62),"",YEAR($B62)) -> 2026 | K62: =IF(ISBLANK($B62),"",WEEKNUM($B62)) -> 9 | L62: =IF(ISBLANK($B62),"",WEEKNUM($F62)) -> 18 | M62: =IF(ISBLANK($B62),"",IF($L62<51,YEAR($F62),YEAR($F62)+1)) -> 2026 | N62: =IF(ISBLANK($B62),"",IF($L62<51,$L62+$N$2,$L62-52+$N$2)) -> 20 | Q62: 2027 | R62: 5 | S62: =S61+7 -> 46416 | T62: =SUMIFS($H:$H,$N:$N,$R62,$M:$M,$Q62) -> 0 | U62: =SUM(T62:T62) -> 0
B63: 03/30/2026 | C63: Invoice | D63: 3985 | E63: HarbourVest:RDC0002544 - HarbourVest - SN - ITSM, CMDB & ITOM with OCM | F63: 04/29/2026 | G63: 93324 | H63: 93324 | I63: 30 | J63: =IF(ISBLANK($B63),"",YEAR($B63)) -> 2026 | K63: =IF(ISBLANK($B63),"",WEEKNUM($B63)) -> 14 | L63: =IF(ISBLANK($B63),"",WEEKNUM($F63)) -> 18 | M63: =IF(ISBLANK($B63),"",IF($L63<51,YEAR($F63),YEAR($F63)+1)) -> 2026 | N63: =IF(ISBLANK($B63),"",IF($L63<51,$L63+$N$2,$L63-52+$N$2)) -> 20 | Q63: 2027 | R63: 6 | S63: =S62+7 -> 46423 | T63: =SUMIFS($H:$H,$N:$N,$R63,$M:$M,$Q63) -> 0 | U63: =SUM(T63:T63) -> 0
B64: 01/30/2026 | C64: Invoice | D64: 3854 | E64: HP Inc.:RDC0002287 - HP Inc. - SVC - DD - EIS Splunk Migration | F64: 04/30/2026 | G64: 159200 | H64: 159200 | I64: 90 | J64: =IF(ISBLANK($B64),"",YEAR($B64)) -> 2026 | K64: =IF(ISBLANK($B64),"",WEEKNUM($B64)) -> 5 | L64: =IF(ISBLANK($B64),"",WEEKNUM($F64)) -> 18 | M64: =IF(ISBLANK($B64),"",IF($L64<51,YEAR($F64),YEAR($F64)+1)) -> 2026 | N64: =IF(ISBLANK($B64),"",IF($L64<51,$L64+$N$2,$L64-52+$N$2)) -> 20 | Q64: 2027 | R64: 7 | S64: =S63+7 -> 46430 | T64: =SUMIFS($H:$H,$N:$N,$R64,$M:$M,$Q64) -> 0 | U64: =SUM(T64:T64) -> 0
B65: 01/30/2026 | C65: Invoice | D65: 3877 | E65: Discovery Communications, LLC:RDC0001976 - Warner Bros. Discovery - SN - ITOM Health | F65: 04/30/2026 | G65: 39615 | H65: 39615 | I65: 90 | J65: =IF(ISBLANK($B65),"",YEAR($B65)) -> 2026 | K65: =IF(ISBLANK($B65),"",WEEKNUM($B65)) -> 5 | L65: =IF(ISBLANK($B65),"",WEEKNUM($F65)) -> 18 | M65: =IF(ISBLANK($B65),"",IF($L65<51,YEAR($F65),YEAR($F65)+1)) -> 2026 | N65: =IF(ISBLANK($B65),"",IF($L65<51,$L65+$N$2,$L65-52+$N$2)) -> 20 | Q65: 2027 | R65: 8 | S65: =S64+7 -> 46437 | T65: =SUMIFS($H:$H,$N:$N,$R65,$M:$M,$Q65) -> 0 | U65: =SUM(T65:T65) -> 0
B66: 03/16/2026 | C66: Invoice | D66: 3960 | E66: Nasdaq:RDC0002458 - Nasdaq - DD - Verafin - Splunk Migration | F66: 04/30/2026 | G66: 55250 | H66: 55250 | I66: 45 | J66: =IF(ISBLANK($B66),"",YEAR($B66)) -> 2026 | K66: =IF(ISBLANK($B66),"",WEEKNUM($B66)) -> 12 | L66: =IF(ISBLANK($B66),"",WEEKNUM($F66)) -> 18 | M66: =IF(ISBLANK($B66),"",IF($L66<51,YEAR($F66),YEAR($F66)+1)) -> 2026 | N66: =IF(ISBLANK($B66),"",IF($L66<51,$L66+$N$2,$L66-52+$N$2)) -> 20 | Q66: 2027 | R66: 9 | S66: =S65+7 -> 46444 | T66: =SUMIFS($H:$H,$N:$N,$R66,$M:$M,$Q66) -> 0 | U66: =SUM(T66:T66) -> 0
B67: 03/31/2026 | C67: Invoice | D67: 3966b | E67: Manchester Airport Group (GBP):RDC0002396 - Manchester Airport Group (MAG) - SN - SPM | F67: 04/30/2026 | G67: 99228 | H67: 99228 | I67: 30 | J67: =IF(ISBLANK($B67),"",YEAR($B67)) -> 2026 | K67: =IF(ISBLANK($B67),"",WEEKNUM($B67)) -> 14 | L67: =IF(ISBLANK($B67),"",WEEKNUM($F67)) -> 18 | M67: =IF(ISBLANK($B67),"",IF($L67<51,YEAR($F67),YEAR($F67)+1)) -> 2026 | N67: =IF(ISBLANK($B67),"",IF($L67<51,$L67+$N$2,$L67-52+$N$2)) -> 20 | Q67: 2027 | R67: 10 | S67: =S66+7 -> 46451 | T67: =SUMIFS($H:$H,$N:$N,$R67,$M:$M,$Q67) -> 0 | U67: =SUM(T67:T67) -> 0
... B106: 03/31/2026 | C106: Invoice | D106: 4015 | E106: Sierra Nevada Company, LLC:RDC0002520 - Sierra Nevada - ServiceNow - Business Apps | F106: 05/15/2026 | G106: 720 | H106: 720 | I106: 45 | J106: =IF(ISBLANK($B106),"",YEAR($B106)) -> 2026 | K106: =IF(ISBLANK($B106),"",WEEKNUM($B106)) -> 14 | L106: =IF(ISBLANK($B106),"",WEEKNUM($F106)) -> 20 | M106: =IF(ISBLANK($B106),"",IF($L106<51,YEAR($F106),YEAR($F106)+1)) -> 2026 | N106: =IF(ISBLANK($B106),"",IF($L106<51,$L106+$N$2,$L106-52+$N$2)) -> 22 | Q106: 2027 | R106: 49 | S106: =S105+7 -> 46724 | T106: =SUMIFS($H:$H,$N:$N,$R106,$M:$M,$Q106) -> 0 | U106: =SUM(T106:T106) -> 0
B107: 03/31/2026 | C107: Invoice | D107: 4018 | E107: Grainger:RDC0002069 - Grainger - SN - ITOM Enhancements | F107: 05/15/2026 | G107: 3510 | H107: 3510 | I107: 45 | J107: =IF(ISBLANK($B107),"",YEAR($B107)) -> 2026 | K107: =IF(ISBLANK($B107),"",WEEKNUM($B107)) -> 14 | L107: =IF(ISBLANK($B107),"",WEEKNUM($F107)) -> 20 | M107: =IF(ISBLANK($B107),"",IF($L107<51,YEAR($F107),YEAR($F107)+1)) -> 2026 | N107: =IF(ISBLANK($B107),"",IF($L107<51,$L107+$N$2,$L107-52+$N$2)) -> 22
B108: 03/31/2026 | C108: Invoice | D108: 4019 | E108: Grainger:RDC0001997 - Grainger - SN - Drawdown CMDB | F108: 05/15/2026 | G108: 10725 | H108: 10725 | I108: 45 | J108: =IF(ISBLANK($B108),"",YEAR($B108)) -> 2026 | K108: =IF(ISBLANK($B108),"",WEEKNUM($B108)) -> 14 | L108: =IF(ISBLANK($B108),"",WEEKNUM($F108)) -> 20 | M108: =IF(ISBLANK($B108),"",IF($L108<51,YEAR($F108),YEAR($F108)+1)) -> 2026 | N108: =IF(ISBLANK($B108),"",IF($L108<51,$L108+$N$2,$L108-52+$N$2)) -> 22
B109: 03/31/2026 | C109: Invoice | D109: 4020 | E109: Blue Cross Blue Shield of Louisiana:RDC0002098 - Blue Cross and Blue Shield of Louisiana - SN - Advisory CO 004 | F109: 05/15/2026 | G109: 18000 | H109: 18000 | I109: 45 | J109: =IF(ISBLANK($B109),"",YEAR($B109)) -> 2026 | K109: =IF(ISBLANK($B109),"",WEEKNUM($B109)) -> 14 | L109: =IF(ISBLANK($B109),"",WEEKNUM($F109)) -> 20 | M109: =IF(ISBLANK($B109),"",IF($L109<51,YEAR($F109),YEAR($F109)+1)) -> 2026 | N109: =IF(ISBLANK($B109),"",IF($L109<51,$L109+$N$2,$L109-52+$N$2)) -> 22
B110: 04/15/2026 | C110: Invoice | D110: 4024 | E110: EnPro Industries, Inc.:RDC0002029 - ENPRO Industries - SN - CMDB | F110: 05/15/2026 | G110: 38016 | H110: 38016 | I110: 30 | J110: =IF(ISBLANK($B110),"",YEAR($B110)) -> 2026 | K110: =IF(ISBLANK($B110),"",WEEKNUM($B110)) -> 16 | L110: =IF(ISBLANK($B110),"",WEEKNUM($F110)) -> 20 | M110: =IF(ISBLANK($B110),"",IF($L110<51,YEAR($F110),YEAR($F110)+1)) -> 2026 | N110: =IF(ISBLANK($B110),"",IF($L110<51,$L110+$N$2,$L110-52+$N$2)) -> 22
B111: 04/15/2026 | C111: Invoice | D111: 4025 | E111: Ahold Delhaize:RDC0002037 - ADUSA - SN - Tufin Integration | F111: 05/15/2026 | G111: 18892.8 | H111: 18892.8 | I111: 30 | J111: =IF(ISBLANK($B111),"",YEAR($B111)) -> 2026 | K111: =IF(ISBLANK($B111),"",WEEKNUM($B111)) -> 16 | L111: =IF(ISBLANK($B111),"",WEEKNUM($F111)) -> 20 | M111: =IF(ISBLANK($B111),"",IF($L111<51,YEAR($F111),YEAR($F111)+1)) -> 2026 | N111: =IF(ISBLANK($B111),"",IF($L111<51,$L111+$N$2,$L111-52+$N$2)) -> 22
B112: 04/15/2026 | C112: Invoice | D112: 4026 | E112: Alliant Credit Union:RDC0002071 - Alliant Credit Union - SN - IRM | F112: 05/15/2026 | G112: 29700 | H112: 29700 | I112: 30 | J112: =IF(ISBLANK($B112),"",YEAR($B112)) -> 2026 | K112: =IF(ISBLANK($B112),"",WEEKNUM($B112)) -> 16 | L112: =IF(ISBLANK($B112),"",WEEKNUM($F112)) -> 20 | M112: =IF(ISBLANK($B112),"",IF($L112<51,YEAR($F112),YEAR($F112)+1)) -> 2026 | N112: =IF(ISBLANK($B112),"",IF($L112<51,$L112+$N$2,$L112-52+$N$2)) -> 22
B113: 04/15/2026 | C113: Invoice | D113: 4027 | E113: Aviva (GBP):RDC0002318 - Aviva - SN - Urgent Mapping & Tagging Remediation | F113: 05/15/2026 | G113: 98710.71 | H113: 98710.706 | I113: 30 | J113: =IF(ISBLANK($B113),"",YEAR($B113)) -> 2026 | K113: =IF(ISBLANK($B113),"",WEEKNUM($B113)) -> 16 | L113: =IF(ISBLANK($B113),"",WEEKNUM($F113)) -> 20 | M113: =IF(ISBLANK($B113),"",IF($L113<51,YEAR($F113),YEAR($F113)+1)) -> 2026 | N113: =IF(ISBLANK($B113),"",IF($L113<51,$L113+$N$2,$L113-52+$N$2)) -> 22
B114: 04/15/2026 | C114: Invoice | D114: 4028 | E114: Reward Gateway:RDC0002094 - Reward Gateway - SoW - FP - New Relic Takeout | F114: 05/15/2026 | G114: 21562.5 | H114: 21562.5 | I114: 30 | J114: =IF(ISBLANK($B114),"",YEAR($B114)) -> 2026 | K114: =IF(ISBLANK($B114),"",WEEKNUM($B114)) -> 16 | L114: =IF(ISBLANK($B114),"",WEEKNUM($F114)) -> 20 | M114: =IF(ISBLANK($B114),"",IF($L114<51,YEAR($F114),YEAR($F114)+1)) -> 2026 | N114: =IF(ISBLANK($B114),"",IF($L114<51,$L114+$N$2,$L114-52+$N$2)) -> 22
B115: 04/15/2026 | C115: Invoice | D115: 4029 | E115: Manchester Airport Group (GBP):RDC0002396 - Manchester Airport Group (MAG) - SN - SPM | F115: 05/15/2026 | G115: 59536.8 | H115: 59536.8 | I115: 30 | J115: =IF(ISBLANK($B115),"",YEAR($B115)) -> 2026 | K115: =IF(ISBLANK($B115),"",WEEKNUM($B115)) -> 16 | L115: =IF(ISBLANK($B115),"",WEEKNUM($F115)) -> 20 | M115: =IF(ISBLANK($B115),"",IF($L115<51,YEAR($F115),YEAR($F115)+1)) -> 2026 | N115: =IF(ISBLANK($B115),"",IF($L115<51,$L115+$N$2,$L115-52+$N$2)) -> 22
B116: 04/15/2026 | C116: Invoice | D116: 4031 | E116: Coppel:RDC0002228 - Coppel - DD - SVC - FP - IT DBM & Core Servers | F116: 05/15/2026 | G116: 182400 | H116: 182400 | I116: 30 | J116: =IF(ISBLANK($B116),"",YEAR($B116)) -> 2026 | K116: =IF(ISBLANK($B116),"",WEEKNUM($B116)) -> 16 | L116: =IF(ISBLANK($B116),"",WEEKNUM($F116)) -> 20 | M116: =IF(ISBLANK($B116),"",IF($L116<51,YEAR($F116),YEAR($F116)+1)) -> 2026 | N116: =IF(ISBLANK($B116),"",IF($L116<51,$L116+$N$2,$L116-52+$N$2)) -> 22
B117: 04/15/2026 | C117: Invoice | D117: 4032 | E117: Coppel:RDC0002256 - Coppel - DD - IT NDM | F117: 05/15/2026 | G117: 40000 | H117: 40000 | I117: 30 | J117: =IF(ISBLANK($B117),"",YEAR($B117)) -> 2026 | K117: =IF(ISBLANK($B117),"",WEEKNUM($B117)) -> 16 | L117: =IF(ISBLANK($B117),"",WEEKNUM($F117)) -> 20 | M117: =IF(ISBLANK($B117),"",IF($L117<51,YEAR($F117),YEAR($F117)+1)) -> 2026 | N117: =IF(ISBLANK($B117),"",IF($L117<51,$L117+$N$2,$L117-52+$N$2)) -> 22
B118: 04/15/2026 | C118: Invoice | D118: 4033 | E118: Coppel:RDC0002256 - Coppel - DD - IT NDM | F118: 05/15/2026 | G118: 159760 | H118: 159760 | I118: 30 | J118: =IF(ISBLANK($B118),"",YEAR($B118)) -> 2026 | K118: =IF(ISBLANK($B118),"",WEEKNUM($B118)) -> 16 | L118: =IF(ISBLANK($B118),"",WEEKNUM($F118)) -> 20 | M118: =IF(ISBLANK($B118),"",IF($L118<51,YEAR($F118),YEAR($F118)+1)) -> 2026 | N118: =IF(ISBLANK($B118),"",IF($L118<51,$L118+$N$2,$L118-52+$N$2)) -> 22
... B139: 04/22/2026 | C139: Invoice | D139: 4037 | E139: Lumen Technologies Service Group:RDC0002506 - Lumen - DD - AppD Migration | F139: 07/21/2026 | G139: 261928 | H139: 261928 | I139: 90 | J139: =IF(ISBLANK($B139),"",YEAR($B139)) -> 2026 | K139: =IF(ISBLANK($B139),"",WEEKNUM($B139)) -> 17 | L139: =IF(ISBLANK($B139),"",WEEKNUM($F139)) -> 30 | M139: =IF(ISBLANK($B139),"",IF($L139<51,YEAR($F139),YEAR($F139)+1)) -> 2026 | N139: =IF(ISBLANK($B139),"",IF($L139<51,$L139+$N$2,$L139-52+$N$2)) -> 32
J140: =IF(ISBLANK($B140),"",YEAR($B140)) | K140: =IF(ISBLANK($B140),"",WEEKNUM($B140)) | L140: =IF(ISBLANK($B140),"",WEEKNUM($F140)) | M140: =IF(ISBLANK($B140),"",IF($L140<51,YEAR($F140),YEAR($F140)+1)) | N140: =IF(ISBLANK($B140),"",IF($L140<51,$L140+$N$2,$L140-52+$N$2))
J141: =IF(ISBLANK($B141),"",YEAR($B141)) | K141: =IF(ISBLANK($B141),"",WEEKNUM($B141)) | L141: =IF(ISBLANK($B141),"",WEEKNUM($F141)) | M141: =IF(ISBLANK($B141),"",IF($L141<51,YEAR($F141),YEAR($F141)+1)) | N141: =IF(ISBLANK($B141),"",IF($L141<51,$L141+$N$2,$L141-52+$N$2))
J142: =IF(ISBLANK($B142),"",YEAR($B142)) | K142: =IF(ISBLANK($B142),"",WEEKNUM($B142)) | L142: =IF(ISBLANK($B142),"",WEEKNUM($F142)) | M142: =IF(ISBLANK($B142),"",IF($L142<51,YEAR($F142),YEAR($F142)+1)) | N142: =IF(ISBLANK($B142),"",IF($L142<51,$L142+$N$2,$L142-52+$N$2))
J143: =IF(ISBLANK($B143),"",YEAR($B143)) | K143: =IF(ISBLANK($B143),"",WEEKNUM($B143)) | L143: =IF(ISBLANK($B143),"",WEEKNUM($F143)) | M143: =IF(ISBLANK($B143),"",IF($L143<51,YEAR($F143),YEAR($F143)+1)) | N143: =IF(ISBLANK($B143),"",IF($L143<51,$L143+$N$2,$L143-52+$N$2))
J144: =IF(ISBLANK($B144),"",YEAR($B144)) | K144: =IF(ISBLANK($B144),"",WEEKNUM($B144)) | L144: =IF(ISBLANK($B144),"",WEEKNUM($F144)) | M144: =IF(ISBLANK($B144),"",IF($L144<51,YEAR($F144),YEAR($F144)+1)) | N144: =IF(ISBLANK($B144),"",IF($L144<51,$L144+$N$2,$L144-52+$N$2))
J145: =IF(ISBLANK($B145),"",YEAR($B145)) | K145: =IF(ISBLANK($B145),"",WEEKNUM($B145)) | L145: =IF(ISBLANK($B145),"",WEEKNUM($F145)) | M145: =IF(ISBLANK($B145),"",IF($L145<51,YEAR($F145),YEAR($F145)+1)) | N145: =IF(ISBLANK($B145),"",IF($L145<51,$L145+$N$2,$L145-52+$N$2))
J146: =IF(ISBLANK($B146),"",YEAR($B146)) | K146: =IF(ISBLANK($B146),"",WEEKNUM($B146)) | L146: =IF(ISBLANK($B146),"",WEEKNUM($F146)) | M146: =IF(ISBLANK($B146),"",IF($L146<51,YEAR($F146),YEAR($F146)+1)) | N146: =IF(ISBLANK($B146),"",IF($L146<51,$L146+$N$2,$L146-52+$N$2))
J147: =IF(ISBLANK($B147),"",YEAR($B147)) | K147: =IF(ISBLANK($B147),"",WEEKNUM($B147)) | L147: =IF(ISBLANK($B147),"",WEEKNUM($F147)) | M147: =IF(ISBLANK($B147),"",IF($L147<51,YEAR($F147),YEAR($F147)+1)) | N147: =IF(ISBLANK($B147),"",IF($L147<51,$L147+$N$2,$L147-52+$N$2))
J148: =IF(ISBLANK($B148),"",YEAR($B148)) | K148: =IF(ISBLANK($B148),"",WEEKNUM($B148)) | L148: =IF(ISBLANK($B148),"",WEEKNUM($F148)) | M148: =IF(ISBLANK($B148),"",IF($L148<51,YEAR($F148),YEAR($F148)+1)) | N148: =IF(ISBLANK($B148),"",IF($L148<51,$L148+$N$2,$L148-52+$N$2))
B152: 46142 | E152: Elevance Health - New Deal - DD - Broadcom Replacement | F152: =IF(ISBLANK($B152),"",B152+I152) -> 46202 | G152: 89500 | H152: =IF(ISBLANK($B152),"",$G152) -> 89500 | I152: 60 | J152: =IF(ISBLANK($B152),"",YEAR($B152)) -> 2026 | K152: =IF(ISBLANK($B152),"",WEEKNUM($B152)) -> 18 | L152: =IF(ISBLANK($B152),"",WEEKNUM($F152)) -> 27 | M152: =IF(ISBLANK($B152),"",IF($L152<51,YEAR($F152),YEAR($F152)+1)) -> 2026 | N152: =IF(ISBLANK($B152),"",IF($L152<51,$L152+$N$2,$L152-52+$N$2)) -> 29
B153: 46142 | E153: Resilience - SN - CMDB, Discovery & Service Mapping | F153: =IF(ISBLANK($B153),"",B153+I153) -> 46172 | G153: 2500 | H153: =IF(ISBLANK($B153),"",$G153) -> 2500 | I153: 30 | J153: =IF(ISBLANK($B153),"",YEAR($B153)) -> 2026 | K153: =IF(ISBLANK($B153),"",WEEKNUM($B153)) -> 18 | L153: =IF(ISBLANK($B153),"",WEEKNUM($F153)) -> 22 | M153: =IF(ISBLANK($B153),"",IF($L153<51,YEAR($F153),YEAR($F153)+1)) -> 2026 | N153: =IF(ISBLANK($B153),"",IF($L153<51,$L153+$N$2,$L153-52+$N$2)) -> 24
B154: 46142 | E154: Global Holdings - DD - SOW - DD (ASM, Ci VIS, DBM) (2) | F154: =IF(ISBLANK($B154),"",B154+I154) -> 46202 | G154: 907.12 | H154: =IF(ISBLANK($B154),"",$G154) -> 907.12 | I154: 60 | J154: =IF(ISBLANK($B154),"",YEAR($B154)) -> 2026 | K154: =IF(ISBLANK($B154),"",WEEKNUM($B154)) -> 18 | L154: =IF(ISBLANK($B154),"",WEEKNUM($F154)) -> 27 | M154: =IF(ISBLANK($B154),"",IF($L154<51,YEAR($F154),YEAR($F154)+1)) -> 2026 | N154: =IF(ISBLANK($B154),"",IF($L154<51,$L154+$N$2,$L154-52+$N$2)) -> 29
B155: 46142 | E155: Commonwealth Financial Network - DD - SOW | F155: =IF(ISBLANK($B155),"",B155+I155) -> 46172 | G155: 3200 | H155: =IF(ISBLANK($B155),"",$G155) -> 3200 | I155: 30 | J155: =IF(ISBLANK($B155),"",YEAR($B155)) -> 2026 | K155: =IF(ISBLANK($B155),"",WEEKNUM($B155)) -> 18 | L155: =IF(ISBLANK($B155),"",WEEKNUM($F155)) -> 22 | M155: =IF(ISBLANK($B155),"",IF($L155<51,YEAR($F155),YEAR($F155)+1)) -> 2026 | N155: =IF(ISBLANK($B155),"",IF($L155<51,$L155+$N$2,$L155-52+$N$2)) -> 24
B156: 46142 | E156: TTEC - DD - Drawdown Renewal | F156: =IF(ISBLANK($B156),"",B156+I156) -> 46202 | G156: 560 | H156: =IF(ISBLANK($B156),"",$G156) -> 560 | I156: 60 | J156: =IF(ISBLANK($B156),"",YEAR($B156)) -> 2026 | K156: =IF(ISBLANK($B156),"",WEEKNUM($B156)) -> 18 | L156: =IF(ISBLANK($B156),"",WEEKNUM($F156)) -> 27 | M156: =IF(ISBLANK($B156),"",IF($L156<51,YEAR($F156),YEAR($F156)+1)) -> 2026 | N156: =IF(ISBLANK($B156),"",IF($L156<51,$L156+$N$2,$L156-52+$N$2)) -> 29
B157: 46142 | E157: T-Mobile - SN - MSO Phase 1 | F157: =IF(ISBLANK($B157),"",B157+I157) -> 46172 | G157: 205902 | H157: =IF(ISBLANK($B157),"",$G157) -> 205902 | I157: 30 | J157: =IF(ISBLANK($B157),"",YEAR($B157)) -> 2026 | K157: =IF(ISBLANK($B157),"",WEEKNUM($B157)) -> 18 | L157: =IF(ISBLANK($B157),"",WEEKNUM($F157)) -> 22 | M157: =IF(ISBLANK($B157),"",IF($L157<51,YEAR($F157),YEAR($F157)+1)) -> 2026 | N157: =IF(ISBLANK($B157),"",IF($L157<51,$L157+$N$2,$L157-52+$N$2)) -> 24
B158: 46142 | E158: Warner Bros. Discovery - SN - ITOM Health | F158: =IF(ISBLANK($B158),"",B158+I158) -> 46202 | G158: 24999.6 | H158: =IF(ISBLANK($B158),"",$G158) -> 24999.6 | I158: 60 | J158: =IF(ISBLANK($B158),"",YEAR($B158)) -> 2026 | K158: =IF(ISBLANK($B158),"",WEEKNUM($B158)) -> 18 | L158: =IF(ISBLANK($B158),"",WEEKNUM($F158)) -> 27 | M158: =IF(ISBLANK($B158),"",IF($L158<51,YEAR($F158),YEAR($F158)+1)) -> 2026 | N158: =IF(ISBLANK($B158),"",IF($L158<51,$L158+$N$2,$L158-52+$N$2)) -> 29
B159: 46142 | E159: Mars - DD - Drawdown - E2E BI visibility(SoftwareOne POCs) | F159: =IF(ISBLANK($B159),"",B159+I159) -> 46187 | G159: 27000 | H159: =IF(ISBLANK($B159),"",$G159) -> 27000 | I159: 45 | J159: =IF(ISBLANK($B159),"",YEAR($B159)) -> 2026 | K159: =IF(ISBLANK($B159),"",WEEKNUM($B159)) -> 18 | L159: =IF(ISBLANK($B159),"",WEEKNUM($F159)) -> 25 | M159: =IF(ISBLANK($B159),"",IF($L159<51,YEAR($F159),YEAR($F159)+1)) -> 2026 | N159: =IF(ISBLANK($B159),"",IF($L159<51,$L159+$N$2,$L159-52+$N$2)) -> 27
B160: 46142 | E160: Grainger - SN - Drawdown CMDB | F160: =IF(ISBLANK($B160),"",B160+I160) -> 46187 | G160: 35750 | H160: =IF(ISBLANK($B160),"",$G160) -> 35750 | I160: 45 | J160: =IF(ISBLANK($B160),"",YEAR($B160)) -> 2026 | K160: =IF(ISBLANK($B160),"",WEEKNUM($B160)) -> 18 | L160: =IF(ISBLANK($B160),"",WEEKNUM($F160)) -> 25 | M160: =IF(ISBLANK($B160),"",IF($L160<51,YEAR($F160),YEAR($F160)+1)) -> 2026 | N160: =IF(ISBLANK($B160),"",IF($L160<51,$L160+$N$2,$L160-52+$N$2)) -> 27
B161: 46142 | E161: Claro Pay - DD - Modern Ops + MGD DD | F161: =IF(ISBLANK($B161),"",B161+I161) -> 46172 | G161: 15000 | H161: =IF(ISBLANK($B161),"",$G161) -> 15000 | I161: 30 | J161: =IF(ISBLANK($B161),"",YEAR($B161)) -> 2026 | K161: =IF(ISBLANK($B161),"",WEEKNUM($B161)) -> 18 | L161: =IF(ISBLANK($B161),"",WEEKNUM($F161)) -> 22 | M161: =IF(ISBLANK($B161),"",IF($L161<51,YEAR($F161),YEAR($F161)+1)) -> 2026 | N161: =IF(ISBLANK($B161),"",IF($L161<51,$L161+$N$2,$L161-52+$N$2)) -> 24
B162: 46142 | E162: Vitality Global - SN - DevOps | F162: =IF(ISBLANK($B162),"",B162+I162) -> 46172 | G162: 44000 | H162: =IF(ISBLANK($B162),"",$G162) -> 44000 | I162: 30 | J162: =IF(ISBLANK($B162),"",YEAR($B162)) -> 2026 | K162: =IF(ISBLANK($B162),"",WEEKNUM($B162)) -> 18 | L162: =IF(ISBLANK($B162),"",WEEKNUM($F162)) -> 22 | M162: =IF(ISBLANK($B162),"",IF($L162<51,YEAR($F162),YEAR($F162)+1)) -> 2026 | N162: =IF(ISBLANK($B162),"",IF($L162<51,$L162+$N$2,$L162-52+$N$2)) -> 24
B163: 46142 | E163: Alliant Credit Union - SN - ITAM Drawdown | F163: =IF(ISBLANK($B163),"",B163+I163) -> 46172 | G163: 18300 | H163: =IF(ISBLANK($B163),"",$G163) -> 18300 | I163: 30 | J163: =IF(ISBLANK($B163),"",YEAR($B163)) -> 2026 | K163: =IF(ISBLANK($B163),"",WEEKNUM($B163)) -> 18 | L163: =IF(ISBLANK($B163),"",WEEKNUM($F163)) -> 22 | M163: =IF(ISBLANK($B163),"",IF($L163<51,YEAR($F163),YEAR($F163)+1)) -> 2026 | N163: =IF(ISBLANK($B163),"",IF($L163<51,$L163+$N$2,$L163-52+$N$2)) -> 24
... B394: 46326 | E394: United Therapeutics - SN - ServiceNow Support Drawdown + Upgrades | F394: =IF(ISBLANK($B394),"",B394+I394) -> 46356 | G394: 10800 | H394: =IF(ISBLANK($B394),"",$G394) -> 10800 | I394: 30 | J394: =IF(ISBLANK($B394),"",YEAR($B394)) -> 2026 | K394: =IF(ISBLANK($B394),"",WEEKNUM($B394)) -> 44 | L394: =IF(ISBLANK($B394),"",WEEKNUM($F394)) -> 49 | M394: =IF(ISBLANK($B394),"",IF($L394<51,YEAR($F394),YEAR($F394)+1)) -> 2026 | N394: =IF(ISBLANK($B394),"",IF($L394<51,$L394+$N$2,$L394-52+$N$2)) -> 51
F395: =IF(ISBLANK($B395),"",B395+I395) | H395: =IF(ISBLANK($B395),"",$G395) | J395: =IF(ISBLANK($B395),"",YEAR($B395)) | K395: =IF(ISBLANK($B395),"",WEEKNUM($B395)) | L395: =IF(ISBLANK($B395),"",WEEKNUM($F395)) | M395: =IF(ISBLANK($B395),"",IF($L395<51,YEAR($F395),YEAR($F395)+1)) | N395: =IF(ISBLANK($B395),"",IF($L395<51,$L395+$N$2,$L395-52+$N$2))
F396: =IF(ISBLANK($B396),"",B396+I396) | H396: =IF(ISBLANK($B396),"",$G396) | J396: =IF(ISBLANK($B396),"",YEAR($B396)) | K396: =IF(ISBLANK($B396),"",WEEKNUM($B396)) | L396: =IF(ISBLANK($B396),"",WEEKNUM($F396)) | M396: =IF(ISBLANK($B396),"",IF($L396<51,YEAR($F396),YEAR($F396)+1)) | N396: =IF(ISBLANK($B396),"",IF($L396<51,$L396+$N$2,$L396-52+$N$2))
F397: =IF(ISBLANK($B397),"",B397+I397) | H397: =IF(ISBLANK($B397),"",$G397) | J397: =IF(ISBLANK($B397),"",YEAR($B397)) | K397: =IF(ISBLANK($B397),"",WEEKNUM($B397)) | L397: =IF(ISBLANK($B397),"",WEEKNUM($F397)) | M397: =IF(ISBLANK($B397),"",IF($L397<51,YEAR($F397),YEAR($F397)+1)) | N397: =IF(ISBLANK($B397),"",IF($L397<51,$L397+$N$2,$L397-52+$N$2))
F398: =IF(ISBLANK($B398),"",B398+I398) | H398: =IF(ISBLANK($B398),"",$G398) | J398: =IF(ISBLANK($B398),"",YEAR($B398)) | K398: =IF(ISBLANK($B398),"",WEEKNUM($B398)) | L398: =IF(ISBLANK($B398),"",WEEKNUM($F398)) | M398: =IF(ISBLANK($B398),"",IF($L398<51,YEAR($F398),YEAR($F398)+1)) | N398: =IF(ISBLANK($B398),"",IF($L398<51,$L398+$N$2,$L398-52+$N$2))
F399: =IF(ISBLANK($B399),"",B399+I399) | H399: =IF(ISBLANK($B399),"",$G399) | J399: =IF(ISBLANK($B399),"",YEAR($B399)) | K399: =IF(ISBLANK($B399),"",WEEKNUM($B399)) | L399: =IF(ISBLANK($B399),"",WEEKNUM($F399)) | M399: =IF(ISBLANK($B399),"",IF($L399<51,YEAR($F399),YEAR($F399)+1)) | N399: =IF(ISBLANK($B399),"",IF($L399<51,$L399+$N$2,$L399-52+$N$2))
F400: =IF(ISBLANK($B400),"",B400+I400) | H400: =IF(ISBLANK($B400),"",$G400) | J400: =IF(ISBLANK($B400),"",YEAR($B400)) | K400: =IF(ISBLANK($B400),"",WEEKNUM($B400)) | L400: =IF(ISBLANK($B400),"",WEEKNUM($F400)) | M400: =IF(ISBLANK($B400),"",IF($L400<51,YEAR($F400),YEAR($F400)+1)) | N400: =IF(ISBLANK($B400),"",IF($L400<51,$L400+$N$2,$L400-52+$N$2))
F401: =IF(ISBLANK($B401),"",B401+I401) | H401: =IF(ISBLANK($B401),"",$G401) | J401: =IF(ISBLANK($B401),"",YEAR($B401)) | K401: =IF(ISBLANK($B401),"",WEEKNUM($B401)) | L401: =IF(ISBLANK($B401),"",WEEKNUM($F401)) | M401: =IF(ISBLANK($B401),"",IF($L401<51,YEAR($F401),YEAR($F401)+1)) | N401: =IF(ISBLANK($B401),"",IF($L401<51,$L401+$N$2,$L401-52+$N$2))
F402: =IF(ISBLANK($B402),"",B402+I402) | H402: =IF(ISBLANK($B402),"",$G402) | J402: =IF(ISBLANK($B402),"",YEAR($B402)) | K402: =IF(ISBLANK($B402),"",WEEKNUM($B402)) | L402: =IF(ISBLANK($B402),"",WEEKNUM($F402)) | M402: =IF(ISBLANK($B402),"",IF($L402<51,YEAR($F402),YEAR($F402)+1)) | N402: =IF(ISBLANK($B402),"",IF($L402<51,$L402+$N$2,$L402-52+$N$2))
F403: =IF(ISBLANK($B403),"",B403+I403) | H403: =IF(ISBLANK($B403),"",$G403) | J403: =IF(ISBLANK($B403),"",YEAR($B403)) | K403: =IF(ISBLANK($B403),"",WEEKNUM($B403)) | L403: =IF(ISBLANK($B403),"",WEEKNUM($F403)) | M403: =IF(ISBLANK($B403),"",IF($L403<51,YEAR($F403),YEAR($F403)+1)) | N403: =IF(ISBLANK($B403),"",IF($L403<51,$L403+$N$2,$L403-52+$N$2))
F404: =IF(ISBLANK($B404),"",B404+I404) | H404: =IF(ISBLANK($B404),"",$G404) | J404: =IF(ISBLANK($B404),"",YEAR($B404)) | K404: =IF(ISBLANK($B404),"",WEEKNUM($B404)) | L404: =IF(ISBLANK($B404),"",WEEKNUM($F404)) | M404: =IF(ISBLANK($B404),"",IF($L404<51,YEAR($F404),YEAR($F404)+1)) | N404: =IF(ISBLANK($B404),"",IF($L404<51,$L404+$N$2,$L404-52+$N$2))
F405: =IF(ISBLANK($B405),"",B405+I405) | H405: =IF(ISBLANK($B405),"",$G405) | J405: =IF(ISBLANK($B405),"",YEAR($B405)) | K405: =IF(ISBLANK($B405),"",WEEKNUM($B405)) | L405: =IF(ISBLANK($B405),"",WEEKNUM($F405)) | M405: =IF(ISBLANK($B405),"",IF($L405<51,YEAR($F405),YEAR($F405)+1)) | N405: =IF(ISBLANK($B405),"",IF($L405<51,$L405+$N$2,$L405-52+$N$2))
F406: =IF(ISBLANK($B406),"",B406+I406) | H406: =IF(ISBLANK($B406),"",$G406) | J406: =IF(ISBLANK($B406),"",YEAR($B406)) | K406: =IF(ISBLANK($B406),"",WEEKNUM($B406)) | L406: =IF(ISBLANK($B406),"",WEEKNUM($F406)) | M406: =IF(ISBLANK($B406),"",IF($L406<51,YEAR($F406),YEAR($F406)+1)) | N406: =IF(ISBLANK($B406),"",IF($L406<51,$L406+$N$2,$L406-52+$N$2))
... F574: =IF(ISBLANK($B574),"",B574+I574) | H574: =IF(ISBLANK($B574),"",$G574) | J574: =IF(ISBLANK($B574),"",YEAR($B574)) | K574: =IF(ISBLANK($B574),"",WEEKNUM($B574)) | L574: =IF(ISBLANK($B574),"",WEEKNUM($F574)) | M574: =IF(ISBLANK($B574),"",IF($L574<51,YEAR($F574),YEAR($F574)+1)) | N574: =IF(ISBLANK($B574),"",IF($L574<51,$L574+$N$2,$L574-52+$N$2))
